Workbook

Sheet Feuil1
A3: DATE
A4: CHAUFFEUR
E6: Arrêt 1 | I6: Arrêt 2 | M6: Arrêt 3 | Q6: PEM PASSAMAINTY
B7: Heure théorique départ | C7: Heure réelle départ | D7: Nbre personnes + | E7: Nbre personnes + | F7: Nbre personnes - | G7: Heure arrivée arrêt 1 | H7: Délai | I7: Nbre personnes + | J7: Nbre personnes - | K7: Heure arrivée arrêt 2 | L7: Délai | M7: Nbre personnes + | N7: Nbre personnes - | O7: Heure arrivée arrêt 3 | P7: Délai | Q7: Nbre personnes - | S7: Heure arrivée finale | T7: Commentaires | U7: Temps Aller
A8: VAHIBE | B8: 0.20833333 | H8: =G8-C8 -> 0 | L8: =K8-G8 -> 0 | P8: =O8-K8 -> 0 | R8: =IF(D8+E8-F8+I8-J8+M8-N8=Q8,"OK",D8+E8-F8+I8-J8+M8-N8-Q8) -> OK | U8: =S8-C8 -> 0
A9: VAHIBE | B9: 0.21527778 | H9: =G9-C9 -> 0 | L9: =K9-G9 -> 0 | P9: =O9-K9 -> 0 | U9: =S9-C9 -> 0
A10: VAHIBE | B10: 0.22222222 | H10: =G10-C10 -> 0 | L10: =K10-G10 -> 0 | P10: =O10-K10 -> 0 | U10: =S10-C10 -> 0
A11: VAHIBE | B11: 0.22916667 | H11: =G11-C11 -> 0 | L11: =K11-G11 -> 0 | P11: =O11-K11 -> 0 | U11: =S11-C11 -> 0
A12: VAHIBE | B12: 0.23611111 | H12: =G12-C12 -> 0 | L12: =K12-G12 -> 0 | P12: =O12-K12 -> 0 | U12: =S12-C12 -> 0
A13: VAHIBE | B13: 0.24305556 | H13: =G13-C13 -> 0 | L13: =K13-G13 -> 0 | P13: =O13-K13 -> 0 | U13: =S13-C13 -> 0
A14: VAHIBE | B14: 0.25 | H14: =G14-C14 -> 0 | L14: =K14-G14 -> 0 | P14: =O14-K14 -> 0 | U14: =S14-C14 -> 0
A15: VAHIBE | B15: 0.25694444 | H15: =G15-C15 -> 0 | L15: =K15-G15 -> 0 | P15: =O15-K15 -> 0 | U15: =S15-C15 -> 0
A16: VAHIBE | B16: 0.26388889 | H16: =G16-C16 -> 0 | L16: =K16-G16 -> 0 | P16: =O16-K16 -> 0 | U16: =S16-C16 -> 0
A17: VAHIBE | B17: 0.27083333 | H17: =G17-C17 -> 0 | L17: =K17-G17 -> 0 | P17: =O17-K17 -> 0 | U17: =S17-C17 -> 0
A18: VAHIBE | B18: 0.27777778 | H18: =G18-C18 -> 0 | L18: =K18-G18 -> 0 | P18: =O18-K18 -> 0 | U18: =S18-C18 -> 0
A19: VAHIBE | B19: 0.28472222 | H19: =G19-C19 -> 0 | L19: =K19-G19 -> 0 | P19: =O19-K19 -> 0 | U19: =S19-C19 -> 0
A20: VAHIBE | B20: 0.29166667 | H20: =G20-C20 -> 0 | L20: =K20-G20 -> 0 | P20: =O20-K20 -> 0 | U20: =S20-C20 -> 0
... A26: VAHIBE | B26: 0.33333333 | H26: =G26-C26 -> 0 | L26: =K26-G26 -> 0 | P26: =O26-K26 -> 0 | U26: =S26-C26 -> 0
Q27: VAHIBE | U27: =SUM(U8:U26) -> 0
A28: PEM PASSAMAINTY | B28: 0.625 | H28: =G28-C28 -> 0 | L28: =K28-G28 -> 0 | P28: =O28-K28 -> 0 | U28: =S28-C28 -> 0
A29: PEM PASSAMAINTY | B29: 0.63194444 | H29: =G29-C29 -> 0 | L29: =K29-G29 -> 0 | P29: =O29-K29 -> 0 | U29: =S29-C29 -> 0
A30: PEM PASSAMAINTY | B30: 0.63888889 | H30: =G30-C30 -> 0 | L30: =K30-G30 -> 0 | P30: =O30-K30 -> 0 | U30: =S30-C30 -> 0
A31: PEM PASSAMAINTY | B31: 0.64583333 | H31: =G31-C31 -> 0 | L31: =K31-G31 -> 0 | P31: =O31-K31 -> 0 | U31: =S31-C31 -> 0
A32: PEM PASSAMAINTY | B32: 0.65277778 | H32: =G32-C32 -> 0 | L32: =K32-G32 -> 0 | P32: =O32-K32 -> 0 | U32: =S32-C32 -> 0
A33: PEM PASSAMAINTY | B33: 0.65972222 | H33: =G33-C33 -> 0 | L33: =K33-G33 -> 0 | P33: =O33-K33 -> 0 | U33: =S33-C33 -> 0
A34: PEM PASSAMAINTY | B34: 0.66666667 | H34: =G34-C34 -> 0 | L34: =K34-G34 -> 0 | P34: =O34-K34 -> 0 | U34: =S34-C34 -> 0
A35: PEM PASSAMAINTY | B35: 0.67361111 | H35: =G35-C35 -> 0 | L35: =K35-G35 -> 0 | P35: =O35-K35 -> 0 | U35: =S35-C35 -> 0
A36: PEM PASSAMAINTY | B36: 0.68055556 | H36: =G36-C36 -> 0 | L36: =K36-G36 -> 0 | P36: =O36-K36 -> 0 | U36: =S36-C36 -> 0
A37: PEM PASSAMAINTY | B37: 0.6875 | H37: =G37-C37 -> 0 | L37: =K37-G37 -> 0 | P37: =O37-K37 -> 0 | U37: =S37-C37 -> 0
A38: PEM PASSAMAINTY | B38: 0.69444444 | H38: =G38-C38 -> 0 | L38: =K38-G38 -> 0 | P38: =O38-K38 -> 0 | U38: =S38-C38 -> 0
A39: PEM PASSAMAINTY | B39: 0.70138889 | H39: =G39-C39 -> 0 | L39: =K39-G39 -> 0 | P39: =O39-K39 -> 0 | U39: =S39-C39 -> 0
... A46: PEM PASSAMAINTY | B46: 0.75 | H46: =G46-C46 -> 0 | L46: =K46-G46 -> 0 | P46: =O46-K46 -> 0 | U46: =S46-C46 -> 0
U47: =SUM(U28:U46) -> 0
U48: =U47+U27 -> 0
C49: Signature Chauffeur | I49: Signature Coordinateur

Sheet REUNION DU 28.04
B1: N° | C1: CADEMA | D1: STATUT | E1: LICENCE TRANSPORTEUR | F1: SIREN LICENCE | G1: VALIDITE LICENCE TRANSP | H1: N° | I1: N° Chauffeur | J1: Type | K1: Nom | L1: Prénom | M1: Téléphone | N1: Mail | O1: Siret | P1: Secteur d'activité | Q1: N° licence | R1: CARTE CONDUCTEUR | S1: VALIDITE CARTE CONDUCTEUR | T1: N° IMMATRICULATION CARTE GRISE | U1: DATE IMMATRICULATION | V1: AGE DU VEHICULE | W1: Type de vehicule | X1: ETAT VEHICULE | Y1: RDV MAY EQUIP | Z1: HABILLAGE | AA1: REGLT HABILLAGE | AB1: EQUIPEMENT | AC1: HABILLAGE 2021 | AD1: HABILLAGE 2023 | AE1: IDENTITE | AF1: NATIONALITE | AG1: VALIDITE CARTE SEJOUR | AH1: CARTE VITALE | AI1: ASSURANCES | AJ1: FACTURE _3 MOIS | AK1: IMPOTS | AL1: PHOTO | AM1: N° AGC | AN1: Capital souscrit | AO1: Année de souscription | AP1: Cotisations versées en 2021 | AQ1: COTISATIONS 2023 | AR1: COTISATIONS 2024 | AS1: N° Rue | AT1: Adresse | AU1: Code postal | AV1: Commune | AW1: REMARQUES
A2: 1 | B2: 11 | C2: CADEMA 1 | D2: AO | E2: NON | F2: - | G2: - | H2: 1 | I2: C4 | J2: C2 | K2: ABDOU MINIHADJI | L2: Amada | M2: 0639 65 03 93 | N2: abdouminihadjiamada@hotmail.com | O2: 066 311 101 000 19 | P2: Centre Sud | Q2: 976-CS-057 | R2: 505 | S2: 45305 | T2: FY-654-BF | U2: 44279 | V2: =2024-YEAR(U2) -> 3 | W2: 9 PLACES | X2: BON | Z2: OUI | AA2: _ | AB2: NON | AC2: OUI | AE2: 43262 | AF2: F | AG2: _ | AH2: NON | AI2: NON | AJ2: 2020 | AL2: OUI | AM2: 2020/13 | AN2: 510 | AO2: 43466 | AP2: 450 | AS2: 64 | AT2: Avenue de rassi | AU2: 97670 | AV2: Chiconi | AW2: ancien gérant - Habillage 2021
A3: 33 | B3: 17 | C3: CADEMA 1 | D3: AO | E3: NON | F3: - | G3: - | H3: 2 | I3: C6 | J3: C10 | K3: ADINANI | L3: Zoubert | M3: 0639 25 77 76 | N3: zoubert.adinani2@gmail.com | O3: 799 358 700 00018 | P3: Mamoudzou | Q3: 976-M-447 | R3: 1050 | S3: 46342 | T3: GR-407-DV | U3: 45182 | V3: =2024-YEAR(U3) -> 1 | W3: 9 PLACES | X3: BON | Y3: 45406 | Z3: NON | AA3: OUI | AB3: NON | AC3: NON | AD3: A venir | AE3: 48415 | AF3: F | AG3: _ | AH3: OUI | AI3: OUI | AJ3: OUI | AK3: 2022 | AL3: OUI | AN3: 510 | AO3: 43466 | AP3: 250 | AQ3: NON | AR3: NON | AT3: Tahiti plage route de poroani | AU3: 97640 | AV3: Sada | AW3: attente débolacge prêt
A4: 65 | B4: 23 | C4: CADEMA 1 | D4: AO | E4: NON | F4: - | G4: - | H4: 3 | J4: C14 | K4: ALI ATTOUMANI | L4: Bacar | M4: 0639 87 21 88 | N4: aattoumani.bacar@gmail.com | O4: 024 068 413 00020 | P4: Mamoudzou | Q4: 976-M-116 | R4: 222 | S4: 45489 | T4: FJ-886-VX | U4: 43707 | W4: 9 PLACES | Z4: A MOITIE | AA4: NON | AC4: OUI PAS PAYE | AE4: 45896 | AF4: F | AH4: NON | AI4: NON | AJ4: NON | AK4: NON | AL4: OUI | AN4: 510 | AO4: 43466 | AP4: 150 | AQ4: NON | AR4: NON | AS4: 4 | AT4: Chemin ma ali andy | AU4: 97640 | AV4: Sada | AW4: Voiture endommagé d'un coté et la tete de taxi aussi habillé en 2021
A5: 129 | B5: 35 | C5: CADEMA 1 | D5: AO | E5: NON | F5: - | G5: - | H5: 4 | K5: ALLAOUI | L5: Inzoudine | M5: 0639 075923/0639 26 27 78 | N5: ambdihoumadi976@gmail.com | O5: 024 078 396 000 41 | P5: Mamoudzou | Q5: 976-M-049 | R5: 1294 | S5: 43992 | T5: GH-790-LS | U5: 44753 | V5: =2024-YEAR(U5) -> 2 | W5: 9 PLACES | Y5: ? Pas payé | Z5: NON | AA5: _ | AB5: NON | AE5: 47882 | AF5: F | AG5: _ | AH5: NON | AI5: NON | AJ5: NON | AK5: NON | AL5: NON | AM5: 2020/44 | AN5: 510 | AO5: 43466 | AP5: 450 | AS5: 85 | AT5: Rue younoussa bamana | AU5: 97640 | AV5: Sada | AW5: a une voiture neuve
A6: 161 | B6: 41 | C6: CADEMA 1 | D6: AO | E6: NON | F6: - | G6: - | H6: 5 | I6: voiture en panne | K6: ALLAOUI | L6: Soibrane | M6: 0639 65 31 82 | N6: stt653182@hotmail.com | O6: 024 043 30 000 11 | P6: Centre Sud | Q6: 976-CS-048 | R6: 806 | S6: 43222 | T6: FZ_148_HW | U6: 44336 | V6: =2024-YEAR(U6) -> 3 | W6: 9 PLACES | X6: OK | Y6: ? Pas payé | Z6: NON | AB6: NON | AC6: OUI | AE6: 46556 | AF6: F | AG6: _ | AH6: OUI | AI6: OUI | AJ6: OUI | AK6: OUI | AL6: OUI | AN6: 510 | AP6: 450 | AT6: Quartier Kami case impasse mavandzani | AU6: 97625 | AV6: Kani kéli | AW6: Il est pas eligible pour la demande de subvention
A7: 129 | B7: 35 | C7: CADEMA 1 | D7: AO | E7: NON | F7: - | G7: - | H7: 6 | J7: C6 | K7: AMBDI | L7: Houmadi | M7: 0639 23 55 69 | N7: ambdihoumadi976@gmail.com | O7: 066 312 224 000 26 | P7: Sud | Q7: 976-S-023 | R7: 759 | S7: 45639 | T7: GC-122-QA | U7: 44495 | V7: =2024-YEAR(U7) -> 3 | W7: 9 PLACES | X7: OK | Z7: OUI | AB7: OUI | AD7: OUI | AE7: 48640 | AF7: F | AG7: _ | AH7: OUI | AI7: OUI | AJ7: NON | AK7: 2022 | AL7: OUI | AM7: 2020/46 | AN7: 510 | AO7: 43466 | AP7: 250 | AQ7: NON | AR7: NON | AT7: Route nationale Mbouanatsa | AU7: 97620 | AV7: BOUENI | AW7: Habillage 2023
A8: 193 | B8: 47 | C8: CADEMA 1 | D8: AO | E8: NON | F8: - | G8: - | H8: 7 | I8: C9 | J8: C7 | K8: BINA HALADI | L8: Bina | M8: 0639 06 05 82 | N8: wonamaore@gmail.com | O8: 853 690 428 000 18 | P8: Sud | Q8: 976-S-045 | R8: 1414 | S8: 45181 | T8: GE-883-ES | U8: 44581 | V8: =2024-YEAR(U8) -> 2 | W8: 9 places | Z8: OUI | AA8: _ | AB8: OUI | AD8: OUI | AE8: 45040 | AF8: F | AG8: _ | AH8: OUI | AI8: 2023 | AJ8: OUI | AK8: 2022 | AL8: NON | AM8: 2020/61 | AN8: 510 | AO8: 44285 | AP8: 450 | AS8: 8 | AT8: Rue Said Fatima | AU8: 97640 | AV8: SADA | AW8: Habillage juin 2023
A9: 225 | B9: 53 | C9: CADEMA 1 | D9: AO | E9: NON | F9: - | G9: - | H9: 8 | J9: C12 | K9: BOINARIZIKI | L9: Zena Dhurari | M9: 0639 66 36 94 06 50 45 94 42 | N9: dhurari.transport@gmail.com | O9: 500 894 043 000 16 | P9: Centre Sud | Q9: 976-CS-071 | R9: 1000 | S9: 44349 | T9: FF-569-NF | U9: 43573 | V9: =2024-YEAR(U9) -> 5 | W9: 9 PLACES | Z9: NON | AA9: _ | AB9: NON | AE9: 45177 | AF9: F | AG9: _ | AH9: OUI | AI9: 2023 | AJ9: OUI | AK9: 2022 | AL9: OUI | AN9: 510 | AO9: 43466 | AP9: 250 | AS9: 97 | AT9: Rue du commerce | AU9: 97640 | AV9: Sada | AW9: voiture pas habillée
A10: 257 | B10: 59 | C10: CADEMA 1 | D10: AO | E10: NON | F10: - | G10: - | H10: 9 | I10: C3 | J10: C8 | K10: COMBO | L10: Said | M10: 0639 68 37 93 | N10: combosaid5@gmail.cpm | O10: 054 394 853 00029 | P10: Mamoudzou | Q10: 976-M-164 | R10: 920 | S10: 44871 | T10: GB-965-EQ | U10: 44419 | V10: =2024-YEAR(U10) -> 3 | W10: 9 PLACES | X10: NEUF | Y10: 45411 | Z10: NON | AA10: NON | AB10: NON | AC10: NON | AD10: NON | AE10: 49279 | AF10: F | AG10: _ | AH10: OUI | AI10: OUI | AJ10: 2024 | AK10: 2022 | AL10: NON | AM10: 2020/70 | AN10: 510 | AO10: 44295 | AP10: 100 | AQ10: NON | AR10: NON | AS10: 193 | AT10: Route Départementale | AU10: 97630 | AV10: Mtsamboro | AW10: Il a reçu sa subvention et il a rien payé, et il a utiliser l'argent
A11: 289 | B11: 65 | C11: CADEMA 1 | D11: AO | E11: NON | F11: - | G11: - | H11: 10 | I11: C1 | J11: C1 | K11: EL ANZIZE SALIM | L11: Hamada | M11: 0639 22 81 28 | N11: elsalimhamada@hotmail.com | O11: 024 076 531 00011 | P11: Mamoudzou | Q11: 976_M_209 | R11: 413 | S11: 46877 | T11: GM_515_YL | U11: 45012 | V11: =2024-YEAR(U11) -> 1 | W11: 9 PLACES | Z11: 2023 | AA11: OUI | AB11: 2023 | AD11: OUI | AE11: 10959 | AF11: G | AG11: _ | AH11: NON | AI11: NON | AJ11: NON | AK11: NON | AL11: OUI | AM11: 2022/198 | AN11: 510 | AO11: 43466 | AP11: 250 | AS11: 8 | AT11: Rue de mjinpia | AU11: 97650 | AV11: Mtsangamoudji | AW11: habillage 9 place 2023
A12: 353 | B12: 77 | C12: CADEMA 1 | D12: AO | E12: NON | F12: - | G12: - | H12: 11 | I12: C5 | J12: C16 | K12: HADHURAMI | L12: Makinedine | M12: 0639 94 46 40 | N12: Hadhuramimakinedine976@gmail.com | O12: 054 397 211 00019 | P12: SUD | Q12: 976_S_069 | R12: 150 | S12: 45874 | T12: FZ-411-ZD | U12: 44362 | V12: =2024-YEAR(U12) -> 3 | W12: 9 PLACES | Z12: OUI | AB12: OUI | AD12: OUI | AE12: 49522 | AF12: F | AG12: _ | AH12: OUI | AI12: 2023 | AJ12: NON | AK12: 2022 | AL12: OUI | AM12: 2020/82 | AN12: 510 | AO12: 43466 | AP12: 550 | AS12: 14 | AT12: Rue foundi hamada m'zé | AU12: 97625 | AV12: Kani kéli | AW12: Habillage 2021 aurait 2 véhicules
A13: 385 | B13: 83 | C13: CADEMA 1 | D13: AO | E13: NON | F13: - | G13: - | H13: 12 | J13: C13 | K13: MADI BOINA | L13: Mkidachi | M13: 0639 22 08 67 | N13: madiboinamkidachi@hotmail.com | O13: 500 793 526 00012 | P13: NORD | Q13: 976-N-63 | R13: 985 | S13: 44456 | T13: GS-501-ZK | U13: 45273 | W13: 9 PLACES | X13: NEUF | Y13: pas de vitre | Z13: NON | AA13: OUI | AB13: OUI | AC13: NON | AD13: A venir | AE13: 45248 | AF13: F | AH13: NON | AI13: NON | AJ13: NON | AK13: NON | AL13: NON | AN13: 510 | AO13: 43466 | AP13: 150 | AQ13: NON | AR13: NON | AS13: 27 | AT13: Rue d'andimaka | AU13: 97650 | AV13: Mtsangamouji
A14: 417 | B14: 89 | C14: CADEMA 1 | D14: AO | E14: NON | F14: - | G14: - | H14: 13 | I14: C7 | J14: C3 | K14: MOISSULI HIMIDI | L14: Enly | M14: 0639 94 58 14 | N14: enlymoissuli@gmail.com | O14: 853 881 084 000 18 | P14: NORD | Q14: 976-N-015 | R14: 994 | S14: 44263 | T14: GW-003-JA | U14: 45394 | W14: 9 PLACES | Y14: att May Equip | Z14: NON | AA14: NON | AB14: NON | AC14: NON | AD14: NON | AE14: 47621 | AF14: F | AH14: NON | AI14: NON | AJ14: NON | AK14: NON | AL14: OUI | AN14: 510 | AO14: 43466 | AP14: 200 | AQ14: NON | AR14: NON | AS14: 5 | AT14: Quartier mronobaban sidi , Hamjago | AU14: 97630 | AV14: Mtsamboro | AW14: Il attend sa subvention , justine lui a dit d'aller harceler le CD pour qui'il debloque sa subvention
A15: 97 | B15: 29 | C15: CADEMA 1 | D15: AO | E15: NON | F15: - | G15: - | H15: 14 | I15: soucis de famille | J15: C4 | K15: OUSSENI | L15: Soula | M15: 0639 69 03 87 | N15: soulaousseni415@gmail.com | O15: 066 307 372 000 12 | P15: Centre NORD | Q15: 976-CN-003 | R15: 249 | S15: 43132 | T15: GP_813_HX | U15: 45083 | V15: =2024-YEAR(U15) -> 1 | W15: 9 PLACES | X15: TBE | Z15: 2023 | AA15: OUI | AB15: 2023 | AD15: OUI | AE15: 49496 | AF15: F | AG15: _ | AH15: OUI | AI15: OUI | AJ15: OUI | AK15: OUI | AL15: OUI | AM15: 2021/181 | AN15: 510 | AO15: 43466 | AP15: 300 | AS15: 2 | AT15: Rue mnadzi moja quartier baitil mali | AU15: 97600 | AV15: Mamoudzou | AW15: Pas de voiture
A16: 321 | B16: 71 | C16: CADEMA 1 | D16: AO | E16: NON | F16: - | G16: - | H16: 15 | I16: C8 | J16: C5 | K16: RENE | L16: Assanati | M16: 0639 07 82 51 | O16: 024 065 633 000 18 | P16: NORD | Q16: 976-N-032 | R16: 1337 | S16: 45235 | T16: GR-921-XZ | U16: 45219 | V16: =2024-YEAR(U16) -> 1 | W16: 9 PLACES | Z16: OUI | AB16: NON | AD16: OUI | AE16: 48068 | AF16: F | AG16: _ | AH16: OUI | AI16: 2023 | AJ16: OUI | AK16: 2022 | AN16: 510 | AO16: 44171 | AP16: 150 | AS16: 32 | AT16: Rue bacar tsimanda | AU16: 97650 | AV16: Mtsangamouji
A17: 49 | B17: 20 | C17: CADEMA 1 | E17: NON | F17: NON | G17: NON | H17: 16 | J17: C9 | K17: SANDI | L17: Maanrouf | M17: 0639 40 58 85 | N17: maanroufsandi@laposte.net | O17: 024 069 635 000 19 | P17: Sud | Q17: 976-S-006 | R17: 1184 | S17: 45262 | T17: GW-255-NY | U17: 45406 | W17: 9 PLACES | X17: NEUF | Z17: NON | AA17: OUI | AB17: NON | AC17: NON | AD17: A VENIR | AE17: 46707 | AF17: F | AH17: OUI | AI17: OUI | AJ17: OUI | AK17: 2022 | AL17: NON | AN17: 510 | AO17: 43466 | AP17: 300 | AQ17: NON | AR17: NON | AT17: Quartier ecole primaire | AU17: 97620 | AV17: Chirongui | AW17: Pas habillé en attente rendez-vous mayotte equipement
A18: 177 | B18: 44 | C18: CADEMA 1 | E18: NON | F18: NON | G18: NON | H18: 17 | I18: C2 | J18: C11 | K18: TOUMBOU | L18: Toibourani | M18: 0639 19 14 22 | N18: toumboutoibourani@outlook.fr / anlia.toumbou97620@gmail.com | O18: 024 054 710 000 25 | P18: Mamoudzou | Q18: 976-M-177 | R18: 357 | S18: 45028 | T18: GF_215_AQ | U18: 44624 | V18: =2024-YEAR(U18) -> 2 | W18: 9 PLACES | X18: OK | Z18: 2023 | AA18: OUI | AB18: 2023 | AD18: OUI | AE18: 45992 | AF18: F | AH18: OUI | AI18: OUI | AJ18: NON | AK18: 2022 | AL18: OUI | AM18: 2020/158 | AN18: 510 | AO18: 43466 | AP18: 350 | AS18: 9 | AT18: Rue Bambou | AU18: 97620 | AV18: Chirongui | AW18: Gérant
A22: 17 | B22: 14 | C22: CADEMA 1 | E22: NON | F22: NON | G22: NON | H22: 2 | K22: ACHIRAFFI pas de chauffeur | L22: Assad | M22: 0639 29 01 58 | N22: achiraffis@gmail.com | O22: 024 046 617 000 15 | P22: Mamoudzou | Q22: 976-M-045 | R22: 90 | S22: 46916 | T22: FY-973-FL | U22: 44285 | V22: =2024-YEAR(U22) -> 3 | W22: 9 PLACES | X22: BON | Z22: OUI | AA22: OUI | AB22: OUI | AC22: OUI | AD22: NON | AE22: 49237 | AF22: F | AG22: _ | AH22: OUI | AI22: OUI | AJ22: OUI | AK22: 2022 | AL22: OUI | AM22: 2020/20 | AN22: 510 | AO22: 43466 | AP22: 450 | AQ22: NON | AR22: NON | AS22: 474 | AT22: Route départemental | AU22: 97630 | AV22: M'tsamboro | AW22: a une voiture - Travaille au Sud

Sheet Horaire détaillé
B2: , | C2: Planning de ramassage de PETITE-TERRE
B6: Ligne CHM PETITE-TERRE
B8: VEHICULES 8 PLACES | F8: MATIN
C10: SENS | F10: CHM-> Barge | G10: La Barge-> CHM | H10: CHM-> Barge | I10: CHM-> Barge | J10: La Barge-> CHM+CRA DIRECT | K10: CHM->Barge Direct | L10: La Barge-> CHM+CRA DIRECT | M10: La Barge-> CHM DIRECT | N10: CHM->Barge Direct | O10: La Barge-> CHM DIRECT
B11: Village | C11: Lieu de ramassage | D11: Non Direct | E11: Direct | F11: Heures de ramassage matin 5h40 CHM vers Barge | G11: Heures de ramassage matin 5:45 La Barge vers CHM | H11: Heures de ramassage matin 6h00 CHM vers Barge | I11: Heures de ramassage matin 6h30 CHM vers la barge | J11: Heures de ramassage matin 07h30 chm vers barge | K11: Heures de ramassage matin 06h55 barge vers chm | L11: Heures de ramassage matin 07h05 chm vers barge | M11: Heures de ramassage matin 07h30 barge vers CHM | N11: Heures de ramassage matin 07h50 CHM vers Barge | O11: Heures de ramassage matin 07h30 barge vers CHM
C12: CHAUFFEURS | F12: ='Feuille saisie'!C8 -> H1 | G12: =Horaire!H9 -> H5 | H12: ='Feuille saisie'!C10 -> H3 | I12: ='Feuille saisie'!C11 -> H1 | J12: ='Feuille saisie'!C12&"ET"&'Feuille saisie'!C13 -> H3ETH5 | K12: ='Feuille saisie'!C14&"ET"&'Feuille saisie'!C15 -> H1ETH5 | L12: ='Feuille saisie'!C16 -> H3 | M12: ='Feuille saisie'!C17 -> H5 | N12: ='Feuille saisie'!C18&" " -> H5 | O12: ='Feuille saisie'!C19 -> H1
B13: PAMANDZI | C13: CRA | D13: 0.0013888889 | E13: 0.0013888889 | J13: =J14+D13 -> 0.28125 | L13: =L14+D13 -> 0.30555556
B14: PAMANDZI | C14: CHM Marcel Henry | F14: ='Feuille saisie'!B8 -> 0.23263889 | G14: 0.25694444 | H14: ='Feuille saisie'!B10 -> 0.25 | I14: ='Feuille saisie'!B11 -> 0.27083333 | J14: =J28+$E$29 -> 0.27986111 | K14: ='Feuille saisie'!B14 -> 0.28819444 | L14: =L28+$E$29 -> 0.30416667 | M14: =M28+$E$29 -> 0.32152778 | N14: ='Feuille saisie'!B18 -> 0.32638889 | O14: =O28+$E$29 -> 0.33541667
B15: PAMANDZI | C15: =UPPER("la poste agence communale") -> LA POSTE AGENCE COMMUNALE | D15: 0.00069444444 | E15: 0.00069444444 | F15: =F14+D15 -> 0.23333333 | G15: =G16+D16 -> 0.25625 | H15: =H14+D15 -> 0.25069444 | I15: =I14+D15 -> 0.27152778
B16: PAMANDZI | C16: CIMETIERE PAMANDZI | D16: 0.00069444444 | E16: 0.00069444444 | F16: =D16+F15 -> 0.23402778 | G16: =G17+D17 -> 0.25555556 | H16: =H15+D16 -> 0.25138889 | I16: =I15+D16 -> 0.27222222
B17: PAMANDZI | C17: LYCEE DE PAMANDZI | D17: 0.0013888889 | E17: 0.00069444444 | F17: =D17+F16 -> 0.23541667 | G17: =G18+D18 -> 0.25416667 | H17: =H16+D17 -> 0.25277778 | I17: =I16+D17 -> 0.27361111
B18: PAMANDZI | C18: COLLEGE ZENA M'DERE PAMANDZI | D18: 0.0013888889 | E18: 0.00069444444 | F18: =D18+F17 -> 0.23680556 | G18: =G19+D19 -> 0.25277778 | H18: =H17+D18 -> 0.25416667 | I18: =I17+D18 -> 0.275
B19: PAMANDZI | C19: TUNNEL | D19: 0.0013888889 | E19: 0.00069444444 | F19: =D19+F18 -> 0.23819444 | G19: =G20+D20 -> 0.25138889 | H19: =H18+D19 -> 0.25555556 | I19: =I18+D19 -> 0.27638889
B20: LABATTOIR | C20: MADININA | D20: 0.0013888889 | E20: 0.00069444444 | F20: =D20+F19 -> 0.23958333 | G20: =G21+D21 -> 0.25 | H20: =H19+D20 -> 0.25694444 | I20: =I19+D20 -> 0.27777778
B21: LABATTOIR | C21: EN FACE DU RESTAURANT LE MOYA | D21: 0.0013888889 | E21: 0.00069444444 | F21: =D21+F20 -> 0.24097222 | G21: =G22+D22 -> 0.24861111 | H21: =H20+D21 -> 0.25833333 | I21: =I20+D21 -> 0.27916667
B22: LABATTOIR | C22: RELAI DE DZIANI | D22: 0.0013888889 | E22: 0.00069444444 | F22: =D22+F21 -> 0.24236111 | G22: =G23+D23 -> 0.24722222 | H22: =H21+D22 -> 0.25972222 | I22: =I21+D22 -> 0.28055556
B23: LABATTOIR | C23: EN FACE DE MAIMOUN DEPOT | D23: 0.00069444444 | E23: 0.00069444444 | F23: =D23+F22 -> 0.24305556 | G23: =G24+D24 -> 0.24652778 | H23: =H22+D23 -> 0.26041667 | I23: =I22+D23 -> 0.28125
B24: LABATTOIR | C24: CARREFOUR MARKET | D24: 0.0013888889 | E24: 0.00069444444 | F24: =D24+F23 -> 0.24444444 | G24: =G25+D25 -> 0.24513889 | H24: =H23+D24 -> 0.26180556 | I24: =I23+D24 -> 0.28263889
B25: LABATTOIR | C25: CIMETIERE LABATTOIR | D25: 0.0013888889 | E25: 0.00069444444 | F25: =D25+F24 -> 0.24583333 | G25: =G26+D26 -> 0.24375 | H25: =H24+D25 -> 0.26319444 | I25: =I24+D25 -> 0.28402778
B26: LABATTOIR | C26: =UPPER("acrinternation allineart tattoo") -> ACRINTERNATION ALLINEART TATTOO | D26: 0.0013888889 | E26: 0 | F26: =D26+F25 -> 0.24722222 | G26: =G27+D27 -> 0.24236111 | H26: =H25+D26 -> 0.26458333 | I26: =I25+D26 -> 0.28541667
B27: LABATTOIR | C27: SOMACO LABATTOIR | D27: 0.0013888889 | E27: 0.00069444444 | F27: =D27+F26 -> 0.24861111 | G27: =G28+D28 -> 0.24097222 | H27: =H26+D27 -> 0.26597222 | I27: =I26+D27 -> 0.28680556
B28: DZAOUDZI | C28: BARGE DE DZAOUDZI | D28: 0.0013888889 | E28: 0.00069444444 | F28: =D28+F27 -> 0.25 | G28: 0.23958333 | H28: =H27+D28 -> 0.26736111 | I28: =I27+D28 -> 0.28819444 | J28: ='Feuille saisie'!B12 -> 0.27083333 | K28: =K14+$E$29 -> 0.29722222 | L28: ='Feuille saisie'!B16 -> 0.29513889 | M28: ='Feuille saisie'!B17 -> 0.3125 | N28: =N14+E29 -> 0.33541667 | O28: ='Feuille saisie'!B19 -> 0.32638889
D29: =SUM(D15:D28) -> 0.017361111 | E29: =SUM(E15:E28) -> 0.0090277778 | G29: NEW
B34: Ligne CHM PETITE-TERRE
B36: VEHICULES 8 PLACES | F36: APRES-MIDI ET SOIREE
C38: SENS | F38: CHM-> Barge Direct | G38: La Barge-> CHM | H38: La Barge-> CHM | I38: CHM-> Barge Direct | J38: La Barge-> CHM | K38: La Barge-> CHM | L38: La Barge-> CHM | M38: La Barge-> CHM | N38: La Barge-> CHM Direct | O38: CHM-> Barge Direct | P38: La Barge-> CHM Direct | Q38: CHM-> Barge Direct | R38: La Barge-> CHM Direct | S38: CRA+CHM-> Barge Direct | T38: La Barge-> CHM Direct
B39: Village | C39: Lieu de ramassage | D39: Non Direct | E39: Direct | F39: Heures de ramassage 14:00 | G39: Heures de ramassage après midi 14h00 barge vers le CHM | H39: Heure de rammasage à 14:45 vers le CHM | I39: Heures de ramassage après midi 15h00 pharmacie vers la barge | J39: Heures de ramassage après midi 15h20 La barge vers le CHM | K39: Heures de ramassage après midi 15h50 La barge vers le CHM | L39: Heures de ramassage après midi 16h30 La barge vers le CHM | M39: Heures de ramassage après midi 17h00 La barge vers le CHM | N39: Heures de ramassage après midi 18h15 La barge vers le CHM | O39: Heures de ramassage après midi 18h15 barge vers chm | P39: Heures de ramassage après midi 18h15 La barge vers le CHM | Q39: Heures de ramassage après midi 18h45 chm vers barge | R39: Heures de ramassage après midi 18h15 La barge vers le CHM | S39: Heures de ramassage après midi 19h25 chm vers la barge | T39: Heures de ramassage après midi 19h45 La Barge vers CHM
C40: CHAUFFEURS | F40: ='Feuille saisie'!C25 -> H3 | G40: ='Feuille saisie'!C24 -> H1 | H40: ='Feuille saisie'!C26&"ET"&'Feuille saisie'!C27 -> H1ETH3 | I40: ='Feuille saisie'!C28 -> H5 | J40: ='Feuille saisie'!C29 -> H1 | K40: ='Feuille saisie'!C30 -> H5 | L40: ='Feuille saisie'!C31 -> H5 | M40: ='Feuille saisie'!C32 -> H5 | N40: ='Feuille saisie'!C33 -> H3 | O40: ='Feuille saisie'!C34 -> H1 | P40: =Horaire!H31 -> H1 | Q40: =Horaire!H32 -> H3 | R40: =Horaire!H33 -> H3 | S40: ='Feuille saisie'!C29 -> H1 | T40: =Horaire!H35 -> H3
B41: PAMANDZI | C41: CRA | E41: 0.0013888889 | S41: 0.80902778 | T41: ='Feuille saisie'!C36 -> H3
B42: PAMANDZI | C42: CHM Marcel Henry | D42: 0.0013888889 | F42: ='Feuille saisie'!B24 -> 0.58333333 | G42: =G43+D43 -> 0.60069444 | H42: =H43+D43 -> 0.63194444 | I42: ='Feuille saisie'!B28 -> 0.625 | J42: =J43+D43 -> 0.65625 | K42: =K43+D43 -> 0.67708333 | L42: =L43+D43 -> 0.70486111 | M42: =M43+D43 -> 0.72916667 | N42: =N56+$E$57 -> 0.76944444 | O42: ='Feuille saisie'!B33 -> 0.76041667 | P42: =P43+D43 -> 0.79861111 | Q42: ='Feuille saisie'!B35 -> 0.78125 | R42: =R43+D43 -> 0.81944444 | S42: =S41+D42 -> 0.81041667 | T42: =T43+D43 -> 0.84027778
B43: PAMANDZI | C43: =UPPER("la poste agence communale") -> LA POSTE AGENCE COMMUNALE | D43: =D15 -> 0.00069444444 | E43: =E15 -> 0.00069444444 | G43: =G44+D44 -> 0.6 | H43: =H44+D44 -> 0.63125 | J43: =J44+D44 -> 0.65555556 | K43: =K44+D44 -> 0.67638889 | L43: =L44+D44 -> 0.70416667 | M43: =M44+D44 -> 0.72847222 | P43: =P44+D44 -> 0.79791667 | R43: =R44+D44 -> 0.81875 | T43: =T44+D44 -> 0.83958333
B44: PAMANDZI | C44: CIMETIERE PAMANDZI | D44: =D16 -> 0.00069444444 | E44: =E16 -> 0.00069444444 | G44: =G45+D45 -> 0.59930556 | H44: =H45+D45 -> 0.63055556 | J44: =J45+D45 -> 0.65486111 | K44: =K45+D45 -> 0.67569444 | L44: =L45+D45 -> 0.70347222 | M44: =M45+D45 -> 0.72777778 | P44: =P45+D45 -> 0.79722222 | R44: =R45+D45 -> 0.81805556 | T44: =T45+D45 -> 0.83888889
B45: PAMANDZI | C45: LYCEE DE PAMANDZI | D45: =D17 -> 0.0013888889 | E45: =E17 -> 0.00069444444 | G45: =G46+D46 -> 0.59791667 | H45: =H46+D46 -> 0.62916667 | J45: =J46+D46 -> 0.65347222 | K45: =K46+D46 -> 0.67430556 | L45: =L46+D46 -> 0.70208333 | M45: =M46+D46 -> 0.72638889 | P45: =P46+D46 -> 0.79583333 | R45: =R46+D46 -> 0.81666667 | T45: =T46+D46 -> 0.8375
B46: PAMANDZI | C46: COLLEGE ZENA M'DERE PAMANDZI | D46: =D18 -> 0.0013888889 | E46: =E18 -> 0.00069444444 | G46: =G47+D47 -> 0.59652778 | H46: =H47+D47 -> 0.62777778 | J46: =J47+D47 -> 0.65208333 | K46: =K47+D47 -> 0.67291667 | L46: =L47+D47 -> 0.70069444 | M46: =M47+D47 -> 0.725 | P46: =P47+D47 -> 0.79444444 | R46: =R47+D47 -> 0.81527778 | T46: =T47+D47 -> 0.83611111
B47: PAMANDZI | C47: TUNNEL | D47: =D19 -> 0.0013888889 | E47: =E19 -> 0.00069444444 | G47: =G48+D48 -> 0.59513889 | H47: =H48+D48 -> 0.62638889 | J47: =J48+D48 -> 0.65069444 | K47: =K48+D48 -> 0.67152778 | L47: =L48+D48 -> 0.69930556 | M47: =M48+D48 -> 0.72361111 | P47: =P48+D48 -> 0.79305556 | R47: =R48+D48 -> 0.81388889 | T47: =T48+D48 -> 0.83472222
B48: LABATTOIR | C48: MADININA | D48: =D20 -> 0.0013888889 | E48: =E20 -> 0.00069444444 | G48: =G49+D49 -> 0.59375 | H48: =H49+D49 -> 0.625 | J48: =J49+D49 -> 0.64930556 | K48: =K49+D49 -> 0.67013889 | L48: =L49+D49 -> 0.69791667 | M48: =M49+D49 -> 0.72222222 | P48: =P49+D49 -> 0.79166667 | R48: =R49+D49 -> 0.8125 | T48: =T49+D49 -> 0.83333333
B49: LABATTOIR | C49: EN FACE DU RESTAURANT LE MOYA | D49: =D21 -> 0.0013888889 | E49: =E21 -> 0.00069444444 | G49: =G50+D50 -> 0.59236111 | H49: =H50+D50 -> 0.62361111 | J49: =J50+D50 -> 0.64791667 | K49: =K50+D50 -> 0.66875 | L49: =L50+D50 -> 0.69652778 | M49: =M50+D50 -> 0.72083333 | P49: =P50+D50 -> 0.79027778 | R49: =R50+D50 -> 0.81111111 | T49: =T50+D50 -> 0.83194444
B50: LABATTOIR | C50: RELAI DE DZIANI | D50: =D22 -> 0.0013888889 | E50: =E22 -> 0.00069444444 | G50: =G51+D51 -> 0.59097222 | H50: =H51+D51 -> 0.62222222 | J50: =J51+D51 -> 0.64652778 | K50: =K51+D51 -> 0.66736111 | L50: =L51+D51 -> 0.69513889 | M50: =M51+D51 -> 0.71944444 | P50: =P51+D51 -> 0.78888889 | R50: =R51+D51 -> 0.80972222 | T50: =T51+D51 -> 0.83055556
B51: LABATTOIR | C51: EN FACE DE MAIMOUN DEPOT | D51: =D23 -> 0.00069444444 | E51: =E23 -> 0.00069444444 | G51: =G52+D52 -> 0.59027778 | H51: =H52+D52 -> 0.62152778 | J51: =J52+D52 -> 0.64583333 | K51: =K52+D52 -> 0.66666667 | L51: =L52+D52 -> 0.69444444 | M51: =M52+D52 -> 0.71875 | P51: =P52+D52 -> 0.78819444 | R51: =R52+D52 -> 0.80902778 | T51: =T52+D52 -> 0.82986111
B52: LABATTOIR | C52: CARREFOUR MARKET | D52: =D24 -> 0.0013888889 | E52: =E24 -> 0.00069444444 | G52: =G53+D53 -> 0.58888889 | H52: =H53+D53 -> 0.62013889 | J52: =J53+D53 -> 0.64444444 | K52: =K53+D53 -> 0.66527778 | L52: =L53+D53 -> 0.69305556 | M52: =M53+D53 -> 0.71736111 | P52: =P53+D53 -> 0.78680556 | R52: =R53+D53 -> 0.80763889 | T52: =T53+D53 -> 0.82847222
B53: LABATTOIR | C53: CIMETIERE LABATTOIR | D53: =D25 -> 0.0013888889 | E53: =E25 -> 0.00069444444 | G53: =G54+D54 -> 0.5875 | H53: =H54+D54 -> 0.61875 | J53: =J54+D54 -> 0.64305556 | K53: =K54+D54 -> 0.66388889 | L53: =L54+D54 -> 0.69166667 | M53: =M54+D54 -> 0.71597222 | P53: =P54+D54 -> 0.78541667 | R53: =R54+D54 -> 0.80625 | T53: =T54+D54 -> 0.82708333
B54: LABATTOIR | C54: =UPPER("acrinternation allineart tattoo") -> ACRINTERNATION ALLINEART TATTOO | D54: =D26 -> 0.0013888889 | E54: =E26 -> 0 | G54: =G55+D55 -> 0.58611111 | H54: =H55+D55 -> 0.61736111 | J54: =J55+D55 -> 0.64166667 | K54: =K55+D55 -> 0.6625 | L54: =L55+D55 -> 0.69027778 | M54: =M55+D55 -> 0.71458333 | P54: =P55+D55 -> 0.78402778 | R54: =R55+D55 -> 0.80486111 | T54: =T55+D55 -> 0.82569444
B55: LABATTOIR | C55: SOMACO LABATTOIR | D55: =D27 -> 0.0013888889 | E55: =E27 -> 0.00069444444 | G55: =G56+D56 -> 0.58472222 | H55: =H56+D56 -> 0.61597222 | J55: =J56+D56 -> 0.64027778 | K55: =K56+D56 -> 0.66111111 | L55: =L56+D56 -> 0.68888889 | M55: =M56+D56 -> 0.71319444 | P55: =P56+D56 -> 0.78263889 | R55: =R56+D56 -> 0.80347222 | T55: =T56+D56 -> 0.82430556
B56: DZAOUDZI | C56: BARGE DE DZAOUDZI | D56: =D28 -> 0.0013888889 | E56: =E28 -> 0.00069444444 | F56: =F42+$E$57 -> 0.59236111 | G56: ='Feuille saisie'!B24 -> 0.58333333 | H56: ='Feuille saisie'!B26 -> 0.61458333 | I56: =I42+E57 -> 0.63402778 | J56: ='Feuille saisie'!B29 -> 0.63888889 | K56: ='Feuille saisie'!B30 -> 0.65972222 | L56: ='Feuille saisie'!B31 -> 0.6875 | M56: ='Feuille saisie'!B32 -> 0.71180556 | N56: ='Feuille saisie'!B33 -> 0.76041667 | O56: =O42+$E$57 -> 0.76944444 | P56: 0.78125 | Q56: =Q42+$E$57 -> 0.79027778 | R56: 0.80208333 | S56: =S42+$E$57 -> 0.81944444 | T56: 0.82291667
D57: =SUM(D43:D56) -> 0.017361111 | E57: =SUM(E43:E56) -> 0.0090277778

Sheet Feuil2
D2: MARCHE AGENT CHM PETITE TERRE
D3: PLANNING INITIAL
G5: CHAUFFEURS
B6: HEURE DE DEPART | C6: LIEU DE DEPART ET DESTINATION | D6: DIRECT | E6: H1 | F6: H2 | G6: H3 | H6: H4 | I6: H5 | J6: H6
E7: Lundi au Samedi | G7: Dimanche | H7: Lundi au Vendredi | J7: Dimanche
B9: 0.23958333 | C9: CHM-> BARGE | D9: NON | E9: X | F9: X | G9: X
B10: 0.26041667 | C10: BARGE-> CHM | D10: OUI | E10: X | F10: X | G10: X | I10: EN RESERVE
B11: 0.28125 | C11: CHM-> BARGE | D11: NON | E11: X | F11: X | G11: X | I11: OPERATIONNEL MOIS
B12: 0.30208333 | C12: BARGE-> CHM | D12: OUI | E12: X | F12: X | G12: X | I12: SUIVANT
B13: 0.3125 | C13: CHM-> BARGE | D13: NON | E13: X | F13: X | G13: X
B15: 0.58333333 | C15: CHM->BARGE | D15: OUI | E15: X | F15: X | G15: X
B16: 0.625 | C16: CHM->BARGE | D16: OUI | E16: X | G16: X
B17: 0.76041667 | C17: CHM->BARGE | D17: NON | E17: X | G17: X
B18: 0.78125 | C18: CHM->BARGE | D18: NON | F18: X | G18: X
B19: 0.8125 | C19: CHM->BARGE | D19: NON | F19: X | G19: X
C21: Nbre trajets | E21: 8 | F21: 8 | G21: 10
E22: 3h/jrs | F22: 3h/jrs | G22: 4h/jrs
C23: Montant par mois | E23: >1920€ | F23: >1920€ | G23: >1040€
C24: Prix au trajet supplémentaire | E24: 12 | F24: 12 | G24: 14€ le dimanche | H24: 12 | I24: 12 | J24: 14€ le dimanche
D26: RESPECT DES HORAIRES
D27: VEHICULE PROPRE ET CLIMATISE
D28: QUALITE D'ACCUEIL
D29: ESPRIT D'EQUIPE
D30: COORDINATEUR : IBRAHIM HAMADA
D31: AFFICHETTES MAGNETIQUES INDIQUANT NAVETTE CHM
D32: CONTRÔLE DES BADGES CHM
D33: DATE DE DEPART : 1/02/2026 (DIMANCHE)

Sheet Previsions facturation
B4: Mois | C4: 46054
C6: Type de trajets | F6: Nombre de trajet quotidien | G6: Nombre de véhicules | H6: Nombre de jours dans le mois | I6: Tarif | J6: Valeur | K6: Tarif achat | L6: Cout achat | N6: Chauffeur | O6: Nbre trajets quotidiens | P6: Nbre jour | Q6: Tarif | R6: Valeur
B7: Jours de la semaine hors samedi, dimanche et jours fériés | C7: Trajets véhicules 8 places avant 7:00 | F7: 3 | G7: 2 | H7: =28-H12-H17 -> 20 | I7: 15.85 | J7: =F7*H7*I7*G7 -> 1902 | K7: 12 | L7: =F7*H7*K7*G7 -> 1440 | N7: H1
C8: Trajets véhicules 8 places de 7:00 à 7:30 | F8: 2 | G8: 2 | I8: 15.06 | J8: =F8*H$7*I8*G8 -> 1204.8 | K8: 12 | L8: =F8*H$7*K8*G8 -> 960 | N8: Semaine 1 et 2 | O8: 8 | P8: 12 | Q8: =K7 -> 12 | R8: =O8*P8*Q8 -> 1152
C9: Trajets véhicules 8 places de 14:00 | F9: 1 | G9: 2 | I9: 15.06 | J9: =F9*H$7*I9*G9 -> 602.4 | K9: 12 | L9: =F9*H$7*K9*G9 -> 480 | N9: Semaine 3 et 4 | O9: 8 | P9: 12 | Q9: =K7 -> 12 | R9: =O9*P9*Q9 -> 1152
C10: Trajets véhicules 8 places de 15:00 à 19:30 | F10: 4 | G10: 1 | I10: 15.06 | J10: =F10*H$7*I10*G10 -> 1204.8 | K10: 12 | L10: =F10*H$7*K10*G10 -> 960 | R10: =SUM(R8:R9) -> 2304
F11: =F7*G7+F8*G8+F9*G9+F10*G10 -> 16 | H11: =F11*H7 -> 320 | I11: Trajets | N11: H2
B12: Samedis | C12: Trajets véhicules 8 places avant 7:00 | F12: 3 | G12: 2 | H12: 4 | I12: 15.85 | J12: =F12*H$12*I12*G12 -> 380.4 | K12: 12 | L12: =F12*H$12*K12*G12 -> 288 | N12: Semaine 1 et 2 | O12: 8 | P12: 12 | Q12: =K8 -> 12 | R12: =O12*P12*Q12 -> 1152
C13: Trajets véhicules 8 places de 7:00 à 7:30 | F13: 2 | G13: 2 | I13: 15.06 | J13: =F13*H$12*I13*G13 -> 240.96 | K13: 12 | L13: =F13*H$12*K13*G13 -> 192 | N13: Semaine 3 et 4 | O13: 8 | P13: 12 | Q13: =K7 -> 12 | R13: =O13*P13*Q13 -> 1152
C14: Trajets véhicules 8 places de 14:00 | F14: 1 | G14: 2 | I14: 15.06 | J14: =F14*H$12*I14*G14 -> 120.48 | K14: 12 | L14: =F14*H$12*K14*G14 -> 96 | R14: =SUM(R11:R13) -> 2304
C15: Trajets véhicules 8 places de 15:00 à 19:30 | F15: 4 | G15: 1 | I15: 15.06 | J15: =F15*H$12*I15*G15 -> 240.96 | K15: 12 | L15: =F15*H$12*K15*G15 -> 192 | N15: H3
F16: =F12*G12+F13*G13+F14*G14+F15*G15 -> 16 | H16: =F16*H12 -> 64 | I16: Trajets
B17: Dimanches et jours fériés | C17: Trajets véhicules 8 places avant 7:00 | F17: 3 | G17: 1 | H17: 4 | I17: 17.39 | J17: =F17*H$17*I17*G17 -> 208.68 | K17: 14 | L17: =F17*H$17*K17*G17 -> 168 | N17: Dimanche | O17: 10 | P17: 4 | Q17: =K17 -> 14 | R17: =O17*P17*Q17 -> 560
C18: Trajets véhicules 8 places de 7:00 à 7:30 | F18: 2 | G18: 1 | I18: 16.61 | J18: =F18*H$17*I18*G18 -> 132.88 | K18: 14 | L18: =F18*H$17*K18*G18 -> 112 | R18: =SUM(R16:R17) -> 560
C19: Trajets véhicules 8 places de 14:00 | F19: 1 | G19: 1 | I19: 16.61 | J19: =F19*H$17*I19*G19 -> 66.44 | K19: 14 | L19: =F19*H$17*K19*G19 -> 56 | R19: =R10+R14+R18 -> 5168
C20: Trajets véhicules 8 places de 15:00 à 19:30 | F20: 4 | G20: 1 | I20: =I19 -> 16.61 | J20: =F20*H$17*I20*G20 -> 265.76 | K20: 14 | L20: =F20*H$17*K20*G20 -> 224
F21: =F17*G17+F18*G18+F19*G19+F20*G20 -> 10 | H21: =F21*H17 -> 40 | I21: Trajets
C22: TOTAL MOIS | H22: =H11+H16+H21 -> 424 | I22: Trajets | J22: =SUM(J7:J21) -> 6570.56 | L22: =SUM(L7:L21) -> 5168
K24: Marge direct | L24: =J22-L22 -> 1402.56 | M24: =L24/J22 -> 0.21346126
K25: Coordinateur | L25: =500*1 -> 500
K26: Marge | L26: =L24-L25 -> 902.56 | M26: =L26/J22 -> 0.13736424

Sheet Feuille saisie dimanché
G1: ù
A2: TYPE | B2: H5
A3: DATE | B3: 45627
A4: CHAUFFEUR | B4: =VLOOKUP(B2,'Liste chauffeur'!$B$5:$L$19,2,TRUE)&" "&VLOOKUP(B2,'Liste chauffeur'!$B$5:$L$19,3,TRUE) -> ATTOUMANI Kamaldine
J6: Arrêt 1 | M6: ARRIVEE | Q6: 8
A7: LIEU DE DEPART | B7: Heure théorique départ | C7: Horaire | D7: Chauffeur | E7: Direct/Non Direct | F7: Heure réelle départ | G7: Trajet non effectué | H7: Départ avec plus de 10 mns retard | I7: Nbre personnes montée | J7: - | K7: + | L7: Nbre personnes descente | M7: Heure arrivée finale | N7: Commentaires | O7: Temps Aller | P7: Nbre personnes moyenne | Q7: Capacité max | R7: Taux Fréquentation
A8: ='Horaire dimanche2'!A8 -> CHM | B8: ='Horaire dimanche2'!E8 -> 0.23263889 | C8: ='Horaire dimanche2'!H8 -> H1 | D8: =VLOOKUP(C8,'Liste chauffeur'!$B$5:$L$19,2,TRUE)&" "&VLOOKUP(C8,'Liste chauffeur'!$B$5:$L$19,3,TRUE) -> CHADHOULI Houmadi | E8: ='Horaire dimanche2'!C8 -> 13 ARRETS | G8: =COUNTBLANK(F8) -> 1 | O8: =IF(G8=1,"",M8-F8) | P8: =I8+K8-J8 -> 0 | Q8: =IF(G8=1,0,Q$6) -> 0 | R8: =IF(Q8=0,0,P8/Q8) -> 0
A9: ='Horaire dimanche2'!A9 -> CHM | B9: ='Horaire dimanche2'!E9 -> 0.25 | C9: ='Horaire dimanche2'!H9 -> H3 | D9: =VLOOKUP(C9,'Liste chauffeur'!$B$5:$L$19,2,TRUE)&" "&VLOOKUP(C9,'Liste chauffeur'!$B$5:$L$19,3,TRUE) -> SAID ALI Kamile | E9: ='Horaire dimanche2'!C9 -> 13 ARRETS | G9: =COUNTBLANK(F9) -> 1 | O9: =IF(G9=1,"",M9-F9) | P9: =I9+K9-J9 -> 0 | Q9: =IF(G9=1,0,Q$6) -> 0 | R9: =IF(Q9=0,0,P9/Q9) -> 0
A10: ='Horaire dimanche2'!A10 -> CHM | B10: ='Horaire dimanche2'!E10 -> 0.27083333 | C10: ='Horaire dimanche2'!H10 -> H1 | D10: =VLOOKUP(C10,'Liste chauffeur'!$B$5:$L$19,2,TRUE)&" "&VLOOKUP(C10,'Liste chauffeur'!$B$5:$L$19,3,TRUE) -> CHADHOULI Houmadi | E10: ='Horaire dimanche2'!C10 -> 13 ARRETS | G10: =COUNTBLANK(F10) -> 1 | O10: =IF(G10=1,"",M10-F10) | P10: =I10+K10-J10 -> 0 | Q10: =IF(G10=1,0,Q$6) -> 0 | R10: =IF(Q10=0,0,P10/Q10) -> 0
A11: ='Horaire dimanche2'!A11 -> LA BARGE | B11: ='Horaire dimanche2'!E11 -> 0.27083333 | C11: ='Horaire dimanche2'!H11 -> H3 | D11: =VLOOKUP(C11,'Liste chauffeur'!$B$5:$L$19,2,TRUE)&" "&VLOOKUP(C11,'Liste chauffeur'!$B$5:$L$19,3,TRUE) -> SAID ALI Kamile | E11: ='Horaire dimanche2'!C11 -> DIRECT | G11: =COUNTBLANK(F11) -> 1 | O11: =IF(G11=1,"",M11-F11) | P11: =I11+K11-J11 -> 0 | Q11: =IF(G11=1,0,Q$6) -> 0 | R11: =IF(Q11=0,0,P11/Q11) -> 0
A12: ='Horaire dimanche2'!A12 -> CHM | B12: ='Horaire dimanche2'!E12 -> 0.28819444 | C12: ='Horaire dimanche2'!H12 -> H1 | D12: =VLOOKUP(C12,'Liste chauffeur'!$B$5:$L$19,2,TRUE)&" "&VLOOKUP(C12,'Liste chauffeur'!$B$5:$L$19,3,TRUE) -> CHADHOULI Houmadi | E12: ='Horaire dimanche2'!C12 -> DIRECT | G12: =COUNTBLANK(F12) -> 1 | O12: =IF(G12=1,"",M12-F12) | P12: =I12+K12-J12 -> 0 | Q12: =IF(G12=1,0,Q$6) -> 0 | R12: =IF(Q12=0,0,P12/Q12) -> 0
A13: ='Horaire dimanche2'!A13 -> LA BARGE | B13: ='Horaire dimanche2'!E13 -> 0.29513889 | C13: ='Horaire dimanche2'!H13 -> H3 | D13: =VLOOKUP(C13,'Liste chauffeur'!$B$5:$L$19,2,TRUE)&" "&VLOOKUP(C13,'Liste chauffeur'!$B$5:$L$19,3,TRUE) -> SAID ALI Kamile | E13: ='Horaire dimanche2'!C13 -> DIRECT | G13: =COUNTBLANK(F13) -> 1 | O13: =IF(G13=1,"",M13-F13) | P13: =I13+K13-J13 -> 0 | Q13: =IF(G13=1,0,Q$6) -> 0 | R13: =IF(Q13=0,0,P13/Q13) -> 0
A14: ='Horaire dimanche2'!A14 -> LA BARGE | B14: ='Horaire dimanche2'!E14 -> 0.3125 | C14: ='Horaire dimanche2'!H14 -> H5 | D14: =VLOOKUP(C14,'Liste chauffeur'!$B$5:$L$19,2,TRUE)&" "&VLOOKUP(C14,'Liste chauffeur'!$B$5:$L$19,3,TRUE) -> ATTOUMANI Kamaldine | E14: ='Horaire dimanche2'!C14 -> DIRECT | G14: =COUNTBLANK(F14) -> 1 | O14: =IF(G14=1,"",M14-F14) | P14: =I14+K14-J14 -> 0 | Q14: =IF(G14=1,0,Q$6) -> 0 | R14: =IF(Q14=0,0,P14/Q14) -> 0
A15: ='Horaire dimanche2'!A15 -> LA BARGE | B15: ='Horaire dimanche2'!E15 -> 0.32638889 | C15: ='Horaire dimanche2'!H15 -> H5 | D15: =VLOOKUP(C15,'Liste chauffeur'!$B$5:$L$19,2,TRUE)&" "&VLOOKUP(C15,'Liste chauffeur'!$B$5:$L$19,3,TRUE) -> ATTOUMANI Kamaldine | E15: ='Horaire dimanche2'!C15 -> DIRECT | G15: =COUNTBLANK(F15) -> 1 | O15: =IF(G15=1,"",M15-F15) | P15: =I15+K15-J15 -> 0 | Q15: =IF(G15=1,0,Q$6) -> 0 | R15: =IF(Q15=0,0,P15/Q15) -> 0
B16: NON PLANIFIE | G16: =COUNTBLANK(F16) -> 1 | O16: =IF(G16=1,"",M16-F16) | P16: =I16+K16-J16 -> 0 | Q16: =IF(G16=1,0,Q$6) -> 0 | R16: =IF(Q16=0,0,P16/Q16) -> 0
B17: NON PLANIFIE | G17: =COUNTBLANK(F17) -> 1 | P17: =I17+K17-J17 -> 0 | Q17: =IF(G17=1,0,Q$6) -> 0 | R17: =IF(Q17=0,0,P17/Q17) -> 0
A18: ='Horaire dimanche'!A18 -> 0 | B18: ='Horaire dimanche'!E18 -> 0 | C18: ='Horaire dimanche'!H18 -> 0 | D18: =VLOOKUP(C18,'Liste chauffeur'!$B$5:$L$19,2,TRUE)&" "&VLOOKUP(C18,'Liste chauffeur'!$B$5:$L$19,3,TRUE) -> #N/A | E18: ='Horaire dimanche'!C18 -> 0 | G18: =SUM(G8:G17) -> 10 | H18: =SUM(H8:H17) -> 0 | O18: =AVERAGE(O8:O17) -> #DIV/0! | P18: =SUM(P8:P17) -> 0 | Q18: =SUM(Q8:Q17) -> 0 | R18: =P18/Q18 -> #DIV/0!
A19: ='Horaire dimanche2'!A16 -> LA BARGE | B19: ='Horaire dimanche2'!E16 -> 0.58333333 | C19: ='Horaire dimanche2'!H16 -> H1 | D19: =VLOOKUP(C19,'Liste chauffeur'!$B$5:$L$19,2,TRUE)&" "&VLOOKUP(C19,'Liste chauffeur'!$B$5:$L$19,3,TRUE) -> CHADHOULI Houmadi | E19: ='Horaire dimanche2'!C16 -> 13 ARRETS | G19: =COUNTBLANK(F19) -> 1 | O19: =IF(G19=1,"",M19-F19) | P19: =I19+K19-J19 -> 0 | Q19: =IF(G19=1,0,Q$6) -> 0 | R19: =IF(Q19=0,0,P19/Q19) -> 0
A20: ='Horaire dimanche2'!A17 -> CHM | B20: ='Horaire dimanche2'!E17 -> 0.58333333 | C20: ='Horaire dimanche2'!H17 -> H3 | D20: =VLOOKUP(C20,'Liste chauffeur'!$B$5:$L$19,2,TRUE)&" "&VLOOKUP(C20,'Liste chauffeur'!$B$5:$L$19,3,TRUE) -> SAID ALI Kamile | E20: ='Horaire dimanche2'!C17 -> DIRECT | G20: =COUNTBLANK(F20) -> 1 | O20: =IF(G20=1,"",M20-F20) | P20: =I20+K20-J20 -> 0 | Q20: =IF(G20=1,0,Q$6) -> 0 | R20: =IF(Q20=0,0,P20/Q20) -> 0
A21: ='Horaire dimanche2'!A18 -> LA BARGE | B21: ='Horaire dimanche2'!E18 -> 0.61458333 | C21: ='Horaire dimanche2'!H18 -> H1 | D21: =VLOOKUP(C21,'Liste chauffeur'!$B$5:$L$19,2,TRUE)&" "&VLOOKUP(C21,'Liste chauffeur'!$B$5:$L$19,3,TRUE) -> CHADHOULI Houmadi | E21: ='Horaire dimanche2'!C18 -> 13 ARRETS | G21: =COUNTBLANK(F21) -> 1 | O21: =IF(G21=1,"",M21-F21) | P21: =I21+K21-J21 -> 0 | Q21: =IF(G21=1,0,Q$6) -> 0 | R21: =IF(Q21=0,0,P21/Q21) -> 0
A22: ='Horaire dimanche2'!A19 -> CHM | B22: ='Horaire dimanche2'!E19 -> 0.625 | C22: ='Horaire dimanche2'!H19 -> H3 | D22: =VLOOKUP(C22,'Liste chauffeur'!$B$5:$L$19,2,TRUE)&" "&VLOOKUP(C22,'Liste chauffeur'!$B$5:$L$19,3,TRUE) -> SAID ALI Kamile | E22: ='Horaire dimanche2'!C19 -> DIRECT | G22: =COUNTBLANK(F22) -> 1 | O22: =IF(G22=1,"",M22-F22) | P22: =I22+K22-J22 -> 0 | Q22: =IF(G22=1,0,Q$6) -> 0 | R22: =IF(Q22=0,0,P22/Q22) -> 0
A23: ='Horaire dimanche2'!A20 -> LA BARGE | B23: ='Horaire dimanche2'!E20 -> 0.63888889 | C23: ='Horaire dimanche2'!H20 -> H1 | D23: =VLOOKUP(C23,'Liste chauffeur'!$B$5:$L$19,2,TRUE)&" "&VLOOKUP(C23,'Liste chauffeur'!$B$5:$L$19,3,TRUE) -> CHADHOULI Houmadi | E23: ='Horaire dimanche2'!C20 -> 13 ARRETS | G23: =COUNTBLANK(F23) -> 1 | O23: =IF(G23=1,"",M23-F23) | P23: =I23+K23-J23 -> 0 | Q23: =IF(G23=1,0,Q$6) -> 0 | R23: =IF(Q23=0,0,P23/Q23) -> 0
A24: ='Horaire dimanche2'!A21 -> LA BARGE | B24: ='Horaire dimanche2'!E21 -> 0.65972222 | C24: ='Horaire dimanche2'!H21 -> H5 | D24: =VLOOKUP(C24,'Liste chauffeur'!$B$5:$L$19,2,TRUE)&" "&VLOOKUP(C24,'Liste chauffeur'!$B$5:$L$19,3,TRUE) -> ATTOUMANI Kamaldine | E24: ='Horaire dimanche2'!C21 -> 13 ARRETS | G24: =COUNTBLANK(F24) -> 1 | O24: =IF(G24=1,"",M24-F24) | P24: =I24+K24-J24 -> 0 | Q24: =IF(G24=1,0,Q$6) -> 0 | R24: =IF(Q24=0,0,P24/Q24) -> 0
A25: ='Horaire dimanche2'!A22 -> LA BARGE | B25: ='Horaire dimanche2'!E22 -> 0.6875 | C25: ='Horaire dimanche2'!H22 -> H5 | D25: =VLOOKUP(C25,'Liste chauffeur'!$B$5:$L$19,2,TRUE)&" "&VLOOKUP(C25,'Liste chauffeur'!$B$5:$L$19,3,TRUE) -> ATTOUMANI Kamaldine | E25: ='Horaire dimanche2'!C22 -> 13 ARRETS | G25: =COUNTBLANK(F25) -> 1 | O25: =IF(G25=1,"",M25-F25) | P25: =I25+K25-J25 -> 0 | Q25: =IF(G25=1,0,Q$6) -> 0 | R25: =IF(Q25=0,0,P25/Q25) -> 0
A26: ='Horaire dimanche2'!A23 -> CHM | B26: ='Horaire dimanche2'!E23 -> 0.76041667 | C26: ='Horaire dimanche2'!H23 -> H3 | D26: =VLOOKUP(C26,'Liste chauffeur'!$B$5:$L$19,2,TRUE)&" "&VLOOKUP(C26,'Liste chauffeur'!$B$5:$L$19,3,TRUE) -> SAID ALI Kamile | E26: ='Horaire dimanche2'!C23 -> DIRECT | G26: =COUNTBLANK(F26) -> 1 | O26: =IF(G26=1,"",M26-F26) | P26: =I26+K26-J26 -> 0 | Q26: =IF(G26=1,0,Q$6) -> 0 | R26: =IF(Q26=0,0,P26/Q26) -> 0
A27: ='Horaire dimanche2'!A24 -> LA BARGE | B27: ='Horaire dimanche2'!E24 -> 0.76041667 | C27: ='Horaire dimanche2'!H24 -> H5 | D27: =VLOOKUP(C27,'Liste chauffeur'!$B$5:$L$19,2,TRUE)&" "&VLOOKUP(C27,'Liste chauffeur'!$B$5:$L$19,3,TRUE) -> ATTOUMANI Kamaldine | E27: ='Horaire dimanche2'!C24 -> 13 ARRETS
A28: ='Horaire dimanche2'!A25 -> CHM | B28: ='Horaire dimanche2'!E25 -> 0.78125 | C28: ='Horaire dimanche2'!H25 -> H5 | D28: =VLOOKUP(C28,'Liste chauffeur'!$B$5:$L$19,2,TRUE)&" "&VLOOKUP(C28,'Liste chauffeur'!$B$5:$L$19,3,TRUE) -> ATTOUMANI Kamaldine | E28: ='Horaire dimanche2'!C25 -> DIRECT
A29: ='Horaire dimanche2'!A26 -> LA BARGE | B29: ='Horaire dimanche2'!E26 -> 0.78125 | C29: ='Horaire dimanche2'!H26 -> H3 | D29: =VLOOKUP(C29,'Liste chauffeur'!$B$5:$L$19,2,TRUE)&" "&VLOOKUP(C29,'Liste chauffeur'!$B$5:$L$19,3,TRUE) -> SAID ALI Kamile | E29: ='Horaire dimanche2'!C26 -> 13 ARRETS | G29: =COUNTBLANK(F29) -> 1
A30: ='Horaire dimanche2'!A27 -> CRA+CHM | B30: ='Horaire dimanche2'!E27 -> 0.80902778 | C30: ='Horaire dimanche2'!H27 -> H5 | D30: =VLOOKUP(C30,'Liste chauffeur'!$B$5:$L$19,2,TRUE)&" "&VLOOKUP(C30,'Liste chauffeur'!$B$5:$L$19,3,TRUE) -> ATTOUMANI Kamaldine | E30: ='Horaire dimanche2'!C27 -> DIRECT
A31: ='Horaire dimanche2'!A28 -> LA BARGE | B31: ='Horaire dimanche2'!E28 -> 0.82291667 | C31: ='Horaire dimanche2'!H28 -> H5 | D31: =VLOOKUP(C31,'Liste chauffeur'!$B$5:$L$19,2,TRUE)&" "&VLOOKUP(C31,'Liste chauffeur'!$B$5:$L$19,3,TRUE) -> ATTOUMANI Kamaldine | E31: ='Horaire dimanche2'!C28 -> 13 ARRETS
B32: NON PLANIFIE | G32: =COUNTBLANK(F32) -> 1 | O32: =IF(G32=1,"",M32-F32) | P32: =I32+K32-J32 -> 0 | Q32: =IF(G32=1,0,Q$6) -> 0 | R32: =IF(Q32=0,0,P32/Q32) -> 0
B33: NON PLANIFIE | G33: =COUNTBLANK(F33) -> 1 | P33: =I33+K33-J33 -> 0 | Q33: =IF(G33=1,0,Q$6) -> 0 | R33: =IF(Q33=0,0,P33/Q33) -> 0
B34: ST2 | C34: ST | G34: =SUM(#REF!) -> #REF! | O34: =AVERAGE(#REF!) -> #REF! | P34: =SUM(#REF!) -> #REF! | Q34: =SUM(#REF!) -> #REF! | R34: =IF(Q34=0,0,P34/Q34) -> #REF!
A35: REMPLACEMENT | C35: H | O35: =AVERAGE(O8:O17,#REF!) -> #REF! | P35: =P18+P34 -> #REF! | Q35: =Q18+Q34 -> #REF! | R35: =IF(Q35=0,0,P35/Q35) -> #REF!
A36: REMPLACEMENT | C36: H
A37: REMPLACEMENT | C37: H
A38: REMPLACEMENT | C38: H
A39: REMPLACEMENT | C39: H
C41: S | F41: Signature Chauffeur | J41: Signature Coordinateur
B44: Statistiques | C44: nbre de trajets planifiés | D44: Nbre trajets non effectués | F44: Nbre trajets effectués non planifiés
B45: H1 | C45: =COUNTIF($B$8:$C$17,B45) -> 3 | D45: =C45-(COUNTIFS(C$8:C$17,B45,N$8:N$17,"")) -> 0 | F45: =COUNTIFS(N$8:N$17,$B45) -> 0
B46: H2 | C46: =COUNTIF($B$8:$C$17,B46) -> 0 | D46: =C46-(COUNTIFS(C$8:C$17,B46,N$8:N$17,"")) -> 0 | F46: =COUNTIFS(N$8:N$17,$B46) -> 0
B47: H3 | C47: =COUNTIF($B$8:$C$17,B47) -> 3 | D47: =C47-(COUNTIFS(C$8:C$17,B47,N$8:N$17,"")) -> 0 | F47: =COUNTIFS(N$8:N$17,$B47) -> 0
B48: H4 | C48: =COUNTIF($B$8:$C$17,B48) -> 0 | D48: =C48-(COUNTIFS(C$8:C$17,B48,N$8:N$17,"")) -> 0 | F48: =COUNTIFS(N$8:N$17,$B48) -> 0
B49: H5 | C49: =COUNTIF($B$8:$C$17,B49) -> 2 | D49: =C49-(COUNTIFS(C$8:C$17,B49,N$8:N$17,"")) -> 0 | F49: =COUNTIFS(N$8:N$17,$B49) -> 0
B50: H6 | C50: =COUNTIF($B$8:$C$17,B50) -> 0 | D50: =C50-(COUNTIFS(C$8:C$17,B50,N$8:N$17,"")) -> 0 | F50: =COUNTIFS(N$8:N$17,$B50) -> 0
B51: H7 | C51: =COUNTIF($B$8:$C$17,B51) -> 0 | D51: =C51-(COUNTIFS(C$8:C$17,B51,N$8:N$17,"")) -> 0 | F51: =COUNTIFS(N$8:N$17,$B51) -> 0
B52: H8 | C52: =COUNTIF($B$8:$C$17,B52) -> 0 | D52: =C52-(COUNTIFS(C$8:C$17,B52,N$8:N$17,"")) -> 0 | F52: =COUNTIFS(N$8:N$17,$B52) -> 0
C53: =SUM(C45:C52) -> 8 | D53: =SUM(D45:D52) -> 0 | F53: =SUM(F45:F52) -> 0 | G53: =G18+#REF!+G34 -> #REF!
F54: =D53-F53 -> 0 | G54: =IF(F54=G53,"OK","ERREUR") -> #REF!

Sheet Feuille saisie
G1: ù
A2: TYPE | B2: H1
A3: DATE | B3: 45627
A4: CHAUFFEUR | B4: =VLOOKUP(B2,'Liste chauffeur'!$B$5:$L$19,2,TRUE)&" "&VLOOKUP(B2,'Liste chauffeur'!$B$5:$L$19,3,TRUE) -> CHADHOULI Houmadi
K6: ARRIVEE | O6: 8
A7: LIEU DE DEPART | B7: Heure théorique départ | C7: Horaire | D7: Chauffeur | E7: Direct/Non Direct | F7: Heure réelle départ | G7: Trajet non effectué | H7: Départ avec plus de 10 mns retard | I7: Nbre personnes montée | J7: Nbre personnes descente | K7: Heure arrivée finale | L7: Commentaires | M7: Temps Aller | N7: Nbre personnes moyenne | O7: Capacité max | P7: Taux Fréquentation
A8: =Horaire!A8 -> CHM | B8: =Horaire!E8 -> 0.23263889 | C8: =Horaire!H8 -> H1 | D8: =VLOOKUP(C8,'Liste chauffeur'!$B$5:$L$19,2,TRUE)&" "&VLOOKUP(C8,'Liste chauffeur'!$B$5:$L$19,3,TRUE) -> CHADHOULI Houmadi | E8: =Horaire!C8 -> 13 ARRETS | G8: =COUNTBLANK(F8) -> 1 | M8: =IF(G8=1,"",K8-F8) | N8: =J8 -> 0 | O8: =IF(G8=1,0,O$6) -> 0 | P8: =IF(O8=0,0,N8/O8) -> 0
A9: =Horaire!A9 -> LA BARGE | B9: =Horaire!E9 -> 0.23958333 | C9: =Horaire!H9 -> H5 | D9: =VLOOKUP(C9,'Liste chauffeur'!$B$5:$L$19,2,TRUE)&" "&VLOOKUP(C9,'Liste chauffeur'!$B$5:$L$19,3,TRUE) -> ATTOUMANI Kamaldine | E9: =Horaire!C9 -> 13 ARRETS | G9: =COUNTBLANK(F9) -> 1 | M9: =IF(G9=1,"",K9-F9) | N9: =J9 -> 0 | O9: =IF(G9=1,0,O$6) -> 0 | P9: =IF(O9=0,0,N9/O9) -> 0
A10: =Horaire!A10 -> CHM | B10: =Horaire!E10 -> 0.25 | C10: =Horaire!H10 -> H3 | D10: =VLOOKUP(C10,'Liste chauffeur'!$B$5:$L$19,2,TRUE)&" "&VLOOKUP(C10,'Liste chauffeur'!$B$5:$L$19,3,TRUE) -> SAID ALI Kamile | E10: =Horaire!C10 -> 13 ARRETS | G10: =COUNTBLANK(F10) -> 1 | M10: =IF(G10=1,"",K10-F10) | N10: =J10 -> 0 | O10: =IF(G10=1,0,O$6) -> 0 | P10: =IF(O10=0,0,N10/O10) -> 0
A11: =Horaire!A11 -> CHM | B11: =Horaire!E11 -> 0.27083333 | C11: =Horaire!H11 -> H1 | D11: =VLOOKUP(C11,'Liste chauffeur'!$B$5:$L$19,2,TRUE)&" "&VLOOKUP(C11,'Liste chauffeur'!$B$5:$L$19,3,TRUE) -> CHADHOULI Houmadi | E11: =Horaire!C11 -> 13 ARRETS | G11: =COUNTBLANK(F11) -> 1 | M11: =IF(G11=1,"",K11-F11) | N11: =J11 -> 0 | O11: =IF(G11=1,0,O$6) -> 0 | P11: =IF(O11=0,0,N11/O11) -> 0
A12: =Horaire!A12 -> LA BARGE | B12: =Horaire!E12 -> 0.27083333 | C12: =Horaire!H12 -> H3 | D12: =VLOOKUP(C12,'Liste chauffeur'!$B$5:$L$19,2,TRUE)&" "&VLOOKUP(C12,'Liste chauffeur'!$B$5:$L$19,3,TRUE) -> SAID ALI Kamile | E12: =Horaire!C12 -> DIRECT | G12: =COUNTBLANK(F12) -> 1 | M12: =IF(G12=1,"",K12-F12) | N12: =J12 -> 0 | O12: =IF(G12=1,0,O$6) -> 0 | P12: =IF(O12=0,0,N12/O12) -> 0
A13: =Horaire!A13 -> LA BARGE | B13: =Horaire!E13 -> 0.27083333 | C13: =Horaire!H13 -> H5 | D13: =VLOOKUP(C13,'Liste chauffeur'!$B$5:$L$19,2,TRUE)&" "&VLOOKUP(C13,'Liste chauffeur'!$B$5:$L$19,3,TRUE) -> ATTOUMANI Kamaldine | E13: =Horaire!C13 -> DIRECT+CRA | G13: =COUNTBLANK(F13) -> 1 | M13: =IF(G13=1,"",K13-F13) | N13: =J13 -> 0 | O13: =IF(G13=1,0,O$6) -> 0 | P13: =IF(O13=0,0,N13/O13) -> 0
A14: =Horaire!A14 -> CHM | B14: =Horaire!E14 -> 0.28819444 | C14: =Horaire!H14 -> H1 | D14: =VLOOKUP(C14,'Liste chauffeur'!$B$5:$L$19,2,TRUE)&" "&VLOOKUP(C14,'Liste chauffeur'!$B$5:$L$19,3,TRUE) -> CHADHOULI Houmadi | E14: =Horaire!C14 -> DIRECT | G14: =COUNTBLANK(F14) -> 1 | M14: =IF(G14=1,"",K14-F14) | N14: =J14 -> 0 | O14: =IF(G14=1,0,O$6) -> 0 | P14: =IF(O14=0,0,N14/O14) -> 0
A15: =Horaire!A15 -> CHM | B15: =Horaire!E15 -> 0.28472222 | C15: =Horaire!H15 -> H5 | D15: =VLOOKUP(C15,'Liste chauffeur'!$B$5:$L$19,2,TRUE)&" "&VLOOKUP(C15,'Liste chauffeur'!$B$5:$L$19,3,TRUE) -> ATTOUMANI Kamaldine | E15: =Horaire!C15 -> DIRECT | G15: =COUNTBLANK(F15) -> 1 | M15: =IF(G15=1,"",K15-F15) | N15: =J15 -> 0 | O15: =IF(G15=1,0,O$6) -> 0 | P15: =IF(O15=0,0,N15/O15) -> 0
A16: =Horaire!A16 -> LA BARGE | B16: =Horaire!E16 -> 0.29513889 | C16: =Horaire!H16 -> H3 | D16: =VLOOKUP(C16,'Liste chauffeur'!$B$5:$L$19,2,TRUE)&" "&VLOOKUP(C16,'Liste chauffeur'!$B$5:$L$19,3,TRUE) -> SAID ALI Kamile | E16: =Horaire!C16 -> DIRECT+CRA | G16: =COUNTBLANK(F16) -> 1 | M16: =IF(G16=1,"",K16-F16) | N16: =J16 -> 0 | O16: =IF(G16=1,0,O$6) -> 0 | P16: =IF(O16=0,0,N16/O16) -> 0
A17: =Horaire!A17 -> LA BARGE | B17: =Horaire!E17 -> 0.3125 | C17: =Horaire!H17 -> H5 | D17: =VLOOKUP(C17,'Liste chauffeur'!$B$5:$L$19,2,TRUE)&" "&VLOOKUP(C17,'Liste chauffeur'!$B$5:$L$19,3,TRUE) -> ATTOUMANI Kamaldine | E17: =Horaire!C17 -> DIRECT | G17: =COUNTBLANK(F17) -> 1 | M17: =IF(G17=1,"",K17-F17) | N17: =J17 -> 0 | O17: =IF(G17=1,0,O$6) -> 0 | P17: =IF(O17=0,0,N17/O17) -> 0
A18: =Horaire!A18 -> CHM | B18: =Horaire!E18 -> 0.32638889 | C18: =Horaire!H18 -> H5 | D18: =VLOOKUP(C18,'Liste chauffeur'!$B$5:$L$19,2,TRUE)&" "&VLOOKUP(C18,'Liste chauffeur'!$B$5:$L$19,3,TRUE) -> ATTOUMANI Kamaldine | E18: =Horaire!C18 -> DIRECT | G18: =COUNTBLANK(F18) -> 1 | N18: =J18 -> 0 | O18: =IF(G18=1,0,O$6) -> 0 | P18: =IF(O18=0,0,N18/O18) -> 0
A19: =Horaire!A19 -> LA BARGE | B19: =Horaire!E19 -> 0.32638889 | C19: =Horaire!H19 -> H1 | D19: =VLOOKUP(C19,'Liste chauffeur'!$B$5:$L$19,2,TRUE)&" "&VLOOKUP(C19,'Liste chauffeur'!$B$5:$L$19,3,TRUE) -> CHADHOULI Houmadi | E19: =Horaire!C19 -> DIRECT | G19: =COUNTBLANK(F19) -> 1 | N19: =J19 -> 0 | O19: =IF(G19=1,0,O$6) -> 0 | P19: =IF(O19=0,0,N19/O19) -> 0
B20: NON PLANIFIE | G20: =COUNTBLANK(F20) -> 1 | N20: =J20 -> 0 | O20: =IF(G20=1,0,O$6) -> 0 | P20: =IF(O20=0,0,N20/O20) -> 0
B21: NON PLANIFIE | G21: =COUNTBLANK(F21) -> 1 | N21: =J21 -> 0 | O21: =IF(G21=1,0,O$6) -> 0 | P21: =IF(O21=0,0,N21/O21) -> 0
B22: NON PLANIFIE | G22: =COUNTBLANK(F22) -> 1 | N22: =J22 -> 0 | O22: =IF(G22=1,0,O$6) -> 0 | P22: =IF(O22=0,0,N22/O22) -> 0
B23: ST1 | G23: =SUM(G8:G19) -> 12 | H23: =SUM(H8:H18) -> 0 | M23: =AVERAGE(M8:M18) -> #DIV/0! | N23: =SUM(N8:N22) -> 0 | O23: =SUM(O8:O22) -> 0 | P23: =N23/O23 -> #DIV/0!
A24: =Horaire!A20 -> LA BARGE | B24: =Horaire!E20 -> 0.58333333 | C24: =Horaire!H20 -> H1 | D24: =VLOOKUP(C24,'Liste chauffeur'!$B$5:$L$19,2,TRUE)&" "&VLOOKUP(C24,'Liste chauffeur'!$B$5:$L$19,3,TRUE) -> CHADHOULI Houmadi | E24: =Horaire!C20 -> 13 ARRETS | G24: =COUNTBLANK(F24) -> 1 | M24: =IF(G24=1,"",K24-F24) | N24: =J24 -> 0 | O24: =IF(G24=1,0,O$6) -> 0 | P24: =IF(O24=0,0,N24/O24) -> 0
A25: =Horaire!A21 -> CHM | B25: =Horaire!E21 -> 0.58333333 | C25: =Horaire!H21 -> H3 | D25: =VLOOKUP(C25,'Liste chauffeur'!$B$5:$L$19,2,TRUE)&" "&VLOOKUP(C25,'Liste chauffeur'!$B$5:$L$19,3,TRUE) -> SAID ALI Kamile | E25: =Horaire!C21 -> DIRECT | G25: =COUNTBLANK(F25) -> 1 | M25: =IF(G25=1,"",K25-F25) | N25: =J25 -> 0 | O25: =IF(G25=1,0,O$6) -> 0 | P25: =IF(O25=0,0,N25/O25) -> 0
A26: =Horaire!A22 -> LA BARGE | B26: =Horaire!E22 -> 0.61458333 | C26: =Horaire!H22 -> H1 | D26: =VLOOKUP(C26,'Liste chauffeur'!$B$5:$L$19,2,TRUE)&" "&VLOOKUP(C26,'Liste chauffeur'!$B$5:$L$19,3,TRUE) -> CHADHOULI Houmadi | E26: =Horaire!C22 -> 13 ARRETS | G26: =COUNTBLANK(F26) -> 1 | M26: =IF(G26=1,"",K26-F26) | N26: =J26 -> 0 | O26: =IF(G26=1,0,O$6) -> 0 | P26: =IF(O26=0,0,N26/O26) -> 0
A27: =Horaire!A23 -> LA BARGE | B27: =Horaire!E23 -> 0.61805556 | C27: =Horaire!H23 -> H3 | D27: =VLOOKUP(C27,'Liste chauffeur'!$B$5:$L$19,2,TRUE)&" "&VLOOKUP(C27,'Liste chauffeur'!$B$5:$L$19,3,TRUE) -> SAID ALI Kamile | E27: =Horaire!C23 -> 13 ARRETS | G27: =COUNTBLANK(F27) -> 1 | M27: =IF(G27=1,"",K27-F27) | N27: =J27 -> 0 | O27: =IF(G27=1,0,O$6) -> 0 | P27: =IF(O27=0,0,N27/O27) -> 0
A28: =Horaire!A24 -> CHM | B28: =Horaire!E24 -> 0.625 | C28: =Horaire!H24 -> H5 | D28: =VLOOKUP(C28,'Liste chauffeur'!$B$5:$L$19,2,TRUE)&" "&VLOOKUP(C28,'Liste chauffeur'!$B$5:$L$19,3,TRUE) -> ATTOUMANI Kamaldine | E28: =Horaire!C24 -> DIRECT | G28: =COUNTBLANK(F28) -> 1 | M28: =IF(G28=1,"",K28-F28) | N28: =J28 -> 0 | O28: =IF(G28=1,0,O$6) -> 0 | P28: =IF(O28=0,0,N28/O28) -> 0
A29: =Horaire!A25 -> LA BARGE | B29: =Horaire!E25 -> 0.63888889 | C29: =Horaire!H25 -> H1 | D29: =VLOOKUP(C29,'Liste chauffeur'!$B$5:$L$19,2,TRUE)&" "&VLOOKUP(C29,'Liste chauffeur'!$B$5:$L$19,3,TRUE) -> CHADHOULI Houmadi | E29: =Horaire!C25 -> 13 ARRETS | G29: =COUNTBLANK(F29) -> 1 | M29: =IF(G29=1,"",K29-F29) | N29: =J29 -> 0 | O29: =IF(G29=1,0,O$6) -> 0 | P29: =IF(O29=0,0,N29/O29) -> 0
A30: =Horaire!A26 -> LA BARGE | B30: =Horaire!E26 -> 0.65972222 | C30: =Horaire!H26 -> H5 | D30: =VLOOKUP(C30,'Liste chauffeur'!$B$5:$L$19,2,TRUE)&" "&VLOOKUP(C30,'Liste chauffeur'!$B$5:$L$19,3,TRUE) -> ATTOUMANI Kamaldine | E30: =Horaire!C26 -> 13 ARRETS | G30: =COUNTBLANK(F30) -> 1 | N30: =J30 -> 0 | O30: =IF(G30=1,0,O$6) -> 0 | P30: =IF(O30=0,0,N30/O30) -> 0
A31: =Horaire!A27 -> LA BARGE | B31: =Horaire!E27 -> 0.6875 | C31: =Horaire!H27 -> H5 | D31: =VLOOKUP(C31,'Liste chauffeur'!$B$5:$L$19,2,TRUE)&" "&VLOOKUP(C31,'Liste chauffeur'!$B$5:$L$19,3,TRUE) -> ATTOUMANI Kamaldine | E31: =Horaire!C27 -> 13 ARRETS | G31: =COUNTBLANK(F31) -> 1 | N31: =J31 -> 0 | O31: =IF(G31=1,0,O$6) -> 0 | P31: =IF(O31=0,0,N31/O31) -> 0
A32: =Horaire!A28 -> LA BARGE | B32: =Horaire!E28 -> 0.71180556 | C32: =Horaire!H28 -> H5 | D32: =VLOOKUP(C32,'Liste chauffeur'!$B$5:$L$19,2,TRUE)&" "&VLOOKUP(C32,'Liste chauffeur'!$B$5:$L$19,3,TRUE) -> ATTOUMANI Kamaldine | E32: =Horaire!C28 -> 13 ARRETS | G32: =COUNTBLANK(F32) -> 1 | N32: =J32 -> 0 | O32: =IF(G32=1,0,O$6) -> 0 | P32: =IF(O32=0,0,N32/O32) -> 0
A33: =Horaire!A29 -> LA BARGE | B33: =Horaire!E29 -> 0.76041667 | C33: =Horaire!H29 -> H3 | D33: =VLOOKUP(C33,'Liste chauffeur'!$B$5:$L$19,2,TRUE)&" "&VLOOKUP(C33,'Liste chauffeur'!$B$5:$L$19,3,TRUE) -> SAID ALI Kamile | E33: =Horaire!C29 -> DIRECT | G33: =COUNTBLANK(F33) -> 1 | N33: =J33 -> 0 | O33: =IF(G33=1,0,O$6) -> 0 | P33: =IF(O33=0,0,N33/O33) -> 0
A34: =Horaire!A30 -> CHM | B34: =Horaire!E30 -> 0.76041667 | C34: =Horaire!H30 -> H1 | D34: =VLOOKUP(C34,'Liste chauffeur'!$B$5:$L$19,2,TRUE)&" "&VLOOKUP(C34,'Liste chauffeur'!$B$5:$L$19,3,TRUE) -> CHADHOULI Houmadi | E34: =Horaire!C30 -> DIRECT | G34: =COUNTBLANK(F34) -> 1 | N34: =J34 -> 0 | O34: =IF(G34=1,0,O$6) -> 0 | P34: =IF(O34=0,0,N34/O34) -> 0
A35: =Horaire!A31 -> LA BARGE | B35: =Horaire!E31 -> 0.78125 | C35: =Horaire!H31 -> H1 | D35: =VLOOKUP(C35,'Liste chauffeur'!$B$5:$L$19,2,TRUE)&" "&VLOOKUP(C35,'Liste chauffeur'!$B$5:$L$19,3,TRUE) -> CHADHOULI Houmadi | E35: =Horaire!C31 -> 13 ARRETS | G35: =COUNTBLANK(F35) -> 1 | N35: =J35 -> 0 | O35: =IF(G35=1,0,O$6) -> 0 | P35: =IF(O35=0,0,N35/O35) -> 0
A36: =Horaire!A32 -> CHM | B36: =Horaire!E32 -> 0.78125 | C36: =Horaire!H32 -> H3 | D36: =VLOOKUP(C36,'Liste chauffeur'!$B$5:$L$19,2,TRUE)&" "&VLOOKUP(C36,'Liste chauffeur'!$B$5:$L$19,3,TRUE) -> SAID ALI Kamile | E36: =Horaire!C32 -> DIRECT | G36: =COUNTBLANK(F36) -> 1 | N36: =J36 -> 0 | O36: =IF(G36=1,0,O$6) -> 0 | P36: =IF(O36=0,0,N36/O36) -> 0
A37: =Horaire!A33 -> LA BARGE | B37: =Horaire!E33 -> 0.80208333 | C37: =Horaire!H33 -> H3 | D37: =VLOOKUP(C37,'Liste chauffeur'!$B$5:$L$19,2,TRUE)&" "&VLOOKUP(C37,'Liste chauffeur'!$B$5:$L$19,3,TRUE) -> SAID ALI Kamile | E37: =Horaire!C33 -> 13 ARRETS | G37: =COUNTBLANK(F37) -> 1 | N37: =J37 -> 0 | O37: =IF(G37=1,0,O$6) -> 0 | P37: =IF(O37=0,0,N37/O37) -> 0
A38: =Horaire!A34 -> CRA+CHM | B38: =Horaire!E34 -> 0.80902778 | C38: =Horaire!H34 -> H1 | D38: =VLOOKUP(C38,'Liste chauffeur'!$B$5:$L$19,2,TRUE)&" "&VLOOKUP(C38,'Liste chauffeur'!$B$5:$L$19,3,TRUE) -> CHADHOULI Houmadi | E38: =Horaire!C34 -> DIRECT+CRA | G38: =COUNTBLANK(F38) -> 1 | N38: =J38 -> 0 | O38: =IF(G38=1,0,O$6) -> 0 | P38: =IF(O38=0,0,N38/O38) -> 0
A39: =Horaire!A35 -> LA BARGE | B39: =Horaire!E35 -> 0.82291667 | C39: =Horaire!H35 -> H3 | D39: =VLOOKUP(C39,'Liste chauffeur'!$B$5:$L$19,2,TRUE)&" "&VLOOKUP(C39,'Liste chauffeur'!$B$5:$L$19,3,TRUE) -> SAID ALI Kamile | E39: =Horaire!C35 -> 13 ARRETS | G39: =COUNTBLANK(F39) -> 1 | N39: =J39 -> 0 | O39: =IF(G39=1,0,O$6) -> 0 | P39: =IF(O39=0,0,N39/O39) -> 0
B40: NON PLANIFIE
B41: NON PLANIFIE
B42: NON PLANIFIE
B43: ST2 | C43: ST | G43: =SUM(G24:G29) -> 6 | M43: =AVERAGE(M24:M29) -> #DIV/0! | N43: =SUM(N24:N29) -> 0 | O43: =SUM(O24:O29) -> 0 | P43: =IF(O43=0,0,N43/O43) -> 0
A44: REMPLACEMENT | C44: H | M44: =AVERAGE(M8:M18,M24:M29) -> #DIV/0! | N44: =N23+N43 -> 0 | O44: =O23+O43 -> 0 | P44: =IF(O44=0,0,N44/O44) -> 0
A45: REMPLACEMENT | C45: H
A46: REMPLACEMENT | C46: H
A47: REMPLACEMENT | C47: H
A48: REMPLACEMENT | C48: H
C50: S | F50: Signature Chauffeur
B53: Statistiques | C53: nbre de trajets planifiés | D53: Nbre trajets non effectués | F53: Nbre trajets effectués non planifiés
B54: H1 | C54: =COUNTIF($B$8:$C$19,B54)+COUNTIF($B$24:$C$39,B54) -> 10 | D54: =C54-(COUNTIFS(C$8:C$19,B54,L$8:L$19,"")+COUNTIFS(C$24:C$39,B54,L$24:L$39,"")) -> 0 | F54: =COUNTIFS(L$8:L$22,$B54)+COUNTIFS(L$24:L$42,$B54) -> 0
B55: H2 | C55: =COUNTIF($B$8:$C$19,B55)+COUNTIF($B$24:$C$39,B55) -> 0 | D55: =C55-(COUNTIFS(C$8:C$19,B55,L$8:L$19,"")+COUNTIFS(C$24:C$39,B55,L$24:L$39,"")) -> 0 | F55: =COUNTIFS(L$8:L$22,$B55)+COUNTIFS(L$24:L$42,$B55) -> 0
B56: H3 | C56: =COUNTIF($B$8:$C$19,B56)+COUNTIF($B$24:$C$39,B56) -> 9 | D56: =C56-(COUNTIFS(C$8:C$19,B56,L$8:L$19,"")+COUNTIFS(C$24:C$39,B56,L$24:L$39,"")) -> 0 | F56: =COUNTIFS(L$8:L$22,$B56)+COUNTIFS(L$24:L$42,$B56) -> 0
B57: H4 | C57: =COUNTIF($B$8:$C$19,B57)+COUNTIF($B$24:$C$39,B57) -> 0 | D57: =C57-(COUNTIFS(C$8:C$19,B57,L$8:L$19,"")+COUNTIFS(C$24:C$39,B57,L$24:L$39,"")) -> 0 | F57: =COUNTIFS(L$8:L$22,$B57)+COUNTIFS(L$24:L$42,$B57) -> 0
B58: H5 | C58: =COUNTIF($B$8:$C$19,B58)+COUNTIF($B$24:$C$39,B58) -> 9 | D58: =C58-(COUNTIFS(C$8:C$19,B58,L$8:L$19,"")+COUNTIFS(C$24:C$39,B58,L$24:L$39,"")) -> 0 | F58: =COUNTIFS(L$8:L$22,$B58)+COUNTIFS(L$24:L$42,$B58) -> 0
B59: H6 | C59: =COUNTIF($B$8:$C$19,B59)+COUNTIF($B$24:$C$39,B59) -> 0 | D59: =C59-(COUNTIFS(C$8:C$19,B59,L$8:L$19,"")+COUNTIFS(C$24:C$39,B59,L$24:L$39,"")) -> 0 | F59: =COUNTIFS(L$8:L$22,$B59)+COUNTIFS(L$24:L$42,$B59) -> 0
B60: H7 | C60: =COUNTIF($B$8:$C$19,B60)+COUNTIF($B$24:$C$39,B60) -> 0 | D60: =C60-(COUNTIFS(C$8:C$19,B60,L$8:L$19,"")+COUNTIFS(C$24:C$39,B60,L$24:L$39,"")) -> 0 | F60: =COUNTIFS(L$8:L$22,$B60)+COUNTIFS(L$24:L$42,$B60) -> 0
B61: H8 | C61: =COUNTIF($B$8:$C$19,B61)+COUNTIF($B$24:$C$39,B61) -> 0 | D61: =C61-(COUNTIFS(C$8:C$19,B61,L$8:L$19,"")+COUNTIFS(C$24:C$39,B61,L$24:L$39,"")) -> 0 | F61: =COUNTIFS(L$8:L$22,$B61)+COUNTIFS(L$24:L$42,$B61) -> 0
C62: =SUM(C54:C61) -> 28 | D62: =SUM(D54:D61) -> 0 | F62: =SUM(F54:F61) -> 0 | G62: =G23+#REF!+G43 -> #REF!
F63: =D62-F62 -> 0 | G63: =IF(F63=G62,"OK","ERREUR") -> #REF!

Sheet H1
G1: ù
A2: TYPE | B2: H1
A3: DATE | B3: 45627
A4: CHAUFFEUR | B4: =VLOOKUP(B2,'Liste chauffeur'!$B$5:$L$19,2,TRUE)&" "&VLOOKUP(B2,'Liste chauffeur'!$B$5:$L$19,3,TRUE) -> CHADHOULI Houmadi | L4: 46143
K6: ARRIVEE | O6: 8
A7: LIEU DE DEPART | B7: Heure théorique départ | C7: Horaire | D7: Chauffeur | E7: Direct/Non Direct | F7: Heure réelle départ | G7: Trajet non effectué | H7: Départ avec plus de 10 mns retard | I7: Nbre personnes montée | J7: Nbre personnes descente | K7: Heure arrivée finale | L7: Commentaires | M7: Temps Aller | N7: Nbre personnes moyenne | O7: Capacité max | P7: Taux Fréquentation
A8: CHM | B8: 0.23263889 | C8: H1 | D8: CHADHOULI Houmadi | E8: 13 ARRETS | G8: 1 | M8: =IF(G8=1,"",K8-F8) | N8: =J8 -> 0 | O8: =IF(G8=1,0,O$6) -> 0 | P8: =IF(O8=0,0,N8/O8) -> 0
A9: CHM | B9: 0.27083333 | C9: H1 | D9: CHADHOULI Houmadi | E9: 13 ARRETS | G9: 1 | M9: =IF(G9=1,"",K9-F9) | N9: =J9 -> 0 | O9: =IF(G9=1,0,O$6) -> 0 | P9: =IF(O9=0,0,N9/O9) -> 0
A10: CHM | B10: 0.28819444 | C10: H1 | D10: CHADHOULI Houmadi | E10: DIRECT | G10: 1 | M10: =IF(G10=1,"",K10-F10) | N10: =J10 -> 0 | O10: =IF(G10=1,0,O$6) -> 0 | P10: =IF(O10=0,0,N10/O10) -> 0
A11: LA BARGE | B11: 0.58333333 | C11: H1 | D11: CHADHOULI Houmadi | E11: 13 ARRETS | G11: 1 | M11: =IF(G11=1,"",K11-F11) | N11: =J11 -> 0 | O11: =IF(G11=1,0,O$6) -> 0 | P11: =IF(O11=0,0,N11/O11) -> 0
A12: LA BARGE | B12: 0.61458333 | C12: H1 | D12: CHADHOULI Houmadi | E12: 13 ARRETS | G12: 1 | M12: =IF(G12=1,"",K12-F12) | N12: =J12 -> 0 | O12: =IF(G12=1,0,O$6) -> 0 | P12: =IF(O12=0,0,N12/O12) -> 0
A13: LA BARGE | B13: 0.63888889 | C13: H1 | D13: CHADHOULI Houmadi | E13: 13 ARRETS | G13: 1 | M13: =IF(G13=1,"",K13-F13) | N13: =J13 -> 0 | O13: =IF(G13=1,0,O$6) -> 0 | P13: =IF(O13=0,0,N13/O13) -> 0
A14: REMPLACEMENT | C14: H | M14: =IF(G14=1,"",K14-F14) -> 0 | N14: =J14 -> 0 | O14: =IF(G14=1,0,O$6) -> 8 | P14: =IF(O14=0,0,N14/O14) -> 0
A15: REMPLACEMENT | C15: H | M15: =IF(G15=1,"",K15-F15) -> 0 | N15: =J15 -> 0 | O15: =IF(G15=1,0,O$6) -> 8 | P15: =IF(O15=0,0,N15/O15) -> 0
A16: REMPLACEMENT | C16: H | M16: =IF(G16=1,"",K16-F16) -> 0 | N16: =J16 -> 0 | O16: =IF(G16=1,0,O$6) -> 8 | P16: =IF(O16=0,0,N16/O16) -> 0
A17: REMPLACEMENT | C17: H | N17: =J17 -> 0 | O17: =IF(G17=1,0,O$6) -> 8 | P17: =IF(O17=0,0,N17/O17) -> 0
A18: REMPLACEMENT | C18: H | N18: =J18 -> 0 | O18: =IF(G18=1,0,O$6) -> 8
C19: S | F19: Signature Chauffeur
A21: TYPE | B21: H1
A22: CHAUFFEUR | B22: CHADHOULI Houmadi | L22: =L4+1 -> 46144
K24: ARRIVEE
A25: LIEU DE DEPART | B25: Heure théorique départ | C25: Horaire | D25: Chauffeur | E25: Direct/Non Direct | F25: Heure réelle départ | G25: Trajet non effectué | H25: Départ avec plus de 10 mns retard | I25: Nbre personnes montée | J25: Nbre personnes descente | K25: Heure arrivée finale | L25: Commentaires
A26: CHM | B26: 0.23263889 | C26: H1 | D26: CHADHOULI Houmadi | E26: 13 ARRETS | G26: 1
A27: CHM | B27: 0.27083333 | C27: H1 | D27: CHADHOULI Houmadi | E27: 13 ARRETS | G27: 1
A28: CHM | B28: 0.28819444 | C28: H1 | D28: CHADHOULI Houmadi | E28: DIRECT | G28: 1
A29: LA BARGE | B29: 0.32638889 | C29: H1 | D29: CHADHOULI Houmadi | E29: DIRECT | G29: 1
A30: LA BARGE | B30: 0.58333333 | C30: H1 | D30: CHADHOULI Houmadi | E30: 13 ARRETS | G30: 1
A31: LA BARGE | B31: 0.61458333 | C31: H1 | D31: CHADHOULI Houmadi | E31: 13 ARRETS | G31: 1
A32: LA BARGE | B32: 0.63888889 | C32: H1 | D32: CHADHOULI Houmadi | E32: 13 ARRETS | G32: 1
A33: CHM | B33: 0.76041667 | C33: H1 | D33: CHADHOULI Houmadi | E33: DIRECT | G33: 1
A34: LA BARGE | B34: 0.78125 | C34: H1 | D34: CHADHOULI Houmadi | E34: 13 ARRETS | G34: 1
A35: CRA+CHM | B35: 0.80902778 | C35: H1 | D35: CHADHOULI Houmadi | E35: DIRECT+CRA | G35: 1
A36: REMPLACEMENT | C36: H
A37: REMPLACEMENT | C37: H
A38: REMPLACEMENT | C38: H
A39: REMPLACEMENT | C39: H
C41: S | F41: Signature Chauffeur
A42: TYPE | B42: H1
A43: CHAUFFEUR | B43: CHADHOULI Houmadi | L43: =L22+1 -> 46145
K45: ARRIVEE
A46: LIEU DE DEPART | B46: Heure théorique départ | C46: Horaire | D46: Chauffeur | E46: Direct/Non Direct | F46: Heure réelle départ | G46: Trajet non effectué | H46: Départ avec plus de 10 mns retard | I46: Nbre personnes montée | J46: Nbre personnes descente | K46: Heure arrivée finale | L46: Commentaires
A47: CHM | B47: 0.23263889 | C47: H1 | D47: CHADHOULI Houmadi | E47: 13 ARRETS | G47: 1
A48: CHM | B48: 0.27083333 | C48: H1 | D48: CHADHOULI Houmadi | E48: 13 ARRETS | G48: 1
A49: CHM | B49: 0.28819444 | C49: H1 | D49: CHADHOULI Houmadi | E49: DIRECT | G49: 1
A50: LA BARGE | B50: 0.58333333 | C50: H1 | D50: CHADHOULI Houmadi | E50: 13 ARRETS | G50: 1
A51: LA BARGE | B51: 0.61458333 | C51: H1 | D51: CHADHOULI Houmadi | E51: 13 ARRETS | G51: 1
A52: LA BARGE | B52: 0.63888889 | C52: H1 | D52: CHADHOULI Houmadi | E52: 13 ARRETS | G52: 1
A53: REMPLACEMENT | C53: H
A54: REMPLACEMENT | C54: H
A55: REMPLACEMENT | C55: H
A56: REMPLACEMENT | C56: H
A57: REMPLACEMENT | C57: H
C58: S | F58: Signature Chauffeur
A60: TYPE | B60: H1
A61: CHAUFFEUR | B61: CHADHOULI Houmadi | L61: =L43+1 -> 46146
K63: ARRIVEE
A64: LIEU DE DEPART | B64: Heure théorique départ | C64: Horaire | D64: Chauffeur | E64: Direct/Non Direct | F64: Heure réelle départ | G64: Trajet non effectué | H64: Départ avec plus de 10 mns retard | I64: Nbre personnes montée | J64: Nbre personnes descente | K64: Heure arrivée finale | L64: Commentaires
A65: CHM | B65: 0.23263889 | C65: H1 | D65: CHADHOULI Houmadi | E65: 13 ARRETS | G65: 1
A66: CHM | B66: 0.27083333 | C66: H1 | D66: CHADHOULI Houmadi | E66: 13 ARRETS | G66: 1
A67: CHM | B67: 0.28819444 | C67: H1 | D67: CHADHOULI Houmadi | E67: DIRECT | G67: 1
A68: LA BARGE | B68: 0.32638889 | C68: H1 | D68: CHADHOULI Houmadi | E68: DIRECT | G68: 1
A69: LA BARGE | B69: 0.58333333 | C69: H1 | D69: CHADHOULI Houmadi | E69: 13 ARRETS | G69: 1
A70: LA BARGE | B70: 0.61458333 | C70: H1 | D70: CHADHOULI Houmadi | E70: 13 ARRETS | G70: 1
A71: LA BARGE | B71: 0.63888889 | C71: H1 | D71: CHADHOULI Houmadi | E71: 13 ARRETS | G71: 1
A72: CHM | B72: 0.76041667 | C72: H1 | D72: CHADHOULI Houmadi | E72: DIRECT | G72: 1
A73: LA BARGE | B73: 0.78125 | C73: H1 | D73: CHADHOULI Houmadi | E73: 13 ARRETS | G73: 1
A74: CRA+CHM | B74: 0.80902778 | C74: H1 | D74: CHADHOULI Houmadi | E74: DIRECT+CRA | G74: 1
A75: REMPLACEMENT | C75: H
A76: REMPLACEMENT | C76: H
A77: REMPLACEMENT | C77: H
A78: REMPLACEMENT | C78: H
C80: S | F80: Signature Chauffeur
A81: TYPE | B81: H1 | L81: =L61+1 -> 46147
A82: CHAUFFEUR | B82: CHADHOULI Houmadi
K84: ARRIVEE | M84: ARRIVEE
A85: LIEU DE DEPART | B85: Heure théorique départ | C85: Horaire | D85: Chauffeur | E85: Direct/Non Direct | F85: Heure réelle départ | G85: Trajet non effectué | H85: Départ avec plus de 10 mns retard | I85: Nbre personnes montée | J85: Nbre personnes descente | K85: Heure arrivée finale | L85: Commentaires | M85: Heure arrivée finale | N85: Commentaires
A86: CHM | B86: 0.23263889 | C86: H1 | D86: CHADHOULI Houmadi | E86: 13 ARRETS | G86: 1
A87: CHM | B87: 0.27083333 | C87: H1 | D87: CHADHOULI Houmadi | E87: 13 ARRETS | G87: 1
A88: CHM | B88: 0.28819444 | C88: H1 | D88: CHADHOULI Houmadi | E88: DIRECT | G88: 1
A89: LA BARGE | B89: 0.32638889 | C89: H1 | D89: CHADHOULI Houmadi | E89: DIRECT | G89: 1
A90: LA BARGE | B90: 0.58333333 | C90: H1 | D90: CHADHOULI Houmadi | E90: 13 ARRETS | G90: 1
A91: LA BARGE | B91: 0.61458333 | C91: H1 | D91: CHADHOULI Houmadi | E91: 13 ARRETS | G91: 1
A92: LA BARGE | B92: 0.63888889 | C92: H1 | D92: CHADHOULI Houmadi | E92: 13 ARRETS | G92: 1
A93: CHM | B93: 0.76041667 | C93: H1 | D93: CHADHOULI Houmadi | E93: DIRECT | G93: 1
A94: LA BARGE | B94: 0.78125 | C94: H1 | D94: CHADHOULI Houmadi | E94: 13 ARRETS | G94: 1
A95: CRA+CHM | B95: 0.80902778 | C95: H1 | D95: CHADHOULI Houmadi | E95: DIRECT+CRA | G95: 1
A96: REMPLACEMENT | C96: H
A97: REMPLACEMENT | C97: H
A98: REMPLACEMENT | C98: H
A99: REMPLACEMENT | C99: H
C101: S | F101: Signature Chauffeur
A102: CHAUFFEUR | B102: CHADHOULI Houmadi | L102: =L81+1 -> 46148
K104: ARRIVEE
A105: LIEU DE DEPART | B105: Heure théorique départ | C105: Horaire | D105: Chauffeur | E105: Direct/Non Direct | F105: Heure réelle départ | G105: Trajet non effectué | H105: Départ avec plus de 10 mns retard | I105: Nbre personnes montée | J105: Nbre personnes descente | K105: Heure arrivée finale | L105: Commentaires
A106: CHM | B106: 0.23263889 | C106: H1 | D106: CHADHOULI Houmadi | E106: 13 ARRETS | G106: 1
A107: CHM | B107: 0.27083333 | C107: H1 | D107: CHADHOULI Houmadi | E107: 13 ARRETS | G107: 1
A108: CHM | B108: 0.28819444 | C108: H1 | D108: CHADHOULI Houmadi | E108: DIRECT | G108: 1
A109: LA BARGE | B109: 0.32638889 | C109: H1 | D109: CHADHOULI Houmadi | E109: DIRECT | G109: 1
A110: LA BARGE | B110: 0.58333333 | C110: H1 | D110: CHADHOULI Houmadi | E110: 13 ARRETS | G110: 1
A111: LA BARGE | B111: 0.61458333 | C111: H1 | D111: CHADHOULI Houmadi | E111: 13 ARRETS | G111: 1
...

Sheet H3B
G1: ù
A2: TYPE | B2: H3
A3: DATE | B3: =#REF! -> #REF!
A4: CHAUFFEUR | B4: =VLOOKUP(B2,'Liste chauffeur'!$B$5:$L$19,2,TRUE)&" "&VLOOKUP(B2,'Liste chauffeur'!$B$5:$L$19,3,TRUE) -> SAID ALI Kamile | L4: 46143
K6: ARRIVEE | O6: 8
A7: LIEU DE DEPART | B7: Heure théorique départ | C7: Horaire | D7: Chauffeur | E7: Direct/Non Direct | F7: Heure réelle départ | G7: Trajet non effectué | H7: Départ avec plus de 10 mns retard | I7: Nbre personnes montée | J7: Nbre personnes descente | K7: Heure arrivée finale | L7: Commentaires | M7: Temps Aller | N7: Nbre personnes moyenne | O7: Capacité max | P7: Taux Fréquentation
A8: CHM | B8: 0.25 | C8: H3 | D8: SAID ALI Kamile | E8: 13 ARRETS | G8: 1 | M8: =IF(G8=1,"",K8-F8) | N8: =J8 -> 0 | O8: =IF(G8=1,0,O$6) -> 0 | P8: =IF(O8=0,0,N8/O8) -> 0
A9: LA BARGE | B9: 0.27083333 | C9: H3 | D9: SAID ALI Kamile | E9: DIRECT | G9: 1 | M9: =IF(G9=1,"",K9-F9) | N9: =J9 -> 0 | O9: =IF(G9=1,0,O$6) -> 0 | P9: =IF(O9=0,0,N9/O9) -> 0
A10: LA BARGE | B10: 0.29513889 | C10: H3 | D10: SAID ALI Kamile | E10: DIRECT | G10: 1 | M10: =IF(G10=1,"",K10-F10) | N10: =J10 -> 0 | O10: =IF(G10=1,0,O$6) -> 0 | P10: =IF(O10=0,0,N10/O10) -> 0
A11: CHM | B11: 0.58333333 | C11: H3 | D11: SAID ALI Kamile | E11: DIRECT | G11: 1 | M11: =IF(G11=1,"",K11-F11) | N11: =J11 -> 0 | O11: =IF(G11=1,0,O$6) -> 0 | P11: =IF(O11=0,0,N11/O11) -> 0
A12: CHM | B12: 0.625 | C12: H3 | D12: SAID ALI Kamile | E12: DIRECT | G12: 1 | M12: =IF(G12=1,"",K12-F12) | N12: =J12 -> 0 | O12: =IF(G12=1,0,O$6) -> 0 | P12: =IF(O12=0,0,N12/O12) -> 0
A13: CHM | B13: 0.76041667 | C13: H3 | D13: SAID ALI Kamile | E13: DIRECT | G13: 1 | M13: =IF(G13=1,"",K13-F13) | N13: =J13 -> 0 | O13: =IF(G13=1,0,O$6) -> 0 | P13: =IF(O13=0,0,N13/O13) -> 0
A14: LA BARGE | B14: 0.78125 | C14: H3 | D14: SAID ALI Kamile | E14: 13 ARRETS | G14: 1 | M14: =IF(G14=1,"",K14-F14) | N14: =J14 -> 0 | O14: =IF(G14=1,0,O$6) -> 0 | P14: =IF(O14=0,0,N14/O14) -> 0
A15: REMPLACEMENT | C15: H | M15: =IF(G15=1,"",K15-F15) -> 0 | N15: =J15 -> 0 | O15: =IF(G15=1,0,O$6) -> 8 | P15: =IF(O15=0,0,N15/O15) -> 0
A16: REMPLACEMENT | C16: H | M16: =IF(G16=1,"",K16-F16) -> 0 | N16: =J16 -> 0 | O16: =IF(G16=1,0,O$6) -> 8 | P16: =IF(O16=0,0,N16/O16) -> 0
A17: REMPLACEMENT | C17: H | N17: =J17 -> 0 | O17: =IF(G17=1,0,O$6) -> 8 | P17: =IF(O17=0,0,N17/O17) -> 0
A18: REMPLACEMENT | C18: H | N18: =J18 -> 0 | O18: =IF(G18=1,0,O$6) -> 8
C19: S | F19: Signature Chauffeur
A20: TYPE | B20: H3
A21: CHAUFFEUR | B21: SAID ALI Kamile | L21: =L4+1 -> 46144
K23: ARRIVEE
A24: LIEU DE DEPART | B24: Heure théorique départ | C24: Horaire | D24: Chauffeur | E24: Direct/Non Direct | F24: Heure réelle départ | G24: Trajet non effectué | H24: Départ avec plus de 10 mns retard | I24: Nbre personnes montée | J24: Nbre personnes descente | K24: Heure arrivée finale | L24: Commentaires
A25: CHM | B25: 0.25 | C25: H3 | D25: SAID ALI Kamile | E25: 13 ARRETS | G25: 1
A26: LA BARGE | B26: 0.27083333 | C26: H3 | D26: SAID ALI Kamile | E26: DIRECT | G26: 1
A27: LA BARGE | B27: 0.29513889 | C27: H3 | D27: SAID ALI Kamile | E27: DIRECT+CRA | G27: 1
A28: CHM | B28: 0.58333333 | C28: H3 | D28: SAID ALI Kamile | E28: DIRECT | G28: 1
A29: LA BARGE | B29: 0.61805556 | C29: H3 | D29: SAID ALI Kamile | E29: 13 ARRETS | G29: 1
A30: LA BARGE | B30: 0.76041667 | C30: H3 | D30: SAID ALI Kamile | E30: DIRECT
A31: CHM | B31: 0.78125 | C31: H3 | D31: SAID ALI Kamile | E31: DIRECT
A32: LA BARGE | B32: 0.80208333 | C32: H3 | D32: SAID ALI Kamile | E32: 13 ARRETS
A33: LA BARGE | B33: 0.82291667 | C33: H3 | D33: SAID ALI Kamile | E33: 13 ARRETS
A34: REMPLACEMENT | C34: H
A35: REMPLACEMENT | C35: H
A36: REMPLACEMENT | C36: H
A37: REMPLACEMENT | C37: H
A38: REMPLACEMENT | C38: H
C39: S | F39: Signature Chauffeur
A41: TYPE | B41: H3
A42: CHAUFFEUR | B42: SAID ALI Kamile | L42: =L21+1 -> 46145
K44: ARRIVEE
A45: LIEU DE DEPART | B45: Heure théorique départ | C45: Horaire | D45: Chauffeur | E45: Direct/Non Direct | F45: Heure réelle départ | G45: Trajet non effectué | H45: Départ avec plus de 10 mns retard | I45: Nbre personnes montée | J45: Nbre personnes descente | K45: Heure arrivée finale | L45: Commentaires
A46: CHM | B46: 0.25 | C46: H3 | D46: SAID ALI Kamile | E46: 13 ARRETS | G46: 1
A47: LA BARGE | B47: 0.27083333 | C47: H3 | D47: SAID ALI Kamile | E47: DIRECT | G47: 1
A48: LA BARGE | B48: 0.29513889 | C48: H3 | D48: SAID ALI Kamile | E48: DIRECT | G48: 1
A49: CHM | B49: 0.58333333 | C49: H3 | D49: SAID ALI Kamile | E49: DIRECT | G49: 1
A50: CHM | B50: 0.625 | C50: H3 | D50: SAID ALI Kamile | E50: DIRECT | G50: 1
A51: CHM | B51: 0.76041667 | C51: H3 | D51: SAID ALI Kamile | E51: DIRECT | G51: 1
A52: LA BARGE | B52: 0.78125 | C52: H3 | D52: SAID ALI Kamile | E52: 13 ARRETS | G52: 1
A53: REMPLACEMENT | C53: H
A54: REMPLACEMENT | C54: H
A55: REMPLACEMENT | C55: H
A56: REMPLACEMENT | C56: H
C57: S | F57: Signature Chauffeur
A59: TYPE | B59: H3
A60: CHAUFFEUR | B60: SAID ALI Kamile | L60: =L42+1 -> 46146
K62: ARRIVEE
A63: LIEU DE DEPART | B63: Heure théorique départ | C63: Horaire | D63: Chauffeur | E63: Direct/Non Direct | F63: Heure réelle départ | G63: Trajet non effectué | H63: Départ avec plus de 10 mns retard | I63: Nbre personnes montée | J63: Nbre personnes descente | K63: Heure arrivée finale | L63: Commentaires
A64: CHM | B64: 0.25 | C64: H3 | D64: SAID ALI Kamile | E64: 13 ARRETS | G64: 1
A65: LA BARGE | B65: 0.27083333 | C65: H3 | D65: SAID ALI Kamile | E65: DIRECT | G65: 1
A66: LA BARGE | B66: 0.29513889 | C66: H3 | D66: SAID ALI Kamile | E66: DIRECT+CRA | G66: 1
A67: CHM | B67: 0.58333333 | C67: H3 | D67: SAID ALI Kamile | E67: DIRECT | G67: 1
A68: LA BARGE | B68: 0.61805556 | C68: H3 | D68: SAID ALI Kamile | E68: 13 ARRETS | G68: 1
A69: LA BARGE | B69: 0.76041667 | C69: H3 | D69: SAID ALI Kamile | E69: DIRECT
A70: CHM | B70: 0.78125 | C70: H3 | D70: SAID ALI Kamile | E70: DIRECT
A71: LA BARGE | B71: 0.80208333 | C71: H3 | D71: SAID ALI Kamile | E71: 13 ARRETS
A72: LA BARGE | B72: 0.82291667 | C72: H3 | D72: SAID ALI Kamile | E72: 13 ARRETS
A73: REMPLACEMENT | C73: H
A74: REMPLACEMENT | C74: H
A75: REMPLACEMENT | C75: H
A76: REMPLACEMENT | C76: H
A77: REMPLACEMENT | C77: H
C78: S | F78: Signature Chauffeur
A79: TYPE | B79: H3 | L79: =L60+1 -> 46147
A80: CHAUFFEUR | B80: SAID ALI Kamile
K82: ARRIVEE | M82: ARRIVEE
A83: LIEU DE DEPART | B83: Heure théorique départ | C83: Horaire | D83: Chauffeur | E83: Direct/Non Direct | F83: Heure réelle départ | G83: Trajet non effectué | H83: Départ avec plus de 10 mns retard | I83: Nbre personnes montée | J83: Nbre personnes descente | K83: Heure arrivée finale | L83: Commentaires | M83: Heure arrivée finale | N83: Commentaires
A84: CHM | B84: 0.25 | C84: H3 | D84: SAID ALI Kamile | E84: 13 ARRETS | G84: 1
A85: LA BARGE | B85: 0.27083333 | C85: H3 | D85: SAID ALI Kamile | E85: DIRECT | G85: 1
A86: LA BARGE | B86: 0.29513889 | C86: H3 | D86: SAID ALI Kamile | E86: DIRECT+CRA | G86: 1
A87: CHM | B87: 0.58333333 | C87: H3 | D87: SAID ALI Kamile | E87: DIRECT | G87: 1
A88: LA BARGE | B88: 0.61805556 | C88: H3 | D88: SAID ALI Kamile | E88: 13 ARRETS | G88: 1
A89: LA BARGE | B89: 0.76041667 | C89: H3 | D89: SAID ALI Kamile | E89: DIRECT
A90: CHM | B90: 0.78125 | C90: H3 | D90: SAID ALI Kamile | E90: DIRECT
A91: LA BARGE | B91: 0.80208333 | C91: H3 | D91: SAID ALI Kamile | E91: 13 ARRETS
A92: LA BARGE | B92: 0.82291667 | C92: H3 | D92: SAID ALI Kamile | E92: 13 ARRETS
A93: REMPLACEMENT | C93: H
A94: REMPLACEMENT | C94: H
A95: REMPLACEMENT | C95: H
A96: REMPLACEMENT | C96: H
A97: REMPLACEMENT | C97: H
C98: S | F98: Signature Chauffeur
A100: TYPE | B100: H3 | L100: =L79+1 -> 46148
A101: CHAUFFEUR | B101: SAID ALI Kamile
K103: ARRIVEE
A104: LIEU DE DEPART | B104: Heure théorique départ | C104: Horaire | D104: Chauffeur | E104: Direct/Non Direct | F104: Heure réelle départ | G104: Trajet non effectué | H104: Départ avec plus de 10 mns retard | I104: Nbre personnes montée | J104: Nbre personnes descente | K104: Heure arrivée finale | L104: Commentaires
A105: CHM | B105: 0.25 | C105: H3 | D105: SAID ALI Kamile | E105: 13 ARRETS | G105: 1
A106: LA BARGE | B106: 0.27083333 | C106: H3 | D106: SAID ALI Kamile | E106: DIRECT | G106: 1
A107: LA BARGE | B107: 0.29513889 | C107: H3 | D107: SAID ALI Kamile | E107: DIRECT+CRA | G107: 1
A108: CHM | B108: 0.58333333 | C108: H3 | D108: SAID ALI Kamile | E108: DIRECT | G108: 1
A109: LA BARGE | B109: 0.61805556 | C109: H3 | D109: SAID ALI Kamile | E109: 13 ARRETS | G109: 1
...

Sheet H5B
G1: ù
A2: TYPE | B2: H5
A3: DATE | B3: 45627
A4: CHAUFFEUR | B4: =VLOOKUP(B2,'Liste chauffeur'!$B$5:$L$19,2,TRUE)&" "&VLOOKUP(B2,'Liste chauffeur'!$B$5:$L$19,3,TRUE) -> ATTOUMANI Kamaldine | L4: 46143
K6: ARRIVEE | O6: 8
A7: LIEU DE DEPART | B7: Heure théorique départ | C7: Horaire | D7: Chauffeur | E7: Direct/Non Direct | F7: Heure réelle départ | G7: Trajet non effectué | H7: Départ avec plus de 10 mns retard | I7: Nbre personnes montée | J7: Nbre personnes descente | K7: Heure arrivée finale | L7: Commentaires | M7: Temps Aller | N7: Nbre personnes moyenne | O7: Capacité max | P7: Taux Fréquentation
A8: LA BARGE | B8: 0.3125 | C8: H5 | D8: ATTOUMANI Kamaldine | E8: DIRECT | G8: 1 | M8: =IF(G8=1,"",K8-F8) | N8: =J8 -> 0 | O8: =IF(G8=1,0,O$6) -> 0 | P8: =IF(O8=0,0,N8/O8) -> 0
A9: LA BARGE | B9: 0.32638889 | C9: H5 | D9: ATTOUMANI Kamaldine | E9: DIRECT | G9: 1 | M9: =IF(G9=1,"",K9-F9) | N9: =J9 -> 0 | O9: =IF(G9=1,0,O$6) -> 0 | P9: =IF(O9=0,0,N9/O9) -> 0
A10: LA BARGE | B10: 0.65972222 | C10: H5 | D10: ATTOUMANI Kamaldine | E10: 13 ARRETS | G10: 1 | M10: =IF(G10=1,"",K10-F10) | N10: =J10 -> 0 | O10: =IF(G10=1,0,O$6) -> 0 | P10: =IF(O10=0,0,N10/O10) -> 0
A11: LA BARGE | B11: 0.6875 | C11: H5 | D11: ATTOUMANI Kamaldine | E11: 13 ARRETS | G11: 1 | M11: =IF(G11=1,"",K11-F11) | N11: =J11 -> 0 | O11: =IF(G11=1,0,O$6) -> 0 | P11: =IF(O11=0,0,N11/O11) -> 0
A12: LA BARGE | B12: 0.76041667 | C12: H5 | D12: ATTOUMANI Kamaldine | E12: 13 ARRETS | M12: =IF(G12=1,"",K12-F12) -> 0 | N12: =J12 -> 0 | O12: =IF(G12=1,0,O$6) -> 8 | P12: =IF(O12=0,0,N12/O12) -> 0
A13: CHM | B13: 0.78125 | C13: H5 | D13: ATTOUMANI Kamaldine | E13: DIRECT | M13: =IF(G13=1,"",K13-F13) -> 0 | N13: =J13 -> 0 | O13: =IF(G13=1,0,O$6) -> 8 | P13: =IF(O13=0,0,N13/O13) -> 0
A14: CRA+CHM | B14: 0.80902778 | C14: H5 | D14: ATTOUMANI Kamaldine | E14: DIRECT | M14: =IF(G14=1,"",K14-F14) -> 0 | N14: =J14 -> 0 | O14: =IF(G14=1,0,O$6) -> 8 | P14: =IF(O14=0,0,N14/O14) -> 0
A15: LA BARGE | B15: 0.82291667 | C15: H5 | D15: ATTOUMANI Kamaldine | E15: 13 ARRETS | M15: =IF(G15=1,"",K15-F15) -> 0 | N15: =J15 -> 0 | O15: =IF(G15=1,0,O$6) -> 8 | P15: =IF(O15=0,0,N15/O15) -> 0
A16: REMPLACEMENT | C16: H | M16: =IF(G16=1,"",K16-F16) -> 0 | N16: =J16 -> 0 | O16: =IF(G16=1,0,O$6) -> 8 | P16: =IF(O16=0,0,N16/O16) -> 0
A17: REMPLACEMENT | C17: H | N17: =J17 -> 0 | O17: =IF(G17=1,0,O$6) -> 8 | P17: =IF(O17=0,0,N17/O17) -> 0
A18: REMPLACEMENT | C18: H | N18: =J18 -> 0 | O18: =IF(G18=1,0,O$6) -> 8
A19: REMPLACEMENT | C19: H
A20: REMPLACEMENT | C20: H
C21: S | F21: Signature Chauffeur
A22: TYPE | B22: H5
A23: CHAUFFEUR | B23: ATTOUMANI Kamaldine | L23: =L4+1 -> 46144
K25: ARRIVEE
A26: LIEU DE DEPART | B26: Heure théorique départ | C26: Horaire | D26: Chauffeur | E26: Direct/Non Direct | F26: Heure réelle départ | G26: Trajet non effectué | H26: Départ avec plus de 10 mns retard | I26: Nbre personnes montée | J26: Nbre personnes descente | K26: Heure arrivée finale | L26: Commentaires
A27: LA BARGE | B27: 0.23958333 | C27: H5 | D27: ATTOUMANI Kamaldine | E27: 13 ARRETS | G27: 1
A28: LA BARGE | B28: 0.27083333 | C28: H5 | D28: ATTOUMANI Kamaldine | E28: DIRECT+CRA | G28: 1
A29: CHM | B29: 0.28472222 | C29: H5 | D29: ATTOUMANI Kamaldine | E29: DIRECT | G29: 1
A30: LA BARGE | B30: 0.3125 | C30: H5 | D30: ATTOUMANI Kamaldine | E30: DIRECT | G30: 1
A31: CHM | B31: 0.32638889 | C31: H5 | D31: ATTOUMANI Kamaldine | E31: DIRECT | G31: 1
A32: CHM | B32: 0.625 | C32: H5 | D32: ATTOUMANI Kamaldine | E32: DIRECT | G32: 1
A33: LA BARGE | B33: 0.65972222 | C33: H5 | D33: ATTOUMANI Kamaldine | E33: 13 ARRETS | G33: 1
A34: LA BARGE | B34: 0.6875 | C34: H5 | D34: ATTOUMANI Kamaldine | E34: 13 ARRETS | G34: 1
A35: LA BARGE | B35: 0.71180556 | C35: H5 | D35: ATTOUMANI Kamaldine | E35: 13 ARRETS | G35: 1
A36: REMPLACEMENT | C36: H
A37: REMPLACEMENT | C37: H
A38: REMPLACEMENT | C38: H
A39: REMPLACEMENT | C39: H
A40: REMPLACEMENT | C40: H
C41: S | F41: Signature Chauffeur
A42: TYPE | B42: H5
A43: CHAUFFEUR | B43: ATTOUMANI Kamaldine | L43: =L23+1 -> 46145
K45: ARRIVEE
A46: LIEU DE DEPART | B46: Heure théorique départ | C46: Horaire | D46: Chauffeur | E46: Direct/Non Direct | F46: Heure réelle départ | G46: Trajet non effectué | H46: Départ avec plus de 10 mns retard | I46: Nbre personnes montée | J46: Nbre personnes descente | K46: Heure arrivée finale | L46: Commentaires
A47: LA BARGE | B47: 0.3125 | C47: H5 | D47: ATTOUMANI Kamaldine | E47: DIRECT | G47: 1
A48: LA BARGE | B48: 0.32638889 | C48: H5 | D48: ATTOUMANI Kamaldine | E48: DIRECT | G48: 1
A49: LA BARGE | B49: 0.65972222 | C49: H5 | D49: ATTOUMANI Kamaldine | E49: 13 ARRETS | G49: 1
A50: LA BARGE | B50: 0.6875 | C50: H5 | D50: ATTOUMANI Kamaldine | E50: 13 ARRETS | G50: 1
A51: LA BARGE | B51: 0.76041667 | C51: H5 | D51: ATTOUMANI Kamaldine | E51: 13 ARRETS
A52: CHM | B52: 0.78125 | C52: H5 | D52: ATTOUMANI Kamaldine | E52: DIRECT
A53: CRA+CHM | B53: 0.80902778 | C53: H5 | D53: ATTOUMANI Kamaldine | E53: DIRECT
A54: LA BARGE | B54: 0.82291667 | C54: H5 | D54: ATTOUMANI Kamaldine | E54: 13 ARRETS
A55: REMPLACEMENT | C55: H
A56: REMPLACEMENT | C56: H
A57: REMPLACEMENT | C57: H
A58: REMPLACEMENT | C58: H
A59: REMPLACEMENT | C59: H
C60: S | F60: Signature Chauffeur
A64: TYPE | B64: H5
A65: CHAUFFEUR | B65: ATTOUMANI Kamaldine | L65: =L43+1 -> 46146
K67: ARRIVEE
A68: LIEU DE DEPART | B68: Heure théorique départ | C68: Horaire | D68: Chauffeur | E68: Direct/Non Direct | F68: Heure réelle départ | G68: Trajet non effectué | H68: Départ avec plus de 10 mns retard | I68: Nbre personnes montée | J68: Nbre personnes descente | K68: Heure arrivée finale | L68: Commentaires
A69: LA BARGE | B69: 0.23958333 | C69: H5 | D69: ATTOUMANI Kamaldine | E69: 13 ARRETS | G69: 1
A70: LA BARGE | B70: 0.27083333 | C70: H5 | D70: ATTOUMANI Kamaldine | E70: DIRECT+CRA | G70: 1
A71: CHM | B71: 0.28472222 | C71: H5 | D71: ATTOUMANI Kamaldine | E71: DIRECT | G71: 1
A72: LA BARGE | B72: 0.3125 | C72: H5 | D72: ATTOUMANI Kamaldine | E72: DIRECT | G72: 1
A73: CHM | B73: 0.32638889 | C73: H5 | D73: ATTOUMANI Kamaldine | E73: DIRECT | G73: 1
A74: CHM | B74: 0.625 | C74: H5 | D74: ATTOUMANI Kamaldine | E74: DIRECT | G74: 1
A75: LA BARGE | B75: 0.65972222 | C75: H5 | D75: ATTOUMANI Kamaldine | E75: 13 ARRETS | G75: 1
A76: LA BARGE | B76: 0.6875 | C76: H5 | D76: ATTOUMANI Kamaldine | E76: 13 ARRETS | G76: 1
A77: LA BARGE | B77: 0.71180556 | C77: H5 | D77: ATTOUMANI Kamaldine | E77: 13 ARRETS | G77: 1
A78: REMPLACEMENT | C78: H
A79: REMPLACEMENT | C79: H
A80: REMPLACEMENT | C80: H
A81: REMPLACEMENT | C81: H
A82: REMPLACEMENT | C82: H
C83: S | F83: Signature Chauffeur
A84: TYPE | B84: H5 | L84: =L65+1 -> 46147
A85: CHAUFFEUR | B85: ATTOUMANI Kamaldine
K87: ARRIVEE | M87: ARRIVEE
A88: LIEU DE DEPART | B88: Heure théorique départ | C88: Horaire | D88: Chauffeur | E88: Direct/Non Direct | F88: Heure réelle départ | G88: Trajet non effectué | H88: Départ avec plus de 10 mns retard | I88: Nbre personnes montée | J88: Nbre personnes descente | K88: Heure arrivée finale | L88: Commentaires | M88: Heure arrivée finale | N88: Commentaires
A89: LA BARGE | B89: 0.23958333 | C89: H5 | D89: ATTOUMANI Kamaldine | E89: 13 ARRETS | G89: 1
A90: LA BARGE | B90: 0.27083333 | C90: H5 | D90: ATTOUMANI Kamaldine | E90: DIRECT+CRA | G90: 1
A91: CHM | B91: 0.28472222 | C91: H5 | D91: ATTOUMANI Kamaldine | E91: DIRECT | G91: 1
A92: LA BARGE | B92: 0.3125 | C92: H5 | D92: ATTOUMANI Kamaldine | E92: DIRECT | G92: 1
A93: CHM | B93: 0.32638889 | C93: H5 | D93: ATTOUMANI Kamaldine | E93: DIRECT | G93: 1
A94: CHM | B94: 0.625 | C94: H5 | D94: ATTOUMANI Kamaldine | E94: DIRECT | G94: 1
A95: LA BARGE | B95: 0.65972222 | C95: H5 | D95: ATTOUMANI Kamaldine | E95: 13 ARRETS | G95: 1
A96: LA BARGE | B96: 0.6875 | C96: H5 | D96: ATTOUMANI Kamaldine | E96: 13 ARRETS | G96: 1
A97: LA BARGE | B97: 0.71180556 | C97: H5 | D97: ATTOUMANI Kamaldine | E97: 13 ARRETS | G97: 1
A98: REMPLACEMENT | C98: H
A99: REMPLACEMENT | C99: H
A100: REMPLACEMENT | C100: H
A101: REMPLACEMENT | C101: H
A102: REMPLACEMENT | C102: H
C103: S | F103: Signature Chauffeur
A104: TYPE | B104: H5 | L104: =L84+1 -> 46148
A105: CHAUFFEUR | B105: ATTOUMANI Kamaldine
K107: ARRIVEE
A108: LIEU DE DEPART | B108: Heure théorique départ | C108: Horaire | D108: Chauffeur | E108: Direct/Non Direct | F108: Heure réelle départ | G108: Trajet non effectué | H108: Départ avec plus de 10 mns retard | I108: Nbre personnes montée | J108: Nbre personnes descente | K108: Heure arrivée finale | L108: Commentaires
A109: LA BARGE | B109: 0.23958333 | C109: H5 | D109: ATTOUMANI Kamaldine | E109: 13 ARRETS | G109: 1
...

Sheet HCOORDINATEUR
G1: ù
A3: DATE | B3: 45627
A4: COORDINATEUR NAVETTES CHM | I4: 46143
A6: Depart | B6: Heure théorique départ | C6: Type chauffeur prévu | D6: Nom chauffeur prévu | E6: Direct/non Direct | F6: Nom Chauffeur réel ( si différent) | G6: Heure réelle départ | H6: Nbre personnes montantes | J6: Temps Aller | K6: Nbre personnes moyenne | L6: Capacité max | M6: Taux Fréquentation
A7: ='Horaire dimanche2'!A13 -> LA BARGE | B7: ='Horaire dimanche2'!E13 -> 0.29513889 | C7: ='Horaire dimanche2'!H13 -> H3 | D7: =VLOOKUP(C7,'Liste chauffeur'!$B$5:$L$19,2,TRUE)&" "&VLOOKUP(C7,'Liste chauffeur'!$B$5:$L$19,3,TRUE) -> SAID ALI Kamile | E7: ='Horaire dimanche2'!C13 -> DIRECT | I7: Observations : | J7: =IF(G7=1,"",#REF!-F7) -> #REF! | K7: =#REF! -> #REF! | L7: =IF(G7=1,0,#REF!) -> #REF! | M7: =IF(L7=0,0,K7/L7) -> #REF!
A8: ='Horaire dimanche2'!A14 -> LA BARGE | B8: ='Horaire dimanche2'!E14 -> 0.3125 | C8: ='Horaire dimanche2'!H14 -> H5 | D8: =VLOOKUP(C8,'Liste chauffeur'!$B$5:$L$19,2,TRUE)&" "&VLOOKUP(C8,'Liste chauffeur'!$B$5:$L$19,3,TRUE) -> ATTOUMANI Kamaldine | E8: ='Horaire dimanche2'!C14 -> DIRECT | J8: =IF(G8=1,"",#REF!-F8) -> #REF! | K8: =#REF! -> #REF! | L8: =IF(G8=1,0,#REF!) -> #REF! | M8: =IF(L8=0,0,K8/L8) -> #REF!
A9: ='Horaire dimanche2'!A15 -> LA BARGE | B9: ='Horaire dimanche2'!E15 -> 0.32638889 | C9: ='Horaire dimanche2'!H15 -> H5 | D9: =VLOOKUP(C9,'Liste chauffeur'!$B$5:$L$19,2,TRUE)&" "&VLOOKUP(C9,'Liste chauffeur'!$B$5:$L$19,3,TRUE) -> ATTOUMANI Kamaldine | E9: ='Horaire dimanche2'!C15 -> DIRECT | I9: Absences : | J9: =IF(G9=1,"",#REF!-F9) -> #REF! | K9: =#REF! -> #REF! | L9: =IF(G9=1,0,#REF!) -> #REF! | M9: =IF(L9=0,0,K9/L9) -> #REF!
A10: ='Horaire dimanche2'!A16 -> LA BARGE | B10: ='Horaire dimanche2'!E16 -> 0.58333333 | C10: ='Horaire dimanche2'!H16 -> H1 | D10: =VLOOKUP(C10,'Liste chauffeur'!$B$5:$L$19,2,TRUE)&" "&VLOOKUP(C10,'Liste chauffeur'!$B$5:$L$19,3,TRUE) -> CHADHOULI Houmadi | E10: ='Horaire dimanche2'!C16 -> 13 ARRETS | F10: =IF(ISBLANK('Feuille saisie'!L17)=TRUE,"",'Feuille saisie'!L17) | J10: =IF(G10=1,"",#REF!-F10) -> #REF! | K10: =#REF! -> #REF! | L10: =IF(G10=1,0,#REF!) -> #REF! | M10: =IF(L10=0,0,K10/L10) -> #REF!
A11: ='Horaire dimanche2'!A17 -> CHM | B11: ='Horaire dimanche2'!E17 -> 0.58333333 | C11: ='Horaire dimanche2'!H17 -> H3 | D11: =VLOOKUP(C11,'Liste chauffeur'!$B$5:$L$19,2,TRUE)&" "&VLOOKUP(C11,'Liste chauffeur'!$B$5:$L$19,3,TRUE) -> SAID ALI Kamile | E11: ='Horaire dimanche2'!C17 -> DIRECT | F11: =IF(ISBLANK('Feuille saisie'!L18)=TRUE,"",'Feuille saisie'!L18) | J11: =IF(G11=1,"",#REF!-F11) -> #REF! | K11: =#REF! -> #REF! | L11: =IF(G11=1,0,#REF!) -> #REF! | M11: =IF(L11=0,0,K11/L11) -> #REF!
A12: ='Horaire dimanche2'!A18 -> LA BARGE | B12: ='Horaire dimanche2'!E18 -> 0.61458333 | C12: ='Horaire dimanche2'!H18 -> H1 | D12: =VLOOKUP(C12,'Liste chauffeur'!$B$5:$L$19,2,TRUE)&" "&VLOOKUP(C12,'Liste chauffeur'!$B$5:$L$19,3,TRUE) -> CHADHOULI Houmadi | E12: ='Horaire dimanche2'!C18 -> 13 ARRETS | F12: =IF(ISBLANK('Feuille saisie'!L19)=TRUE,"",'Feuille saisie'!L19) | I12: Trajets non effectués : | J12: =IF(G12=1,"",#REF!-F12) -> #REF! | K12: =#REF! -> #REF! | L12: =IF(G12=1,0,#REF!) -> #REF! | M12: =IF(L12=0,0,K12/L12) -> #REF!
A13: ='Horaire dimanche2'!A19 -> CHM | B13: ='Horaire dimanche2'!E19 -> 0.625 | C13: ='Horaire dimanche2'!H19 -> H3 | D13: =VLOOKUP(C13,'Liste chauffeur'!$B$5:$L$19,2,TRUE)&" "&VLOOKUP(C13,'Liste chauffeur'!$B$5:$L$19,3,TRUE) -> SAID ALI Kamile | E13: ='Horaire dimanche2'!C19 -> DIRECT | F13: =IF(ISBLANK('Feuille saisie'!L20)=TRUE,"",'Feuille saisie'!L20) | J13: =IF(G13=1,"",#REF!-F13) -> #REF! | K13: =#REF! -> #REF! | L13: =IF(G13=1,0,#REF!) -> #REF! | M13: =IF(L13=0,0,K13/L13) -> #REF!
A14: ='Horaire dimanche2'!A20 -> LA BARGE | B14: ='Horaire dimanche2'!E20 -> 0.63888889 | C14: ='Horaire dimanche2'!H20 -> H1 | D14: =VLOOKUP(C14,'Liste chauffeur'!$B$5:$L$19,2,TRUE)&" "&VLOOKUP(C14,'Liste chauffeur'!$B$5:$L$19,3,TRUE) -> CHADHOULI Houmadi | E14: ='Horaire dimanche2'!C20 -> 13 ARRETS | F14: =IF(ISBLANK('Feuille saisie'!L21)=TRUE,"",'Feuille saisie'!L21) | I14: Signature Coordinateur 1 : | J14: =IF(G14=1,"",#REF!-F14) -> #REF! | K14: =#REF! -> #REF! | L14: =IF(G14=1,0,#REF!) -> #REF! | M14: =IF(L14=0,0,K14/L14) -> #REF!
A15: ='Horaire dimanche2'!A21 -> LA BARGE | B15: ='Horaire dimanche2'!E21 -> 0.65972222 | C15: ='Horaire dimanche2'!H21 -> H5 | D15: =VLOOKUP(C15,'Liste chauffeur'!$B$5:$L$19,2,TRUE)&" "&VLOOKUP(C15,'Liste chauffeur'!$B$5:$L$19,3,TRUE) -> ATTOUMANI Kamaldine | E15: ='Horaire dimanche2'!C21 -> 13 ARRETS | F15: =IF(ISBLANK('Feuille saisie'!L22)=TRUE,"",'Feuille saisie'!L22) | J15: =IF(G15=1,"",#REF!-F15) -> #REF! | K15: =#REF! -> #REF! | L15: =IF(G15=1,0,#REF!) -> #REF! | M15: =IF(L15=0,0,K15/L15) -> #REF!
A16: ='Horaire dimanche2'!A22 -> LA BARGE | B16: ='Horaire dimanche2'!E22 -> 0.6875 | C16: ='Horaire dimanche2'!H22 -> H5 | D16: =VLOOKUP(C16,'Liste chauffeur'!$B$5:$L$19,2,TRUE)&" "&VLOOKUP(C16,'Liste chauffeur'!$B$5:$L$19,3,TRUE) -> ATTOUMANI Kamaldine | E16: ='Horaire dimanche2'!C22 -> 13 ARRETS | K16: =#REF! -> #REF! | L16: =IF(G16=1,0,#REF!) -> #REF! | M16: =IF(L16=0,0,K16/L16) -> #REF!
A17: ='Horaire dimanche2'!A23 -> CHM | B17: ='Horaire dimanche2'!E23 -> 0.76041667 | C17: ='Horaire dimanche2'!H23 -> H3 | D17: =VLOOKUP(C17,'Liste chauffeur'!$B$5:$L$19,2,TRUE)&" "&VLOOKUP(C17,'Liste chauffeur'!$B$5:$L$19,3,TRUE) -> SAID ALI Kamile | E17: ='Horaire dimanche2'!C23 -> DIRECT | F17: =IF(ISBLANK('Feuille saisie'!L29)=TRUE,"",'Feuille saisie'!L29) | K17: =#REF! -> #REF! | L17: =IF(G17=1,0,#REF!) -> #REF!
A18: ='Horaire dimanche2'!A24 -> LA BARGE | B18: ='Horaire dimanche2'!E24 -> 0.76041667 | C18: ='Horaire dimanche2'!H24 -> H5 | D18: =VLOOKUP(C18,'Liste chauffeur'!$B$5:$L$19,2,TRUE)&" "&VLOOKUP(C18,'Liste chauffeur'!$B$5:$L$19,3,TRUE) -> ATTOUMANI Kamaldine | E18: ='Horaire dimanche2'!C24 -> 13 ARRETS | F18: =IF(ISBLANK('Feuille saisie'!L30)=TRUE,"",'Feuille saisie'!L30)
A19: ='Horaire dimanche2'!A25 -> CHM | B19: ='Horaire dimanche2'!E25 -> 0.78125 | C19: ='Horaire dimanche2'!H25 -> H5 | D19: =VLOOKUP(C19,'Liste chauffeur'!$B$5:$L$19,2,TRUE)&" "&VLOOKUP(C19,'Liste chauffeur'!$B$5:$L$19,3,TRUE) -> ATTOUMANI Kamaldine | E19: ='Horaire dimanche2'!C25 -> DIRECT | F19: =IF(ISBLANK('Feuille saisie'!L31)=TRUE,"",'Feuille saisie'!L31)
A20: ='Horaire dimanche2'!A26 -> LA BARGE | B20: ='Horaire dimanche2'!E26 -> 0.78125 | C20: ='Horaire dimanche2'!H26 -> H3 | D20: =VLOOKUP(C20,'Liste chauffeur'!$B$5:$L$19,2,TRUE)&" "&VLOOKUP(C20,'Liste chauffeur'!$B$5:$L$19,3,TRUE) -> SAID ALI Kamile | E20: ='Horaire dimanche2'!C26 -> 13 ARRETS | F20: =IF(ISBLANK('Feuille saisie'!L32)=TRUE,"",'Feuille saisie'!L32)
A21: ='Horaire dimanche2'!A27 -> CRA+CHM | B21: ='Horaire dimanche2'!E27 -> 0.80902778 | C21: ='Horaire dimanche2'!H27 -> H5 | D21: =VLOOKUP(C21,'Liste chauffeur'!$B$5:$L$19,2,TRUE)&" "&VLOOKUP(C21,'Liste chauffeur'!$B$5:$L$19,3,TRUE) -> ATTOUMANI Kamaldine | E21: ='Horaire dimanche2'!C27 -> DIRECT | F21: =IF(ISBLANK('Feuille saisie'!L34)=TRUE,"",'Feuille saisie'!L34)
A22: ='Horaire dimanche2'!A28 -> LA BARGE | B22: ='Horaire dimanche2'!E28 -> 0.82291667 | C22: ='Horaire dimanche2'!H28 -> H5 | D22: =VLOOKUP(C22,'Liste chauffeur'!$B$5:$L$19,2,TRUE)&" "&VLOOKUP(C22,'Liste chauffeur'!$B$5:$L$19,3,TRUE) -> ATTOUMANI Kamaldine | E22: ='Horaire dimanche2'!C28 -> 13 ARRETS | F22: =IF(ISBLANK('Feuille saisie'!L48)=TRUE,"",'Feuille saisie'!L48)
A27: COORDINATEUR NAVETTES CHM | I27: =I4+1 -> 46144
A29: Depart | B29: Heure théorique départ | C29: Type chauffeur prévu | D29: Nom chauffeur prévu | E29: Direct / Non Direct | F29: Nom Chauffeur réel ( si différent) | G29: Heure réelle départ | H29: Nbre personnes montantes
A30: CHM | B30: 0.23263889 | C30: H1 | D30: CHADHOULI Houmadi | E30: 13 ARRETS
A31: LA BARGE | B31: 0.23958333 | C31: H5 | D31: ATTOUMANI Kamaldine | E31: 13 ARRETS
A32: CHM | B32: 0.25 | C32: H3 | D32: SAID ALI Kamile | E32: 13 ARRETS
A33: CHM | B33: 0.27083333 | C33: H1 | D33: CHADHOULI Houmadi | E33: 13 ARRETS | I33: Observations :
A34: LA BARGE | B34: 0.27083333 | C34: H3 | D34: SAID ALI Kamile | E34: DIRECT
A35: LA BARGE | B35: 0.27083333 | C35: H5 | D35: ATTOUMANI Kamaldine | E35: DIRECT+CRA
A36: CHM | B36: 0.28819444 | C36: H1 | D36: CHADHOULI Houmadi | E36: DIRECT
A37: CHM | B37: 0.28472222 | C37: H5 | D37: ATTOUMANI Kamaldine | E37: DIRECT | I37: Absences :
A38: LA BARGE | B38: 0.29513889 | C38: H3 | D38: SAID ALI Kamile | E38: DIRECT+CRA
A39: LA BARGE | B39: 0.3125 | C39: H5 | D39: ATTOUMANI Kamaldine | E39: DIRECT | I39: Trajets non effectués :
A40: CHM | B40: 0.32638889 | C40: H5 | D40: ATTOUMANI Kamaldine | E40: DIRECT
A41: LA BARGE | B41: 0.32638889 | C41: H1 | D41: CHADHOULI Houmadi | E41: DIRECT
A42: LA BARGE | B42: 0.58333333 | C42: H1 | D42: CHADHOULI Houmadi | E42: 13 ARRETS | I42: Signature Coordinateur 1 :
A43: CHM | B43: 0.58333333 | C43: H3 | D43: SAID ALI Kamile | E43: DIRECT
A44: LA BARGE | B44: 0.61458333 | C44: H1 | D44: CHADHOULI Houmadi | E44: 13 ARRETS
A45: LA BARGE | B45: 0.61805556 | C45: H3 | D45: SAID ALI Kamile | E45: 13 ARRETS
A46: CHM | B46: 0.625 | C46: H5 | D46: ATTOUMANI Kamaldine | E46: DIRECT
A47: LA BARGE | B47: 0.63888889 | C47: H1 | D47: CHADHOULI Houmadi | E47: 13 ARRETS
A48: LA BARGE | B48: 0.65972222 | C48: H5 | D48: ATTOUMANI Kamaldine | E48: 13 ARRETS
A49: LA BARGE | B49: 0.6875 | C49: H5 | D49: ATTOUMANI Kamaldine | E49: 13 ARRETS
A50: LA BARGE | B50: 0.71180556 | C50: H5 | D50: ATTOUMANI Kamaldine | E50: 13 ARRETS
A51: LA BARGE | B51: 0.76041667 | C51: H3 | D51: SAID ALI Kamile | E51: DIRECT
A52: CHM | B52: 0.76041667 | C52: H1 | D52: CHADHOULI Houmadi | E52: DIRECT
A53: LA BARGE | B53: 0.78125 | C53: H1 | D53: CHADHOULI Houmadi | E53: 13 ARRETS
A54: CHM | B54: 0.78125 | C54: H3 | D54: SAID ALI Kamile | E54: DIRECT
... A57: LA BARGE | B57: 0.82291667 | C57: H3 | D57: SAID ALI Kamile | E57: 13 ARRETS
A62: COORDINATEUR NAVETTES CHM | I62: =I27+1 -> 46145
A64: Depart | B64: Heure théorique départ | C64: Type chauffeur prévu | D64: Nom chauffeur prévu | E64: Direct/non Direct | F64: Nom Chauffeur réel ( si différent) | G64: Heure réelle départ | H64: Nbre personnes montantes
A65: LA BARGE | B65: 0.29513889 | C65: H3 | D65: SAID ALI Kamile | E65: DIRECT | I65: Observations :
A66: LA BARGE | B66: 0.3125 | C66: H5 | D66: ATTOUMANI Kamaldine | E66: DIRECT
A67: LA BARGE | B67: 0.32638889 | C67: H5 | D67: ATTOUMANI Kamaldine | E67: DIRECT | I67: Absences :
A68: LA BARGE | B68: 0.58333333 | C68: H1 | D68: CHADHOULI Houmadi | E68: 13 ARRETS
A69: CHM | B69: 0.58333333 | C69: H3 | D69: SAID ALI Kamile | E69: DIRECT
A70: LA BARGE | B70: 0.61458333 | C70: H1 | D70: CHADHOULI Houmadi | E70: 13 ARRETS | I70: Trajets non effectués :
A71: CHM | B71: 0.625 | C71: H3 | D71: SAID ALI Kamile | E71: DIRECT
A72: LA BARGE | B72: 0.63888889 | C72: H1 | D72: CHADHOULI Houmadi | E72: 13 ARRETS | I72: Signature Coordinateur 1 :
A73: LA BARGE | B73: 0.65972222 | C73: H5 | D73: ATTOUMANI Kamaldine | E73: 13 ARRETS
A74: LA BARGE | B74: 0.6875 | C74: H5 | D74: ATTOUMANI Kamaldine | E74: 13 ARRETS
A75: CHM | B75: 0.76041667 | C75: H3 | D75: SAID ALI Kamile | E75: DIRECT
A76: LA BARGE | B76: 0.76041667 | C76: H5 | D76: ATTOUMANI Kamaldine | E76: 13 ARRETS
A77: CHM | B77: 0.78125 | C77: H5 | D77: ATTOUMANI Kamaldine | E77: DIRECT
A78: LA BARGE | B78: 0.78125 | C78: H3 | D78: SAID ALI Kamile | E78: 13 ARRETS
A79: CRA+CHM | B79: 0.80902778 | C79: H5 | D79: ATTOUMANI Kamaldine | E79: DIRECT
A80: LA BARGE | B80: 0.82291667 | C80: H5 | D80: ATTOUMANI Kamaldine | E80: 13 ARRETS
A84: COORDINATEUR NAVETTES CHM | I84: =I62+1 -> 46146
A86: Depart | B86: Heure théorique départ | C86: Type chauffeur prévu | D86: Nom chauffeur prévu | E86: Direct / Non Direct | F86: Nom Chauffeur réel ( si différent) | G86: Heure réelle départ | H86: Nbre personnes montantes
A87: CHM | B87: 0.23263889 | C87: H1 | D87: CHADHOULI Houmadi | E87: 13 ARRETS
A88: LA BARGE | B88: 0.23958333 | C88: H5 | D88: ATTOUMANI Kamaldine | E88: 13 ARRETS
A89: CHM | B89: 0.25 | C89: H3 | D89: SAID ALI Kamile | E89: 13 ARRETS
A90: CHM | B90: 0.27083333 | C90: H1 | D90: CHADHOULI Houmadi | E90: 13 ARRETS | I90: Observations :
A91: LA BARGE | B91: 0.27083333 | C91: H3 | D91: SAID ALI Kamile | E91: DIRECT
A92: LA BARGE | B92: 0.27083333 | C92: H5 | D92: ATTOUMANI Kamaldine | E92: DIRECT+CRA
A93: CHM | B93: 0.28819444 | C93: H1 | D93: CHADHOULI Houmadi | E93: DIRECT
A94: CHM | B94: 0.28472222 | C94: H5 | D94: ATTOUMANI Kamaldine | E94: DIRECT | I94: Absences :
A95: LA BARGE | B95: 0.29513889 | C95: H3 | D95: SAID ALI Kamile | E95: DIRECT+CRA
A96: LA BARGE | B96: 0.3125 | C96: H5 | D96: ATTOUMANI Kamaldine | E96: DIRECT | I96: Trajets non effectués :
A97: CHM | B97: 0.32638889 | C97: H5 | D97: ATTOUMANI Kamaldine | E97: DIRECT
A98: LA BARGE | B98: 0.32638889 | C98: H1 | D98: CHADHOULI Houmadi | E98: DIRECT
A99: LA BARGE | B99: 0.58333333 | C99: H1 | D99: CHADHOULI Houmadi | E99: 13 ARRETS | I99: Signature Coordinateur 1 :
A100: CHM | B100: 0.58333333 | C100: H3 | D100: SAID ALI Kamile | E100: DIRECT
A101: LA BARGE | B101: 0.61458333 | C101: H1 | D101: CHADHOULI Houmadi | E101: 13 ARRETS
A102: LA BARGE | B102: 0.61805556 | C102: H3 | D102: SAID ALI Kamile | E102: 13 ARRETS
A103: CHM | B103: 0.625 | C103: H5 | D103: ATTOUMANI Kamaldine | E103: DIRECT
A104: LA BARGE | B104: 0.63888889 | C104: H1 | D104: CHADHOULI Houmadi | E104: 13 ARRETS
A105: LA BARGE | B105: 0.65972222 | C105: H5 | D105: ATTOUMANI Kamaldine | E105: 13 ARRETS
A106: LA BARGE | B106: 0.6875 | C106: H5 | D106: ATTOUMANI Kamaldine | E106: 13 ARRETS
A107: LA BARGE | B107: 0.71180556 | C107: H5 | D107: ATTOUMANI Kamaldine | E107: 13 ARRETS
A108: LA BARGE | B108: 0.76041667 | C108: H3 | D108: SAID ALI Kamile | E108: DIRECT
A109: CHM | B109: 0.76041667 | C109: H1 | D109: CHADHOULI Houmadi | E109: DIRECT
A110: LA BARGE | B110: 0.78125 | C110: H1 | D110: CHADHOULI Houmadi | E110: 13 ARRETS
A111: CHM | B111: 0.78125 | C111: H3 | D111: SAID ALI Kamile | E111: DIRECT
... A114: LA BARGE | B114: 0.82291667 | C114: H3 | D114: SAID ALI Kamile | E114: 13 ARRETS
A119: COORDINATEUR NAVETTES CHM | I119: =I84+1 -> 46147
A121: Depart | B121: Heure théorique départ | C121: Type chauffeur prévu | D121: Nom chauffeur prévu | E121: Direct / Non Direct | F121: Nom Chauffeur réel ( si différent) | G121: Heure réelle départ | H121: Nbre personnes montantes
A122: CHM | B122: 0.23263889 | C122: H1 | D122: CHADHOULI Houmadi | E122: 13 ARRETS | J122: ARRIVEE
A123: LA BARGE | B123: 0.23958333 | C123: H5 | D123: ATTOUMANI Kamaldine | E123: 13 ARRETS | J123: Heure arrivée finale | K123: Commentaires
A124: CHM | B124: 0.25 | C124: H3 | D124: SAID ALI Kamile | E124: 13 ARRETS
A125: CHM | B125: 0.27083333 | C125: H1 | D125: CHADHOULI Houmadi | E125: 13 ARRETS | I125: Observations :
...

Sheet feuille coordinateur
A1: COORDINATEUR NAVETTES CHM
A2: Depart | B2: Heure théorique départ | C2: Type chauffeur prévu | D2: Nom chauffeur prévu | E2: Direct / Non Direct | F2: Nom Chauffeur réel ( si différent) | G2: Heure réelle départ | H2: Nbre personnes montantes
A3: =Horaire!A8 -> CHM | B3: =Horaire!E8 -> 0.23263889 | C3: =Horaire!H8 -> H1 | D3: =VLOOKUP(C3,'Liste chauffeur'!$B$5:$L$19,2,TRUE)&" "&VLOOKUP(C3,'Liste chauffeur'!$B$5:$L$19,3,TRUE) -> CHADHOULI Houmadi | E3: =Horaire!C8 -> 13 ARRETS
A4: =Horaire!A9 -> LA BARGE | B4: =Horaire!E9 -> 0.23958333 | C4: =Horaire!H9 -> H5 | D4: =VLOOKUP(C4,'Liste chauffeur'!$B$5:$L$19,2,TRUE)&" "&VLOOKUP(C4,'Liste chauffeur'!$B$5:$L$19,3,TRUE) -> ATTOUMANI Kamaldine | E4: =Horaire!C9 -> 13 ARRETS
A5: =Horaire!A10 -> CHM | B5: =Horaire!E10 -> 0.25 | C5: =Horaire!H10 -> H3 | D5: =VLOOKUP(C5,'Liste chauffeur'!$B$5:$L$19,2,TRUE)&" "&VLOOKUP(C5,'Liste chauffeur'!$B$5:$L$19,3,TRUE) -> SAID ALI Kamile | E5: =Horaire!C10 -> 13 ARRETS
A6: =Horaire!A11 -> CHM | B6: =Horaire!E11 -> 0.27083333 | C6: =Horaire!H11 -> H1 | D6: =VLOOKUP(C6,'Liste chauffeur'!$B$5:$L$19,2,TRUE)&" "&VLOOKUP(C6,'Liste chauffeur'!$B$5:$L$19,3,TRUE) -> CHADHOULI Houmadi | E6: =Horaire!C11 -> 13 ARRETS | I6: Observations :
A7: =Horaire!A12 -> LA BARGE | B7: =Horaire!E12 -> 0.27083333 | C7: =Horaire!H12 -> H3 | D7: =VLOOKUP(C7,'Liste chauffeur'!$B$5:$L$19,2,TRUE)&" "&VLOOKUP(C7,'Liste chauffeur'!$B$5:$L$19,3,TRUE) -> SAID ALI Kamile | E7: =Horaire!C12 -> DIRECT | F7: =IF(ISBLANK('Feuille saisie'!L12)=TRUE,"",'Feuille saisie'!L12)
A8: =Horaire!A13 -> LA BARGE | B8: =Horaire!E13 -> 0.27083333 | C8: =Horaire!H13 -> H5 | D8: =VLOOKUP(C8,'Liste chauffeur'!$B$5:$L$19,2,TRUE)&" "&VLOOKUP(C8,'Liste chauffeur'!$B$5:$L$19,3,TRUE) -> ATTOUMANI Kamaldine | E8: =Horaire!C13 -> DIRECT+CRA | F8: =IF(ISBLANK('Feuille saisie'!L13)=TRUE,"",'Feuille saisie'!L13)
A9: =Horaire!A14 -> CHM | B9: =Horaire!E14 -> 0.28819444 | C9: =Horaire!H14 -> H1 | D9: =VLOOKUP(C9,'Liste chauffeur'!$B$5:$L$19,2,TRUE)&" "&VLOOKUP(C9,'Liste chauffeur'!$B$5:$L$19,3,TRUE) -> CHADHOULI Houmadi | E9: =Horaire!C14 -> DIRECT | F9: =IF(ISBLANK('Feuille saisie'!L14)=TRUE,"",'Feuille saisie'!L14)
A10: =Horaire!A15 -> CHM | B10: =Horaire!E15 -> 0.28472222 | C10: =Horaire!H15 -> H5 | D10: =VLOOKUP(C10,'Liste chauffeur'!$B$5:$L$19,2,TRUE)&" "&VLOOKUP(C10,'Liste chauffeur'!$B$5:$L$19,3,TRUE) -> ATTOUMANI Kamaldine | E10: =Horaire!C15 -> DIRECT | F10: =IF(ISBLANK('Feuille saisie'!L15)=TRUE,"",'Feuille saisie'!L15) | I10: Absences :
A11: =Horaire!A16 -> LA BARGE | B11: =Horaire!E16 -> 0.29513889 | C11: =Horaire!H16 -> H3 | D11: =VLOOKUP(C11,'Liste chauffeur'!$B$5:$L$19,2,TRUE)&" "&VLOOKUP(C11,'Liste chauffeur'!$B$5:$L$19,3,TRUE) -> SAID ALI Kamile | E11: =Horaire!C16 -> DIRECT+CRA | F11: =IF(ISBLANK('Feuille saisie'!L16)=TRUE,"",'Feuille saisie'!L16)
A12: =Horaire!A17 -> LA BARGE | B12: =Horaire!E17 -> 0.3125 | C12: =Horaire!H17 -> H5 | D12: =VLOOKUP(C12,'Liste chauffeur'!$B$5:$L$19,2,TRUE)&" "&VLOOKUP(C12,'Liste chauffeur'!$B$5:$L$19,3,TRUE) -> ATTOUMANI Kamaldine | E12: =Horaire!C17 -> DIRECT | F12: =IF(ISBLANK('Feuille saisie'!L17)=TRUE,"",'Feuille saisie'!L17) | I12: Trajets non effectués :
A13: =Horaire!A18 -> CHM | B13: =Horaire!E18 -> 0.32638889 | C13: =Horaire!H18 -> H5 | D13: =VLOOKUP(C13,'Liste chauffeur'!$B$5:$L$19,2,TRUE)&" "&VLOOKUP(C13,'Liste chauffeur'!$B$5:$L$19,3,TRUE) -> ATTOUMANI Kamaldine | E13: =Horaire!C18 -> DIRECT
A14: =Horaire!A19 -> LA BARGE | B14: =Horaire!E19 -> 0.32638889 | C14: =Horaire!H19 -> H1 | D14: =VLOOKUP(C14,'Liste chauffeur'!$B$5:$L$19,2,TRUE)&" "&VLOOKUP(C14,'Liste chauffeur'!$B$5:$L$19,3,TRUE) -> CHADHOULI Houmadi | E14: =Horaire!C19 -> DIRECT | F14: =IF(ISBLANK('Feuille saisie'!L24)=TRUE,"",'Feuille saisie'!L24)
A15: =Horaire!A20 -> LA BARGE | B15: =Horaire!E20 -> 0.58333333 | C15: =Horaire!H20 -> H1 | D15: =VLOOKUP(C15,'Liste chauffeur'!$B$5:$L$19,2,TRUE)&" "&VLOOKUP(C15,'Liste chauffeur'!$B$5:$L$19,3,TRUE) -> CHADHOULI Houmadi | E15: =Horaire!C20 -> 13 ARRETS | F15: =IF(ISBLANK('Feuille saisie'!L25)=TRUE,"",'Feuille saisie'!L25) | I15: Signature Coordinateur 1 :
A16: =Horaire!A21 -> CHM | B16: =Horaire!E21 -> 0.58333333 | C16: =Horaire!H21 -> H3 | D16: =VLOOKUP(C16,'Liste chauffeur'!$B$5:$L$19,2,TRUE)&" "&VLOOKUP(C16,'Liste chauffeur'!$B$5:$L$19,3,TRUE) -> SAID ALI Kamile | E16: =Horaire!C21 -> DIRECT | F16: =IF(ISBLANK('Feuille saisie'!L26)=TRUE,"",'Feuille saisie'!L26)
A17: =Horaire!A22 -> LA BARGE | B17: =Horaire!E22 -> 0.61458333 | C17: =Horaire!H22 -> H1 | D17: =VLOOKUP(C17,'Liste chauffeur'!$B$5:$L$19,2,TRUE)&" "&VLOOKUP(C17,'Liste chauffeur'!$B$5:$L$19,3,TRUE) -> CHADHOULI Houmadi | E17: =Horaire!C22 -> 13 ARRETS | F17: =IF(ISBLANK('Feuille saisie'!L27)=TRUE,"",'Feuille saisie'!L27)
A18: =Horaire!A23 -> LA BARGE | B18: =Horaire!E23 -> 0.61805556 | C18: =Horaire!H23 -> H3 | D18: =VLOOKUP(C18,'Liste chauffeur'!$B$5:$L$19,2,TRUE)&" "&VLOOKUP(C18,'Liste chauffeur'!$B$5:$L$19,3,TRUE) -> SAID ALI Kamile | E18: =Horaire!C23 -> 13 ARRETS | F18: =IF(ISBLANK('Feuille saisie'!L29)=TRUE,"",'Feuille saisie'!L29)
A19: =Horaire!A24 -> CHM | B19: =Horaire!E24 -> 0.625 | C19: =Horaire!H24 -> H5 | D19: =VLOOKUP(C19,'Liste chauffeur'!$B$5:$L$19,2,TRUE)&" "&VLOOKUP(C19,'Liste chauffeur'!$B$5:$L$19,3,TRUE) -> ATTOUMANI Kamaldine | E19: =Horaire!C24 -> DIRECT | F19: =IF(ISBLANK('Feuille saisie'!L43)=TRUE,"",'Feuille saisie'!L43)
A20: =Horaire!A25 -> LA BARGE | B20: =Horaire!E25 -> 0.63888889 | C20: =Horaire!H25 -> H1 | D20: =VLOOKUP(C20,'Liste chauffeur'!$B$5:$L$19,2,TRUE)&" "&VLOOKUP(C20,'Liste chauffeur'!$B$5:$L$19,3,TRUE) -> CHADHOULI Houmadi | E20: =Horaire!C25 -> 13 ARRETS | F20: =IF(ISBLANK('Feuille saisie'!L44)=TRUE,"",'Feuille saisie'!L44)
A21: =Horaire!A26 -> LA BARGE | B21: =Horaire!E26 -> 0.65972222 | C21: =Horaire!H26 -> H5 | D21: =VLOOKUP(C21,'Liste chauffeur'!$B$5:$L$19,2,TRUE)&" "&VLOOKUP(C21,'Liste chauffeur'!$B$5:$L$19,3,TRUE) -> ATTOUMANI Kamaldine | E21: =Horaire!C26 -> 13 ARRETS | F21: =IF(ISBLANK('Feuille saisie'!L45)=TRUE,"",'Feuille saisie'!L45)
A22: =Horaire!A27 -> LA BARGE | B22: =Horaire!E27 -> 0.6875 | C22: =Horaire!H27 -> H5 | D22: =VLOOKUP(C22,'Liste chauffeur'!$B$5:$L$19,2,TRUE)&" "&VLOOKUP(C22,'Liste chauffeur'!$B$5:$L$19,3,TRUE) -> ATTOUMANI Kamaldine | E22: =Horaire!C27 -> 13 ARRETS | F22: =IF(ISBLANK('Feuille saisie'!L46)=TRUE,"",'Feuille saisie'!L46)
A23: =Horaire!A28 -> LA BARGE | B23: =Horaire!E28 -> 0.71180556 | C23: =Horaire!H28 -> H5 | D23: =VLOOKUP(C23,'Liste chauffeur'!$B$5:$L$19,2,TRUE)&" "&VLOOKUP(C23,'Liste chauffeur'!$B$5:$L$19,3,TRUE) -> ATTOUMANI Kamaldine | E23: =Horaire!C28 -> 13 ARRETS | F23: =IF(ISBLANK('Feuille saisie'!L47)=TRUE,"",'Feuille saisie'!L47)
A24: =Horaire!A29 -> LA BARGE | B24: =Horaire!E29 -> 0.76041667 | C24: =Horaire!H29 -> H3 | D24: =VLOOKUP(C24,'Liste chauffeur'!$B$5:$L$19,2,TRUE)&" "&VLOOKUP(C24,'Liste chauffeur'!$B$5:$L$19,3,TRUE) -> SAID ALI Kamile | E24: =Horaire!C29 -> DIRECT | F24: =IF(ISBLANK('Feuille saisie'!L48)=TRUE,"",'Feuille saisie'!L48)
A25: =Horaire!A30 -> CHM | B25: =Horaire!E30 -> 0.76041667 | C25: =Horaire!H30 -> H1 | D25: =VLOOKUP(C25,'Liste chauffeur'!$B$5:$L$19,2,TRUE)&" "&VLOOKUP(C25,'Liste chauffeur'!$B$5:$L$19,3,TRUE) -> CHADHOULI Houmadi | E25: =Horaire!C30 -> DIRECT | F25: =IF(ISBLANK('Feuille saisie'!L49)=TRUE,"",'Feuille saisie'!L49)
A26: =Horaire!A31 -> LA BARGE | B26: =Horaire!E31 -> 0.78125 | C26: =Horaire!H31 -> H1 | D26: =VLOOKUP(C26,'Liste chauffeur'!$B$5:$L$19,2,TRUE)&" "&VLOOKUP(C26,'Liste chauffeur'!$B$5:$L$19,3,TRUE) -> CHADHOULI Houmadi | E26: =Horaire!C31 -> 13 ARRETS | F26: =IF(ISBLANK('Feuille saisie'!L50)=TRUE,"",'Feuille saisie'!L50)
A27: =Horaire!A32 -> CHM | B27: =Horaire!E32 -> 0.78125 | C27: =Horaire!H32 -> H3 | D27: =VLOOKUP(C27,'Liste chauffeur'!$B$5:$L$19,2,TRUE)&" "&VLOOKUP(C27,'Liste chauffeur'!$B$5:$L$19,3,TRUE) -> SAID ALI Kamile | E27: =Horaire!C32 -> DIRECT | F27: =IF(ISBLANK('Feuille saisie'!L51)=TRUE,"",'Feuille saisie'!L51)
A28: =Horaire!A33 -> LA BARGE | B28: =Horaire!E33 -> 0.80208333 | C28: =Horaire!H33 -> H3 | D28: =VLOOKUP(C28,'Liste chauffeur'!$B$5:$L$19,2,TRUE)&" "&VLOOKUP(C28,'Liste chauffeur'!$B$5:$L$19,3,TRUE) -> SAID ALI Kamile | E28: =Horaire!C33 -> 13 ARRETS | F28: =IF(ISBLANK('Feuille saisie'!L52)=TRUE,"",'Feuille saisie'!L52)
A29: =Horaire!A34 -> CRA+CHM | B29: =Horaire!E34 -> 0.80902778 | C29: =Horaire!H34 -> H1 | D29: =VLOOKUP(C29,'Liste chauffeur'!$B$5:$L$19,2,TRUE)&" "&VLOOKUP(C29,'Liste chauffeur'!$B$5:$L$19,3,TRUE) -> CHADHOULI Houmadi | E29: =Horaire!C34 -> DIRECT+CRA | F29: =IF(ISBLANK('Feuille saisie'!L53)=TRUE,"",'Feuille saisie'!L53)
A30: =Horaire!A35 -> LA BARGE | B30: =Horaire!E35 -> 0.82291667 | C30: =Horaire!H35 -> H3 | D30: =VLOOKUP(C30,'Liste chauffeur'!$B$5:$L$19,2,TRUE)&" "&VLOOKUP(C30,'Liste chauffeur'!$B$5:$L$19,3,TRUE) -> SAID ALI Kamile | E30: =Horaire!C35 -> 13 ARRETS | F30: =IF(ISBLANK('Feuille saisie'!L54)=TRUE,"",'Feuille saisie'!L54)

Sheet feuille coordinateur dimanche
A1: COORDINATEUR NAVETTES CHM
A2: Depart | B2: Heure théorique départ | C2: Type chauffeur prévu | D2: Nom chauffeur prévu | E2: Direct/non Direct | F2: Nom Chauffeur réel ( si différent) | G2: Heure réelle départ | H2: Nbre personnes montantes
A3: ='Horaire dimanche2'!A8 -> CHM | B3: ='Horaire dimanche2'!E8 -> 0.23263889 | C3: ='Horaire dimanche2'!H8 -> H1 | D3: =VLOOKUP(C3,'Liste chauffeur'!$B$5:$L$19,2,TRUE)&" "&VLOOKUP(C3,'Liste chauffeur'!$B$5:$L$19,3,TRUE) -> CHADHOULI Houmadi | E3: ='Horaire dimanche2'!C8 -> 13 ARRETS | I3: Observations :
A4: ='Horaire dimanche2'!A9 -> CHM | B4: ='Horaire dimanche2'!E9 -> 0.25 | C4: ='Horaire dimanche2'!H9 -> H3 | D4: =VLOOKUP(C4,'Liste chauffeur'!$B$5:$L$19,2,TRUE)&" "&VLOOKUP(C4,'Liste chauffeur'!$B$5:$L$19,3,TRUE) -> SAID ALI Kamile | E4: ='Horaire dimanche2'!C9 -> 13 ARRETS
A5: ='Horaire dimanche2'!A10 -> CHM | B5: ='Horaire dimanche2'!E10 -> 0.27083333 | C5: ='Horaire dimanche2'!H10 -> H1 | D5: =VLOOKUP(C5,'Liste chauffeur'!$B$5:$L$19,2,TRUE)&" "&VLOOKUP(C5,'Liste chauffeur'!$B$5:$L$19,3,TRUE) -> CHADHOULI Houmadi | E5: ='Horaire dimanche2'!C10 -> 13 ARRETS | I5: Absences :
A6: ='Horaire dimanche2'!A11 -> LA BARGE | B6: ='Horaire dimanche2'!E11 -> 0.27083333 | C6: ='Horaire dimanche2'!H11 -> H3 | D6: =VLOOKUP(C6,'Liste chauffeur'!$B$5:$L$19,2,TRUE)&" "&VLOOKUP(C6,'Liste chauffeur'!$B$5:$L$19,3,TRUE) -> SAID ALI Kamile | E6: ='Horaire dimanche2'!C11 -> DIRECT | F6: =IF(ISBLANK('Feuille saisie'!L12)=TRUE,"",'Feuille saisie'!L12)
A7: ='Horaire dimanche2'!A12 -> CHM | B7: ='Horaire dimanche2'!E12 -> 0.28819444 | C7: ='Horaire dimanche2'!H12 -> H1 | D7: =VLOOKUP(C7,'Liste chauffeur'!$B$5:$L$19,2,TRUE)&" "&VLOOKUP(C7,'Liste chauffeur'!$B$5:$L$19,3,TRUE) -> CHADHOULI Houmadi | E7: ='Horaire dimanche2'!C12 -> DIRECT | F7: =IF(ISBLANK('Feuille saisie'!L13)=TRUE,"",'Feuille saisie'!L13)
A8: ='Horaire dimanche2'!A13 -> LA BARGE | B8: ='Horaire dimanche2'!E13 -> 0.29513889 | C8: ='Horaire dimanche2'!H13 -> H3 | D8: =VLOOKUP(C8,'Liste chauffeur'!$B$5:$L$19,2,TRUE)&" "&VLOOKUP(C8,'Liste chauffeur'!$B$5:$L$19,3,TRUE) -> SAID ALI Kamile | E8: ='Horaire dimanche2'!C13 -> DIRECT | F8: =IF(ISBLANK('Feuille saisie'!L14)=TRUE,"",'Feuille saisie'!L14) | I8: Trajets non effectués :
A9: ='Horaire dimanche2'!A14 -> LA BARGE | B9: ='Horaire dimanche2'!E14 -> 0.3125 | C9: ='Horaire dimanche2'!H14 -> H5 | D9: =VLOOKUP(C9,'Liste chauffeur'!$B$5:$L$19,2,TRUE)&" "&VLOOKUP(C9,'Liste chauffeur'!$B$5:$L$19,3,TRUE) -> ATTOUMANI Kamaldine | E9: ='Horaire dimanche2'!C14 -> DIRECT | F9: =IF(ISBLANK('Feuille saisie'!L15)=TRUE,"",'Feuille saisie'!L15)
A10: ='Horaire dimanche2'!A15 -> LA BARGE | B10: ='Horaire dimanche2'!E15 -> 0.32638889 | C10: ='Horaire dimanche2'!H15 -> H5 | D10: =VLOOKUP(C10,'Liste chauffeur'!$B$5:$L$19,2,TRUE)&" "&VLOOKUP(C10,'Liste chauffeur'!$B$5:$L$19,3,TRUE) -> ATTOUMANI Kamaldine | E10: ='Horaire dimanche2'!C15 -> DIRECT | F10: =IF(ISBLANK('Feuille saisie'!L16)=TRUE,"",'Feuille saisie'!L16) | I10: Signature Coordinateur 1 :
A11: ='Horaire dimanche2'!A16 -> LA BARGE | B11: ='Horaire dimanche2'!E16 -> 0.58333333 | C11: ='Horaire dimanche2'!H16 -> H1 | D11: =VLOOKUP(C11,'Liste chauffeur'!$B$5:$L$19,2,TRUE)&" "&VLOOKUP(C11,'Liste chauffeur'!$B$5:$L$19,3,TRUE) -> CHADHOULI Houmadi | E11: ='Horaire dimanche2'!C16 -> 13 ARRETS | F11: =IF(ISBLANK('Feuille saisie'!L17)=TRUE,"",'Feuille saisie'!L17)
A12: ='Horaire dimanche2'!A17 -> CHM | B12: ='Horaire dimanche2'!E17 -> 0.58333333 | C12: ='Horaire dimanche2'!H17 -> H3 | D12: =VLOOKUP(C12,'Liste chauffeur'!$B$5:$L$19,2,TRUE)&" "&VLOOKUP(C12,'Liste chauffeur'!$B$5:$L$19,3,TRUE) -> SAID ALI Kamile | E12: ='Horaire dimanche2'!C17 -> DIRECT
A13: ='Horaire dimanche2'!A18 -> LA BARGE | B13: ='Horaire dimanche2'!E18 -> 0.61458333 | C13: ='Horaire dimanche2'!H18 -> H1 | D13: =VLOOKUP(C13,'Liste chauffeur'!$B$5:$L$19,2,TRUE)&" "&VLOOKUP(C13,'Liste chauffeur'!$B$5:$L$19,3,TRUE) -> CHADHOULI Houmadi | E13: ='Horaire dimanche2'!C18 -> 13 ARRETS | F13: =IF(ISBLANK('Feuille saisie'!L24)=TRUE,"",'Feuille saisie'!L24)
A14: ='Horaire dimanche2'!A19 -> CHM | B14: ='Horaire dimanche2'!E19 -> 0.625 | C14: ='Horaire dimanche2'!H19 -> H3 | D14: =VLOOKUP(C14,'Liste chauffeur'!$B$5:$L$19,2,TRUE)&" "&VLOOKUP(C14,'Liste chauffeur'!$B$5:$L$19,3,TRUE) -> SAID ALI Kamile | E14: ='Horaire dimanche2'!C19 -> DIRECT | F14: =IF(ISBLANK('Feuille saisie'!L25)=TRUE,"",'Feuille saisie'!L25)
A15: ='Horaire dimanche2'!A20 -> LA BARGE | B15: ='Horaire dimanche2'!E20 -> 0.63888889 | C15: ='Horaire dimanche2'!H20 -> H1 | D15: =VLOOKUP(C15,'Liste chauffeur'!$B$5:$L$19,2,TRUE)&" "&VLOOKUP(C15,'Liste chauffeur'!$B$5:$L$19,3,TRUE) -> CHADHOULI Houmadi | E15: ='Horaire dimanche2'!C20 -> 13 ARRETS | F15: =IF(ISBLANK('Feuille saisie'!L26)=TRUE,"",'Feuille saisie'!L26)
A16: ='Horaire dimanche2'!A21 -> LA BARGE | B16: ='Horaire dimanche2'!E21 -> 0.65972222 | C16: ='Horaire dimanche2'!H21 -> H5 | D16: =VLOOKUP(C16,'Liste chauffeur'!$B$5:$L$19,2,TRUE)&" "&VLOOKUP(C16,'Liste chauffeur'!$B$5:$L$19,3,TRUE) -> ATTOUMANI Kamaldine | E16: ='Horaire dimanche2'!C21 -> 13 ARRETS | F16: =IF(ISBLANK('Feuille saisie'!L27)=TRUE,"",'Feuille saisie'!L27)
A17: ='Horaire dimanche2'!A22 -> LA BARGE | B17: ='Horaire dimanche2'!E22 -> 0.6875 | C17: ='Horaire dimanche2'!H22 -> H5 | D17: =VLOOKUP(C17,'Liste chauffeur'!$B$5:$L$19,2,TRUE)&" "&VLOOKUP(C17,'Liste chauffeur'!$B$5:$L$19,3,TRUE) -> ATTOUMANI Kamaldine | E17: ='Horaire dimanche2'!C22 -> 13 ARRETS | F17: =IF(ISBLANK('Feuille saisie'!L29)=TRUE,"",'Feuille saisie'!L29)
A18: ='Horaire dimanche2'!A23 -> CHM | B18: ='Horaire dimanche2'!E23 -> 0.76041667 | C18: ='Horaire dimanche2'!H23 -> H3 | D18: =VLOOKUP(C18,'Liste chauffeur'!$B$5:$L$19,2,TRUE)&" "&VLOOKUP(C18,'Liste chauffeur'!$B$5:$L$19,3,TRUE) -> SAID ALI Kamile | E18: ='Horaire dimanche2'!C23 -> DIRECT | F18: =IF(ISBLANK('Feuille saisie'!L43)=TRUE,"",'Feuille saisie'!L43)
A19: ='Horaire dimanche2'!A24 -> LA BARGE | B19: ='Horaire dimanche2'!E24 -> 0.76041667 | C19: ='Horaire dimanche2'!H24 -> H5 | D19: =VLOOKUP(C19,'Liste chauffeur'!$B$5:$L$19,2,TRUE)&" "&VLOOKUP(C19,'Liste chauffeur'!$B$5:$L$19,3,TRUE) -> ATTOUMANI Kamaldine | E19: ='Horaire dimanche2'!C24 -> 13 ARRETS | F19: =IF(ISBLANK('Feuille saisie'!L44)=TRUE,"",'Feuille saisie'!L44)
A20: ='Horaire dimanche2'!A25 -> CHM | B20: ='Horaire dimanche2'!E25 -> 0.78125 | C20: ='Horaire dimanche2'!H25 -> H5 | D20: =VLOOKUP(C20,'Liste chauffeur'!$B$5:$L$19,2,TRUE)&" "&VLOOKUP(C20,'Liste chauffeur'!$B$5:$L$19,3,TRUE) -> ATTOUMANI Kamaldine | E20: ='Horaire dimanche2'!C25 -> DIRECT | F20: =IF(ISBLANK('Feuille saisie'!L45)=TRUE,"",'Feuille saisie'!L45)
A21: ='Horaire dimanche2'!A26 -> LA BARGE | B21: ='Horaire dimanche2'!E26 -> 0.78125 | C21: ='Horaire dimanche2'!H26 -> H3 | D21: =VLOOKUP(C21,'Liste chauffeur'!$B$5:$L$19,2,TRUE)&" "&VLOOKUP(C21,'Liste chauffeur'!$B$5:$L$19,3,TRUE) -> SAID ALI Kamile | E21: ='Horaire dimanche2'!C26 -> 13 ARRETS
A22: ='Horaire dimanche2'!A27 -> CRA+CHM | B22: ='Horaire dimanche2'!E27 -> 0.80902778 | C22: ='Horaire dimanche2'!H27 -> H5 | D22: =VLOOKUP(C22,'Liste chauffeur'!$B$5:$L$19,2,TRUE)&" "&VLOOKUP(C22,'Liste chauffeur'!$B$5:$L$19,3,TRUE) -> ATTOUMANI Kamaldine | E22: ='Horaire dimanche2'!C27 -> DIRECT
A23: ='Horaire dimanche2'!A28 -> LA BARGE | B23: ='Horaire dimanche2'!E28 -> 0.82291667 | C23: ='Horaire dimanche2'!H28 -> H5 | D23: =VLOOKUP(C23,'Liste chauffeur'!$B$5:$L$19,2,TRUE)&" "&VLOOKUP(C23,'Liste chauffeur'!$B$5:$L$19,3,TRUE) -> ATTOUMANI Kamaldine | E23: ='Horaire dimanche2'!C28 -> 13 ARRETS

Sheet Feuille présence
B5: Nom chauffeur | C5: Prénom Chauffeur | D5: N° adhérent | E5: N° telephone | F5: Mail | G5: SIRET | H5: Secteur | I5: N° Licence | J5: N° CHAUFFEUR | K5: SIGNATURE | L5: COMMENTAIRES
B6: DAOU LOUNGOU | C6: Zakaria Ismael | D6: 59 | E6: 639647468 | F6: daouloungouzakaria@gmail.com | G6: 066 305 186 000 18 | H6: Petite Terre | I6: 976-PT-055
B7: AHAMADA | C7: Ibrahim | D7: 17 | E7: 06 39 66 58 62 | F7: ahamada.ibrahim1957@gmail.com | G7: 024 062 515 00028 | H7: Petite Terre | I7: 976-PT-007
B8: ATTOUMANI | C8: Kamaldine | D8: 45 | E8: 639666921 | F8: monagelika976@gmail.com | G8: 828 373 431 000 18 | H8: Petite Terre | I8: 976-PT-133 | J8: H5
B9: BACAR ALI | C9: Mohamed | D9: 48 | E9: 783827652 | F9: mohamedbacarali@gmail.com | G9: 066 302 928 000 24 | H9: Petite Terre | I9: 976-PT-050 | J9: H4 | L9: Doit 260€ pour solder son adhésion
B10: CHADHOULI | C10: Houmadi | D10: 54 | E10: 639022970 | F10: houmadi.chadhouli@gmail.com | G10: 054 393 749 000 19 | H10: Petite Terre | I10: 976-PT-026 | J10: H1
B11: CHAMSSOUNE | C11: Ahmed | D11: 56 | E11: 639953545 | F11: Ahmedadel97615@gmail.com | G11: 024 083 602 00029 | H11: Petite Terre | I11: 976-PT-041 | J11: H2
B12: DAHALANE | C12: Youssoufi | D12: 58 | E12: 0693479741 | F12: youssoufidahalane@gmail.com | G12: 054 399 407 000 29 | H12: Petite Terre | I12: 976-PT-076 | L12: Doit 50€ pour solder son adhésion Doit 80€ ( 2 affichettes)
B13: FAKIHI | C13: M'Bouchi | D13: 63 | E13: 0639233680 0693493111 | F13: artisan97615@gmail.com | G13: 881 267 686 00015 | H13: Petite Terre | I13: 976-PT-081
B14: MADI | C14: Hamada Hairoudine | D14: 78 | E14: 639613552 | F14: madihamadahairidine@gmail.com | G14: 066 311 226 00014 | H14: Petite Terre | I14: 976-PT-114 | L14: N'a pas payé son adhésion
B15: HOUMADI | C15: Ibrahim
B16: OIHABOU | C16: Bacari | D16: 95 | E16: 639213701 | F16: oihaboubacari123@gmail.com | G16: 751 080 185 000 18 | H16: Petite Terre | I16: 976-PT-032
B17: AHMED | C17: Abdallah | D17: 22 | E17: 639223900 | F17: taxi.ahmedabdallah@gmail.com | G17: 054 396 627 000 17 | H17: Petite Terre | I17: 976-PT-036
B18: ALI | C18: Mohamed 035 | D18: 29 | E18: 639298042 | F18: alimohamed012c@gmail.com | G18: 099 383 127 00026 | H18: Petite Terre | I18: 976-PT-035 | L18: Doit 120€ ( 3 affichettes)
B19: ALI | C19: Mohamed 120 | D19: 28 | E19: 639729302 | G19: 75295719100014 | H19: Petite Terre | I19: 976-PT-120
B20: HASSANI | C20: Attoumani | D20: 70 | E20: 639396534 | F20: hassaniattoumani1@gmail.com | G20: 498 001 387 00014 | H20: Petite Terre | I20: 976-PT-053
B21: AHMED | C21: Radhuia Rosna | D21: 24 | E21: 639666022 | F21: raduaahmed07@gmail.com | G21: 054 397 039 00014 | H21: Petite Terre | I21: 976-PT-064
B22: SAID | C22: Hedja La France | D22: 101 | E22: 639403811 | F22: saidhedja@hotmail.com | G22: 024 036 485 000 27 | H22: Petite Terre | I22: 976-PT-100
B23: SAID ALI | C23: Kamile | D23: 103 | E23: 06 39 22 01 83 | F23: saidali.kamile976@gmail.com | G23: 752 926 618 000 22 | H23: Petite Terre | I23: 976-PT-124
B24: SAIDI | C24: Ahamadi Abdou | D24: 106 | E24: 639023024 | F24: ahamadi0303@gmail.com | G24: 066 306 549 000 16 | H24: Petite Terre | I24: 976-PT-097

Sheet Liste chauffeur
B4: Type chauffeur | C4: Nom chauffeur | D4: Prénom Chauffeur | E4: N° adhérent | F4: N° telephone | G4: Mail | H4: SIRET | I4: Secteur | J4: N° Licence | K4: N° Carte conducteur | L4: Validité carte conducteur | M4: N° immatriculation | N4: Date première immatriculation | O4: MARQUE | P4: CLIM | Q4: Habillage | R4: Capacité | S4: Modalité facturation | T4: Commentaires
A5: Y | B5: H1 | C5: CHADHOULI | D5: Houmadi | E5: 54 | F5: 639022970 | G5: houmadi.chadhouli@gmail.com | H5: 054 393 749 000 19 | I5: Petite Terre | J5: 976-PT-026 | K5: 127 | L5: 46021 | M5: GT-434-BT | N5: 45278 | O5: RENAULT TRAFIC | P5: OUI | Q5: OUI | R5: 9 | S5: Trajet | T5: Titre de séjour_>2031
A6: Y | B6: H2 | C6: CHAMSSOUNE | D6: Ahmed | E6: 56 | F6: 639953545 | G6: Ahmedadel97615@gmail.com | H6: 024 083 602 00029 | I6: Petite Terre | J6: 976-PT-041 | K6: 444 | L6: 46824 | M6: DV-201-DH | N6: 42236 | O6: OPEL VIVARO | P6: OUI | Q6: NON | R6: 9 | S6: Trajet | T6: Titre de sejour->2025
A7: Y | B7: H3 | C7: SAID ALI | D7: Kamile | E7: 59 | F7: 06 39 22 01 83 | G7: saidali.kamile976@gmail.com | H7: 752 926 618 000 22 | I7: Petite Terre | J7: 976-PT-124 | K7: 501 | L7: 45395 | M7: EF-251-RR | N7: 42643 | O7: RENAULT | P7: OUI | Q7: NON | R7: 8 | S7: Trajet
A8: Y | B8: H4 | C8: BACAR ALI | D8: Mohamed | E8: 48 | F8: 783827652 | G8: mohamedbacarali@gmail.com | H8: 066 302 928 000 24 | I8: Petite Terre | J8: 976-PT-050 | K8: 523 | L8: 46257 | M8: EE-142-DQ | N8: 42576 | O8: RENAULT TRAFIC | P8: OUI | Q8: NON | R8: 9 | S8: Trajet | T8: Doit 260€
A9: Y | B9: H5 | C9: ATTOUMANI | D9: Kamaldine | E9: 45 | F9: 639666921 | G9: monagelika976@gmail.com | H9: 828 373 431 000 18 | I9: Petite Terre | J9: 976-PT-133 | K9: 902 | L9: 45485 | M9: DG-106-XM | N9: 39968 | O9: VOLKSWAGEN TRANSP | P9: OUI | Q9: NON | R9: 9 | S9: Trajet
A10: Y | B10: H6 | C10: MADI | D10: Hamada Hairoudine | E10: 78 | F10: 639613552 | G10: madihamadahairidine@gmail.com | H10: 066 311 226 00014 | I10: Petite Terre | J10: 976-PT-114 | K10: 181 | L10: 45272 | M10: AD-649-QS | N10: 39619 | O10: RENAULT TRAFIC | P10: OUI ? | Q10: NON | R10: 9 | S10: Trajet | T10: RESTE DU: 510€ Clim à vérifier
A11: Y | B11: H7 | C11: OIHABOU | D11: Bacari | E11: 95 | F11: 639213701 | G11: oihaboubacari123@gmail.com | H11: 751 080 185 000 18 | I11: Petite Terre | J11: 976-PT-032 | K11: 170 | L11: 45744 | M11: DX-651-JT | N11: 42173 | O11: RENAULT TRAFIC | P11: OUI | Q11: NON | R11: 9 | S11: Trajet | T11: A partir d'avril
A12: Y | B12: H8 | C12: AHMED | D12: Abdallah | E12: 22 | F12: 639223900 | G12: taxi.ahmedabdallah@gmail.com | H12: 054 396 627 000 17 | I12: Petite Terre | J12: 976-PT-036 | K12: 194 | L12: 44947 | M12: AK-861-JF | N12: 37251 | O12: PEUGEOT | Q12: NON | R12: 9 | S12: Trajet | T12: Voir état véhicule
A13: N | C13: HASSANI | D13: Attoumani | E13: 70 | F13: 639396534 | G13: hassaniattoumani1@gmail.com | H13: 498 001 387 00014 | I13: Petite Terre | J13: 976-PT-053 | K13: 952 | L13: 45395 | M13: DG-919-FP | N13: 39499 | O13: FIAT SCUDO | Q13: NON | R13: 8 | S13: Trajet
A14: N | C14: DAHALANE | D14: Youssoufi | E14: 58 | F14: 0693479741 | G14: youssoufidahalane@gmail.com | H14: 054 399 407 000 29 | I14: Petite Terre | J14: 976PT076 | K14: 391 | L14: 46219 | M14: CJ-429-CN | N14: 41115 | O14: DACIA SANDERO | P14: OUI | Q14: NON | R14: 5 | T14: Doit 250€
A15: N | C15: AHAMADA | D15: Ibrahim | E15: 17 | F15: 06 39 66 58 62 | G15: ahamada.ibrahim1957@gmail.com | H15: 024 062 515 00028 | I15: Petite Terre | J15: 976-PT-007 | K15: 774 | L15: 45753 | M15: GN-673-FP | N15: 45023 | O15: PEUGEOT | Q15: OUI | R15: 5 | S15: Trajet
A16: N | C16: SAID ALI | D16: Kamile | E16: 103 | F16: 06 39 22 01 83 | G16: saidali.kamile976@gmail.com | H16: 752 926 618 000 22 | I16: Petite Terre | J16: 976-PT-124 | K16: 501 | L16: 45395 | M16: CA-755-NZ | N16: 35919 | O16: PEUGEOT | Q16: NON | R16: 8 | S16: Trajet
A17: N | C17: SAIDI | D17: Ahamadi Abdou | E17: 106 | F17: 639023024 | G17: ahamadi0303@gmail.com | H17: 066 306 549 000 16 | I17: Petite Terre | J17: 976-PT-097 | K17: 213 | L17: 44699 | M17: DR-955-ZZ | N17: 37064 | O17: CITROEN EVASION | Q17: NON | R17: 8 | S17: Trajet
C18: ATHMANI | D18: Abdou | E18: 43 | F18: 639392814 | G18: athmani.abdou67@gmail.com | H18: 751 019 860 000 12 | I18: Petite Terre | J18: 976-PT-123 | K18: 901 | L18: 45620 | M18: BT-888-VN | N18: 36376 | Q18: NON | R18: 8 | S18: Trajet | T18: PARTI
A19: N | C19: FAKIHI | D19: M'Bouchi | E19: 63 | F19: 0639233680 0693493111 | G19: artisan97615@gmail.com | H19: 881 267 686 00015 | I19: Petite Terre | J19: 976-PT-081 | K19: 663 | L19: 46770 | M19: CW-054-BG | N19: 37244 | O19: PEUGEOT | Q19: NON | R19: 7 | S19: Trajet | T19: DOIT 200€
C20: ABDOULHAFFOUR | D20: Mohamed | E20: 11 | F20: 639194023 | G20: mohamed.abdoulhaffour@orange.fr | H20: 501 023 444 000 18 | I20: Petite Terre
A21: N | C21: ALI | D21: Mohamed 120 | E21: 28 | F21: 639729302 | H21: 75295719100014 | I21: Petite Terre | J21: 976-PT-120 | K21: 784 | L21: 46835 | M21: EG-086-GF | N21: 42668 | O21: RENAULT TRAFIC | Q21: NON | R21: 9
A22: N | C22: SAID | D22: Hedja La France | E22: 101 | F22: 639403811 | G22: saidhedja@hotmail.com | H22: 024 036 485 000 27 | I22: Petite Terre | J22: 976PT100 | K22: 472 | L22: 46909 | M22: GP464EE | N22: 45076 | O22: KIA | P22: OUI | Q22: OUI | R22: 5
B23: H17 | C23: AHAMADA | D23: Assoumani | E23: 16 | I23: Petite Terre | J23: 976-PT-002 | M23: EF-006-YC | N23: 37950 | R23: 9 | T23: NON ACTION
B24: H18 | C24: HAMADA | D24: Abdallah | E24: 65 | I24: Petite Terre | J24: 976-PT-122 | M24: EP-581-HZ | N24: 38126 | R24: 9 | T24: NON ACTION
B25: H19 | C25: HAMISSI | D25: Selemani | E25: 68 | I25: Petite Terre | J25: 976-PT-017 | M25: ED-484-NV | N25: 42550 | R25: 9 | T25: NON ACTION
B26: H20 | C26: MBIAVOU | D26: Ismael | E26: 83 | I26: Petite Terre | J26: 976-PT-003 | M26: GD-071-AV | N26: 44519 | R26: 9 | T26: NON ACTION
B27: H21 | C27: SANDA | D27: Mahamoud | E27: 108 | I27: Petite Terre | J27: 976-PT-042 | M27: AF-455-RR | N27: 36210 | R27: 9 | T27: NON ACTION
A28: NON | C28: AHMED | D28: Radhuia Rosna | E28: 24 | F28: 639666022 | G28: raduaahmed07@gmail.com | H28: 054 397 039 00014 | I28: Petite Terre | J28: 976-PT-064 | K28: 1261 | L28: 45600 | M28: GD-631-HT | N28: 44533 | O28: PEUGEOT | Q28: OUI | R28: 5 | S28: Trajet
A29: ? | C29: ALI | D29: Mohamed 035 | E29: 29 | F29: 639298042 | G29: alimohamed012c@gmail.com | H29: 099 383 127 00026 | I29: Petite Terre | J29: 976-PT-035 | K29: 182 | L29: 46387 | M29: FJ-982-GV AG-146-AG | N29: 01/08/2019 20/04/2006 | O29: RENAULT | Q29: NON | R29: 8 5 | S29: Trajet | T29: Quel véhicule ?

Sheet Horaire par chauffeur
B2: NAVETTES CADEMA- HORAIRES DECEMBRE
A3: C1 MARDI NAVETTE
A4: C1 | B4: =VLOOKUP(A4,'Liste chauffeur'!$B$5:$L$19,2,TRUE)&" "&VLOOKUP(A4,'Liste chauffeur'!$B$5:$L$19,3,TRUE) -> #N/A | E4: C2 | F4: =VLOOKUP(E4,'Liste chauffeur'!$B$5:$L$19,2,TRUE)&" "&VLOOKUP(E4,'Liste chauffeur'!$B$5:$L$19,3,TRUE) -> #N/A | I4: Heure réelle départ | J4: Nbre personnes montantes | K4: Commentaires | M4: Astreinte 1 | N4: Astreinte 2
A5: VAHIBE | B5: 0.1875 | E5: VAHIBE | F5: 0.22222222
A6: VAHIBE | B6: 0.22222222 | E6: VAHIBE | F6: 0.26388889 | G6: 5 tr.
A7: VAHIBE | B7: 0.26388889 | C7: 5 tr | E7: VAHIBE | F7: 0.31944444 | G7: =F7+#REF!-F5+#REF!+#REF!-F9 -> #REF! | M7: C16 | N7: C11
A8: VAHIBE | B8: 0.31944444 | E8: PEM PASSAMAINTY | F8: 0.58333333 | M8: C16 | N8: C11
A9: PEM PASSAMAINTY | B9: 0.77083333 | E9: PEM PASSAMAINTY | F9: 0.61805556 | M9: C16 | N9: C11
E11: C5 MARDI NAVETTE | M11: C16 | N11: C11
A12: C4 | B12: =VLOOKUP(A12,'Liste chauffeur'!$B$5:$L$19,2,TRUE)&" "&VLOOKUP(A12,'Liste chauffeur'!$B$5:$L$19,3,TRUE) -> #N/A | E12: C5 | F12: =VLOOKUP(E12,'Liste chauffeur'!$B$5:$L$19,2,TRUE)&" "&VLOOKUP(E12,'Liste chauffeur'!$B$5:$L$19,3,TRUE) -> #N/A | M12: C16 | N12: C11
A13: VAHIBE 2 | B13: 0.25 | E13: VAHIBE | F13: 0.25694444 | M13: C16 | N13: C11
A14: VAHIBE | B14: 0.29861111 | C14: 5 tr | E14: VAHIBE | F14: 0.3125
A15: VAHIBE | B15: 0.36805556 | C15: =B15-B13+#REF!+B17+#REF!-B16 -> #REF! | E15: PEM PASSAMAINTY | F15: 0.6875 | G15: 5 tr
A16: PEM PASSAMAINTY | B16: 0.625 | E16: PEM PASSAMAINTY | F16: 0.72222222
A17: PEM PASSAMAINTY | B17: 0.65972222 | E17: PEM PASSAMAINTY | F17: 0.75
E19: C8 MERCREDI NAVETTE
A20: C22 | B20: =VLOOKUP(A20,'Liste chauffeur'!$B$5:$L$19,2,TRUE)&" "&VLOOKUP(A20,'Liste chauffeur'!$B$5:$L$19,3,TRUE) -> #N/A | E20: C8 | F20: =VLOOKUP(E20,'Liste chauffeur'!$B$5:$L$19,2,TRUE)&" "&VLOOKUP(E20,'Liste chauffeur'!$B$5:$L$19,3,TRUE) -> #N/A
A21: VAHIBE 2 | B21: 0.20833333 | C21: 5 tr | E21: VAHIBE 2 | F21: 0.22916667
A22: VAHIBE | B22: 0.24305556 | C22: =B23+#REF!-B21+B25+#REF!-B24 -> #REF! | E22: VAHIBE 2 | F22: 0.27083333 | G22: =F22+G2-F21+F24+#REF!-F23 -> #REF!
A23: VAHIBE | B23: 0.29166667 | E23: VAHIBE | F23: 0.32638889
A24: PEM PASSAMAINTY | B24: 0.61111111 | E24: PEM PASSAMAINTY | F24: 0.67361111 | G24: 5 tr
A25: PEM PASSAMAINTY | B25: 0.65277778 | E25: PEM PASSAMAINTY | F25: 0.70138889 | G25: =F23+#REF!-F21+F25+#REF!-#REF! -> #REF!
E27: C13 | F27: =VLOOKUP(E27,'Liste chauffeur'!$B$5:$L$19,2,TRUE)&" "&VLOOKUP(E27,'Liste chauffeur'!$B$5:$L$19,3,TRUE) -> #N/A
A28: C9 | B28: =VLOOKUP(A28,'Liste chauffeur'!$B$5:$L$19,2,TRUE)&" "&VLOOKUP(A28,'Liste chauffeur'!$B$5:$L$19,3,TRUE) -> #N/A | C28: =#REF!+G2-B30+B33+#REF!-B31 -> #REF! | F28: Heure théorique départ
A29: VAHIBE | B29: 0.21527778 | E29: VAHIBE | F29: 0.20138889
A30: VAHIBE | B30: 0.28472222 | C30: 5 tr | E30: VAHIBE | F30: 0.22916667 | G30: 5 tr
A31: PEM PASSAMAINTY | B31: 0.60416667 | E31: VAHIBE | F31: 0.27777778 | G31: =F31+#REF!-F29+F33+#REF!-F32 -> #REF!
A32: PEM PASSAMAINTY | B32: 0.63194444 | E32: PEM PASSAMAINTY | F32: 0.65972222
A33: PEM PASSAMAINTY | B33: 0.68055556 | E33: PEM PASSAMAINTY | F33: 0.6875
A35: C15 JEUDI NAVETTE
A36: C15 | B36: =VLOOKUP(A36,'Liste chauffeur'!$B$5:$L$19,2,TRUE)&" "&VLOOKUP(A36,'Liste chauffeur'!$B$5:$L$19,3,TRUE) -> #N/A | E36: C17 | F36: =VLOOKUP(E36,'Liste chauffeur'!$B$5:$L$19,2,TRUE)&" "&VLOOKUP(E36,'Liste chauffeur'!$B$5:$L$19,3,TRUE) -> #N/A
A37: VAHIBE | B37: 0.27083333 | F37: Heure théorique départ
A38: VAHIBE | B38: 0.32638889 | C38: 5 tr | E38: VAHIBE | F38: 0.22916667 | G38: 4 tr.
A39: PEM PASSAMAINTY | B39: 0.63194444 | C39: =B38+#REF!-B37+B41+#REF!-B39 -> #REF! | E39: VAHIBE | F39: 0.29861111
A40: PEM PASSAMAINTY | B40: 0.66666667 | E40: VAHIBE | F40: 0.34027778
A41: PEM PASSAMAINTY | B41: 0.69444444 | E41: PEM PASSAMAINTY | F41: 0.59722222
A44: C19 | B44: =VLOOKUP(A44,'Liste chauffeur'!$B$5:$L$19,2,TRUE)&" "&VLOOKUP(A44,'Liste chauffeur'!$B$5:$L$19,3,TRUE) -> #N/A | E44: C20 | F44: =VLOOKUP(E44,'Liste chauffeur'!$B$5:$L$19,2,TRUE)&" "&VLOOKUP(E44,'Liste chauffeur'!$B$5:$L$19,3,TRUE) -> #N/A
A45: VAHIBE | B45: 0.23611111 | E45: VAHIBE | F45: 0.23611111 | G45: =#REF!+G2-#REF!+F48+#REF!-F45 -> #REF!
A46: VAHIBE | B46: 0.28472222 | C46: 5 tr | E46: PEM PASSAMAINTY | F46: 0.64583333 | G46: 4 tr.
A47: VAHINE | B47: 0.36111111 | C47: =B47+#REF!-B45+B49+B3-B48 -> #REF! | E47: PEM PASSAMAINTY | F47: 0.70138889
A48: PEM PASSAMAINTY | B48: 0.68055556 | E48: PEM PASSAMAINTY | F48: 0.74305556
A49: PEM PASSAMAINTY | B49: 0.70833333
A51: C23 JEUDI NAVETTE | E51: C24 | F51: =VLOOKUP(E51,'Liste chauffeur'!$B$5:$L$19,2,TRUE)&" "&VLOOKUP(E51,'Liste chauffeur'!$B$5:$L$19,3,TRUE) -> #N/A
A52: C23 | B52: =VLOOKUP(A52,'Liste chauffeur'!$B$5:$L$19,2,TRUE)&" "&VLOOKUP(A52,'Liste chauffeur'!$B$5:$L$19,3,TRUE) -> #N/A | E52: VAHIBE | F52: 0.20833333
A53: VAHIBE | B53: 0.27777778 | E53: VAHIBE | F53: 0.25 | G53: 5 tr
A54: VAHIBE | B54: 0.33333333 | C54: 6 tr | E54: VAHIBE | F54: 0.3125
A55: PEM PASSAMAINTY | B55: 0.65277778 | C55: =B54+#REF!-#REF!+B58+#REF!-B55 -> #REF! | E55: PEM PASSAMAINTY | F55: 0.63888889 | G55: =F55+#REF!-F52+#REF!+#REF!-F56 -> #REF!
A56: PEM PASSAMAINTY | B56: 0.69444444 | E56: PEM PASSAMAINTY | F56: 0.66666667
A57: PEM PASSAMAINTY | B57: 0.72916667
A58: PEM PASSAMAINTY | B58: 0.76388889 | E58: C27 LUNDI NAVETTE
E59: C27 | F59: =VLOOKUP(E59,'Liste chauffeur'!$B$5:$L$19,2,TRUE)&" "&VLOOKUP(E59,'Liste chauffeur'!$B$5:$L$19,3,TRUE) -> #N/A
E60: VAHIBE | F60: 0.24305556
A61: C26 | B61: =VLOOKUP(A61,'Liste chauffeur'!$B$5:$L$19,2,TRUE)&" "&VLOOKUP(A61,'Liste chauffeur'!$B$5:$L$19,3,TRUE) -> #N/A | E61: VAHIBE | F61: 0.29166667
A62: VAHIBE | B62: 0.21527778 | E62: VAHINE | F62: 0.34722222
A63: VAHIBE | B63: 0.27083333 | E63: PEM PASSAMAINTY | F63: 0.59027778 | G63: =F61+#REF!-F60+F64+C12-F62 -> #REF!
A64: VAHIBE | B64: 0.33333333 | C64: 5 tr | E64: PEM PASSAMAINTY | F64: 0.625
A65: PEM PASSAMAINTY | B65: 0.73611111 | C65: =B64+#REF!-B63+#REF!+#REF!-B65 -> #REF! | G65: 5 tr
A66: PEM PASSAMAINTY | B66: 0.77083333 | G66: =F62+#REF!-F60+F64+#REF!-F63 -> #REF!
A68: C28 VENDREDI NAVETTE
A69: C28 | B69: =VLOOKUP(A69,'Liste chauffeur'!$B$5:$L$19,2,TRUE)&" "&VLOOKUP(A69,'Liste chauffeur'!$B$5:$L$19,3,TRUE) -> #N/A | E69: C11 | F69: =VLOOKUP(E69,'Liste chauffeur'!$B$5:$L$19,2,TRUE)&" "&VLOOKUP(E69,'Liste chauffeur'!$B$5:$L$19,3,TRUE) -> #N/A
A70: VAHIBE | B70: 0.20833333 | E70: VAHIBE | F70: 0.19444444
A71: VAHIBE | B71: 0.25 | E71: VAHIBE | F71: 0.25694444
A72: VAHIBE | B72: 0.30555556 | C72: 6 tr | E72: VAHIBE | F72: 0.30555556 | G72: 5 tr
A73: VAHIBE | B73: 0.35416667 | E73: PEM PASSAMAINTY | F73: 0.64583333 | G73: =F72+#REF!-F70+F74+#REF!-F73 -> #REF!
A74: PEM PASSAMAINTY | B74: 0.71527778 | C74: =B72+#REF!-B70+B75+#REF!-B74 -> #REF! | E74: PEM PASSAMAINTY | F74: 0.67361111
A75: PEM PASSAMAINTY | B75: 0.75694444

Sheet Horaire
K1: ,
A3: DATE | F3: 0.013888889 | I3: NOVEMBRE
A4: CHAUFFEUR | F4: 0.017361111
F5: 0.0090277778
A7: DEPART | B7: ARRIVEE | C7: DIRECT/ AVEC ARRET | D7: N° LIGNE | E7: Heure théorique départ | F7: Temps théorique | G7: Heure arrivée théorique | H7: Type chauffeur prévu | I7: Nom chauffeur prévu | J7: Nbre trajets | K7: Delai entre 2 départs | L7: Délai avant | M7: Astreinte 1 | N7: Nom Chauffeur astreinte 1 | O7: Astreinte 2 | P7: Nom Chauffeur astreinte 2 | Q7: Heure réelle départ | R7: Nbre personnes + | S7: Commentaires
A8: CHM | B8: LA BARGE | C8: 13 ARRETS | D8: L1 | E8: 0.23263889 | F8: =IF(C8="DIRECT",F$5,F$4) -> 0.017361111 | G8: =E8+F8 -> 0.25 | H8: H1 | I8: =VLOOKUP(H8,'Liste chauffeur'!$B$5:$L$19,2,TRUE)&" "&VLOOKUP(H8,'Liste chauffeur'!$B$5:$L$19,3,TRUE) -> CHADHOULI Houmadi | J8: 1 | K8: =E11-G8 -> 0.020833333
A9: LA BARGE | B9: CHM | C9: 13 ARRETS | E9: 0.23958333 | F9: =IF(C9="DIRECT",F$5,F$4) -> 0.017361111 | G9: =E9+F9 -> 0.25694444 | H9: H5 | I9: =VLOOKUP(H9,'Liste chauffeur'!$B$5:$L$19,2,TRUE)&" "&VLOOKUP(H9,'Liste chauffeur'!$B$5:$L$19,3,TRUE) -> ATTOUMANI Kamaldine | K9: =E13-G9 -> 0.013888889
A10: CHM | B10: LA BARGE | C10: 13 ARRETS | E10: 0.25 | F10: =IF(C10="DIRECT",F$5,F$4) -> 0.017361111 | G10: =E10+F10 -> 0.26736111 | H10: H3 | I10: =VLOOKUP(H10,'Liste chauffeur'!$B$5:$L$19,2,TRUE)&" "&VLOOKUP(H10,'Liste chauffeur'!$B$5:$L$19,3,TRUE) -> SAID ALI Kamile | K10: =E12-G10 -> 0.0034722222
A11: CHM | B11: LA BARGE | C11: 13 ARRETS | E11: 0.27083333 | F11: =IF(C11="DIRECT",F$5,F$4) -> 0.017361111 | G11: =E11+F11 -> 0.28819444 | H11: H1 | I11: =VLOOKUP(H11,'Liste chauffeur'!$B$5:$L$19,2,TRUE)&" "&VLOOKUP(H11,'Liste chauffeur'!$B$5:$L$19,3,TRUE) -> CHADHOULI Houmadi | K11: =E14-G11 -> 0
A12: LA BARGE | B12: CHM | C12: DIRECT | D12: L1 | E12: 0.27083333 | F12: =IF(C12="DIRECT",F$5,F$4) -> 0.0090277778 | G12: =E12+F12 -> 0.27986111 | H12: H3 | I12: =VLOOKUP(H12,'Liste chauffeur'!$B$5:$L$19,2,TRUE)&" "&VLOOKUP(H12,'Liste chauffeur'!$B$5:$L$19,3,TRUE) -> SAID ALI Kamile | J12: 2 | K12: =E16-G12 -> 0.015277778
A13: LA BARGE | B13: CHM+CRA | C13: DIRECT+CRA | D13: L2 | E13: 0.27083333 | F13: =F3 -> 0.013888889 | G13: =E13+F13 -> 0.28472222 | H13: H5 | I13: =VLOOKUP(H13,'Liste chauffeur'!$B$5:$L$19,2,TRUE)&" "&VLOOKUP(H13,'Liste chauffeur'!$B$5:$L$19,3,TRUE) -> ATTOUMANI Kamaldine | J13: 3 | K13: =E15-G13 -> 0
A14: CHM | B14: LA BARGE | C14: DIRECT | E14: 0.28819444 | F14: =IF(C14="DIRECT",F$5,F$4) -> 0.0090277778 | G14: =E14+F14 -> 0.29722222 | H14: H1 | I14: =VLOOKUP(H14,'Liste chauffeur'!$B$5:$L$19,2,TRUE)&" "&VLOOKUP(H14,'Liste chauffeur'!$B$5:$L$19,3,TRUE) -> CHADHOULI Houmadi | K14: =E19-G14 -> 0.029166667
A15: CHM | B15: LA BARGE | C15: DIRECT | D15: L1 | E15: 0.28472222 | F15: =IF(C15="DIRECT",F$5,F$4) -> 0.0090277778 | G15: =E15+F15 -> 0.29375 | H15: H5 | I15: =VLOOKUP(H15,'Liste chauffeur'!$B$5:$L$19,2,TRUE)&" "&VLOOKUP(H15,'Liste chauffeur'!$B$5:$L$19,3,TRUE) -> ATTOUMANI Kamaldine | J15: 2 | K15: =E17-G15 -> 0.01875
A16: LA BARGE | B16: CHM+CRA | C16: DIRECT+CRA | D16: L1 | E16: 0.29513889 | F16: =IF(C16="DIRECT",F$5,F$4) -> 0.017361111 | G16: =E16+F16 -> 0.3125 | H16: H3 | I16: =VLOOKUP(H16,'Liste chauffeur'!$B$5:$L$19,2,TRUE)&" "&VLOOKUP(H16,'Liste chauffeur'!$B$5:$L$19,3,TRUE) -> SAID ALI Kamile | J16: 4
A17: LA BARGE | B17: CHM | C17: DIRECT | D17: L1 | E17: 0.3125 | F17: =IF(C17="DIRECT",F$5,F$4) -> 0.0090277778 | G17: =E17+F17 -> 0.32152778 | H17: H5 | I17: =VLOOKUP(H17,'Liste chauffeur'!$B$5:$L$19,2,TRUE)&" "&VLOOKUP(H17,'Liste chauffeur'!$B$5:$L$19,3,TRUE) -> ATTOUMANI Kamaldine | J17: 3 | K17: =E18-G17 -> 0.0048611111
A18: CHM | B18: LA BARGE | C18: DIRECT | D18: L1 | E18: 0.32638889 | F18: =IF(C18="DIRECT",F$5,F$4) -> 0.0090277778 | G18: =E18+F18 -> 0.33541667 | H18: H5 | I18: =VLOOKUP(H18,'Liste chauffeur'!$B$5:$L$19,2,TRUE)&" "&VLOOKUP(H18,'Liste chauffeur'!$B$5:$L$19,3,TRUE) -> ATTOUMANI Kamaldine | J18: 3
A19: LA BARGE | B19: CHM | C19: DIRECT | D19: L1 | E19: 0.32638889 | F19: =IF(C19="DIRECT",F$5,F$4) -> 0.0090277778 | G19: =E19+F19 -> 0.33541667 | H19: H1 | I19: =VLOOKUP(H19,'Liste chauffeur'!$B$5:$L$19,2,TRUE)&" "&VLOOKUP(H19,'Liste chauffeur'!$B$5:$L$19,3,TRUE) -> CHADHOULI Houmadi | J19: 3
A20: LA BARGE | B20: CHM | C20: 13 ARRETS | E20: 0.58333333 | F20: =IF(C20="DIRECT",F$5,F$4) -> 0.017361111 | G20: =E20+F20 -> 0.60069444 | H20: H1 | I20: =VLOOKUP(H20,'Liste chauffeur'!$B$5:$L$19,2,TRUE)&" "&VLOOKUP(H20,'Liste chauffeur'!$B$5:$L$19,3,TRUE) -> CHADHOULI Houmadi | K20: =E22-G20 -> 0.013888889
A21: CHM | B21: LA BARGE | C21: DIRECT | D21: L2 | E21: 0.58333333 | F21: =IF(C21="DIRECT",F$5,F$4) -> 0.0090277778 | G21: =E21+F21 -> 0.59236111 | H21: H3 | I21: =VLOOKUP(H21,'Liste chauffeur'!$B$5:$L$19,2,TRUE)&" "&VLOOKUP(H21,'Liste chauffeur'!$B$5:$L$19,3,TRUE) -> SAID ALI Kamile | J21: 4 | K21: =E23-G21 -> 0.025694444
A22: LA BARGE | B22: CHM | C22: 13 ARRETS | E22: 0.61458333 | F22: =IF(C22="DIRECT",F$5,F$4) -> 0.017361111 | G22: =E22+F22 -> 0.63194444 | H22: H1 | I22: =VLOOKUP(H22,'Liste chauffeur'!$B$5:$L$19,2,TRUE)&" "&VLOOKUP(H22,'Liste chauffeur'!$B$5:$L$19,3,TRUE) -> CHADHOULI Houmadi | K22: =E25-G22 -> 0.0069444444
A23: LA BARGE | B23: CHM | C23: 13 ARRETS | E23: 0.61805556 | F23: =IF(C23="DIRECT",F$5,F$4) -> 0.017361111 | G23: =E23+F23 -> 0.63541667 | H23: H3 | I23: =VLOOKUP(H23,'Liste chauffeur'!$B$5:$L$19,2,TRUE)&" "&VLOOKUP(H23,'Liste chauffeur'!$B$5:$L$19,3,TRUE) -> SAID ALI Kamile
A24: CHM | B24: LA BARGE | C24: DIRECT | E24: 0.625 | F24: =IF(C24="DIRECT",F$5,F$4) -> 0.0090277778 | G24: =E24+F24 -> 0.63402778 | H24: H5 | I24: =VLOOKUP(H24,'Liste chauffeur'!$B$5:$L$19,2,TRUE)&" "&VLOOKUP(H24,'Liste chauffeur'!$B$5:$L$19,3,TRUE) -> ATTOUMANI Kamaldine | K24: =E26-G24 -> 0.025694444
A25: LA BARGE | B25: CHM | C25: 13 ARRETS | E25: 0.63888889 | F25: =IF(C25="DIRECT",F$5,F$4) -> 0.017361111 | G25: =E25+F25 -> 0.65625 | H25: H1 | I25: =VLOOKUP(H25,'Liste chauffeur'!$B$5:$L$19,2,TRUE)&" "&VLOOKUP(H25,'Liste chauffeur'!$B$5:$L$19,3,TRUE) -> CHADHOULI Houmadi
A26: LA BARGE | B26: CHM | C26: 13 ARRETS | E26: 0.65972222 | F26: =IF(C26="DIRECT",F$5,F$4) -> 0.017361111 | G26: =E26+F26 -> 0.67708333 | H26: H5 | I26: =VLOOKUP(H26,'Liste chauffeur'!$B$5:$L$19,2,TRUE)&" "&VLOOKUP(H26,'Liste chauffeur'!$B$5:$L$19,3,TRUE) -> ATTOUMANI Kamaldine | K26: =E27-G26 -> 0.010416667
A27: LA BARGE | B27: CHM | C27: 13 ARRETS | E27: 0.6875 | F27: =IF(C27="DIRECT",F$5,F$4) -> 0.017361111 | G27: =E27+F27 -> 0.70486111 | H27: H5 | I27: =VLOOKUP(H27,'Liste chauffeur'!$B$5:$L$19,2,TRUE)&" "&VLOOKUP(H27,'Liste chauffeur'!$B$5:$L$19,3,TRUE) -> ATTOUMANI Kamaldine | K27: =E28-G27 -> 0.0069444444
A28: LA BARGE | B28: CHM | C28: 13 ARRETS | E28: 0.71180556 | F28: =IF(C28="DIRECT",F$5,F$4) -> 0.017361111 | G28: =E28+F28 -> 0.72916667 | H28: H5 | I28: =VLOOKUP(H28,'Liste chauffeur'!$B$5:$L$19,2,TRUE)&" "&VLOOKUP(H28,'Liste chauffeur'!$B$5:$L$19,3,TRUE) -> ATTOUMANI Kamaldine
A29: LA BARGE | B29: CHM | C29: DIRECT | D29: L1 | E29: 0.76041667 | F29: =IF(C29="DIRECT",F$5,F$4) -> 0.0090277778 | G29: =E29+F29 -> 0.76944444 | H29: H3 | I29: =VLOOKUP(H29,'Liste chauffeur'!$B$5:$L$19,2,TRUE)&" "&VLOOKUP(H29,'Liste chauffeur'!$B$5:$L$19,3,TRUE) -> SAID ALI Kamile | J29: 6 | K29: =E32-G29 -> 0.011805556
A30: CHM | B30: LA BARGE | C30: DIRECT | E30: 0.76041667 | F30: =IF(C30="DIRECT",F$5,F$4) -> 0.0090277778 | G30: =E30+F30 -> 0.76944444 | H30: H1 | I30: =VLOOKUP(H30,'Liste chauffeur'!$B$5:$L$19,2,TRUE)&" "&VLOOKUP(H30,'Liste chauffeur'!$B$5:$L$19,3,TRUE) -> CHADHOULI Houmadi
A31: LA BARGE | B31: CHM | C31: 13 ARRETS | E31: 0.78125 | F31: =IF(C31="DIRECT",F$5,F$4) -> 0.017361111 | G31: =E31+F31 -> 0.79861111 | H31: H1 | I31: =VLOOKUP(H31,'Liste chauffeur'!$B$5:$L$19,2,TRUE)&" "&VLOOKUP(H31,'Liste chauffeur'!$B$5:$L$19,3,TRUE) -> CHADHOULI Houmadi
A32: CHM | B32: LA BARGE | C32: DIRECT | E32: 0.78125 | F32: =IF(C32="DIRECT",F$5,F$4) -> 0.0090277778 | G32: =E32+F32 -> 0.79027778 | H32: H3 | I32: =VLOOKUP(H32,'Liste chauffeur'!$B$5:$L$19,2,TRUE)&" "&VLOOKUP(H32,'Liste chauffeur'!$B$5:$L$19,3,TRUE) -> SAID ALI Kamile | K32: =E34-G32 -> 0.01875
A33: LA BARGE | B33: CHM | C33: 13 ARRETS | E33: 0.80208333 | F33: =IF(C33="DIRECT",F$5,F$4) -> 0.017361111 | G33: =E33+F33 -> 0.81944444 | H33: H3 | I33: =VLOOKUP(H33,'Liste chauffeur'!$B$5:$L$19,2,TRUE)&" "&VLOOKUP(H33,'Liste chauffeur'!$B$5:$L$19,3,TRUE) -> SAID ALI Kamile
A34: CRA+CHM | B34: LA BARGE | C34: DIRECT+CRA | D34: L1 | E34: 0.80902778 | F34: 0.0090277778 | G34: =E34+F34 -> 0.81805556 | H34: H1 | I34: =VLOOKUP(H34,'Liste chauffeur'!$B$5:$L$19,2,TRUE)&" "&VLOOKUP(H34,'Liste chauffeur'!$B$5:$L$19,3,TRUE) -> CHADHOULI Houmadi | J34: 5
A35: LA BARGE | B35: CHM | C35: 13 ARRETS | E35: 0.82291667 | F35: =IF(C35="DIRECT",F$5,F$4) -> 0.017361111 | G35: =E35+F35 -> 0.84027778 | H35: H3 | I35: =VLOOKUP(H35,'Liste chauffeur'!$B$5:$L$19,2,TRUE)&" "&VLOOKUP(H35,'Liste chauffeur'!$B$5:$L$19,3,TRUE) -> SAID ALI Kamile
F37: =SUBTOTAL(9,F8:F36) -> 0.38263889 | K37: =SUBTOTAL(9,K8:K36) -> 0.22638889
N38: Signature Coordinateur 2

Sheet Horaire dimanche2
K1: ,
A3: DATE | F3: 0.013888889 | I3: NOVEMBRE
A4: CHAUFFEUR | F4: 0.013888889
F5: 0.0083333333
A7: DEPART | B7: ARRIVEE | C7: DIRECT/ AVEC ARRET | D7: N° LIGNE | E7: Heure théorique départ | F7: Temps théorique | G7: Heure arrivée théorique | H7: Type chauffeur prévu | I7: Nom chauffeur prévu | J7: Nbre trajets | K7: Delai entre 2 départs | L7: Délai avant | M7: Astreinte 1 | N7: Nom Chauffeur astreinte 1 | O7: Astreinte 2 | P7: Nom Chauffeur astreinte 2 | Q7: Heure réelle départ | R7: Nbre personnes + | S7: Commentaires
A8: CHM | B8: LA BARGE | C8: 13 ARRETS | D8: L1 | E8: 0.23263889 | F8: =IF(C8="DIRECT",F$5,F$4) -> 0.013888889 | G8: =E8+F8 -> 0.24652778 | H8: H1 | I8: =VLOOKUP(H8,'Liste chauffeur'!$B$5:$L$19,2,TRUE)&" "&VLOOKUP(H8,'Liste chauffeur'!$B$5:$L$19,3,TRUE) -> CHADHOULI Houmadi | J8: 1 | K8: =E10-G8 -> 0.024305556
A9: CHM | B9: LA BARGE | C9: 13 ARRETS | E9: 0.25 | F9: =IF(C9="DIRECT",F$5,F$4) -> 0.013888889 | G9: =E9+F9 -> 0.26388889 | H9: H3 | I9: =VLOOKUP(H9,'Liste chauffeur'!$B$5:$L$19,2,TRUE)&" "&VLOOKUP(H9,'Liste chauffeur'!$B$5:$L$19,3,TRUE) -> SAID ALI Kamile | K9: =E11-G9 -> 0.0069444444
A10: CHM | B10: LA BARGE | C10: 13 ARRETS | E10: 0.27083333 | F10: =IF(C10="DIRECT",F$5,F$4) -> 0.013888889 | G10: =E10+F10 -> 0.28472222 | H10: H1 | I10: =VLOOKUP(H10,'Liste chauffeur'!$B$5:$L$19,2,TRUE)&" "&VLOOKUP(H10,'Liste chauffeur'!$B$5:$L$19,3,TRUE) -> CHADHOULI Houmadi | K10: =E12-G10 -> 0.0034722222
A11: LA BARGE | B11: CHM | C11: DIRECT | D11: L1 | E11: 0.27083333 | F11: =IF(C11="DIRECT",F$5,F$4) -> 0.0083333333 | G11: =E11+F11 -> 0.27916667 | H11: H3 | I11: =VLOOKUP(H11,'Liste chauffeur'!$B$5:$L$19,2,TRUE)&" "&VLOOKUP(H11,'Liste chauffeur'!$B$5:$L$19,3,TRUE) -> SAID ALI Kamile | J11: 2 | K11: =E13-G11 -> 0.015972222
A12: CHM | B12: LA BARGE | C12: DIRECT | E12: 0.28819444 | F12: =IF(C12="DIRECT",F$5,F$4) -> 0.0083333333 | G12: =E12+F12 -> 0.29652778 | H12: H1 | I12: =VLOOKUP(H12,'Liste chauffeur'!$B$5:$L$19,2,TRUE)&" "&VLOOKUP(H12,'Liste chauffeur'!$B$5:$L$19,3,TRUE) -> CHADHOULI Houmadi | K12: =E15-G12 -> 0.029861111
A13: LA BARGE | B13: CHM+CRA | C13: DIRECT | D13: L1 | E13: 0.29513889 | F13: =IF(C13="DIRECT",F$5,F$4) -> 0.0083333333 | G13: =E13+F13 -> 0.30347222 | H13: H3 | I13: =VLOOKUP(H13,'Liste chauffeur'!$B$5:$L$19,2,TRUE)&" "&VLOOKUP(H13,'Liste chauffeur'!$B$5:$L$19,3,TRUE) -> SAID ALI Kamile | J13: 4
A14: LA BARGE | B14: CHM | C14: DIRECT | D14: L1 | E14: 0.3125 | F14: =IF(C14="DIRECT",F$5,F$4) -> 0.0083333333 | G14: =E14+F14 -> 0.32083333 | H14: H5 | I14: =VLOOKUP(H14,'Liste chauffeur'!$B$5:$L$19,2,TRUE)&" "&VLOOKUP(H14,'Liste chauffeur'!$B$5:$L$19,3,TRUE) -> ATTOUMANI Kamaldine | J14: 3 | K14: =E15-G14 -> 0.0055555556
A15: LA BARGE | B15: CHM | C15: DIRECT | D15: L1 | E15: 0.32638889 | F15: =IF(C15="DIRECT",F$5,F$4) -> 0.0083333333 | G15: =E15+F15 -> 0.33472222 | H15: H5 | I15: =VLOOKUP(H15,'Liste chauffeur'!$B$5:$L$19,2,TRUE)&" "&VLOOKUP(H15,'Liste chauffeur'!$B$5:$L$19,3,TRUE) -> ATTOUMANI Kamaldine | J15: 3
A16: LA BARGE | B16: CHM | C16: 13 ARRETS | E16: 0.58333333 | F16: =IF(C16="DIRECT",F$5,F$4) -> 0.013888889 | G16: =E16+F16 -> 0.59722222 | H16: H1 | I16: =VLOOKUP(H16,'Liste chauffeur'!$B$5:$L$19,2,TRUE)&" "&VLOOKUP(H16,'Liste chauffeur'!$B$5:$L$19,3,TRUE) -> CHADHOULI Houmadi | K16: =E18-G16 -> 0.017361111
A17: CHM | B17: LA BARGE | C17: DIRECT | D17: L2 | E17: 0.58333333 | F17: =IF(C17="DIRECT",F$5,F$4) -> 0.0083333333 | G17: =E17+F17 -> 0.59166667 | H17: H3 | I17: =VLOOKUP(H17,'Liste chauffeur'!$B$5:$L$19,2,TRUE)&" "&VLOOKUP(H17,'Liste chauffeur'!$B$5:$L$19,3,TRUE) -> SAID ALI Kamile | J17: 4 | K17: =E19-G17 -> 0.033333333
A18: LA BARGE | B18: CHM | C18: 13 ARRETS | E18: 0.61458333 | F18: =IF(C18="DIRECT",F$5,F$4) -> 0.013888889 | G18: =E18+F18 -> 0.62847222 | H18: H1 | I18: =VLOOKUP(H18,'Liste chauffeur'!$B$5:$L$19,2,TRUE)&" "&VLOOKUP(H18,'Liste chauffeur'!$B$5:$L$19,3,TRUE) -> CHADHOULI Houmadi | K18: =E20-G18 -> 0.010416667
A19: CHM | B19: LA BARGE | C19: DIRECT | E19: 0.625 | F19: =IF(C19="DIRECT",F$5,F$4) -> 0.0083333333 | G19: =E19+F19 -> 0.63333333 | H19: H3 | I19: =VLOOKUP(H19,'Liste chauffeur'!$B$5:$L$19,2,TRUE)&" "&VLOOKUP(H19,'Liste chauffeur'!$B$5:$L$19,3,TRUE) -> SAID ALI Kamile
A20: LA BARGE | B20: CHM | C20: 13 ARRETS | E20: 0.63888889 | F20: =IF(C20="DIRECT",F$5,F$4) -> 0.013888889 | G20: =E20+F20 -> 0.65277778 | H20: H1 | I20: =VLOOKUP(H20,'Liste chauffeur'!$B$5:$L$19,2,TRUE)&" "&VLOOKUP(H20,'Liste chauffeur'!$B$5:$L$19,3,TRUE) -> CHADHOULI Houmadi
A21: LA BARGE | B21: CHM | C21: 13 ARRETS | E21: 0.65972222 | F21: =IF(C21="DIRECT",F$5,F$4) -> 0.013888889 | G21: =E21+F21 -> 0.67361111 | H21: H5 | I21: =VLOOKUP(H21,'Liste chauffeur'!$B$5:$L$19,2,TRUE)&" "&VLOOKUP(H21,'Liste chauffeur'!$B$5:$L$19,3,TRUE) -> ATTOUMANI Kamaldine | K21: =E22-G21 -> 0.013888889
A22: LA BARGE | B22: CHM | C22: 13 ARRETS | E22: 0.6875 | F22: =IF(C22="DIRECT",F$5,F$4) -> 0.013888889 | G22: =E22+F22 -> 0.70138889 | H22: H5 | I22: =VLOOKUP(H22,'Liste chauffeur'!$B$5:$L$19,2,TRUE)&" "&VLOOKUP(H22,'Liste chauffeur'!$B$5:$L$19,3,TRUE) -> ATTOUMANI Kamaldine
A23: CHM | B23: LA BARGE | C23: DIRECT | E23: 0.76041667 | F23: =IF(C23="DIRECT",F$5,F$4) -> 0.0083333333 | G23: =E23+F23 -> 0.76875 | H23: H3 | I23: =VLOOKUP(H23,'Liste chauffeur'!$B$5:$L$19,2,TRUE)&" "&VLOOKUP(H23,'Liste chauffeur'!$B$5:$L$19,3,TRUE) -> SAID ALI Kamile | K23: =E25-G23 -> 0.0125
A24: LA BARGE | B24: CHM | C24: 13 ARRETS | E24: 0.76041667 | F24: =IF(C24="DIRECT",F$5,F$4) -> 0.013888889 | G24: =E24+F24 -> 0.77430556 | H24: H5 | I24: =VLOOKUP(H24,'Liste chauffeur'!$B$5:$L$19,2,TRUE)&" "&VLOOKUP(H24,'Liste chauffeur'!$B$5:$L$19,3,TRUE) -> ATTOUMANI Kamaldine
A25: CHM | B25: LA BARGE | C25: DIRECT | E25: 0.78125 | F25: =IF(C25="DIRECT",F$5,F$4) -> 0.0083333333 | G25: =E25+F25 -> 0.78958333 | H25: H5 | I25: =VLOOKUP(H25,'Liste chauffeur'!$B$5:$L$19,2,TRUE)&" "&VLOOKUP(H25,'Liste chauffeur'!$B$5:$L$19,3,TRUE) -> ATTOUMANI Kamaldine | K25: =E27-G25 -> 0.019444444
A26: LA BARGE | B26: CHM | C26: 13 ARRETS | E26: 0.78125 | F26: =IF(C26="DIRECT",F$5,F$4) -> 0.013888889 | G26: =E26+F26 -> 0.79513889 | H26: H3 | I26: =VLOOKUP(H26,'Liste chauffeur'!$B$5:$L$19,2,TRUE)&" "&VLOOKUP(H26,'Liste chauffeur'!$B$5:$L$19,3,TRUE) -> SAID ALI Kamile
A27: CRA+CHM | B27: LA BARGE | C27: DIRECT | D27: L1 | E27: 0.80902778 | F27: =IF(C27="DIRECT",F$5,F$4) -> 0.0083333333 | G27: =E27+F27 -> 0.81736111 | H27: H5 | I27: =VLOOKUP(H27,'Liste chauffeur'!$B$5:$L$19,2,TRUE)&" "&VLOOKUP(H27,'Liste chauffeur'!$B$5:$L$19,3,TRUE) -> ATTOUMANI Kamaldine | J27: 5
A28: LA BARGE | B28: CHM | C28: 13 ARRETS | E28: 0.82291667 | F28: =IF(C28="DIRECT",F$5,F$4) -> 0.013888889 | G28: =E28+F28 -> 0.83680556 | H28: H5 | I28: =VLOOKUP(H28,'Liste chauffeur'!$B$5:$L$19,2,TRUE)&" "&VLOOKUP(H28,'Liste chauffeur'!$B$5:$L$19,3,TRUE) -> ATTOUMANI Kamaldine
F30: =SUBTOTAL(9,F8:F29) -> 0.23611111 | K30: =SUBTOTAL(9,K8:K29) -> 0.19305556
N31: Signature Coordinateur 2

Sheet Horaire dimanche
A3: DATE | F3: 0.013888889 | I3: NOVEMBRE
A4: CHAUFFEUR | F4: 0.017361111
F5: 0.0083333333
A7: DEPART | B7: ARRIVEE | C7: DIRECT/ AVEC ARRET | D7: N° LIGNE | E7: Heure théorique départ | F7: Temps théorique | G7: Heure arrivée théorique | H7: Type chauffeur prévu | I7: Nom chauffeur prévu | J7: Nbre trajets | K7: Delai entre 2 départs | L7: Délai avant | M7: Astreinte 1 | N7: Nom Chauffeur astreinte 1 | O7: Astreinte 2 | P7: Nom Chauffeur astreinte 2 | Q7: Heure réelle départ | R7: Nbre personnes + | S7: Commentaires
A8: CHM | B8: LA BARGE | C8: 13 ARRETS | D8: L1 | E8: 0.23958333 | F8: =F4 -> 0.017361111 | G8: =E8+F8 -> 0.25694444 | H8: H2 | I8: =VLOOKUP(H8,'Liste chauffeur'!$B$5:$L$19,2,TRUE)&" "&VLOOKUP(H8,'Liste chauffeur'!$B$5:$L$19,3,TRUE) -> CHAMSSOUNE Ahmed | J8: 1 | K8: =E9-G8 -> 0.0034722222
A9: LA BARGE | B9: CHM | C9: DIRECT | D9: L1 | E9: 0.26041667 | F9: =IF(D9="L1",F$5,F$4) -> 0.0083333333 | G9: =E9+F9 -> 0.26875 | H9: =H$8 -> H2 | I9: =VLOOKUP(H9,'Liste chauffeur'!$B$5:$L$19,2,TRUE)&" "&VLOOKUP(H9,'Liste chauffeur'!$B$5:$L$19,3,TRUE) -> CHAMSSOUNE Ahmed | J9: 2 | K9: =E10-G9 -> 0.0125
A10: CHM | B10: LA BARGE | C10: 13 ARRETS | D10: L1 | E10: 0.28125 | F10: =F4 -> 0.017361111 | G10: =E10+F10 -> 0.29861111 | H10: =H$8 -> H2 | I10: =VLOOKUP(H10,'Liste chauffeur'!$B$5:$L$19,2,TRUE)&" "&VLOOKUP(H10,'Liste chauffeur'!$B$5:$L$19,3,TRUE) -> CHAMSSOUNE Ahmed | J10: 3 | K10: =E11-G10 -> 0.0034722222
A11: LA BARGE | B11: CHM | C11: DIRECT | D11: L1 | E11: 0.30208333 | F11: =F5 -> 0.0083333333 | G11: =E11+F11 -> 0.31041667 | H11: =H$8 -> H2 | I11: =VLOOKUP(H11,'Liste chauffeur'!$B$5:$L$19,2,TRUE)&" "&VLOOKUP(H11,'Liste chauffeur'!$B$5:$L$19,3,TRUE) -> CHAMSSOUNE Ahmed | J11: 3 | K11: =E12-G11 -> 0.0020833333
A12: CHM | B12: LA BARGE | C12: 13 ARRETS | D12: L2 | E12: 0.3125 | F12: =F4 -> 0.017361111 | G12: =E12+F12 -> 0.32986111 | H12: =H$8 -> H2 | I12: =VLOOKUP(H12,'Liste chauffeur'!$B$5:$L$19,2,TRUE)&" "&VLOOKUP(H12,'Liste chauffeur'!$B$5:$L$19,3,TRUE) -> CHAMSSOUNE Ahmed | J12: 5
A13: CHM | B13: LA BARGE | C13: DIRECT | D13: L2 | E13: 0.58333333 | F13: =F5 -> 0.0083333333 | G13: =E13+F13 -> 0.59166667 | H13: =H$8 -> H2 | I13: =VLOOKUP(H13,'Liste chauffeur'!$B$5:$L$19,2,TRUE)&" "&VLOOKUP(H13,'Liste chauffeur'!$B$5:$L$19,3,TRUE) -> CHAMSSOUNE Ahmed | J13: 4 | K13: =E14-G13 -> 0.033333333
A14: CHM | B14: LA BARGE | C14: DIRECT | D14: L1 | E14: 0.625 | F14: =IF(D14="L1",F$5,F$4) -> 0.0083333333 | G14: =E14+F14 -> 0.63333333 | H14: =H$8 -> H2 | I14: =VLOOKUP(H14,'Liste chauffeur'!$B$5:$L$19,2,TRUE)&" "&VLOOKUP(H14,'Liste chauffeur'!$B$5:$L$19,3,TRUE) -> CHAMSSOUNE Ahmed | J14: 5
A15: CHM | B15: LA BARGE | C15: 13 ARRETS | D15: L1 | E15: 0.76041667 | F15: =F3 -> 0.013888889 | G15: =E15+F15 -> 0.77430556 | H15: =H$8 -> H2 | I15: =VLOOKUP(H15,'Liste chauffeur'!$B$5:$L$19,2,TRUE)&" "&VLOOKUP(H15,'Liste chauffeur'!$B$5:$L$19,3,TRUE) -> CHAMSSOUNE Ahmed | J15: 6 | K15: =E16-G15 -> 0.0069444444
A16: CHM | B16: LA BARGE | C16: 13 ARRETS | E16: 0.78125 | F16: =F3 -> 0.013888889 | G16: =E16+F16 -> 0.79513889 | H16: =H$8 -> H2 | I16: =VLOOKUP(H16,'Liste chauffeur'!$B$5:$L$19,2,TRUE)&" "&VLOOKUP(H16,'Liste chauffeur'!$B$5:$L$19,3,TRUE) -> CHAMSSOUNE Ahmed | K16: =E17-G16 -> 0.017361111
A17: CHM | B17: LA BARGE | C17: 13 ARRETS | D17: L1 | E17: 0.8125 | F17: =F4 -> 0.017361111 | G17: =E17+F17 -> 0.82986111 | H17: =H$8 -> H2 | I17: =VLOOKUP(H17,'Liste chauffeur'!$B$5:$L$19,2,TRUE)&" "&VLOOKUP(H17,'Liste chauffeur'!$B$5:$L$19,3,TRUE) -> CHAMSSOUNE Ahmed | J17: 5
N20: Signature Coordinateur 2

Sheet C2
A2: TYPE | B2: C2
A3: DATE | B3: =IF(ISBLANK(Feuil1!$B$3),"",Feuil1!$B$3)
A4: CHAUFFEUR | B4: =VLOOKUP(B2,'Liste chauffeur'!$B$5:$L$19,2,TRUE)&" "&VLOOKUP(B2,'Liste chauffeur'!$B$5:$L$19,3,TRUE) -> #N/A
E6: Arrêt 1 | I6: Arrêt 2 | M6: Arrêt 3 | S6: PEM PASSAMAINTY
B7: Heure théorique départ | C7: Heure réelle départ | D7: Nbre personnes montée | E7: - | F7: + | G7: Heure arrivée arrêt 1 | H7: Délai | I7: - | J7: + | K7: Heure arrivée arrêt 2 | L7: Délai | M7: - | N7: + | O7: Heure arrivée arrêt 3 | P7: Délai | Q7: Nbre personnes descente | S7: Heure arrivée finale | T7: Commentaires | U7: Temps Aller
A8: VAHIBE | B8: 0.20833333 | H8: =G8-C8 -> 0 | L8: =K8-G8 -> 0 | P8: =O8-K8 -> 0 | R8: =IF(D8+E8-F8+I8-J8+M8-N8=Q8,"OK",D8+E8-F8+I8-J8+M8-N8-Q8) -> OK | U8: =S8-C8 -> 0
A9: VAHIBE | B9: 0.21527778 | H9: =G9-C9 -> 0 | L9: =K9-G9 -> 0 | P9: =O9-K9 -> 0 | U9: =S9-C9 -> 0
A10: VAHIBE | B10: 0.22222222 | H10: =G10-C10 -> 0 | L10: =K10-G10 -> 0 | P10: =O10-K10 -> 0 | U10: =S10-C10 -> 0
A11: VAHIBE | B11: 0.22916667 | H11: =G11-C11 -> 0 | L11: =K11-G11 -> 0 | P11: =O11-K11 -> 0 | U11: =S11-C11 -> 0
A12: VAHIBE | B12: 0.23611111 | H12: =G12-C12 -> 0 | L12: =K12-G12 -> 0 | P12: =O12-K12 -> 0 | U12: =S12-C12 -> 0
A13: VAHIBE | B13: 0.24305556 | H13: =G13-C13 -> 0 | L13: =K13-G13 -> 0 | P13: =O13-K13 -> 0 | U13: =S13-C13 -> 0
A14: VAHIBE | B14: 0.25 | H14: =G14-C14 -> 0 | L14: =K14-G14 -> 0 | P14: =O14-K14 -> 0 | U14: =S14-C14 -> 0
A15: VAHIBE | B15: 0.25694444 | H15: =G15-C15 -> 0 | L15: =K15-G15 -> 0 | P15: =O15-K15 -> 0 | U15: =S15-C15 -> 0
A16: VAHIBE | B16: 0.26388889 | H16: =G16-C16 -> 0 | L16: =K16-G16 -> 0 | P16: =O16-K16 -> 0 | U16: =S16-C16 -> 0
A17: VAHIBE | B17: 0.27083333 | H17: =G17-C17 -> 0 | L17: =K17-G17 -> 0 | P17: =O17-K17 -> 0 | U17: =S17-C17 -> 0
A18: VAHIBE | B18: 0.27777778 | H18: =G18-C18 -> 0 | L18: =K18-G18 -> 0 | P18: =O18-K18 -> 0 | U18: =S18-C18 -> 0
A19: VAHIBE | B19: 0.28472222 | H19: =G19-C19 -> 0 | L19: =K19-G19 -> 0 | P19: =O19-K19 -> 0 | U19: =S19-C19 -> 0
A20: VAHIBE | B20: 0.29166667 | H20: =G20-C20 -> 0 | L20: =K20-G20 -> 0 | P20: =O20-K20 -> 0 | U20: =S20-C20 -> 0
... A26: VAHIBE | B26: 0.33333333 | H26: =G26-C26 -> 0 | L26: =K26-G26 -> 0 | P26: =O26-K26 -> 0 | U26: =S26-C26 -> 0
Q27: VAHIBE | U27: =SUM(U8:U26) -> 0
A28: PEM PASSAMAINTY | B28: 0.625 | H28: =G28-C28 -> 0 | L28: =K28-G28 -> 0 | P28: =O28-K28 -> 0 | U28: =S28-C28 -> 0
A29: PEM PASSAMAINTY | B29: 0.63194444 | H29: =G29-C29 -> 0 | L29: =K29-G29 -> 0 | P29: =O29-K29 -> 0 | U29: =S29-C29 -> 0
A30: PEM PASSAMAINTY | B30: 0.63888889 | H30: =G30-C30 -> 0 | L30: =K30-G30 -> 0 | P30: =O30-K30 -> 0 | U30: =S30-C30 -> 0
A31: PEM PASSAMAINTY | B31: 0.64583333 | H31: =G31-C31 -> 0 | L31: =K31-G31 -> 0 | P31: =O31-K31 -> 0 | U31: =S31-C31 -> 0
A32: PEM PASSAMAINTY | B32: 0.65277778 | H32: =G32-C32 -> 0 | L32: =K32-G32 -> 0 | P32: =O32-K32 -> 0 | U32: =S32-C32 -> 0
A33: PEM PASSAMAINTY | B33: 0.65972222 | H33: =G33-C33 -> 0 | L33: =K33-G33 -> 0 | P33: =O33-K33 -> 0 | U33: =S33-C33 -> 0
A34: PEM PASSAMAINTY | B34: 0.66666667 | H34: =G34-C34 -> 0 | L34: =K34-G34 -> 0 | P34: =O34-K34 -> 0 | U34: =S34-C34 -> 0
A35: PEM PASSAMAINTY | B35: 0.67361111 | H35: =G35-C35 -> 0 | L35: =K35-G35 -> 0 | P35: =O35-K35 -> 0 | U35: =S35-C35 -> 0
A36: PEM PASSAMAINTY | B36: 0.68055556 | H36: =G36-C36 -> 0 | L36: =K36-G36 -> 0 | P36: =O36-K36 -> 0 | U36: =S36-C36 -> 0
A37: PEM PASSAMAINTY | B37: 0.6875 | H37: =G37-C37 -> 0 | L37: =K37-G37 -> 0 | P37: =O37-K37 -> 0 | U37: =S37-C37 -> 0
A38: PEM PASSAMAINTY | B38: 0.69444444 | H38: =G38-C38 -> 0 | L38: =K38-G38 -> 0 | P38: =O38-K38 -> 0 | U38: =S38-C38 -> 0
A39: PEM PASSAMAINTY | B39: 0.70138889 | H39: =G39-C39 -> 0 | L39: =K39-G39 -> 0 | P39: =O39-K39 -> 0 | U39: =S39-C39 -> 0
... A46: PEM PASSAMAINTY | B46: 0.75 | H46: =G46-C46 -> 0 | L46: =K46-G46 -> 0 | P46: =O46-K46 -> 0 | U46: =S46-C46 -> 0
U47: =SUM(U28:U46) -> 0
U48: =U47+U27 -> 0
C49: Signature Chauffeur | I49: Signature Coordinateur

Sheet C3
A2: TYPE | B2: C3
A3: DATE | B3: =IF(ISBLANK(Feuil1!$B$3),"",Feuil1!$B$3)
A4: CHAUFFEUR | B4: =VLOOKUP(B2,'Liste chauffeur'!$B$5:$L$19,2,TRUE)&" "&VLOOKUP(B2,'Liste chauffeur'!$B$5:$L$19,3,TRUE) -> #N/A
E6: Arrêt 1 | I6: Arrêt 2 | M6: Arrêt 3 | S6: PEM PASSAMAINTY
B7: Heure théorique départ | C7: Heure réelle départ | D7: Nbre personnes montée | E7: - | F7: + | G7: Heure arrivée arrêt 1 | H7: Délai | I7: - | J7: + | K7: Heure arrivée arrêt 2 | L7: Délai | M7: - | N7: + | O7: Heure arrivée arrêt 3 | P7: Délai | Q7: Nbre personnes descente | S7: Heure arrivée finale | T7: Commentaires | U7: Temps Aller
A8: VAHIBE | B8: 0.20833333 | H8: =G8-C8 -> 0 | L8: =K8-G8 -> 0 | P8: =O8-K8 -> 0 | R8: =IF(D8+E8-F8+I8-J8+M8-N8=Q8,"OK",D8+E8-F8+I8-J8+M8-N8-Q8) -> OK | U8: =S8-C8 -> 0
A9: VAHIBE | B9: 0.21527778 | H9: =G9-C9 -> 0 | L9: =K9-G9 -> 0 | P9: =O9-K9 -> 0 | U9: =S9-C9 -> 0
A10: VAHIBE | B10: 0.22222222 | H10: =G10-C10 -> 0 | L10: =K10-G10 -> 0 | P10: =O10-K10 -> 0 | U10: =S10-C10 -> 0
A11: VAHIBE | B11: 0.22916667 | H11: =G11-C11 -> 0 | L11: =K11-G11 -> 0 | P11: =O11-K11 -> 0 | U11: =S11-C11 -> 0
A12: VAHIBE | B12: 0.23611111 | H12: =G12-C12 -> 0 | L12: =K12-G12 -> 0 | P12: =O12-K12 -> 0 | U12: =S12-C12 -> 0
A13: VAHIBE | B13: 0.24305556 | H13: =G13-C13 -> 0 | L13: =K13-G13 -> 0 | P13: =O13-K13 -> 0 | U13: =S13-C13 -> 0
A14: VAHIBE | B14: 0.25 | H14: =G14-C14 -> 0 | L14: =K14-G14 -> 0 | P14: =O14-K14 -> 0 | U14: =S14-C14 -> 0
A15: VAHIBE | B15: 0.25694444 | H15: =G15-C15 -> 0 | L15: =K15-G15 -> 0 | P15: =O15-K15 -> 0 | U15: =S15-C15 -> 0
A16: VAHIBE | B16: 0.26388889 | H16: =G16-C16 -> 0 | L16: =K16-G16 -> 0 | P16: =O16-K16 -> 0 | U16: =S16-C16 -> 0
A17: VAHIBE | B17: 0.27083333 | H17: =G17-C17 -> 0 | L17: =K17-G17 -> 0 | P17: =O17-K17 -> 0 | U17: =S17-C17 -> 0
A18: VAHIBE | B18: 0.27777778 | H18: =G18-C18 -> 0 | L18: =K18-G18 -> 0 | P18: =O18-K18 -> 0 | U18: =S18-C18 -> 0
A19: VAHIBE | B19: 0.28472222 | H19: =G19-C19 -> 0 | L19: =K19-G19 -> 0 | P19: =O19-K19 -> 0 | U19: =S19-C19 -> 0
A20: VAHIBE | B20: 0.29166667 | H20: =G20-C20 -> 0 | L20: =K20-G20 -> 0 | P20: =O20-K20 -> 0 | U20: =S20-C20 -> 0
... A26: VAHIBE | B26: 0.33333333 | H26: =G26-C26 -> 0 | L26: =K26-G26 -> 0 | P26: =O26-K26 -> 0 | U26: =S26-C26 -> 0
Q27: VAHIBE | U27: =SUM(U8:U26) -> 0
A28: PEM PASSAMAINTY | B28: 0.625 | H28: =G28-C28 -> 0 | L28: =K28-G28 -> 0 | P28: =O28-K28 -> 0 | U28: =S28-C28 -> 0
A29: PEM PASSAMAINTY | B29: 0.63194444 | H29: =G29-C29 -> 0 | L29: =K29-G29 -> 0 | P29: =O29-K29 -> 0 | U29: =S29-C29 -> 0
A30: PEM PASSAMAINTY | B30: 0.63888889 | H30: =G30-C30 -> 0 | L30: =K30-G30 -> 0 | P30: =O30-K30 -> 0 | U30: =S30-C30 -> 0
A31: PEM PASSAMAINTY | B31: 0.64583333 | H31: =G31-C31 -> 0 | L31: =K31-G31 -> 0 | P31: =O31-K31 -> 0 | U31: =S31-C31 -> 0
A32: PEM PASSAMAINTY | B32: 0.65277778 | H32: =G32-C32 -> 0 | L32: =K32-G32 -> 0 | P32: =O32-K32 -> 0 | U32: =S32-C32 -> 0
A33: PEM PASSAMAINTY | B33: 0.65972222 | H33: =G33-C33 -> 0 | L33: =K33-G33 -> 0 | P33: =O33-K33 -> 0 | U33: =S33-C33 -> 0
A34: PEM PASSAMAINTY | B34: 0.66666667 | H34: =G34-C34 -> 0 | L34: =K34-G34 -> 0 | P34: =O34-K34 -> 0 | U34: =S34-C34 -> 0
A35: PEM PASSAMAINTY | B35: 0.67361111 | H35: =G35-C35 -> 0 | L35: =K35-G35 -> 0 | P35: =O35-K35 -> 0 | U35: =S35-C35 -> 0
A36: PEM PASSAMAINTY | B36: 0.68055556 | H36: =G36-C36 -> 0 | L36: =K36-G36 -> 0 | P36: =O36-K36 -> 0 | U36: =S36-C36 -> 0
A37: PEM PASSAMAINTY | B37: 0.6875 | H37: =G37-C37 -> 0 | L37: =K37-G37 -> 0 | P37: =O37-K37 -> 0 | U37: =S37-C37 -> 0
A38: PEM PASSAMAINTY | B38: 0.69444444 | H38: =G38-C38 -> 0 | L38: =K38-G38 -> 0 | P38: =O38-K38 -> 0 | U38: =S38-C38 -> 0
A39: PEM PASSAMAINTY | B39: 0.70138889 | H39: =G39-C39 -> 0 | L39: =K39-G39 -> 0 | P39: =O39-K39 -> 0 | U39: =S39-C39 -> 0
... A46: PEM PASSAMAINTY | B46: 0.75 | H46: =G46-C46 -> 0 | L46: =K46-G46 -> 0 | P46: =O46-K46 -> 0 | U46: =S46-C46 -> 0
U47: =SUM(U28:U46) -> 0
U48: =U47+U27 -> 0
C49: Signature Chauffeur | I49: Signature Coordinateur

Sheet C4
A2: TYPE | B2: C4
A3: DATE | B3: =IF(ISBLANK(Feuil1!$B$3),"",Feuil1!$B$3)
A4: CHAUFFEUR | B4: =VLOOKUP(B2,'Liste chauffeur'!$B$5:$L$19,2,TRUE)&" "&VLOOKUP(B2,'Liste chauffeur'!$B$5:$L$19,3,TRUE) -> #N/A
E6: Arrêt 1 | I6: Arrêt 2 | M6: Arrêt 3 | S6: PEM PASSAMAINTY
B7: Heure théorique départ | C7: Heure réelle départ | D7: Nbre personnes montée | E7: - | F7: + | G7: Heure arrivée arrêt 1 | H7: Délai | I7: - | J7: + | K7: Heure arrivée arrêt 2 | L7: Délai | M7: - | N7: + | O7: Heure arrivée arrêt 3 | P7: Délai | Q7: Nbre personnes descente | S7: Heure arrivée finale | T7: Commentaires | U7: Temps Aller
A8: VAHIBE | B8: 0.20833333 | H8: =G8-C8 -> 0 | L8: =K8-G8 -> 0 | P8: =O8-K8 -> 0 | R8: =IF(D8+E8-F8+I8-J8+M8-N8=Q8,"OK",D8+E8-F8+I8-J8+M8-N8-Q8) -> OK | U8: =S8-C8 -> 0
A9: VAHIBE | B9: 0.21527778 | H9: =G9-C9 -> 0 | L9: =K9-G9 -> 0 | P9: =O9-K9 -> 0 | U9: =S9-C9 -> 0
A10: VAHIBE | B10: 0.22222222 | H10: =G10-C10 -> 0 | L10: =K10-G10 -> 0 | P10: =O10-K10 -> 0 | U10: =S10-C10 -> 0
A11: VAHIBE | B11: 0.22916667 | H11: =G11-C11 -> 0 | L11: =K11-G11 -> 0 | P11: =O11-K11 -> 0 | U11: =S11-C11 -> 0
A12: VAHIBE | B12: 0.23611111 | H12: =G12-C12 -> 0 | L12: =K12-G12 -> 0 | P12: =O12-K12 -> 0 | U12: =S12-C12 -> 0
A13: VAHIBE | B13: 0.24305556 | H13: =G13-C13 -> 0 | L13: =K13-G13 -> 0 | P13: =O13-K13 -> 0 | U13: =S13-C13 -> 0
A14: VAHIBE | B14: 0.25 | H14: =G14-C14 -> 0 | L14: =K14-G14 -> 0 | P14: =O14-K14 -> 0 | U14: =S14-C14 -> 0
A15: VAHIBE | B15: 0.25694444 | H15: =G15-C15 -> 0 | L15: =K15-G15 -> 0 | P15: =O15-K15 -> 0 | U15: =S15-C15 -> 0
A16: VAHIBE | B16: 0.26388889 | H16: =G16-C16 -> 0 | L16: =K16-G16 -> 0 | P16: =O16-K16 -> 0 | U16: =S16-C16 -> 0
A17: VAHIBE | B17: 0.27083333 | H17: =G17-C17 -> 0 | L17: =K17-G17 -> 0 | P17: =O17-K17 -> 0 | U17: =S17-C17 -> 0
A18: VAHIBE | B18: 0.27777778 | H18: =G18-C18 -> 0 | L18: =K18-G18 -> 0 | P18: =O18-K18 -> 0 | U18: =S18-C18 -> 0
A19: VAHIBE | B19: 0.28472222 | H19: =G19-C19 -> 0 | L19: =K19-G19 -> 0 | P19: =O19-K19 -> 0 | U19: =S19-C19 -> 0
A20: VAHIBE | B20: 0.29166667 | H20: =G20-C20 -> 0 | L20: =K20-G20 -> 0 | P20: =O20-K20 -> 0 | U20: =S20-C20 -> 0
... A26: VAHIBE | B26: 0.33333333 | H26: =G26-C26 -> 0 | L26: =K26-G26 -> 0 | P26: =O26-K26 -> 0 | U26: =S26-C26 -> 0
Q27: VAHIBE | U27: =SUM(U8:U26) -> 0
A28: PEM PASSAMAINTY | B28: 0.625 | H28: =G28-C28 -> 0 | L28: =K28-G28 -> 0 | P28: =O28-K28 -> 0 | U28: =S28-C28 -> 0
A29: PEM PASSAMAINTY | B29: 0.63194444 | H29: =G29-C29 -> 0 | L29: =K29-G29 -> 0 | P29: =O29-K29 -> 0 | U29: =S29-C29 -> 0
A30: PEM PASSAMAINTY | B30: 0.63888889 | H30: =G30-C30 -> 0 | L30: =K30-G30 -> 0 | P30: =O30-K30 -> 0 | U30: =S30-C30 -> 0
A31: PEM PASSAMAINTY | B31: 0.64583333 | H31: =G31-C31 -> 0 | L31: =K31-G31 -> 0 | P31: =O31-K31 -> 0 | U31: =S31-C31 -> 0
A32: PEM PASSAMAINTY | B32: 0.65277778 | H32: =G32-C32 -> 0 | L32: =K32-G32 -> 0 | P32: =O32-K32 -> 0 | U32: =S32-C32 -> 0
A33: PEM PASSAMAINTY | B33: 0.65972222 | H33: =G33-C33 -> 0 | L33: =K33-G33 -> 0 | P33: =O33-K33 -> 0 | U33: =S33-C33 -> 0
A34: PEM PASSAMAINTY | B34: 0.66666667 | H34: =G34-C34 -> 0 | L34: =K34-G34 -> 0 | P34: =O34-K34 -> 0 | U34: =S34-C34 -> 0
A35: PEM PASSAMAINTY | B35: 0.67361111 | H35: =G35-C35 -> 0 | L35: =K35-G35 -> 0 | P35: =O35-K35 -> 0 | U35: =S35-C35 -> 0
A36: PEM PASSAMAINTY | B36: 0.68055556 | H36: =G36-C36 -> 0 | L36: =K36-G36 -> 0 | P36: =O36-K36 -> 0 | U36: =S36-C36 -> 0
A37: PEM PASSAMAINTY | B37: 0.6875 | H37: =G37-C37 -> 0 | L37: =K37-G37 -> 0 | P37: =O37-K37 -> 0 | U37: =S37-C37 -> 0
A38: PEM PASSAMAINTY | B38: 0.69444444 | H38: =G38-C38 -> 0 | L38: =K38-G38 -> 0 | P38: =O38-K38 -> 0 | U38: =S38-C38 -> 0
A39: PEM PASSAMAINTY | B39: 0.70138889 | H39: =G39-C39 -> 0 | L39: =K39-G39 -> 0 | P39: =O39-K39 -> 0 | U39: =S39-C39 -> 0
... A46: PEM PASSAMAINTY | B46: 0.75 | H46: =G46-C46 -> 0 | L46: =K46-G46 -> 0 | P46: =O46-K46 -> 0 | U46: =S46-C46 -> 0
U47: =SUM(U28:U46) -> 0
U48: =U47+U27 -> 0
C49: Signature Chauffeur | I49: Signature Coordinateur

Sheet C5
A2: TYPE | B2: C5
A3: DATE | B3: =IF(ISBLANK(Feuil1!$B$3),"",Feuil1!$B$3)
A4: CHAUFFEUR | B4: COMBO SOUFFOU (RENE ASSANATI)
E6: Arrêt 1 | I6: Arrêt 2 | M6: Arrêt 3 | S6: PEM PASSAMAINTY
B7: Heure théorique départ | C7: Heure réelle départ | D7: Nbre personnes montée | E7: - | F7: + | G7: Heure arrivée arrêt 1 | H7: Délai | I7: - | J7: + | K7: Heure arrivée arrêt 2 | L7: Délai | M7: - | N7: + | O7: Heure arrivée arrêt 3 | P7: Délai | Q7: Nbre personnes descente | S7: Heure arrivée finale | T7: Commentaires | U7: Temps Aller
A8: VAHIBE | B8: 0.20833333 | H8: =G8-C8 -> 0 | L8: =K8-G8 -> 0 | P8: =O8-K8 -> 0 | R8: =IF(D8+E8-F8+I8-J8+M8-N8=Q8,"OK",D8+E8-F8+I8-J8+M8-N8-Q8) -> OK | U8: =S8-C8 -> 0
A9: VAHIBE | B9: 0.21527778 | H9: =G9-C9 -> 0 | L9: =K9-G9 -> 0 | P9: =O9-K9 -> 0 | U9: =S9-C9 -> 0
A10: VAHIBE | B10: 0.22222222 | H10: =G10-C10 -> 0 | L10: =K10-G10 -> 0 | P10: =O10-K10 -> 0 | U10: =S10-C10 -> 0
A11: VAHIBE | B11: 0.22916667 | H11: =G11-C11 -> 0 | L11: =K11-G11 -> 0 | P11: =O11-K11 -> 0 | U11: =S11-C11 -> 0
A12: VAHIBE | B12: 0.23611111 | H12: =G12-C12 -> 0 | L12: =K12-G12 -> 0 | P12: =O12-K12 -> 0 | U12: =S12-C12 -> 0
A13: VAHIBE | B13: 0.24305556 | H13: =G13-C13 -> 0 | L13: =K13-G13 -> 0 | P13: =O13-K13 -> 0 | U13: =S13-C13 -> 0
A14: VAHIBE | B14: 0.25 | H14: =G14-C14 -> 0 | L14: =K14-G14 -> 0 | P14: =O14-K14 -> 0 | U14: =S14-C14 -> 0
A15: VAHIBE | B15: 0.25694444 | H15: =G15-C15 -> 0 | L15: =K15-G15 -> 0 | P15: =O15-K15 -> 0 | U15: =S15-C15 -> 0
A16: VAHIBE | B16: 0.26388889 | H16: =G16-C16 -> 0 | L16: =K16-G16 -> 0 | P16: =O16-K16 -> 0 | U16: =S16-C16 -> 0
A17: VAHIBE | B17: 0.27083333 | H17: =G17-C17 -> 0 | L17: =K17-G17 -> 0 | P17: =O17-K17 -> 0 | U17: =S17-C17 -> 0
A18: VAHIBE | B18: 0.27777778 | H18: =G18-C18 -> 0 | L18: =K18-G18 -> 0 | P18: =O18-K18 -> 0 | U18: =S18-C18 -> 0
A19: VAHIBE | B19: 0.28472222 | H19: =G19-C19 -> 0 | L19: =K19-G19 -> 0 | P19: =O19-K19 -> 0 | U19: =S19-C19 -> 0
A20: VAHIBE | B20: 0.29166667 | H20: =G20-C20 -> 0 | L20: =K20-G20 -> 0 | P20: =O20-K20 -> 0 | U20: =S20-C20 -> 0
... A26: VAHIBE | B26: 0.33333333 | H26: =G26-C26 -> 0 | L26: =K26-G26 -> 0 | P26: =O26-K26 -> 0 | U26: =S26-C26 -> 0
Q27: VAHIBE | U27: =SUM(U8:U26) -> 0
A28: PEM PASSAMAINTY | B28: 0.625 | H28: =G28-C28 -> 0 | L28: =K28-G28 -> 0 | P28: =O28-K28 -> 0 | U28: =S28-C28 -> 0
A29: PEM PASSAMAINTY | B29: 0.63194444 | H29: =G29-C29 -> 0 | L29: =K29-G29 -> 0 | P29: =O29-K29 -> 0 | U29: =S29-C29 -> 0
A30: PEM PASSAMAINTY | B30: 0.63888889 | H30: =G30-C30 -> 0 | L30: =K30-G30 -> 0 | P30: =O30-K30 -> 0 | U30: =S30-C30 -> 0
A31: PEM PASSAMAINTY | B31: 0.64583333 | H31: =G31-C31 -> 0 | L31: =K31-G31 -> 0 | P31: =O31-K31 -> 0 | U31: =S31-C31 -> 0
A32: PEM PASSAMAINTY | B32: 0.65277778 | H32: =G32-C32 -> 0 | L32: =K32-G32 -> 0 | P32: =O32-K32 -> 0 | U32: =S32-C32 -> 0
A33: PEM PASSAMAINTY | B33: 0.65972222 | H33: =G33-C33 -> 0 | L33: =K33-G33 -> 0 | P33: =O33-K33 -> 0 | U33: =S33-C33 -> 0
A34: PEM PASSAMAINTY | B34: 0.66666667 | H34: =G34-C34 -> 0 | L34: =K34-G34 -> 0 | P34: =O34-K34 -> 0 | U34: =S34-C34 -> 0
A35: PEM PASSAMAINTY | B35: 0.67361111 | H35: =G35-C35 -> 0 | L35: =K35-G35 -> 0 | P35: =O35-K35 -> 0 | U35: =S35-C35 -> 0
A36: PEM PASSAMAINTY | B36: 0.68055556 | H36: =G36-C36 -> 0 | L36: =K36-G36 -> 0 | P36: =O36-K36 -> 0 | U36: =S36-C36 -> 0
A37: PEM PASSAMAINTY | B37: 0.6875 | H37: =G37-C37 -> 0 | L37: =K37-G37 -> 0 | P37: =O37-K37 -> 0 | U37: =S37-C37 -> 0
A38: PEM PASSAMAINTY | B38: 0.69444444 | H38: =G38-C38 -> 0 | L38: =K38-G38 -> 0 | P38: =O38-K38 -> 0 | U38: =S38-C38 -> 0
A39: PEM PASSAMAINTY | B39: 0.70138889 | H39: =G39-C39 -> 0 | L39: =K39-G39 -> 0 | P39: =O39-K39 -> 0 | U39: =S39-C39 -> 0
... A46: PEM PASSAMAINTY | B46: 0.75 | H46: =G46-C46 -> 0 | L46: =K46-G46 -> 0 | P46: =O46-K46 -> 0 | U46: =S46-C46 -> 0
U47: =SUM(U28:U46) -> 0
U48: =U47+U27 -> 0
C49: Signature Chauffeur | I49: Signature Coordinateur

Sheet C6
A2: TYPE | B2: C6
A3: DATE | B3: =IF(ISBLANK(Feuil1!$B$3),"",Feuil1!$B$3)
A4: CHAUFFEUR | B4: =VLOOKUP(B2,'Liste chauffeur'!$B$5:$L$19,2,TRUE)&" "&VLOOKUP(B2,'Liste chauffeur'!$B$5:$L$19,3,TRUE) -> #N/A
E6: Arrêt 1 | I6: Arrêt 2 | M6: Arrêt 3 | S6: PEM PASSAMAINTY
B7: Heure théorique départ | C7: Heure réelle départ | D7: Nbre personnes montée | E7: - | F7: + | G7: Heure arrivée arrêt 1 | H7: Délai | I7: - | J7: + | K7: Heure arrivée arrêt 2 | L7: Délai | M7: - | N7: + | O7: Heure arrivée arrêt 3 | P7: Délai | Q7: Nbre personnes descente | S7: Heure arrivée finale | T7: Commentaires | U7: Temps Aller
A8: VAHIBE | B8: 0.20833333 | H8: =G8-C8 -> 0 | L8: =K8-G8 -> 0 | P8: =O8-K8 -> 0 | R8: =IF(D8+E8-F8+I8-J8+M8-N8=Q8,"OK",D8+E8-F8+I8-J8+M8-N8-Q8) -> OK | U8: =S8-C8 -> 0
A9: VAHIBE | B9: 0.21527778 | H9: =G9-C9 -> 0 | L9: =K9-G9 -> 0 | P9: =O9-K9 -> 0 | U9: =S9-C9 -> 0
A10: VAHIBE | B10: 0.22222222 | H10: =G10-C10 -> 0 | L10: =K10-G10 -> 0 | P10: =O10-K10 -> 0 | U10: =S10-C10 -> 0
A11: VAHIBE | B11: 0.22916667 | H11: =G11-C11 -> 0 | L11: =K11-G11 -> 0 | P11: =O11-K11 -> 0 | U11: =S11-C11 -> 0
A12: VAHIBE | B12: 0.23611111 | H12: =G12-C12 -> 0 | L12: =K12-G12 -> 0 | P12: =O12-K12 -> 0 | U12: =S12-C12 -> 0
A13: VAHIBE | B13: 0.24305556 | H13: =G13-C13 -> 0 | L13: =K13-G13 -> 0 | P13: =O13-K13 -> 0 | U13: =S13-C13 -> 0
A14: VAHIBE | B14: 0.25 | H14: =G14-C14 -> 0 | L14: =K14-G14 -> 0 | P14: =O14-K14 -> 0 | U14: =S14-C14 -> 0
A15: VAHIBE | B15: 0.25694444 | H15: =G15-C15 -> 0 | L15: =K15-G15 -> 0 | P15: =O15-K15 -> 0 | U15: =S15-C15 -> 0
A16: VAHIBE | B16: 0.26388889 | H16: =G16-C16 -> 0 | L16: =K16-G16 -> 0 | P16: =O16-K16 -> 0 | U16: =S16-C16 -> 0
A17: VAHIBE | B17: 0.27083333 | H17: =G17-C17 -> 0 | L17: =K17-G17 -> 0 | P17: =O17-K17 -> 0 | U17: =S17-C17 -> 0
A18: VAHIBE | B18: 0.27777778 | H18: =G18-C18 -> 0 | L18: =K18-G18 -> 0 | P18: =O18-K18 -> 0 | U18: =S18-C18 -> 0
A19: VAHIBE | B19: 0.28472222 | H19: =G19-C19 -> 0 | L19: =K19-G19 -> 0 | P19: =O19-K19 -> 0 | U19: =S19-C19 -> 0
A20: VAHIBE | B20: 0.29166667 | H20: =G20-C20 -> 0 | L20: =K20-G20 -> 0 | P20: =O20-K20 -> 0 | U20: =S20-C20 -> 0
... A26: VAHIBE | B26: 0.33333333 | H26: =G26-C26 -> 0 | L26: =K26-G26 -> 0 | P26: =O26-K26 -> 0 | U26: =S26-C26 -> 0
Q27: VAHIBE | U27: =SUM(U8:U26) -> 0
A28: PEM PASSAMAINTY | B28: 0.625 | H28: =G28-C28 -> 0 | L28: =K28-G28 -> 0 | P28: =O28-K28 -> 0 | U28: =S28-C28 -> 0
A29: PEM PASSAMAINTY | B29: 0.63194444 | H29: =G29-C29 -> 0 | L29: =K29-G29 -> 0 | P29: =O29-K29 -> 0 | U29: =S29-C29 -> 0
A30: PEM PASSAMAINTY | B30: 0.63888889 | H30: =G30-C30 -> 0 | L30: =K30-G30 -> 0 | P30: =O30-K30 -> 0 | U30: =S30-C30 -> 0
A31: PEM PASSAMAINTY | B31: 0.64583333 | H31: =G31-C31 -> 0 | L31: =K31-G31 -> 0 | P31: =O31-K31 -> 0 | U31: =S31-C31 -> 0
A32: PEM PASSAMAINTY | B32: 0.65277778 | H32: =G32-C32 -> 0 | L32: =K32-G32 -> 0 | P32: =O32-K32 -> 0 | U32: =S32-C32 -> 0
A33: PEM PASSAMAINTY | B33: 0.65972222 | H33: =G33-C33 -> 0 | L33: =K33-G33 -> 0 | P33: =O33-K33 -> 0 | U33: =S33-C33 -> 0
A34: PEM PASSAMAINTY | B34: 0.66666667 | H34: =G34-C34 -> 0 | L34: =K34-G34 -> 0 | P34: =O34-K34 -> 0 | U34: =S34-C34 -> 0
A35: PEM PASSAMAINTY | B35: 0.67361111 | H35: =G35-C35 -> 0 | L35: =K35-G35 -> 0 | P35: =O35-K35 -> 0 | U35: =S35-C35 -> 0
A36: PEM PASSAMAINTY | B36: 0.68055556 | H36: =G36-C36 -> 0 | L36: =K36-G36 -> 0 | P36: =O36-K36 -> 0 | U36: =S36-C36 -> 0
A37: PEM PASSAMAINTY | B37: 0.6875 | H37: =G37-C37 -> 0 | L37: =K37-G37 -> 0 | P37: =O37-K37 -> 0 | U37: =S37-C37 -> 0
A38: PEM PASSAMAINTY | B38: 0.69444444 | H38: =G38-C38 -> 0 | L38: =K38-G38 -> 0 | P38: =O38-K38 -> 0 | U38: =S38-C38 -> 0
A39: PEM PASSAMAINTY | B39: 0.70138889 | H39: =G39-C39 -> 0 | L39: =K39-G39 -> 0 | P39: =O39-K39 -> 0 | U39: =S39-C39 -> 0
... A46: PEM PASSAMAINTY | B46: 0.75 | H46: =G46-C46 -> 0 | L46: =K46-G46 -> 0 | P46: =O46-K46 -> 0 | U46: =S46-C46 -> 0
U47: =SUM(U28:U46) -> 0
U48: =U47+U27 -> 0
C49: Signature Chauffeur | I49: Signature Coordinateur

Sheet C7
A2: TYPE | B2: C7
A3: DATE | B3: =IF(ISBLANK(Feuil1!$B$3),"",Feuil1!$B$3)
A4: CHAUFFEUR | B4: =VLOOKUP(B2,'Liste chauffeur'!$B$5:$L$19,2,TRUE)&" "&VLOOKUP(B2,'Liste chauffeur'!$B$5:$L$19,3,TRUE) -> #N/A
E6: Arrêt 1 | I6: Arrêt 2 | M6: Arrêt 3 | S6: PEM PASSAMAINTY
B7: Heure théorique départ | C7: Heure réelle départ | D7: Nbre personnes montée | E7: - | F7: + | G7: Heure arrivée arrêt 1 | H7: Délai | I7: - | J7: + | K7: Heure arrivée arrêt 2 | L7: Délai | M7: - | N7: + | O7: Heure arrivée arrêt 3 | P7: Délai | Q7: Nbre personnes descente | S7: Heure arrivée finale | T7: Commentaires | U7: Temps Aller
A8: VAHIBE | B8: 0.20833333 | H8: =G8-C8 -> 0 | L8: =K8-G8 -> 0 | P8: =O8-K8 -> 0 | R8: =IF(D8+E8-F8+I8-J8+M8-N8=Q8,"OK",D8+E8-F8+I8-J8+M8-N8-Q8) -> OK | U8: =S8-C8 -> 0
A9: VAHIBE | B9: 0.21527778 | H9: =G9-C9 -> 0 | L9: =K9-G9 -> 0 | P9: =O9-K9 -> 0 | U9: =S9-C9 -> 0
A10: VAHIBE | B10: 0.22222222 | H10: =G10-C10 -> 0 | L10: =K10-G10 -> 0 | P10: =O10-K10 -> 0 | U10: =S10-C10 -> 0
A11: VAHIBE | B11: 0.22916667 | H11: =G11-C11 -> 0 | L11: =K11-G11 -> 0 | P11: =O11-K11 -> 0 | U11: =S11-C11 -> 0
A12: VAHIBE | B12: 0.23611111 | H12: =G12-C12 -> 0 | L12: =K12-G12 -> 0 | P12: =O12-K12 -> 0 | U12: =S12-C12 -> 0
A13: VAHIBE | B13: 0.24305556 | H13: =G13-C13 -> 0 | L13: =K13-G13 -> 0 | P13: =O13-K13 -> 0 | U13: =S13-C13 -> 0
A14: VAHIBE | B14: 0.25 | H14: =G14-C14 -> 0 | L14: =K14-G14 -> 0 | P14: =O14-K14 -> 0 | U14: =S14-C14 -> 0
A15: VAHIBE | B15: 0.25694444 | H15: =G15-C15 -> 0 | L15: =K15-G15 -> 0 | P15: =O15-K15 -> 0 | U15: =S15-C15 -> 0
A16: VAHIBE | B16: 0.26388889 | H16: =G16-C16 -> 0 | L16: =K16-G16 -> 0 | P16: =O16-K16 -> 0 | U16: =S16-C16 -> 0
A17: VAHIBE | B17: 0.27083333 | H17: =G17-C17 -> 0 | L17: =K17-G17 -> 0 | P17: =O17-K17 -> 0 | U17: =S17-C17 -> 0
A18: VAHIBE | B18: 0.27777778 | H18: =G18-C18 -> 0 | L18: =K18-G18 -> 0 | P18: =O18-K18 -> 0 | U18: =S18-C18 -> 0
A19: VAHIBE | B19: 0.28472222 | H19: =G19-C19 -> 0 | L19: =K19-G19 -> 0 | P19: =O19-K19 -> 0 | U19: =S19-C19 -> 0
A20: VAHIBE | B20: 0.29166667 | H20: =G20-C20 -> 0 | L20: =K20-G20 -> 0 | P20: =O20-K20 -> 0 | U20: =S20-C20 -> 0
... A26: VAHIBE | B26: 0.33333333 | H26: =G26-C26 -> 0 | L26: =K26-G26 -> 0 | P26: =O26-K26 -> 0 | U26: =S26-C26 -> 0
Q27: VAHIBE | U27: =SUM(U8:U26) -> 0
A28: PEM PASSAMAINTY | B28: 0.625 | H28: =G28-C28 -> 0 | L28: =K28-G28 -> 0 | P28: =O28-K28 -> 0 | U28: =S28-C28 -> 0
A29: PEM PASSAMAINTY | B29: 0.63194444 | H29: =G29-C29 -> 0 | L29: =K29-G29 -> 0 | P29: =O29-K29 -> 0 | U29: =S29-C29 -> 0
A30: PEM PASSAMAINTY | B30: 0.63888889 | H30: =G30-C30 -> 0 | L30: =K30-G30 -> 0 | P30: =O30-K30 -> 0 | U30: =S30-C30 -> 0
A31: PEM PASSAMAINTY | B31: 0.64583333 | H31: =G31-C31 -> 0 | L31: =K31-G31 -> 0 | P31: =O31-K31 -> 0 | U31: =S31-C31 -> 0
A32: PEM PASSAMAINTY | B32: 0.65277778 | H32: =G32-C32 -> 0 | L32: =K32-G32 -> 0 | P32: =O32-K32 -> 0 | U32: =S32-C32 -> 0
A33: PEM PASSAMAINTY | B33: 0.65972222 | H33: =G33-C33 -> 0 | L33: =K33-G33 -> 0 | P33: =O33-K33 -> 0 | U33: =S33-C33 -> 0
A34: PEM PASSAMAINTY | B34: 0.66666667 | H34: =G34-C34 -> 0 | L34: =K34-G34 -> 0 | P34: =O34-K34 -> 0 | U34: =S34-C34 -> 0
A35: PEM PASSAMAINTY | B35: 0.67361111 | H35: =G35-C35 -> 0 | L35: =K35-G35 -> 0 | P35: =O35-K35 -> 0 | U35: =S35-C35 -> 0
A36: PEM PASSAMAINTY | B36: 0.68055556 | H36: =G36-C36 -> 0 | L36: =K36-G36 -> 0 | P36: =O36-K36 -> 0 | U36: =S36-C36 -> 0
A37: PEM PASSAMAINTY | B37: 0.6875 | H37: =G37-C37 -> 0 | L37: =K37-G37 -> 0 | P37: =O37-K37 -> 0 | U37: =S37-C37 -> 0
A38: PEM PASSAMAINTY | B38: 0.69444444 | H38: =G38-C38 -> 0 | L38: =K38-G38 -> 0 | P38: =O38-K38 -> 0 | U38: =S38-C38 -> 0
A39: PEM PASSAMAINTY | B39: 0.70138889 | H39: =G39-C39 -> 0 | L39: =K39-G39 -> 0 | P39: =O39-K39 -> 0 | U39: =S39-C39 -> 0
... A46: PEM PASSAMAINTY | B46: 0.75 | H46: =G46-C46 -> 0 | L46: =K46-G46 -> 0 | P46: =O46-K46 -> 0 | U46: =S46-C46 -> 0
U47: =SUM(U28:U46) -> 0
U48: =U47+U27 -> 0
C49: Signature Chauffeur | I49: Signature Coordinateur

Sheet C8
A2: TYPE | B2: C8
A3: DATE | B3: =IF(ISBLANK(Feuil1!$B$3),"",Feuil1!$B$3)
A4: CHAUFFEUR | B4: =VLOOKUP(B2,'Liste chauffeur'!$B$5:$L$19,2,TRUE)&" "&VLOOKUP(B2,'Liste chauffeur'!$B$5:$L$19,3,TRUE) -> #N/A
E6: Arrêt 1 | I6: Arrêt 2 | M6: Arrêt 3 | S6: PEM PASSAMAINTY
B7: Heure théorique départ | C7: Heure réelle départ | D7: Nbre personnes montée | E7: - | F7: + | G7: Heure arrivée arrêt 1 | H7: Délai | I7: - | J7: + | K7: Heure arrivée arrêt 2 | L7: Délai | M7: - | N7: + | O7: Heure arrivée arrêt 3 | P7: Délai | Q7: Nbre personnes descente | S7: Heure arrivée finale | T7: Commentaires | U7: Temps Aller
A8: VAHIBE | B8: 0.20833333 | H8: =G8-C8 -> 0 | L8: =K8-G8 -> 0 | P8: =O8-K8 -> 0 | R8: =IF(D8+E8-F8+I8-J8+M8-N8=Q8,"OK",D8+E8-F8+I8-J8+M8-N8-Q8) -> OK | U8: =S8-C8 -> 0
A9: VAHIBE | B9: 0.21527778 | H9: =G9-C9 -> 0 | L9: =K9-G9 -> 0 | P9: =O9-K9 -> 0 | U9: =S9-C9 -> 0
A10: VAHIBE | B10: 0.22222222 | H10: =G10-C10 -> 0 | L10: =K10-G10 -> 0 | P10: =O10-K10 -> 0 | U10: =S10-C10 -> 0
A11: VAHIBE | B11: 0.22916667 | H11: =G11-C11 -> 0 | L11: =K11-G11 -> 0 | P11: =O11-K11 -> 0 | U11: =S11-C11 -> 0
A12: VAHIBE | B12: 0.23611111 | H12: =G12-C12 -> 0 | L12: =K12-G12 -> 0 | P12: =O12-K12 -> 0 | U12: =S12-C12 -> 0
A13: VAHIBE | B13: 0.24305556 | H13: =G13-C13 -> 0 | L13: =K13-G13 -> 0 | P13: =O13-K13 -> 0 | U13: =S13-C13 -> 0
A14: VAHIBE | B14: 0.25 | H14: =G14-C14 -> 0 | L14: =K14-G14 -> 0 | P14: =O14-K14 -> 0 | U14: =S14-C14 -> 0
A15: VAHIBE | B15: 0.25694444 | H15: =G15-C15 -> 0 | L15: =K15-G15 -> 0 | P15: =O15-K15 -> 0 | U15: =S15-C15 -> 0
A16: VAHIBE | B16: 0.26388889 | H16: =G16-C16 -> 0 | L16: =K16-G16 -> 0 | P16: =O16-K16 -> 0 | U16: =S16-C16 -> 0
A17: VAHIBE | B17: 0.27083333 | H17: =G17-C17 -> 0 | L17: =K17-G17 -> 0 | P17: =O17-K17 -> 0 | U17: =S17-C17 -> 0
A18: VAHIBE | B18: 0.27777778 | H18: =G18-C18 -> 0 | L18: =K18-G18 -> 0 | P18: =O18-K18 -> 0 | U18: =S18-C18 -> 0
A19: VAHIBE | B19: 0.28472222 | H19: =G19-C19 -> 0 | L19: =K19-G19 -> 0 | P19: =O19-K19 -> 0 | U19: =S19-C19 -> 0
A20: VAHIBE | B20: 0.29166667 | H20: =G20-C20 -> 0 | L20: =K20-G20 -> 0 | P20: =O20-K20 -> 0 | U20: =S20-C20 -> 0
... A26: VAHIBE | B26: 0.33333333 | H26: =G26-C26 -> 0 | L26: =K26-G26 -> 0 | P26: =O26-K26 -> 0 | U26: =S26-C26 -> 0
Q27: VAHIBE | U27: =SUM(U8:U26) -> 0
A28: PEM PASSAMAINTY | B28: 0.625 | H28: =G28-C28 -> 0 | L28: =K28-G28 -> 0 | P28: =O28-K28 -> 0 | U28: =S28-C28 -> 0
A29: PEM PASSAMAINTY | B29: 0.63194444 | H29: =G29-C29 -> 0 | L29: =K29-G29 -> 0 | P29: =O29-K29 -> 0 | U29: =S29-C29 -> 0
A30: PEM PASSAMAINTY | B30: 0.63888889 | H30: =G30-C30 -> 0 | L30: =K30-G30 -> 0 | P30: =O30-K30 -> 0 | U30: =S30-C30 -> 0
A31: PEM PASSAMAINTY | B31: 0.64583333 | H31: =G31-C31 -> 0 | L31: =K31-G31 -> 0 | P31: =O31-K31 -> 0 | U31: =S31-C31 -> 0
A32: PEM PASSAMAINTY | B32: 0.65277778 | H32: =G32-C32 -> 0 | L32: =K32-G32 -> 0 | P32: =O32-K32 -> 0 | U32: =S32-C32 -> 0
A33: PEM PASSAMAINTY | B33: 0.65972222 | H33: =G33-C33 -> 0 | L33: =K33-G33 -> 0 | P33: =O33-K33 -> 0 | U33: =S33-C33 -> 0
A34: PEM PASSAMAINTY | B34: 0.66666667 | H34: =G34-C34 -> 0 | L34: =K34-G34 -> 0 | P34: =O34-K34 -> 0 | U34: =S34-C34 -> 0
A35: PEM PASSAMAINTY | B35: 0.67361111 | H35: =G35-C35 -> 0 | L35: =K35-G35 -> 0 | P35: =O35-K35 -> 0 | U35: =S35-C35 -> 0
A36: PEM PASSAMAINTY | B36: 0.68055556 | H36: =G36-C36 -> 0 | L36: =K36-G36 -> 0 | P36: =O36-K36 -> 0 | U36: =S36-C36 -> 0
A37: PEM PASSAMAINTY | B37: 0.6875 | H37: =G37-C37 -> 0 | L37: =K37-G37 -> 0 | P37: =O37-K37 -> 0 | U37: =S37-C37 -> 0
A38: PEM PASSAMAINTY | B38: 0.69444444 | H38: =G38-C38 -> 0 | L38: =K38-G38 -> 0 | P38: =O38-K38 -> 0 | U38: =S38-C38 -> 0
A39: PEM PASSAMAINTY | B39: 0.70138889 | H39: =G39-C39 -> 0 | L39: =K39-G39 -> 0 | P39: =O39-K39 -> 0 | U39: =S39-C39 -> 0
... A46: PEM PASSAMAINTY | B46: 0.75 | H46: =G46-C46 -> 0 | L46: =K46-G46 -> 0 | P46: =O46-K46 -> 0 | U46: =S46-C46 -> 0
U47: =SUM(U28:U46) -> 0
U48: =U47+U27 -> 0
C49: Signature Chauffeur | I49: Signature Coordinateur

Sheet C9
A2: TYPE | B2: C9
A3: DATE | B3: =IF(ISBLANK(Feuil1!$B$3),"",Feuil1!$B$3)
A4: CHAUFFEUR | B4: =VLOOKUP(B2,'Liste chauffeur'!$B$5:$L$19,2,TRUE)&" "&VLOOKUP(B2,'Liste chauffeur'!$B$5:$L$19,3,TRUE) -> #N/A
E6: Arrêt 1 | I6: Arrêt 2 | M6: Arrêt 3 | S6: PEM PASSAMAINTY
B7: Heure théorique départ | C7: Heure réelle départ | D7: Nbre personnes montée | E7: - | F7: + | G7: Heure arrivée arrêt 1 | H7: Délai | I7: - | J7: + | K7: Heure arrivée arrêt 2 | L7: Délai | M7: - | N7: + | O7: Heure arrivée arrêt 3 | P7: Délai | Q7: Nbre personnes descente | S7: Heure arrivée finale | T7: Commentaires | U7: Temps Aller
A8: VAHIBE | B8: 0.20833333 | H8: =G8-C8 -> 0 | L8: =K8-G8 -> 0 | P8: =O8-K8 -> 0 | R8: =IF(D8+E8-F8+I8-J8+M8-N8=Q8,"OK",D8+E8-F8+I8-J8+M8-N8-Q8) -> OK | U8: =S8-C8 -> 0
A9: VAHIBE | B9: 0.21527778 | H9: =G9-C9 -> 0 | L9: =K9-G9 -> 0 | P9: =O9-K9 -> 0 | U9: =S9-C9 -> 0
A10: VAHIBE | B10: 0.22222222 | H10: =G10-C10 -> 0 | L10: =K10-G10 -> 0 | P10: =O10-K10 -> 0 | U10: =S10-C10 -> 0
A11: VAHIBE | B11: 0.22916667 | H11: =G11-C11 -> 0 | L11: =K11-G11 -> 0 | P11: =O11-K11 -> 0 | U11: =S11-C11 -> 0
A12: VAHIBE | B12: 0.23611111 | H12: =G12-C12 -> 0 | L12: =K12-G12 -> 0 | P12: =O12-K12 -> 0 | U12: =S12-C12 -> 0
A13: VAHIBE | B13: 0.24305556 | H13: =G13-C13 -> 0 | L13: =K13-G13 -> 0 | P13: =O13-K13 -> 0 | U13: =S13-C13 -> 0
A14: VAHIBE | B14: 0.25 | H14: =G14-C14 -> 0 | L14: =K14-G14 -> 0 | P14: =O14-K14 -> 0 | U14: =S14-C14 -> 0
A15: VAHIBE | B15: 0.25694444 | H15: =G15-C15 -> 0 | L15: =K15-G15 -> 0 | P15: =O15-K15 -> 0 | U15: =S15-C15 -> 0
A16: VAHIBE | B16: 0.26388889 | H16: =G16-C16 -> 0 | L16: =K16-G16 -> 0 | P16: =O16-K16 -> 0 | U16: =S16-C16 -> 0
A17: VAHIBE | B17: 0.27083333 | H17: =G17-C17 -> 0 | L17: =K17-G17 -> 0 | P17: =O17-K17 -> 0 | U17: =S17-C17 -> 0
A18: VAHIBE | B18: 0.27777778 | H18: =G18-C18 -> 0 | L18: =K18-G18 -> 0 | P18: =O18-K18 -> 0 | U18: =S18-C18 -> 0
A19: VAHIBE | B19: 0.28472222 | H19: =G19-C19 -> 0 | L19: =K19-G19 -> 0 | P19: =O19-K19 -> 0 | U19: =S19-C19 -> 0
A20: VAHIBE | B20: 0.29166667 | H20: =G20-C20 -> 0 | L20: =K20-G20 -> 0 | P20: =O20-K20 -> 0 | U20: =S20-C20 -> 0
... A26: VAHIBE | B26: 0.33333333 | H26: =G26-C26 -> 0 | L26: =K26-G26 -> 0 | P26: =O26-K26 -> 0 | U26: =S26-C26 -> 0
Q27: VAHIBE | U27: =SUM(U8:U26) -> 0
A28: PEM PASSAMAINTY | B28: 0.625 | H28: =G28-C28 -> 0 | L28: =K28-G28 -> 0 | P28: =O28-K28 -> 0 | U28: =S28-C28 -> 0
A29: PEM PASSAMAINTY | B29: 0.63194444 | H29: =G29-C29 -> 0 | L29: =K29-G29 -> 0 | P29: =O29-K29 -> 0 | U29: =S29-C29 -> 0
A30: PEM PASSAMAINTY | B30: 0.63888889 | H30: =G30-C30 -> 0 | L30: =K30-G30 -> 0 | P30: =O30-K30 -> 0 | U30: =S30-C30 -> 0
A31: PEM PASSAMAINTY | B31: 0.64583333 | H31: =G31-C31 -> 0 | L31: =K31-G31 -> 0 | P31: =O31-K31 -> 0 | U31: =S31-C31 -> 0
A32: PEM PASSAMAINTY | B32: 0.65277778 | H32: =G32-C32 -> 0 | L32: =K32-G32 -> 0 | P32: =O32-K32 -> 0 | U32: =S32-C32 -> 0
A33: PEM PASSAMAINTY | B33: 0.65972222 | H33: =G33-C33 -> 0 | L33: =K33-G33 -> 0 | P33: =O33-K33 -> 0 | U33: =S33-C33 -> 0
A34: PEM PASSAMAINTY | B34: 0.66666667 | H34: =G34-C34 -> 0 | L34: =K34-G34 -> 0 | P34: =O34-K34 -> 0 | U34: =S34-C34 -> 0
A35: PEM PASSAMAINTY | B35: 0.67361111 | H35: =G35-C35 -> 0 | L35: =K35-G35 -> 0 | P35: =O35-K35 -> 0 | U35: =S35-C35 -> 0
A36: PEM PASSAMAINTY | B36: 0.68055556 | H36: =G36-C36 -> 0 | L36: =K36-G36 -> 0 | P36: =O36-K36 -> 0 | U36: =S36-C36 -> 0
A37: PEM PASSAMAINTY | B37: 0.6875 | H37: =G37-C37 -> 0 | L37: =K37-G37 -> 0 | P37: =O37-K37 -> 0 | U37: =S37-C37 -> 0
A38: PEM PASSAMAINTY | B38: 0.69444444 | H38: =G38-C38 -> 0 | L38: =K38-G38 -> 0 | P38: =O38-K38 -> 0 | U38: =S38-C38 -> 0
A39: PEM PASSAMAINTY | B39: 0.70138889 | H39: =G39-C39 -> 0 | L39: =K39-G39 -> 0 | P39: =O39-K39 -> 0 | U39: =S39-C39 -> 0
... A46: PEM PASSAMAINTY | B46: 0.75 | H46: =G46-C46 -> 0 | L46: =K46-G46 -> 0 | P46: =O46-K46 -> 0 | U46: =S46-C46 -> 0
U47: =SUM(U28:U46) -> 0
U48: =U47+U27 -> 0
C49: Signature Chauffeur | I49: Signature Coordinateur

Sheet C10
A2: TYPE | B2: C10
A3: DATE | B3: =IF(ISBLANK(Feuil1!$B$3),"",Feuil1!$B$3)
A4: CHAUFFEUR | B4: =VLOOKUP(B2,'Liste chauffeur'!$B$5:$L$19,2,TRUE)&" "&VLOOKUP(B2,'Liste chauffeur'!$B$5:$L$19,3,TRUE) -> #N/A
E6: Arrêt 1 | I6: Arrêt 2 | M6: Arrêt 3 | S6: PEM PASSAMAINTY
B7: Heure théorique départ | C7: Heure réelle départ | D7: Nbre personnes montée | E7: - | F7: + | G7: Heure arrivée arrêt 1 | H7: Délai | I7: - | J7: + | K7: Heure arrivée arrêt 2 | L7: Délai | M7: - | N7: + | O7: Heure arrivée arrêt 3 | P7: Délai | Q7: Nbre personnes descente | S7: Heure arrivée finale | T7: Commentaires | U7: Temps Aller
A8: VAHIBE | B8: 0.20833333 | H8: =G8-C8 -> 0 | L8: =K8-G8 -> 0 | P8: =O8-K8 -> 0 | R8: =IF(D8+E8-F8+I8-J8+M8-N8=Q8,"OK",D8+E8-F8+I8-J8+M8-N8-Q8) -> OK | U8: =S8-C8 -> 0
A9: VAHIBE | B9: 0.21527778 | H9: =G9-C9 -> 0 | L9: =K9-G9 -> 0 | P9: =O9-K9 -> 0 | U9: =S9-C9 -> 0
A10: VAHIBE | B10: 0.22222222 | H10: =G10-C10 -> 0 | L10: =K10-G10 -> 0 | P10: =O10-K10 -> 0 | U10: =S10-C10 -> 0
A11: VAHIBE | B11: 0.22916667 | H11: =G11-C11 -> 0 | L11: =K11-G11 -> 0 | P11: =O11-K11 -> 0 | U11: =S11-C11 -> 0
A12: VAHIBE | B12: 0.23611111 | H12: =G12-C12 -> 0 | L12: =K12-G12 -> 0 | P12: =O12-K12 -> 0 | U12: =S12-C12 -> 0
A13: VAHIBE | B13: 0.24305556 | H13: =G13-C13 -> 0 | L13: =K13-G13 -> 0 | P13: =O13-K13 -> 0 | U13: =S13-C13 -> 0
A14: VAHIBE | B14: 0.25 | H14: =G14-C14 -> 0 | L14: =K14-G14 -> 0 | P14: =O14-K14 -> 0 | U14: =S14-C14 -> 0
A15: VAHIBE | B15: 0.25694444 | H15: =G15-C15 -> 0 | L15: =K15-G15 -> 0 | P15: =O15-K15 -> 0 | U15: =S15-C15 -> 0
A16: VAHIBE | B16: 0.26388889 | H16: =G16-C16 -> 0 | L16: =K16-G16 -> 0 | P16: =O16-K16 -> 0 | U16: =S16-C16 -> 0
A17: VAHIBE | B17: 0.27083333 | H17: =G17-C17 -> 0 | L17: =K17-G17 -> 0 | P17: =O17-K17 -> 0 | U17: =S17-C17 -> 0
A18: VAHIBE | B18: 0.27777778 | H18: =G18-C18 -> 0 | L18: =K18-G18 -> 0 | P18: =O18-K18 -> 0 | U18: =S18-C18 -> 0
A19: VAHIBE | B19: 0.28472222 | H19: =G19-C19 -> 0 | L19: =K19-G19 -> 0 | P19: =O19-K19 -> 0 | U19: =S19-C19 -> 0
A20: VAHIBE | B20: 0.29166667 | H20: =G20-C20 -> 0 | L20: =K20-G20 -> 0 | P20: =O20-K20 -> 0 | U20: =S20-C20 -> 0
... A26: VAHIBE | B26: 0.33333333 | H26: =G26-C26 -> 0 | L26: =K26-G26 -> 0 | P26: =O26-K26 -> 0 | U26: =S26-C26 -> 0
Q27: VAHIBE | U27: =SUM(U8:U26) -> 0
A28: PEM PASSAMAINTY | B28: 0.625 | H28: =G28-C28 -> 0 | L28: =K28-G28 -> 0 | P28: =O28-K28 -> 0 | U28: =S28-C28 -> 0
A29: PEM PASSAMAINTY | B29: 0.63194444 | H29: =G29-C29 -> 0 | L29: =K29-G29 -> 0 | P29: =O29-K29 -> 0 | U29: =S29-C29 -> 0
A30: PEM PASSAMAINTY | B30: 0.63888889 | H30: =G30-C30 -> 0 | L30: =K30-G30 -> 0 | P30: =O30-K30 -> 0 | U30: =S30-C30 -> 0
A31: PEM PASSAMAINTY | B31: 0.64583333 | H31: =G31-C31 -> 0 | L31: =K31-G31 -> 0 | P31: =O31-K31 -> 0 | U31: =S31-C31 -> 0
A32: PEM PASSAMAINTY | B32: 0.65277778 | H32: =G32-C32 -> 0 | L32: =K32-G32 -> 0 | P32: =O32-K32 -> 0 | U32: =S32-C32 -> 0
A33: PEM PASSAMAINTY | B33: 0.65972222 | H33: =G33-C33 -> 0 | L33: =K33-G33 -> 0 | P33: =O33-K33 -> 0 | U33: =S33-C33 -> 0
A34: PEM PASSAMAINTY | B34: 0.66666667 | H34: =G34-C34 -> 0 | L34: =K34-G34 -> 0 | P34: =O34-K34 -> 0 | U34: =S34-C34 -> 0
A35: PEM PASSAMAINTY | B35: 0.67361111 | H35: =G35-C35 -> 0 | L35: =K35-G35 -> 0 | P35: =O35-K35 -> 0 | U35: =S35-C35 -> 0
A36: PEM PASSAMAINTY | B36: 0.68055556 | H36: =G36-C36 -> 0 | L36: =K36-G36 -> 0 | P36: =O36-K36 -> 0 | U36: =S36-C36 -> 0
A37: PEM PASSAMAINTY | B37: 0.6875 | H37: =G37-C37 -> 0 | L37: =K37-G37 -> 0 | P37: =O37-K37 -> 0 | U37: =S37-C37 -> 0
A38: PEM PASSAMAINTY | B38: 0.69444444 | H38: =G38-C38 -> 0 | L38: =K38-G38 -> 0 | P38: =O38-K38 -> 0 | U38: =S38-C38 -> 0
A39: PEM PASSAMAINTY | B39: 0.70138889 | H39: =G39-C39 -> 0 | L39: =K39-G39 -> 0 | P39: =O39-K39 -> 0 | U39: =S39-C39 -> 0
... A46: PEM PASSAMAINTY | B46: 0.75 | H46: =G46-C46 -> 0 | L46: =K46-G46 -> 0 | P46: =O46-K46 -> 0 | U46: =S46-C46 -> 0
U47: =SUM(U28:U46) -> 0
U48: =U47+U27 -> 0
C49: Signature Chauffeur | I49: Signature Coordinateur

Sheet C11
A2: TYPE | B2: C11
A3: DATE | B3: =IF(ISBLANK(Feuil1!$B$3),"",Feuil1!$B$3)
A4: CHAUFFEUR | B4: =VLOOKUP(B2,'Liste chauffeur'!$B$5:$L$19,2,TRUE)&" "&VLOOKUP(B2,'Liste chauffeur'!$B$5:$L$19,3,TRUE) -> #N/A
E6: Arrêt 1 | I6: Arrêt 2 | M6: Arrêt 3 | S6: PEM PASSAMAINTY
B7: Heure théorique départ | C7: Heure réelle départ | D7: Nbre personnes montée | E7: - | F7: + | G7: Heure arrivée arrêt 1 | H7: Délai | I7: - | J7: + | K7: Heure arrivée arrêt 2 | L7: Délai | M7: - | N7: + | O7: Heure arrivée arrêt 3 | P7: Délai | Q7: Nbre personnes descente | S7: Heure arrivée finale | T7: Commentaires | U7: Temps Aller
A8: VAHIBE | B8: 0.20833333 | H8: =G8-C8 -> 0 | L8: =K8-G8 -> 0 | P8: =O8-K8 -> 0 | R8: =IF(D8+E8-F8+I8-J8+M8-N8=Q8,"OK",D8+E8-F8+I8-J8+M8-N8-Q8) -> OK | U8: =S8-C8 -> 0
A9: VAHIBE | B9: 0.21527778 | H9: =G9-C9 -> 0 | L9: =K9-G9 -> 0 | P9: =O9-K9 -> 0 | U9: =S9-C9 -> 0
A10: VAHIBE | B10: 0.22222222 | H10: =G10-C10 -> 0 | L10: =K10-G10 -> 0 | P10: =O10-K10 -> 0 | U10: =S10-C10 -> 0
A11: VAHIBE | B11: 0.22916667 | H11: =G11-C11 -> 0 | L11: =K11-G11 -> 0 | P11: =O11-K11 -> 0 | U11: =S11-C11 -> 0
A12: VAHIBE | B12: 0.23611111 | H12: =G12-C12 -> 0 | L12: =K12-G12 -> 0 | P12: =O12-K12 -> 0 | U12: =S12-C12 -> 0
A13: VAHIBE | B13: 0.24305556 | H13: =G13-C13 -> 0 | L13: =K13-G13 -> 0 | P13: =O13-K13 -> 0 | U13: =S13-C13 -> 0
A14: VAHIBE | B14: 0.25 | H14: =G14-C14 -> 0 | L14: =K14-G14 -> 0 | P14: =O14-K14 -> 0 | U14: =S14-C14 -> 0
A15: VAHIBE | B15: 0.25694444 | H15: =G15-C15 -> 0 | L15: =K15-G15 -> 0 | P15: =O15-K15 -> 0 | U15: =S15-C15 -> 0
A16: VAHIBE | B16: 0.26388889 | H16: =G16-C16 -> 0 | L16: =K16-G16 -> 0 | P16: =O16-K16 -> 0 | U16: =S16-C16 -> 0
A17: VAHIBE | B17: 0.27083333 | H17: =G17-C17 -> 0 | L17: =K17-G17 -> 0 | P17: =O17-K17 -> 0 | U17: =S17-C17 -> 0
A18: VAHIBE | B18: 0.27777778 | H18: =G18-C18 -> 0 | L18: =K18-G18 -> 0 | P18: =O18-K18 -> 0 | U18: =S18-C18 -> 0
A19: VAHIBE | B19: 0.28472222 | H19: =G19-C19 -> 0 | L19: =K19-G19 -> 0 | P19: =O19-K19 -> 0 | U19: =S19-C19 -> 0
A20: VAHIBE | B20: 0.29166667 | H20: =G20-C20 -> 0 | L20: =K20-G20 -> 0 | P20: =O20-K20 -> 0 | U20: =S20-C20 -> 0
... A26: VAHIBE | B26: 0.33333333 | H26: =G26-C26 -> 0 | L26: =K26-G26 -> 0 | P26: =O26-K26 -> 0 | U26: =S26-C26 -> 0
Q27: VAHIBE | U27: =SUM(U8:U26) -> 0
A28: PEM PASSAMAINTY | B28: 0.625 | H28: =G28-C28 -> 0 | L28: =K28-G28 -> 0 | P28: =O28-K28 -> 0 | U28: =S28-C28 -> 0
A29: PEM PASSAMAINTY | B29: 0.63194444 | H29: =G29-C29 -> 0 | L29: =K29-G29 -> 0 | P29: =O29-K29 -> 0 | U29: =S29-C29 -> 0
A30: PEM PASSAMAINTY | B30: 0.63888889 | H30: =G30-C30 -> 0 | L30: =K30-G30 -> 0 | P30: =O30-K30 -> 0 | U30: =S30-C30 -> 0
A31: PEM PASSAMAINTY | B31: 0.64583333 | H31: =G31-C31 -> 0 | L31: =K31-G31 -> 0 | P31: =O31-K31 -> 0 | U31: =S31-C31 -> 0
A32: PEM PASSAMAINTY | B32: 0.65277778 | H32: =G32-C32 -> 0 | L32: =K32-G32 -> 0 | P32: =O32-K32 -> 0 | U32: =S32-C32 -> 0
A33: PEM PASSAMAINTY | B33: 0.65972222 | H33: =G33-C33 -> 0 | L33: =K33-G33 -> 0 | P33: =O33-K33 -> 0 | U33: =S33-C33 -> 0
A34: PEM PASSAMAINTY | B34: 0.66666667 | H34: =G34-C34 -> 0 | L34: =K34-G34 -> 0 | P34: =O34-K34 -> 0 | U34: =S34-C34 -> 0
A35: PEM PASSAMAINTY | B35: 0.67361111 | H35: =G35-C35 -> 0 | L35: =K35-G35 -> 0 | P35: =O35-K35 -> 0 | U35: =S35-C35 -> 0
A36: PEM PASSAMAINTY | B36: 0.68055556 | H36: =G36-C36 -> 0 | L36: =K36-G36 -> 0 | P36: =O36-K36 -> 0 | U36: =S36-C36 -> 0
A37: PEM PASSAMAINTY | B37: 0.6875 | H37: =G37-C37 -> 0 | L37: =K37-G37 -> 0 | P37: =O37-K37 -> 0 | U37: =S37-C37 -> 0
A38: PEM PASSAMAINTY | B38: 0.69444444 | H38: =G38-C38 -> 0 | L38: =K38-G38 -> 0 | P38: =O38-K38 -> 0 | U38: =S38-C38 -> 0
A39: PEM PASSAMAINTY | B39: 0.70138889 | H39: =G39-C39 -> 0 | L39: =K39-G39 -> 0 | P39: =O39-K39 -> 0 | U39: =S39-C39 -> 0
... A46: PEM PASSAMAINTY | B46: 0.75 | H46: =G46-C46 -> 0 | L46: =K46-G46 -> 0 | P46: =O46-K46 -> 0 | U46: =S46-C46 -> 0
U47: =SUM(U28:U46) -> 0
U48: =U47+U27 -> 0
C49: Signature Chauffeur | I49: Signature Coordinateur

Sheet C12
A2: TYPE | B2: C12
A3: DATE | B3: =IF(ISBLANK(Feuil1!$B$3),"",Feuil1!$B$3)
A4: CHAUFFEUR | B4: MOHAMED (BOINA RIEZIKI ZENA DHURARI)
E6: Arrêt 1 | I6: Arrêt 2 | M6: Arrêt 3 | S6: PEM PASSAMAINTY
B7: Heure théorique départ | C7: Heure réelle départ | D7: Nbre personnes montée | E7: - | F7: + | G7: Heure arrivée arrêt 1 | H7: Délai | I7: - | J7: + | K7: Heure arrivée arrêt 2 | L7: Délai | M7: - | N7: + | O7: Heure arrivée arrêt 3 | P7: Délai | Q7: Nbre personnes descente | S7: Heure arrivée finale | T7: Commentaires | U7: Temps Aller
A8: VAHIBE | B8: 0.20833333 | H8: =G8-C8 -> 0 | L8: =K8-G8 -> 0 | P8: =O8-K8 -> 0 | R8: =IF(D8+E8-F8+I8-J8+M8-N8=Q8,"OK",D8+E8-F8+I8-J8+M8-N8-Q8) -> OK | U8: =S8-C8 -> 0
A9: VAHIBE | B9: 0.21527778 | H9: =G9-C9 -> 0 | L9: =K9-G9 -> 0 | P9: =O9-K9 -> 0 | U9: =S9-C9 -> 0
A10: VAHIBE | B10: 0.22222222 | H10: =G10-C10 -> 0 | L10: =K10-G10 -> 0 | P10: =O10-K10 -> 0 | U10: =S10-C10 -> 0
A11: VAHIBE | B11: 0.22916667 | H11: =G11-C11 -> 0 | L11: =K11-G11 -> 0 | P11: =O11-K11 -> 0 | U11: =S11-C11 -> 0
A12: VAHIBE | B12: 0.23611111 | H12: =G12-C12 -> 0 | L12: =K12-G12 -> 0 | P12: =O12-K12 -> 0 | U12: =S12-C12 -> 0
A13: VAHIBE | B13: 0.24305556 | H13: =G13-C13 -> 0 | L13: =K13-G13 -> 0 | P13: =O13-K13 -> 0 | U13: =S13-C13 -> 0
A14: VAHIBE | B14: 0.25 | H14: =G14-C14 -> 0 | L14: =K14-G14 -> 0 | P14: =O14-K14 -> 0 | U14: =S14-C14 -> 0
A15: VAHIBE | B15: 0.25694444 | H15: =G15-C15 -> 0 | L15: =K15-G15 -> 0 | P15: =O15-K15 -> 0 | U15: =S15-C15 -> 0
A16: VAHIBE | B16: 0.26388889 | H16: =G16-C16 -> 0 | L16: =K16-G16 -> 0 | P16: =O16-K16 -> 0 | U16: =S16-C16 -> 0
A17: VAHIBE | B17: 0.27083333 | H17: =G17-C17 -> 0 | L17: =K17-G17 -> 0 | P17: =O17-K17 -> 0 | U17: =S17-C17 -> 0
A18: VAHIBE | B18: 0.27777778 | H18: =G18-C18 -> 0 | L18: =K18-G18 -> 0 | P18: =O18-K18 -> 0 | U18: =S18-C18 -> 0
A19: VAHIBE | B19: 0.28472222 | H19: =G19-C19 -> 0 | L19: =K19-G19 -> 0 | P19: =O19-K19 -> 0 | U19: =S19-C19 -> 0
A20: VAHIBE | B20: 0.29166667 | H20: =G20-C20 -> 0 | L20: =K20-G20 -> 0 | P20: =O20-K20 -> 0 | U20: =S20-C20 -> 0
... A26: VAHIBE | B26: 0.33333333 | H26: =G26-C26 -> 0 | L26: =K26-G26 -> 0 | P26: =O26-K26 -> 0 | U26: =S26-C26 -> 0
Q27: VAHIBE | U27: =SUM(U8:U26) -> 0
A28: PEM PASSAMAINTY | B28: 0.625 | H28: =G28-C28 -> 0 | L28: =K28-G28 -> 0 | P28: =O28-K28 -> 0 | U28: =S28-C28 -> 0
A29: PEM PASSAMAINTY | B29: 0.63194444 | H29: =G29-C29 -> 0 | L29: =K29-G29 -> 0 | P29: =O29-K29 -> 0 | U29: =S29-C29 -> 0
A30: PEM PASSAMAINTY | B30: 0.63888889 | H30: =G30-C30 -> 0 | L30: =K30-G30 -> 0 | P30: =O30-K30 -> 0 | U30: =S30-C30 -> 0
A31: PEM PASSAMAINTY | B31: 0.64583333 | H31: =G31-C31 -> 0 | L31: =K31-G31 -> 0 | P31: =O31-K31 -> 0 | U31: =S31-C31 -> 0
A32: PEM PASSAMAINTY | B32: 0.65277778 | H32: =G32-C32 -> 0 | L32: =K32-G32 -> 0 | P32: =O32-K32 -> 0 | U32: =S32-C32 -> 0
A33: PEM PASSAMAINTY | B33: 0.65972222 | H33: =G33-C33 -> 0 | L33: =K33-G33 -> 0 | P33: =O33-K33 -> 0 | U33: =S33-C33 -> 0
A34: PEM PASSAMAINTY | B34: 0.66666667 | H34: =G34-C34 -> 0 | L34: =K34-G34 -> 0 | P34: =O34-K34 -> 0 | U34: =S34-C34 -> 0
A35: PEM PASSAMAINTY | B35: 0.67361111 | H35: =G35-C35 -> 0 | L35: =K35-G35 -> 0 | P35: =O35-K35 -> 0 | U35: =S35-C35 -> 0
A36: PEM PASSAMAINTY | B36: 0.68055556 | H36: =G36-C36 -> 0 | L36: =K36-G36 -> 0 | P36: =O36-K36 -> 0 | U36: =S36-C36 -> 0
A37: PEM PASSAMAINTY | B37: 0.6875 | H37: =G37-C37 -> 0 | L37: =K37-G37 -> 0 | P37: =O37-K37 -> 0 | U37: =S37-C37 -> 0
A38: PEM PASSAMAINTY | B38: 0.69444444 | H38: =G38-C38 -> 0 | L38: =K38-G38 -> 0 | P38: =O38-K38 -> 0 | U38: =S38-C38 -> 0
A39: PEM PASSAMAINTY | B39: 0.70138889 | H39: =G39-C39 -> 0 | L39: =K39-G39 -> 0 | P39: =O39-K39 -> 0 | U39: =S39-C39 -> 0
... A46: PEM PASSAMAINTY | B46: 0.75 | H46: =G46-C46 -> 0 | L46: =K46-G46 -> 0 | P46: =O46-K46 -> 0 | U46: =S46-C46 -> 0
U47: =SUM(U28:U46) -> 0
U48: =U47+U27 -> 0
C49: Signature Chauffeur | I49: Signature Coordinateur

Sheet C13
A2: TYPE | B2: C13
A3: DATE | B3: =IF(ISBLANK(Feuil1!$B$3),"",Feuil1!$B$3)
A4: CHAUFFEUR | B4: =VLOOKUP(B2,'Liste chauffeur'!$B$5:$L$19,2,TRUE)&" "&VLOOKUP(B2,'Liste chauffeur'!$B$5:$L$19,3,TRUE) -> #N/A
E6: Arrêt 1 | I6: Arrêt 2 | M6: Arrêt 3 | S6: PEM PASSAMAINTY
B7: Heure théorique départ | C7: Heure réelle départ | D7: Nbre personnes montée | E7: - | F7: + | G7: Heure arrivée arrêt 1 | H7: Délai | I7: - | J7: + | K7: Heure arrivée arrêt 2 | L7: Délai | M7: - | N7: + | O7: Heure arrivée arrêt 3 | P7: Délai | Q7: Nbre personnes descente | S7: Heure arrivée finale | T7: Commentaires | U7: Temps Aller
A8: VAHIBE | B8: 0.20833333 | H8: =G8-C8 -> 0 | L8: =K8-G8 -> 0 | P8: =O8-K8 -> 0 | R8: =IF(D8+E8-F8+I8-J8+M8-N8=Q8,"OK",D8+E8-F8+I8-J8+M8-N8-Q8) -> OK | U8: =S8-C8 -> 0
A9: VAHIBE | B9: 0.21527778 | H9: =G9-C9 -> 0 | L9: =K9-G9 -> 0 | P9: =O9-K9 -> 0 | U9: =S9-C9 -> 0
A10: VAHIBE | B10: 0.22222222 | H10: =G10-C10 -> 0 | L10: =K10-G10 -> 0 | P10: =O10-K10 -> 0 | U10: =S10-C10 -> 0
A11: VAHIBE | B11: 0.22916667 | H11: =G11-C11 -> 0 | L11: =K11-G11 -> 0 | P11: =O11-K11 -> 0 | U11: =S11-C11 -> 0
A12: VAHIBE | B12: 0.23611111 | H12: =G12-C12 -> 0 | L12: =K12-G12 -> 0 | P12: =O12-K12 -> 0 | U12: =S12-C12 -> 0
A13: VAHIBE | B13: 0.24305556 | H13: =G13-C13 -> 0 | L13: =K13-G13 -> 0 | P13: =O13-K13 -> 0 | U13: =S13-C13 -> 0
A14: VAHIBE | B14: 0.25 | H14: =G14-C14 -> 0 | L14: =K14-G14 -> 0 | P14: =O14-K14 -> 0 | U14: =S14-C14 -> 0
A15: VAHIBE | B15: 0.25694444 | H15: =G15-C15 -> 0 | L15: =K15-G15 -> 0 | P15: =O15-K15 -> 0 | U15: =S15-C15 -> 0
A16: VAHIBE | B16: 0.26388889 | H16: =G16-C16 -> 0 | L16: =K16-G16 -> 0 | P16: =O16-K16 -> 0 | U16: =S16-C16 -> 0
A17: VAHIBE | B17: 0.27083333 | H17: =G17-C17 -> 0 | L17: =K17-G17 -> 0 | P17: =O17-K17 -> 0 | U17: =S17-C17 -> 0
A18: VAHIBE | B18: 0.27777778 | H18: =G18-C18 -> 0 | L18: =K18-G18 -> 0 | P18: =O18-K18 -> 0 | U18: =S18-C18 -> 0
A19: VAHIBE | B19: 0.28472222 | H19: =G19-C19 -> 0 | L19: =K19-G19 -> 0 | P19: =O19-K19 -> 0 | U19: =S19-C19 -> 0
