Workbook

Sheet Feuil1
A3: DATE
A4: CHAUFFEUR
E6: Arrêt 1 | I6: Arrêt 2 | M6: Arrêt 3 | Q6: PEM PASSAMAINTY
B7: Heure théorique départ | C7: Heure réelle départ | D7: Nbre personnes + | E7: Nbre personnes + | F7: Nbre personnes - | G7: Heure arrivée arrêt 1 | H7: Délai | I7: Nbre personnes + | J7: Nbre personnes - | K7: Heure arrivée arrêt 2 | L7: Délai | M7: Nbre personnes + | N7: Nbre personnes - | O7: Heure arrivée arrêt 3 | P7: Délai | Q7: Nbre personnes - | S7: Heure arrivée finale | T7: Commentaires | U7: Temps Aller
A8: VAHIBE | B8: 0.20833333 | H8: =G8-C8 -> 0 | L8: =K8-G8 -> 0 | P8: =O8-K8 -> 0 | R8: =IF(D8+E8-F8+I8-J8+M8-N8=Q8,"OK",D8+E8-F8+I8-J8+M8-N8-Q8) -> OK | U8: =S8-C8 -> 0
A9: VAHIBE | B9: 0.21527778 | H9: =G9-C9 -> 0 | L9: =K9-G9 -> 0 | P9: =O9-K9 -> 0 | U9: =S9-C9 -> 0
A10: VAHIBE | B10: 0.22222222 | H10: =G10-C10 -> 0 | L10: =K10-G10 -> 0 | P10: =O10-K10 -> 0 | U10: =S10-C10 -> 0
A11: VAHIBE | B11: 0.22916667 | H11: =G11-C11 -> 0 | L11: =K11-G11 -> 0 | P11: =O11-K11 -> 0 | U11: =S11-C11 -> 0
A12: VAHIBE | B12: 0.23611111 | H12: =G12-C12 -> 0 | L12: =K12-G12 -> 0 | P12: =O12-K12 -> 0 | U12: =S12-C12 -> 0
A13: VAHIBE | B13: 0.24305556 | H13: =G13-C13 -> 0 | L13: =K13-G13 -> 0 | P13: =O13-K13 -> 0 | U13: =S13-C13 -> 0
A14: VAHIBE | B14: 0.25 | H14: =G14-C14 -> 0 | L14: =K14-G14 -> 0 | P14: =O14-K14 -> 0 | U14: =S14-C14 -> 0
A15: VAHIBE | B15: 0.25694444 | H15: =G15-C15 -> 0 | L15: =K15-G15 -> 0 | P15: =O15-K15 -> 0 | U15: =S15-C15 -> 0
A16: VAHIBE | B16: 0.26388889 | H16: =G16-C16 -> 0 | L16: =K16-G16 -> 0 | P16: =O16-K16 -> 0 | U16: =S16-C16 -> 0
A17: VAHIBE | B17: 0.27083333 | H17: =G17-C17 -> 0 | L17: =K17-G17 -> 0 | P17: =O17-K17 -> 0 | U17: =S17-C17 -> 0
A18: VAHIBE | B18: 0.27777778 | H18: =G18-C18 -> 0 | L18: =K18-G18 -> 0 | P18: =O18-K18 -> 0 | U18: =S18-C18 -> 0
A19: VAHIBE | B19: 0.28472222 | H19: =G19-C19 -> 0 | L19: =K19-G19 -> 0 | P19: =O19-K19 -> 0 | U19: =S19-C19 -> 0
A20: VAHIBE | B20: 0.29166667 | H20: =G20-C20 -> 0 | L20: =K20-G20 -> 0 | P20: =O20-K20 -> 0 | U20: =S20-C20 -> 0
... A26: VAHIBE | B26: 0.33333333 | H26: =G26-C26 -> 0 | L26: =K26-G26 -> 0 | P26: =O26-K26 -> 0 | U26: =S26-C26 -> 0
Q27: VAHIBE | U27: =SUM(U8:U26) -> 0
A28: PEM PASSAMAINTY | B28: 0.625 | H28: =G28-C28 -> 0 | L28: =K28-G28 -> 0 | P28: =O28-K28 -> 0 | U28: =S28-C28 -> 0
A29: PEM PASSAMAINTY | B29: 0.63194444 | H29: =G29-C29 -> 0 | L29: =K29-G29 -> 0 | P29: =O29-K29 -> 0 | U29: =S29-C29 -> 0
A30: PEM PASSAMAINTY | B30: 0.63888889 | H30: =G30-C30 -> 0 | L30: =K30-G30 -> 0 | P30: =O30-K30 -> 0 | U30: =S30-C30 -> 0
A31: PEM PASSAMAINTY | B31: 0.64583333 | H31: =G31-C31 -> 0 | L31: =K31-G31 -> 0 | P31: =O31-K31 -> 0 | U31: =S31-C31 -> 0
A32: PEM PASSAMAINTY | B32: 0.65277778 | H32: =G32-C32 -> 0 | L32: =K32-G32 -> 0 | P32: =O32-K32 -> 0 | U32: =S32-C32 -> 0
A33: PEM PASSAMAINTY | B33: 0.65972222 | H33: =G33-C33 -> 0 | L33: =K33-G33 -> 0 | P33: =O33-K33 -> 0 | U33: =S33-C33 -> 0
A34: PEM PASSAMAINTY | B34: 0.66666667 | H34: =G34-C34 -> 0 | L34: =K34-G34 -> 0 | P34: =O34-K34 -> 0 | U34: =S34-C34 -> 0
A35: PEM PASSAMAINTY | B35: 0.67361111 | H35: =G35-C35 -> 0 | L35: =K35-G35 -> 0 | P35: =O35-K35 -> 0 | U35: =S35-C35 -> 0
A36: PEM PASSAMAINTY | B36: 0.68055556 | H36: =G36-C36 -> 0 | L36: =K36-G36 -> 0 | P36: =O36-K36 -> 0 | U36: =S36-C36 -> 0
A37: PEM PASSAMAINTY | B37: 0.6875 | H37: =G37-C37 -> 0 | L37: =K37-G37 -> 0 | P37: =O37-K37 -> 0 | U37: =S37-C37 -> 0
A38: PEM PASSAMAINTY | B38: 0.69444444 | H38: =G38-C38 -> 0 | L38: =K38-G38 -> 0 | P38: =O38-K38 -> 0 | U38: =S38-C38 -> 0
A39: PEM PASSAMAINTY | B39: 0.70138889 | H39: =G39-C39 -> 0 | L39: =K39-G39 -> 0 | P39: =O39-K39 -> 0 | U39: =S39-C39 -> 0
... A46: PEM PASSAMAINTY | B46: 0.75 | H46: =G46-C46 -> 0 | L46: =K46-G46 -> 0 | P46: =O46-K46 -> 0 | U46: =S46-C46 -> 0
U47: =SUM(U28:U46) -> 0
U48: =U47+U27 -> 0
C49: Signature Chauffeur | I49: Signature Coordinateur

Sheet REUNION DU 28.04
B1: N° | C1: CADEMA | D1: STATUT | E1: LICENCE TRANSPORTEUR | F1: SIREN LICENCE | G1: VALIDITE LICENCE TRANSP | H1: N° | I1: N° Chauffeur | J1: Type | K1: Nom | L1: Prénom | M1: Téléphone | N1: Mail | O1: Siret | P1: Secteur d'activité | Q1: N° licence | R1: CARTE CONDUCTEUR | S1: VALIDITE CARTE CONDUCTEUR | T1: N° IMMATRICULATION CARTE GRISE | U1: DATE IMMATRICULATION | V1: AGE DU VEHICULE | W1: Type de vehicule | X1: ETAT VEHICULE | Y1: RDV MAY EQUIP | Z1: HABILLAGE | AA1: REGLT HABILLAGE | AB1: EQUIPEMENT | AC1: HABILLAGE 2021 | AD1: HABILLAGE 2023 | AE1: IDENTITE | AF1: NATIONALITE | AG1: VALIDITE CARTE SEJOUR | AH1: CARTE VITALE | AI1: ASSURANCES | AJ1: FACTURE _3 MOIS | AK1: IMPOTS | AL1: PHOTO | AM1: N° AGC | AN1: Capital souscrit | AO1: Année de souscription | AP1: Cotisations versées en 2021 | AQ1: COTISATIONS 2023 | AR1: COTISATIONS 2024 | AS1: N° Rue | AT1: Adresse | AU1: Code postal | AV1: Commune | AW1: REMARQUES
A2: 1 | B2: 11 | C2: CADEMA 1 | D2: AO | E2: NON | F2: - | G2: - | H2: 1 | I2: C4 | J2: C2 | K2: ABDOU MINIHADJI | L2: Amada | M2: 0639 65 03 93 | N2: abdouminihadjiamada@hotmail.com | O2: 066 311 101 000 19 | P2: Centre Sud | Q2: 976-CS-057 | R2: 505 | S2: 45305 | T2: FY-654-BF | U2: 44279 | V2: =2024-YEAR(U2) -> 3 | W2: 9 PLACES | X2: BON | Z2: OUI | AA2: _ | AB2: NON | AC2: OUI | AE2: 43262 | AF2: F | AG2: _ | AH2: NON | AI2: NON | AJ2: 2020 | AL2: OUI | AM2: 2020/13 | AN2: 510 | AO2: 43466 | AP2: 450 | AS2: 64 | AT2: Avenue de rassi | AU2: 97670 | AV2: Chiconi | AW2: ancien gérant - Habillage 2021
A3: 33 | B3: 17 | C3: CADEMA 1 | D3: AO | E3: NON | F3: - | G3: - | H3: 2 | I3: C6 | J3: C10 | K3: ADINANI | L3: Zoubert | M3: 0639 25 77 76 | N3: zoubert.adinani2@gmail.com | O3: 799 358 700 00018 | P3: Mamoudzou | Q3: 976-M-447 | R3: 1050 | S3: 46342 | T3: GR-407-DV | U3: 45182 | V3: =2024-YEAR(U3) -> 1 | W3: 9 PLACES | X3: BON | Y3: 45406 | Z3: NON | AA3: OUI | AB3: NON | AC3: NON | AD3: A venir | AE3: 48415 | AF3: F | AG3: _ | AH3: OUI | AI3: OUI | AJ3: OUI | AK3: 2022 | AL3: OUI | AN3: 510 | AO3: 43466 | AP3: 250 | AQ3: NON | AR3: NON | AT3: Tahiti plage route de poroani | AU3: 97640 | AV3: Sada | AW3: attente débolacge prêt
A4: 65 | B4: 23 | C4: CADEMA 1 | D4: AO | E4: NON | F4: - | G4: - | H4: 3 | J4: C14 | K4: ALI ATTOUMANI | L4: Bacar | M4: 0639 87 21 88 | N4: aattoumani.bacar@gmail.com | O4: 024 068 413 00020 | P4: Mamoudzou | Q4: 976-M-116 | R4: 222 | S4: 45489 | T4: FJ-886-VX | U4: 43707 | W4: 9 PLACES | Z4: A MOITIE | AA4: NON | AC4: OUI PAS PAYE | AE4: 45896 | AF4: F | AH4: NON | AI4: NON | AJ4: NON | AK4: NON | AL4: OUI | AN4: 510 | AO4: 43466 | AP4: 150 | AQ4: NON | AR4: NON | AS4: 4 | AT4: Chemin ma ali andy | AU4: 97640 | AV4: Sada | AW4: Voiture endommagé d'un coté et la tete de taxi aussi habillé en 2021
A5: 129 | B5: 35 | C5: CADEMA 1 | D5: AO | E5: NON | F5: - | G5: - | H5: 4 | K5: ALLAOUI | L5: Inzoudine | M5: 0639 075923/0639 26 27 78 | N5: ambdihoumadi976@gmail.com | O5: 024 078 396 000 41 | P5: Mamoudzou | Q5: 976-M-049 | R5: 1294 | S5: 43992 | T5: GH-790-LS | U5: 44753 | V5: =2024-YEAR(U5) -> 2 | W5: 9 PLACES | Y5: ? Pas payé | Z5: NON | AA5: _ | AB5: NON | AE5: 47882 | AF5: F | AG5: _ | AH5: NON | AI5: NON | AJ5: NON | AK5: NON | AL5: NON | AM5: 2020/44 | AN5: 510 | AO5: 43466 | AP5: 450 | AS5: 85 | AT5: Rue younoussa bamana | AU5: 97640 | AV5: Sada | AW5: a une voiture neuve
A6: 161 | B6: 41 | C6: CADEMA 1 | D6: AO | E6: NON | F6: - | G6: - | H6: 5 | I6: voiture en panne | K6: ALLAOUI | L6: Soibrane | M6: 0639 65 31 82 | N6: stt653182@hotmail.com | O6: 024 043 30 000 11 | P6: Centre Sud | Q6: 976-CS-048 | R6: 806 | S6: 43222 | T6: FZ_148_HW | U6: 44336 | V6: =2024-YEAR(U6) -> 3 | W6: 9 PLACES | X6: OK | Y6: ? Pas payé | Z6: NON | AB6: NON | AC6: OUI | AE6: 46556 | AF6: F | AG6: _ | AH6: OUI | AI6: OUI | AJ6: OUI | AK6: OUI | AL6: OUI | AN6: 510 | AP6: 450 | AT6: Quartier Kami case impasse mavandzani | AU6: 97625 | AV6: Kani kéli | AW6: Il est pas eligible pour la demande de subvention
A7: 129 | B7: 35 | C7: CADEMA 1 | D7: AO | E7: NON | F7: - | G7: - | H7: 6 | J7: C6 | K7: AMBDI | L7: Houmadi | M7: 0639 23 55 69 | N7: ambdihoumadi976@gmail.com | O7: 066 312 224 000 26 | P7: Sud | Q7: 976-S-023 | R7: 759 | S7: 45639 | T7: GC-122-QA | U7: 44495 | V7: =2024-YEAR(U7) -> 3 | W7: 9 PLACES | X7: OK | Z7: OUI | AB7: OUI | AD7: OUI | AE7: 48640 | AF7: F | AG7: _ | AH7: OUI | AI7: OUI | AJ7: NON | AK7: 2022 | AL7: OUI | AM7: 2020/46 | AN7: 510 | AO7: 43466 | AP7: 250 | AQ7: NON | AR7: NON | AT7: Route nationale Mbouanatsa | AU7: 97620 | AV7: BOUENI | AW7: Habillage 2023
A8: 193 | B8: 47 | C8: CADEMA 1 | D8: AO | E8: NON | F8: - | G8: - | H8: 7 | I8: C9 | J8: C7 | K8: BINA HALADI | L8: Bina | M8: 0639 06 05 82 | N8: wonamaore@gmail.com | O8: 853 690 428 000 18 | P8: Sud | Q8: 976-S-045 | R8: 1414 | S8: 45181 | T8: GE-883-ES | U8: 44581 | V8: =2024-YEAR(U8) -> 2 | W8: 9 places | Z8: OUI | AA8: _ | AB8: OUI | AD8: OUI | AE8: 45040 | AF8: F | AG8: _ | AH8: OUI | AI8: 2023 | AJ8: OUI | AK8: 2022 | AL8: NON | AM8: 2020/61 | AN8: 510 | AO8: 44285 | AP8: 450 | AS8: 8 | AT8: Rue Said Fatima | AU8: 97640 | AV8: SADA | AW8: Habillage juin 2023
A9: 225 | B9: 53 | C9: CADEMA 1 | D9: AO | E9: NON | F9: - | G9: - | H9: 8 | J9: C12 | K9: BOINARIZIKI | L9: Zena Dhurari | M9: 0639 66 36 94 06 50 45 94 42 | N9: dhurari.transport@gmail.com | O9: 500 894 043 000 16 | P9: Centre Sud | Q9: 976-CS-071 | R9: 1000 | S9: 44349 | T9: FF-569-NF | U9: 43573 | V9: =2024-YEAR(U9) -> 5 | W9: 9 PLACES | Z9: NON | AA9: _ | AB9: NON | AE9: 45177 | AF9: F | AG9: _ | AH9: OUI | AI9: 2023 | AJ9: OUI | AK9: 2022 | AL9: OUI | AN9: 510 | AO9: 43466 | AP9: 250 | AS9: 97 | AT9: Rue du commerce | AU9: 97640 | AV9: Sada | AW9: voiture pas habillée
A10: 257 | B10: 59 | C10: CADEMA 1 | D10: AO | E10: NON | F10: - | G10: - | H10: 9 | I10: C3 | J10: C8 | K10: COMBO | L10: Said | M10: 0639 68 37 93 | N10: combosaid5@gmail.cpm | O10: 054 394 853 00029 | P10: Mamoudzou | Q10: 976-M-164 | R10: 920 | S10: 44871 | T10: GB-965-EQ | U10: 44419 | V10: =2024-YEAR(U10) -> 3 | W10: 9 PLACES | X10: NEUF | Y10: 45411 | Z10: NON | AA10: NON | AB10: NON | AC10: NON | AD10: NON | AE10: 49279 | AF10: F | AG10: _ | AH10: OUI | AI10: OUI | AJ10: 2024 | AK10: 2022 | AL10: NON | AM10: 2020/70 | AN10: 510 | AO10: 44295 | AP10: 100 | AQ10: NON | AR10: NON | AS10: 193 | AT10: Route Départementale | AU10: 97630 | AV10: Mtsamboro | AW10: Il a reçu sa subvention et il a rien payé, et il a utiliser l'argent
A11: 289 | B11: 65 | C11: CADEMA 1 | D11: AO | E11: NON | F11: - | G11: - | H11: 10 | I11: C1 | J11: C1 | K11: EL ANZIZE SALIM | L11: Hamada | M11: 0639 22 81 28 | N11: elsalimhamada@hotmail.com | O11: 024 076 531 00011 | P11: Mamoudzou | Q11: 976_M_209 | R11: 413 | S11: 46877 | T11: GM_515_YL | U11: 45012 | V11: =2024-YEAR(U11) -> 1 | W11: 9 PLACES | Z11: 2023 | AA11: OUI | AB11: 2023 | AD11: OUI | AE11: 10959 | AF11: G | AG11: _ | AH11: NON | AI11: NON | AJ11: NON | AK11: NON | AL11: OUI | AM11: 2022/198 | AN11: 510 | AO11: 43466 | AP11: 250 | AS11: 8 | AT11: Rue de mjinpia | AU11: 97650 | AV11: Mtsangamoudji | AW11: habillage 9 place 2023
A12: 353 | B12: 77 | C12: CADEMA 1 | D12: AO | E12: NON | F12: - | G12: - | H12: 11 | I12: C5 | J12: C16 | K12: HADHURAMI | L12: Makinedine | M12: 0639 94 46 40 | N12: Hadhuramimakinedine976@gmail.com | O12: 054 397 211 00019 | P12: SUD | Q12: 976_S_069 | R12: 150 | S12: 45874 | T12: FZ-411-ZD | U12: 44362 | V12: =2024-YEAR(U12) -> 3 | W12: 9 PLACES | Z12: OUI | AB12: OUI | AD12: OUI | AE12: 49522 | AF12: F | AG12: _ | AH12: OUI | AI12: 2023 | AJ12: NON | AK12: 2022 | AL12: OUI | AM12: 2020/82 | AN12: 510 | AO12: 43466 | AP12: 550 | AS12: 14 | AT12: Rue foundi hamada m'zé | AU12: 97625 | AV12: Kani kéli | AW12: Habillage 2021 aurait 2 véhicules
A13: 385 | B13: 83 | C13: CADEMA 1 | D13: AO | E13: NON | F13: - | G13: - | H13: 12 | J13: C13 | K13: MADI BOINA | L13: Mkidachi | M13: 0639 22 08 67 | N13: madiboinamkidachi@hotmail.com | O13: 500 793 526 00012 | P13: NORD | Q13: 976-N-63 | R13: 985 | S13: 44456 | T13: GS-501-ZK | U13: 45273 | W13: 9 PLACES | X13: NEUF | Y13: pas de vitre | Z13: NON | AA13: OUI | AB13: OUI | AC13: NON | AD13: A venir | AE13: 45248 | AF13: F | AH13: NON | AI13: NON | AJ13: NON | AK13: NON | AL13: NON | AN13: 510 | AO13: 43466 | AP13: 150 | AQ13: NON | AR13: NON | AS13: 27 | AT13: Rue d'andimaka | AU13: 97650 | AV13: Mtsangamouji
A14: 417 | B14: 89 | C14: CADEMA 1 | D14: AO | E14: NON | F14: - | G14: - | H14: 13 | I14: C7 | J14: C3 | K14: MOISSULI HIMIDI | L14: Enly | M14: 0639 94 58 14 | N14: enlymoissuli@gmail.com | O14: 853 881 084 000 18 | P14: NORD | Q14: 976-N-015 | R14: 994 | S14: 44263 | T14: GW-003-JA | U14: 45394 | W14: 9 PLACES | Y14: att May Equip | Z14: NON | AA14: NON | AB14: NON | AC14: NON | AD14: NON | AE14: 47621 | AF14: F | AH14: NON | AI14: NON | AJ14: NON | AK14: NON | AL14: OUI | AN14: 510 | AO14: 43466 | AP14: 200 | AQ14: NON | AR14: NON | AS14: 5 | AT14: Quartier mronobaban sidi , Hamjago | AU14: 97630 | AV14: Mtsamboro | AW14: Il attend sa subvention , justine lui a dit d'aller harceler le CD pour qui'il debloque sa subvention
A15: 97 | B15: 29 | C15: CADEMA 1 | D15: AO | E15: NON | F15: - | G15: - | H15: 14 | I15: soucis de famille | J15: C4 | K15: OUSSENI | L15: Soula | M15: 0639 69 03 87 | N15: soulaousseni415@gmail.com | O15: 066 307 372 000 12 | P15: Centre NORD | Q15: 976-CN-003 | R15: 249 | S15: 43132 | T15: GP_813_HX | U15: 45083 | V15: =2024-YEAR(U15) -> 1 | W15: 9 PLACES | X15: TBE | Z15: 2023 | AA15: OUI | AB15: 2023 | AD15: OUI | AE15: 49496 | AF15: F | AG15: _ | AH15: OUI | AI15: OUI | AJ15: OUI | AK15: OUI | AL15: OUI | AM15: 2021/181 | AN15: 510 | AO15: 43466 | AP15: 300 | AS15: 2 | AT15: Rue mnadzi moja quartier baitil mali | AU15: 97600 | AV15: Mamoudzou | AW15: Pas de voiture
A16: 321 | B16: 71 | C16: CADEMA 1 | D16: AO | E16: NON | F16: - | G16: - | H16: 15 | I16: C8 | J16: C5 | K16: RENE | L16: Assanati | M16: 0639 07 82 51 | O16: 024 065 633 000 18 | P16: NORD | Q16: 976-N-032 | R16: 1337 | S16: 45235 | T16: GR-921-XZ | U16: 45219 | V16: =2024-YEAR(U16) -> 1 | W16: 9 PLACES | Z16: OUI | AB16: NON | AD16: OUI | AE16: 48068 | AF16: F | AG16: _ | AH16: OUI | AI16: 2023 | AJ16: OUI | AK16: 2022 | AN16: 510 | AO16: 44171 | AP16: 150 | AS16: 32 | AT16: Rue bacar tsimanda | AU16: 97650 | AV16: Mtsangamouji
A17: 49 | B17: 20 | C17: CADEMA 1 | E17: NON | F17: NON | G17: NON | H17: 16 | J17: C9 | K17: SANDI | L17: Maanrouf | M17: 0639 40 58 85 | N17: maanroufsandi@laposte.net | O17: 024 069 635 000 19 | P17: Sud | Q17: 976-S-006 | R17: 1184 | S17: 45262 | T17: GW-255-NY | U17: 45406 | W17: 9 PLACES | X17: NEUF | Z17: NON | AA17: OUI | AB17: NON | AC17: NON | AD17: A VENIR | AE17: 46707 | AF17: F | AH17: OUI | AI17: OUI | AJ17: OUI | AK17: 2022 | AL17: NON | AN17: 510 | AO17: 43466 | AP17: 300 | AQ17: NON | AR17: NON | AT17: Quartier ecole primaire | AU17: 97620 | AV17: Chirongui | AW17: Pas habillé en attente rendez-vous mayotte equipement
A18: 177 | B18: 44 | C18: CADEMA 1 | E18: NON | F18: NON | G18: NON | H18: 17 | I18: C2 | J18: C11 | K18: TOUMBOU | L18: Toibourani | M18: 0639 19 14 22 | N18: toumboutoibourani@outlook.fr / anlia.toumbou97620@gmail.com | O18: 024 054 710 000 25 | P18: Mamoudzou | Q18: 976-M-177 | R18: 357 | S18: 45028 | T18: GF_215_AQ | U18: 44624 | V18: =2024-YEAR(U18) -> 2 | W18: 9 PLACES | X18: OK | Z18: 2023 | AA18: OUI | AB18: 2023 | AD18: OUI | AE18: 45992 | AF18: F | AH18: OUI | AI18: OUI | AJ18: NON | AK18: 2022 | AL18: OUI | AM18: 2020/158 | AN18: 510 | AO18: 43466 | AP18: 350 | AS18: 9 | AT18: Rue Bambou | AU18: 97620 | AV18: Chirongui | AW18: Gérant
A22: 17 | B22: 14 | C22: CADEMA 1 | E22: NON | F22: NON | G22: NON | H22: 2 | K22: ACHIRAFFI pas de chauffeur | L22: Assad | M22: 0639 29 01 58 | N22: achiraffis@gmail.com | O22: 024 046 617 000 15 | P22: Mamoudzou | Q22: 976-M-045 | R22: 90 | S22: 46916 | T22: FY-973-FL | U22: 44285 | V22: =2024-YEAR(U22) -> 3 | W22: 9 PLACES | X22: BON | Z22: OUI | AA22: OUI | AB22: OUI | AC22: OUI | AD22: NON | AE22: 49237 | AF22: F | AG22: _ | AH22: OUI | AI22: OUI | AJ22: OUI | AK22: 2022 | AL22: OUI | AM22: 2020/20 | AN22: 510 | AO22: 43466 | AP22: 450 | AQ22: NON | AR22: NON | AS22: 474 | AT22: Route départemental | AU22: 97630 | AV22: M'tsamboro | AW22: a une voiture - Travaille au Sud

Sheet PLANNING GENERAL
D1: LISTE DES INTERVENANTS SUR LE MARCHE CARIBUS
A2: LIGNE 4 : VAHIBE <-> PASSAMAINTY
C3: C1 El Anziz Hamada | D3: C2 Bina Haladi Bina | E3: C3 Abdou Minihadji Hamada | F3: C4 Toubou Toibranne | G3: C5 Ahamadi Bacar Raenmouddine | H3: C6 Ousseni Soula | I3: C7 Hamidou Dahalani | J3: C8 Hadhurami Manikedine | K3: C9 Sandi Manrouf | L3: C10 M'changama Issihaka | M3: C11 Madi Boina Mikidachi | N3: C12 Alliloifa Said Siradj | O3: C13 Chauffeur Taxi Vanille (Ben) | P3: C14 Kamardine Mansour | Q3: C15 Mansour Kamardine (salarié) | R3: Coordinateurs
A4: VEHICULE | C4: VEHICULE TV1 | O4: VEHICULE TV5 | P4: VEHICULE TV7 | Q4: VEHICULE TV6
A5: Jours de semaine AM | C5: 4:30-12:45 | D5: 4:30-8:40 | E5: 4:50-8:30 | F5: 5:00- 8:30 | G5: 6:00- 9:30 | H5: 6:30- 14:15 | I5: 4:30-11:00 Astreinte de 4:30 à 6:40 et de 9:00 à 11:00 | J5: 5:10-8:45 | K5: 5:20-8:00 | L5: 5:30-8:10 | M5: 5:00-8:30 | N5: 6:00-8:30 | O5: 6:30-9:00 | P5: 6:40-8:10 | R5: Allaoui Soibrane
A6: Jours de semaine PM | D6: 13:00-16:00 | E6: 14:30-17:00 | F6: 19:00-20:45 Astreinte de 17:00 à 19:00 | G6: 17:00-21:15 | M6: 17:30-18:45 | N6: 16:30-17:30 | R6: El Anziz Hamada
A7: Samedi Matin | J7: 6:00-13:45 | Q7: 6:30-13:45 | R7: Toumbou Toibrane
A8: Samedi PM | L8: 14:00- 20:45 | M8: 14:00-21:15 | R8: El Anziz Hamada
A9: Dimanche et jours fériés matin | G9: 8:00-13:45 1 Dimanche sur 2 | L9: 8:00-13:45 1 Dimanche sur 2 | R9: Toumbou Toibrane
A10: Dimanche et jours fériés AM | J10: 14:00-19:15 1 Dimanche sur 2 | P10: 14:00-19:15 1 Dimanche sur 2 | R10: Allaoui Soibrane
A13: LIGNE 3 : DOUJANI <-> LE PASSOT BARGE
C14: D1 Mohamed Ali La Glace | D14: D2 Baraka Soumaila | E14: D3 Abdourahim Mohamed | F14: D4 Ambdi Houmadi | G14: D5 Amina Selemani | H14: D6 Abdou Hamidoune Nassabia | I14: D7 Combo Said | J14: D8 Dailami Issouf | K14: D9 Renee Assanati | L14: D10 Mansour Kamardine (Salarié) | M14: D11 Allaoui Soibrane | N14: D12 Velou M'Colo | O14: D13 Mourdi Aktoir | P14: D14 Ahamadi Laydine | Q14: D15 Kamardine Mansour | R14: Coordinateurs
A15: VEHICULE | F15: VEHICULE TV2 | G15: VEHICULE TV3 | L15: VEHICULE TV6 | P15: VEHICULE TV4 | Q15: VEHICULE TV7
A16: Jours de semaine AM | C16: 5:00-8:30 | D16: 6:20-14:50 | E16: 5:40-8:10 | F16: 6:00-14:00 | G16: 5:20-8:10 | H16: 6:20-8:20 | I16: 6:20-8:20 | L16: 5:50-14:10 | M16: 6:00-13:50 | N16: 5:10-8:10 | O16: 5:30-8:30 | P16: 6:10-8:10 Astreinte de 4:30 à 6:00 et de 8:10 à 11:00 | R16: Younoussa Hamada
A17: Jours de semaine PM | C17: 14:40-18:10 | E17: 14:40-18:10 | G17: 15:20-17:50 | H17: 15:00-20:30 | I17: 17:50-20:50 | J17: 14:20-21:10 | K17: 15:20-21:30 | R17: Mansour Kamardine
A18: Samedi Matin | G18: 6:40-14:40 | N18: 6:00-14:00 | O18: 6:20-14:20 | R18: Ousseni Soula
A19: Samedi PM | K19: 14:00-19:00 | P19: 14:20-21:20 | Q19: 14:40-20:40 | R19: Mansour Kamardine
A20: Dimanche et jours fériés matin | I20: 8:30-14:00 | N20: 8:00-13:30 | R20: Ousseni Soula
A21: Dimanche et jours fériés AM | J21: 14:00-19:30 1 Dimanche sur 2 | O21: 14:30-19:30 1 Dimanche sur 2 | P21: 14:00-19:00 | R21: Mansour Kamardine
R25: Coordinateur La Barge PM et samedi PM et Dimanche PM
R26: Coordinateur Vahibe matin Jours de semaine et Dimanche PM
R39: Coordinateur Doujani matin jours de semaine

Sheet Feuille saisie
A2: TYPE | B2: D15
A3: DATE | B3: 45627
B4: =VLOOKUP(B2,'Liste chauffeur'!$B$5:$L$19,2,TRUE)&" "&VLOOKUP(B2,'Liste chauffeur'!$B$5:$L$19,3,TRUE) -> KAMARDINE Mansour
I6: Arrêt 1 | M6: Arrêt 2 | Q6: Arrêt 3 | W6: ARRIVEE | AA6: 8
B7: Heure théorique départ | C7: Horaire | D7: Chauffeur | E7: Heure réelle départ | F7: Trajet non effectué | G7: Départ avec plus de 10 mns retard | H7: Nbre personnes montée | I7: - | J7: + | K7: Heure arrivée arrêt 1 | L7: Délai | M7: - | N7: + | O7: Heure arrivée arrêt 2 | P7: Délai | Q7: - | R7: + | S7: Heure arrivée arrêt 3 | T7: Délai | U7: Nbre personnes descente | W7: Heure arrivée finale | X7: Commentaires | Y7: Temps Aller | Z7: Nbre personnes moyenne | AA7: Capacité max | AB7: Taux Fréquentation
A8: =Horaire!A8 -> DOUJANI | B8: =Horaire!B8 -> 0.20833333 | C8: =Horaire!C8 -> D1 | D8: =VLOOKUP(C8,'Liste chauffeur'!$B$5:$L$19,2,TRUE)&" "&VLOOKUP(C8,'Liste chauffeur'!$B$5:$L$19,3,TRUE) -> MOHAMED Ali (laglace) | F8: =COUNTBLANK(E8) -> 1 | Y8: =IF(F8=1,"",W8-E8) | Z8: =H8+J8-I8 -> 0 | AA8: =IF(F8=1,0,AA$6) -> 0 | AB8: =IF(AA8=0,0,Z8/AA8) -> 0
A9: =Horaire!A9 -> DOUJANI | B9: =Horaire!B9 -> 0.21527778 | C9: =Horaire!C9 -> D12 | D9: =VLOOKUP(C9,'Liste chauffeur'!$B$5:$L$19,2,TRUE)&" "&VLOOKUP(C9,'Liste chauffeur'!$B$5:$L$19,3,TRUE) -> VELOU M'COLO M'Berou | F9: =COUNTBLANK(E9) -> 1 | Y9: =IF(F9=1,"",W9-E9) | Z9: =H9+J9-I9 -> 0 | AA9: =IF(F9=1,0,AA$6) -> 0 | AB9: =IF(AA9=0,0,Z9/AA9) -> 0
A10: =Horaire!A10 -> DOUJANI | B10: =Horaire!B10 -> 0.22222222 | C10: =Horaire!C10 -> D5 | D10: =VLOOKUP(C10,'Liste chauffeur'!$B$5:$L$19,2,TRUE)&" "&VLOOKUP(C10,'Liste chauffeur'!$B$5:$L$19,3,TRUE) -> AMINA Selemani | F10: =COUNTBLANK(E10) -> 1 | Y10: =IF(F10=1,"",W10-E10) | Z10: =H10+J10-I10 -> 0 | AA10: =IF(F10=1,0,AA$6) -> 0 | AB10: =IF(AA10=0,0,Z10/AA10) -> 0
A11: =Horaire!A11 -> DOUJANI | B11: =Horaire!B11 -> 0.22916667 | C11: =Horaire!C11 -> D13 | D11: =VLOOKUP(C11,'Liste chauffeur'!$B$5:$L$19,2,TRUE)&" "&VLOOKUP(C11,'Liste chauffeur'!$B$5:$L$19,3,TRUE) -> MOURIDI Aktoir | F11: =COUNTBLANK(E11) -> 1 | Y11: =IF(F11=1,"",W11-E11) | Z11: =H11+J11-I11 -> 0 | AA11: =IF(F11=1,0,AA$6) -> 0 | AB11: =IF(AA11=0,0,Z11/AA11) -> 0
A12: =Horaire!A12 -> PASSOT LA BARGE | B12: =Horaire!B12 -> 0.22916667 | C12: =Horaire!C12 -> D1 | D12: =VLOOKUP(C12,'Liste chauffeur'!$B$5:$L$19,2,TRUE)&" "&VLOOKUP(C12,'Liste chauffeur'!$B$5:$L$19,3,TRUE) -> MOHAMED Ali (laglace) | F12: =COUNTBLANK(E12) -> 1 | L12: =K12-E12 -> 0 | P12: =O12-K12 -> 0 | T12: =S12-O12 -> 0 | V12: =IF(H12-I12+J12-M12+N12-Q12+R12=U12,"OK",H12-I12+J12-M12+N12-Q12+R12-U12) -> OK | Y12: =IF(F12=1,"",W12-E12) | Z12: =H12+J12-I12 -> 0 | AA12: =IF(F12=1,0,AA$6) -> 0 | AB12: =IF(AA12=0,0,Z12/AA12) -> 0
A13: =Horaire!A13 -> DOUJANI | B13: =Horaire!B13 -> 0.23611111 | C13: =Horaire!C13 -> D3 | D13: =VLOOKUP(C13,'Liste chauffeur'!$B$5:$L$19,2,TRUE)&" "&VLOOKUP(C13,'Liste chauffeur'!$B$5:$L$19,3,TRUE) -> ABDOURAHIM Mohamed | F13: =COUNTBLANK(E13) -> 1 | L13: =K13-E13 -> 0 | P13: =O13-K13 -> 0 | T13: =S13-O13 -> 0 | Y13: =IF(F13=1,"",W13-E13) | Z13: =H13+J13-I13 -> 0 | AA13: =IF(F13=1,0,AA$6) -> 0 | AB13: =IF(AA13=0,0,Z13/AA13) -> 0
A14: =Horaire!A14 -> PASSOT LA BARGE | B14: =Horaire!B14 -> 0.23611111 | C14: =Horaire!C14 -> D12 | D14: =VLOOKUP(C14,'Liste chauffeur'!$B$5:$L$19,2,TRUE)&" "&VLOOKUP(C14,'Liste chauffeur'!$B$5:$L$19,3,TRUE) -> VELOU M'COLO M'Berou | F14: =COUNTBLANK(E14) -> 1 | L14: =K14-E14 -> 0 | P14: =O14-K14 -> 0 | T14: =S14-O14 -> 0 | Y14: =IF(F14=1,"",W14-E14) | Z14: =H14+J14-I14 -> 0 | AA14: =IF(F14=1,0,AA$6) -> 0 | AB14: =IF(AA14=0,0,Z14/AA14) -> 0
A15: =Horaire!A15 -> DOUJANI | B15: =Horaire!B15 -> 0.24305556 | C15: =Horaire!C15 -> D10 | D15: =VLOOKUP(C15,'Liste chauffeur'!$B$5:$L$19,2,TRUE)&" "&VLOOKUP(C15,'Liste chauffeur'!$B$5:$L$19,3,TRUE) -> KAMARDINE Mansour (Salarié) | F15: =COUNTBLANK(E15) -> 1 | L15: =K15-E15 -> 0 | P15: =O15-K15 -> 0 | T15: =S15-O15 -> 0 | Y15: =IF(F15=1,"",W15-E15) | Z15: =H15+J15-I15 -> 0 | AA15: =IF(F15=1,0,AA$6) -> 0 | AB15: =IF(AA15=0,0,Z15/AA15) -> 0
A16: =Horaire!A16 -> PASSOT LA BARGE | B16: =Horaire!B16 -> 0.24305556 | C16: =Horaire!C16 -> D5 | D16: =VLOOKUP(C16,'Liste chauffeur'!$B$5:$L$19,2,TRUE)&" "&VLOOKUP(C16,'Liste chauffeur'!$B$5:$L$19,3,TRUE) -> AMINA Selemani | F16: =COUNTBLANK(E16) -> 1 | L16: =K16-E16 -> 0 | P16: =O16-K16 -> 0 | T16: =S16-O16 -> 0 | V16: =IF(H16-I16+J16-M16+N16-Q16+R16=U16,"OK",H16-I16+J16-M16+N16-Q16+R16-U16) -> OK | Y16: =IF(F16=1,"",W16-E16) | Z16: =H16+J16-I16 -> 0 | AA16: =IF(F16=1,0,AA$6) -> 0 | AB16: =IF(AA16=0,0,Z16/AA16) -> 0
A17: =Horaire!A17 -> DOUJANI | B17: =Horaire!B17 -> 0.25 | C17: =Horaire!C17 -> D1 | D17: =VLOOKUP(C17,'Liste chauffeur'!$B$5:$L$19,2,TRUE)&" "&VLOOKUP(C17,'Liste chauffeur'!$B$5:$L$19,3,TRUE) -> MOHAMED Ali (laglace) | F17: =COUNTBLANK(E17) -> 1 | L17: =K17-E17 -> 0 | P17: =O17-K17 -> 0 | T17: =S17-O17 -> 0 | V17: =IF(H17-I17+J17-M17+N17-Q17+R17=U17,"OK",H17-I17+J17-M17+N17-Q17+R17-U17) -> OK | Y17: =IF(F17=1,"",W17-E17) | Z17: =H17+J17-I17 -> 0 | AA17: =IF(F17=1,0,AA$6) -> 0 | AB17: =IF(AA17=0,0,Z17/AA17) -> 0
A18: =Horaire!A18 -> PASSOT LA BARGE | B18: =Horaire!B18 -> 0.25 | C18: =Horaire!C18 -> D13 | D18: =VLOOKUP(C18,'Liste chauffeur'!$B$5:$L$19,2,TRUE)&" "&VLOOKUP(C18,'Liste chauffeur'!$B$5:$L$19,3,TRUE) -> MOURIDI Aktoir | F18: =COUNTBLANK(E18) -> 1 | Z18: =H18+J18-I18 -> 0 | AA18: =IF(F18=1,0,AA$6) -> 0 | AB18: =IF(AA18=0,0,Z18/AA18) -> 0
A19: M'TSAPERE | B19: =Horaire!B19 -> 0.25 | C19: =Horaire!C19 -> D4 | D19: =VLOOKUP(C19,'Liste chauffeur'!$B$5:$L$19,2,TRUE)&" "&VLOOKUP(C19,'Liste chauffeur'!$B$5:$L$19,3,TRUE) -> AMBDI Houmadi | F19: =COUNTBLANK(E19) -> 1 | L19: =K19-E19 -> 0 | P19: =O19-K19 -> 0 | T19: =S19-O19 -> 0 | V19: =IF(H19-I19+J19-M19+N19-Q19+R19=U19,"OK",H19-I19+J19-M19+N19-Q19+R19-U19) -> OK | Y19: =IF(F19=1,"",W19-E19) | Z19: =H19+J19-I19 -> 0 | AA19: =IF(F19=1,0,AA$6) -> 0 | AB19: =IF(AA19=0,0,Z19/AA19) -> 0
A20: =Horaire!A20 -> PASSOT LA BARGE | B20: =Horaire!B20 -> 0.25 | C20: =Horaire!C20 -> D11 | D20: =VLOOKUP(C20,'Liste chauffeur'!$B$5:$L$19,2,TRUE)&" "&VLOOKUP(C20,'Liste chauffeur'!$B$5:$L$19,3,TRUE) -> ALLAOUI Soibrane | F20: =COUNTBLANK(E20) -> 1 | L20: =K20-E20 -> 0 | P20: =O20-K20 -> 0 | T20: =S20-O20 -> 0 | V20: =IF(H20-I20+J20-M20+N20-Q20+R20=U20,"OK",H20-I20+J20-M20+N20-Q20+R20-U20) -> OK | Y20: =IF(F20=1,"",W20-E20) | Z20: =H20+J20-I20 -> 0 | AA20: =IF(F20=1,0,AA$6) -> 0 | AB20: =IF(AA20=0,0,Z20/AA20) -> 0
A21: =Horaire!A21 -> DOUJANI | B21: =Horaire!B21 -> 0.25694444 | C21: =Horaire!C21 -> D12 | D21: =VLOOKUP(C21,'Liste chauffeur'!$B$5:$L$19,2,TRUE)&" "&VLOOKUP(C21,'Liste chauffeur'!$B$5:$L$19,3,TRUE) -> VELOU M'COLO M'Berou | F21: =COUNTBLANK(E21) -> 1 | L21: =K21-E21 -> 0 | P21: =O21-K21 -> 0 | T21: =S21-O21 -> 0 | V21: =IF(H21-I21+J21-M21+N21-Q21+R21=U21,"OK",H21-I21+J21-M21+N21-Q21+R21-U21) -> OK | Y21: =IF(F21=1,"",W21-E21) | Z21: =H21+J21-I21 -> 0 | AA21: =IF(F21=1,0,AA$6) -> 0 | AB21: =IF(AA21=0,0,Z21/AA21) -> 0
A22: =Horaire!A22 -> PASSOT LA BARGE | B22: =Horaire!B22 -> 0.25694444 | C22: =Horaire!C22 -> D3 | D22: =VLOOKUP(C22,'Liste chauffeur'!$B$5:$L$19,2,TRUE)&" "&VLOOKUP(C22,'Liste chauffeur'!$B$5:$L$19,3,TRUE) -> ABDOURAHIM Mohamed | F22: =COUNTBLANK(E22) -> 1 | L22: =K22-E22 -> 0 | P22: =O22-K22 -> 0 | T22: =S22-O22 -> 0 | V22: =IF(H22-I22+J22-M22+N22-Q22+R22=U22,"OK",H22-I22+J22-M22+N22-Q22+R22-U22) -> OK | Y22: =IF(F22=1,"",W22-E22) | Z22: =H22+J22-I22 -> 0 | AA22: =IF(F22=1,0,AA$6) -> 0 | AB22: =IF(AA22=0,0,Z22/AA22) -> 0
A23: M'TSAPERE | B23: =Horaire!B23 -> 0.25694444 | C23: =Horaire!C23 -> D5 | D23: =VLOOKUP(C23,'Liste chauffeur'!$B$5:$L$19,2,TRUE)&" "&VLOOKUP(C23,'Liste chauffeur'!$B$5:$L$19,3,TRUE) -> AMINA Selemani | F23: =COUNTBLANK(E23) -> 1 | L23: =K23-E23 -> 0 | P23: =O23-K23 -> 0 | T23: =S23-O23 -> 0 | V23: =IF(H23-I23+J23-M23+N23-Q23+R23=U23,"OK",H23-I23+J23-M23+N23-Q23+R23-U23) -> OK | Y23: =IF(F23=1,"",W23-E23) | Z23: =H23+J23-I23 -> 0 | AA23: =IF(F23=1,0,AA$6) -> 0 | AB23: =IF(AA23=0,0,Z23/AA23) -> 0
A24: =Horaire!A24 -> PASSOT LA BARGE | B24: =Horaire!B24 -> 0.25694444 | C24: =Horaire!C24 -> D14 | D24: =VLOOKUP(C24,'Liste chauffeur'!$B$5:$L$19,2,TRUE)&" "&VLOOKUP(C24,'Liste chauffeur'!$B$5:$L$19,3,TRUE) -> AHAMADI Laydine | F24: =COUNTBLANK(E24) -> 1 | L24: =K24-E24 -> 0 | P24: =O24-K24 -> 0 | T24: =S24-O24 -> 0 | V24: =IF(H24-I24+J24-M24+N24-Q24+R24=U24,"OK",H24-I24+J24-M24+N24-Q24+R24-U24) -> OK | Y24: =IF(F24=1,"",W24-E24) | Z24: =H24+J24-I24 -> 0 | AA24: =IF(F24=1,0,AA$6) -> 0 | AB24: =IF(AA24=0,0,Z24/AA24) -> 0
A25: =Horaire!A25 -> DOUJANI | B25: =Horaire!B25 -> 0.26388889 | C25: =Horaire!C25 -> D2 | D25: =VLOOKUP(C25,'Liste chauffeur'!$B$5:$L$19,2,TRUE)&" "&VLOOKUP(C25,'Liste chauffeur'!$B$5:$L$19,3,TRUE) -> BARAKA Soumaila | F25: =COUNTBLANK(E25) -> 1 | Z25: =H25+J25-I25 -> 0 | AA25: =IF(F25=1,0,AA$6) -> 0 | AB25: =IF(AA25=0,0,Z25/AA25) -> 0
A26: =Horaire!A26 -> PASSOT LA BARGE | B26: =Horaire!B26 -> 0.26388889 | C26: =Horaire!C26 -> D10 | D26: =VLOOKUP(C26,'Liste chauffeur'!$B$5:$L$19,2,TRUE)&" "&VLOOKUP(C26,'Liste chauffeur'!$B$5:$L$19,3,TRUE) -> KAMARDINE Mansour (Salarié) | F26: =COUNTBLANK(E26) -> 1 | L26: =K26-E26 -> 0 | P26: =O26-K26 -> 0 | T26: =S26-O26 -> 0 | V26: =IF(H26-I26+J26-M26+N26-Q26+R26=U26,"OK",H26-I26+J26-M26+N26-Q26+R26-U26) -> OK | Y26: =IF(F26=1,"",W26-E26) | Z26: =H26+J26-I26 -> 0 | AA26: =IF(F26=1,0,AA$6) -> 0 | AB26: =IF(AA26=0,0,Z26/AA26) -> 0
A27: M'TSAPERE | B27: =Horaire!B27 -> 0.26388889 | C27: =Horaire!C27 -> D7 | D27: =VLOOKUP(C27,'Liste chauffeur'!$B$5:$L$19,2,TRUE)&" "&VLOOKUP(C27,'Liste chauffeur'!$B$5:$L$19,3,TRUE) -> COMBO Said | F27: =COUNTBLANK(E27) -> 1 | L27: =K27-E27 -> 0 | P27: =O27-K27 -> 0 | T27: =S27-O27 -> 0 | V27: =IF(H27-I27+J27-M27+N27-Q27+R27=U27,"OK",H27-I27+J27-M27+N27-Q27+R27-U27) -> OK | Y27: =IF(F27=1,"",W27-E27) | Z27: =H27+J27-I27 -> 0 | AA27: =IF(F27=1,0,AA$6) -> 0 | AB27: =IF(AA27=0,0,Z27/AA27) -> 0
A28: =Horaire!A28 -> PASSOT LA BARGE | B28: =Horaire!B28 -> 0.26388889 | C28: =Horaire!C28 -> D6 | D28: =VLOOKUP(C28,'Liste chauffeur'!$B$5:$L$19,2,TRUE)&" "&VLOOKUP(C28,'Liste chauffeur'!$B$5:$L$19,3,TRUE) -> ABDOU HAMIDOUNE Nassabia | F28: =COUNTBLANK(E28) -> 1 | L28: =K28-E28 -> 0 | P28: =O28-K28 -> 0 | T28: =S28-O28 -> 0 | V28: =IF(H28-I28+J28-M28+N28-Q28+R28=U28,"OK",H28-I28+J28-M28+N28-Q28+R28-U28) -> OK | Y28: =IF(F28=1,"",W28-E28) | Z28: =H28+J28-I28 -> 0 | AA28: =IF(F28=1,0,AA$6) -> 0 | AB28: =IF(AA28=0,0,Z28/AA28) -> 0
A29: =Horaire!A29 -> DOUJANI | B29: =Horaire!B29 -> 0.27083333 | C29: =Horaire!C29 -> D13 | D29: =VLOOKUP(C29,'Liste chauffeur'!$B$5:$L$19,2,TRUE)&" "&VLOOKUP(C29,'Liste chauffeur'!$B$5:$L$19,3,TRUE) -> MOURIDI Aktoir | F29: =COUNTBLANK(E29) -> 1 | L29: =K29-E29 -> 0 | P29: =O29-K29 -> 0 | T29: =S29-O29 -> 0 | V29: =IF(H29-I29+J29-M29+N29-Q29+R29=U29,"OK",H29-I29+J29-M29+N29-Q29+R29-U29) -> OK | Y29: =IF(F29=1,"",W29-E29) | Z29: =H29+J29-I29 -> 0 | AA29: =IF(F29=1,0,AA$6) -> 0 | AB29: =IF(AA29=0,0,Z29/AA29) -> 0
A30: =Horaire!A30 -> PASSOT LA BARGE | B30: =Horaire!B30 -> 0.27083333 | C30: =Horaire!C30 -> D1 | D30: =VLOOKUP(C30,'Liste chauffeur'!$B$5:$L$19,2,TRUE)&" "&VLOOKUP(C30,'Liste chauffeur'!$B$5:$L$19,3,TRUE) -> MOHAMED Ali (laglace) | F30: =COUNTBLANK(E30) -> 1 | L30: =K30-E30 -> 0 | P30: =O30-K30 -> 0 | T30: =S30-O30 -> 0 | V30: =IF(H30-I30+J30-M30+N30-Q30+R30=U30,"OK",H30-I30+J30-M30+N30-Q30+R30-U30) -> OK | Y30: =IF(F30=1,"",W30-E30) | Z30: =H30+J30-I30 -> 0 | AA30: =IF(F30=1,0,AA$6) -> 0 | AB30: =IF(AA30=0,0,Z30/AA30) -> 0
A31: M'TSAPERE | B31: =Horaire!B31 -> 0.27083333 | C31: =Horaire!C31 -> D11 | D31: =VLOOKUP(C31,'Liste chauffeur'!$B$5:$L$19,2,TRUE)&" "&VLOOKUP(C31,'Liste chauffeur'!$B$5:$L$19,3,TRUE) -> ALLAOUI Soibrane | F31: =COUNTBLANK(E31) -> 1 | L31: =K31-E31 -> 0 | P31: =O31-K31 -> 0 | T31: =S31-O31 -> 0 | V31: =IF(H31-I31+J31-M31+N31-Q31+R31=U31,"OK",H31-I31+J31-M31+N31-Q31+R31-U31) -> OK | Y31: =IF(F31=1,"",W31-E31) | Z31: =H31+J31-I31 -> 0 | AA31: =IF(F31=1,0,AA$6) -> 0 | AB31: =IF(AA31=0,0,Z31/AA31) -> 0
A32: =Horaire!A32 -> PASSOT LA BARGE | B32: =Horaire!B32 -> 0.27083333 | C32: =Horaire!C32 -> D4 | D32: =VLOOKUP(C32,'Liste chauffeur'!$B$5:$L$19,2,TRUE)&" "&VLOOKUP(C32,'Liste chauffeur'!$B$5:$L$19,3,TRUE) -> AMBDI Houmadi | F32: =COUNTBLANK(E32) -> 1 | Z32: =H32+J32-I32 -> 0 | AA32: =IF(F32=1,0,AA$6) -> 0 | AB32: =IF(AA32=0,0,Z32/AA32) -> 0
A33: =Horaire!A33 -> DOUJANI | B33: =Horaire!B33 -> 0.27777778 | C33: =Horaire!C33 -> D3 | D33: =VLOOKUP(C33,'Liste chauffeur'!$B$5:$L$19,2,TRUE)&" "&VLOOKUP(C33,'Liste chauffeur'!$B$5:$L$19,3,TRUE) -> ABDOURAHIM Mohamed | F33: =COUNTBLANK(E33) -> 1 | L33: =K33-E33 -> 0 | P33: =O33-K33 -> 0 | T33: =S33-O33 -> 0 | V33: =IF(H33-I33+J33-M33+N33-Q33+R33=U33,"OK",H33-I33+J33-M33+N33-Q33+R33-U33) -> OK | Y33: =IF(F33=1,"",W33-E33) | Z33: =H33+J33-I33 -> 0 | AA33: =IF(F33=1,0,AA$6) -> 0 | AB33: =IF(AA33=0,0,Z33/AA33) -> 0
A34: =Horaire!A34 -> PASSOT LA BARGE | B34: =Horaire!B34 -> 0.27777778 | C34: =Horaire!C34 -> D12 | D34: =VLOOKUP(C34,'Liste chauffeur'!$B$5:$L$19,2,TRUE)&" "&VLOOKUP(C34,'Liste chauffeur'!$B$5:$L$19,3,TRUE) -> VELOU M'COLO M'Berou | F34: =COUNTBLANK(E34) -> 1 | L34: =K34-E34 -> 0 | V34: =IF(H34-I34+J34-M34+N34-Q34+R34=U34,"OK",H34-I34+J34-M34+N34-Q34+R34-U34) -> OK | Y34: =IF(F34=1,"",W34-E34) | Z34: =H34+J34-I34 -> 0 | AA34: =IF(F34=1,0,AA$6) -> 0 | AB34: =IF(AA34=0,0,Z34/AA34) -> 0
A35: M'TSAPERE | B35: =Horaire!B35 -> 0.27777778 | C35: =Horaire!C35 -> D14 | D35: =VLOOKUP(C35,'Liste chauffeur'!$B$5:$L$19,2,TRUE)&" "&VLOOKUP(C35,'Liste chauffeur'!$B$5:$L$19,3,TRUE) -> AHAMADI Laydine | F35: =COUNTBLANK(E35) -> 1 | L35: =K35-E35 -> 0 | V35: =IF(H35-I35+J35-M35+N35-Q35+R35=U35,"OK",H35-I35+J35-M35+N35-Q35+R35-U35) -> OK | Y35: =IF(F35=1,"",W35-E35) | Z35: =H35+J35-I35 -> 0 | AA35: =IF(F35=1,0,AA$6) -> 0 | AB35: =IF(AA35=0,0,Z35/AA35) -> 0
A36: =Horaire!A36 -> PASSOT LA BARGE | B36: =Horaire!B36 -> 0.27777778 | C36: =Horaire!C36 -> D5 | D36: =VLOOKUP(C36,'Liste chauffeur'!$B$5:$L$19,2,TRUE)&" "&VLOOKUP(C36,'Liste chauffeur'!$B$5:$L$19,3,TRUE) -> AMINA Selemani | F36: =COUNTBLANK(E36) -> 1 | L36: =K36-E36 -> 0 | V36: =IF(H36-I36+J36-M36+N36-Q36+R36=U36,"OK",H36-I36+J36-M36+N36-Q36+R36-U36) -> OK | Y36: =IF(F36=1,"",W36-E36) | Z36: =H36+J36-I36 -> 0 | AA36: =IF(F36=1,0,AA$6) -> 0 | AB36: =IF(AA36=0,0,Z36/AA36) -> 0
A37: =Horaire!A37 -> DOUJANI | B37: =Horaire!B37 -> 0.28472222 | C37: =Horaire!C37 -> D10 | D37: =VLOOKUP(C37,'Liste chauffeur'!$B$5:$L$19,2,TRUE)&" "&VLOOKUP(C37,'Liste chauffeur'!$B$5:$L$19,3,TRUE) -> KAMARDINE Mansour (Salarié) | F37: =COUNTBLANK(E37) -> 1 | L37: =K37-E37 -> 0 | V37: =IF(H37-I37+J37-M37+N37-Q37+R37=U37,"OK",H37-I37+J37-M37+N37-Q37+R37-U37) -> OK | Y37: =IF(F37=1,"",W37-E37) | Z37: =H37+J37-I37 -> 0 | AA37: =IF(F37=1,0,AA$6) -> 0 | AB37: =IF(AA37=0,0,Z37/AA37) -> 0
A38: =Horaire!A38 -> PASSOT LA BARGE | B38: =Horaire!B38 -> 0.28472222 | C38: =Horaire!C38 -> D2 | D38: =VLOOKUP(C38,'Liste chauffeur'!$B$5:$L$19,2,TRUE)&" "&VLOOKUP(C38,'Liste chauffeur'!$B$5:$L$19,3,TRUE) -> BARAKA Soumaila | F38: =COUNTBLANK(E38) -> 1 | L38: =K38-E38 -> 0 | V38: =IF(H38-I38+J38-M38+N38-Q38+R38=U38,"OK",H38-I38+J38-M38+N38-Q38+R38-U38) -> OK | Y38: =IF(F38=1,"",W38-E38) | Z38: =H38+J38-I38 -> 0 | AA38: =IF(F38=1,0,AA$6) -> 0 | AB38: =IF(AA38=0,0,Z38/AA38) -> 0
A39: M'TSAPERE | B39: =Horaire!B39 -> 0.28472222 | C39: =Horaire!C39 -> D6 | D39: =VLOOKUP(C39,'Liste chauffeur'!$B$5:$L$19,2,TRUE)&" "&VLOOKUP(C39,'Liste chauffeur'!$B$5:$L$19,3,TRUE) -> ABDOU HAMIDOUNE Nassabia | F39: =COUNTBLANK(E39) -> 1 | L39: =K39-E39 -> 0 | V39: =IF(H39-I39+J39-M39+N39-Q39+R39=U39,"OK",H39-I39+J39-M39+N39-Q39+R39-U39) -> OK | Y39: =IF(F39=1,"",W39-E39) | Z39: =H39+J39-I39 -> 0 | AA39: =IF(F39=1,0,AA$6) -> 0 | AB39: =IF(AA39=0,0,Z39/AA39) -> 0
A40: =Horaire!A40 -> PASSOT LA BARGE | B40: =Horaire!B40 -> 0.28472222 | C40: =Horaire!C40 -> D7 | D40: =VLOOKUP(C40,'Liste chauffeur'!$B$5:$L$19,2,TRUE)&" "&VLOOKUP(C40,'Liste chauffeur'!$B$5:$L$19,3,TRUE) -> COMBO Said | F40: =COUNTBLANK(E40) -> 1 | L40: =K40-E40 -> 0 | V40: =IF(H40-I40+J40-M40+N40-Q40+R40=U40,"OK",H40-I40+J40-M40+N40-Q40+R40-U40) -> OK | Y40: =IF(F40=1,"",W40-E40) | Z40: =H40+J40-I40 -> 0 | AA40: =IF(F40=1,0,AA$6) -> 0 | AB40: =IF(AA40=0,0,Z40/AA40) -> 0
A41: =Horaire!A41 -> DOUJANI | B41: =Horaire!B41 -> 0.29166667 | C41: =Horaire!C41 -> D1 | D41: =VLOOKUP(C41,'Liste chauffeur'!$B$5:$L$19,2,TRUE)&" "&VLOOKUP(C41,'Liste chauffeur'!$B$5:$L$19,3,TRUE) -> MOHAMED Ali (laglace) | F41: =COUNTBLANK(E41) -> 1 | L41: =K41-E41 -> 0 | V41: =IF(H41-I41+J41-M41+N41-Q41+R41=U41,"OK",H41-I41+J41-M41+N41-Q41+R41-U41) -> OK | Y41: =IF(F41=1,"",W41-E41) | Z41: =H41+J41-I41 -> 0 | AA41: =IF(F41=1,0,AA$6) -> 0 | AB41: =IF(AA41=0,0,Z41/AA41) -> 0
A42: =Horaire!A42 -> PASSOT LA BARGE | B42: =Horaire!B42 -> 0.29166667 | C42: =Horaire!C42 -> D13 | D42: =VLOOKUP(C42,'Liste chauffeur'!$B$5:$L$19,2,TRUE)&" "&VLOOKUP(C42,'Liste chauffeur'!$B$5:$L$19,3,TRUE) -> MOURIDI Aktoir | F42: =COUNTBLANK(E42) -> 1 | L42: =K42-E42 -> 0 | V42: =IF(H42-I42+J42-M42+N42-Q42+R42=U42,"OK",H42-I42+J42-M42+N42-Q42+R42-U42) -> OK | Y42: =IF(F42=1,"",W42-E42) | Z42: =H42+J42-I42 -> 0 | AA42: =IF(F42=1,0,AA$6) -> 0 | AB42: =IF(AA42=0,0,Z42/AA42) -> 0
A43: M'TSAPERE | B43: =Horaire!B43 -> 0.29166667 | C43: =Horaire!C43 -> D4 | D43: =VLOOKUP(C43,'Liste chauffeur'!$B$5:$L$19,2,TRUE)&" "&VLOOKUP(C43,'Liste chauffeur'!$B$5:$L$19,3,TRUE) -> AMBDI Houmadi | F43: =COUNTBLANK(E43) -> 1 | L43: =K43-E43 -> 0 | V43: =IF(H43-I43+J43-M43+N43-Q43+R43=U43,"OK",H43-I43+J43-M43+N43-Q43+R43-U43) -> OK | Y43: =IF(F43=1,"",W43-E43) | Z43: =H43+J43-I43 -> 0 | AA43: =IF(F43=1,0,AA$6) -> 0 | AB43: =IF(AA43=0,0,Z43/AA43) -> 0
A44: =Horaire!A44 -> PASSOT LA BARGE | B44: =Horaire!B44 -> 0.29166667 | C44: =Horaire!C44 -> D11 | D44: =VLOOKUP(C44,'Liste chauffeur'!$B$5:$L$19,2,TRUE)&" "&VLOOKUP(C44,'Liste chauffeur'!$B$5:$L$19,3,TRUE) -> ALLAOUI Soibrane | F44: =COUNTBLANK(E44) -> 1 | L44: =K44-E44 -> 0 | V44: =IF(H44-I44+J44-M44+N44-Q44+R44=U44,"OK",H44-I44+J44-M44+N44-Q44+R44-U44) -> OK | Y44: =IF(F44=1,"",W44-E44) | Z44: =H44+J44-I44 -> 0 | AA44: =IF(F44=1,0,AA$6) -> 0 | AB44: =IF(AA44=0,0,Z44/AA44) -> 0
A45: =Horaire!A45 -> DOUJANI | B45: =Horaire!B45 -> 0.29861111 | C45: =Horaire!C45 -> D12 | D45: =VLOOKUP(C45,'Liste chauffeur'!$B$5:$L$19,2,TRUE)&" "&VLOOKUP(C45,'Liste chauffeur'!$B$5:$L$19,3,TRUE) -> VELOU M'COLO M'Berou | F45: =COUNTBLANK(E45) -> 1 | L45: =K45-E45 -> 0 | V45: =IF(H45-I45+J45-M45+N45-Q45+R45=U45,"OK",H45-I45+J45-M45+N45-Q45+R45-U45) -> OK | Y45: =IF(F45=1,"",W45-E45) | Z45: =H45+J45-I45 -> 0 | AA45: =IF(F45=1,0,AA$6) -> 0 | AB45: =IF(AA45=0,0,Z45/AA45) -> 0
A46: =Horaire!A46 -> PASSOT LA BARGE | B46: =Horaire!B46 -> 0.29861111 | C46: =Horaire!C46 -> D3 | D46: =VLOOKUP(C46,'Liste chauffeur'!$B$5:$L$19,2,TRUE)&" "&VLOOKUP(C46,'Liste chauffeur'!$B$5:$L$19,3,TRUE) -> ABDOURAHIM Mohamed | F46: =COUNTBLANK(E46) -> 1 | L46: =K46-E46 -> 0 | V46: =IF(H46-I46+J46-M46+N46-Q46+R46=U46,"OK",H46-I46+J46-M46+N46-Q46+R46-U46) -> OK | Y46: =IF(F46=1,"",W46-E46) | Z46: =H46+J46-I46 -> 0 | AA46: =IF(F46=1,0,AA$6) -> 0 | AB46: =IF(AA46=0,0,Z46/AA46) -> 0
A47: M'TSAPERE | B47: =Horaire!B47 -> 0.29861111 | C47: =Horaire!C47 -> D5 | D47: =VLOOKUP(C47,'Liste chauffeur'!$B$5:$L$19,2,TRUE)&" "&VLOOKUP(C47,'Liste chauffeur'!$B$5:$L$19,3,TRUE) -> AMINA Selemani | F47: =COUNTBLANK(E47) -> 1 | L47: =K47-E47 -> 0 | Y47: =IF(F47=1,"",W47-E47) | Z47: =H47+J47-I47 -> 0 | AA47: =IF(F47=1,0,AA$6) -> 0 | AB47: =IF(AA47=0,0,Z47/AA47) -> 0
A48: =Horaire!A48 -> PASSOT LA BARGE | B48: =Horaire!B48 -> 0.29861111 | C48: =Horaire!C48 -> D14 | D48: =VLOOKUP(C48,'Liste chauffeur'!$B$5:$L$19,2,TRUE)&" "&VLOOKUP(C48,'Liste chauffeur'!$B$5:$L$19,3,TRUE) -> AHAMADI Laydine | F48: =COUNTBLANK(E48) -> 1 | Y48: =IF(F48=1,"",W48-E48) | Z48: =H48+J48-I48 -> 0 | AA48: =IF(F48=1,0,AA$6) -> 0 | AB48: =IF(AA48=0,0,Z48/AA48) -> 0
A49: =Horaire!A49 -> DOUJANI | B49: =Horaire!B49 -> 0.30555556 | C49: =Horaire!C49 -> D2 | D49: =VLOOKUP(C49,'Liste chauffeur'!$B$5:$L$19,2,TRUE)&" "&VLOOKUP(C49,'Liste chauffeur'!$B$5:$L$19,3,TRUE) -> BARAKA Soumaila | F49: =COUNTBLANK(E49) -> 1 | Y49: =IF(F49=1,"",W49-E49) | Z49: =H49+J49-I49 -> 0 | AA49: =IF(F49=1,0,AA$6) -> 0 | AB49: =IF(AA49=0,0,Z49/AA49) -> 0
A50: =Horaire!A50 -> PASSOT LA BARGE | B50: =Horaire!B50 -> 0.30555556 | C50: =Horaire!C50 -> D10 | D50: =VLOOKUP(C50,'Liste chauffeur'!$B$5:$L$19,2,TRUE)&" "&VLOOKUP(C50,'Liste chauffeur'!$B$5:$L$19,3,TRUE) -> KAMARDINE Mansour (Salarié) | F50: =COUNTBLANK(E50) -> 1 | Y50: =IF(F50=1,"",W50-E50) | Z50: =H50+J50-I50 -> 0 | AA50: =IF(F50=1,0,AA$6) -> 0 | AB50: =IF(AA50=0,0,Z50/AA50) -> 0
A51: M'TSAPERE | B51: =Horaire!B51 -> 0.30555556 | C51: =Horaire!C51 -> D7 | D51: =VLOOKUP(C51,'Liste chauffeur'!$B$5:$L$19,2,TRUE)&" "&VLOOKUP(C51,'Liste chauffeur'!$B$5:$L$19,3,TRUE) -> COMBO Said | F51: =COUNTBLANK(E51) -> 1 | Y51: =IF(F51=1,"",W51-E51) | Z51: =H51+J51-I51 -> 0 | AA51: =IF(F51=1,0,AA$6) -> 0 | AB51: =IF(AA51=0,0,Z51/AA51) -> 0
A52: =Horaire!A52 -> PASSOT LA BARGE | B52: =Horaire!B52 -> 0.30555556 | C52: =Horaire!C52 -> D6 | D52: =VLOOKUP(C52,'Liste chauffeur'!$B$5:$L$19,2,TRUE)&" "&VLOOKUP(C52,'Liste chauffeur'!$B$5:$L$19,3,TRUE) -> ABDOU HAMIDOUNE Nassabia | F52: =COUNTBLANK(E52) -> 1 | Y52: =IF(F52=1,"",W52-E52) | Z52: =H52+J52-I52 -> 0 | AA52: =IF(F52=1,0,AA$6) -> 0 | AB52: =IF(AA52=0,0,Z52/AA52) -> 0
A53: =Horaire!A53 -> DOUJANI | B53: =Horaire!B53 -> 0.3125 | C53: =Horaire!C53 -> D13 | D53: =VLOOKUP(C53,'Liste chauffeur'!$B$5:$L$19,2,TRUE)&" "&VLOOKUP(C53,'Liste chauffeur'!$B$5:$L$19,3,TRUE) -> MOURIDI Aktoir | F53: =COUNTBLANK(E53) -> 1 | Y53: =IF(F53=1,"",W53-E53) | Z53: =H53+J53-I53 -> 0 | AA53: =IF(F53=1,0,AA$6) -> 0 | AB53: =IF(AA53=0,0,Z53/AA53) -> 0
A54: =Horaire!A54 -> PASSOT LA BARGE | B54: =Horaire!B54 -> 0.3125 | C54: =Horaire!C54 -> D1 | D54: =VLOOKUP(C54,'Liste chauffeur'!$B$5:$L$19,2,TRUE)&" "&VLOOKUP(C54,'Liste chauffeur'!$B$5:$L$19,3,TRUE) -> MOHAMED Ali (laglace) | F54: =COUNTBLANK(E54) -> 1 | Y54: =IF(F54=1,"",W54-E54) | Z54: =H54+J54-I54 -> 0 | AA54: =IF(F54=1,0,AA$6) -> 0 | AB54: =IF(AA54=0,0,Z54/AA54) -> 0
A55: M'TSAPERE | B55: =Horaire!B55 -> 0.3125 | C55: =Horaire!C55 -> D11 | D55: =VLOOKUP(C55,'Liste chauffeur'!$B$5:$L$19,2,TRUE)&" "&VLOOKUP(C55,'Liste chauffeur'!$B$5:$L$19,3,TRUE) -> ALLAOUI Soibrane | F55: =COUNTBLANK(E55) -> 1 | Y55: =IF(F55=1,"",W55-E55) | Z55: =H55+J55-I55 -> 0 | AA55: =IF(F55=1,0,AA$6) -> 0 | AB55: =IF(AA55=0,0,Z55/AA55) -> 0
A56: =Horaire!A56 -> PASSOT LA BARGE | B56: =Horaire!B56 -> 0.3125 | C56: =Horaire!C56 -> D4 | D56: =VLOOKUP(C56,'Liste chauffeur'!$B$5:$L$19,2,TRUE)&" "&VLOOKUP(C56,'Liste chauffeur'!$B$5:$L$19,3,TRUE) -> AMBDI Houmadi | F56: =COUNTBLANK(E56) -> 1 | Z56: =H56+J56-I56 -> 0 | AA56: =IF(F56=1,0,AA$6) -> 0 | AB56: =IF(AA56=0,0,Z56/AA56) -> 0
A57: =Horaire!A57 -> DOUJANI | B57: =Horaire!B57 -> 0.31944444 | C57: =Horaire!C57 -> D3 | D57: =VLOOKUP(C57,'Liste chauffeur'!$B$5:$L$19,2,TRUE)&" "&VLOOKUP(C57,'Liste chauffeur'!$B$5:$L$19,3,TRUE) -> ABDOURAHIM Mohamed | F57: =COUNTBLANK(E57) -> 1 | Z57: =H57+J57-I57 -> 0 | AA57: =IF(F57=1,0,AA$6) -> 0 | AB57: =IF(AA57=0,0,Z57/AA57) -> 0
A58: =Horaire!A58 -> PASSOT LA BARGE | B58: =Horaire!B58 -> 0.31944444 | C58: =Horaire!C58 -> D12 | D58: =VLOOKUP(C58,'Liste chauffeur'!$B$5:$L$19,2,TRUE)&" "&VLOOKUP(C58,'Liste chauffeur'!$B$5:$L$19,3,TRUE) -> VELOU M'COLO M'Berou | F58: =COUNTBLANK(E58) -> 1 | Z58: =H58+J58-I58 -> 0 | AA58: =IF(F58=1,0,AA$6) -> 0 | AB58: =IF(AA58=0,0,Z58/AA58) -> 0
A59: M'TSAPERE | B59: =Horaire!B59 -> 0.31944444 | C59: =Horaire!C59 -> D14 | D59: =VLOOKUP(C59,'Liste chauffeur'!$B$5:$L$19,2,TRUE)&" "&VLOOKUP(C59,'Liste chauffeur'!$B$5:$L$19,3,TRUE) -> AHAMADI Laydine | F59: =COUNTBLANK(E59) -> 1 | Z59: =H59+J59-I59 -> 0 | AA59: =IF(F59=1,0,AA$6) -> 0 | AB59: =IF(AA59=0,0,Z59/AA59) -> 0
A60: =Horaire!A60 -> PASSOT LA BARGE | B60: =Horaire!B60 -> 0.31944444 | C60: =Horaire!C60 -> D5 | D60: =VLOOKUP(C60,'Liste chauffeur'!$B$5:$L$19,2,TRUE)&" "&VLOOKUP(C60,'Liste chauffeur'!$B$5:$L$19,3,TRUE) -> AMINA Selemani | F60: =COUNTBLANK(E60) -> 1 | Z60: =H60+J60-I60 -> 0 | AA60: =IF(F60=1,0,AA$6) -> 0 | AB60: =IF(AA60=0,0,Z60/AA60) -> 0
A61: =Horaire!A61 -> DOUJANI | B61: =Horaire!B61 -> 0.32638889 | C61: =Horaire!C61 -> D10 | D61: =VLOOKUP(C61,'Liste chauffeur'!$B$5:$L$19,2,TRUE)&" "&VLOOKUP(C61,'Liste chauffeur'!$B$5:$L$19,3,TRUE) -> KAMARDINE Mansour (Salarié) | F61: =COUNTBLANK(E61) -> 1 | Z61: =H61+J61-I61 -> 0 | AA61: =IF(F61=1,0,AA$6) -> 0 | AB61: =IF(AA61=0,0,Z61/AA61) -> 0
A62: =Horaire!A62 -> PASSOT LA BARGE | B62: =Horaire!B62 -> 0.32638889 | C62: =Horaire!C62 -> D2 | D62: =VLOOKUP(C62,'Liste chauffeur'!$B$5:$L$19,2,TRUE)&" "&VLOOKUP(C62,'Liste chauffeur'!$B$5:$L$19,3,TRUE) -> BARAKA Soumaila | F62: =COUNTBLANK(E62) -> 1 | Z62: =H62+J62-I62 -> 0 | AA62: =IF(F62=1,0,AA$6) -> 0 | AB62: =IF(AA62=0,0,Z62/AA62) -> 0
A63: M'TSAPERE | B63: =Horaire!B63 -> 0.32638889 | C63: =Horaire!C63 -> D6 | D63: =VLOOKUP(C63,'Liste chauffeur'!$B$5:$L$19,2,TRUE)&" "&VLOOKUP(C63,'Liste chauffeur'!$B$5:$L$19,3,TRUE) -> ABDOU HAMIDOUNE Nassabia | F63: =COUNTBLANK(E63) -> 1 | Z63: =H63+J63-I63 -> 0 | AA63: =IF(F63=1,0,AA$6) -> 0 | AB63: =IF(AA63=0,0,Z63/AA63) -> 0
A64: =Horaire!A64 -> PASSOT LA BARGE | B64: =Horaire!B64 -> 0.32638889 | C64: =Horaire!C64 -> D7 | D64: =VLOOKUP(C64,'Liste chauffeur'!$B$5:$L$19,2,TRUE)&" "&VLOOKUP(C64,'Liste chauffeur'!$B$5:$L$19,3,TRUE) -> COMBO Said | F64: =COUNTBLANK(E64) -> 1 | Z64: =H64+J64-I64 -> 0 | AA64: =IF(F64=1,0,AA$6) -> 0 | AB64: =IF(AA64=0,0,Z64/AA64) -> 0
A65: =Horaire!A65 -> DOUJANI | B65: =Horaire!B65 -> 0.33333333 | C65: =Horaire!C65 -> D1 | D65: =VLOOKUP(C65,'Liste chauffeur'!$B$5:$L$19,2,TRUE)&" "&VLOOKUP(C65,'Liste chauffeur'!$B$5:$L$19,3,TRUE) -> MOHAMED Ali (laglace) | F65: =COUNTBLANK(E65) -> 1 | Z65: =H65+J65-I65 -> 0 | AA65: =IF(F65=1,0,AA$6) -> 0 | AB65: =IF(AA65=0,0,Z65/AA65) -> 0
A66: =Horaire!A66 -> PASSOT LA BARGE | B66: =Horaire!B66 -> 0.33333333 | C66: =Horaire!C66 -> D13 | D66: =VLOOKUP(C66,'Liste chauffeur'!$B$5:$L$19,2,TRUE)&" "&VLOOKUP(C66,'Liste chauffeur'!$B$5:$L$19,3,TRUE) -> MOURIDI Aktoir | F66: =COUNTBLANK(E66) -> 1 | Z66: =H66+J66-I66 -> 0 | AA66: =IF(F66=1,0,AA$6) -> 0 | AB66: =IF(AA66=0,0,Z66/AA66) -> 0
A67: M'TSAPERE | B67: =Horaire!B67 -> 0.33333333 | C67: =Horaire!C67 -> D4 | D67: =VLOOKUP(C67,'Liste chauffeur'!$B$5:$L$19,2,TRUE)&" "&VLOOKUP(C67,'Liste chauffeur'!$B$5:$L$19,3,TRUE) -> AMBDI Houmadi | F67: =COUNTBLANK(E67) -> 1 | Z67: =H67+J67-I67 -> 0 | AA67: =IF(F67=1,0,AA$6) -> 0 | AB67: =IF(AA67=0,0,Z67/AA67) -> 0
A68: =Horaire!A68 -> PASSOT LA BARGE | B68: =Horaire!B68 -> 0.33333333 | C68: =Horaire!C68 -> D11 | D68: =VLOOKUP(C68,'Liste chauffeur'!$B$5:$L$19,2,TRUE)&" "&VLOOKUP(C68,'Liste chauffeur'!$B$5:$L$19,3,TRUE) -> ALLAOUI Soibrane | F68: =COUNTBLANK(E68) -> 1 | Z68: =H68+J68-I68 -> 0 | AA68: =IF(F68=1,0,AA$6) -> 0 | AB68: =IF(AA68=0,0,Z68/AA68) -> 0
A69: =Horaire!A69 -> DOUJANI | B69: =Horaire!B69 -> 0.34722222 | C69: =Horaire!C69 -> D2 | D69: =VLOOKUP(C69,'Liste chauffeur'!$B$5:$L$19,2,TRUE)&" "&VLOOKUP(C69,'Liste chauffeur'!$B$5:$L$19,3,TRUE) -> BARAKA Soumaila | F69: =COUNTBLANK(E69) -> 1 | Z69: =H69+J69-I69 -> 0 | AA69: =IF(F69=1,0,AA$6) -> 0 | AB69: =IF(AA69=0,0,Z69/AA69) -> 0
A70: =Horaire!A70 -> PASSOT LA BARGE | B70: =Horaire!B70 -> 0.34722222 | C70: =Horaire!C70 -> D10 | D70: =VLOOKUP(C70,'Liste chauffeur'!$B$5:$L$19,2,TRUE)&" "&VLOOKUP(C70,'Liste chauffeur'!$B$5:$L$19,3,TRUE) -> KAMARDINE Mansour (Salarié) | F70: =COUNTBLANK(E70) -> 1 | Z70: =H70+J70-I70 -> 0 | AA70: =IF(F70=1,0,AA$6) -> 0 | AB70: =IF(AA70=0,0,Z70/AA70) -> 0
A71: =Horaire!A71 -> DOUJANI | B71: =Horaire!B71 -> 0.36111111 | C71: =Horaire!C71 -> D11 | D71: =VLOOKUP(C71,'Liste chauffeur'!$B$5:$L$19,2,TRUE)&" "&VLOOKUP(C71,'Liste chauffeur'!$B$5:$L$19,3,TRUE) -> ALLAOUI Soibrane | F71: =COUNTBLANK(E71) -> 1 | Z71: =H71+J71-I71 -> 0 | AA71: =IF(F71=1,0,AA$6) -> 0 | AB71: =IF(AA71=0,0,Z71/AA71) -> 0
A72: =Horaire!A72 -> PASSOT LA BARGE | B72: =Horaire!B72 -> 0.36111111 | C72: =Horaire!C72 -> D4 | D72: =VLOOKUP(C72,'Liste chauffeur'!$B$5:$L$19,2,TRUE)&" "&VLOOKUP(C72,'Liste chauffeur'!$B$5:$L$19,3,TRUE) -> AMBDI Houmadi | F72: =COUNTBLANK(E72) -> 1 | Z72: =H72+J72-I72 -> 0 | AA72: =IF(F72=1,0,AA$6) -> 0 | AB72: =IF(AA72=0,0,Z72/AA72) -> 0
A73: =Horaire!A73 -> DOUJANI | B73: =Horaire!B73 -> 0.375 | C73: =Horaire!C73 -> D10 | D73: =VLOOKUP(C73,'Liste chauffeur'!$B$5:$L$19,2,TRUE)&" "&VLOOKUP(C73,'Liste chauffeur'!$B$5:$L$19,3,TRUE) -> KAMARDINE Mansour (Salarié) | F73: =COUNTBLANK(E73) -> 1 | Z73: =H73+J73-I73 -> 0 | AA73: =IF(F73=1,0,AA$6) -> 0 | AB73: =IF(AA73=0,0,Z73/AA73) -> 0
A74: =Horaire!A74 -> PASSOT LA BARGE | B74: =Horaire!B74 -> 0.375 | C74: =Horaire!C74 -> D2 | D74: =VLOOKUP(C74,'Liste chauffeur'!$B$5:$L$19,2,TRUE)&" "&VLOOKUP(C74,'Liste chauffeur'!$B$5:$L$19,3,TRUE) -> BARAKA Soumaila | F74: =COUNTBLANK(E74) -> 1 | Z74: =H74+J74-I74 -> 0 | AA74: =IF(F74=1,0,AA$6) -> 0 | AB74: =IF(AA74=0,0,Z74/AA74) -> 0
A75: =Horaire!A75 -> DOUJANI | B75: =Horaire!B75 -> 0.38888889 | C75: =Horaire!C75 -> D4 | D75: =VLOOKUP(C75,'Liste chauffeur'!$B$5:$L$19,2,TRUE)&" "&VLOOKUP(C75,'Liste chauffeur'!$B$5:$L$19,3,TRUE) -> AMBDI Houmadi | F75: =COUNTBLANK(E75) -> 1 | Z75: =H75+J75-I75 -> 0 | AA75: =IF(F75=1,0,AA$6) -> 0 | AB75: =IF(AA75=0,0,Z75/AA75) -> 0
A76: =Horaire!A76 -> PASSOT LA BARGE | B76: =Horaire!B76 -> 0.38888889 | C76: =Horaire!C76 -> D11 | D76: =VLOOKUP(C76,'Liste chauffeur'!$B$5:$L$19,2,TRUE)&" "&VLOOKUP(C76,'Liste chauffeur'!$B$5:$L$19,3,TRUE) -> ALLAOUI Soibrane | F76: =COUNTBLANK(E76) -> 1 | Z76: =H76+J76-I76 -> 0 | AA76: =IF(F76=1,0,AA$6) -> 0 | AB76: =IF(AA76=0,0,Z76/AA76) -> 0
A77: =Horaire!A77 -> DOUJANI | B77: =Horaire!B77 -> 0.40277778 | C77: =Horaire!C77 -> D2 | D77: =VLOOKUP(C77,'Liste chauffeur'!$B$5:$L$19,2,TRUE)&" "&VLOOKUP(C77,'Liste chauffeur'!$B$5:$L$19,3,TRUE) -> BARAKA Soumaila | F77: =COUNTBLANK(E77) -> 1 | Z77: =H77+J77-I77 -> 0 | AA77: =IF(F77=1,0,AA$6) -> 0 | AB77: =IF(AA77=0,0,Z77/AA77) -> 0
A78: =Horaire!A78 -> PASSOT LA BARGE | B78: =Horaire!B78 -> 0.40277778 | C78: =Horaire!C78 -> D10 | D78: =VLOOKUP(C78,'Liste chauffeur'!$B$5:$L$19,2,TRUE)&" "&VLOOKUP(C78,'Liste chauffeur'!$B$5:$L$19,3,TRUE) -> KAMARDINE Mansour (Salarié) | F78: =COUNTBLANK(E78) -> 1 | Z78: =H78+J78-I78 -> 0 | AA78: =IF(F78=1,0,AA$6) -> 0 | AB78: =IF(AA78=0,0,Z78/AA78) -> 0
A79: =Horaire!A79 -> DOUJANI | B79: =Horaire!B79 -> 0.41666667 | C79: =Horaire!C79 -> D11 | D79: =VLOOKUP(C79,'Liste chauffeur'!$B$5:$L$19,2,TRUE)&" "&VLOOKUP(C79,'Liste chauffeur'!$B$5:$L$19,3,TRUE) -> ALLAOUI Soibrane | F79: =COUNTBLANK(E79) -> 1 | Z79: =H79+J79-I79 -> 0 | AA79: =IF(F79=1,0,AA$6) -> 0 | AB79: =IF(AA79=0,0,Z79/AA79) -> 0
... A92: =Horaire!A92 -> PASSOT LA BARGE | B92: =Horaire!B92 -> 0.5 | C92: =Horaire!C92 -> D11 | D92: =VLOOKUP(C92,'Liste chauffeur'!$B$5:$L$19,2,TRUE)&" "&VLOOKUP(C92,'Liste chauffeur'!$B$5:$L$19,3,TRUE) -> ALLAOUI Soibrane | F92: =COUNTBLANK(E92) -> 1 | Z92: =H92+J92-I92 -> 0 | AA92: =IF(F92=1,0,AA$6) -> 0 | AB92: =IF(AA92=0,0,Z92/AA92) -> 0
B93: ST1 | F93: =SUM(F8:F92) -> 85 | G93: =SUM(G8:G92) -> 0 | Y93: =AVERAGE(Y8:Y92) -> #DIV/0! | Z93: =SUM(Z8:Z92) -> 0 | AA93: =SUM(AA8:AA92) -> 0 | AB93: =Z93/AA93 -> #DIV/0!
A94: =Horaire!A93 -> DOUJANI | B94: =Horaire!B93 -> 0.51388889 | C94: =Horaire!C93 -> D2 | D94: =VLOOKUP(C94,'Liste chauffeur'!$B$5:$L$19,2,TRUE)&" "&VLOOKUP(C94,'Liste chauffeur'!$B$5:$L$19,3,TRUE) -> BARAKA Soumaila | F94: =COUNTBLANK(E94) -> 1 | Z94: =H94+J94-I94 -> 0 | AA94: =IF(F94=1,0,AA$6) -> 0 | AB94: =IF(AA94=0,0,Z94/AA94) -> 0
A95: =Horaire!A94 -> PASSOT LA BARGE | B95: =Horaire!B94 -> 0.51388889 | C95: =Horaire!C94 -> D10 | D95: =VLOOKUP(C95,'Liste chauffeur'!$B$5:$L$19,2,TRUE)&" "&VLOOKUP(C95,'Liste chauffeur'!$B$5:$L$19,3,TRUE) -> KAMARDINE Mansour (Salarié) | F95: =COUNTBLANK(E95) -> 1 | Z95: =H95+J95-I95 -> 0 | AA95: =IF(F95=1,0,AA$6) -> 0 | AB95: =IF(AA95=0,0,Z95/AA95) -> 0
A96: =Horaire!A95 -> DOUJANI | B96: =Horaire!B95 -> 0.52777778 | C96: =Horaire!C95 -> D11 | D96: =VLOOKUP(C96,'Liste chauffeur'!$B$5:$L$19,2,TRUE)&" "&VLOOKUP(C96,'Liste chauffeur'!$B$5:$L$19,3,TRUE) -> ALLAOUI Soibrane | F96: =COUNTBLANK(E96) -> 1 | Z96: =H96+J96-I96 -> 0 | AA96: =IF(F96=1,0,AA$6) -> 0 | AB96: =IF(AA96=0,0,Z96/AA96) -> 0
A97: =Horaire!A96 -> PASSOT LA BARGE | B97: =Horaire!B96 -> 0.52777778 | C97: =Horaire!C96 -> D4 | D97: =VLOOKUP(C97,'Liste chauffeur'!$B$5:$L$19,2,TRUE)&" "&VLOOKUP(C97,'Liste chauffeur'!$B$5:$L$19,3,TRUE) -> AMBDI Houmadi | F97: =COUNTBLANK(E97) -> 1 | Z97: =H97+J97-I97 -> 0 | AA97: =IF(F97=1,0,AA$6) -> 0 | AB97: =IF(AA97=0,0,Z97/AA97) -> 0
A98: =Horaire!A97 -> DOUJANI | B98: =Horaire!B97 -> 0.54166667 | C98: =Horaire!C97 -> D10 | D98: =VLOOKUP(C98,'Liste chauffeur'!$B$5:$L$19,2,TRUE)&" "&VLOOKUP(C98,'Liste chauffeur'!$B$5:$L$19,3,TRUE) -> KAMARDINE Mansour (Salarié) | F98: =COUNTBLANK(E98) -> 1 | Z98: =H98+J98-I98 -> 0 | AA98: =IF(F98=1,0,AA$6) -> 0 | AB98: =IF(AA98=0,0,Z98/AA98) -> 0
A99: =Horaire!A98 -> PASSOT LA BARGE | B99: =Horaire!B98 -> 0.54166667 | C99: =Horaire!C98 -> D2 | D99: =VLOOKUP(C99,'Liste chauffeur'!$B$5:$L$19,2,TRUE)&" "&VLOOKUP(C99,'Liste chauffeur'!$B$5:$L$19,3,TRUE) -> BARAKA Soumaila | F99: =COUNTBLANK(E99) -> 1 | Z99: =H99+J99-I99 -> 0 | AA99: =IF(F99=1,0,AA$6) -> 0 | AB99: =IF(AA99=0,0,Z99/AA99) -> 0
A100: =Horaire!A99 -> DOUJANI | B100: =Horaire!B99 -> 0.55555556 | C100: =Horaire!C99 -> D4 | D100: =VLOOKUP(C100,'Liste chauffeur'!$B$5:$L$19,2,TRUE)&" "&VLOOKUP(C100,'Liste chauffeur'!$B$5:$L$19,3,TRUE) -> AMBDI Houmadi | F100: =COUNTBLANK(E100) -> 1 | Z100: =H100+J100-I100 -> 0 | AA100: =IF(F100=1,0,AA$6) -> 0 | AB100: =IF(AA100=0,0,Z100/AA100) -> 0
A101: =Horaire!A100 -> PASSOT LA BARGE | B101: =Horaire!B100 -> 0.55555556 | C101: =Horaire!C100 -> D11 | D101: =VLOOKUP(C101,'Liste chauffeur'!$B$5:$L$19,2,TRUE)&" "&VLOOKUP(C101,'Liste chauffeur'!$B$5:$L$19,3,TRUE) -> ALLAOUI Soibrane | F101: =COUNTBLANK(E101) -> 1 | Z101: =H101+J101-I101 -> 0 | AA101: =IF(F101=1,0,AA$6) -> 0 | AB101: =IF(AA101=0,0,Z101/AA101) -> 0
A102: =Horaire!A101 -> DOUJANI | B102: =Horaire!B101 -> 0.56944444 | C102: =Horaire!C101 -> D2 | D102: =VLOOKUP(C102,'Liste chauffeur'!$B$5:$L$19,2,TRUE)&" "&VLOOKUP(C102,'Liste chauffeur'!$B$5:$L$19,3,TRUE) -> BARAKA Soumaila | F102: =COUNTBLANK(E102) -> 1 | Z102: =H102+J102-I102 -> 0 | AA102: =IF(F102=1,0,AA$6) -> 0 | AB102: =IF(AA102=0,0,Z102/AA102) -> 0
A103: =Horaire!A102 -> PASSOT LA BARGE | B103: =Horaire!B102 -> 0.56944444 | C103: =Horaire!C102 -> D10 | D103: =VLOOKUP(C103,'Liste chauffeur'!$B$5:$L$19,2,TRUE)&" "&VLOOKUP(C103,'Liste chauffeur'!$B$5:$L$19,3,TRUE) -> KAMARDINE Mansour (Salarié) | F103: =COUNTBLANK(E103) -> 1 | Z103: =H103+J103-I103 -> 0 | AA103: =IF(F103=1,0,AA$6) -> 0 | AB103: =IF(AA103=0,0,Z103/AA103) -> 0
A104: =Horaire!A103 -> DOUJANI | B104: =Horaire!B103 -> 0.58333333 | C104: =Horaire!C103 -> D1 | D104: =VLOOKUP(C104,'Liste chauffeur'!$B$5:$L$19,2,TRUE)&" "&VLOOKUP(C104,'Liste chauffeur'!$B$5:$L$19,3,TRUE) -> MOHAMED Ali (laglace) | F104: =COUNTBLANK(E104) -> 1 | Z104: =H104+J104-I104 -> 0 | AA104: =IF(F104=1,0,AA$6) -> 0 | AB104: =IF(AA104=0,0,Z104/AA104) -> 0
A105: =Horaire!A104 -> PASSOT LA BARGE | B105: =Horaire!B104 -> 0.58333333 | C105: =Horaire!C104 -> D4 | D105: =VLOOKUP(C105,'Liste chauffeur'!$B$5:$L$19,2,TRUE)&" "&VLOOKUP(C105,'Liste chauffeur'!$B$5:$L$19,3,TRUE) -> AMBDI Houmadi | F105: =COUNTBLANK(E105) -> 1 | Z105: =H105+J105-I105 -> 0 | AA105: =IF(F105=1,0,AA$6) -> 0 | AB105: =IF(AA105=0,0,Z105/AA105) -> 0
... A163: =Horaire!A162 -> PASSOT LA BARGE | B163: =Horaire!B162 -> 0.875 | C163: =Horaire!C162 -> D9 | D163: =VLOOKUP(C163,'Liste chauffeur'!$B$5:$L$19,2,TRUE)&" "&VLOOKUP(C163,'Liste chauffeur'!$B$5:$L$19,3,TRUE) -> RENEE Assanati | F163: =COUNTBLANK(E163) -> 1 | Z163: =H163+J163-I163 -> 0 | AA163: =IF(F163=1,0,AA$6) -> 0 | AB163: =IF(AA163=0,0,Z163/AA163) -> 0
B164: ST2 | C164: ST | F164: =SUM(F94:F163) -> 70 | G164: =SUM(G94:G163) -> 0 | Y164: =AVERAGE(Y94:Y163) -> #DIV/0! | Z164: =SUM(Z94:Z163) -> 0 | AA164: =SUM(AA94:AA163) -> 0 | AB164: =IF(AA164=0,0,Z164/AA164) -> 0
B165: ST3 | C165: ST | F165: =F93+F164 -> 155 | G165: =G93+G164 -> 0 | Y165: =AVERAGE(Y8:Y92,Y94:Y163) -> #DIV/0! | Z165: =Z93+Z164 -> 0 | AA165: =AA93+AA164 -> 0 | AB165: =Z165/AA165 -> #DIV/0!
A166: REMPLACEMENT | C166: D
A167: REMPLACEMENT | C167: D
A168: REMPLACEMENT | C168: D
A169: REMPLACEMENT | C169: D | O169: =M169-#REF! -> #REF! | P169: =#REF!+#REF!-#REF! -> #REF!
A170: REMPLACEMENT | C170: D | O170: =M170-#REF! -> #REF! | P170: =#REF!+#REF!-#REF! -> #REF!
E172: Signature Chauffeur | I172: Signature Coordinateur
...

Sheet Feuille saisie samedi
A2: TYPE | B2: D15
A3: DATE | B3: 45627
A4: CHAUFFEUR | B4: =VLOOKUP(B2,'Liste chauffeur'!$B$5:$L$19,2,TRUE)&" "&VLOOKUP(B2,'Liste chauffeur'!$B$5:$L$19,3,TRUE) -> KAMARDINE Mansour
I6: Arrêt 1 | M6: Arrêt 2 | Q6: Arrêt 3 | W6: ARRIVEE | AA6: 8
B7: Heure théorique départ | C7: Horaire | D7: Chauffeur | E7: Heure réelle départ | F7: Trajet non effectué | G7: Départ avec plus de 10 mns retard | H7: Nbre personnes montée | I7: - | J7: + | K7: Heure arrivée arrêt 1 | L7: Délai | M7: - | N7: + | O7: Heure arrivée arrêt 2 | P7: Délai | Q7: - | R7: + | S7: Heure arrivée arrêt 3 | T7: Délai | U7: Nbre personnes descente | W7: Heure arrivée finale | X7: Commentaires | Y7: Temps Aller | Z7: Nbre personnes moyenne | AA7: Capacité max | AB7: Taux Fréquentation
A8: ='Horaire samedi'!A8 -> DOUJANI | B8: ='Horaire samedi'!B8 -> 0.25 | C8: ='Horaire samedi'!C8 -> D12 | D8: =VLOOKUP(C8,'Liste chauffeur'!$B$5:$L$18,2,TRUE)&" "&VLOOKUP(C8,'Liste chauffeur'!$B$5:$L$18,3,TRUE) -> VELOU M'COLO M'Berou | F8: =COUNTBLANK(E8) -> 1 | Y8: =IF(F8=1,"",W8-E8) | Z8: =H8+J8-I8 -> 0 | AA8: =IF(F8=1,0,AA$6) -> 0 | AB8: =IF(AA8=0,0,Z8/AA8) -> 0
A9: ='Horaire samedi'!A9 -> DOUJANI | B9: ='Horaire samedi'!B9 -> 0.26388889 | C9: ='Horaire samedi'!C9 -> D13 | D9: =VLOOKUP(C9,'Liste chauffeur'!$B$5:$L$18,2,TRUE)&" "&VLOOKUP(C9,'Liste chauffeur'!$B$5:$L$18,3,TRUE) -> MOURIDI Aktoir | F9: =COUNTBLANK(E9) -> 1 | Y9: =IF(F9=1,"",W9-E9) | Z9: =H9+J9-I9 -> 0 | AA9: =IF(F9=1,0,AA$6) -> 0 | AB9: =IF(AA9=0,0,Z9/AA9) -> 0
A10: ='Horaire samedi'!A10 -> PASSOT LA BARGE | B10: ='Horaire samedi'!B10 -> 0.27083333 | C10: ='Horaire samedi'!C10 -> D12 | D10: =VLOOKUP(C10,'Liste chauffeur'!$B$5:$L$18,2,TRUE)&" "&VLOOKUP(C10,'Liste chauffeur'!$B$5:$L$18,3,TRUE) -> VELOU M'COLO M'Berou | F10: =COUNTBLANK(E10) -> 1 | Y10: =IF(F10=1,"",W10-E10) | Z10: =H10+J10-I10 -> 0 | AA10: =IF(F10=1,0,AA$6) -> 0 | AB10: =IF(AA10=0,0,Z10/AA10) -> 0
A11: ='Horaire samedi'!A11 -> DOUJANI | B11: ='Horaire samedi'!B11 -> 0.27777778 | C11: ='Horaire samedi'!C11 -> D5 | D11: =VLOOKUP(C11,'Liste chauffeur'!$B$5:$L$18,2,TRUE)&" "&VLOOKUP(C11,'Liste chauffeur'!$B$5:$L$18,3,TRUE) -> AMINA Selemani | F11: =COUNTBLANK(E11) -> 1 | Y11: =IF(F11=1,"",W11-E11) | Z11: =H11+J11-I11 -> 0 | AA11: =IF(F11=1,0,AA$6) -> 0 | AB11: =IF(AA11=0,0,Z11/AA11) -> 0
A12: ='Horaire samedi'!A12 -> PASSOT LA BARGE | B12: ='Horaire samedi'!B12 -> 0.28472222 | C12: ='Horaire samedi'!C12 -> D13 | D12: =VLOOKUP(C12,'Liste chauffeur'!$B$5:$L$18,2,TRUE)&" "&VLOOKUP(C12,'Liste chauffeur'!$B$5:$L$18,3,TRUE) -> MOURIDI Aktoir | F12: =COUNTBLANK(E12) -> 1 | L12: =K12-E12 -> 0 | P12: =O12-K12 -> 0 | T12: =S12-O12 -> 0 | V12: =IF(H12-I12+J12-M12+N12-Q12+R12=U12,"OK",H12-I12+J12-M12+N12-Q12+R12-U12) -> OK | Y12: =IF(F12=1,"",W12-E12) | Z12: =H12+J12-I12 -> 0 | AA12: =IF(F12=1,0,AA$6) -> 0 | AB12: =IF(AA12=0,0,Z12/AA12) -> 0
A13: ='Horaire samedi'!A13 -> DOUJANI | B13: ='Horaire samedi'!B13 -> 0.29166667 | C13: ='Horaire samedi'!C13 -> D12 | D13: =VLOOKUP(C13,'Liste chauffeur'!$B$5:$L$18,2,TRUE)&" "&VLOOKUP(C13,'Liste chauffeur'!$B$5:$L$18,3,TRUE) -> VELOU M'COLO M'Berou | F13: =COUNTBLANK(E13) -> 1 | L13: =K13-E13 -> 0 | P13: =O13-K13 -> 0 | T13: =S13-O13 -> 0 | Y13: =IF(F13=1,"",W13-E13) | Z13: =H13+J13-I13 -> 0 | AA13: =IF(F13=1,0,AA$6) -> 0 | AB13: =IF(AA13=0,0,Z13/AA13) -> 0
A14: ='Horaire samedi'!A14 -> PASSOT LA BARGE | B14: ='Horaire samedi'!B14 -> 0.29861111 | C14: ='Horaire samedi'!C14 -> D5 | D14: =VLOOKUP(C14,'Liste chauffeur'!$B$5:$L$18,2,TRUE)&" "&VLOOKUP(C14,'Liste chauffeur'!$B$5:$L$18,3,TRUE) -> AMINA Selemani | F14: =COUNTBLANK(E14) -> 1 | L14: =K14-E14 -> 0 | P14: =O14-K14 -> 0 | T14: =S14-O14 -> 0 | Y14: =IF(F14=1,"",W14-E14) | Z14: =H14+J14-I14 -> 0 | AA14: =IF(F14=1,0,AA$6) -> 0 | AB14: =IF(AA14=0,0,Z14/AA14) -> 0
A15: ='Horaire samedi'!A15 -> DOUJANI | B15: ='Horaire samedi'!B15 -> 0.30555556 | C15: ='Horaire samedi'!C15 -> D13 | D15: =VLOOKUP(C15,'Liste chauffeur'!$B$5:$L$18,2,TRUE)&" "&VLOOKUP(C15,'Liste chauffeur'!$B$5:$L$18,3,TRUE) -> MOURIDI Aktoir | F15: =COUNTBLANK(E15) -> 1 | L15: =K15-E15 -> 0 | P15: =O15-K15 -> 0 | T15: =S15-O15 -> 0 | Y15: =IF(F15=1,"",W15-E15) | Z15: =H15+J15-I15 -> 0 | AA15: =IF(F15=1,0,AA$6) -> 0 | AB15: =IF(AA15=0,0,Z15/AA15) -> 0
A16: ='Horaire samedi'!A16 -> PASSOT LA BARGE | B16: ='Horaire samedi'!B16 -> 0.3125 | C16: ='Horaire samedi'!C16 -> D12 | D16: =VLOOKUP(C16,'Liste chauffeur'!$B$5:$L$18,2,TRUE)&" "&VLOOKUP(C16,'Liste chauffeur'!$B$5:$L$18,3,TRUE) -> VELOU M'COLO M'Berou | F16: =COUNTBLANK(E16) -> 1 | L16: =K16-E16 -> 0 | P16: =O16-K16 -> 0 | T16: =S16-O16 -> 0 | V16: =IF(H16-I16+J16-M16+N16-Q16+R16=U16,"OK",H16-I16+J16-M16+N16-Q16+R16-U16) -> OK | Y16: =IF(F16=1,"",W16-E16) | Z16: =H16+J16-I16 -> 0 | AA16: =IF(F16=1,0,AA$6) -> 0 | AB16: =IF(AA16=0,0,Z16/AA16) -> 0
A17: ='Horaire samedi'!A17 -> DOUJANI | B17: ='Horaire samedi'!B17 -> 0.31944444 | C17: ='Horaire samedi'!C17 -> D5 | D17: =VLOOKUP(C17,'Liste chauffeur'!$B$5:$L$18,2,TRUE)&" "&VLOOKUP(C17,'Liste chauffeur'!$B$5:$L$18,3,TRUE) -> AMINA Selemani | F17: =COUNTBLANK(E17) -> 1 | L17: =K17-E17 -> 0 | P17: =O17-K17 -> 0 | T17: =S17-O17 -> 0 | V17: =IF(H17-I17+J17-M17+N17-Q17+R17=U17,"OK",H17-I17+J17-M17+N17-Q17+R17-U17) -> OK | Y17: =IF(F17=1,"",W17-E17) | Z17: =H17+J17-I17 -> 0 | AA17: =IF(F17=1,0,AA$6) -> 0 | AB17: =IF(AA17=0,0,Z17/AA17) -> 0
A18: ='Horaire samedi'!A18 -> PASSOT LA BARGE | B18: ='Horaire samedi'!B18 -> 0.32638889 | C18: ='Horaire samedi'!C18 -> D13 | D18: =VLOOKUP(C18,'Liste chauffeur'!$B$5:$L$18,2,TRUE)&" "&VLOOKUP(C18,'Liste chauffeur'!$B$5:$L$18,3,TRUE) -> MOURIDI Aktoir | F18: =COUNTBLANK(E18) -> 1 | Z18: =H18+J18-I18 -> 0 | AA18: =IF(F18=1,0,AA$6) -> 0 | AB18: =IF(AA18=0,0,Z18/AA18) -> 0
A19: ='Horaire samedi'!A19 -> DOUJANI | B19: ='Horaire samedi'!B19 -> 0.33333333 | C19: ='Horaire samedi'!C19 -> D12 | D19: =VLOOKUP(C19,'Liste chauffeur'!$B$5:$L$18,2,TRUE)&" "&VLOOKUP(C19,'Liste chauffeur'!$B$5:$L$18,3,TRUE) -> VELOU M'COLO M'Berou | F19: =COUNTBLANK(E19) -> 1 | L19: =K19-E19 -> 0 | P19: =O19-K19 -> 0 | T19: =S19-O19 -> 0 | V19: =IF(H19-I19+J19-M19+N19-Q19+R19=U19,"OK",H19-I19+J19-M19+N19-Q19+R19-U19) -> OK | Y19: =IF(F19=1,"",W19-E19) | Z19: =H19+J19-I19 -> 0 | AA19: =IF(F19=1,0,AA$6) -> 0 | AB19: =IF(AA19=0,0,Z19/AA19) -> 0
A20: ='Horaire samedi'!A20 -> PASSOT LA BARGE | B20: ='Horaire samedi'!B20 -> 0.34027778 | C20: ='Horaire samedi'!C20 -> D5 | D20: =VLOOKUP(C20,'Liste chauffeur'!$B$5:$L$18,2,TRUE)&" "&VLOOKUP(C20,'Liste chauffeur'!$B$5:$L$18,3,TRUE) -> AMINA Selemani | F20: =COUNTBLANK(E20) -> 1 | L20: =K20-E20 -> 0 | P20: =O20-K20 -> 0 | T20: =S20-O20 -> 0 | V20: =IF(H20-I20+J20-M20+N20-Q20+R20=U20,"OK",H20-I20+J20-M20+N20-Q20+R20-U20) -> OK | Y20: =IF(F20=1,"",W20-E20) | Z20: =H20+J20-I20 -> 0 | AA20: =IF(F20=1,0,AA$6) -> 0 | AB20: =IF(AA20=0,0,Z20/AA20) -> 0
A21: ='Horaire samedi'!A21 -> DOUJANI | B21: ='Horaire samedi'!B21 -> 0.34722222 | C21: ='Horaire samedi'!C21 -> D13 | D21: =VLOOKUP(C21,'Liste chauffeur'!$B$5:$L$18,2,TRUE)&" "&VLOOKUP(C21,'Liste chauffeur'!$B$5:$L$18,3,TRUE) -> MOURIDI Aktoir | F21: =COUNTBLANK(E21) -> 1 | L21: =K21-E21 -> 0 | P21: =O21-K21 -> 0 | T21: =S21-O21 -> 0 | V21: =IF(H21-I21+J21-M21+N21-Q21+R21=U21,"OK",H21-I21+J21-M21+N21-Q21+R21-U21) -> OK | Y21: =IF(F21=1,"",W21-E21) | Z21: =H21+J21-I21 -> 0 | AA21: =IF(F21=1,0,AA$6) -> 0 | AB21: =IF(AA21=0,0,Z21/AA21) -> 0
A22: ='Horaire samedi'!A22 -> PASSOT LA BARGE | B22: ='Horaire samedi'!B22 -> 0.35416667 | C22: ='Horaire samedi'!C22 -> D12 | D22: =VLOOKUP(C22,'Liste chauffeur'!$B$5:$L$18,2,TRUE)&" "&VLOOKUP(C22,'Liste chauffeur'!$B$5:$L$18,3,TRUE) -> VELOU M'COLO M'Berou | F22: =COUNTBLANK(E22) -> 1 | L22: =K22-E22 -> 0 | P22: =O22-K22 -> 0 | T22: =S22-O22 -> 0 | V22: =IF(H22-I22+J22-M22+N22-Q22+R22=U22,"OK",H22-I22+J22-M22+N22-Q22+R22-U22) -> OK | Y22: =IF(F22=1,"",W22-E22) | Z22: =H22+J22-I22 -> 0 | AA22: =IF(F22=1,0,AA$6) -> 0 | AB22: =IF(AA22=0,0,Z22/AA22) -> 0
A23: ='Horaire samedi'!A23 -> DOUJANI | B23: ='Horaire samedi'!B23 -> 0.36111111 | C23: ='Horaire samedi'!C23 -> D5 | D23: =VLOOKUP(C23,'Liste chauffeur'!$B$5:$L$18,2,TRUE)&" "&VLOOKUP(C23,'Liste chauffeur'!$B$5:$L$18,3,TRUE) -> AMINA Selemani | F23: =COUNTBLANK(E23) -> 1 | L23: =K23-E23 -> 0 | P23: =O23-K23 -> 0 | T23: =S23-O23 -> 0 | V23: =IF(H23-I23+J23-M23+N23-Q23+R23=U23,"OK",H23-I23+J23-M23+N23-Q23+R23-U23) -> OK | Y23: =IF(F23=1,"",W23-E23) | Z23: =H23+J23-I23 -> 0 | AA23: =IF(F23=1,0,AA$6) -> 0 | AB23: =IF(AA23=0,0,Z23/AA23) -> 0
A24: ='Horaire samedi'!A24 -> PASSOT LA BARGE | B24: ='Horaire samedi'!B24 -> 0.36805556 | C24: ='Horaire samedi'!C24 -> D13 | D24: =VLOOKUP(C24,'Liste chauffeur'!$B$5:$L$18,2,TRUE)&" "&VLOOKUP(C24,'Liste chauffeur'!$B$5:$L$18,3,TRUE) -> MOURIDI Aktoir | F24: =COUNTBLANK(E24) -> 1 | L24: =K24-E24 -> 0 | P24: =O24-K24 -> 0 | T24: =S24-O24 -> 0 | V24: =IF(H24-I24+J24-M24+N24-Q24+R24=U24,"OK",H24-I24+J24-M24+N24-Q24+R24-U24) -> OK | Y24: =IF(F24=1,"",W24-E24) | Z24: =H24+J24-I24 -> 0 | AA24: =IF(F24=1,0,AA$6) -> 0 | AB24: =IF(AA24=0,0,Z24/AA24) -> 0
A25: ='Horaire samedi'!A25 -> DOUJANI | B25: ='Horaire samedi'!B25 -> 0.375 | C25: ='Horaire samedi'!C25 -> D12 | D25: =VLOOKUP(C25,'Liste chauffeur'!$B$5:$L$18,2,TRUE)&" "&VLOOKUP(C25,'Liste chauffeur'!$B$5:$L$18,3,TRUE) -> VELOU M'COLO M'Berou | F25: =COUNTBLANK(E25) -> 1 | Z25: =H25+J25-I25 -> 0 | AA25: =IF(F25=1,0,AA$6) -> 0 | AB25: =IF(AA25=0,0,Z25/AA25) -> 0
A26: ='Horaire samedi'!A26 -> PASSOT LA BARGE | B26: ='Horaire samedi'!B26 -> 0.38194444 | C26: ='Horaire samedi'!C26 -> D5 | D26: =VLOOKUP(C26,'Liste chauffeur'!$B$5:$L$18,2,TRUE)&" "&VLOOKUP(C26,'Liste chauffeur'!$B$5:$L$18,3,TRUE) -> AMINA Selemani | F26: =COUNTBLANK(E26) -> 1 | L26: =K26-E26 -> 0 | P26: =O26-K26 -> 0 | T26: =S26-O26 -> 0 | V26: =IF(H26-I26+J26-M26+N26-Q26+R26=U26,"OK",H26-I26+J26-M26+N26-Q26+R26-U26) -> OK | Y26: =IF(F26=1,"",W26-E26) | Z26: =H26+J26-I26 -> 0 | AA26: =IF(F26=1,0,AA$6) -> 0 | AB26: =IF(AA26=0,0,Z26/AA26) -> 0
A27: ='Horaire samedi'!A27 -> DOUJANI | B27: ='Horaire samedi'!B27 -> 0.38888889 | C27: ='Horaire samedi'!C27 -> D13 | D27: =VLOOKUP(C27,'Liste chauffeur'!$B$5:$L$18,2,TRUE)&" "&VLOOKUP(C27,'Liste chauffeur'!$B$5:$L$18,3,TRUE) -> MOURIDI Aktoir | F27: =COUNTBLANK(E27) -> 1 | L27: =K27-E27 -> 0 | P27: =O27-K27 -> 0 | T27: =S27-O27 -> 0 | V27: =IF(H27-I27+J27-M27+N27-Q27+R27=U27,"OK",H27-I27+J27-M27+N27-Q27+R27-U27) -> OK | Y27: =IF(F27=1,"",W27-E27) | Z27: =H27+J27-I27 -> 0 | AA27: =IF(F27=1,0,AA$6) -> 0 | AB27: =IF(AA27=0,0,Z27/AA27) -> 0
A28: ='Horaire samedi'!A28 -> PASSOT LA BARGE | B28: ='Horaire samedi'!B28 -> 0.39583333 | C28: ='Horaire samedi'!C28 -> D12 | D28: =VLOOKUP(C28,'Liste chauffeur'!$B$5:$L$18,2,TRUE)&" "&VLOOKUP(C28,'Liste chauffeur'!$B$5:$L$18,3,TRUE) -> VELOU M'COLO M'Berou | F28: =COUNTBLANK(E28) -> 1 | L28: =K28-E28 -> 0 | P28: =O28-K28 -> 0 | T28: =S28-O28 -> 0 | V28: =IF(H28-I28+J28-M28+N28-Q28+R28=U28,"OK",H28-I28+J28-M28+N28-Q28+R28-U28) -> OK | Y28: =IF(F28=1,"",W28-E28) | Z28: =H28+J28-I28 -> 0 | AA28: =IF(F28=1,0,AA$6) -> 0 | AB28: =IF(AA28=0,0,Z28/AA28) -> 0
A29: ='Horaire samedi'!A29 -> DOUJANI | B29: ='Horaire samedi'!B29 -> 0.40277778 | C29: ='Horaire samedi'!C29 -> D5 | D29: =VLOOKUP(C29,'Liste chauffeur'!$B$5:$L$18,2,TRUE)&" "&VLOOKUP(C29,'Liste chauffeur'!$B$5:$L$18,3,TRUE) -> AMINA Selemani | F29: =COUNTBLANK(E29) -> 1 | L29: =K29-E29 -> 0 | P29: =O29-K29 -> 0 | T29: =S29-O29 -> 0 | V29: =IF(H29-I29+J29-M29+N29-Q29+R29=U29,"OK",H29-I29+J29-M29+N29-Q29+R29-U29) -> OK | Y29: =IF(F29=1,"",W29-E29) | Z29: =H29+J29-I29 -> 0 | AA29: =IF(F29=1,0,AA$6) -> 0 | AB29: =IF(AA29=0,0,Z29/AA29) -> 0
A30: ='Horaire samedi'!A30 -> PASSOT LA BARGE | B30: ='Horaire samedi'!B30 -> 0.40972222 | C30: ='Horaire samedi'!C30 -> D13 | D30: =VLOOKUP(C30,'Liste chauffeur'!$B$5:$L$18,2,TRUE)&" "&VLOOKUP(C30,'Liste chauffeur'!$B$5:$L$18,3,TRUE) -> MOURIDI Aktoir | F30: =COUNTBLANK(E30) -> 1 | L30: =K30-E30 -> 0 | P30: =O30-K30 -> 0 | T30: =S30-O30 -> 0 | V30: =IF(H30-I30+J30-M30+N30-Q30+R30=U30,"OK",H30-I30+J30-M30+N30-Q30+R30-U30) -> OK | Y30: =IF(F30=1,"",W30-E30) | Z30: =H30+J30-I30 -> 0 | AA30: =IF(F30=1,0,AA$6) -> 0 | AB30: =IF(AA30=0,0,Z30/AA30) -> 0
A31: ='Horaire samedi'!A31 -> DOUJANI | B31: ='Horaire samedi'!B31 -> 0.41666667 | C31: ='Horaire samedi'!C31 -> D12 | D31: =VLOOKUP(C31,'Liste chauffeur'!$B$5:$L$18,2,TRUE)&" "&VLOOKUP(C31,'Liste chauffeur'!$B$5:$L$18,3,TRUE) -> VELOU M'COLO M'Berou | F31: =COUNTBLANK(E31) -> 1 | L31: =K31-E31 -> 0 | P31: =O31-K31 -> 0 | T31: =S31-O31 -> 0 | V31: =IF(H31-I31+J31-M31+N31-Q31+R31=U31,"OK",H31-I31+J31-M31+N31-Q31+R31-U31) -> OK | Y31: =IF(F31=1,"",W31-E31) | Z31: =H31+J31-I31 -> 0 | AA31: =IF(F31=1,0,AA$6) -> 0 | AB31: =IF(AA31=0,0,Z31/AA31) -> 0
A32: ='Horaire samedi'!A32 -> PASSOT LA BARGE | B32: ='Horaire samedi'!B32 -> 0.42361111 | C32: ='Horaire samedi'!C32 -> D5 | D32: =VLOOKUP(C32,'Liste chauffeur'!$B$5:$L$18,2,TRUE)&" "&VLOOKUP(C32,'Liste chauffeur'!$B$5:$L$18,3,TRUE) -> AMINA Selemani | F32: =COUNTBLANK(E32) -> 1 | Z32: =H32+J32-I32 -> 0 | AA32: =IF(F32=1,0,AA$6) -> 0 | AB32: =IF(AA32=0,0,Z32/AA32) -> 0
A33: ='Horaire samedi'!A33 -> DOUJANI | B33: ='Horaire samedi'!B33 -> 0.43055556 | C33: ='Horaire samedi'!C33 -> D13 | D33: =VLOOKUP(C33,'Liste chauffeur'!$B$5:$L$18,2,TRUE)&" "&VLOOKUP(C33,'Liste chauffeur'!$B$5:$L$18,3,TRUE) -> MOURIDI Aktoir | F33: =COUNTBLANK(E33) -> 1 | L33: =K33-E33 -> 0 | P33: =O33-K33 -> 0 | T33: =S33-O33 -> 0 | V33: =IF(H33-I33+J33-M33+N33-Q33+R33=U33,"OK",H33-I33+J33-M33+N33-Q33+R33-U33) -> OK | Y33: =IF(F33=1,"",W33-E33) | Z33: =H33+J33-I33 -> 0 | AA33: =IF(F33=1,0,AA$6) -> 0 | AB33: =IF(AA33=0,0,Z33/AA33) -> 0
A34: ='Horaire samedi'!A34 -> PASSOT LA BARGE | B34: ='Horaire samedi'!B34 -> 0.4375 | C34: ='Horaire samedi'!C34 -> D12 | D34: =VLOOKUP(C34,'Liste chauffeur'!$B$5:$L$18,2,TRUE)&" "&VLOOKUP(C34,'Liste chauffeur'!$B$5:$L$18,3,TRUE) -> VELOU M'COLO M'Berou | F34: =COUNTBLANK(E34) -> 1 | L34: =K34-E34 -> 0 | V34: =IF(H34-I34+J34-M34+N34-Q34+R34=U34,"OK",H34-I34+J34-M34+N34-Q34+R34-U34) -> OK | Y34: =IF(F34=1,"",W34-E34) | Z34: =H34+J34-I34 -> 0 | AA34: =IF(F34=1,0,AA$6) -> 0 | AB34: =IF(AA34=0,0,Z34/AA34) -> 0
A35: ='Horaire samedi'!A35 -> DOUJANI | B35: ='Horaire samedi'!B35 -> 0.44444444 | C35: ='Horaire samedi'!C35 -> D5 | D35: =VLOOKUP(C35,'Liste chauffeur'!$B$5:$L$18,2,TRUE)&" "&VLOOKUP(C35,'Liste chauffeur'!$B$5:$L$18,3,TRUE) -> AMINA Selemani | F35: =COUNTBLANK(E35) -> 1 | L35: =K35-E35 -> 0 | V35: =IF(H35-I35+J35-M35+N35-Q35+R35=U35,"OK",H35-I35+J35-M35+N35-Q35+R35-U35) -> OK | Y35: =IF(F35=1,"",W35-E35) | Z35: =H35+J35-I35 -> 0 | AA35: =IF(F35=1,0,AA$6) -> 0 | AB35: =IF(AA35=0,0,Z35/AA35) -> 0
A36: ='Horaire samedi'!A36 -> PASSOT LA BARGE | B36: ='Horaire samedi'!B36 -> 0.45138889 | C36: ='Horaire samedi'!C36 -> D13 | D36: =VLOOKUP(C36,'Liste chauffeur'!$B$5:$L$18,2,TRUE)&" "&VLOOKUP(C36,'Liste chauffeur'!$B$5:$L$18,3,TRUE) -> MOURIDI Aktoir | F36: =COUNTBLANK(E36) -> 1 | L36: =K36-E36 -> 0 | V36: =IF(H36-I36+J36-M36+N36-Q36+R36=U36,"OK",H36-I36+J36-M36+N36-Q36+R36-U36) -> OK | Y36: =IF(F36=1,"",W36-E36) | Z36: =H36+J36-I36 -> 0 | AA36: =IF(F36=1,0,AA$6) -> 0 | AB36: =IF(AA36=0,0,Z36/AA36) -> 0
A37: ='Horaire samedi'!A37 -> DOUJANI | B37: ='Horaire samedi'!B37 -> 0.45833333 | C37: ='Horaire samedi'!C37 -> D12 | D37: =VLOOKUP(C37,'Liste chauffeur'!$B$5:$L$18,2,TRUE)&" "&VLOOKUP(C37,'Liste chauffeur'!$B$5:$L$18,3,TRUE) -> VELOU M'COLO M'Berou | F37: =COUNTBLANK(E37) -> 1 | L37: =K37-E37 -> 0 | V37: =IF(H37-I37+J37-M37+N37-Q37+R37=U37,"OK",H37-I37+J37-M37+N37-Q37+R37-U37) -> OK | Y37: =IF(F37=1,"",W37-E37) | Z37: =H37+J37-I37 -> 0 | AA37: =IF(F37=1,0,AA$6) -> 0 | AB37: =IF(AA37=0,0,Z37/AA37) -> 0
A38: ='Horaire samedi'!A38 -> PASSOT LA BARGE | B38: ='Horaire samedi'!B38 -> 0.46527778 | C38: ='Horaire samedi'!C38 -> D5 | D38: =VLOOKUP(C38,'Liste chauffeur'!$B$5:$L$18,2,TRUE)&" "&VLOOKUP(C38,'Liste chauffeur'!$B$5:$L$18,3,TRUE) -> AMINA Selemani | F38: =COUNTBLANK(E38) -> 1 | L38: =K38-E38 -> 0 | V38: =IF(H38-I38+J38-M38+N38-Q38+R38=U38,"OK",H38-I38+J38-M38+N38-Q38+R38-U38) -> OK | Y38: =IF(F38=1,"",W38-E38) | Z38: =H38+J38-I38 -> 0 | AA38: =IF(F38=1,0,AA$6) -> 0 | AB38: =IF(AA38=0,0,Z38/AA38) -> 0
A39: ='Horaire samedi'!A39 -> DOUJANI | B39: ='Horaire samedi'!B39 -> 0.47222222 | C39: ='Horaire samedi'!C39 -> D13 | D39: =VLOOKUP(C39,'Liste chauffeur'!$B$5:$L$18,2,TRUE)&" "&VLOOKUP(C39,'Liste chauffeur'!$B$5:$L$18,3,TRUE) -> MOURIDI Aktoir | F39: =COUNTBLANK(E39) -> 1 | L39: =K39-E39 -> 0 | V39: =IF(H39-I39+J39-M39+N39-Q39+R39=U39,"OK",H39-I39+J39-M39+N39-Q39+R39-U39) -> OK | Y39: =IF(F39=1,"",W39-E39) | Z39: =H39+J39-I39 -> 0 | AA39: =IF(F39=1,0,AA$6) -> 0 | AB39: =IF(AA39=0,0,Z39/AA39) -> 0
A40: ='Horaire samedi'!A40 -> PASSOT LA BARGE | B40: ='Horaire samedi'!B40 -> 0.47916667 | C40: ='Horaire samedi'!C40 -> D12 | D40: =VLOOKUP(C40,'Liste chauffeur'!$B$5:$L$18,2,TRUE)&" "&VLOOKUP(C40,'Liste chauffeur'!$B$5:$L$18,3,TRUE) -> VELOU M'COLO M'Berou | F40: =COUNTBLANK(E40) -> 1 | L40: =K40-E40 -> 0 | V40: =IF(H40-I40+J40-M40+N40-Q40+R40=U40,"OK",H40-I40+J40-M40+N40-Q40+R40-U40) -> OK | Y40: =IF(F40=1,"",W40-E40) | Z40: =H40+J40-I40 -> 0 | AA40: =IF(F40=1,0,AA$6) -> 0 | AB40: =IF(AA40=0,0,Z40/AA40) -> 0
A41: ='Horaire samedi'!A41 -> DOUJANI | B41: ='Horaire samedi'!B41 -> 0.48611111 | C41: ='Horaire samedi'!C41 -> D5 | D41: =VLOOKUP(C41,'Liste chauffeur'!$B$5:$L$18,2,TRUE)&" "&VLOOKUP(C41,'Liste chauffeur'!$B$5:$L$18,3,TRUE) -> AMINA Selemani | F41: =COUNTBLANK(E41) -> 1 | L41: =K41-E41 -> 0 | V41: =IF(H41-I41+J41-M41+N41-Q41+R41=U41,"OK",H41-I41+J41-M41+N41-Q41+R41-U41) -> OK | Y41: =IF(F41=1,"",W41-E41) | Z41: =H41+J41-I41 -> 0 | AA41: =IF(F41=1,0,AA$6) -> 0 | AB41: =IF(AA41=0,0,Z41/AA41) -> 0
A42: ='Horaire samedi'!A42 -> PASSOT LA BARGE | B42: ='Horaire samedi'!B42 -> 0.49305556 | C42: ='Horaire samedi'!C42 -> D13 | D42: =VLOOKUP(C42,'Liste chauffeur'!$B$5:$L$18,2,TRUE)&" "&VLOOKUP(C42,'Liste chauffeur'!$B$5:$L$18,3,TRUE) -> MOURIDI Aktoir | F42: =COUNTBLANK(E42) -> 1 | L42: =K42-E42 -> 0 | V42: =IF(H42-I42+J42-M42+N42-Q42+R42=U42,"OK",H42-I42+J42-M42+N42-Q42+R42-U42) -> OK | Y42: =IF(F42=1,"",W42-E42) | Z42: =H42+J42-I42 -> 0 | AA42: =IF(F42=1,0,AA$6) -> 0 | AB42: =IF(AA42=0,0,Z42/AA42) -> 0
A43: ='Horaire samedi'!A43 -> DOUJANI | B43: ='Horaire samedi'!B43 -> 0.5 | C43: ='Horaire samedi'!C43 -> D12 | D43: =VLOOKUP(C43,'Liste chauffeur'!$B$5:$L$18,2,TRUE)&" "&VLOOKUP(C43,'Liste chauffeur'!$B$5:$L$18,3,TRUE) -> VELOU M'COLO M'Berou | F43: =COUNTBLANK(E43) -> 1 | L43: =K43-E43 -> 0 | V43: =IF(H43-I43+J43-M43+N43-Q43+R43=U43,"OK",H43-I43+J43-M43+N43-Q43+R43-U43) -> OK | Y43: =IF(F43=1,"",W43-E43) | Z43: =H43+J43-I43 -> 0 | AA43: =IF(F43=1,0,AA$6) -> 0 | AB43: =IF(AA43=0,0,Z43/AA43) -> 0
B44: ST1 | F44: =SUM(F8:F43) -> 36 | G44: =SUM(G8:G43) -> 0 | Y44: =AVERAGE(Y8:Y43) -> #DIV/0! | Z44: =SUM(Z8:Z43) -> 0 | AA44: =SUM(AA8:AA43) -> 0 | AB44: =IF(AA44=0,0,Z44/AA44) -> 0 | AC44: =SUM(#REF!) -> #REF! | AD44: =AB44/AC44 -> #REF!
A45: ='Horaire samedi'!A44 -> PASSOT LA BARGE | B45: ='Horaire samedi'!B44 -> 0.50694444 | C45: ='Horaire samedi'!C44 -> D5 | D45: =VLOOKUP(C45,'Liste chauffeur'!$B$5:$L$18,2,TRUE)&" "&VLOOKUP(C45,'Liste chauffeur'!$B$5:$L$18,3,TRUE) -> AMINA Selemani | F45: =COUNTBLANK(E45) -> 1 | L45: =K45-E45 -> 0 | V45: =IF(H45-I45+J45-M45+N45-Q45+R45=U45,"OK",H45-I45+J45-M45+N45-Q45+R45-U45) -> OK | Y45: =IF(F45=1,"",W45-E45) | Z45: =H45+J45-I45 -> 0 | AA45: =IF(F45=1,0,AA$6) -> 0 | AB45: =IF(AA45=0,0,Z45/AA45) -> 0
A46: ='Horaire samedi'!A45 -> DOUJANI | B46: ='Horaire samedi'!B45 -> 0.51388889 | C46: ='Horaire samedi'!C45 -> D13 | D46: =VLOOKUP(C46,'Liste chauffeur'!$B$5:$L$18,2,TRUE)&" "&VLOOKUP(C46,'Liste chauffeur'!$B$5:$L$18,3,TRUE) -> MOURIDI Aktoir | F46: =COUNTBLANK(E46) -> 1 | L46: =K46-E46 -> 0 | V46: =IF(H46-I46+J46-M46+N46-Q46+R46=U46,"OK",H46-I46+J46-M46+N46-Q46+R46-U46) -> OK | Y46: =IF(F46=1,"",W46-E46) | Z46: =H46+J46-I46 -> 0 | AA46: =IF(F46=1,0,AA$6) -> 0 | AB46: =IF(AA46=0,0,Z46/AA46) -> 0
A47: ='Horaire samedi'!A46 -> PASSOT LA BARGE | B47: ='Horaire samedi'!B46 -> 0.52083333 | C47: ='Horaire samedi'!C46 -> D12 | D47: =VLOOKUP(C47,'Liste chauffeur'!$B$5:$L$18,2,TRUE)&" "&VLOOKUP(C47,'Liste chauffeur'!$B$5:$L$18,3,TRUE) -> VELOU M'COLO M'Berou | F47: =COUNTBLANK(E47) -> 1 | L47: =K47-E47 -> 0 | V47: =IF(H47-I47+J47-M47+N47-Q47+R47=U47,"OK",H47-I47+J47-M47+N47-Q47+R47-U47) -> OK | Y47: =IF(F47=1,"",W47-E47) | Z47: =H47+J47-I47 -> 0 | AA47: =IF(F47=1,0,AA$6) -> 0 | AB47: =IF(AA47=0,0,Z47/AA47) -> 0
A48: ='Horaire samedi'!A47 -> DOUJANI | B48: ='Horaire samedi'!B47 -> 0.52777778 | C48: ='Horaire samedi'!C47 -> D5 | D48: =VLOOKUP(C48,'Liste chauffeur'!$B$5:$L$18,2,TRUE)&" "&VLOOKUP(C48,'Liste chauffeur'!$B$5:$L$18,3,TRUE) -> AMINA Selemani | F48: =COUNTBLANK(E48) -> 1 | L48: =K48-E48 -> 0 | Y48: =IF(F48=1,"",W48-E48) | Z48: =H48+J48-I48 -> 0 | AA48: =IF(F48=1,0,AA$6) -> 0 | AB48: =IF(AA48=0,0,Z48/AA48) -> 0
A49: ='Horaire samedi'!A48 -> PASSOT LA BARGE | B49: ='Horaire samedi'!B48 -> 0.53472222 | C49: ='Horaire samedi'!C48 -> D13 | D49: =VLOOKUP(C49,'Liste chauffeur'!$B$5:$L$18,2,TRUE)&" "&VLOOKUP(C49,'Liste chauffeur'!$B$5:$L$18,3,TRUE) -> MOURIDI Aktoir | F49: =COUNTBLANK(E49) -> 1 | Y49: =IF(F49=1,"",W49-E49) | Z49: =H49+J49-I49 -> 0 | AA49: =IF(F49=1,0,AA$6) -> 0 | AB49: =IF(AA49=0,0,Z49/AA49) -> 0
A50: ='Horaire samedi'!A49 -> DOUJANI | B50: ='Horaire samedi'!B49 -> 0.54166667 | C50: ='Horaire samedi'!C49 -> D12 | D50: =VLOOKUP(C50,'Liste chauffeur'!$B$5:$L$18,2,TRUE)&" "&VLOOKUP(C50,'Liste chauffeur'!$B$5:$L$18,3,TRUE) -> VELOU M'COLO M'Berou | F50: =COUNTBLANK(E50) -> 1 | Y50: =IF(F50=1,"",W50-E50) | Z50: =H50+J50-I50 -> 0 | AA50: =IF(F50=1,0,AA$6) -> 0 | AB50: =IF(AA50=0,0,Z50/AA50) -> 0
A51: ='Horaire samedi'!A50 -> PASSOT LA BARGE | B51: ='Horaire samedi'!B50 -> 0.54861111 | C51: ='Horaire samedi'!C50 -> D5 | D51: =VLOOKUP(C51,'Liste chauffeur'!$B$5:$L$18,2,TRUE)&" "&VLOOKUP(C51,'Liste chauffeur'!$B$5:$L$18,3,TRUE) -> AMINA Selemani | F51: =COUNTBLANK(E51) -> 1 | Y51: =IF(F51=1,"",W51-E51) | Z51: =H51+J51-I51 -> 0 | AA51: =IF(F51=1,0,AA$6) -> 0 | AB51: =IF(AA51=0,0,Z51/AA51) -> 0
A52: ='Horaire samedi'!A51 -> DOUJANI | B52: ='Horaire samedi'!B51 -> 0.55555556 | C52: ='Horaire samedi'!C51 -> D13 | D52: =VLOOKUP(C52,'Liste chauffeur'!$B$5:$L$18,2,TRUE)&" "&VLOOKUP(C52,'Liste chauffeur'!$B$5:$L$18,3,TRUE) -> MOURIDI Aktoir | F52: =COUNTBLANK(E52) -> 1 | Y52: =IF(F52=1,"",W52-E52) | Z52: =H52+J52-I52 -> 0 | AA52: =IF(F52=1,0,AA$6) -> 0 | AB52: =IF(AA52=0,0,Z52/AA52) -> 0
A53: ='Horaire samedi'!A52 -> PASSOT LA BARGE | B53: ='Horaire samedi'!B52 -> 0.5625 | C53: ='Horaire samedi'!C52 -> D12 | D53: =VLOOKUP(C53,'Liste chauffeur'!$B$5:$L$18,2,TRUE)&" "&VLOOKUP(C53,'Liste chauffeur'!$B$5:$L$18,3,TRUE) -> VELOU M'COLO M'Berou | F53: =COUNTBLANK(E53) -> 1 | Y53: =IF(F53=1,"",W53-E53) | Z53: =H53+J53-I53 -> 0 | AA53: =IF(F53=1,0,AA$6) -> 0 | AB53: =IF(AA53=0,0,Z53/AA53) -> 0
A54: ='Horaire samedi'!A53 -> DOUJANI | B54: ='Horaire samedi'!B53 -> 0.56944444 | C54: ='Horaire samedi'!C53 -> D5 | D54: =VLOOKUP(C54,'Liste chauffeur'!$B$5:$L$18,2,TRUE)&" "&VLOOKUP(C54,'Liste chauffeur'!$B$5:$L$18,3,TRUE) -> AMINA Selemani | F54: =COUNTBLANK(E54) -> 1 | Y54: =IF(F54=1,"",W54-E54) | Z54: =H54+J54-I54 -> 0 | AA54: =IF(F54=1,0,AA$6) -> 0 | AB54: =IF(AA54=0,0,Z54/AA54) -> 0
A55: ='Horaire samedi'!A54 -> PASSOT LA BARGE | B55: ='Horaire samedi'!B54 -> 0.57638889 | C55: ='Horaire samedi'!C54 -> D13 | D55: =VLOOKUP(C55,'Liste chauffeur'!$B$5:$L$18,2,TRUE)&" "&VLOOKUP(C55,'Liste chauffeur'!$B$5:$L$18,3,TRUE) -> MOURIDI Aktoir | F55: =COUNTBLANK(E55) -> 1 | Y55: =IF(F55=1,"",W55-E55) | Z55: =H55+J55-I55 -> 0 | AA55: =IF(F55=1,0,AA$6) -> 0 | AB55: =IF(AA55=0,0,Z55/AA55) -> 0
A56: ='Horaire samedi'!A55 -> DOUJANI | B56: ='Horaire samedi'!B55 -> 0.58333333 | C56: ='Horaire samedi'!C55 -> D9 | D56: =VLOOKUP(C56,'Liste chauffeur'!$B$5:$L$19,2,TRUE)&" "&VLOOKUP(C56,'Liste chauffeur'!$B$5:$L$19,3,TRUE) -> RENEE Assanati | F56: =COUNTBLANK(E56) -> 1 | Y56: =IF(F56=1,"",W56-E56) | Z56: =H56+J56-I56 -> 0 | AA56: =IF(F56=1,0,AA$6) -> 0 | AB56: =IF(AA56=0,0,Z56/AA56) -> 0
A57: ='Horaire samedi'!A56 -> PASSOT LA BARGE | B57: ='Horaire samedi'!B56 -> 0.59027778 | C57: ='Horaire samedi'!C56 -> D5 | D57: =VLOOKUP(C57,'Liste chauffeur'!$B$5:$L$18,2,TRUE)&" "&VLOOKUP(C57,'Liste chauffeur'!$B$5:$L$18,3,TRUE) -> AMINA Selemani | F57: =COUNTBLANK(E57) -> 1 | Z57: =H57+J57-I57 -> 0 | AA57: =IF(F57=1,0,AA$6) -> 0 | AB57: =IF(AA57=0,0,Z57/AA57) -> 0
A58: ='Horaire samedi'!A57 -> DOUJANI | B58: ='Horaire samedi'!B57 -> 0.59722222 | C58: ='Horaire samedi'!C57 -> C15 | D58: =VLOOKUP(C58,'Liste chauffeur'!$B$5:$L$20,2,FALSE)&" "&VLOOKUP(C58,'Liste chauffeur'!$B$5:$L$20,3,FALSE) -> HAMADA Babou | F58: =COUNTBLANK(E58) -> 1 | Z58: =H58+J58-I58 -> 0 | AA58: =IF(F58=1,0,AA$6) -> 0 | AB58: =IF(AA58=0,0,Z58/AA58) -> 0
A59: ='Horaire samedi'!A58 -> PASSOT LA BARGE | B59: ='Horaire samedi'!B58 -> 0.60416667 | C59: ='Horaire samedi'!C58 -> D9 | D59: =VLOOKUP(C59,'Liste chauffeur'!$B$5:$L$19,2,TRUE)&" "&VLOOKUP(C59,'Liste chauffeur'!$B$5:$L$19,3,TRUE) -> RENEE Assanati | F59: =COUNTBLANK(E59) -> 1 | Z59: =H59+J59-I59 -> 0 | AA59: =IF(F59=1,0,AA$6) -> 0 | AB59: =IF(AA59=0,0,Z59/AA59) -> 0
A60: ='Horaire samedi'!A59 -> DOUJANI | B60: ='Horaire samedi'!B59 -> 0.61111111 | C60: ='Horaire samedi'!C59 -> D15 | D60: =VLOOKUP(C60,'Liste chauffeur'!$B$5:$L$18,2,TRUE)&" "&VLOOKUP(C60,'Liste chauffeur'!$B$5:$L$18,3,TRUE) -> KAMARDINE Mansour | F60: =COUNTBLANK(E60) -> 1 | Z60: =H60+J60-I60 -> 0 | AA60: =IF(F60=1,0,AA$6) -> 0 | AB60: =IF(AA60=0,0,Z60/AA60) -> 0
A61: ='Horaire samedi'!A60 -> PASSOT LA BARGE | B61: ='Horaire samedi'!B60 -> 0.61805556 | C61: ='Horaire samedi'!C60 -> C15 | D61: =VLOOKUP(C61,'Liste chauffeur'!$B$5:$L$20,2,FALSE)&" "&VLOOKUP(C61,'Liste chauffeur'!$B$5:$L$20,3,FALSE) -> HAMADA Babou | F61: =COUNTBLANK(E61) -> 1 | Z61: =H61+J61-I61 -> 0 | AA61: =IF(F61=1,0,AA$6) -> 0 | AB61: =IF(AA61=0,0,Z61/AA61) -> 0
A62: ='Horaire samedi'!A61 -> DOUJANI | B62: ='Horaire samedi'!B61 -> 0.625 | C62: ='Horaire samedi'!C61 -> D9 | D62: =VLOOKUP(C62,'Liste chauffeur'!$B$5:$L$19,2,TRUE)&" "&VLOOKUP(C62,'Liste chauffeur'!$B$5:$L$19,3,TRUE) -> RENEE Assanati | F62: =COUNTBLANK(E62) -> 1 | Z62: =H62+J62-I62 -> 0 | AA62: =IF(F62=1,0,AA$6) -> 0 | AB62: =IF(AA62=0,0,Z62/AA62) -> 0
A63: ='Horaire samedi'!A62 -> PASSOT LA BARGE | B63: ='Horaire samedi'!B62 -> 0.63194444 | C63: ='Horaire samedi'!C62 -> D15 | D63: =VLOOKUP(C63,'Liste chauffeur'!$B$5:$L$18,2,TRUE)&" "&VLOOKUP(C63,'Liste chauffeur'!$B$5:$L$18,3,TRUE) -> KAMARDINE Mansour | F63: =COUNTBLANK(E63) -> 1 | Z63: =H63+J63-I63 -> 0 | AA63: =IF(F63=1,0,AA$6) -> 0 | AB63: =IF(AA63=0,0,Z63/AA63) -> 0
A64: ='Horaire samedi'!A63 -> DOUJANI | B64: ='Horaire samedi'!B63 -> 0.63888889 | C64: ='Horaire samedi'!C63 -> C15 | D64: =VLOOKUP(C64,'Liste chauffeur'!$B$5:$L$20,2,FALSE)&" "&VLOOKUP(C64,'Liste chauffeur'!$B$5:$L$20,3,FALSE) -> HAMADA Babou | F64: =COUNTBLANK(E64) -> 1 | Z64: =H64+J64-I64 -> 0 | AA64: =IF(F64=1,0,AA$6) -> 0 | AB64: =IF(AA64=0,0,Z64/AA64) -> 0
A65: ='Horaire samedi'!A64 -> PASSOT LA BARGE | B65: ='Horaire samedi'!B64 -> 0.64583333 | C65: ='Horaire samedi'!C64 -> D9 | D65: =VLOOKUP(C65,'Liste chauffeur'!$B$5:$L$19,2,TRUE)&" "&VLOOKUP(C65,'Liste chauffeur'!$B$5:$L$19,3,TRUE) -> RENEE Assanati | F65: =COUNTBLANK(E65) -> 1 | Z65: =H65+J65-I65 -> 0 | AA65: =IF(F65=1,0,AA$6) -> 0 | AB65: =IF(AA65=0,0,Z65/AA65) -> 0
A66: ='Horaire samedi'!A65 -> DOUJANI | B66: ='Horaire samedi'!B65 -> 0.65277778 | C66: ='Horaire samedi'!C65 -> D15 | D66: =VLOOKUP(C66,'Liste chauffeur'!$B$5:$L$18,2,TRUE)&" "&VLOOKUP(C66,'Liste chauffeur'!$B$5:$L$18,3,TRUE) -> KAMARDINE Mansour | F66: =COUNTBLANK(E66) -> 1 | Z66: =H66+J66-I66 -> 0 | AA66: =IF(F66=1,0,AA$6) -> 0 | AB66: =IF(AA66=0,0,Z66/AA66) -> 0
A67: ='Horaire samedi'!A66 -> PASSOT LA BARGE | B67: ='Horaire samedi'!B66 -> 0.65972222 | C67: ='Horaire samedi'!C66 -> C15 | D67: =VLOOKUP(C67,'Liste chauffeur'!$B$5:$L$20,2,FALSE)&" "&VLOOKUP(C67,'Liste chauffeur'!$B$5:$L$20,3,FALSE) -> HAMADA Babou | F67: =COUNTBLANK(E67) -> 1 | Z67: =H67+J67-I67 -> 0 | AA67: =IF(F67=1,0,AA$6) -> 0 | AB67: =IF(AA67=0,0,Z67/AA67) -> 0
A68: ='Horaire samedi'!A67 -> DOUJANI | B68: ='Horaire samedi'!B67 -> 0.66666667 | C68: ='Horaire samedi'!C67 -> D9 | D68: =VLOOKUP(C68,'Liste chauffeur'!$B$5:$L$19,2,TRUE)&" "&VLOOKUP(C68,'Liste chauffeur'!$B$5:$L$19,3,TRUE) -> RENEE Assanati | F68: =COUNTBLANK(E68) -> 1 | Z68: =H68+J68-I68 -> 0 | AA68: =IF(F68=1,0,AA$6) -> 0 | AB68: =IF(AA68=0,0,Z68/AA68) -> 0
A69: ='Horaire samedi'!A68 -> PASSOT LA BARGE | B69: ='Horaire samedi'!B68 -> 0.67361111 | C69: ='Horaire samedi'!C68 -> D15 | D69: =VLOOKUP(C69,'Liste chauffeur'!$B$5:$L$18,2,TRUE)&" "&VLOOKUP(C69,'Liste chauffeur'!$B$5:$L$18,3,TRUE) -> KAMARDINE Mansour | F69: =COUNTBLANK(E69) -> 1 | Z69: =H69+J69-I69 -> 0 | AA69: =IF(F69=1,0,AA$6) -> 0 | AB69: =IF(AA69=0,0,Z69/AA69) -> 0
A70: ='Horaire samedi'!A69 -> DOUJANI | B70: ='Horaire samedi'!B69 -> 0.68055556 | C70: ='Horaire samedi'!C69 -> C15 | D70: =VLOOKUP(C70,'Liste chauffeur'!$B$5:$L$20,2,FALSE)&" "&VLOOKUP(C70,'Liste chauffeur'!$B$5:$L$20,3,FALSE) -> HAMADA Babou | F70: =COUNTBLANK(E70) -> 1 | Z70: =H70+J70-I70 -> 0 | AA70: =IF(F70=1,0,AA$6) -> 0 | AB70: =IF(AA70=0,0,Z70/AA70) -> 0
A71: ='Horaire samedi'!A70 -> PASSOT LA BARGE | B71: ='Horaire samedi'!B70 -> 0.6875 | C71: ='Horaire samedi'!C70 -> D9 | D71: =VLOOKUP(C71,'Liste chauffeur'!$B$5:$L$19,2,TRUE)&" "&VLOOKUP(C71,'Liste chauffeur'!$B$5:$L$19,3,TRUE) -> RENEE Assanati | F71: =COUNTBLANK(E71) -> 1 | Z71: =H71+J71-I71 -> 0 | AA71: =IF(F71=1,0,AA$6) -> 0 | AB71: =IF(AA71=0,0,Z71/AA71) -> 0
A72: ='Horaire samedi'!A71 -> DOUJANI | B72: ='Horaire samedi'!B71 -> 0.69444444 | C72: ='Horaire samedi'!C71 -> D15 | D72: =VLOOKUP(C72,'Liste chauffeur'!$B$5:$L$18,2,TRUE)&" "&VLOOKUP(C72,'Liste chauffeur'!$B$5:$L$18,3,TRUE) -> KAMARDINE Mansour | F72: =COUNTBLANK(E72) -> 1 | Z72: =H72+J72-I72 -> 0 | AA72: =IF(F72=1,0,AA$6) -> 0 | AB72: =IF(AA72=0,0,Z72/AA72) -> 0
A73: ='Horaire samedi'!A72 -> PASSOT LA BARGE | B73: ='Horaire samedi'!B72 -> 0.70138889 | C73: ='Horaire samedi'!C72 -> C15 | D73: =VLOOKUP(C73,'Liste chauffeur'!$B$5:$L$20,2,FALSE)&" "&VLOOKUP(C73,'Liste chauffeur'!$B$5:$L$20,3,FALSE) -> HAMADA Babou | F73: =COUNTBLANK(E73) -> 1 | Z73: =H73+J73-I73 -> 0 | AA73: =IF(F73=1,0,AA$6) -> 0 | AB73: =IF(AA73=0,0,Z73/AA73) -> 0
A74: ='Horaire samedi'!A73 -> DOUJANI | B74: ='Horaire samedi'!B73 -> 0.70833333 | C74: ='Horaire samedi'!C73 -> D9 | D74: =VLOOKUP(C74,'Liste chauffeur'!$B$5:$L$19,2,TRUE)&" "&VLOOKUP(C74,'Liste chauffeur'!$B$5:$L$19,3,TRUE) -> RENEE Assanati | F74: =COUNTBLANK(E74) -> 1 | Z74: =H74+J74-I74 -> 0 | AA74: =IF(F74=1,0,AA$6) -> 0 | AB74: =IF(AA74=0,0,Z74/AA74) -> 0
A75: ='Horaire samedi'!A74 -> PASSOT LA BARGE | B75: ='Horaire samedi'!B74 -> 0.71527778 | C75: ='Horaire samedi'!C74 -> D15 | D75: =VLOOKUP(C75,'Liste chauffeur'!$B$5:$L$18,2,TRUE)&" "&VLOOKUP(C75,'Liste chauffeur'!$B$5:$L$18,3,TRUE) -> KAMARDINE Mansour | F75: =COUNTBLANK(E75) -> 1 | Z75: =H75+J75-I75 -> 0 | AA75: =IF(F75=1,0,AA$6) -> 0 | AB75: =IF(AA75=0,0,Z75/AA75) -> 0
A76: ='Horaire samedi'!A75 -> DOUJANI | B76: ='Horaire samedi'!B75 -> 0.72222222 | C76: ='Horaire samedi'!C75 -> C15 | D76: =VLOOKUP(C76,'Liste chauffeur'!$B$5:$L$20,2,FALSE)&" "&VLOOKUP(C76,'Liste chauffeur'!$B$5:$L$20,3,FALSE) -> HAMADA Babou | F76: =COUNTBLANK(E76) -> 1 | Z76: =H76+J76-I76 -> 0 | AA76: =IF(F76=1,0,AA$6) -> 0 | AB76: =IF(AA76=0,0,Z76/AA76) -> 0
A77: ='Horaire samedi'!A76 -> PASSOT LA BARGE | B77: ='Horaire samedi'!B76 -> 0.72916667 | C77: ='Horaire samedi'!C76 -> D9 | D77: =VLOOKUP(C77,'Liste chauffeur'!$B$5:$L$19,2,TRUE)&" "&VLOOKUP(C77,'Liste chauffeur'!$B$5:$L$19,3,TRUE) -> RENEE Assanati | F77: =COUNTBLANK(E77) -> 1 | Z77: =H77+J77-I77 -> 0 | AA77: =IF(F77=1,0,AA$6) -> 0 | AB77: =IF(AA77=0,0,Z77/AA77) -> 0
A78: ='Horaire samedi'!A77 -> DOUJANI | B78: ='Horaire samedi'!B77 -> 0.73611111 | C78: ='Horaire samedi'!C77 -> D15 | D78: =VLOOKUP(C78,'Liste chauffeur'!$B$5:$L$18,2,TRUE)&" "&VLOOKUP(C78,'Liste chauffeur'!$B$5:$L$18,3,TRUE) -> KAMARDINE Mansour | F78: =COUNTBLANK(E78) -> 1 | Z78: =H78+J78-I78 -> 0 | AA78: =IF(F78=1,0,AA$6) -> 0 | AB78: =IF(AA78=0,0,Z78/AA78) -> 0
A79: ='Horaire samedi'!A78 -> PASSOT LA BARGE | B79: ='Horaire samedi'!B78 -> 0.74305556 | C79: ='Horaire samedi'!C78 -> C15 | D79: =VLOOKUP(C79,'Liste chauffeur'!$B$5:$L$20,2,FALSE)&" "&VLOOKUP(C79,'Liste chauffeur'!$B$5:$L$20,3,FALSE) -> HAMADA Babou | F79: =COUNTBLANK(E79) -> 1 | Z79: =H79+J79-I79 -> 0 | AA79: =IF(F79=1,0,AA$6) -> 0 | AB79: =IF(AA79=0,0,Z79/AA79) -> 0
A80: ='Horaire samedi'!A79 -> DOUJANI | B80: ='Horaire samedi'!B79 -> 0.75 | C80: ='Horaire samedi'!C79 -> D9 | D80: =VLOOKUP(C80,'Liste chauffeur'!$B$5:$L$19,2,TRUE)&" "&VLOOKUP(C80,'Liste chauffeur'!$B$5:$L$19,3,TRUE) -> RENEE Assanati | F80: =COUNTBLANK(E80) -> 1 | Z80: =H80+J80-I80 -> 0 | AA80: =IF(F80=1,0,AA$6) -> 0 | AB80: =IF(AA80=0,0,Z80/AA80) -> 0
A81: ='Horaire samedi'!A80 -> PASSOT LA BARGE | B81: ='Horaire samedi'!B80 -> 0.75694444 | C81: ='Horaire samedi'!C80 -> D15 | D81: =VLOOKUP(C81,'Liste chauffeur'!$B$5:$L$18,2,TRUE)&" "&VLOOKUP(C81,'Liste chauffeur'!$B$5:$L$18,3,TRUE) -> KAMARDINE Mansour | F81: =COUNTBLANK(E81) -> 1 | Z81: =H81+J81-I81 -> 0 | AA81: =IF(F81=1,0,AA$6) -> 0 | AB81: =IF(AA81=0,0,Z81/AA81) -> 0
A82: ='Horaire samedi'!A81 -> DOUJANI | B82: ='Horaire samedi'!B81 -> 0.76388889 | C82: ='Horaire samedi'!C81 -> C15 | D82: =VLOOKUP(C82,'Liste chauffeur'!$B$5:$L$20,2,FALSE)&" "&VLOOKUP(C82,'Liste chauffeur'!$B$5:$L$20,3,FALSE) -> HAMADA Babou | F82: =COUNTBLANK(E82) -> 1 | Z82: =H82+J82-I82 -> 0 | AA82: =IF(F82=1,0,AA$6) -> 0 | AB82: =IF(AA82=0,0,Z82/AA82) -> 0
A83: ='Horaire samedi'!A82 -> PASSOT LA BARGE | B83: ='Horaire samedi'!B82 -> 0.77083333 | C83: ='Horaire samedi'!C82 -> D9 | D83: =VLOOKUP(C83,'Liste chauffeur'!$B$5:$L$19,2,TRUE)&" "&VLOOKUP(C83,'Liste chauffeur'!$B$5:$L$19,3,TRUE) -> RENEE Assanati | F83: =COUNTBLANK(E83) -> 1 | Z83: =H83+J83-I83 -> 0 | AA83: =IF(F83=1,0,AA$6) -> 0 | AB83: =IF(AA83=0,0,Z83/AA83) -> 0
A84: ='Horaire samedi'!A83 -> DOUJANI | B84: ='Horaire samedi'!B83 -> 0.77777778 | C84: ='Horaire samedi'!C83 -> D15 | D84: =VLOOKUP(C84,'Liste chauffeur'!$B$5:$L$18,2,TRUE)&" "&VLOOKUP(C84,'Liste chauffeur'!$B$5:$L$18,3,TRUE) -> KAMARDINE Mansour | F84: =COUNTBLANK(E84) -> 1 | Z84: =H84+J84-I84 -> 0 | AA84: =IF(F84=1,0,AA$6) -> 0 | AB84: =IF(AA84=0,0,Z84/AA84) -> 0
A85: ='Horaire samedi'!A84 -> PASSOT LA BARGE | B85: ='Horaire samedi'!B84 -> 0.78472222 | C85: ='Horaire samedi'!C84 -> C15 | D85: =VLOOKUP(C85,'Liste chauffeur'!$B$5:$L$20,2,FALSE)&" "&VLOOKUP(C85,'Liste chauffeur'!$B$5:$L$20,3,FALSE) -> HAMADA Babou | F85: =COUNTBLANK(E85) -> 1 | Z85: =H85+J85-I85 -> 0 | AA85: =IF(F85=1,0,AA$6) -> 0 | AB85: =IF(AA85=0,0,Z85/AA85) -> 0
A86: ='Horaire samedi'!A85 -> DOUJANI | B86: ='Horaire samedi'!B85 -> 0.79166667 | C86: ='Horaire samedi'!C85 -> D9 | D86: =VLOOKUP(C86,'Liste chauffeur'!$B$5:$L$19,2,TRUE)&" "&VLOOKUP(C86,'Liste chauffeur'!$B$5:$L$19,3,TRUE) -> RENEE Assanati | F86: =COUNTBLANK(E86) -> 1 | Z86: =H86+J86-I86 -> 0 | AA86: =IF(F86=1,0,AA$6) -> 0 | AB86: =IF(AA86=0,0,Z86/AA86) -> 0
A87: ='Horaire samedi'!A86 -> PASSOT LA BARGE | B87: ='Horaire samedi'!B86 -> 0.79861111 | C87: ='Horaire samedi'!C86 -> D15 | D87: =VLOOKUP(C87,'Liste chauffeur'!$B$5:$L$18,2,TRUE)&" "&VLOOKUP(C87,'Liste chauffeur'!$B$5:$L$18,3,TRUE) -> KAMARDINE Mansour | F87: =COUNTBLANK(E87) -> 1 | Z87: =H87+J87-I87 -> 0 | AA87: =IF(F87=1,0,AA$6) -> 0 | AB87: =IF(AA87=0,0,Z87/AA87) -> 0
A88: ='Horaire samedi'!A87 -> DOUJANI | B88: ='Horaire samedi'!B87 -> 0.80555556 | C88: ='Horaire samedi'!C87 -> C15 | D88: =VLOOKUP(C88,'Liste chauffeur'!$B$5:$L$20,2,FALSE)&" "&VLOOKUP(C88,'Liste chauffeur'!$B$5:$L$20,3,FALSE) -> HAMADA Babou | F88: =COUNTBLANK(E88) -> 1 | Z88: =H88+J88-I88 -> 0 | AA88: =IF(F88=1,0,AA$6) -> 0 | AB88: =IF(AA88=0,0,Z88/AA88) -> 0
A89: ='Horaire samedi'!A88 -> PASSOT LA BARGE | B89: ='Horaire samedi'!B88 -> 0.8125 | C89: ='Horaire samedi'!C88 -> D9 | D89: =VLOOKUP(C89,'Liste chauffeur'!$B$5:$L$19,2,TRUE)&" "&VLOOKUP(C89,'Liste chauffeur'!$B$5:$L$19,3,TRUE) -> RENEE Assanati | F89: =COUNTBLANK(E89) -> 1 | Z89: =H89+J89-I89 -> 0 | AA89: =IF(F89=1,0,AA$6) -> 0 | AB89: =IF(AA89=0,0,Z89/AA89) -> 0
A90: ='Horaire samedi'!A89 -> DOUJANI | B90: ='Horaire samedi'!B89 -> 0.81944444 | C90: ='Horaire samedi'!C89 -> D15 | D90: =VLOOKUP(C90,'Liste chauffeur'!$B$5:$L$18,2,TRUE)&" "&VLOOKUP(C90,'Liste chauffeur'!$B$5:$L$18,3,TRUE) -> KAMARDINE Mansour | F90: =COUNTBLANK(E90) -> 1 | Z90: =H90+J90-I90 -> 0 | AA90: =IF(F90=1,0,AA$6) -> 0 | AB90: =IF(AA90=0,0,Z90/AA90) -> 0
A91: ='Horaire samedi'!A90 -> PASSOT LA BARGE | B91: ='Horaire samedi'!B90 -> 0.82638889 | C91: ='Horaire samedi'!C90 -> C15 | D91: =VLOOKUP(C91,'Liste chauffeur'!$B$5:$L$20,2,FALSE)&" "&VLOOKUP(C91,'Liste chauffeur'!$B$5:$L$20,3,FALSE) -> HAMADA Babou | F91: =COUNTBLANK(E91) -> 1 | Z91: =H91+J91-I91 -> 0 | AA91: =IF(F91=1,0,AA$6) -> 0 | AB91: =IF(AA91=0,0,Z91/AA91) -> 0
A92: ='Horaire samedi'!A91 -> DOUJANI | B92: ='Horaire samedi'!B91 -> 0.83333333 | C92: ='Horaire samedi'!C91 -> D9 | D92: =VLOOKUP(C92,'Liste chauffeur'!$B$5:$L$19,2,TRUE)&" "&VLOOKUP(C92,'Liste chauffeur'!$B$5:$L$19,3,TRUE) -> RENEE Assanati | F92: =COUNTBLANK(E92) -> 1 | Z92: =H92+J92-I92 -> 0 | AA92: =IF(F92=1,0,AA$6) -> 0 | AB92: =IF(AA92=0,0,Z92/AA92) -> 0
A93: ='Horaire samedi'!A92 -> PASSOT LA BARGE | B93: ='Horaire samedi'!B92 -> 0.84027778 | C93: ='Horaire samedi'!C92 -> D15 | D93: =VLOOKUP(C93,'Liste chauffeur'!$B$5:$L$18,2,TRUE)&" "&VLOOKUP(C93,'Liste chauffeur'!$B$5:$L$18,3,TRUE) -> KAMARDINE Mansour | F93: =COUNTBLANK(E93) -> 1 | Z93: =H93+J93-I93 -> 0 | AA93: =IF(F93=1,0,AA$6) -> 0 | AB93: =IF(AA93=0,0,Z93/AA93) -> 0
A94: ='Horaire samedi'!A93 -> DOUJANI | B94: ='Horaire samedi'!B93 -> 0.84722222 | C94: ='Horaire samedi'!C93 -> C15 | D94: =VLOOKUP(C94,'Liste chauffeur'!$B$5:$L$20,2,FALSE)&" "&VLOOKUP(C94,'Liste chauffeur'!$B$5:$L$20,3,FALSE) -> HAMADA Babou | F94: =COUNTBLANK(E94) -> 1 | Z94: =H94+J94-I94 -> 0 | AA94: =IF(F94=1,0,AA$6) -> 0 | AB94: =IF(AA94=0,0,Z94/AA94) -> 0
A95: ='Horaire samedi'!A94 -> PASSOT LA BARGE | B95: ='Horaire samedi'!B94 -> 0.85416667 | C95: ='Horaire samedi'!C94 -> D9 | D95: =VLOOKUP(C95,'Liste chauffeur'!$B$5:$L$19,2,TRUE)&" "&VLOOKUP(C95,'Liste chauffeur'!$B$5:$L$19,3,TRUE) -> RENEE Assanati | F95: =COUNTBLANK(E95) -> 1 | Z95: =H95+J95-I95 -> 0 | AA95: =IF(F95=1,0,AA$6) -> 0 | AB95: =IF(AA95=0,0,Z95/AA95) -> 0
A96: ='Horaire samedi'!A95 -> DOUJANI | B96: ='Horaire samedi'!B95 -> 0.86111111 | C96: ='Horaire samedi'!C95 -> D15 | D96: =VLOOKUP(C96,'Liste chauffeur'!$B$5:$L$18,2,TRUE)&" "&VLOOKUP(C96,'Liste chauffeur'!$B$5:$L$18,3,TRUE) -> KAMARDINE Mansour | F96: =COUNTBLANK(E96) -> 1 | Z96: =H96+J96-I96 -> 0 | AA96: =IF(F96=1,0,AA$6) -> 0 | AB96: =IF(AA96=0,0,Z96/AA96) -> 0
A97: ='Horaire samedi'!A96 -> PASSOT LA BARGE | B97: ='Horaire samedi'!B96 -> 0.86805556 | C97: ='Horaire samedi'!C96 -> C15 | D97: =VLOOKUP(C97,'Liste chauffeur'!$B$5:$L$20,2,FALSE)&" "&VLOOKUP(C97,'Liste chauffeur'!$B$5:$L$20,3,FALSE) -> HAMADA Babou | F97: =COUNTBLANK(E97) -> 1 | Z97: =H97+J97-I97 -> 0 | AA97: =IF(F97=1,0,AA$6) -> 0 | AB97: =IF(AA97=0,0,Z97/AA97) -> 0
B98: ST2 | C98: ST | G98: =SUM(G8:G97) -> 0 | Y98: =AVERAGE(Y45:Y97) -> #DIV/0! | Z98: =SUM(Z45:Z97) -> 0 | AA98: =SUM(AA45:AA97) -> 0 | AB98: =IF(AA98=0,0,Z98/AA98) -> 0
B99: ST3 | F99: =F44+F98 -> 36 | G99: =G44+G98 -> 0 | Y99: =AVERAGE(Y8:Y43,Y45:Y97) -> #DIV/0! | Z99: =Z44+Z98 -> 0 | AA99: =AA44+AA98 -> 0 | AB99: =IF(AA99=0,0,Z99/AA99) -> 0
A100: REMPLACEMENT | C100: D
A101: REMPLACEMENT | C101: D
A102: REMPLACEMENT | C102: D | O102: =M102-#REF! -> #REF! | P102: =#REF!+#REF!-#REF! -> #REF!
...

Sheet Feuille saisie dimanche 1
A2: TYPE | B2: D14
A3: DATE | B3: 45627
A4: CHAUFFEUR | B4: =VLOOKUP(B2,'Liste chauffeur'!$B$5:$L$18,2,TRUE)&" "&VLOOKUP(B2,'Liste chauffeur'!$B$5:$L$18,3,TRUE) -> AHAMADI Laydine
I6: Arrêt 1 | M6: Arrêt 2 | Q6: Arrêt 3 | W6: ARRIVEE | AA6: 8
B7: Heure théorique départ | C7: Horaire | D7: Chauffeur | E7: Heure réelle départ | F7: Trajet non effectué | G7: Départ avec plus de 10 mns retard | H7: Nbre personnes montée | I7: - | J7: + | K7: Heure arrivée arrêt 1 | L7: Délai | M7: - | N7: + | O7: Heure arrivée arrêt 2 | P7: Délai | Q7: - | R7: + | S7: Heure arrivée arrêt 3 | T7: Délai | U7: Nbre personnes descente | W7: Heure arrivée finale | X7: Commentaires | Y7: Temps Aller | Z7: Nbre personnes moyenne | AA7: Capacité max | AB7: Taux Fréquentation
A8: ='Horaire dimanche 1'!A8 -> DOUJANI | B8: ='Horaire dimanche 1'!B8 -> 0.33333333 | C8: ='Horaire dimanche 1'!C8 -> D12 | D8: =VLOOKUP(C8,'Liste chauffeur'!$B$5:$L$18,2,TRUE)&" "&VLOOKUP(C8,'Liste chauffeur'!$B$5:$L$18,3,TRUE) -> VELOU M'COLO M'Berou | F8: =COUNTBLANK(E8) -> 1 | Y8: =IF(F8=1,"",W8-E8) | Z8: =H8+J8-I8 -> 0 | AA8: =IF(F8=1,0,AA$6) -> 0 | AB8: =IF(AA8=0,0,Z8/AA8) -> 0
A9: ='Horaire dimanche 1'!A9 -> PASSOT LA BARGE | B9: ='Horaire dimanche 1'!B9 -> 0.35416667 | C9: ='Horaire dimanche 1'!C9 -> D12 | D9: =VLOOKUP(C9,'Liste chauffeur'!$B$5:$L$18,2,TRUE)&" "&VLOOKUP(C9,'Liste chauffeur'!$B$5:$L$18,3,TRUE) -> VELOU M'COLO M'Berou | F9: =COUNTBLANK(E9) -> 1 | Y9: =IF(F9=1,"",W9-E9) | Z9: =H9+J9-I9 -> 0 | AA9: =IF(F9=1,0,AA$6) -> 0 | AB9: =IF(AA9=0,0,Z9/AA9) -> 0
A10: ='Horaire dimanche 1'!A10 -> DOUJANI | B10: ='Horaire dimanche 1'!B10 -> 0.35416667 | C10: ='Horaire dimanche 1'!C10 -> D7 | D10: =VLOOKUP(C10,'Liste chauffeur'!$B$5:$L$18,2,TRUE)&" "&VLOOKUP(C10,'Liste chauffeur'!$B$5:$L$18,3,TRUE) -> COMBO Said | F10: =COUNTBLANK(E10) -> 1 | Y10: =IF(F10=1,"",W10-E10) | Z10: =H10+J10-I10 -> 0 | AA10: =IF(F10=1,0,AA$6) -> 0 | AB10: =IF(AA10=0,0,Z10/AA10) -> 0
A11: ='Horaire dimanche 1'!A11 -> PASSOT LA BARGE | B11: ='Horaire dimanche 1'!B11 -> 0.375 | C11: ='Horaire dimanche 1'!C11 -> D7 | D11: =VLOOKUP(C11,'Liste chauffeur'!$B$5:$L$18,2,TRUE)&" "&VLOOKUP(C11,'Liste chauffeur'!$B$5:$L$18,3,TRUE) -> COMBO Said | F11: =COUNTBLANK(E11) -> 1 | Y11: =IF(F11=1,"",W11-E11) | Z11: =H11+J11-I11 -> 0 | AA11: =IF(F11=1,0,AA$6) -> 0 | AB11: =IF(AA11=0,0,Z11/AA11) -> 0
A12: ='Horaire dimanche 1'!A12 -> DOUJANI | B12: ='Horaire dimanche 1'!B12 -> 0.375 | C12: ='Horaire dimanche 1'!C12 -> D12 | D12: =VLOOKUP(C12,'Liste chauffeur'!$B$5:$L$18,2,TRUE)&" "&VLOOKUP(C12,'Liste chauffeur'!$B$5:$L$18,3,TRUE) -> VELOU M'COLO M'Berou | F12: =COUNTBLANK(E12) -> 1 | L12: =K12-E12 -> 0 | P12: =O12-K12 -> 0 | T12: =S12-O12 -> 0 | V12: =IF(H12-I12+J12-M12+N12-Q12+R12=U12,"OK",H12-I12+J12-M12+N12-Q12+R12-U12) -> OK | Y12: =IF(F12=1,"",W12-E12) | Z12: =H12+J12-I12 -> 0 | AA12: =IF(F12=1,0,AA$6) -> 0 | AB12: =IF(AA12=0,0,Z12/AA12) -> 0
A13: ='Horaire dimanche 1'!A13 -> PASSOT LA BARGE | B13: ='Horaire dimanche 1'!B13 -> 0.39583333 | C13: ='Horaire dimanche 1'!C13 -> D12 | D13: =VLOOKUP(C13,'Liste chauffeur'!$B$5:$L$18,2,TRUE)&" "&VLOOKUP(C13,'Liste chauffeur'!$B$5:$L$18,3,TRUE) -> VELOU M'COLO M'Berou | F13: =COUNTBLANK(E13) -> 1 | L13: =K13-E13 -> 0 | P13: =O13-K13 -> 0 | T13: =S13-O13 -> 0 | Y13: =IF(F13=1,"",W13-E13) | Z13: =H13+J13-I13 -> 0 | AA13: =IF(F13=1,0,AA$6) -> 0 | AB13: =IF(AA13=0,0,Z13/AA13) -> 0
A14: ='Horaire dimanche 1'!A14 -> DOUJANI | B14: ='Horaire dimanche 1'!B14 -> 0.39583333 | C14: ='Horaire dimanche 1'!C14 -> D7 | D14: =VLOOKUP(C14,'Liste chauffeur'!$B$5:$L$18,2,TRUE)&" "&VLOOKUP(C14,'Liste chauffeur'!$B$5:$L$18,3,TRUE) -> COMBO Said | F14: =COUNTBLANK(E14) -> 1 | L14: =K14-E14 -> 0 | P14: =O14-K14 -> 0 | T14: =S14-O14 -> 0 | Y14: =IF(F14=1,"",W14-E14) | Z14: =H14+J14-I14 -> 0 | AA14: =IF(F14=1,0,AA$6) -> 0 | AB14: =IF(AA14=0,0,Z14/AA14) -> 0
A15: ='Horaire dimanche 1'!A15 -> PASSOT LA BARGE | B15: ='Horaire dimanche 1'!B15 -> 0.41666667 | C15: ='Horaire dimanche 1'!C15 -> D7 | D15: =VLOOKUP(C15,'Liste chauffeur'!$B$5:$L$18,2,TRUE)&" "&VLOOKUP(C15,'Liste chauffeur'!$B$5:$L$18,3,TRUE) -> COMBO Said | F15: =COUNTBLANK(E15) -> 1 | L15: =K15-E15 -> 0 | P15: =O15-K15 -> 0 | T15: =S15-O15 -> 0 | Y15: =IF(F15=1,"",W15-E15) | Z15: =H15+J15-I15 -> 0 | AA15: =IF(F15=1,0,AA$6) -> 0 | AB15: =IF(AA15=0,0,Z15/AA15) -> 0
A16: ='Horaire dimanche 1'!A16 -> DOUJANI | B16: ='Horaire dimanche 1'!B16 -> 0.41666667 | C16: ='Horaire dimanche 1'!C16 -> D12 | D16: =VLOOKUP(C16,'Liste chauffeur'!$B$5:$L$18,2,TRUE)&" "&VLOOKUP(C16,'Liste chauffeur'!$B$5:$L$18,3,TRUE) -> VELOU M'COLO M'Berou | F16: =COUNTBLANK(E16) -> 1 | L16: =K16-E16 -> 0 | P16: =O16-K16 -> 0 | T16: =S16-O16 -> 0 | V16: =IF(H16-I16+J16-M16+N16-Q16+R16=U16,"OK",H16-I16+J16-M16+N16-Q16+R16-U16) -> OK | Y16: =IF(F16=1,"",W16-E16) | Z16: =H16+J16-I16 -> 0 | AA16: =IF(F16=1,0,AA$6) -> 0 | AB16: =IF(AA16=0,0,Z16/AA16) -> 0
A17: ='Horaire dimanche 1'!A17 -> PASSOT LA BARGE | B17: ='Horaire dimanche 1'!B17 -> 0.4375 | C17: ='Horaire dimanche 1'!C17 -> D12 | D17: =VLOOKUP(C17,'Liste chauffeur'!$B$5:$L$18,2,TRUE)&" "&VLOOKUP(C17,'Liste chauffeur'!$B$5:$L$18,3,TRUE) -> VELOU M'COLO M'Berou | F17: =COUNTBLANK(E17) -> 1 | L17: =K17-E17 -> 0 | P17: =O17-K17 -> 0 | T17: =S17-O17 -> 0 | V17: =IF(H17-I17+J17-M17+N17-Q17+R17=U17,"OK",H17-I17+J17-M17+N17-Q17+R17-U17) -> OK | Y17: =IF(F17=1,"",W17-E17) | Z17: =H17+J17-I17 -> 0 | AA17: =IF(F17=1,0,AA$6) -> 0 | AB17: =IF(AA17=0,0,Z17/AA17) -> 0
A18: ='Horaire dimanche 1'!A18 -> DOUJANI | B18: ='Horaire dimanche 1'!B18 -> 0.4375 | C18: ='Horaire dimanche 1'!C18 -> D7 | D18: =VLOOKUP(C18,'Liste chauffeur'!$B$5:$L$18,2,TRUE)&" "&VLOOKUP(C18,'Liste chauffeur'!$B$5:$L$18,3,TRUE) -> COMBO Said | F18: =COUNTBLANK(E18) -> 1 | Z18: =H18+J18-I18 -> 0 | AA18: =IF(F18=1,0,AA$6) -> 0 | AB18: =IF(AA18=0,0,Z18/AA18) -> 0
A19: ='Horaire dimanche 1'!A19 -> PASSOT LA BARGE | B19: ='Horaire dimanche 1'!B19 -> 0.45833333 | C19: ='Horaire dimanche 1'!C19 -> D7 | D19: =VLOOKUP(C19,'Liste chauffeur'!$B$5:$L$18,2,TRUE)&" "&VLOOKUP(C19,'Liste chauffeur'!$B$5:$L$18,3,TRUE) -> COMBO Said | F19: =COUNTBLANK(E19) -> 1 | L19: =K19-E19 -> 0 | P19: =O19-K19 -> 0 | T19: =S19-O19 -> 0 | V19: =IF(H19-I19+J19-M19+N19-Q19+R19=U19,"OK",H19-I19+J19-M19+N19-Q19+R19-U19) -> OK | Y19: =IF(F19=1,"",W19-E19) | Z19: =H19+J19-I19 -> 0 | AA19: =IF(F19=1,0,AA$6) -> 0 | AB19: =IF(AA19=0,0,Z19/AA19) -> 0
A20: ='Horaire dimanche 1'!A20 -> DOUJANI | B20: ='Horaire dimanche 1'!B20 -> 0.45833333 | C20: ='Horaire dimanche 1'!C20 -> D12 | D20: =VLOOKUP(C20,'Liste chauffeur'!$B$5:$L$18,2,TRUE)&" "&VLOOKUP(C20,'Liste chauffeur'!$B$5:$L$18,3,TRUE) -> VELOU M'COLO M'Berou | F20: =COUNTBLANK(E20) -> 1 | L20: =K20-E20 -> 0 | P20: =O20-K20 -> 0 | T20: =S20-O20 -> 0 | V20: =IF(H20-I20+J20-M20+N20-Q20+R20=U20,"OK",H20-I20+J20-M20+N20-Q20+R20-U20) -> OK | Y20: =IF(F20=1,"",W20-E20) | Z20: =H20+J20-I20 -> 0 | AA20: =IF(F20=1,0,AA$6) -> 0 | AB20: =IF(AA20=0,0,Z20/AA20) -> 0
A21: ='Horaire dimanche 1'!A21 -> PASSOT LA BARGE | B21: ='Horaire dimanche 1'!B21 -> 0.47916667 | C21: ='Horaire dimanche 1'!C21 -> D12 | D21: =VLOOKUP(C21,'Liste chauffeur'!$B$5:$L$18,2,TRUE)&" "&VLOOKUP(C21,'Liste chauffeur'!$B$5:$L$18,3,TRUE) -> VELOU M'COLO M'Berou | F21: =COUNTBLANK(E21) -> 1 | L21: =K21-E21 -> 0 | P21: =O21-K21 -> 0 | T21: =S21-O21 -> 0 | V21: =IF(H21-I21+J21-M21+N21-Q21+R21=U21,"OK",H21-I21+J21-M21+N21-Q21+R21-U21) -> OK | Y21: =IF(F21=1,"",W21-E21) | Z21: =H21+J21-I21 -> 0 | AA21: =IF(F21=1,0,AA$6) -> 0 | AB21: =IF(AA21=0,0,Z21/AA21) -> 0
A22: ='Horaire dimanche 1'!A22 -> DOUJANI | B22: ='Horaire dimanche 1'!B22 -> 0.47916667 | C22: ='Horaire dimanche 1'!C22 -> D7 | D22: =VLOOKUP(C22,'Liste chauffeur'!$B$5:$L$18,2,TRUE)&" "&VLOOKUP(C22,'Liste chauffeur'!$B$5:$L$18,3,TRUE) -> COMBO Said | F22: =COUNTBLANK(E22) -> 1 | L22: =K22-E22 -> 0 | P22: =O22-K22 -> 0 | T22: =S22-O22 -> 0 | V22: =IF(H22-I22+J22-M22+N22-Q22+R22=U22,"OK",H22-I22+J22-M22+N22-Q22+R22-U22) -> OK | Y22: =IF(F22=1,"",W22-E22) | Z22: =H22+J22-I22 -> 0 | AA22: =IF(F22=1,0,AA$6) -> 0 | AB22: =IF(AA22=0,0,Z22/AA22) -> 0
A23: ='Horaire dimanche 1'!A23 -> PASSOT LA BARGE | B23: ='Horaire dimanche 1'!B23 -> 0.5 | C23: ='Horaire dimanche 1'!C23 -> D7 | D23: =VLOOKUP(C23,'Liste chauffeur'!$B$5:$L$18,2,TRUE)&" "&VLOOKUP(C23,'Liste chauffeur'!$B$5:$L$18,3,TRUE) -> COMBO Said | F23: =COUNTBLANK(E23) -> 1 | L23: =K23-E23 -> 0 | P23: =O23-K23 -> 0 | T23: =S23-O23 -> 0 | V23: =IF(H23-I23+J23-M23+N23-Q23+R23=U23,"OK",H23-I23+J23-M23+N23-Q23+R23-U23) -> OK | Y23: =IF(F23=1,"",W23-E23) | Z23: =H23+J23-I23 -> 0 | AA23: =IF(F23=1,0,AA$6) -> 0 | AB23: =IF(AA23=0,0,Z23/AA23) -> 0
A24: ='Horaire dimanche 1'!A24 -> DOUJANI | B24: ='Horaire dimanche 1'!B24 -> 0.5 | C24: ='Horaire dimanche 1'!C24 -> D12 | D24: =VLOOKUP(C24,'Liste chauffeur'!$B$5:$L$18,2,TRUE)&" "&VLOOKUP(C24,'Liste chauffeur'!$B$5:$L$18,3,TRUE) -> VELOU M'COLO M'Berou | F24: =COUNTBLANK(E24) -> 1 | L24: =K24-E24 -> 0 | P24: =O24-K24 -> 0 | T24: =S24-O24 -> 0 | V24: =IF(H24-I24+J24-M24+N24-Q24+R24=U24,"OK",H24-I24+J24-M24+N24-Q24+R24-U24) -> OK | Y24: =IF(F24=1,"",W24-E24) | Z24: =H24+J24-I24 -> 0 | AA24: =IF(F24=1,0,AA$6) -> 0 | AB24: =IF(AA24=0,0,Z24/AA24) -> 0
B25: ST1 | F25: =SUM(F8:F24) -> 17 | G25: =SUM(G8:G24) -> 0 | Y25: =AVERAGE(Y8:Y24) -> #DIV/0! | Z25: =SUM(Z8:Z24) -> 0 | AA25: =SUM(AA8:AA24) -> 0 | AB25: =IF(AA25=0,0,Z25/AA25) -> 0
A26: ='Horaire dimanche 1'!A25 -> PASSOT LA BARGE | B26: ='Horaire dimanche 1'!B25 -> 0.52083333 | C26: ='Horaire dimanche 1'!C25 -> D12 | D26: =VLOOKUP(C26,'Liste chauffeur'!$B$5:$L$18,2,TRUE)&" "&VLOOKUP(C26,'Liste chauffeur'!$B$5:$L$18,3,TRUE) -> VELOU M'COLO M'Berou | F26: =COUNTBLANK(E26) -> 1 | Z26: =H26+J26-I26 -> 0 | AA26: =IF(F26=1,0,AA$6) -> 0 | AB26: =IF(AA26=0,0,Z26/AA26) -> 0
A27: ='Horaire dimanche 1'!A26 -> DOUJANI | B27: ='Horaire dimanche 1'!B26 -> 0.52083333 | C27: ='Horaire dimanche 1'!C26 -> D7 | D27: =VLOOKUP(C27,'Liste chauffeur'!$B$5:$L$18,2,TRUE)&" "&VLOOKUP(C27,'Liste chauffeur'!$B$5:$L$18,3,TRUE) -> COMBO Said | F27: =COUNTBLANK(E27) -> 1 | L27: =K27-E27 -> 0 | P27: =O27-K27 -> 0 | T27: =S27-O27 -> 0 | V27: =IF(H27-I27+J27-M27+N27-Q27+R27=U27,"OK",H27-I27+J27-M27+N27-Q27+R27-U27) -> OK | Y27: =IF(F27=1,"",W27-E27) | Z27: =H27+J27-I27 -> 0 | AA27: =IF(F27=1,0,AA$6) -> 0 | AB27: =IF(AA27=0,0,Z27/AA27) -> 0
A28: ='Horaire dimanche 1'!A27 -> PASSOT LA BARGE | B28: ='Horaire dimanche 1'!B27 -> 0.54166667 | C28: ='Horaire dimanche 1'!C27 -> D7 | D28: =VLOOKUP(C28,'Liste chauffeur'!$B$5:$L$18,2,TRUE)&" "&VLOOKUP(C28,'Liste chauffeur'!$B$5:$L$18,3,TRUE) -> COMBO Said | F28: =COUNTBLANK(E28) -> 1 | L28: =K28-E28 -> 0 | P28: =O28-K28 -> 0 | T28: =S28-O28 -> 0 | V28: =IF(H28-I28+J28-M28+N28-Q28+R28=U28,"OK",H28-I28+J28-M28+N28-Q28+R28-U28) -> OK | Y28: =IF(F28=1,"",W28-E28) | Z28: =H28+J28-I28 -> 0 | AA28: =IF(F28=1,0,AA$6) -> 0 | AB28: =IF(AA28=0,0,Z28/AA28) -> 0
A29: ='Horaire dimanche 1'!A28 -> DOUJANI | B29: ='Horaire dimanche 1'!B28 -> 0.54166667 | C29: ='Horaire dimanche 1'!C28 -> D12 | D29: =VLOOKUP(C29,'Liste chauffeur'!$B$5:$L$18,2,TRUE)&" "&VLOOKUP(C29,'Liste chauffeur'!$B$5:$L$18,3,TRUE) -> VELOU M'COLO M'Berou | F29: =COUNTBLANK(E29) -> 1 | L29: =K29-E29 -> 0 | P29: =O29-K29 -> 0 | T29: =S29-O29 -> 0 | V29: =IF(H29-I29+J29-M29+N29-Q29+R29=U29,"OK",H29-I29+J29-M29+N29-Q29+R29-U29) -> OK | Y29: =IF(F29=1,"",W29-E29) | Z29: =H29+J29-I29 -> 0 | AA29: =IF(F29=1,0,AA$6) -> 0 | AB29: =IF(AA29=0,0,Z29/AA29) -> 0
A30: ='Horaire dimanche 1'!A29 -> PASSOT LA BARGE | B30: ='Horaire dimanche 1'!B29 -> 0.5625 | C30: ='Horaire dimanche 1'!C29 -> D14 | D30: =VLOOKUP(C30,'Liste chauffeur'!$B$5:$L$18,2,TRUE)&" "&VLOOKUP(C30,'Liste chauffeur'!$B$5:$L$18,3,TRUE) -> AHAMADI Laydine | F30: =COUNTBLANK(E30) -> 1 | L30: =K30-E30 -> 0 | P30: =O30-K30 -> 0 | T30: =S30-O30 -> 0 | V30: =IF(H30-I30+J30-M30+N30-Q30+R30=U30,"OK",H30-I30+J30-M30+N30-Q30+R30-U30) -> OK | Y30: =IF(F30=1,"",W30-E30) | Z30: =H30+J30-I30 -> 0 | AA30: =IF(F30=1,0,AA$6) -> 0 | AB30: =IF(AA30=0,0,Z30/AA30) -> 0
A31: ='Horaire dimanche 1'!A30 -> DOUJANI | B31: ='Horaire dimanche 1'!B30 -> 0.5625 | C31: ='Horaire dimanche 1'!C30 -> D7 | D31: =VLOOKUP(C31,'Liste chauffeur'!$B$5:$L$18,2,TRUE)&" "&VLOOKUP(C31,'Liste chauffeur'!$B$5:$L$18,3,TRUE) -> COMBO Said | F31: =COUNTBLANK(E31) -> 1 | L31: =K31-E31 -> 0 | P31: =O31-K31 -> 0 | T31: =S31-O31 -> 0 | V31: =IF(H31-I31+J31-M31+N31-Q31+R31=U31,"OK",H31-I31+J31-M31+N31-Q31+R31-U31) -> OK | Y31: =IF(F31=1,"",W31-E31) | Z31: =H31+J31-I31 -> 0 | AA31: =IF(F31=1,0,AA$6) -> 0 | AB31: =IF(AA31=0,0,Z31/AA31) -> 0
A32: ='Horaire dimanche 1'!A31 -> PASSOT LA BARGE | B32: ='Horaire dimanche 1'!B31 -> 0.58333333 | C32: ='Horaire dimanche 1'!C31 -> D13 | D32: =VLOOKUP(C32,'Liste chauffeur'!$B$5:$L$18,2,TRUE)&" "&VLOOKUP(C32,'Liste chauffeur'!$B$5:$L$18,3,TRUE) -> MOURIDI Aktoir | F32: =COUNTBLANK(E32) -> 1 | L32: =K32-E32 -> 0 | P32: =O32-K32 -> 0 | T32: =S32-O32 -> 0 | V32: =IF(H32-I32+J32-M32+N32-Q32+R32=U32,"OK",H32-I32+J32-M32+N32-Q32+R32-U32) -> OK | Y32: =IF(F32=1,"",W32-E32) | Z32: =H32+J32-I32 -> 0 | AA32: =IF(F32=1,0,AA$6) -> 0 | AB32: =IF(AA32=0,0,Z32/AA32) -> 0
A33: ='Horaire dimanche 1'!A32 -> DOUJANI | B33: ='Horaire dimanche 1'!B32 -> 0.58333333 | C33: ='Horaire dimanche 1'!C32 -> D14 | D33: =VLOOKUP(C33,'Liste chauffeur'!$B$5:$L$18,2,TRUE)&" "&VLOOKUP(C33,'Liste chauffeur'!$B$5:$L$18,3,TRUE) -> AHAMADI Laydine | F33: =COUNTBLANK(E33) -> 1 | Z33: =H33+J33-I33 -> 0 | AA33: =IF(F33=1,0,AA$6) -> 0 | AB33: =IF(AA33=0,0,Z33/AA33) -> 0
A34: ='Horaire dimanche 1'!A33 -> PASSOT LA BARGE | B34: ='Horaire dimanche 1'!B33 -> 0.60416667 | C34: ='Horaire dimanche 1'!C33 -> D14 | D34: =VLOOKUP(C34,'Liste chauffeur'!$B$5:$L$18,2,TRUE)&" "&VLOOKUP(C34,'Liste chauffeur'!$B$5:$L$18,3,TRUE) -> AHAMADI Laydine | F34: =COUNTBLANK(E34) -> 1 | L34: =K34-E34 -> 0 | P34: =O34-K34 -> 0 | T34: =S34-O34 -> 0 | V34: =IF(H34-I34+J34-M34+N34-Q34+R34=U34,"OK",H34-I34+J34-M34+N34-Q34+R34-U34) -> OK | Y34: =IF(F34=1,"",W34-E34) | Z34: =H34+J34-I34 -> 0 | AA34: =IF(F34=1,0,AA$6) -> 0 | AB34: =IF(AA34=0,0,Z34/AA34) -> 0
A35: ='Horaire dimanche 1'!A34 -> DOUJANI | B35: ='Horaire dimanche 1'!B34 -> 0.60416667 | C35: ='Horaire dimanche 1'!C34 -> D13 | D35: =VLOOKUP(C35,'Liste chauffeur'!$B$5:$L$18,2,TRUE)&" "&VLOOKUP(C35,'Liste chauffeur'!$B$5:$L$18,3,TRUE) -> MOURIDI Aktoir | F35: =COUNTBLANK(E35) -> 1 | L35: =K35-E35 -> 0 | V35: =IF(H35-I35+J35-M35+N35-Q35+R35=U35,"OK",H35-I35+J35-M35+N35-Q35+R35-U35) -> OK | Y35: =IF(F35=1,"",W35-E35) | Z35: =H35+J35-I35 -> 0 | AA35: =IF(F35=1,0,AA$6) -> 0 | AB35: =IF(AA35=0,0,Z35/AA35) -> 0
A36: ='Horaire dimanche 1'!A35 -> PASSOT LA BARGE | B36: ='Horaire dimanche 1'!B35 -> 0.625 | C36: ='Horaire dimanche 1'!C35 -> D13 | D36: =VLOOKUP(C36,'Liste chauffeur'!$B$5:$L$18,2,TRUE)&" "&VLOOKUP(C36,'Liste chauffeur'!$B$5:$L$18,3,TRUE) -> MOURIDI Aktoir | F36: =COUNTBLANK(E36) -> 1 | L36: =K36-E36 -> 0 | V36: =IF(H36-I36+J36-M36+N36-Q36+R36=U36,"OK",H36-I36+J36-M36+N36-Q36+R36-U36) -> OK | Y36: =IF(F36=1,"",W36-E36) | Z36: =H36+J36-I36 -> 0 | AA36: =IF(F36=1,0,AA$6) -> 0 | AB36: =IF(AA36=0,0,Z36/AA36) -> 0
A37: ='Horaire dimanche 1'!A36 -> DOUJANI | B37: ='Horaire dimanche 1'!B36 -> 0.625 | C37: ='Horaire dimanche 1'!C36 -> D14 | D37: =VLOOKUP(C37,'Liste chauffeur'!$B$5:$L$18,2,TRUE)&" "&VLOOKUP(C37,'Liste chauffeur'!$B$5:$L$18,3,TRUE) -> AHAMADI Laydine | F37: =COUNTBLANK(E37) -> 1 | L37: =K37-E37 -> 0 | V37: =IF(H37-I37+J37-M37+N37-Q37+R37=U37,"OK",H37-I37+J37-M37+N37-Q37+R37-U37) -> OK | Y37: =IF(F37=1,"",W37-E37) | Z37: =H37+J37-I37 -> 0 | AA37: =IF(F37=1,0,AA$6) -> 0 | AB37: =IF(AA37=0,0,Z37/AA37) -> 0
A38: ='Horaire dimanche 1'!A37 -> PASSOT LA BARGE | B38: ='Horaire dimanche 1'!B37 -> 0.64583333 | C38: ='Horaire dimanche 1'!C37 -> D14 | D38: =VLOOKUP(C38,'Liste chauffeur'!$B$5:$L$18,2,TRUE)&" "&VLOOKUP(C38,'Liste chauffeur'!$B$5:$L$18,3,TRUE) -> AHAMADI Laydine | F38: =COUNTBLANK(E38) -> 1 | L38: =K38-E38 -> 0 | V38: =IF(H38-I38+J38-M38+N38-Q38+R38=U38,"OK",H38-I38+J38-M38+N38-Q38+R38-U38) -> OK | Y38: =IF(F38=1,"",W38-E38) | Z38: =H38+J38-I38 -> 0 | AA38: =IF(F38=1,0,AA$6) -> 0 | AB38: =IF(AA38=0,0,Z38/AA38) -> 0
A39: ='Horaire dimanche 1'!A38 -> DOUJANI | B39: ='Horaire dimanche 1'!B38 -> 0.64583333 | C39: ='Horaire dimanche 1'!C38 -> D13 | D39: =VLOOKUP(C39,'Liste chauffeur'!$B$5:$L$18,2,TRUE)&" "&VLOOKUP(C39,'Liste chauffeur'!$B$5:$L$18,3,TRUE) -> MOURIDI Aktoir | F39: =COUNTBLANK(E39) -> 1 | L39: =K39-E39 -> 0 | V39: =IF(H39-I39+J39-M39+N39-Q39+R39=U39,"OK",H39-I39+J39-M39+N39-Q39+R39-U39) -> OK | Y39: =IF(F39=1,"",W39-E39) | Z39: =H39+J39-I39 -> 0 | AA39: =IF(F39=1,0,AA$6) -> 0 | AB39: =IF(AA39=0,0,Z39/AA39) -> 0
A40: ='Horaire dimanche 1'!A39 -> PASSOT LA BARGE | B40: ='Horaire dimanche 1'!B39 -> 0.66666667 | C40: ='Horaire dimanche 1'!C39 -> D13 | D40: =VLOOKUP(C40,'Liste chauffeur'!$B$5:$L$18,2,TRUE)&" "&VLOOKUP(C40,'Liste chauffeur'!$B$5:$L$18,3,TRUE) -> MOURIDI Aktoir | F40: =COUNTBLANK(E40) -> 1 | L40: =K40-E40 -> 0 | V40: =IF(H40-I40+J40-M40+N40-Q40+R40=U40,"OK",H40-I40+J40-M40+N40-Q40+R40-U40) -> OK | Y40: =IF(F40=1,"",W40-E40) | Z40: =H40+J40-I40 -> 0 | AA40: =IF(F40=1,0,AA$6) -> 0 | AB40: =IF(AA40=0,0,Z40/AA40) -> 0
A41: ='Horaire dimanche 1'!A40 -> DOUJANI | B41: ='Horaire dimanche 1'!B40 -> 0.66666667 | C41: ='Horaire dimanche 1'!C40 -> D14 | D41: =VLOOKUP(C41,'Liste chauffeur'!$B$5:$L$18,2,TRUE)&" "&VLOOKUP(C41,'Liste chauffeur'!$B$5:$L$18,3,TRUE) -> AHAMADI Laydine | F41: =COUNTBLANK(E41) -> 1 | L41: =K41-E41 -> 0 | V41: =IF(H41-I41+J41-M41+N41-Q41+R41=U41,"OK",H41-I41+J41-M41+N41-Q41+R41-U41) -> OK | Y41: =IF(F41=1,"",W41-E41) | Z41: =H41+J41-I41 -> 0 | AA41: =IF(F41=1,0,AA$6) -> 0 | AB41: =IF(AA41=0,0,Z41/AA41) -> 0
A42: ='Horaire dimanche 1'!A41 -> PASSOT LA BARGE | B42: ='Horaire dimanche 1'!B41 -> 0.6875 | C42: ='Horaire dimanche 1'!C41 -> D14 | D42: =VLOOKUP(C42,'Liste chauffeur'!$B$5:$L$18,2,TRUE)&" "&VLOOKUP(C42,'Liste chauffeur'!$B$5:$L$18,3,TRUE) -> AHAMADI Laydine | F42: =COUNTBLANK(E42) -> 1 | L42: =K42-E42 -> 0 | V42: =IF(H42-I42+J42-M42+N42-Q42+R42=U42,"OK",H42-I42+J42-M42+N42-Q42+R42-U42) -> OK | Y42: =IF(F42=1,"",W42-E42) | Z42: =H42+J42-I42 -> 0 | AA42: =IF(F42=1,0,AA$6) -> 0 | AB42: =IF(AA42=0,0,Z42/AA42) -> 0
A43: ='Horaire dimanche 1'!A42 -> DOUJANI | B43: ='Horaire dimanche 1'!B42 -> 0.6875 | C43: ='Horaire dimanche 1'!C42 -> D13 | D43: =VLOOKUP(C43,'Liste chauffeur'!$B$5:$L$18,2,TRUE)&" "&VLOOKUP(C43,'Liste chauffeur'!$B$5:$L$18,3,TRUE) -> MOURIDI Aktoir | F43: =COUNTBLANK(E43) -> 1 | L43: =K43-E43 -> 0 | V43: =IF(H43-I43+J43-M43+N43-Q43+R43=U43,"OK",H43-I43+J43-M43+N43-Q43+R43-U43) -> OK | Y43: =IF(F43=1,"",W43-E43) | Z43: =H43+J43-I43 -> 0 | AA43: =IF(F43=1,0,AA$6) -> 0 | AB43: =IF(AA43=0,0,Z43/AA43) -> 0
A44: ='Horaire dimanche 1'!A43 -> PASSOT LA BARGE | B44: ='Horaire dimanche 1'!B43 -> 0.70833333 | C44: ='Horaire dimanche 1'!C43 -> D13 | D44: =VLOOKUP(C44,'Liste chauffeur'!$B$5:$L$18,2,TRUE)&" "&VLOOKUP(C44,'Liste chauffeur'!$B$5:$L$18,3,TRUE) -> MOURIDI Aktoir | F44: =COUNTBLANK(E44) -> 1 | L44: =K44-E44 -> 0 | V44: =IF(H44-I44+J44-M44+N44-Q44+R44=U44,"OK",H44-I44+J44-M44+N44-Q44+R44-U44) -> OK | Y44: =IF(F44=1,"",W44-E44) | Z44: =H44+J44-I44 -> 0 | AA44: =IF(F44=1,0,AA$6) -> 0 | AB44: =IF(AA44=0,0,Z44/AA44) -> 0
A45: ='Horaire dimanche 1'!A44 -> DOUJANI | B45: ='Horaire dimanche 1'!B44 -> 0.70833333 | C45: ='Horaire dimanche 1'!C44 -> D14 | D45: =VLOOKUP(C45,'Liste chauffeur'!$B$5:$L$18,2,TRUE)&" "&VLOOKUP(C45,'Liste chauffeur'!$B$5:$L$18,3,TRUE) -> AHAMADI Laydine | F45: =COUNTBLANK(E45) -> 1 | L45: =K45-E45 -> 0 | V45: =IF(H45-I45+J45-M45+N45-Q45+R45=U45,"OK",H45-I45+J45-M45+N45-Q45+R45-U45) -> OK | Y45: =IF(F45=1,"",W45-E45) | Z45: =H45+J45-I45 -> 0 | AA45: =IF(F45=1,0,AA$6) -> 0 | AB45: =IF(AA45=0,0,Z45/AA45) -> 0
A46: ='Horaire dimanche 1'!A45 -> PASSOT LA BARGE | B46: ='Horaire dimanche 1'!B45 -> 0.72916667 | C46: ='Horaire dimanche 1'!C45 -> D14 | D46: =VLOOKUP(C46,'Liste chauffeur'!$B$5:$L$18,2,TRUE)&" "&VLOOKUP(C46,'Liste chauffeur'!$B$5:$L$18,3,TRUE) -> AHAMADI Laydine | F46: =COUNTBLANK(E46) -> 1 | L46: =K46-E46 -> 0 | V46: =IF(H46-I46+J46-M46+N46-Q46+R46=U46,"OK",H46-I46+J46-M46+N46-Q46+R46-U46) -> OK | Y46: =IF(F46=1,"",W46-E46) | Z46: =H46+J46-I46 -> 0 | AA46: =IF(F46=1,0,AA$6) -> 0 | AB46: =IF(AA46=0,0,Z46/AA46) -> 0
A47: ='Horaire dimanche 1'!A46 -> DOUJANI | B47: ='Horaire dimanche 1'!B46 -> 0.72916667 | C47: ='Horaire dimanche 1'!C46 -> D13 | D47: =VLOOKUP(C47,'Liste chauffeur'!$B$5:$L$18,2,TRUE)&" "&VLOOKUP(C47,'Liste chauffeur'!$B$5:$L$18,3,TRUE) -> MOURIDI Aktoir | F47: =COUNTBLANK(E47) -> 1 | L47: =K47-E47 -> 0 | V47: =IF(H47-I47+J47-M47+N47-Q47+R47=U47,"OK",H47-I47+J47-M47+N47-Q47+R47-U47) -> OK | Y47: =IF(F47=1,"",W47-E47) | Z47: =H47+J47-I47 -> 0 | AA47: =IF(F47=1,0,AA$6) -> 0 | AB47: =IF(AA47=0,0,Z47/AA47) -> 0
A48: ='Horaire dimanche 1'!A47 -> PASSOT LA BARGE | B48: ='Horaire dimanche 1'!B47 -> 0.75 | C48: ='Horaire dimanche 1'!C47 -> D13 | D48: =VLOOKUP(C48,'Liste chauffeur'!$B$5:$L$18,2,TRUE)&" "&VLOOKUP(C48,'Liste chauffeur'!$B$5:$L$18,3,TRUE) -> MOURIDI Aktoir | F48: =COUNTBLANK(E48) -> 1 | L48: =K48-E48 -> 0 | Y48: =IF(F48=1,"",W48-E48) | Z48: =H48+J48-I48 -> 0 | AA48: =IF(F48=1,0,AA$6) -> 0 | AB48: =IF(AA48=0,0,Z48/AA48) -> 0
A49: ='Horaire dimanche 1'!A48 -> DOUJANI | B49: ='Horaire dimanche 1'!B48 -> 0.75 | C49: ='Horaire dimanche 1'!C48 -> D14 | D49: =VLOOKUP(C49,'Liste chauffeur'!$B$5:$L$18,2,TRUE)&" "&VLOOKUP(C49,'Liste chauffeur'!$B$5:$L$18,3,TRUE) -> AHAMADI Laydine | F49: =COUNTBLANK(E49) -> 1 | Y49: =IF(F49=1,"",W49-E49) | Z49: =H49+J49-I49 -> 0 | AA49: =IF(F49=1,0,AA$6) -> 0 | AB49: =IF(AA49=0,0,Z49/AA49) -> 0
A50: ='Horaire dimanche 1'!A49 -> PASSOT LA BARGE | B50: ='Horaire dimanche 1'!B49 -> 0.77083333 | C50: ='Horaire dimanche 1'!C49 -> D14 | D50: =VLOOKUP(C50,'Liste chauffeur'!$B$5:$L$18,2,TRUE)&" "&VLOOKUP(C50,'Liste chauffeur'!$B$5:$L$18,3,TRUE) -> AHAMADI Laydine | F50: =COUNTBLANK(E50) -> 1 | Y50: =IF(F50=1,"",W50-E50) | Z50: =H50+J50-I50 -> 0 | AA50: =IF(F50=1,0,AA$6) -> 0 | AB50: =IF(AA50=0,0,Z50/AA50) -> 0
A51: ='Horaire dimanche 1'!A50 -> DOUJANI | B51: ='Horaire dimanche 1'!B50 -> 0.77083333 | C51: ='Horaire dimanche 1'!C50 -> D13 | D51: =VLOOKUP(C51,'Liste chauffeur'!$B$5:$L$18,2,TRUE)&" "&VLOOKUP(C51,'Liste chauffeur'!$B$5:$L$18,3,TRUE) -> MOURIDI Aktoir | F51: =COUNTBLANK(E51) -> 1 | Y51: =IF(F51=1,"",W51-E51) | Z51: =H51+J51-I51 -> 0 | AA51: =IF(F51=1,0,AA$6) -> 0 | AB51: =IF(AA51=0,0,Z51/AA51) -> 0
A52: ='Horaire dimanche 1'!A51 -> PASSOT LA BARGE | B52: ='Horaire dimanche 1'!B51 -> 0.79166667 | C52: ='Horaire dimanche 1'!C51 -> D13 | D52: =VLOOKUP(C52,'Liste chauffeur'!$B$5:$L$18,2,TRUE)&" "&VLOOKUP(C52,'Liste chauffeur'!$B$5:$L$18,3,TRUE) -> MOURIDI Aktoir | F52: =COUNTBLANK(E52) -> 1 | Y52: =IF(F52=1,"",W52-E52) | Z52: =H52+J52-I52 -> 0 | AA52: =IF(F52=1,0,AA$6) -> 0 | AB52: =IF(AA52=0,0,Z52/AA52) -> 0
B53: ST2 | C53: ST | F53: =SUM(F26:F52) -> 27 | G53: =SUM(G26:G52) -> 0 | Y53: =AVERAGE(Y26:Y52) -> #DIV/0! | Z53: =SUM(Z26:Z52) -> 0 | AA53: =SUM(AA26:AA52) -> 0 | AB53: =IF(AA53=0,0,Z53/AA53) -> 0
B54: ST3 | C54: ST | F54: =F25+F53 -> 44 | G54: =G25+G53 -> 0 | Y54: =AVERAGE(Y8:Y24,Y26:Y52) -> #DIV/0! | Z54: =Z25+Z53 -> 0 | AA54: =AA25+AA53 -> 0 | AB54: =IF(AA54=0,0,Z54/AA54) -> 0
A55: REMPLACEMENT | C55: D
A56: REMPLACEMENT | C56: D
A57: REMPLACEMENT | C57: D | O57: =M57-#REF! -> #REF! | P57: =#REF!+#REF!-#REF! -> #REF!
A58: REMPLACEMENT | C58: D | O58: =M58-#REF! -> #REF! | P58: =#REF!+#REF!-#REF! -> #REF!
E60: Signature Chauffeur | I60: Signature Coordinateur
B63: Statistiques | C63: nbre de trajets planifiés | D63: Nbre trajets non effectués | E63: Nbre trajets effectués non planifiés | F63: Nbre trajets dont départ > 10 minutes en retard
B64: D1 | C64: =COUNTIF($B$8:$C$52,B64) -> 0 | D64: =C64-(COUNTIFS(C$8:C$52,B64,X$8:X$52,"")) -> 0 | E64: =COUNTIFS(X$8:X$52,$B64) -> 0 | F64: =COUNTIFS(G$8:G$52,$B64) -> 0
B65: D2 | C65: =COUNTIF($B$8:$C$52,B65) -> 0 | D65: =C65-(COUNTIFS(C$8:C$52,B65,X$8:X$52,"")) -> 0 | E65: =COUNTIFS(X$8:X$52,$B65) -> 0 | F65: =COUNTIFS(G$8:G$52,$B65) -> 0
B66: D3 | C66: =COUNTIF($B$8:$C$52,B66) -> 0 | D66: =C66-(COUNTIFS(C$8:C$52,B66,X$8:X$52,"")) -> 0 | E66: =COUNTIFS(X$8:X$52,$B66) -> 0 | F66: =COUNTIFS(G$8:G$52,$B66) -> 0
B67: D4 | C67: =COUNTIF($B$8:$C$52,B67) -> 0 | D67: =C67-(COUNTIFS(C$8:C$52,B67,X$8:X$52,"")) -> 0 | E67: =COUNTIFS(X$8:X$52,$B67) -> 0 | F67: =COUNTIFS(G$8:G$52,$B67) -> 0
B68: D5 | C68: =COUNTIF($B$8:$C$52,B68) -> 0 | D68: =C68-(COUNTIFS(C$8:C$52,B68,X$8:X$52,"")) -> 0 | E68: =COUNTIFS(X$8:X$52,$B68) -> 0 | F68: =COUNTIFS(G$8:G$52,$B68) -> 0
B69: D6 | C69: =COUNTIF($B$8:$C$52,B69) -> 0 | D69: =C69-(COUNTIFS(C$8:C$52,B69,X$8:X$52,"")) -> 0 | E69: =COUNTIFS(X$8:X$52,$B69) -> 0 | F69: =COUNTIFS(G$8:G$52,$B69) -> 0
B70: D7 | C70: =COUNTIF($B$8:$C$52,B70) -> 11 | D70: =C70-(COUNTIFS(C$8:C$52,B70,X$8:X$52,"")) -> 0 | E70: =COUNTIFS(X$8:X$52,$B70) -> 0 | F70: =COUNTIFS(G$8:G$52,$B70) -> 0
B71: D8 | C71: =COUNTIF($B$8:$C$52,B71) -> 0 | D71: =C71-(COUNTIFS(C$8:C$52,B71,X$8:X$52,"")) -> 0 | E71: =COUNTIFS(X$8:X$52,$B71) -> 0 | F71: =COUNTIFS(G$8:G$52,$B71) -> 0
B72: D9 | C72: =COUNTIF($B$8:$C$52,B72) -> 0 | D72: =C72-(COUNTIFS(C$8:C$52,B72,X$8:X$52,"")) -> 0 | E72: =COUNTIFS(X$8:X$52,$B72) -> 0 | F72: =COUNTIFS(G$8:G$52,$B72) -> 0
B73: D10 | C73: =COUNTIF($B$8:$C$52,B73) -> 0 | D73: =C73-(COUNTIFS(C$8:C$52,B73,X$8:X$52,"")) -> 0 | E73: =COUNTIFS(X$8:X$52,$B73) -> 0 | F73: =COUNTIFS(G$8:G$52,$B73) -> 0
B74: D11 | C74: =COUNTIF($B$8:$C$52,B74) -> 0 | D74: =C74-(COUNTIFS(C$8:C$52,B74,X$8:X$52,"")) -> 0 | E74: =COUNTIFS(X$8:X$52,$B74) -> 0 | F74: =COUNTIFS(G$8:G$52,$B74) -> 0
B75: D12 | C75: =COUNTIF($B$8:$C$52,B75) -> 11 | D75: =C75-(COUNTIFS(C$8:C$52,B75,X$8:X$52,"")) -> 0 | E75: =COUNTIFS(X$8:X$52,$B75) -> 0 | F75: =COUNTIFS(G$8:G$52,$B75) -> 0
... B86: D23 | C86: =COUNTIF($B$8:$C$52,B86) -> 0 | D86: =C86-(COUNTIFS(C$8:C$52,B86,X$8:X$52,"")) -> 0 | E86: =COUNTIFS(X$8:X$52,$B86) -> 0 | F86: =COUNTIFS(G$8:G$52,$B86) -> 0
C87: =SUM(C64:C86) -> 44 | D87: =SUM(D64:D86) -> 0 | E87: =SUM(E64:E86) -> 0 | F87: =SUM(F64:F86) -> 0
E88: =D87-E87 -> 0 | F88: =IF(E88=F87,"OK","ERREUR") -> OK

Sheet Feuille saisie dimanche 2
A2: TYPE | B2: D14
A3: DATE | B3: 45627
A4: CHAUFFEUR | B4: =VLOOKUP(B2,'Liste chauffeur'!$B$5:$L$18,2,TRUE)&" "&VLOOKUP(B2,'Liste chauffeur'!$B$5:$L$18,3,TRUE) -> AHAMADI Laydine
I6: Arrêt 1 | M6: Arrêt 2 | Q6: Arrêt 3 | W6: ARRIVEE | AA6: 8
B7: Heure théorique départ | C7: Horaire | D7: Chauffeur | E7: Heure réelle départ | F7: Trajet non effectué | G7: Départ avec plus de 10 mns retard | H7: Nbre personnes montée | I7: - | J7: + | K7: Heure arrivée arrêt 1 | L7: Délai | M7: - | N7: + | O7: Heure arrivée arrêt 2 | P7: Délai | Q7: - | R7: + | S7: Heure arrivée arrêt 3 | T7: Délai | U7: Nbre personnes descente | W7: Heure arrivée finale | X7: Commentaires | Y7: Temps Aller | Z7: Nbre personnes moyenne | AA7: Capacité max | AB7: Taux Fréquentation
A8: ='Horaire dimanche 2'!A8 -> DOUJANI | B8: ='Horaire dimanche 2'!B8 -> 0.33333333 | C8: ='Horaire dimanche 2'!C8 -> D12 | D8: =VLOOKUP(C8,'Liste chauffeur'!$B$5:$L$18,2,TRUE)&" "&VLOOKUP(C8,'Liste chauffeur'!$B$5:$L$18,3,TRUE) -> VELOU M'COLO M'Berou | F8: =COUNTBLANK(E8) -> 1 | Y8: =IF(F8=1,"",W8-E8) | Z8: =H8+J8-I8 -> 0 | AA8: =IF(F8=1,0,AA$6) -> 0 | AB8: =IF(AA8=0,0,Z8/AA8) -> 0
A9: ='Horaire dimanche 2'!A9 -> PASSOT LA BARGE | B9: ='Horaire dimanche 2'!B9 -> 0.35416667 | C9: ='Horaire dimanche 2'!C9 -> D12 | D9: =VLOOKUP(C9,'Liste chauffeur'!$B$5:$L$18,2,TRUE)&" "&VLOOKUP(C9,'Liste chauffeur'!$B$5:$L$18,3,TRUE) -> VELOU M'COLO M'Berou | F9: =COUNTBLANK(E9) -> 1 | Y9: =IF(F9=1,"",W9-E9) | Z9: =H9+J9-I9 -> 0 | AA9: =IF(F9=1,0,AA$6) -> 0 | AB9: =IF(AA9=0,0,Z9/AA9) -> 0
A10: ='Horaire dimanche 2'!A10 -> DOUJANI | B10: ='Horaire dimanche 2'!B10 -> 0.35416667 | C10: ='Horaire dimanche 2'!C10 -> D7 | D10: =VLOOKUP(C10,'Liste chauffeur'!$B$5:$L$18,2,TRUE)&" "&VLOOKUP(C10,'Liste chauffeur'!$B$5:$L$18,3,TRUE) -> COMBO Said | F10: =COUNTBLANK(E10) -> 1 | Y10: =IF(F10=1,"",W10-E10) | Z10: =H10+J10-I10 -> 0 | AA10: =IF(F10=1,0,AA$6) -> 0 | AB10: =IF(AA10=0,0,Z10/AA10) -> 0
A11: ='Horaire dimanche 2'!A11 -> PASSOT LA BARGE | B11: ='Horaire dimanche 2'!B11 -> 0.375 | C11: ='Horaire dimanche 2'!C11 -> D7 | D11: =VLOOKUP(C11,'Liste chauffeur'!$B$5:$L$18,2,TRUE)&" "&VLOOKUP(C11,'Liste chauffeur'!$B$5:$L$18,3,TRUE) -> COMBO Said | F11: =COUNTBLANK(E11) -> 1 | Y11: =IF(F11=1,"",W11-E11) | Z11: =H11+J11-I11 -> 0 | AA11: =IF(F11=1,0,AA$6) -> 0 | AB11: =IF(AA11=0,0,Z11/AA11) -> 0
A12: ='Horaire dimanche 2'!A12 -> DOUJANI | B12: ='Horaire dimanche 2'!B12 -> 0.375 | C12: ='Horaire dimanche 2'!C12 -> D12 | D12: =VLOOKUP(C12,'Liste chauffeur'!$B$5:$L$18,2,TRUE)&" "&VLOOKUP(C12,'Liste chauffeur'!$B$5:$L$18,3,TRUE) -> VELOU M'COLO M'Berou | F12: =COUNTBLANK(E12) -> 1 | L12: =K12-E12 -> 0 | P12: =O12-K12 -> 0 | T12: =S12-O12 -> 0 | V12: =IF(H12-I12+J12-M12+N12-Q12+R12=U12,"OK",H12-I12+J12-M12+N12-Q12+R12-U12) -> OK | Y12: =IF(F12=1,"",W12-E12) | Z12: =H12+J12-I12 -> 0 | AA12: =IF(F12=1,0,AA$6) -> 0 | AB12: =IF(AA12=0,0,Z12/AA12) -> 0
A13: ='Horaire dimanche 2'!A13 -> PASSOT LA BARGE | B13: ='Horaire dimanche 2'!B13 -> 0.39583333 | C13: ='Horaire dimanche 2'!C13 -> D12 | D13: =VLOOKUP(C13,'Liste chauffeur'!$B$5:$L$18,2,TRUE)&" "&VLOOKUP(C13,'Liste chauffeur'!$B$5:$L$18,3,TRUE) -> VELOU M'COLO M'Berou | F13: =COUNTBLANK(E13) -> 1 | L13: =K13-E13 -> 0 | P13: =O13-K13 -> 0 | T13: =S13-O13 -> 0 | Y13: =IF(F13=1,"",W13-E13) | Z13: =H13+J13-I13 -> 0 | AA13: =IF(F13=1,0,AA$6) -> 0 | AB13: =IF(AA13=0,0,Z13/AA13) -> 0
A14: ='Horaire dimanche 2'!A14 -> DOUJANI | B14: ='Horaire dimanche 2'!B14 -> 0.39583333 | C14: ='Horaire dimanche 2'!C14 -> D7 | D14: =VLOOKUP(C14,'Liste chauffeur'!$B$5:$L$18,2,TRUE)&" "&VLOOKUP(C14,'Liste chauffeur'!$B$5:$L$18,3,TRUE) -> COMBO Said | F14: =COUNTBLANK(E14) -> 1 | L14: =K14-E14 -> 0 | P14: =O14-K14 -> 0 | T14: =S14-O14 -> 0 | Y14: =IF(F14=1,"",W14-E14) | Z14: =H14+J14-I14 -> 0 | AA14: =IF(F14=1,0,AA$6) -> 0 | AB14: =IF(AA14=0,0,Z14/AA14) -> 0
A15: ='Horaire dimanche 2'!A15 -> PASSOT LA BARGE | B15: ='Horaire dimanche 2'!B15 -> 0.41666667 | C15: ='Horaire dimanche 2'!C15 -> D7 | D15: =VLOOKUP(C15,'Liste chauffeur'!$B$5:$L$18,2,TRUE)&" "&VLOOKUP(C15,'Liste chauffeur'!$B$5:$L$18,3,TRUE) -> COMBO Said | F15: =COUNTBLANK(E15) -> 1 | L15: =K15-E15 -> 0 | P15: =O15-K15 -> 0 | T15: =S15-O15 -> 0 | Y15: =IF(F15=1,"",W15-E15) | Z15: =H15+J15-I15 -> 0 | AA15: =IF(F15=1,0,AA$6) -> 0 | AB15: =IF(AA15=0,0,Z15/AA15) -> 0
A16: ='Horaire dimanche 2'!A16 -> DOUJANI | B16: ='Horaire dimanche 2'!B16 -> 0.41666667 | C16: ='Horaire dimanche 2'!C16 -> D12 | D16: =VLOOKUP(C16,'Liste chauffeur'!$B$5:$L$18,2,TRUE)&" "&VLOOKUP(C16,'Liste chauffeur'!$B$5:$L$18,3,TRUE) -> VELOU M'COLO M'Berou | F16: =COUNTBLANK(E16) -> 1 | L16: =K16-E16 -> 0 | P16: =O16-K16 -> 0 | T16: =S16-O16 -> 0 | V16: =IF(H16-I16+J16-M16+N16-Q16+R16=U16,"OK",H16-I16+J16-M16+N16-Q16+R16-U16) -> OK | Y16: =IF(F16=1,"",W16-E16) | Z16: =H16+J16-I16 -> 0 | AA16: =IF(F16=1,0,AA$6) -> 0 | AB16: =IF(AA16=0,0,Z16/AA16) -> 0
A17: ='Horaire dimanche 2'!A17 -> PASSOT LA BARGE | B17: ='Horaire dimanche 2'!B17 -> 0.4375 | C17: ='Horaire dimanche 2'!C17 -> D12 | D17: =VLOOKUP(C17,'Liste chauffeur'!$B$5:$L$18,2,TRUE)&" "&VLOOKUP(C17,'Liste chauffeur'!$B$5:$L$18,3,TRUE) -> VELOU M'COLO M'Berou | F17: =COUNTBLANK(E17) -> 1 | L17: =K17-E17 -> 0 | P17: =O17-K17 -> 0 | T17: =S17-O17 -> 0 | V17: =IF(H17-I17+J17-M17+N17-Q17+R17=U17,"OK",H17-I17+J17-M17+N17-Q17+R17-U17) -> OK | Y17: =IF(F17=1,"",W17-E17) | Z17: =H17+J17-I17 -> 0 | AA17: =IF(F17=1,0,AA$6) -> 0 | AB17: =IF(AA17=0,0,Z17/AA17) -> 0
A18: ='Horaire dimanche 2'!A18 -> DOUJANI | B18: ='Horaire dimanche 2'!B18 -> 0.4375 | C18: ='Horaire dimanche 2'!C18 -> D7 | D18: =VLOOKUP(C18,'Liste chauffeur'!$B$5:$L$18,2,TRUE)&" "&VLOOKUP(C18,'Liste chauffeur'!$B$5:$L$18,3,TRUE) -> COMBO Said | F18: =COUNTBLANK(E18) -> 1 | Z18: =H18+J18-I18 -> 0 | AA18: =IF(F18=1,0,AA$6) -> 0 | AB18: =IF(AA18=0,0,Z18/AA18) -> 0
A19: ='Horaire dimanche 2'!A19 -> PASSOT LA BARGE | B19: ='Horaire dimanche 2'!B19 -> 0.45833333 | C19: ='Horaire dimanche 2'!C19 -> D7 | D19: =VLOOKUP(C19,'Liste chauffeur'!$B$5:$L$18,2,TRUE)&" "&VLOOKUP(C19,'Liste chauffeur'!$B$5:$L$18,3,TRUE) -> COMBO Said | F19: =COUNTBLANK(E19) -> 1 | L19: =K19-E19 -> 0 | P19: =O19-K19 -> 0 | T19: =S19-O19 -> 0 | V19: =IF(H19-I19+J19-M19+N19-Q19+R19=U19,"OK",H19-I19+J19-M19+N19-Q19+R19-U19) -> OK | Y19: =IF(F19=1,"",W19-E19) | Z19: =H19+J19-I19 -> 0 | AA19: =IF(F19=1,0,AA$6) -> 0 | AB19: =IF(AA19=0,0,Z19/AA19) -> 0
A20: ='Horaire dimanche 2'!A20 -> DOUJANI | B20: ='Horaire dimanche 2'!B20 -> 0.45833333 | C20: ='Horaire dimanche 2'!C20 -> D12 | D20: =VLOOKUP(C20,'Liste chauffeur'!$B$5:$L$18,2,TRUE)&" "&VLOOKUP(C20,'Liste chauffeur'!$B$5:$L$18,3,TRUE) -> VELOU M'COLO M'Berou | F20: =COUNTBLANK(E20) -> 1 | L20: =K20-E20 -> 0 | P20: =O20-K20 -> 0 | T20: =S20-O20 -> 0 | V20: =IF(H20-I20+J20-M20+N20-Q20+R20=U20,"OK",H20-I20+J20-M20+N20-Q20+R20-U20) -> OK | Y20: =IF(F20=1,"",W20-E20) | Z20: =H20+J20-I20 -> 0 | AA20: =IF(F20=1,0,AA$6) -> 0 | AB20: =IF(AA20=0,0,Z20/AA20) -> 0
A21: ='Horaire dimanche 2'!A21 -> PASSOT LA BARGE | B21: ='Horaire dimanche 2'!B21 -> 0.47916667 | C21: ='Horaire dimanche 2'!C21 -> D12 | D21: =VLOOKUP(C21,'Liste chauffeur'!$B$5:$L$18,2,TRUE)&" "&VLOOKUP(C21,'Liste chauffeur'!$B$5:$L$18,3,TRUE) -> VELOU M'COLO M'Berou | F21: =COUNTBLANK(E21) -> 1 | L21: =K21-E21 -> 0 | P21: =O21-K21 -> 0 | T21: =S21-O21 -> 0 | V21: =IF(H21-I21+J21-M21+N21-Q21+R21=U21,"OK",H21-I21+J21-M21+N21-Q21+R21-U21) -> OK | Y21: =IF(F21=1,"",W21-E21) | Z21: =H21+J21-I21 -> 0 | AA21: =IF(F21=1,0,AA$6) -> 0 | AB21: =IF(AA21=0,0,Z21/AA21) -> 0
A22: ='Horaire dimanche 2'!A22 -> DOUJANI | B22: ='Horaire dimanche 2'!B22 -> 0.47916667 | C22: ='Horaire dimanche 2'!C22 -> D7 | D22: =VLOOKUP(C22,'Liste chauffeur'!$B$5:$L$18,2,TRUE)&" "&VLOOKUP(C22,'Liste chauffeur'!$B$5:$L$18,3,TRUE) -> COMBO Said | F22: =COUNTBLANK(E22) -> 1 | L22: =K22-E22 -> 0 | P22: =O22-K22 -> 0 | T22: =S22-O22 -> 0 | V22: =IF(H22-I22+J22-M22+N22-Q22+R22=U22,"OK",H22-I22+J22-M22+N22-Q22+R22-U22) -> OK | Y22: =IF(F22=1,"",W22-E22) | Z22: =H22+J22-I22 -> 0 | AA22: =IF(F22=1,0,AA$6) -> 0 | AB22: =IF(AA22=0,0,Z22/AA22) -> 0
A23: ='Horaire dimanche 2'!A23 -> PASSOT LA BARGE | B23: ='Horaire dimanche 2'!B23 -> 0.5 | C23: ='Horaire dimanche 2'!C23 -> D7 | D23: =VLOOKUP(C23,'Liste chauffeur'!$B$5:$L$18,2,TRUE)&" "&VLOOKUP(C23,'Liste chauffeur'!$B$5:$L$18,3,TRUE) -> COMBO Said | F23: =COUNTBLANK(E23) -> 1 | L23: =K23-E23 -> 0 | P23: =O23-K23 -> 0 | T23: =S23-O23 -> 0 | V23: =IF(H23-I23+J23-M23+N23-Q23+R23=U23,"OK",H23-I23+J23-M23+N23-Q23+R23-U23) -> OK | Y23: =IF(F23=1,"",W23-E23) | Z23: =H23+J23-I23 -> 0 | AA23: =IF(F23=1,0,AA$6) -> 0 | AB23: =IF(AA23=0,0,Z23/AA23) -> 0
A24: ='Horaire dimanche 2'!A24 -> DOUJANI | B24: ='Horaire dimanche 2'!B24 -> 0.5 | C24: ='Horaire dimanche 2'!C24 -> D12 | D24: =VLOOKUP(C24,'Liste chauffeur'!$B$5:$L$18,2,TRUE)&" "&VLOOKUP(C24,'Liste chauffeur'!$B$5:$L$18,3,TRUE) -> VELOU M'COLO M'Berou | F24: =COUNTBLANK(E24) -> 1 | L24: =K24-E24 -> 0 | P24: =O24-K24 -> 0 | T24: =S24-O24 -> 0 | V24: =IF(H24-I24+J24-M24+N24-Q24+R24=U24,"OK",H24-I24+J24-M24+N24-Q24+R24-U24) -> OK | Y24: =IF(F24=1,"",W24-E24) | Z24: =H24+J24-I24 -> 0 | AA24: =IF(F24=1,0,AA$6) -> 0 | AB24: =IF(AA24=0,0,Z24/AA24) -> 0
B25: ST1 | F25: =SUM(F8:F24) -> 17 | G25: =SUM(G8:G24) -> 0 | Y25: =AVERAGE(Y8:Y24) -> #DIV/0! | Z25: =SUM(Z8:Z24) -> 0 | AA25: =SUM(AA8:AA24) -> 0 | AB25: =IF(AA25=0,0,Z25/AA25) -> 0
A26: ='Horaire dimanche 2'!A25 -> PASSOT LA BARGE | B26: ='Horaire dimanche 2'!B25 -> 0.52083333 | C26: ='Horaire dimanche 2'!C25 -> D12 | D26: =VLOOKUP(C26,'Liste chauffeur'!$B$5:$L$18,2,TRUE)&" "&VLOOKUP(C26,'Liste chauffeur'!$B$5:$L$18,3,TRUE) -> VELOU M'COLO M'Berou | F26: =COUNTBLANK(E26) -> 1 | Z26: =H26+J26-I26 -> 0 | AA26: =IF(F26=1,0,AA$6) -> 0 | AB26: =IF(AA26=0,0,Z26/AA26) -> 0
A27: ='Horaire dimanche 2'!A26 -> DOUJANI | B27: ='Horaire dimanche 2'!B26 -> 0.52083333 | C27: ='Horaire dimanche 2'!C26 -> D7 | D27: =VLOOKUP(C27,'Liste chauffeur'!$B$5:$L$18,2,TRUE)&" "&VLOOKUP(C27,'Liste chauffeur'!$B$5:$L$18,3,TRUE) -> COMBO Said | F27: =COUNTBLANK(E27) -> 1 | L27: =K27-E27 -> 0 | P27: =O27-K27 -> 0 | T27: =S27-O27 -> 0 | V27: =IF(H27-I27+J27-M27+N27-Q27+R27=U27,"OK",H27-I27+J27-M27+N27-Q27+R27-U27) -> OK | Y27: =IF(F27=1,"",W27-E27) | Z27: =H27+J27-I27 -> 0 | AA27: =IF(F27=1,0,AA$6) -> 0 | AB27: =IF(AA27=0,0,Z27/AA27) -> 0
A28: ='Horaire dimanche 2'!A27 -> PASSOT LA BARGE | B28: ='Horaire dimanche 2'!B27 -> 0.54166667 | C28: ='Horaire dimanche 2'!C27 -> D7 | D28: =VLOOKUP(C28,'Liste chauffeur'!$B$5:$L$18,2,TRUE)&" "&VLOOKUP(C28,'Liste chauffeur'!$B$5:$L$18,3,TRUE) -> COMBO Said | F28: =COUNTBLANK(E28) -> 1 | L28: =K28-E28 -> 0 | P28: =O28-K28 -> 0 | T28: =S28-O28 -> 0 | V28: =IF(H28-I28+J28-M28+N28-Q28+R28=U28,"OK",H28-I28+J28-M28+N28-Q28+R28-U28) -> OK | Y28: =IF(F28=1,"",W28-E28) | Z28: =H28+J28-I28 -> 0 | AA28: =IF(F28=1,0,AA$6) -> 0 | AB28: =IF(AA28=0,0,Z28/AA28) -> 0
A29: ='Horaire dimanche 2'!A28 -> DOUJANI | B29: ='Horaire dimanche 2'!B28 -> 0.54166667 | C29: ='Horaire dimanche 2'!C28 -> D12 | D29: =VLOOKUP(C29,'Liste chauffeur'!$B$5:$L$18,2,TRUE)&" "&VLOOKUP(C29,'Liste chauffeur'!$B$5:$L$18,3,TRUE) -> VELOU M'COLO M'Berou | F29: =COUNTBLANK(E29) -> 1 | L29: =K29-E29 -> 0 | P29: =O29-K29 -> 0 | T29: =S29-O29 -> 0 | V29: =IF(H29-I29+J29-M29+N29-Q29+R29=U29,"OK",H29-I29+J29-M29+N29-Q29+R29-U29) -> OK | Y29: =IF(F29=1,"",W29-E29) | Z29: =H29+J29-I29 -> 0 | AA29: =IF(F29=1,0,AA$6) -> 0 | AB29: =IF(AA29=0,0,Z29/AA29) -> 0
A30: ='Horaire dimanche 2'!A29 -> PASSOT LA BARGE | B30: ='Horaire dimanche 2'!B29 -> 0.5625 | C30: ='Horaire dimanche 2'!C29 -> D14 | D30: =VLOOKUP(C30,'Liste chauffeur'!$B$5:$L$18,2,TRUE)&" "&VLOOKUP(C30,'Liste chauffeur'!$B$5:$L$18,3,TRUE) -> AHAMADI Laydine | F30: =COUNTBLANK(E30) -> 1 | L30: =K30-E30 -> 0 | P30: =O30-K30 -> 0 | T30: =S30-O30 -> 0 | V30: =IF(H30-I30+J30-M30+N30-Q30+R30=U30,"OK",H30-I30+J30-M30+N30-Q30+R30-U30) -> OK | Y30: =IF(F30=1,"",W30-E30) | Z30: =H30+J30-I30 -> 0 | AA30: =IF(F30=1,0,AA$6) -> 0 | AB30: =IF(AA30=0,0,Z30/AA30) -> 0
A31: ='Horaire dimanche 2'!A30 -> DOUJANI | B31: ='Horaire dimanche 2'!B30 -> 0.5625 | C31: ='Horaire dimanche 2'!C30 -> D7 | D31: =VLOOKUP(C31,'Liste chauffeur'!$B$5:$L$18,2,TRUE)&" "&VLOOKUP(C31,'Liste chauffeur'!$B$5:$L$18,3,TRUE) -> COMBO Said | F31: =COUNTBLANK(E31) -> 1 | L31: =K31-E31 -> 0 | P31: =O31-K31 -> 0 | T31: =S31-O31 -> 0 | V31: =IF(H31-I31+J31-M31+N31-Q31+R31=U31,"OK",H31-I31+J31-M31+N31-Q31+R31-U31) -> OK | Y31: =IF(F31=1,"",W31-E31) | Z31: =H31+J31-I31 -> 0 | AA31: =IF(F31=1,0,AA$6) -> 0 | AB31: =IF(AA31=0,0,Z31/AA31) -> 0
A32: ='Horaire dimanche 2'!A31 -> PASSOT LA BARGE | B32: ='Horaire dimanche 2'!B31 -> 0.58333333 | C32: ='Horaire dimanche 2'!C31 -> D8 | D32: =VLOOKUP(C32,'Liste chauffeur'!$B$5:$L$18,2,TRUE)&" "&VLOOKUP(C32,'Liste chauffeur'!$B$5:$L$18,3,TRUE) -> ISSOUF Dailami | F32: =COUNTBLANK(E32) -> 1 | L32: =K32-E32 -> 0 | P32: =O32-K32 -> 0 | T32: =S32-O32 -> 0 | V32: =IF(H32-I32+J32-M32+N32-Q32+R32=U32,"OK",H32-I32+J32-M32+N32-Q32+R32-U32) -> OK | Y32: =IF(F32=1,"",W32-E32) | Z32: =H32+J32-I32 -> 0 | AA32: =IF(F32=1,0,AA$6) -> 0 | AB32: =IF(AA32=0,0,Z32/AA32) -> 0
A33: ='Horaire dimanche 2'!A32 -> DOUJANI | B33: ='Horaire dimanche 2'!B32 -> 0.58333333 | C33: ='Horaire dimanche 2'!C32 -> D14 | D33: =VLOOKUP(C33,'Liste chauffeur'!$B$5:$L$18,2,TRUE)&" "&VLOOKUP(C33,'Liste chauffeur'!$B$5:$L$18,3,TRUE) -> AHAMADI Laydine | F33: =COUNTBLANK(E33) -> 1 | Z33: =H33+J33-I33 -> 0 | AA33: =IF(F33=1,0,AA$6) -> 0 | AB33: =IF(AA33=0,0,Z33/AA33) -> 0
A34: ='Horaire dimanche 2'!A33 -> PASSOT LA BARGE | B34: ='Horaire dimanche 2'!B33 -> 0.60416667 | C34: ='Horaire dimanche 2'!C33 -> D14 | D34: =VLOOKUP(C34,'Liste chauffeur'!$B$5:$L$18,2,TRUE)&" "&VLOOKUP(C34,'Liste chauffeur'!$B$5:$L$18,3,TRUE) -> AHAMADI Laydine | F34: =COUNTBLANK(E34) -> 1 | L34: =K34-E34 -> 0 | P34: =O34-K34 -> 0 | T34: =S34-O34 -> 0 | V34: =IF(H34-I34+J34-M34+N34-Q34+R34=U34,"OK",H34-I34+J34-M34+N34-Q34+R34-U34) -> OK | Y34: =IF(F34=1,"",W34-E34) | Z34: =H34+J34-I34 -> 0 | AA34: =IF(F34=1,0,AA$6) -> 0 | AB34: =IF(AA34=0,0,Z34/AA34) -> 0
A35: ='Horaire dimanche 2'!A34 -> DOUJANI | B35: ='Horaire dimanche 2'!B34 -> 0.60416667 | C35: ='Horaire dimanche 2'!C34 -> D8 | D35: =VLOOKUP(C35,'Liste chauffeur'!$B$5:$L$18,2,TRUE)&" "&VLOOKUP(C35,'Liste chauffeur'!$B$5:$L$18,3,TRUE) -> ISSOUF Dailami | F35: =COUNTBLANK(E35) -> 1 | L35: =K35-E35 -> 0 | V35: =IF(H35-I35+J35-M35+N35-Q35+R35=U35,"OK",H35-I35+J35-M35+N35-Q35+R35-U35) -> OK | Y35: =IF(F35=1,"",W35-E35) | Z35: =H35+J35-I35 -> 0 | AA35: =IF(F35=1,0,AA$6) -> 0 | AB35: =IF(AA35=0,0,Z35/AA35) -> 0
A36: ='Horaire dimanche 2'!A35 -> PASSOT LA BARGE | B36: ='Horaire dimanche 2'!B35 -> 0.625 | C36: ='Horaire dimanche 2'!C35 -> D8 | D36: =VLOOKUP(C36,'Liste chauffeur'!$B$5:$L$18,2,TRUE)&" "&VLOOKUP(C36,'Liste chauffeur'!$B$5:$L$18,3,TRUE) -> ISSOUF Dailami | F36: =COUNTBLANK(E36) -> 1 | L36: =K36-E36 -> 0 | V36: =IF(H36-I36+J36-M36+N36-Q36+R36=U36,"OK",H36-I36+J36-M36+N36-Q36+R36-U36) -> OK | Y36: =IF(F36=1,"",W36-E36) | Z36: =H36+J36-I36 -> 0 | AA36: =IF(F36=1,0,AA$6) -> 0 | AB36: =IF(AA36=0,0,Z36/AA36) -> 0
A37: ='Horaire dimanche 2'!A36 -> DOUJANI | B37: ='Horaire dimanche 2'!B36 -> 0.625 | C37: ='Horaire dimanche 2'!C36 -> D14 | D37: =VLOOKUP(C37,'Liste chauffeur'!$B$5:$L$18,2,TRUE)&" "&VLOOKUP(C37,'Liste chauffeur'!$B$5:$L$18,3,TRUE) -> AHAMADI Laydine | F37: =COUNTBLANK(E37) -> 1 | L37: =K37-E37 -> 0 | V37: =IF(H37-I37+J37-M37+N37-Q37+R37=U37,"OK",H37-I37+J37-M37+N37-Q37+R37-U37) -> OK | Y37: =IF(F37=1,"",W37-E37) | Z37: =H37+J37-I37 -> 0 | AA37: =IF(F37=1,0,AA$6) -> 0 | AB37: =IF(AA37=0,0,Z37/AA37) -> 0
A38: ='Horaire dimanche 2'!A37 -> PASSOT LA BARGE | B38: ='Horaire dimanche 2'!B37 -> 0.64583333 | C38: ='Horaire dimanche 2'!C37 -> D14 | D38: =VLOOKUP(C38,'Liste chauffeur'!$B$5:$L$18,2,TRUE)&" "&VLOOKUP(C38,'Liste chauffeur'!$B$5:$L$18,3,TRUE) -> AHAMADI Laydine | F38: =COUNTBLANK(E38) -> 1 | L38: =K38-E38 -> 0 | V38: =IF(H38-I38+J38-M38+N38-Q38+R38=U38,"OK",H38-I38+J38-M38+N38-Q38+R38-U38) -> OK | Y38: =IF(F38=1,"",W38-E38) | Z38: =H38+J38-I38 -> 0 | AA38: =IF(F38=1,0,AA$6) -> 0 | AB38: =IF(AA38=0,0,Z38/AA38) -> 0
A39: ='Horaire dimanche 2'!A38 -> DOUJANI | B39: ='Horaire dimanche 2'!B38 -> 0.64583333 | C39: ='Horaire dimanche 2'!C38 -> D8 | D39: =VLOOKUP(C39,'Liste chauffeur'!$B$5:$L$18,2,TRUE)&" "&VLOOKUP(C39,'Liste chauffeur'!$B$5:$L$18,3,TRUE) -> ISSOUF Dailami | F39: =COUNTBLANK(E39) -> 1 | L39: =K39-E39 -> 0 | V39: =IF(H39-I39+J39-M39+N39-Q39+R39=U39,"OK",H39-I39+J39-M39+N39-Q39+R39-U39) -> OK | Y39: =IF(F39=1,"",W39-E39) | Z39: =H39+J39-I39 -> 0 | AA39: =IF(F39=1,0,AA$6) -> 0 | AB39: =IF(AA39=0,0,Z39/AA39) -> 0
A40: ='Horaire dimanche 2'!A39 -> PASSOT LA BARGE | B40: ='Horaire dimanche 2'!B39 -> 0.66666667 | C40: ='Horaire dimanche 2'!C39 -> D8 | D40: =VLOOKUP(C40,'Liste chauffeur'!$B$5:$L$18,2,TRUE)&" "&VLOOKUP(C40,'Liste chauffeur'!$B$5:$L$18,3,TRUE) -> ISSOUF Dailami | F40: =COUNTBLANK(E40) -> 1 | L40: =K40-E40 -> 0 | V40: =IF(H40-I40+J40-M40+N40-Q40+R40=U40,"OK",H40-I40+J40-M40+N40-Q40+R40-U40) -> OK | Y40: =IF(F40=1,"",W40-E40) | Z40: =H40+J40-I40 -> 0 | AA40: =IF(F40=1,0,AA$6) -> 0 | AB40: =IF(AA40=0,0,Z40/AA40) -> 0
A41: ='Horaire dimanche 2'!A40 -> DOUJANI | B41: ='Horaire dimanche 2'!B40 -> 0.66666667 | C41: ='Horaire dimanche 2'!C40 -> D14 | D41: =VLOOKUP(C41,'Liste chauffeur'!$B$5:$L$18,2,TRUE)&" "&VLOOKUP(C41,'Liste chauffeur'!$B$5:$L$18,3,TRUE) -> AHAMADI Laydine | F41: =COUNTBLANK(E41) -> 1 | L41: =K41-E41 -> 0 | V41: =IF(H41-I41+J41-M41+N41-Q41+R41=U41,"OK",H41-I41+J41-M41+N41-Q41+R41-U41) -> OK | Y41: =IF(F41=1,"",W41-E41) | Z41: =H41+J41-I41 -> 0 | AA41: =IF(F41=1,0,AA$6) -> 0 | AB41: =IF(AA41=0,0,Z41/AA41) -> 0
A42: ='Horaire dimanche 2'!A41 -> PASSOT LA BARGE | B42: ='Horaire dimanche 2'!B41 -> 0.6875 | C42: ='Horaire dimanche 2'!C41 -> D14 | D42: =VLOOKUP(C42,'Liste chauffeur'!$B$5:$L$18,2,TRUE)&" "&VLOOKUP(C42,'Liste chauffeur'!$B$5:$L$18,3,TRUE) -> AHAMADI Laydine | F42: =COUNTBLANK(E42) -> 1 | L42: =K42-E42 -> 0 | V42: =IF(H42-I42+J42-M42+N42-Q42+R42=U42,"OK",H42-I42+J42-M42+N42-Q42+R42-U42) -> OK | Y42: =IF(F42=1,"",W42-E42) | Z42: =H42+J42-I42 -> 0 | AA42: =IF(F42=1,0,AA$6) -> 0 | AB42: =IF(AA42=0,0,Z42/AA42) -> 0
A43: ='Horaire dimanche 2'!A42 -> DOUJANI | B43: ='Horaire dimanche 2'!B42 -> 0.6875 | C43: ='Horaire dimanche 2'!C42 -> D8 | D43: =VLOOKUP(C43,'Liste chauffeur'!$B$5:$L$18,2,TRUE)&" "&VLOOKUP(C43,'Liste chauffeur'!$B$5:$L$18,3,TRUE) -> ISSOUF Dailami | F43: =COUNTBLANK(E43) -> 1 | L43: =K43-E43 -> 0 | V43: =IF(H43-I43+J43-M43+N43-Q43+R43=U43,"OK",H43-I43+J43-M43+N43-Q43+R43-U43) -> OK | Y43: =IF(F43=1,"",W43-E43) | Z43: =H43+J43-I43 -> 0 | AA43: =IF(F43=1,0,AA$6) -> 0 | AB43: =IF(AA43=0,0,Z43/AA43) -> 0
A44: ='Horaire dimanche 2'!A43 -> PASSOT LA BARGE | B44: ='Horaire dimanche 2'!B43 -> 0.70833333 | C44: ='Horaire dimanche 2'!C43 -> D8 | D44: =VLOOKUP(C44,'Liste chauffeur'!$B$5:$L$18,2,TRUE)&" "&VLOOKUP(C44,'Liste chauffeur'!$B$5:$L$18,3,TRUE) -> ISSOUF Dailami | F44: =COUNTBLANK(E44) -> 1 | L44: =K44-E44 -> 0 | V44: =IF(H44-I44+J44-M44+N44-Q44+R44=U44,"OK",H44-I44+J44-M44+N44-Q44+R44-U44) -> OK | Y44: =IF(F44=1,"",W44-E44) | Z44: =H44+J44-I44 -> 0 | AA44: =IF(F44=1,0,AA$6) -> 0 | AB44: =IF(AA44=0,0,Z44/AA44) -> 0
A45: ='Horaire dimanche 2'!A44 -> DOUJANI | B45: ='Horaire dimanche 2'!B44 -> 0.70833333 | C45: ='Horaire dimanche 2'!C44 -> D14 | D45: =VLOOKUP(C45,'Liste chauffeur'!$B$5:$L$18,2,TRUE)&" "&VLOOKUP(C45,'Liste chauffeur'!$B$5:$L$18,3,TRUE) -> AHAMADI Laydine | F45: =COUNTBLANK(E45) -> 1 | L45: =K45-E45 -> 0 | V45: =IF(H45-I45+J45-M45+N45-Q45+R45=U45,"OK",H45-I45+J45-M45+N45-Q45+R45-U45) -> OK | Y45: =IF(F45=1,"",W45-E45) | Z45: =H45+J45-I45 -> 0 | AA45: =IF(F45=1,0,AA$6) -> 0 | AB45: =IF(AA45=0,0,Z45/AA45) -> 0
A46: ='Horaire dimanche 2'!A45 -> PASSOT LA BARGE | B46: ='Horaire dimanche 2'!B45 -> 0.72916667 | C46: ='Horaire dimanche 2'!C45 -> D14 | D46: =VLOOKUP(C46,'Liste chauffeur'!$B$5:$L$18,2,TRUE)&" "&VLOOKUP(C46,'Liste chauffeur'!$B$5:$L$18,3,TRUE) -> AHAMADI Laydine | F46: =COUNTBLANK(E46) -> 1 | L46: =K46-E46 -> 0 | V46: =IF(H46-I46+J46-M46+N46-Q46+R46=U46,"OK",H46-I46+J46-M46+N46-Q46+R46-U46) -> OK | Y46: =IF(F46=1,"",W46-E46) | Z46: =H46+J46-I46 -> 0 | AA46: =IF(F46=1,0,AA$6) -> 0 | AB46: =IF(AA46=0,0,Z46/AA46) -> 0
A47: ='Horaire dimanche 2'!A46 -> DOUJANI | B47: ='Horaire dimanche 2'!B46 -> 0.72916667 | C47: ='Horaire dimanche 2'!C46 -> D8 | D47: =VLOOKUP(C47,'Liste chauffeur'!$B$5:$L$18,2,TRUE)&" "&VLOOKUP(C47,'Liste chauffeur'!$B$5:$L$18,3,TRUE) -> ISSOUF Dailami | F47: =COUNTBLANK(E47) -> 1 | L47: =K47-E47 -> 0 | V47: =IF(H47-I47+J47-M47+N47-Q47+R47=U47,"OK",H47-I47+J47-M47+N47-Q47+R47-U47) -> OK | Y47: =IF(F47=1,"",W47-E47) | Z47: =H47+J47-I47 -> 0 | AA47: =IF(F47=1,0,AA$6) -> 0 | AB47: =IF(AA47=0,0,Z47/AA47) -> 0
A48: ='Horaire dimanche 2'!A47 -> PASSOT LA BARGE | B48: ='Horaire dimanche 2'!B47 -> 0.75 | C48: ='Horaire dimanche 2'!C47 -> D8 | D48: =VLOOKUP(C48,'Liste chauffeur'!$B$5:$L$18,2,TRUE)&" "&VLOOKUP(C48,'Liste chauffeur'!$B$5:$L$18,3,TRUE) -> ISSOUF Dailami | F48: =COUNTBLANK(E48) -> 1 | L48: =K48-E48 -> 0 | Y48: =IF(F48=1,"",W48-E48) | Z48: =H48+J48-I48 -> 0 | AA48: =IF(F48=1,0,AA$6) -> 0 | AB48: =IF(AA48=0,0,Z48/AA48) -> 0
A49: ='Horaire dimanche 2'!A48 -> DOUJANI | B49: ='Horaire dimanche 2'!B48 -> 0.75 | C49: ='Horaire dimanche 2'!C48 -> D14 | D49: =VLOOKUP(C49,'Liste chauffeur'!$B$5:$L$18,2,TRUE)&" "&VLOOKUP(C49,'Liste chauffeur'!$B$5:$L$18,3,TRUE) -> AHAMADI Laydine | F49: =COUNTBLANK(E49) -> 1 | Y49: =IF(F49=1,"",W49-E49) | Z49: =H49+J49-I49 -> 0 | AA49: =IF(F49=1,0,AA$6) -> 0 | AB49: =IF(AA49=0,0,Z49/AA49) -> 0
A50: ='Horaire dimanche 2'!A49 -> PASSOT LA BARGE | B50: ='Horaire dimanche 2'!B49 -> 0.77083333 | C50: ='Horaire dimanche 2'!C49 -> D14 | D50: =VLOOKUP(C50,'Liste chauffeur'!$B$5:$L$18,2,TRUE)&" "&VLOOKUP(C50,'Liste chauffeur'!$B$5:$L$18,3,TRUE) -> AHAMADI Laydine | F50: =COUNTBLANK(E50) -> 1 | Y50: =IF(F50=1,"",W50-E50) | Z50: =H50+J50-I50 -> 0 | AA50: =IF(F50=1,0,AA$6) -> 0 | AB50: =IF(AA50=0,0,Z50/AA50) -> 0
A51: ='Horaire dimanche 2'!A50 -> DOUJANI | B51: ='Horaire dimanche 2'!B50 -> 0.77083333 | C51: ='Horaire dimanche 2'!C50 -> D8 | D51: =VLOOKUP(C51,'Liste chauffeur'!$B$5:$L$18,2,TRUE)&" "&VLOOKUP(C51,'Liste chauffeur'!$B$5:$L$18,3,TRUE) -> ISSOUF Dailami | F51: =COUNTBLANK(E51) -> 1 | Y51: =IF(F51=1,"",W51-E51) | Z51: =H51+J51-I51 -> 0 | AA51: =IF(F51=1,0,AA$6) -> 0 | AB51: =IF(AA51=0,0,Z51/AA51) -> 0
A52: ='Horaire dimanche 2'!A51 -> PASSOT LA BARGE | B52: ='Horaire dimanche 2'!B51 -> 0.79166667 | C52: ='Horaire dimanche 2'!C51 -> D8 | D52: =VLOOKUP(C52,'Liste chauffeur'!$B$5:$L$18,2,TRUE)&" "&VLOOKUP(C52,'Liste chauffeur'!$B$5:$L$18,3,TRUE) -> ISSOUF Dailami | F52: =COUNTBLANK(E52) -> 1 | Y52: =IF(F52=1,"",W52-E52) | Z52: =H52+J52-I52 -> 0 | AA52: =IF(F52=1,0,AA$6) -> 0 | AB52: =IF(AA52=0,0,Z52/AA52) -> 0
B53: ST2 | C53: ST | F53: =SUM(F26:F52) -> 27 | G53: =SUM(G26:G52) -> 0 | Y53: =AVERAGE(Y26:Y52) -> #DIV/0! | Z53: =SUM(Z26:Z52) -> 0 | AA53: =SUM(AA26:AA52) -> 0 | AB53: =IF(AA53=0,0,Z53/AA53) -> 0
B54: ST3 | C54: ST | F54: =F25+F53 -> 44 | G54: =G25+G53 -> 0 | Y54: =AVERAGE(Y8:Y24,Y26:Y52) -> #DIV/0! | Z54: =Z25+Z53 -> 0 | AA54: =AA25+AA53 -> 0 | AB54: =IF(AA54=0,0,Z54/AA54) -> 0
A55: REMPLACEMENT | C55: D
A56: REMPLACEMENT | C56: D
A57: REMPLACEMENT | C57: D | O57: =M57-#REF! -> #REF! | P57: =#REF!+#REF!-#REF! -> #REF!
A58: REMPLACEMENT | C58: D | O58: =M58-#REF! -> #REF! | P58: =#REF!+#REF!-#REF! -> #REF!
E60: Signature Chauffeur | I60: Signature Coordinateur
B63: Statistiques | C63: nbre de trajets planifiés | D63: Nbre trajets non effectués | E63: Nbre trajets effectués non planifiés | F63: Nbre trajets dont départ > 10 minutes en retard
B64: D1 | C64: =COUNTIF($B$8:$C$52,B64) -> 0 | D64: =C64-(COUNTIFS(C$8:C$52,B64,X$8:X$52,"")) -> 0 | E64: =COUNTIFS(X$8:X$52,$B64) -> 0 | F64: =COUNTIFS(G$8:G$52,$B64) -> 0
B65: D2 | C65: =COUNTIF($B$8:$C$52,B65) -> 0 | D65: =C65-(COUNTIFS(C$8:C$52,B65,X$8:X$52,"")) -> 0 | E65: =COUNTIFS(X$8:X$52,$B65) -> 0 | F65: =COUNTIFS(G$8:G$52,$B65) -> 0
B66: D3 | C66: =COUNTIF($B$8:$C$52,B66) -> 0 | D66: =C66-(COUNTIFS(C$8:C$52,B66,X$8:X$52,"")) -> 0 | E66: =COUNTIFS(X$8:X$52,$B66) -> 0 | F66: =COUNTIFS(G$8:G$52,$B66) -> 0
B67: D4 | C67: =COUNTIF($B$8:$C$52,B67) -> 0 | D67: =C67-(COUNTIFS(C$8:C$52,B67,X$8:X$52,"")) -> 0 | E67: =COUNTIFS(X$8:X$52,$B67) -> 0 | F67: =COUNTIFS(G$8:G$52,$B67) -> 0
B68: D5 | C68: =COUNTIF($B$8:$C$52,B68) -> 0 | D68: =C68-(COUNTIFS(C$8:C$52,B68,X$8:X$52,"")) -> 0 | E68: =COUNTIFS(X$8:X$52,$B68) -> 0 | F68: =COUNTIFS(G$8:G$52,$B68) -> 0
B69: D6 | C69: =COUNTIF($B$8:$C$52,B69) -> 0 | D69: =C69-(COUNTIFS(C$8:C$52,B69,X$8:X$52,"")) -> 0 | E69: =COUNTIFS(X$8:X$52,$B69) -> 0 | F69: =COUNTIFS(G$8:G$52,$B69) -> 0
B70: D7 | C70: =COUNTIF($B$8:$C$52,B70) -> 11 | D70: =C70-(COUNTIFS(C$8:C$52,B70,X$8:X$52,"")) -> 0 | E70: =COUNTIFS(X$8:X$52,$B70) -> 0 | F70: =COUNTIFS(G$8:G$52,$B70) -> 0
B71: D8 | C71: =COUNTIF($B$8:$C$52,B71) -> 11 | D71: =C71-(COUNTIFS(C$8:C$52,B71,X$8:X$52,"")) -> 0 | E71: =COUNTIFS(X$8:X$52,$B71) -> 0 | F71: =COUNTIFS(G$8:G$52,$B71) -> 0
B72: D9 | C72: =COUNTIF($B$8:$C$52,B72) -> 0 | D72: =C72-(COUNTIFS(C$8:C$52,B72,X$8:X$52,"")) -> 0 | E72: =COUNTIFS(X$8:X$52,$B72) -> 0 | F72: =COUNTIFS(G$8:G$52,$B72) -> 0
B73: D10 | C73: =COUNTIF($B$8:$C$52,B73) -> 0 | D73: =C73-(COUNTIFS(C$8:C$52,B73,X$8:X$52,"")) -> 0 | E73: =COUNTIFS(X$8:X$52,$B73) -> 0 | F73: =COUNTIFS(G$8:G$52,$B73) -> 0
B74: D11 | C74: =COUNTIF($B$8:$C$52,B74) -> 0 | D74: =C74-(COUNTIFS(C$8:C$52,B74,X$8:X$52,"")) -> 0 | E74: =COUNTIFS(X$8:X$52,$B74) -> 0 | F74: =COUNTIFS(G$8:G$52,$B74) -> 0
B75: D12 | C75: =COUNTIF($B$8:$C$52,B75) -> 11 | D75: =C75-(COUNTIFS(C$8:C$52,B75,X$8:X$52,"")) -> 0 | E75: =COUNTIFS(X$8:X$52,$B75) -> 0 | F75: =COUNTIFS(G$8:G$52,$B75) -> 0
... B86: D23 | C86: =COUNTIF($B$8:$C$52,B86) -> 0 | D86: =C86-(COUNTIFS(C$8:C$52,B86,X$8:X$52,"")) -> 0 | E86: =COUNTIFS(X$8:X$52,$B86) -> 0 | F86: =COUNTIFS(G$8:G$52,$B86) -> 0
C87: =SUM(C64:C86) -> 44 | D87: =SUM(D64:D86) -> 0 | E87: =SUM(E64:E86) -> 0 | F87: =SUM(F64:F86) -> 0
E88: =D87-E87 -> 0 | F88: =IF(E88=F87,"OK","ERREUR") -> OK

Sheet coordinateur matin
A1: COORDINATEUR SEMAINE LIGNE 3 NAVETTES CARIBUS | E1: 46082 | I1: NOM COORDINATEUR
A2: Depart | B2: Heure théorique départ | C2: Type chauffeur prévu | D2: Nom chauffeur prévu | E2: Astreinte | F2: Nom Chauffeur réel ( si différent) | G2: Heure réelle départ | H2: Nbre personnes montantes
A3: =Horaire!A8 -> DOUJANI | B3: =Horaire!B8 -> 0.20833333 | C3: =Horaire!C8 -> D1 | D3: =VLOOKUP(C3,'Liste chauffeur'!$B$5:$L$19,2,TRUE)&" "&VLOOKUP(C3,'Liste chauffeur'!$B$5:$L$19,3,TRUE) -> MOHAMED Ali (laglace) | E3: D14
A4: =Horaire!A9 -> DOUJANI | B4: =Horaire!B9 -> 0.21527778 | C4: =Horaire!C9 -> D12 | D4: =VLOOKUP(C4,'Liste chauffeur'!$B$5:$L$18,2,TRUE)&" "&VLOOKUP(C4,'Liste chauffeur'!$B$5:$L$18,3,TRUE) -> VELOU M'COLO M'Berou | E4: D14
A5: =Horaire!A10 -> DOUJANI | B5: =Horaire!B10 -> 0.22222222 | C5: =Horaire!C10 -> D5 | D5: =VLOOKUP(C5,'Liste chauffeur'!$B$5:$L$18,2,TRUE)&" "&VLOOKUP(C5,'Liste chauffeur'!$B$5:$L$18,3,TRUE) -> AMINA Selemani | E5: D14
A6: =Horaire!A11 -> DOUJANI | B6: =Horaire!B11 -> 0.22916667 | C6: =Horaire!C11 -> D13 | D6: =VLOOKUP(C6,'Liste chauffeur'!$B$5:$L$18,2,TRUE)&" "&VLOOKUP(C6,'Liste chauffeur'!$B$5:$L$18,3,TRUE) -> MOURIDI Aktoir | E6: D14
A7: =Horaire!A12 -> PASSOT LA BARGE | B7: =Horaire!B12 -> 0.22916667 | C7: =Horaire!C12 -> D1 | D7: =VLOOKUP(C7,'Liste chauffeur'!$B$5:$L$18,2,TRUE)&" "&VLOOKUP(C7,'Liste chauffeur'!$B$5:$L$18,3,TRUE) -> MOHAMED Ali (laglace) | E7: D14 | F7: =IF(ISBLANK('Feuille saisie'!X12)=TRUE,"",'Feuille saisie'!X12)
A8: =Horaire!A13 -> DOUJANI | B8: =Horaire!B13 -> 0.23611111 | C8: =Horaire!C13 -> D3 | D8: =VLOOKUP(C8,'Liste chauffeur'!$B$5:$L$18,2,TRUE)&" "&VLOOKUP(C8,'Liste chauffeur'!$B$5:$L$18,3,TRUE) -> ABDOURAHIM Mohamed | E8: D14 | F8: =IF(ISBLANK('Feuille saisie'!X13)=TRUE,"",'Feuille saisie'!X13) | I8: Observations :
A9: =Horaire!A14 -> PASSOT LA BARGE | B9: =Horaire!B14 -> 0.23611111 | C9: =Horaire!C14 -> D12 | D9: =VLOOKUP(C9,'Liste chauffeur'!$B$5:$L$18,2,TRUE)&" "&VLOOKUP(C9,'Liste chauffeur'!$B$5:$L$18,3,TRUE) -> VELOU M'COLO M'Berou | E9: D14 | F9: =IF(ISBLANK('Feuille saisie'!X14)=TRUE,"",'Feuille saisie'!X14)
A10: =Horaire!A15 -> DOUJANI | B10: =Horaire!B15 -> 0.24305556 | C10: =Horaire!C15 -> D10 | D10: =VLOOKUP(C10,'Liste chauffeur'!$B$5:$L$18,2,TRUE)&" "&VLOOKUP(C10,'Liste chauffeur'!$B$5:$L$18,3,TRUE) -> KAMARDINE Mansour (Salarié) | F10: =IF(ISBLANK('Feuille saisie'!X15)=TRUE,"",'Feuille saisie'!X15)
A11: =Horaire!A16 -> PASSOT LA BARGE | B11: =Horaire!B16 -> 0.24305556 | C11: =Horaire!C16 -> D5 | D11: =VLOOKUP(C11,'Liste chauffeur'!$B$5:$L$18,2,TRUE)&" "&VLOOKUP(C11,'Liste chauffeur'!$B$5:$L$18,3,TRUE) -> AMINA Selemani | F11: =IF(ISBLANK('Feuille saisie'!X16)=TRUE,"",'Feuille saisie'!X16)
A12: =Horaire!A17 -> DOUJANI | B12: =Horaire!B17 -> 0.25 | C12: =Horaire!C17 -> D1 | D12: =VLOOKUP(C12,'Liste chauffeur'!$B$5:$L$18,2,TRUE)&" "&VLOOKUP(C12,'Liste chauffeur'!$B$5:$L$18,3,TRUE) -> MOHAMED Ali (laglace) | F12: =IF(ISBLANK('Feuille saisie'!X17)=TRUE,"",'Feuille saisie'!X17)
A13: =Horaire!A18 -> PASSOT LA BARGE | B13: =Horaire!B18 -> 0.25 | C13: =Horaire!C18 -> D13 | D13: =VLOOKUP(C13,'Liste chauffeur'!$B$5:$L$18,2,TRUE)&" "&VLOOKUP(C13,'Liste chauffeur'!$B$5:$L$18,3,TRUE) -> MOURIDI Aktoir
A14: =Horaire!A19 -> M'TSAPERE | B14: =Horaire!B19 -> 0.25 | C14: =Horaire!C19 -> D4 | D14: =VLOOKUP(C14,'Liste chauffeur'!$B$5:$L$18,2,TRUE)&" "&VLOOKUP(C14,'Liste chauffeur'!$B$5:$L$18,3,TRUE) -> AMBDI Houmadi | F14: =IF(ISBLANK('Feuille saisie'!X19)=TRUE,"",'Feuille saisie'!X19)
A15: =Horaire!A20 -> PASSOT LA BARGE | B15: =Horaire!B20 -> 0.25 | C15: =Horaire!C20 -> D11 | D15: =VLOOKUP(C15,'Liste chauffeur'!$B$5:$L$18,2,TRUE)&" "&VLOOKUP(C15,'Liste chauffeur'!$B$5:$L$18,3,TRUE) -> ALLAOUI Soibrane | F15: =IF(ISBLANK('Feuille saisie'!X20)=TRUE,"",'Feuille saisie'!X20)
A16: =Horaire!A21 -> DOUJANI | B16: =Horaire!B21 -> 0.25694444 | C16: =Horaire!C21 -> D12 | D16: =VLOOKUP(C16,'Liste chauffeur'!$B$5:$L$18,2,TRUE)&" "&VLOOKUP(C16,'Liste chauffeur'!$B$5:$L$18,3,TRUE) -> VELOU M'COLO M'Berou | F16: =IF(ISBLANK('Feuille saisie'!X21)=TRUE,"",'Feuille saisie'!X21)
A17: =Horaire!A22 -> PASSOT LA BARGE | B17: =Horaire!B22 -> 0.25694444 | C17: =Horaire!C22 -> D3 | D17: =VLOOKUP(C17,'Liste chauffeur'!$B$5:$L$18,2,TRUE)&" "&VLOOKUP(C17,'Liste chauffeur'!$B$5:$L$18,3,TRUE) -> ABDOURAHIM Mohamed | F17: =IF(ISBLANK('Feuille saisie'!X22)=TRUE,"",'Feuille saisie'!X22)
A18: =Horaire!A23 -> M'TSAPERE | B18: =Horaire!B23 -> 0.25694444 | C18: =Horaire!C23 -> D5 | D18: =VLOOKUP(C18,'Liste chauffeur'!$B$5:$L$18,2,TRUE)&" "&VLOOKUP(C18,'Liste chauffeur'!$B$5:$L$18,3,TRUE) -> AMINA Selemani | F18: =IF(ISBLANK('Feuille saisie'!X23)=TRUE,"",'Feuille saisie'!X23)
A19: =Horaire!A24 -> PASSOT LA BARGE | B19: =Horaire!B24 -> 0.25694444 | C19: =Horaire!C24 -> D14 | D19: =VLOOKUP(C19,'Liste chauffeur'!$B$5:$L$18,2,TRUE)&" "&VLOOKUP(C19,'Liste chauffeur'!$B$5:$L$18,3,TRUE) -> AHAMADI Laydine | F19: =IF(ISBLANK('Feuille saisie'!X24)=TRUE,"",'Feuille saisie'!X24)
A20: =Horaire!A25 -> DOUJANI | B20: =Horaire!B25 -> 0.26388889 | C20: =Horaire!C25 -> D2 | D20: =VLOOKUP(C20,'Liste chauffeur'!$B$5:$L$18,2,TRUE)&" "&VLOOKUP(C20,'Liste chauffeur'!$B$5:$L$18,3,TRUE) -> BARAKA Soumaila
A21: =Horaire!A26 -> PASSOT LA BARGE | B21: =Horaire!B26 -> 0.26388889 | C21: =Horaire!C26 -> D10 | D21: =VLOOKUP(C21,'Liste chauffeur'!$B$5:$L$18,2,TRUE)&" "&VLOOKUP(C21,'Liste chauffeur'!$B$5:$L$18,3,TRUE) -> KAMARDINE Mansour (Salarié) | F21: =IF(ISBLANK('Feuille saisie'!X26)=TRUE,"",'Feuille saisie'!X26)
A22: =Horaire!A27 -> M'TSAPERE | B22: =Horaire!B27 -> 0.26388889 | C22: =Horaire!C27 -> D7 | D22: =VLOOKUP(C22,'Liste chauffeur'!$B$5:$L$18,2,TRUE)&" "&VLOOKUP(C22,'Liste chauffeur'!$B$5:$L$18,3,TRUE) -> COMBO Said | F22: =IF(ISBLANK('Feuille saisie'!X27)=TRUE,"",'Feuille saisie'!X27)
A23: =Horaire!A28 -> PASSOT LA BARGE | B23: =Horaire!B28 -> 0.26388889 | C23: =Horaire!C28 -> D6 | D23: =VLOOKUP(C23,'Liste chauffeur'!$B$5:$L$18,2,TRUE)&" "&VLOOKUP(C23,'Liste chauffeur'!$B$5:$L$18,3,TRUE) -> ABDOU HAMIDOUNE Nassabia | F23: =IF(ISBLANK('Feuille saisie'!X28)=TRUE,"",'Feuille saisie'!X28)
A24: =Horaire!A29 -> DOUJANI | B24: =Horaire!B29 -> 0.27083333 | C24: =Horaire!C29 -> D13 | D24: =VLOOKUP(C24,'Liste chauffeur'!$B$5:$L$18,2,TRUE)&" "&VLOOKUP(C24,'Liste chauffeur'!$B$5:$L$18,3,TRUE) -> MOURIDI Aktoir | F24: =IF(ISBLANK('Feuille saisie'!X29)=TRUE,"",'Feuille saisie'!X29) | I24: Absences :
A25: =Horaire!A30 -> PASSOT LA BARGE | B25: =Horaire!B30 -> 0.27083333 | C25: =Horaire!C30 -> D1 | D25: =VLOOKUP(C25,'Liste chauffeur'!$B$5:$L$18,2,TRUE)&" "&VLOOKUP(C25,'Liste chauffeur'!$B$5:$L$18,3,TRUE) -> MOHAMED Ali (laglace) | F25: =IF(ISBLANK('Feuille saisie'!X30)=TRUE,"",'Feuille saisie'!X30)
A26: =Horaire!A31 -> M'TSAPERE | B26: =Horaire!B31 -> 0.27083333 | C26: =Horaire!C31 -> D11 | D26: =VLOOKUP(C26,'Liste chauffeur'!$B$5:$L$18,2,TRUE)&" "&VLOOKUP(C26,'Liste chauffeur'!$B$5:$L$18,3,TRUE) -> ALLAOUI Soibrane | F26: =IF(ISBLANK('Feuille saisie'!X31)=TRUE,"",'Feuille saisie'!X31)
A27: =Horaire!A32 -> PASSOT LA BARGE | B27: =Horaire!B32 -> 0.27083333 | C27: =Horaire!C32 -> D4 | D27: =VLOOKUP(C27,'Liste chauffeur'!$B$5:$L$18,2,TRUE)&" "&VLOOKUP(C27,'Liste chauffeur'!$B$5:$L$18,3,TRUE) -> AMBDI Houmadi
A28: =Horaire!A33 -> DOUJANI | B28: =Horaire!B33 -> 0.27777778 | C28: =Horaire!C33 -> D3 | D28: =VLOOKUP(C28,'Liste chauffeur'!$B$5:$L$18,2,TRUE)&" "&VLOOKUP(C28,'Liste chauffeur'!$B$5:$L$18,3,TRUE) -> ABDOURAHIM Mohamed | F28: =IF(ISBLANK('Feuille saisie'!X33)=TRUE,"",'Feuille saisie'!X33)
A29: =Horaire!A34 -> PASSOT LA BARGE | B29: =Horaire!B34 -> 0.27777778 | C29: =Horaire!C34 -> D12 | D29: =VLOOKUP(C29,'Liste chauffeur'!$B$5:$L$18,2,TRUE)&" "&VLOOKUP(C29,'Liste chauffeur'!$B$5:$L$18,3,TRUE) -> VELOU M'COLO M'Berou | F29: =IF(ISBLANK('Feuille saisie'!X34)=TRUE,"",'Feuille saisie'!X34)
A30: =Horaire!A35 -> M'TSAPERE | B30: =Horaire!B35 -> 0.27777778 | C30: =Horaire!C35 -> D14 | D30: =VLOOKUP(C30,'Liste chauffeur'!$B$5:$L$18,2,TRUE)&" "&VLOOKUP(C30,'Liste chauffeur'!$B$5:$L$18,3,TRUE) -> AHAMADI Laydine | F30: =IF(ISBLANK('Feuille saisie'!X35)=TRUE,"",'Feuille saisie'!X35)
A31: =Horaire!A36 -> PASSOT LA BARGE | B31: =Horaire!B36 -> 0.27777778 | C31: =Horaire!C36 -> D5 | D31: =VLOOKUP(C31,'Liste chauffeur'!$B$5:$L$18,2,TRUE)&" "&VLOOKUP(C31,'Liste chauffeur'!$B$5:$L$18,3,TRUE) -> AMINA Selemani | F31: =IF(ISBLANK('Feuille saisie'!X36)=TRUE,"",'Feuille saisie'!X36)
A32: =Horaire!A37 -> DOUJANI | B32: =Horaire!B37 -> 0.28472222 | C32: =Horaire!C37 -> D10 | D32: =VLOOKUP(C32,'Liste chauffeur'!$B$5:$L$18,2,TRUE)&" "&VLOOKUP(C32,'Liste chauffeur'!$B$5:$L$18,3,TRUE) -> KAMARDINE Mansour (Salarié) | F32: =IF(ISBLANK('Feuille saisie'!X37)=TRUE,"",'Feuille saisie'!X37) | I32: Trajets non effectués :
A33: =Horaire!A38 -> PASSOT LA BARGE | B33: =Horaire!B38 -> 0.28472222 | C33: =Horaire!C38 -> D2 | D33: =VLOOKUP(C33,'Liste chauffeur'!$B$5:$L$18,2,TRUE)&" "&VLOOKUP(C33,'Liste chauffeur'!$B$5:$L$18,3,TRUE) -> BARAKA Soumaila | F33: =IF(ISBLANK('Feuille saisie'!X38)=TRUE,"",'Feuille saisie'!X38)
A34: =Horaire!A39 -> M'TSAPERE | B34: =Horaire!B39 -> 0.28472222 | C34: =Horaire!C39 -> D6 | D34: =VLOOKUP(C34,'Liste chauffeur'!$B$5:$L$18,2,TRUE)&" "&VLOOKUP(C34,'Liste chauffeur'!$B$5:$L$18,3,TRUE) -> ABDOU HAMIDOUNE Nassabia | F34: =IF(ISBLANK('Feuille saisie'!X39)=TRUE,"",'Feuille saisie'!X39)
A35: =Horaire!A40 -> PASSOT LA BARGE | B35: =Horaire!B40 -> 0.28472222 | C35: =Horaire!C40 -> D7 | D35: =VLOOKUP(C35,'Liste chauffeur'!$B$5:$L$18,2,TRUE)&" "&VLOOKUP(C35,'Liste chauffeur'!$B$5:$L$18,3,TRUE) -> COMBO Said | F35: =IF(ISBLANK('Feuille saisie'!X40)=TRUE,"",'Feuille saisie'!X40) | I35: Signature Coordinateur 1 :
A36: =Horaire!A41 -> DOUJANI | B36: =Horaire!B41 -> 0.29166667 | C36: =Horaire!C41 -> D1 | D36: =VLOOKUP(C36,'Liste chauffeur'!$B$5:$L$18,2,TRUE)&" "&VLOOKUP(C36,'Liste chauffeur'!$B$5:$L$18,3,TRUE) -> MOHAMED Ali (laglace) | F36: =IF(ISBLANK('Feuille saisie'!X41)=TRUE,"",'Feuille saisie'!X41)
A37: =Horaire!A42 -> PASSOT LA BARGE | B37: =Horaire!B42 -> 0.29166667 | C37: =Horaire!C42 -> D13 | D37: =VLOOKUP(C37,'Liste chauffeur'!$B$5:$L$18,2,TRUE)&" "&VLOOKUP(C37,'Liste chauffeur'!$B$5:$L$18,3,TRUE) -> MOURIDI Aktoir | F37: =IF(ISBLANK('Feuille saisie'!X42)=TRUE,"",'Feuille saisie'!X42)
A38: =Horaire!A43 -> M'TSAPERE | B38: =Horaire!B43 -> 0.29166667 | C38: =Horaire!C43 -> D4 | D38: =VLOOKUP(C38,'Liste chauffeur'!$B$5:$L$18,2,TRUE)&" "&VLOOKUP(C38,'Liste chauffeur'!$B$5:$L$18,3,TRUE) -> AMBDI Houmadi | F38: =IF(ISBLANK('Feuille saisie'!X43)=TRUE,"",'Feuille saisie'!X43)
A39: =Horaire!A44 -> PASSOT LA BARGE | B39: =Horaire!B44 -> 0.29166667 | C39: =Horaire!C44 -> D11 | D39: =VLOOKUP(C39,'Liste chauffeur'!$B$5:$L$18,2,TRUE)&" "&VLOOKUP(C39,'Liste chauffeur'!$B$5:$L$18,3,TRUE) -> ALLAOUI Soibrane | F39: =IF(ISBLANK('Feuille saisie'!X44)=TRUE,"",'Feuille saisie'!X44)
A40: =Horaire!A45 -> DOUJANI | B40: =Horaire!B45 -> 0.29861111 | C40: =Horaire!C45 -> D12 | D40: =VLOOKUP(C40,'Liste chauffeur'!$B$5:$L$18,2,TRUE)&" "&VLOOKUP(C40,'Liste chauffeur'!$B$5:$L$18,3,TRUE) -> VELOU M'COLO M'Berou | F40: =IF(ISBLANK('Feuille saisie'!X45)=TRUE,"",'Feuille saisie'!X45)
A41: =Horaire!A46 -> PASSOT LA BARGE | B41: =Horaire!B46 -> 0.29861111 | C41: =Horaire!C46 -> D3 | D41: =VLOOKUP(C41,'Liste chauffeur'!$B$5:$L$18,2,TRUE)&" "&VLOOKUP(C41,'Liste chauffeur'!$B$5:$L$18,3,TRUE) -> ABDOURAHIM Mohamed | F41: =IF(ISBLANK('Feuille saisie'!X46)=TRUE,"",'Feuille saisie'!X46)
A42: =Horaire!A47 -> M'TSAPERE | B42: =Horaire!B47 -> 0.29861111 | C42: =Horaire!C47 -> D5 | D42: =VLOOKUP(C42,'Liste chauffeur'!$B$5:$L$18,2,TRUE)&" "&VLOOKUP(C42,'Liste chauffeur'!$B$5:$L$18,3,TRUE) -> AMINA Selemani | F42: =IF(ISBLANK('Feuille saisie'!X47)=TRUE,"",'Feuille saisie'!X47)
A43: =Horaire!A48 -> PASSOT LA BARGE | B43: =Horaire!B48 -> 0.29861111 | C43: =Horaire!C48 -> D14 | D43: =VLOOKUP(C43,'Liste chauffeur'!$B$5:$L$18,2,TRUE)&" "&VLOOKUP(C43,'Liste chauffeur'!$B$5:$L$18,3,TRUE) -> AHAMADI Laydine | F43: =IF(ISBLANK('Feuille saisie'!X48)=TRUE,"",'Feuille saisie'!X48)
A44: =Horaire!A49 -> DOUJANI | B44: =Horaire!B49 -> 0.30555556 | C44: =Horaire!C49 -> D2 | D44: =VLOOKUP(C44,'Liste chauffeur'!$B$5:$L$19,2,TRUE)&" "&VLOOKUP(C44,'Liste chauffeur'!$B$5:$L$19,3,TRUE) -> BARAKA Soumaila | F44: =IF(ISBLANK('Feuille saisie'!X49)=TRUE,"",'Feuille saisie'!X49)
A45: =Horaire!A50 -> PASSOT LA BARGE | B45: =Horaire!B50 -> 0.30555556 | C45: =Horaire!C50 -> D10 | D45: =VLOOKUP(C45,'Liste chauffeur'!$B$5:$L$19,2,TRUE)&" "&VLOOKUP(C45,'Liste chauffeur'!$B$5:$L$19,3,TRUE) -> KAMARDINE Mansour (Salarié) | F45: =IF(ISBLANK('Feuille saisie'!X50)=TRUE,"",'Feuille saisie'!X50)
A46: =Horaire!A51 -> M'TSAPERE | B46: =Horaire!B51 -> 0.30555556 | C46: =Horaire!C51 -> D7 | D46: =VLOOKUP(C46,'Liste chauffeur'!$B$5:$L$19,2,TRUE)&" "&VLOOKUP(C46,'Liste chauffeur'!$B$5:$L$19,3,TRUE) -> COMBO Said | F46: =IF(ISBLANK('Feuille saisie'!X51)=TRUE,"",'Feuille saisie'!X51)
A47: =Horaire!A52 -> PASSOT LA BARGE | B47: =Horaire!B52 -> 0.30555556 | C47: =Horaire!C52 -> D6 | D47: =VLOOKUP(C47,'Liste chauffeur'!$B$5:$L$19,2,TRUE)&" "&VLOOKUP(C47,'Liste chauffeur'!$B$5:$L$19,3,TRUE) -> ABDOU HAMIDOUNE Nassabia | F47: =IF(ISBLANK('Feuille saisie'!X52)=TRUE,"",'Feuille saisie'!X52)
A48: =Horaire!A53 -> DOUJANI | B48: =Horaire!B53 -> 0.3125 | C48: =Horaire!C53 -> D13 | D48: =VLOOKUP(C48,'Liste chauffeur'!$B$5:$L$19,2,TRUE)&" "&VLOOKUP(C48,'Liste chauffeur'!$B$5:$L$19,3,TRUE) -> MOURIDI Aktoir | F48: =IF(ISBLANK('Feuille saisie'!X53)=TRUE,"",'Feuille saisie'!X53)
A49: =Horaire!A54 -> PASSOT LA BARGE | B49: =Horaire!B54 -> 0.3125 | C49: =Horaire!C54 -> D1 | D49: =VLOOKUP(C49,'Liste chauffeur'!$B$5:$L$19,2,TRUE)&" "&VLOOKUP(C49,'Liste chauffeur'!$B$5:$L$19,3,TRUE) -> MOHAMED Ali (laglace) | F49: =IF(ISBLANK('Feuille saisie'!X54)=TRUE,"",'Feuille saisie'!X54)
A50: =Horaire!A55 -> M'TSAPERE | B50: =Horaire!B55 -> 0.3125 | C50: =Horaire!C55 -> D11 | D50: =VLOOKUP(C50,'Liste chauffeur'!$B$5:$L$19,2,TRUE)&" "&VLOOKUP(C50,'Liste chauffeur'!$B$5:$L$19,3,TRUE) -> ALLAOUI Soibrane | F50: =IF(ISBLANK('Feuille saisie'!X55)=TRUE,"",'Feuille saisie'!X55)
A51: =Horaire!A56 -> PASSOT LA BARGE | B51: =Horaire!B56 -> 0.3125 | C51: =Horaire!C56 -> D4 | D51: =VLOOKUP(C51,'Liste chauffeur'!$B$5:$L$19,2,TRUE)&" "&VLOOKUP(C51,'Liste chauffeur'!$B$5:$L$19,3,TRUE) -> AMBDI Houmadi
A52: =Horaire!A57 -> DOUJANI | B52: =Horaire!B57 -> 0.31944444 | C52: =Horaire!C57 -> D3 | D52: =VLOOKUP(C52,'Liste chauffeur'!$B$5:$L$19,2,TRUE)&" "&VLOOKUP(C52,'Liste chauffeur'!$B$5:$L$19,3,TRUE) -> ABDOURAHIM Mohamed
A53: =Horaire!A58 -> PASSOT LA BARGE | B53: =Horaire!B58 -> 0.31944444 | C53: =Horaire!C58 -> D12 | D53: =VLOOKUP(C53,'Liste chauffeur'!$B$5:$L$19,2,TRUE)&" "&VLOOKUP(C53,'Liste chauffeur'!$B$5:$L$19,3,TRUE) -> VELOU M'COLO M'Berou | I53: Observations :
A54: =Horaire!A59 -> M'TSAPERE | B54: =Horaire!B59 -> 0.31944444 | C54: =Horaire!C59 -> D14 | D54: =VLOOKUP(C54,'Liste chauffeur'!$B$5:$L$19,2,TRUE)&" "&VLOOKUP(C54,'Liste chauffeur'!$B$5:$L$19,3,TRUE) -> AHAMADI Laydine
A55: =Horaire!A60 -> PASSOT LA BARGE | B55: =Horaire!B60 -> 0.31944444 | C55: =Horaire!C60 -> D5 | D55: =VLOOKUP(C55,'Liste chauffeur'!$B$5:$L$19,2,TRUE)&" "&VLOOKUP(C55,'Liste chauffeur'!$B$5:$L$19,3,TRUE) -> AMINA Selemani
A56: =Horaire!A61 -> DOUJANI | B56: =Horaire!B61 -> 0.32638889 | C56: =Horaire!C61 -> D10 | D56: =VLOOKUP(C56,'Liste chauffeur'!$B$5:$L$19,2,TRUE)&" "&VLOOKUP(C56,'Liste chauffeur'!$B$5:$L$19,3,TRUE) -> KAMARDINE Mansour (Salarié) | I56: Absences :
A57: =Horaire!A62 -> PASSOT LA BARGE | B57: =Horaire!B62 -> 0.32638889 | C57: =Horaire!C62 -> D2 | D57: =VLOOKUP(C57,'Liste chauffeur'!$B$5:$L$19,2,TRUE)&" "&VLOOKUP(C57,'Liste chauffeur'!$B$5:$L$19,3,TRUE) -> BARAKA Soumaila
A58: =Horaire!A63 -> M'TSAPERE | B58: =Horaire!B63 -> 0.32638889 | C58: =Horaire!C63 -> D6 | D58: =VLOOKUP(C58,'Liste chauffeur'!$B$5:$L$19,2,TRUE)&" "&VLOOKUP(C58,'Liste chauffeur'!$B$5:$L$19,3,TRUE) -> ABDOU HAMIDOUNE Nassabia
A59: =Horaire!A64 -> PASSOT LA BARGE | B59: =Horaire!B64 -> 0.32638889 | C59: =Horaire!C64 -> D7 | D59: =VLOOKUP(C59,'Liste chauffeur'!$B$5:$L$19,2,TRUE)&" "&VLOOKUP(C59,'Liste chauffeur'!$B$5:$L$19,3,TRUE) -> COMBO Said
A60: =Horaire!A65 -> DOUJANI | B60: =Horaire!B65 -> 0.33333333 | C60: =Horaire!C65 -> D1 | D60: =VLOOKUP(C60,'Liste chauffeur'!$B$5:$L$19,2,TRUE)&" "&VLOOKUP(C60,'Liste chauffeur'!$B$5:$L$19,3,TRUE) -> MOHAMED Ali (laglace)
A61: =Horaire!A66 -> PASSOT LA BARGE | B61: =Horaire!B66 -> 0.33333333 | C61: =Horaire!C66 -> D13 | D61: =VLOOKUP(C61,'Liste chauffeur'!$B$5:$L$19,2,TRUE)&" "&VLOOKUP(C61,'Liste chauffeur'!$B$5:$L$19,3,TRUE) -> MOURIDI Aktoir
A62: =Horaire!A67 -> M'TSAPERE | B62: =Horaire!B67 -> 0.33333333 | C62: =Horaire!C67 -> D4 | D62: =VLOOKUP(C62,'Liste chauffeur'!$B$5:$L$19,2,TRUE)&" "&VLOOKUP(C62,'Liste chauffeur'!$B$5:$L$19,3,TRUE) -> AMBDI Houmadi
A63: =Horaire!A68 -> PASSOT LA BARGE | B63: =Horaire!B68 -> 0.33333333 | C63: =Horaire!C68 -> D11 | D63: =VLOOKUP(C63,'Liste chauffeur'!$B$5:$L$19,2,TRUE)&" "&VLOOKUP(C63,'Liste chauffeur'!$B$5:$L$19,3,TRUE) -> ALLAOUI Soibrane | I63: Trajets non effectués :
A64: =Horaire!A69 -> DOUJANI | B64: =Horaire!B69 -> 0.34722222 | C64: =Horaire!C69 -> D2 | D64: =VLOOKUP(C64,'Liste chauffeur'!$B$5:$L$19,2,TRUE)&" "&VLOOKUP(C64,'Liste chauffeur'!$B$5:$L$19,3,TRUE) -> BARAKA Soumaila | E64: D14
A65: =Horaire!A70 -> PASSOT LA BARGE | B65: =Horaire!B70 -> 0.34722222 | C65: =Horaire!C70 -> D10 | D65: =VLOOKUP(C65,'Liste chauffeur'!$B$5:$L$19,2,TRUE)&" "&VLOOKUP(C65,'Liste chauffeur'!$B$5:$L$19,3,TRUE) -> KAMARDINE Mansour (Salarié) | E65: D14
A66: =Horaire!A71 -> DOUJANI | B66: =Horaire!B71 -> 0.36111111 | C66: =Horaire!C71 -> D11 | D66: =VLOOKUP(C66,'Liste chauffeur'!$B$5:$L$19,2,TRUE)&" "&VLOOKUP(C66,'Liste chauffeur'!$B$5:$L$19,3,TRUE) -> ALLAOUI Soibrane | E66: D14 | I66: Signature Coordinateur 1 :
A67: =Horaire!A72 -> PASSOT LA BARGE | B67: =Horaire!B72 -> 0.36111111 | C67: =Horaire!C72 -> D4 | D67: =VLOOKUP(C67,'Liste chauffeur'!$B$5:$L$19,2,TRUE)&" "&VLOOKUP(C67,'Liste chauffeur'!$B$5:$L$19,3,TRUE) -> AMBDI Houmadi | E67: D14
A68: =Horaire!A73 -> DOUJANI | B68: =Horaire!B73 -> 0.375 | C68: =Horaire!C73 -> D10 | D68: =VLOOKUP(C68,'Liste chauffeur'!$B$5:$L$19,2,TRUE)&" "&VLOOKUP(C68,'Liste chauffeur'!$B$5:$L$19,3,TRUE) -> KAMARDINE Mansour (Salarié) | E68: D14
A69: =Horaire!A74 -> PASSOT LA BARGE | B69: =Horaire!B74 -> 0.375 | C69: =Horaire!C74 -> D2 | D69: =VLOOKUP(C69,'Liste chauffeur'!$B$5:$L$19,2,TRUE)&" "&VLOOKUP(C69,'Liste chauffeur'!$B$5:$L$19,3,TRUE) -> BARAKA Soumaila | E69: D14
A70: =Horaire!A75 -> DOUJANI | B70: =Horaire!B75 -> 0.38888889 | C70: =Horaire!C75 -> D4 | D70: =VLOOKUP(C70,'Liste chauffeur'!$B$5:$L$19,2,TRUE)&" "&VLOOKUP(C70,'Liste chauffeur'!$B$5:$L$19,3,TRUE) -> AMBDI Houmadi | E70: D14
A71: =Horaire!A76 -> PASSOT LA BARGE | B71: =Horaire!B76 -> 0.38888889 | C71: =Horaire!C76 -> D11 | D71: =VLOOKUP(C71,'Liste chauffeur'!$B$5:$L$19,2,TRUE)&" "&VLOOKUP(C71,'Liste chauffeur'!$B$5:$L$19,3,TRUE) -> ALLAOUI Soibrane | E71: D14
A72: =Horaire!A77 -> DOUJANI | B72: =Horaire!B77 -> 0.40277778 | C72: =Horaire!C77 -> D2 | D72: =VLOOKUP(C72,'Liste chauffeur'!$B$5:$L$19,2,TRUE)&" "&VLOOKUP(C72,'Liste chauffeur'!$B$5:$L$19,3,TRUE) -> BARAKA Soumaila | E72: D14
A73: =Horaire!A78 -> PASSOT LA BARGE | B73: =Horaire!B78 -> 0.40277778 | C73: =Horaire!C78 -> D10 | D73: =VLOOKUP(C73,'Liste chauffeur'!$B$5:$L$19,2,TRUE)&" "&VLOOKUP(C73,'Liste chauffeur'!$B$5:$L$19,3,TRUE) -> KAMARDINE Mansour (Salarié) | E73: D14
A74: =Horaire!A79 -> DOUJANI | B74: =Horaire!B79 -> 0.41666667 | C74: =Horaire!C79 -> D11 | D74: =VLOOKUP(C74,'Liste chauffeur'!$B$5:$L$19,2,TRUE)&" "&VLOOKUP(C74,'Liste chauffeur'!$B$5:$L$19,3,TRUE) -> ALLAOUI Soibrane | E74: D14
A75: =Horaire!A80 -> PASSOT LA BARGE | B75: =Horaire!B80 -> 0.41666667 | C75: =Horaire!C80 -> D4 | D75: =VLOOKUP(C75,'Liste chauffeur'!$B$5:$L$19,2,TRUE)&" "&VLOOKUP(C75,'Liste chauffeur'!$B$5:$L$19,3,TRUE) -> AMBDI Houmadi | E75: D14
A76: =Horaire!A81 -> DOUJANI | B76: =Horaire!B81 -> 0.43055556 | C76: =Horaire!C81 -> D10 | D76: =VLOOKUP(C76,'Liste chauffeur'!$B$5:$L$19,2,TRUE)&" "&VLOOKUP(C76,'Liste chauffeur'!$B$5:$L$19,3,TRUE) -> KAMARDINE Mansour (Salarié) | E76: D14
A77: =Horaire!A82 -> PASSOT LA BARGE | B77: =Horaire!B82 -> 0.43055556 | C77: =Horaire!C82 -> D2 | D77: =VLOOKUP(C77,'Liste chauffeur'!$B$5:$L$19,2,TRUE)&" "&VLOOKUP(C77,'Liste chauffeur'!$B$5:$L$19,3,TRUE) -> BARAKA Soumaila | E77: D14
A78: =Horaire!A83 -> DOUJANI | B78: =Horaire!B83 -> 0.44444444 | C78: =Horaire!C83 -> D4 | D78: =VLOOKUP(C78,'Liste chauffeur'!$B$5:$L$19,2,TRUE)&" "&VLOOKUP(C78,'Liste chauffeur'!$B$5:$L$19,3,TRUE) -> AMBDI Houmadi | E78: D14
... A81: =Horaire!A86 -> PASSOT LA BARGE | B81: =Horaire!B86 -> 0.45833333 | C81: =Horaire!C86 -> D10 | D81: =VLOOKUP(C81,'Liste chauffeur'!$B$5:$L$19,2,TRUE)&" "&VLOOKUP(C81,'Liste chauffeur'!$B$5:$L$19,3,TRUE) -> KAMARDINE Mansour (Salarié) | E81: D14
A82: =Horaire!A87 -> DOUJANI | B82: =Horaire!B87 -> 0.47222222 | C82: =Horaire!C87 -> D11 | D82: =VLOOKUP(C82,'Liste chauffeur'!$B$5:$L$19,2,TRUE)&" "&VLOOKUP(C82,'Liste chauffeur'!$B$5:$L$19,3,TRUE) -> ALLAOUI Soibrane
A83: =Horaire!A88 -> PASSOT LA BARGE | B83: =Horaire!B88 -> 0.47222222 | C83: =Horaire!C88 -> D4 | D83: =VLOOKUP(C83,'Liste chauffeur'!$B$5:$L$19,2,TRUE)&" "&VLOOKUP(C83,'Liste chauffeur'!$B$5:$L$19,3,TRUE) -> AMBDI Houmadi
A84: =Horaire!A89 -> DOUJANI | B84: =Horaire!B89 -> 0.48611111 | C84: =Horaire!C89 -> D10 | D84: =VLOOKUP(C84,'Liste chauffeur'!$B$5:$L$19,2,TRUE)&" "&VLOOKUP(C84,'Liste chauffeur'!$B$5:$L$19,3,TRUE) -> KAMARDINE Mansour (Salarié)
A85: =Horaire!A90 -> PASSOT LA BARGE | B85: =Horaire!B90 -> 0.48611111 | C85: =Horaire!C90 -> D2 | D85: =VLOOKUP(C85,'Liste chauffeur'!$B$5:$L$19,2,TRUE)&" "&VLOOKUP(C85,'Liste chauffeur'!$B$5:$L$19,3,TRUE) -> BARAKA Soumaila
A86: =Horaire!A91 -> DOUJANI | B86: =Horaire!B91 -> 0.5 | C86: =Horaire!C91 -> D4 | D86: =VLOOKUP(C86,'Liste chauffeur'!$B$5:$L$19,2,TRUE)&" "&VLOOKUP(C86,'Liste chauffeur'!$B$5:$L$19,3,TRUE) -> AMBDI Houmadi
A87: =Horaire!A92 -> PASSOT LA BARGE | B87: =Horaire!B92 -> 0.5 | C87: =Horaire!C92 -> D11 | D87: =VLOOKUP(C87,'Liste chauffeur'!$B$5:$L$19,2,TRUE)&" "&VLOOKUP(C87,'Liste chauffeur'!$B$5:$L$19,3,TRUE) -> ALLAOUI Soibrane
A88: =Horaire!A93 -> DOUJANI | B88: =Horaire!B93 -> 0.51388889 | C88: =Horaire!C93 -> D2 | D88: =VLOOKUP(C88,'Liste chauffeur'!$B$5:$L$19,2,TRUE)&" "&VLOOKUP(C88,'Liste chauffeur'!$B$5:$L$19,3,TRUE) -> BARAKA Soumaila
A89: =Horaire!A94 -> PASSOT LA BARGE | B89: =Horaire!B94 -> 0.51388889 | C89: =Horaire!C94 -> D10 | D89: =VLOOKUP(C89,'Liste chauffeur'!$B$5:$L$19,2,TRUE)&" "&VLOOKUP(C89,'Liste chauffeur'!$B$5:$L$19,3,TRUE) -> KAMARDINE Mansour (Salarié)
A90: =Horaire!A95 -> DOUJANI | B90: =Horaire!B95 -> 0.52777778 | C90: =Horaire!C95 -> D11 | D90: =VLOOKUP(C90,'Liste chauffeur'!$B$5:$L$19,2,TRUE)&" "&VLOOKUP(C90,'Liste chauffeur'!$B$5:$L$19,3,TRUE) -> ALLAOUI Soibrane
A91: =Horaire!A96 -> PASSOT LA BARGE | B91: =Horaire!B96 -> 0.52777778 | C91: =Horaire!C96 -> D4 | D91: =VLOOKUP(C91,'Liste chauffeur'!$B$5:$L$19,2,TRUE)&" "&VLOOKUP(C91,'Liste chauffeur'!$B$5:$L$19,3,TRUE) -> AMBDI Houmadi
A92: =Horaire!A97 -> DOUJANI | B92: =Horaire!B97 -> 0.54166667 | C92: =Horaire!C97 -> D10 | D92: =VLOOKUP(C92,'Liste chauffeur'!$B$5:$L$19,2,TRUE)&" "&VLOOKUP(C92,'Liste chauffeur'!$B$5:$L$19,3,TRUE) -> KAMARDINE Mansour (Salarié)
A93: =Horaire!A98 -> PASSOT LA BARGE | B93: =Horaire!B98 -> 0.54166667 | C93: =Horaire!C98 -> D2 | D93: =VLOOKUP(C93,'Liste chauffeur'!$B$5:$L$19,2,TRUE)&" "&VLOOKUP(C93,'Liste chauffeur'!$B$5:$L$19,3,TRUE) -> BARAKA Soumaila
A94: =Horaire!A99 -> DOUJANI | B94: =Horaire!B99 -> 0.55555556 | C94: =Horaire!C99 -> D4 | D94: =VLOOKUP(C94,'Liste chauffeur'!$B$5:$L$19,2,TRUE)&" "&VLOOKUP(C94,'Liste chauffeur'!$B$5:$L$19,3,TRUE) -> AMBDI Houmadi
A95: =Horaire!A100 -> PASSOT LA BARGE | B95: =Horaire!B100 -> 0.55555556 | C95: =Horaire!C100 -> D11 | D95: =VLOOKUP(C95,'Liste chauffeur'!$B$5:$L$19,2,TRUE)&" "&VLOOKUP(C95,'Liste chauffeur'!$B$5:$L$19,3,TRUE) -> ALLAOUI Soibrane | I95: Observations :
A96: =Horaire!A101 -> DOUJANI | B96: =Horaire!B101 -> 0.56944444 | C96: =Horaire!C101 -> D2 | D96: =VLOOKUP(C96,'Liste chauffeur'!$B$5:$L$19,2,TRUE)&" "&VLOOKUP(C96,'Liste chauffeur'!$B$5:$L$19,3,TRUE) -> BARAKA Soumaila
A97: =Horaire!A102 -> PASSOT LA BARGE | B97: =Horaire!B102 -> 0.56944444 | C97: =Horaire!C102 -> D10 | D97: =VLOOKUP(C97,'Liste chauffeur'!$B$5:$L$19,2,TRUE)&" "&VLOOKUP(C97,'Liste chauffeur'!$B$5:$L$19,3,TRUE) -> KAMARDINE Mansour (Salarié)
A98: =Horaire!A103 -> DOUJANI | B98: =Horaire!B103 -> 0.58333333 | C98: =Horaire!C103 -> D1 | D98: =VLOOKUP(C98,'Liste chauffeur'!$B$5:$L$19,2,TRUE)&" "&VLOOKUP(C98,'Liste chauffeur'!$B$5:$L$19,3,TRUE) -> MOHAMED Ali (laglace) | I98: Absences :
A99: =Horaire!A104 -> PASSOT LA BARGE | B99: =Horaire!B104 -> 0.58333333 | C99: =Horaire!C104 -> D4 | D99: =VLOOKUP(C99,'Liste chauffeur'!$B$5:$L$19,2,TRUE)&" "&VLOOKUP(C99,'Liste chauffeur'!$B$5:$L$19,3,TRUE) -> AMBDI Houmadi
A100: =Horaire!A105 -> DOUJANI | B100: =Horaire!B105 -> 0.59722222 | C100: =Horaire!C105 -> D8 | D100: =VLOOKUP(C100,'Liste chauffeur'!$B$5:$L$19,2,TRUE)&" "&VLOOKUP(C100,'Liste chauffeur'!$B$5:$L$19,3,TRUE) -> ISSOUF Dailami
A101: =Horaire!A106 -> PASSOT LA BARGE | B101: =Horaire!B106 -> 0.59722222 | C101: =Horaire!C106 -> D2 | D101: =VLOOKUP(C101,'Liste chauffeur'!$B$5:$L$19,2,TRUE)&" "&VLOOKUP(C101,'Liste chauffeur'!$B$5:$L$19,3,TRUE) -> BARAKA Soumaila
A102: =Horaire!A107 -> DOUJANI | B102: =Horaire!B107 -> 0.61111111 | C102: =Horaire!C107 -> D3 | D102: =VLOOKUP(C102,'Liste chauffeur'!$B$5:$L$19,2,TRUE)&" "&VLOOKUP(C102,'Liste chauffeur'!$B$5:$L$19,3,TRUE) -> ABDOURAHIM Mohamed
...

Sheet coordinateur après-midi
A1: COORDINATEUR MATIN DOUJANI NAVETTES CARIBUS MARS 2026 | I1: NOM COORDINATEUR PASSOT LA BARGE
A2: Depart | B2: Heure théorique départ | C2: Type chauffeur prévu | D2: Nom chauffeur prévu | E2: Astreinte | F2: Nom Chauffeur réel ( si différent) | G2: Heure réelle départ | H2: Nbre personnes montantes
A3: =Horaire!A8 -> DOUJANI | B3: =Horaire!B8 -> 0.20833333 | C3: =Horaire!C8 -> D1 | D3: =VLOOKUP(C3,'Liste chauffeur'!$B$5:$L$19,2,TRUE)&" "&VLOOKUP(C3,'Liste chauffeur'!$B$5:$L$19,3,TRUE) -> MOHAMED Ali (laglace) | E3: D14
A4: =Horaire!A9 -> DOUJANI | B4: =Horaire!B9 -> 0.21527778 | C4: =Horaire!C9 -> D12 | D4: =VLOOKUP(C4,'Liste chauffeur'!$B$5:$L$18,2,TRUE)&" "&VLOOKUP(C4,'Liste chauffeur'!$B$5:$L$18,3,TRUE) -> VELOU M'COLO M'Berou | E4: D14
A5: =Horaire!A10 -> DOUJANI | B5: =Horaire!B10 -> 0.22222222 | C5: =Horaire!C10 -> D5 | D5: =VLOOKUP(C5,'Liste chauffeur'!$B$5:$L$18,2,TRUE)&" "&VLOOKUP(C5,'Liste chauffeur'!$B$5:$L$18,3,TRUE) -> AMINA Selemani | E5: D14
A6: =Horaire!A11 -> DOUJANI | B6: =Horaire!B11 -> 0.22916667 | C6: =Horaire!C11 -> D13 | D6: =VLOOKUP(C6,'Liste chauffeur'!$B$5:$L$18,2,TRUE)&" "&VLOOKUP(C6,'Liste chauffeur'!$B$5:$L$18,3,TRUE) -> MOURIDI Aktoir | E6: D14
A7: =Horaire!A12 -> PASSOT LA BARGE | B7: =Horaire!B12 -> 0.22916667 | C7: =Horaire!C12 -> D1 | D7: =VLOOKUP(C7,'Liste chauffeur'!$B$5:$L$18,2,TRUE)&" "&VLOOKUP(C7,'Liste chauffeur'!$B$5:$L$18,3,TRUE) -> MOHAMED Ali (laglace) | E7: D14 | F7: =IF(ISBLANK('Feuille saisie'!X12)=TRUE,"",'Feuille saisie'!X12)
A8: =Horaire!A13 -> DOUJANI | B8: =Horaire!B13 -> 0.23611111 | C8: =Horaire!C13 -> D3 | D8: =VLOOKUP(C8,'Liste chauffeur'!$B$5:$L$18,2,TRUE)&" "&VLOOKUP(C8,'Liste chauffeur'!$B$5:$L$18,3,TRUE) -> ABDOURAHIM Mohamed | E8: D14 | F8: =IF(ISBLANK('Feuille saisie'!X13)=TRUE,"",'Feuille saisie'!X13) | I8: Observations :
A9: =Horaire!A14 -> PASSOT LA BARGE | B9: =Horaire!B14 -> 0.23611111 | C9: =Horaire!C14 -> D12 | D9: =VLOOKUP(C9,'Liste chauffeur'!$B$5:$L$18,2,TRUE)&" "&VLOOKUP(C9,'Liste chauffeur'!$B$5:$L$18,3,TRUE) -> VELOU M'COLO M'Berou | E9: D14 | F9: =IF(ISBLANK('Feuille saisie'!X14)=TRUE,"",'Feuille saisie'!X14)
A10: =Horaire!A15 -> DOUJANI | B10: =Horaire!B15 -> 0.24305556 | C10: =Horaire!C15 -> D10 | D10: =VLOOKUP(C10,'Liste chauffeur'!$B$5:$L$18,2,TRUE)&" "&VLOOKUP(C10,'Liste chauffeur'!$B$5:$L$18,3,TRUE) -> KAMARDINE Mansour (Salarié) | E10: D14 | F10: =IF(ISBLANK('Feuille saisie'!X15)=TRUE,"",'Feuille saisie'!X15)
A11: =Horaire!A16 -> PASSOT LA BARGE | B11: =Horaire!B16 -> 0.24305556 | C11: =Horaire!C16 -> D5 | D11: =VLOOKUP(C11,'Liste chauffeur'!$B$5:$L$18,2,TRUE)&" "&VLOOKUP(C11,'Liste chauffeur'!$B$5:$L$18,3,TRUE) -> AMINA Selemani | E11: D14 | F11: =IF(ISBLANK('Feuille saisie'!X16)=TRUE,"",'Feuille saisie'!X16)
A12: =Horaire!A17 -> DOUJANI | B12: =Horaire!B17 -> 0.25 | C12: =Horaire!C17 -> D1 | D12: =VLOOKUP(C12,'Liste chauffeur'!$B$5:$L$18,2,TRUE)&" "&VLOOKUP(C12,'Liste chauffeur'!$B$5:$L$18,3,TRUE) -> MOHAMED Ali (laglace) | E12: D14 | F12: =IF(ISBLANK('Feuille saisie'!X17)=TRUE,"",'Feuille saisie'!X17)
A13: =Horaire!A18 -> PASSOT LA BARGE | B13: =Horaire!B18 -> 0.25 | C13: =Horaire!C18 -> D13 | D13: =VLOOKUP(C13,'Liste chauffeur'!$B$5:$L$18,2,TRUE)&" "&VLOOKUP(C13,'Liste chauffeur'!$B$5:$L$18,3,TRUE) -> MOURIDI Aktoir
A14: =Horaire!A19 -> M'TSAPERE | B14: =Horaire!B19 -> 0.25 | C14: =Horaire!C19 -> D4 | D14: =VLOOKUP(C14,'Liste chauffeur'!$B$5:$L$18,2,TRUE)&" "&VLOOKUP(C14,'Liste chauffeur'!$B$5:$L$18,3,TRUE) -> AMBDI Houmadi | F14: =IF(ISBLANK('Feuille saisie'!X19)=TRUE,"",'Feuille saisie'!X19)
A15: =Horaire!A20 -> PASSOT LA BARGE | B15: =Horaire!B20 -> 0.25 | C15: =Horaire!C20 -> D11 | D15: =VLOOKUP(C15,'Liste chauffeur'!$B$5:$L$18,2,TRUE)&" "&VLOOKUP(C15,'Liste chauffeur'!$B$5:$L$18,3,TRUE) -> ALLAOUI Soibrane | F15: =IF(ISBLANK('Feuille saisie'!X20)=TRUE,"",'Feuille saisie'!X20)
A16: =Horaire!A21 -> DOUJANI | B16: =Horaire!B21 -> 0.25694444 | C16: =Horaire!C21 -> D12 | D16: =VLOOKUP(C16,'Liste chauffeur'!$B$5:$L$18,2,TRUE)&" "&VLOOKUP(C16,'Liste chauffeur'!$B$5:$L$18,3,TRUE) -> VELOU M'COLO M'Berou | F16: =IF(ISBLANK('Feuille saisie'!X21)=TRUE,"",'Feuille saisie'!X21)
A17: =Horaire!A22 -> PASSOT LA BARGE | B17: =Horaire!B22 -> 0.25694444 | C17: =Horaire!C22 -> D3 | D17: =VLOOKUP(C17,'Liste chauffeur'!$B$5:$L$18,2,TRUE)&" "&VLOOKUP(C17,'Liste chauffeur'!$B$5:$L$18,3,TRUE) -> ABDOURAHIM Mohamed | F17: =IF(ISBLANK('Feuille saisie'!X22)=TRUE,"",'Feuille saisie'!X22)
A18: =Horaire!A23 -> M'TSAPERE | B18: =Horaire!B23 -> 0.25694444 | C18: =Horaire!C23 -> D5 | D18: =VLOOKUP(C18,'Liste chauffeur'!$B$5:$L$18,2,TRUE)&" "&VLOOKUP(C18,'Liste chauffeur'!$B$5:$L$18,3,TRUE) -> AMINA Selemani | F18: =IF(ISBLANK('Feuille saisie'!X23)=TRUE,"",'Feuille saisie'!X23)
A19: =Horaire!A24 -> PASSOT LA BARGE | B19: =Horaire!B24 -> 0.25694444 | C19: =Horaire!C24 -> D14 | D19: =VLOOKUP(C19,'Liste chauffeur'!$B$5:$L$18,2,TRUE)&" "&VLOOKUP(C19,'Liste chauffeur'!$B$5:$L$18,3,TRUE) -> AHAMADI Laydine | F19: =IF(ISBLANK('Feuille saisie'!X24)=TRUE,"",'Feuille saisie'!X24)
A20: =Horaire!A25 -> DOUJANI | B20: =Horaire!B25 -> 0.26388889 | C20: =Horaire!C25 -> D2 | D20: =VLOOKUP(C20,'Liste chauffeur'!$B$5:$L$18,2,TRUE)&" "&VLOOKUP(C20,'Liste chauffeur'!$B$5:$L$18,3,TRUE) -> BARAKA Soumaila
A21: =Horaire!A26 -> PASSOT LA BARGE | B21: =Horaire!B26 -> 0.26388889 | C21: =Horaire!C26 -> D10 | D21: =VLOOKUP(C21,'Liste chauffeur'!$B$5:$L$18,2,TRUE)&" "&VLOOKUP(C21,'Liste chauffeur'!$B$5:$L$18,3,TRUE) -> KAMARDINE Mansour (Salarié) | F21: =IF(ISBLANK('Feuille saisie'!X26)=TRUE,"",'Feuille saisie'!X26)
A22: =Horaire!A27 -> M'TSAPERE | B22: =Horaire!B27 -> 0.26388889 | C22: =Horaire!C27 -> D7 | D22: =VLOOKUP(C22,'Liste chauffeur'!$B$5:$L$18,2,TRUE)&" "&VLOOKUP(C22,'Liste chauffeur'!$B$5:$L$18,3,TRUE) -> COMBO Said | F22: =IF(ISBLANK('Feuille saisie'!X27)=TRUE,"",'Feuille saisie'!X27)
A23: =Horaire!A28 -> PASSOT LA BARGE | B23: =Horaire!B28 -> 0.26388889 | C23: =Horaire!C28 -> D6 | D23: =VLOOKUP(C23,'Liste chauffeur'!$B$5:$L$18,2,TRUE)&" "&VLOOKUP(C23,'Liste chauffeur'!$B$5:$L$18,3,TRUE) -> ABDOU HAMIDOUNE Nassabia | F23: =IF(ISBLANK('Feuille saisie'!X28)=TRUE,"",'Feuille saisie'!X28)
A24: =Horaire!A29 -> DOUJANI | B24: =Horaire!B29 -> 0.27083333 | C24: =Horaire!C29 -> D13 | D24: =VLOOKUP(C24,'Liste chauffeur'!$B$5:$L$18,2,TRUE)&" "&VLOOKUP(C24,'Liste chauffeur'!$B$5:$L$18,3,TRUE) -> MOURIDI Aktoir | F24: =IF(ISBLANK('Feuille saisie'!X29)=TRUE,"",'Feuille saisie'!X29) | I24: Absences :
A25: =Horaire!A30 -> PASSOT LA BARGE | B25: =Horaire!B30 -> 0.27083333 | C25: =Horaire!C30 -> D1 | D25: =VLOOKUP(C25,'Liste chauffeur'!$B$5:$L$18,2,TRUE)&" "&VLOOKUP(C25,'Liste chauffeur'!$B$5:$L$18,3,TRUE) -> MOHAMED Ali (laglace) | F25: =IF(ISBLANK('Feuille saisie'!X30)=TRUE,"",'Feuille saisie'!X30)
A26: =Horaire!A31 -> M'TSAPERE | B26: =Horaire!B31 -> 0.27083333 | C26: =Horaire!C31 -> D11 | D26: =VLOOKUP(C26,'Liste chauffeur'!$B$5:$L$18,2,TRUE)&" "&VLOOKUP(C26,'Liste chauffeur'!$B$5:$L$18,3,TRUE) -> ALLAOUI Soibrane | F26: =IF(ISBLANK('Feuille saisie'!X31)=TRUE,"",'Feuille saisie'!X31)
A27: =Horaire!A32 -> PASSOT LA BARGE | B27: =Horaire!B32 -> 0.27083333 | C27: =Horaire!C32 -> D4 | D27: =VLOOKUP(C27,'Liste chauffeur'!$B$5:$L$18,2,TRUE)&" "&VLOOKUP(C27,'Liste chauffeur'!$B$5:$L$18,3,TRUE) -> AMBDI Houmadi
A28: =Horaire!A33 -> DOUJANI | B28: =Horaire!B33 -> 0.27777778 | C28: =Horaire!C33 -> D3 | D28: =VLOOKUP(C28,'Liste chauffeur'!$B$5:$L$18,2,TRUE)&" "&VLOOKUP(C28,'Liste chauffeur'!$B$5:$L$18,3,TRUE) -> ABDOURAHIM Mohamed | F28: =IF(ISBLANK('Feuille saisie'!X33)=TRUE,"",'Feuille saisie'!X33)
A29: =Horaire!A34 -> PASSOT LA BARGE | B29: =Horaire!B34 -> 0.27777778 | C29: =Horaire!C34 -> D12 | D29: =VLOOKUP(C29,'Liste chauffeur'!$B$5:$L$18,2,TRUE)&" "&VLOOKUP(C29,'Liste chauffeur'!$B$5:$L$18,3,TRUE) -> VELOU M'COLO M'Berou | F29: =IF(ISBLANK('Feuille saisie'!X34)=TRUE,"",'Feuille saisie'!X34)
A30: =Horaire!A35 -> M'TSAPERE | B30: =Horaire!B35 -> 0.27777778 | C30: =Horaire!C35 -> D14 | D30: =VLOOKUP(C30,'Liste chauffeur'!$B$5:$L$18,2,TRUE)&" "&VLOOKUP(C30,'Liste chauffeur'!$B$5:$L$18,3,TRUE) -> AHAMADI Laydine | F30: =IF(ISBLANK('Feuille saisie'!X35)=TRUE,"",'Feuille saisie'!X35)
A31: =Horaire!A36 -> PASSOT LA BARGE | B31: =Horaire!B36 -> 0.27777778 | C31: =Horaire!C36 -> D5 | D31: =VLOOKUP(C31,'Liste chauffeur'!$B$5:$L$18,2,TRUE)&" "&VLOOKUP(C31,'Liste chauffeur'!$B$5:$L$18,3,TRUE) -> AMINA Selemani | F31: =IF(ISBLANK('Feuille saisie'!X36)=TRUE,"",'Feuille saisie'!X36)
A32: =Horaire!A37 -> DOUJANI | B32: =Horaire!B37 -> 0.28472222 | C32: =Horaire!C37 -> D10 | D32: =VLOOKUP(C32,'Liste chauffeur'!$B$5:$L$18,2,TRUE)&" "&VLOOKUP(C32,'Liste chauffeur'!$B$5:$L$18,3,TRUE) -> KAMARDINE Mansour (Salarié) | F32: =IF(ISBLANK('Feuille saisie'!X37)=TRUE,"",'Feuille saisie'!X37) | I32: Trajets non effectués :
A33: =Horaire!A38 -> PASSOT LA BARGE | B33: =Horaire!B38 -> 0.28472222 | C33: =Horaire!C38 -> D2 | D33: =VLOOKUP(C33,'Liste chauffeur'!$B$5:$L$18,2,TRUE)&" "&VLOOKUP(C33,'Liste chauffeur'!$B$5:$L$18,3,TRUE) -> BARAKA Soumaila | F33: =IF(ISBLANK('Feuille saisie'!X38)=TRUE,"",'Feuille saisie'!X38)
A34: =Horaire!A39 -> M'TSAPERE | B34: =Horaire!B39 -> 0.28472222 | C34: =Horaire!C39 -> D6 | D34: =VLOOKUP(C34,'Liste chauffeur'!$B$5:$L$18,2,TRUE)&" "&VLOOKUP(C34,'Liste chauffeur'!$B$5:$L$18,3,TRUE) -> ABDOU HAMIDOUNE Nassabia | F34: =IF(ISBLANK('Feuille saisie'!X39)=TRUE,"",'Feuille saisie'!X39)
A35: =Horaire!A40 -> PASSOT LA BARGE | B35: =Horaire!B40 -> 0.28472222 | C35: =Horaire!C40 -> D7 | D35: =VLOOKUP(C35,'Liste chauffeur'!$B$5:$L$18,2,TRUE)&" "&VLOOKUP(C35,'Liste chauffeur'!$B$5:$L$18,3,TRUE) -> COMBO Said | F35: =IF(ISBLANK('Feuille saisie'!X40)=TRUE,"",'Feuille saisie'!X40) | I35: Signature Coordinateur 1 :
A36: =Horaire!A41 -> DOUJANI | B36: =Horaire!B41 -> 0.29166667 | C36: =Horaire!C41 -> D1 | D36: =VLOOKUP(C36,'Liste chauffeur'!$B$5:$L$18,2,TRUE)&" "&VLOOKUP(C36,'Liste chauffeur'!$B$5:$L$18,3,TRUE) -> MOHAMED Ali (laglace) | F36: =IF(ISBLANK('Feuille saisie'!X41)=TRUE,"",'Feuille saisie'!X41)
A37: =Horaire!A42 -> PASSOT LA BARGE | B37: =Horaire!B42 -> 0.29166667 | C37: =Horaire!C42 -> D13 | D37: =VLOOKUP(C37,'Liste chauffeur'!$B$5:$L$18,2,TRUE)&" "&VLOOKUP(C37,'Liste chauffeur'!$B$5:$L$18,3,TRUE) -> MOURIDI Aktoir | F37: =IF(ISBLANK('Feuille saisie'!X42)=TRUE,"",'Feuille saisie'!X42)
A38: =Horaire!A43 -> M'TSAPERE | B38: =Horaire!B43 -> 0.29166667 | C38: =Horaire!C43 -> D4 | D38: =VLOOKUP(C38,'Liste chauffeur'!$B$5:$L$18,2,TRUE)&" "&VLOOKUP(C38,'Liste chauffeur'!$B$5:$L$18,3,TRUE) -> AMBDI Houmadi | F38: =IF(ISBLANK('Feuille saisie'!X43)=TRUE,"",'Feuille saisie'!X43)
A39: =Horaire!A44 -> PASSOT LA BARGE | B39: =Horaire!B44 -> 0.29166667 | C39: =Horaire!C44 -> D11 | D39: =VLOOKUP(C39,'Liste chauffeur'!$B$5:$L$18,2,TRUE)&" "&VLOOKUP(C39,'Liste chauffeur'!$B$5:$L$18,3,TRUE) -> ALLAOUI Soibrane | F39: =IF(ISBLANK('Feuille saisie'!X44)=TRUE,"",'Feuille saisie'!X44)
A40: =Horaire!A45 -> DOUJANI | B40: =Horaire!B45 -> 0.29861111 | C40: =Horaire!C45 -> D12 | D40: =VLOOKUP(C40,'Liste chauffeur'!$B$5:$L$18,2,TRUE)&" "&VLOOKUP(C40,'Liste chauffeur'!$B$5:$L$18,3,TRUE) -> VELOU M'COLO M'Berou | F40: =IF(ISBLANK('Feuille saisie'!X45)=TRUE,"",'Feuille saisie'!X45)
A41: =Horaire!A46 -> PASSOT LA BARGE | B41: =Horaire!B46 -> 0.29861111 | C41: =Horaire!C46 -> D3 | D41: =VLOOKUP(C41,'Liste chauffeur'!$B$5:$L$18,2,TRUE)&" "&VLOOKUP(C41,'Liste chauffeur'!$B$5:$L$18,3,TRUE) -> ABDOURAHIM Mohamed | F41: =IF(ISBLANK('Feuille saisie'!X46)=TRUE,"",'Feuille saisie'!X46)
A42: =Horaire!A47 -> M'TSAPERE | B42: =Horaire!B47 -> 0.29861111 | C42: =Horaire!C47 -> D5 | D42: =VLOOKUP(C42,'Liste chauffeur'!$B$5:$L$18,2,TRUE)&" "&VLOOKUP(C42,'Liste chauffeur'!$B$5:$L$18,3,TRUE) -> AMINA Selemani | F42: =IF(ISBLANK('Feuille saisie'!X47)=TRUE,"",'Feuille saisie'!X47)
A43: =Horaire!A48 -> PASSOT LA BARGE | B43: =Horaire!B48 -> 0.29861111 | C43: =Horaire!C48 -> D14 | D43: =VLOOKUP(C43,'Liste chauffeur'!$B$5:$L$18,2,TRUE)&" "&VLOOKUP(C43,'Liste chauffeur'!$B$5:$L$18,3,TRUE) -> AHAMADI Laydine | F43: =IF(ISBLANK('Feuille saisie'!X48)=TRUE,"",'Feuille saisie'!X48)
A44: =Horaire!A49 -> DOUJANI | B44: =Horaire!B49 -> 0.30555556 | C44: =Horaire!C49 -> D2 | D44: =VLOOKUP(C44,'Liste chauffeur'!$B$5:$L$18,2,TRUE)&" "&VLOOKUP(C44,'Liste chauffeur'!$B$5:$L$18,3,TRUE) -> BARAKA Soumaila | F44: =IF(ISBLANK('Feuille saisie'!X49)=TRUE,"",'Feuille saisie'!X49)
A45: =Horaire!A50 -> PASSOT LA BARGE | B45: =Horaire!B50 -> 0.30555556 | C45: =Horaire!C50 -> D10 | D45: =VLOOKUP(C45,'Liste chauffeur'!$B$5:$L$18,2,TRUE)&" "&VLOOKUP(C45,'Liste chauffeur'!$B$5:$L$18,3,TRUE) -> KAMARDINE Mansour (Salarié) | F45: =IF(ISBLANK('Feuille saisie'!X50)=TRUE,"",'Feuille saisie'!X50)
A46: =Horaire!A51 -> M'TSAPERE | B46: =Horaire!B51 -> 0.30555556 | C46: =Horaire!C51 -> D7 | D46: =VLOOKUP(C46,'Liste chauffeur'!$B$5:$L$18,2,TRUE)&" "&VLOOKUP(C46,'Liste chauffeur'!$B$5:$L$18,3,TRUE) -> COMBO Said | F46: =IF(ISBLANK('Feuille saisie'!X51)=TRUE,"",'Feuille saisie'!X51)
A47: =Horaire!A52 -> PASSOT LA BARGE | B47: =Horaire!B52 -> 0.30555556 | C47: =Horaire!C52 -> D6 | D47: =VLOOKUP(C47,'Liste chauffeur'!$B$5:$L$18,2,TRUE)&" "&VLOOKUP(C47,'Liste chauffeur'!$B$5:$L$18,3,TRUE) -> ABDOU HAMIDOUNE Nassabia | F47: =IF(ISBLANK('Feuille saisie'!X52)=TRUE,"",'Feuille saisie'!X52)
... A50: =Horaire!A55 -> M'TSAPERE | B50: =Horaire!B55 -> 0.3125 | C50: =Horaire!C55 -> D11 | D50: =VLOOKUP(C50,'Liste chauffeur'!$B$5:$L$18,2,TRUE)&" "&VLOOKUP(C50,'Liste chauffeur'!$B$5:$L$18,3,TRUE) -> ALLAOUI Soibrane | F50: =IF(ISBLANK('Feuille saisie'!X55)=TRUE,"",'Feuille saisie'!X55)
A51: =Horaire!A56 -> PASSOT LA BARGE | B51: =Horaire!B56 -> 0.3125 | C51: =Horaire!C56 -> D4 | D51: =VLOOKUP(C51,'Liste chauffeur'!$B$5:$L$18,2,TRUE)&" "&VLOOKUP(C51,'Liste chauffeur'!$B$5:$L$18,3,TRUE) -> AMBDI Houmadi
A52: =Horaire!A57 -> DOUJANI | B52: =Horaire!B57 -> 0.31944444 | C52: =Horaire!C57 -> D3 | D52: =VLOOKUP(C52,'Liste chauffeur'!$B$5:$L$18,2,TRUE)&" "&VLOOKUP(C52,'Liste chauffeur'!$B$5:$L$18,3,TRUE) -> ABDOURAHIM Mohamed
A53: =Horaire!A58 -> PASSOT LA BARGE | B53: =Horaire!B58 -> 0.31944444 | C53: =Horaire!C58 -> D12 | D53: =VLOOKUP(C53,'Liste chauffeur'!$B$5:$L$18,2,TRUE)&" "&VLOOKUP(C53,'Liste chauffeur'!$B$5:$L$18,3,TRUE) -> VELOU M'COLO M'Berou | I53: Observations :
A54: =Horaire!A59 -> M'TSAPERE | B54: =Horaire!B59 -> 0.31944444 | C54: =Horaire!C59 -> D14 | D54: =VLOOKUP(C54,'Liste chauffeur'!$B$5:$L$18,2,TRUE)&" "&VLOOKUP(C54,'Liste chauffeur'!$B$5:$L$18,3,TRUE) -> AHAMADI Laydine
A55: =Horaire!A60 -> PASSOT LA BARGE | B55: =Horaire!B60 -> 0.31944444 | C55: =Horaire!C60 -> D5 | D55: =VLOOKUP(C55,'Liste chauffeur'!$B$5:$L$18,2,TRUE)&" "&VLOOKUP(C55,'Liste chauffeur'!$B$5:$L$18,3,TRUE) -> AMINA Selemani
A56: =Horaire!A61 -> DOUJANI | B56: =Horaire!B61 -> 0.32638889 | C56: =Horaire!C61 -> D10 | D56: =VLOOKUP(C56,'Liste chauffeur'!$B$5:$L$18,2,TRUE)&" "&VLOOKUP(C56,'Liste chauffeur'!$B$5:$L$18,3,TRUE) -> KAMARDINE Mansour (Salarié) | I56: Absences :
A57: =Horaire!A62 -> PASSOT LA BARGE | B57: =Horaire!B62 -> 0.32638889 | C57: =Horaire!C62 -> D2 | D57: =VLOOKUP(C57,'Liste chauffeur'!$B$5:$L$18,2,TRUE)&" "&VLOOKUP(C57,'Liste chauffeur'!$B$5:$L$18,3,TRUE) -> BARAKA Soumaila
A58: =Horaire!A63 -> M'TSAPERE | B58: =Horaire!B63 -> 0.32638889 | C58: =Horaire!C63 -> D6 | D58: =VLOOKUP(C58,'Liste chauffeur'!$B$5:$L$18,2,TRUE)&" "&VLOOKUP(C58,'Liste chauffeur'!$B$5:$L$18,3,TRUE) -> ABDOU HAMIDOUNE Nassabia
A59: =Horaire!A64 -> PASSOT LA BARGE | B59: =Horaire!B64 -> 0.32638889 | C59: =Horaire!C64 -> D7 | D59: =VLOOKUP(C59,'Liste chauffeur'!$B$5:$L$18,2,TRUE)&" "&VLOOKUP(C59,'Liste chauffeur'!$B$5:$L$18,3,TRUE) -> COMBO Said
A60: =Horaire!A65 -> DOUJANI | B60: =Horaire!B65 -> 0.33333333 | C60: =Horaire!C65 -> D1 | D60: =VLOOKUP(C60,'Liste chauffeur'!$B$5:$L$18,2,TRUE)&" "&VLOOKUP(C60,'Liste chauffeur'!$B$5:$L$18,3,TRUE) -> MOHAMED Ali (laglace)
A61: =Horaire!A66 -> PASSOT LA BARGE | B61: =Horaire!B66 -> 0.33333333 | C61: =Horaire!C66 -> D13 | D61: =VLOOKUP(C61,'Liste chauffeur'!$B$5:$L$18,2,TRUE)&" "&VLOOKUP(C61,'Liste chauffeur'!$B$5:$L$18,3,TRUE) -> MOURIDI Aktoir
A62: =Horaire!A67 -> M'TSAPERE | B62: =Horaire!B67 -> 0.33333333 | C62: =Horaire!C67 -> D4 | D62: =VLOOKUP(C62,'Liste chauffeur'!$B$5:$L$18,2,TRUE)&" "&VLOOKUP(C62,'Liste chauffeur'!$B$5:$L$18,3,TRUE) -> AMBDI Houmadi
A63: =Horaire!A68 -> PASSOT LA BARGE | B63: =Horaire!B68 -> 0.33333333 | C63: =Horaire!C68 -> D11 | D63: =VLOOKUP(C63,'Liste chauffeur'!$B$5:$L$18,2,TRUE)&" "&VLOOKUP(C63,'Liste chauffeur'!$B$5:$L$18,3,TRUE) -> ALLAOUI Soibrane | I63: Trajets non effectués :
A64: =Horaire!A69 -> DOUJANI | B64: =Horaire!B69 -> 0.34722222 | C64: =Horaire!C69 -> D2 | D64: =VLOOKUP(C64,'Liste chauffeur'!$B$5:$L$18,2,TRUE)&" "&VLOOKUP(C64,'Liste chauffeur'!$B$5:$L$18,3,TRUE) -> BARAKA Soumaila | E64: D14
A65: =Horaire!A70 -> PASSOT LA BARGE | B65: =Horaire!B70 -> 0.34722222 | C65: =Horaire!C70 -> D10 | D65: =VLOOKUP(C65,'Liste chauffeur'!$B$5:$L$18,2,TRUE)&" "&VLOOKUP(C65,'Liste chauffeur'!$B$5:$L$18,3,TRUE) -> KAMARDINE Mansour (Salarié) | E65: D14
A66: =Horaire!A71 -> DOUJANI | B66: =Horaire!B71 -> 0.36111111 | C66: =Horaire!C71 -> D11 | D66: =VLOOKUP(C66,'Liste chauffeur'!$B$5:$L$18,2,TRUE)&" "&VLOOKUP(C66,'Liste chauffeur'!$B$5:$L$18,3,TRUE) -> ALLAOUI Soibrane | E66: D14 | I66: Signature Coordinateur 1 :
A67: =Horaire!A72 -> PASSOT LA BARGE | B67: =Horaire!B72 -> 0.36111111 | C67: =Horaire!C72 -> D4 | D67: =VLOOKUP(C67,'Liste chauffeur'!$B$5:$L$18,2,TRUE)&" "&VLOOKUP(C67,'Liste chauffeur'!$B$5:$L$18,3,TRUE) -> AMBDI Houmadi | E67: D14
A68: =Horaire!A73 -> DOUJANI | B68: =Horaire!B73 -> 0.375 | C68: =Horaire!C73 -> D10 | D68: =VLOOKUP(C68,'Liste chauffeur'!$B$5:$L$18,2,TRUE)&" "&VLOOKUP(C68,'Liste chauffeur'!$B$5:$L$18,3,TRUE) -> KAMARDINE Mansour (Salarié) | E68: D14
A69: =Horaire!A74 -> PASSOT LA BARGE | B69: =Horaire!B74 -> 0.375 | C69: =Horaire!C74 -> D2 | D69: =VLOOKUP(C69,'Liste chauffeur'!$B$5:$L$18,2,TRUE)&" "&VLOOKUP(C69,'Liste chauffeur'!$B$5:$L$18,3,TRUE) -> BARAKA Soumaila | E69: D14
A70: =Horaire!A75 -> DOUJANI | B70: =Horaire!B75 -> 0.38888889 | C70: =Horaire!C75 -> D4 | D70: =VLOOKUP(C70,'Liste chauffeur'!$B$5:$L$18,2,TRUE)&" "&VLOOKUP(C70,'Liste chauffeur'!$B$5:$L$18,3,TRUE) -> AMBDI Houmadi | E70: D14
A71: =Horaire!A76 -> PASSOT LA BARGE | B71: =Horaire!B76 -> 0.38888889 | C71: =Horaire!C76 -> D11 | D71: =VLOOKUP(C71,'Liste chauffeur'!$B$5:$L$18,2,TRUE)&" "&VLOOKUP(C71,'Liste chauffeur'!$B$5:$L$18,3,TRUE) -> ALLAOUI Soibrane | E71: D14
A72: =Horaire!A77 -> DOUJANI | B72: =Horaire!B77 -> 0.40277778 | C72: =Horaire!C77 -> D2 | D72: =VLOOKUP(C72,'Liste chauffeur'!$B$5:$L$18,2,TRUE)&" "&VLOOKUP(C72,'Liste chauffeur'!$B$5:$L$18,3,TRUE) -> BARAKA Soumaila | E72: D14
A73: =Horaire!A78 -> PASSOT LA BARGE | B73: =Horaire!B78 -> 0.40277778 | C73: =Horaire!C78 -> D10 | D73: =VLOOKUP(C73,'Liste chauffeur'!$B$5:$L$18,2,TRUE)&" "&VLOOKUP(C73,'Liste chauffeur'!$B$5:$L$18,3,TRUE) -> KAMARDINE Mansour (Salarié) | E73: D14
A74: =Horaire!A79 -> DOUJANI | B74: =Horaire!B79 -> 0.41666667 | C74: =Horaire!C79 -> D11 | D74: =VLOOKUP(C74,'Liste chauffeur'!$B$5:$L$18,2,TRUE)&" "&VLOOKUP(C74,'Liste chauffeur'!$B$5:$L$18,3,TRUE) -> ALLAOUI Soibrane | E74: D14
A75: =Horaire!A80 -> PASSOT LA BARGE | B75: =Horaire!B80 -> 0.41666667 | C75: =Horaire!C80 -> D4 | D75: =VLOOKUP(C75,'Liste chauffeur'!$B$5:$L$18,2,TRUE)&" "&VLOOKUP(C75,'Liste chauffeur'!$B$5:$L$18,3,TRUE) -> AMBDI Houmadi | E75: D14
A76: =Horaire!A81 -> DOUJANI | B76: =Horaire!B81 -> 0.43055556 | C76: =Horaire!C81 -> D10 | D76: =VLOOKUP(C76,'Liste chauffeur'!$B$5:$L$18,2,TRUE)&" "&VLOOKUP(C76,'Liste chauffeur'!$B$5:$L$18,3,TRUE) -> KAMARDINE Mansour (Salarié) | E76: D14
A77: =Horaire!A82 -> PASSOT LA BARGE | B77: =Horaire!B82 -> 0.43055556 | C77: =Horaire!C82 -> D2 | D77: =VLOOKUP(C77,'Liste chauffeur'!$B$5:$L$18,2,TRUE)&" "&VLOOKUP(C77,'Liste chauffeur'!$B$5:$L$18,3,TRUE) -> BARAKA Soumaila | E77: D14
A78: =Horaire!A83 -> DOUJANI | B78: =Horaire!B83 -> 0.44444444 | C78: =Horaire!C83 -> D4 | D78: =VLOOKUP(C78,'Liste chauffeur'!$B$5:$L$18,2,TRUE)&" "&VLOOKUP(C78,'Liste chauffeur'!$B$5:$L$18,3,TRUE) -> AMBDI Houmadi | E78: D14
... A81: =Horaire!A86 -> PASSOT LA BARGE | B81: =Horaire!B86 -> 0.45833333 | C81: =Horaire!C86 -> D10 | D81: =VLOOKUP(C81,'Liste chauffeur'!$B$5:$L$18,2,TRUE)&" "&VLOOKUP(C81,'Liste chauffeur'!$B$5:$L$18,3,TRUE) -> KAMARDINE Mansour (Salarié) | E81: D14
A82: =Horaire!A87 -> DOUJANI | B82: =Horaire!B87 -> 0.47222222 | C82: =Horaire!C87 -> D11 | D82: =VLOOKUP(C82,'Liste chauffeur'!$B$5:$L$18,2,TRUE)&" "&VLOOKUP(C82,'Liste chauffeur'!$B$5:$L$18,3,TRUE) -> ALLAOUI Soibrane
A83: =Horaire!A88 -> PASSOT LA BARGE | B83: =Horaire!B88 -> 0.47222222 | C83: =Horaire!C88 -> D4 | D83: =VLOOKUP(C83,'Liste chauffeur'!$B$5:$L$18,2,TRUE)&" "&VLOOKUP(C83,'Liste chauffeur'!$B$5:$L$18,3,TRUE) -> AMBDI Houmadi
A84: =Horaire!A89 -> DOUJANI | B84: =Horaire!B89 -> 0.48611111 | C84: =Horaire!C89 -> D10 | D84: =VLOOKUP(C84,'Liste chauffeur'!$B$5:$L$18,2,TRUE)&" "&VLOOKUP(C84,'Liste chauffeur'!$B$5:$L$18,3,TRUE) -> KAMARDINE Mansour (Salarié)
A85: =Horaire!A90 -> PASSOT LA BARGE | B85: =Horaire!B90 -> 0.48611111 | C85: =Horaire!C90 -> D2 | D85: =VLOOKUP(C85,'Liste chauffeur'!$B$5:$L$18,2,TRUE)&" "&VLOOKUP(C85,'Liste chauffeur'!$B$5:$L$18,3,TRUE) -> BARAKA Soumaila
A86: =Horaire!A91 -> DOUJANI | B86: =Horaire!B91 -> 0.5 | C86: =Horaire!C91 -> D4 | D86: =VLOOKUP(C86,'Liste chauffeur'!$B$5:$L$18,2,TRUE)&" "&VLOOKUP(C86,'Liste chauffeur'!$B$5:$L$18,3,TRUE) -> AMBDI Houmadi
A87: =Horaire!A92 -> PASSOT LA BARGE | B87: =Horaire!B92 -> 0.5 | C87: =Horaire!C92 -> D11 | D87: =VLOOKUP(C87,'Liste chauffeur'!$B$5:$L$18,2,TRUE)&" "&VLOOKUP(C87,'Liste chauffeur'!$B$5:$L$18,3,TRUE) -> ALLAOUI Soibrane
A88: =Horaire!A93 -> DOUJANI | B88: =Horaire!B93 -> 0.51388889 | C88: =Horaire!C93 -> D2 | D88: =VLOOKUP(C88,'Liste chauffeur'!$B$5:$L$18,2,TRUE)&" "&VLOOKUP(C88,'Liste chauffeur'!$B$5:$L$18,3,TRUE) -> BARAKA Soumaila
A89: =Horaire!A94 -> PASSOT LA BARGE | B89: =Horaire!B94 -> 0.51388889 | C89: =Horaire!C94 -> D10 | D89: =VLOOKUP(C89,'Liste chauffeur'!$B$5:$L$18,2,TRUE)&" "&VLOOKUP(C89,'Liste chauffeur'!$B$5:$L$18,3,TRUE) -> KAMARDINE Mansour (Salarié)
A90: =Horaire!A95 -> DOUJANI | B90: =Horaire!B95 -> 0.52777778 | C90: =Horaire!C95 -> D11 | D90: =VLOOKUP(C90,'Liste chauffeur'!$B$5:$L$18,2,TRUE)&" "&VLOOKUP(C90,'Liste chauffeur'!$B$5:$L$18,3,TRUE) -> ALLAOUI Soibrane
A91: =Horaire!A96 -> PASSOT LA BARGE | B91: =Horaire!B96 -> 0.52777778 | C91: =Horaire!C96 -> D4 | D91: =VLOOKUP(C91,'Liste chauffeur'!$B$5:$L$18,2,TRUE)&" "&VLOOKUP(C91,'Liste chauffeur'!$B$5:$L$18,3,TRUE) -> AMBDI Houmadi
A92: =Horaire!A97 -> DOUJANI | B92: =Horaire!B97 -> 0.54166667 | C92: =Horaire!C97 -> D10 | D92: =VLOOKUP(C92,'Liste chauffeur'!$B$5:$L$18,2,TRUE)&" "&VLOOKUP(C92,'Liste chauffeur'!$B$5:$L$18,3,TRUE) -> KAMARDINE Mansour (Salarié)
A93: =Horaire!A98 -> PASSOT LA BARGE | B93: =Horaire!B98 -> 0.54166667 | C93: =Horaire!C98 -> D2 | D93: =VLOOKUP(C93,'Liste chauffeur'!$B$5:$L$18,2,TRUE)&" "&VLOOKUP(C93,'Liste chauffeur'!$B$5:$L$18,3,TRUE) -> BARAKA Soumaila
A94: =Horaire!A99 -> DOUJANI | B94: =Horaire!B99 -> 0.55555556 | C94: =Horaire!C99 -> D4 | D94: =VLOOKUP(C94,'Liste chauffeur'!$B$5:$L$18,2,TRUE)&" "&VLOOKUP(C94,'Liste chauffeur'!$B$5:$L$18,3,TRUE) -> AMBDI Houmadi
A95: =Horaire!A100 -> PASSOT LA BARGE | B95: =Horaire!B100 -> 0.55555556 | C95: =Horaire!C100 -> D11 | D95: =VLOOKUP(C95,'Liste chauffeur'!$B$5:$L$18,2,TRUE)&" "&VLOOKUP(C95,'Liste chauffeur'!$B$5:$L$18,3,TRUE) -> ALLAOUI Soibrane | I95: Observations :
A96: =Horaire!A101 -> DOUJANI | B96: =Horaire!B101 -> 0.56944444 | C96: =Horaire!C101 -> D2 | D96: =VLOOKUP(C96,'Liste chauffeur'!$B$5:$L$18,2,TRUE)&" "&VLOOKUP(C96,'Liste chauffeur'!$B$5:$L$18,3,TRUE) -> BARAKA Soumaila
A97: =Horaire!A102 -> PASSOT LA BARGE | B97: =Horaire!B102 -> 0.56944444 | C97: =Horaire!C102 -> D10 | D97: =VLOOKUP(C97,'Liste chauffeur'!$B$5:$L$18,2,TRUE)&" "&VLOOKUP(C97,'Liste chauffeur'!$B$5:$L$18,3,TRUE) -> KAMARDINE Mansour (Salarié)
A98: =Horaire!A103 -> DOUJANI | B98: =Horaire!B103 -> 0.58333333 | C98: =Horaire!C103 -> D1 | D98: =VLOOKUP(C98,'Liste chauffeur'!$B$5:$L$18,2,TRUE)&" "&VLOOKUP(C98,'Liste chauffeur'!$B$5:$L$18,3,TRUE) -> MOHAMED Ali (laglace) | I98: Absences :
A99: =Horaire!A104 -> PASSOT LA BARGE | B99: =Horaire!B104 -> 0.58333333 | C99: =Horaire!C104 -> D4 | D99: =VLOOKUP(C99,'Liste chauffeur'!$B$5:$L$18,2,TRUE)&" "&VLOOKUP(C99,'Liste chauffeur'!$B$5:$L$18,3,TRUE) -> AMBDI Houmadi
A100: =Horaire!A105 -> DOUJANI | B100: =Horaire!B105 -> 0.59722222 | C100: =Horaire!C105 -> D8 | D100: =VLOOKUP(C100,'Liste chauffeur'!$B$5:$L$18,2,TRUE)&" "&VLOOKUP(C100,'Liste chauffeur'!$B$5:$L$18,3,TRUE) -> ISSOUF Dailami
A101: =Horaire!A106 -> PASSOT LA BARGE | B101: =Horaire!B106 -> 0.59722222 | C101: =Horaire!C106 -> D2 | D101: =VLOOKUP(C101,'Liste chauffeur'!$B$5:$L$18,2,TRUE)&" "&VLOOKUP(C101,'Liste chauffeur'!$B$5:$L$18,3,TRUE) -> BARAKA Soumaila
A102: =Horaire!A107 -> DOUJANI | B102: =Horaire!B107 -> 0.61111111 | C102: =Horaire!C107 -> D3 | D102: =VLOOKUP(C102,'Liste chauffeur'!$B$5:$L$18,2,TRUE)&" "&VLOOKUP(C102,'Liste chauffeur'!$B$5:$L$18,3,TRUE) -> ABDOURAHIM Mohamed
A103: =Horaire!A108 -> PASSOT LA BARGE | B103: =Horaire!B108 -> 0.61111111 | C103: =Horaire!C108 -> D1 | D103: =VLOOKUP(C103,'Liste chauffeur'!$B$5:$L$18,2,TRUE)&" "&VLOOKUP(C103,'Liste chauffeur'!$B$5:$L$18,3,TRUE) -> MOHAMED Ali (laglace)
A104: =Horaire!A109 -> DOUJANI | B104: =Horaire!B109 -> 0.625 | C104: =Horaire!C109 -> D6 | D104: =VLOOKUP(C104,'Liste chauffeur'!$B$5:$L$18,2,TRUE)&" "&VLOOKUP(C104,'Liste chauffeur'!$B$5:$L$18,3,TRUE) -> ABDOU HAMIDOUNE Nassabia
...

Sheet coordinateur samedi
A1: COORDINATEUR SAMEDI LIGNE 3 NAVETTES CARIBUS | E1: 46082 | I1: NOM COORDINATEUR
A2: Depart | B2: Heure théorique départ | C2: Type chauffeur prévu | D2: Nom chauffeur prévu | E2: Astreinte | F2: Nom Chauffeur réel ( si différent) | G2: Heure réelle départ | H2: Nbre personnes montantes
