Workbook

Sheet Feuil1
A3: DATE
A4: CHAUFFEUR
E6: Arrêt 1 | I6: Arrêt 2 | M6: Arrêt 3 | Q6: PEM PASSAMAINTY
B7: Heure théorique départ | C7: Heure réelle départ | D7: Nbre personnes + | E7: Nbre personnes + | F7: Nbre personnes - | G7: Heure arrivée arrêt 1 | H7: Délai | I7: Nbre personnes + | J7: Nbre personnes - | K7: Heure arrivée arrêt 2 | L7: Délai | M7: Nbre personnes + | N7: Nbre personnes - | O7: Heure arrivée arrêt 3 | P7: Délai | Q7: Nbre personnes - | S7: Heure arrivée finale | T7: Commentaires | U7: Temps Aller
A8: VAHIBE | B8: 0.20833333 | H8: =G8-C8 -> 0 | L8: =K8-G8 -> 0 | P8: =O8-K8 -> 0 | R8: =IF(D8+E8-F8+I8-J8+M8-N8=Q8,"OK",D8+E8-F8+I8-J8+M8-N8-Q8) -> OK | U8: =S8-C8 -> 0
A9: VAHIBE | B9: 0.21527778 | H9: =G9-C9 -> 0 | L9: =K9-G9 -> 0 | P9: =O9-K9 -> 0 | U9: =S9-C9 -> 0
A10: VAHIBE | B10: 0.22222222 | H10: =G10-C10 -> 0 | L10: =K10-G10 -> 0 | P10: =O10-K10 -> 0 | U10: =S10-C10 -> 0
A11: VAHIBE | B11: 0.22916667 | H11: =G11-C11 -> 0 | L11: =K11-G11 -> 0 | P11: =O11-K11 -> 0 | U11: =S11-C11 -> 0
A12: VAHIBE | B12: 0.23611111 | H12: =G12-C12 -> 0 | L12: =K12-G12 -> 0 | P12: =O12-K12 -> 0 | U12: =S12-C12 -> 0
A13: VAHIBE | B13: 0.24305556 | H13: =G13-C13 -> 0 | L13: =K13-G13 -> 0 | P13: =O13-K13 -> 0 | U13: =S13-C13 -> 0
A14: VAHIBE | B14: 0.25 | H14: =G14-C14 -> 0 | L14: =K14-G14 -> 0 | P14: =O14-K14 -> 0 | U14: =S14-C14 -> 0
A15: VAHIBE | B15: 0.25694444 | H15: =G15-C15 -> 0 | L15: =K15-G15 -> 0 | P15: =O15-K15 -> 0 | U15: =S15-C15 -> 0
A16: VAHIBE | B16: 0.26388889 | H16: =G16-C16 -> 0 | L16: =K16-G16 -> 0 | P16: =O16-K16 -> 0 | U16: =S16-C16 -> 0
A17: VAHIBE | B17: 0.27083333 | H17: =G17-C17 -> 0 | L17: =K17-G17 -> 0 | P17: =O17-K17 -> 0 | U17: =S17-C17 -> 0
A18: VAHIBE | B18: 0.27777778 | H18: =G18-C18 -> 0 | L18: =K18-G18 -> 0 | P18: =O18-K18 -> 0 | U18: =S18-C18 -> 0
A19: VAHIBE | B19: 0.28472222 | H19: =G19-C19 -> 0 | L19: =K19-G19 -> 0 | P19: =O19-K19 -> 0 | U19: =S19-C19 -> 0
A20: VAHIBE | B20: 0.29166667 | H20: =G20-C20 -> 0 | L20: =K20-G20 -> 0 | P20: =O20-K20 -> 0 | U20: =S20-C20 -> 0
... A26: VAHIBE | B26: 0.33333333 | H26: =G26-C26 -> 0 | L26: =K26-G26 -> 0 | P26: =O26-K26 -> 0 | U26: =S26-C26 -> 0
Q27: VAHIBE | U27: =SUM(U8:U26) -> 0
A28: PEM PASSAMAINTY | B28: 0.625 | H28: =G28-C28 -> 0 | L28: =K28-G28 -> 0 | P28: =O28-K28 -> 0 | U28: =S28-C28 -> 0
A29: PEM PASSAMAINTY | B29: 0.63194444 | H29: =G29-C29 -> 0 | L29: =K29-G29 -> 0 | P29: =O29-K29 -> 0 | U29: =S29-C29 -> 0
A30: PEM PASSAMAINTY | B30: 0.63888889 | H30: =G30-C30 -> 0 | L30: =K30-G30 -> 0 | P30: =O30-K30 -> 0 | U30: =S30-C30 -> 0
A31: PEM PASSAMAINTY | B31: 0.64583333 | H31: =G31-C31 -> 0 | L31: =K31-G31 -> 0 | P31: =O31-K31 -> 0 | U31: =S31-C31 -> 0
A32: PEM PASSAMAINTY | B32: 0.65277778 | H32: =G32-C32 -> 0 | L32: =K32-G32 -> 0 | P32: =O32-K32 -> 0 | U32: =S32-C32 -> 0
A33: PEM PASSAMAINTY | B33: 0.65972222 | H33: =G33-C33 -> 0 | L33: =K33-G33 -> 0 | P33: =O33-K33 -> 0 | U33: =S33-C33 -> 0
A34: PEM PASSAMAINTY | B34: 0.66666667 | H34: =G34-C34 -> 0 | L34: =K34-G34 -> 0 | P34: =O34-K34 -> 0 | U34: =S34-C34 -> 0
A35: PEM PASSAMAINTY | B35: 0.67361111 | H35: =G35-C35 -> 0 | L35: =K35-G35 -> 0 | P35: =O35-K35 -> 0 | U35: =S35-C35 -> 0
A36: PEM PASSAMAINTY | B36: 0.68055556 | H36: =G36-C36 -> 0 | L36: =K36-G36 -> 0 | P36: =O36-K36 -> 0 | U36: =S36-C36 -> 0
A37: PEM PASSAMAINTY | B37: 0.6875 | H37: =G37-C37 -> 0 | L37: =K37-G37 -> 0 | P37: =O37-K37 -> 0 | U37: =S37-C37 -> 0
A38: PEM PASSAMAINTY | B38: 0.69444444 | H38: =G38-C38 -> 0 | L38: =K38-G38 -> 0 | P38: =O38-K38 -> 0 | U38: =S38-C38 -> 0
A39: PEM PASSAMAINTY | B39: 0.70138889 | H39: =G39-C39 -> 0 | L39: =K39-G39 -> 0 | P39: =O39-K39 -> 0 | U39: =S39-C39 -> 0
... A46: PEM PASSAMAINTY | B46: 0.75 | H46: =G46-C46 -> 0 | L46: =K46-G46 -> 0 | P46: =O46-K46 -> 0 | U46: =S46-C46 -> 0
U47: =SUM(U28:U46) -> 0
U48: =U47+U27 -> 0
C49: Signature Chauffeur | I49: Signature Coordinateur

Sheet REUNION DU 28.04
B1: N° | C1: CADEMA | D1: STATUT | E1: LICENCE TRANSPORTEUR | F1: SIREN LICENCE | G1: VALIDITE LICENCE TRANSP | H1: N° | I1: N° Chauffeur | J1: Type | K1: Nom | L1: Prénom | M1: Téléphone | N1: Mail | O1: Siret | P1: Secteur d'activité | Q1: N° licence | R1: CARTE CONDUCTEUR | S1: VALIDITE CARTE CONDUCTEUR | T1: N° IMMATRICULATION CARTE GRISE | U1: DATE IMMATRICULATION | V1: AGE DU VEHICULE | W1: Type de vehicule | X1: ETAT VEHICULE | Y1: RDV MAY EQUIP | Z1: HABILLAGE | AA1: REGLT HABILLAGE | AB1: EQUIPEMENT | AC1: HABILLAGE 2021 | AD1: HABILLAGE 2023 | AE1: IDENTITE | AF1: NATIONALITE | AG1: VALIDITE CARTE SEJOUR | AH1: CARTE VITALE | AI1: ASSURANCES | AJ1: FACTURE _3 MOIS | AK1: IMPOTS | AL1: PHOTO | AM1: N° AGC | AN1: Capital souscrit | AO1: Année de souscription | AP1: Cotisations versées en 2021 | AQ1: COTISATIONS 2023 | AR1: COTISATIONS 2024 | AS1: N° Rue | AT1: Adresse | AU1: Code postal | AV1: Commune | AW1: REMARQUES
A2: 1 | B2: 11 | C2: CADEMA 1 | D2: AO | E2: NON | F2: - | G2: - | H2: 1 | I2: C4 | J2: C2 | K2: ABDOU MINIHADJI | L2: Amada | M2: 0639 65 03 93 | N2: abdouminihadjiamada@hotmail.com | O2: 066 311 101 000 19 | P2: Centre Sud | Q2: 976-CS-057 | R2: 505 | S2: 45305 | T2: FY-654-BF | U2: 44279 | V2: =2024-YEAR(U2) -> 3 | W2: 9 PLACES | X2: BON | Z2: OUI | AA2: _ | AB2: NON | AC2: OUI | AE2: 43262 | AF2: F | AG2: _ | AH2: NON | AI2: NON | AJ2: 2020 | AL2: OUI | AM2: 2020/13 | AN2: 510 | AO2: 43466 | AP2: 450 | AS2: 64 | AT2: Avenue de rassi | AU2: 97670 | AV2: Chiconi | AW2: ancien gérant - Habillage 2021
A3: 33 | B3: 17 | C3: CADEMA 1 | D3: AO | E3: NON | F3: - | G3: - | H3: 2 | I3: C6 | J3: C10 | K3: ADINANI | L3: Zoubert | M3: 0639 25 77 76 | N3: zoubert.adinani2@gmail.com | O3: 799 358 700 00018 | P3: Mamoudzou | Q3: 976-M-447 | R3: 1050 | S3: 46342 | T3: GR-407-DV | U3: 45182 | V3: =2024-YEAR(U3) -> 1 | W3: 9 PLACES | X3: BON | Y3: 45406 | Z3: NON | AA3: OUI | AB3: NON | AC3: NON | AD3: A venir | AE3: 48415 | AF3: F | AG3: _ | AH3: OUI | AI3: OUI | AJ3: OUI | AK3: 2022 | AL3: OUI | AN3: 510 | AO3: 43466 | AP3: 250 | AQ3: NON | AR3: NON | AT3: Tahiti plage route de poroani | AU3: 97640 | AV3: Sada | AW3: attente débolacge prêt
A4: 65 | B4: 23 | C4: CADEMA 1 | D4: AO | E4: NON | F4: - | G4: - | H4: 3 | J4: C14 | K4: ALI ATTOUMANI | L4: Bacar | M4: 0639 87 21 88 | N4: aattoumani.bacar@gmail.com | O4: 024 068 413 00020 | P4: Mamoudzou | Q4: 976-M-116 | R4: 222 | S4: 45489 | T4: FJ-886-VX | U4: 43707 | W4: 9 PLACES | Z4: A MOITIE | AA4: NON | AC4: OUI PAS PAYE | AE4: 45896 | AF4: F | AH4: NON | AI4: NON | AJ4: NON | AK4: NON | AL4: OUI | AN4: 510 | AO4: 43466 | AP4: 150 | AQ4: NON | AR4: NON | AS4: 4 | AT4: Chemin ma ali andy | AU4: 97640 | AV4: Sada | AW4: Voiture endommagé d'un coté et la tete de taxi aussi habillé en 2021
A5: 129 | B5: 35 | C5: CADEMA 1 | D5: AO | E5: NON | F5: - | G5: - | H5: 4 | K5: ALLAOUI | L5: Inzoudine | M5: 0639 075923/0639 26 27 78 | N5: ambdihoumadi976@gmail.com | O5: 024 078 396 000 41 | P5: Mamoudzou | Q5: 976-M-049 | R5: 1294 | S5: 43992 | T5: GH-790-LS | U5: 44753 | V5: =2024-YEAR(U5) -> 2 | W5: 9 PLACES | Y5: ? Pas payé | Z5: NON | AA5: _ | AB5: NON | AE5: 47882 | AF5: F | AG5: _ | AH5: NON | AI5: NON | AJ5: NON | AK5: NON | AL5: NON | AM5: 2020/44 | AN5: 510 | AO5: 43466 | AP5: 450 | AS5: 85 | AT5: Rue younoussa bamana | AU5: 97640 | AV5: Sada | AW5: a une voiture neuve
A6: 161 | B6: 41 | C6: CADEMA 1 | D6: AO | E6: NON | F6: - | G6: - | H6: 5 | I6: voiture en panne | K6: ALLAOUI | L6: Soibrane | M6: 0639 65 31 82 | N6: stt653182@hotmail.com | O6: 024 043 30 000 11 | P6: Centre Sud | Q6: 976-CS-048 | R6: 806 | S6: 43222 | T6: FZ_148_HW | U6: 44336 | V6: =2024-YEAR(U6) -> 3 | W6: 9 PLACES | X6: OK | Y6: ? Pas payé | Z6: NON | AB6: NON | AC6: OUI | AE6: 46556 | AF6: F | AG6: _ | AH6: OUI | AI6: OUI | AJ6: OUI | AK6: OUI | AL6: OUI | AN6: 510 | AP6: 450 | AT6: Quartier Kami case impasse mavandzani | AU6: 97625 | AV6: Kani kéli | AW6: Il est pas eligible pour la demande de subvention
A7: 129 | B7: 35 | C7: CADEMA 1 | D7: AO | E7: NON | F7: - | G7: - | H7: 6 | J7: C6 | K7: AMBDI | L7: Houmadi | M7: 0639 23 55 69 | N7: ambdihoumadi976@gmail.com | O7: 066 312 224 000 26 | P7: Sud | Q7: 976-S-023 | R7: 759 | S7: 45639 | T7: GC-122-QA | U7: 44495 | V7: =2024-YEAR(U7) -> 3 | W7: 9 PLACES | X7: OK | Z7: OUI | AB7: OUI | AD7: OUI | AE7: 48640 | AF7: F | AG7: _ | AH7: OUI | AI7: OUI | AJ7: NON | AK7: 2022 | AL7: OUI | AM7: 2020/46 | AN7: 510 | AO7: 43466 | AP7: 250 | AQ7: NON | AR7: NON | AT7: Route nationale Mbouanatsa | AU7: 97620 | AV7: BOUENI | AW7: Habillage 2023
A8: 193 | B8: 47 | C8: CADEMA 1 | D8: AO | E8: NON | F8: - | G8: - | H8: 7 | I8: C9 | J8: C7 | K8: BINA HALADI | L8: Bina | M8: 0639 06 05 82 | N8: wonamaore@gmail.com | O8: 853 690 428 000 18 | P8: Sud | Q8: 976-S-045 | R8: 1414 | S8: 45181 | T8: GE-883-ES | U8: 44581 | V8: =2024-YEAR(U8) -> 2 | W8: 9 places | Z8: OUI | AA8: _ | AB8: OUI | AD8: OUI | AE8: 45040 | AF8: F | AG8: _ | AH8: OUI | AI8: 2023 | AJ8: OUI | AK8: 2022 | AL8: NON | AM8: 2020/61 | AN8: 510 | AO8: 44285 | AP8: 450 | AS8: 8 | AT8: Rue Said Fatima | AU8: 97640 | AV8: SADA | AW8: Habillage juin 2023
A9: 225 | B9: 53 | C9: CADEMA 1 | D9: AO | E9: NON | F9: - | G9: - | H9: 8 | J9: C12 | K9: BOINARIZIKI | L9: Zena Dhurari | M9: 0639 66 36 94 06 50 45 94 42 | N9: dhurari.transport@gmail.com | O9: 500 894 043 000 16 | P9: Centre Sud | Q9: 976-CS-071 | R9: 1000 | S9: 44349 | T9: FF-569-NF | U9: 43573 | V9: =2024-YEAR(U9) -> 5 | W9: 9 PLACES | Z9: NON | AA9: _ | AB9: NON | AE9: 45177 | AF9: F | AG9: _ | AH9: OUI | AI9: 2023 | AJ9: OUI | AK9: 2022 | AL9: OUI | AN9: 510 | AO9: 43466 | AP9: 250 | AS9: 97 | AT9: Rue du commerce | AU9: 97640 | AV9: Sada | AW9: voiture pas habillée
A10: 257 | B10: 59 | C10: CADEMA 1 | D10: AO | E10: NON | F10: - | G10: - | H10: 9 | I10: C3 | J10: C8 | K10: COMBO | L10: Said | M10: 0639 68 37 93 | N10: combosaid5@gmail.cpm | O10: 054 394 853 00029 | P10: Mamoudzou | Q10: 976-M-164 | R10: 920 | S10: 44871 | T10: GB-965-EQ | U10: 44419 | V10: =2024-YEAR(U10) -> 3 | W10: 9 PLACES | X10: NEUF | Y10: 45411 | Z10: NON | AA10: NON | AB10: NON | AC10: NON | AD10: NON | AE10: 49279 | AF10: F | AG10: _ | AH10: OUI | AI10: OUI | AJ10: 2024 | AK10: 2022 | AL10: NON | AM10: 2020/70 | AN10: 510 | AO10: 44295 | AP10: 100 | AQ10: NON | AR10: NON | AS10: 193 | AT10: Route Départementale | AU10: 97630 | AV10: Mtsamboro | AW10: Il a reçu sa subvention et il a rien payé, et il a utiliser l'argent
A11: 289 | B11: 65 | C11: CADEMA 1 | D11: AO | E11: NON | F11: - | G11: - | H11: 10 | I11: C1 | J11: C1 | K11: EL ANZIZE SALIM | L11: Hamada | M11: 0639 22 81 28 | N11: elsalimhamada@hotmail.com | O11: 024 076 531 00011 | P11: Mamoudzou | Q11: 976_M_209 | R11: 413 | S11: 46877 | T11: GM_515_YL | U11: 45012 | V11: =2024-YEAR(U11) -> 1 | W11: 9 PLACES | Z11: 2023 | AA11: OUI | AB11: 2023 | AD11: OUI | AE11: 10959 | AF11: G | AG11: _ | AH11: NON | AI11: NON | AJ11: NON | AK11: NON | AL11: OUI | AM11: 2022/198 | AN11: 510 | AO11: 43466 | AP11: 250 | AS11: 8 | AT11: Rue de mjinpia | AU11: 97650 | AV11: Mtsangamoudji | AW11: habillage 9 place 2023
A12: 353 | B12: 77 | C12: CADEMA 1 | D12: AO | E12: NON | F12: - | G12: - | H12: 11 | I12: C5 | J12: C16 | K12: HADHURAMI | L12: Makinedine | M12: 0639 94 46 40 | N12: Hadhuramimakinedine976@gmail.com | O12: 054 397 211 00019 | P12: SUD | Q12: 976_S_069 | R12: 150 | S12: 45874 | T12: FZ-411-ZD | U12: 44362 | V12: =2024-YEAR(U12) -> 3 | W12: 9 PLACES | Z12: OUI | AB12: OUI | AD12: OUI | AE12: 49522 | AF12: F | AG12: _ | AH12: OUI | AI12: 2023 | AJ12: NON | AK12: 2022 | AL12: OUI | AM12: 2020/82 | AN12: 510 | AO12: 43466 | AP12: 550 | AS12: 14 | AT12: Rue foundi hamada m'zé | AU12: 97625 | AV12: Kani kéli | AW12: Habillage 2021 aurait 2 véhicules
A13: 385 | B13: 83 | C13: CADEMA 1 | D13: AO | E13: NON | F13: - | G13: - | H13: 12 | J13: C13 | K13: MADI BOINA | L13: Mkidachi | M13: 0639 22 08 67 | N13: madiboinamkidachi@hotmail.com | O13: 500 793 526 00012 | P13: NORD | Q13: 976-N-63 | R13: 985 | S13: 44456 | T13: GS-501-ZK | U13: 45273 | W13: 9 PLACES | X13: NEUF | Y13: pas de vitre | Z13: NON | AA13: OUI | AB13: OUI | AC13: NON | AD13: A venir | AE13: 45248 | AF13: F | AH13: NON | AI13: NON | AJ13: NON | AK13: NON | AL13: NON | AN13: 510 | AO13: 43466 | AP13: 150 | AQ13: NON | AR13: NON | AS13: 27 | AT13: Rue d'andimaka | AU13: 97650 | AV13: Mtsangamouji
A14: 417 | B14: 89 | C14: CADEMA 1 | D14: AO | E14: NON | F14: - | G14: - | H14: 13 | I14: C7 | J14: C3 | K14: MOISSULI HIMIDI | L14: Enly | M14: 0639 94 58 14 | N14: enlymoissuli@gmail.com | O14: 853 881 084 000 18 | P14: NORD | Q14: 976-N-015 | R14: 994 | S14: 44263 | T14: GW-003-JA | U14: 45394 | W14: 9 PLACES | Y14: att May Equip | Z14: NON | AA14: NON | AB14: NON | AC14: NON | AD14: NON | AE14: 47621 | AF14: F | AH14: NON | AI14: NON | AJ14: NON | AK14: NON | AL14: OUI | AN14: 510 | AO14: 43466 | AP14: 200 | AQ14: NON | AR14: NON | AS14: 5 | AT14: Quartier mronobaban sidi , Hamjago | AU14: 97630 | AV14: Mtsamboro | AW14: Il attend sa subvention , justine lui a dit d'aller harceler le CD pour qui'il debloque sa subvention
A15: 97 | B15: 29 | C15: CADEMA 1 | D15: AO | E15: NON | F15: - | G15: - | H15: 14 | I15: soucis de famille | J15: C4 | K15: OUSSENI | L15: Soula | M15: 0639 69 03 87 | N15: soulaousseni415@gmail.com | O15: 066 307 372 000 12 | P15: Centre NORD | Q15: 976-CN-003 | R15: 249 | S15: 43132 | T15: GP_813_HX | U15: 45083 | V15: =2024-YEAR(U15) -> 1 | W15: 9 PLACES | X15: TBE | Z15: 2023 | AA15: OUI | AB15: 2023 | AD15: OUI | AE15: 49496 | AF15: F | AG15: _ | AH15: OUI | AI15: OUI | AJ15: OUI | AK15: OUI | AL15: OUI | AM15: 2021/181 | AN15: 510 | AO15: 43466 | AP15: 300 | AS15: 2 | AT15: Rue mnadzi moja quartier baitil mali | AU15: 97600 | AV15: Mamoudzou | AW15: Pas de voiture
A16: 321 | B16: 71 | C16: CADEMA 1 | D16: AO | E16: NON | F16: - | G16: - | H16: 15 | I16: C8 | J16: C5 | K16: RENE | L16: Assanati | M16: 0639 07 82 51 | O16: 024 065 633 000 18 | P16: NORD | Q16: 976-N-032 | R16: 1337 | S16: 45235 | T16: GR-921-XZ | U16: 45219 | V16: =2024-YEAR(U16) -> 1 | W16: 9 PLACES | Z16: OUI | AB16: NON | AD16: OUI | AE16: 48068 | AF16: F | AG16: _ | AH16: OUI | AI16: 2023 | AJ16: OUI | AK16: 2022 | AN16: 510 | AO16: 44171 | AP16: 150 | AS16: 32 | AT16: Rue bacar tsimanda | AU16: 97650 | AV16: Mtsangamouji
A17: 49 | B17: 20 | C17: CADEMA 1 | E17: NON | F17: NON | G17: NON | H17: 16 | J17: C9 | K17: SANDI | L17: Maanrouf | M17: 0639 40 58 85 | N17: maanroufsandi@laposte.net | O17: 024 069 635 000 19 | P17: Sud | Q17: 976-S-006 | R17: 1184 | S17: 45262 | T17: GW-255-NY | U17: 45406 | W17: 9 PLACES | X17: NEUF | Z17: NON | AA17: OUI | AB17: NON | AC17: NON | AD17: A VENIR | AE17: 46707 | AF17: F | AH17: OUI | AI17: OUI | AJ17: OUI | AK17: 2022 | AL17: NON | AN17: 510 | AO17: 43466 | AP17: 300 | AQ17: NON | AR17: NON | AT17: Quartier ecole primaire | AU17: 97620 | AV17: Chirongui | AW17: Pas habillé en attente rendez-vous mayotte equipement
A18: 177 | B18: 44 | C18: CADEMA 1 | E18: NON | F18: NON | G18: NON | H18: 17 | I18: C2 | J18: C11 | K18: TOUMBOU | L18: Toibourani | M18: 0639 19 14 22 | N18: toumboutoibourani@outlook.fr / anlia.toumbou97620@gmail.com | O18: 024 054 710 000 25 | P18: Mamoudzou | Q18: 976-M-177 | R18: 357 | S18: 45028 | T18: GF_215_AQ | U18: 44624 | V18: =2024-YEAR(U18) -> 2 | W18: 9 PLACES | X18: OK | Z18: 2023 | AA18: OUI | AB18: 2023 | AD18: OUI | AE18: 45992 | AF18: F | AH18: OUI | AI18: OUI | AJ18: NON | AK18: 2022 | AL18: OUI | AM18: 2020/158 | AN18: 510 | AO18: 43466 | AP18: 350 | AS18: 9 | AT18: Rue Bambou | AU18: 97620 | AV18: Chirongui | AW18: Gérant
A22: 17 | B22: 14 | C22: CADEMA 1 | E22: NON | F22: NON | G22: NON | H22: 2 | K22: ACHIRAFFI pas de chauffeur | L22: Assad | M22: 0639 29 01 58 | N22: achiraffis@gmail.com | O22: 024 046 617 000 15 | P22: Mamoudzou | Q22: 976-M-045 | R22: 90 | S22: 46916 | T22: FY-973-FL | U22: 44285 | V22: =2024-YEAR(U22) -> 3 | W22: 9 PLACES | X22: BON | Z22: OUI | AA22: OUI | AB22: OUI | AC22: OUI | AD22: NON | AE22: 49237 | AF22: F | AG22: _ | AH22: OUI | AI22: OUI | AJ22: OUI | AK22: 2022 | AL22: OUI | AM22: 2020/20 | AN22: 510 | AO22: 43466 | AP22: 450 | AQ22: NON | AR22: NON | AS22: 474 | AT22: Route départemental | AU22: 97630 | AV22: M'tsamboro | AW22: a une voiture - Travaille au Sud

Sheet Feuille saisie
A2: TYPE | B2: C15
A3: DATE | B3: 45627
A4: CHAUFFEUR | B4: =VLOOKUP(B2,'Liste chauffeur'!$B$5:$L$20,2,TRUE)&" "&VLOOKUP(B2,'Liste chauffeur'!$B$5:$L$20,3,TRUE) -> HAMADA Babou
I6: Arrêts | K6: ARRIVEE | P6: 8
A7: Lieu de départ | B7: Heure théorique départ | C7: Horaire | D7: Chauffeur | E7: Heure réelle départ | F7: Trajet non effectué | G7: Départ avec plus de 10 mns retard | H7: Nbre personnes montée | I7: - | J7: + | K7: Nbre personnes descente | L7: Heure arrivée finale | M7: Commentaires | N7: Temps Aller | O7: Nbre personnes moyenne | P7: Capacité max | Q7: Taux Fréquentation
A8: =Horaire!A8 -> VAHIBE | B8: =Horaire!B8 -> 0.1875 | C8: =Horaire!C8 -> C2 | D8: =VLOOKUP(C8,'Liste chauffeur'!$B$5:$L$20,2,TRUE)&" "&VLOOKUP(C8,'Liste chauffeur'!$B$5:$L$20,3,TRUE) -> BINA HALADI Bina | F8: =COUNTBLANK(E8) -> 1 | N8: =IF(F8=1,"",L8-E8) | O8: =H8+J8-I8 -> 0 | P8: =IF(F8=1,0,P$6) -> 0 | Q8: =IF(P8=0,0,O8/P8) -> 0
A9: =Horaire!A9 -> VAHIBE | B9: =Horaire!B9 -> 0.19444444 | C9: =Horaire!C9 -> C1 | D9: =VLOOKUP(C9,'Liste chauffeur'!$B$5:$L$20,2,TRUE)&" "&VLOOKUP(C9,'Liste chauffeur'!$B$5:$L$20,3,TRUE) -> EL ANZIZE SALIM Hamada | F9: =COUNTBLANK(E9) -> 1 | N9: =IF(F9=1,"",L9-E9) | O9: =H9+J9-I9 -> 0 | P9: =IF(F9=1,0,P$6) -> 0 | Q9: =IF(P9=0,0,O9/P9) -> 0
A10: =Horaire!A10 -> VAHIBE | B10: =Horaire!B10 -> 0.20138889 | C10: =Horaire!C10 -> C3 | D10: =VLOOKUP(C10,'Liste chauffeur'!$B$5:$L$20,2,TRUE)&" "&VLOOKUP(C10,'Liste chauffeur'!$B$5:$L$20,3,TRUE) -> ABDOU MINIHADJI Amada | F10: =COUNTBLANK(E10) -> 1 | N10: =IF(F10=1,"",L10-E10) | O10: =H10+J10-I10 -> 0 | P10: =IF(F10=1,0,P$6) -> 0 | Q10: =IF(P10=0,0,O10/P10) -> 0
A11: =Horaire!A11 -> PASSAMAINTY | B11: =Horaire!B11 -> 0.20138889 | C11: =Horaire!C11 -> C2 | D11: =VLOOKUP(C11,'Liste chauffeur'!$B$5:$L$20,2,TRUE)&" "&VLOOKUP(C11,'Liste chauffeur'!$B$5:$L$20,3,TRUE) -> BINA HALADI Bina | F11: =COUNTBLANK(E11) -> 1 | N11: =IF(F11=1,"",L11-E11) | O11: =H11+J11-I11 -> 0 | P11: =IF(F11=1,0,P$6) -> 0 | Q11: =IF(P11=0,0,O11/P11) -> 0
A12: =Horaire!A12 -> VAHIBE | B12: =Horaire!B12 -> 0.20833333 | C12: =Horaire!C12 -> C4 | D12: =VLOOKUP(C12,'Liste chauffeur'!$B$5:$L$20,2,TRUE)&" "&VLOOKUP(C12,'Liste chauffeur'!$B$5:$L$20,3,TRUE) -> TOUMBOU Toibourani | F12: =COUNTBLANK(E12) -> 1 | N12: =IF(F12=1,"",L12-E12) | O12: =H12+J12-I12 -> 0 | P12: =IF(F12=1,0,P$6) -> 0 | Q12: =IF(P12=0,0,O12/P12) -> 0
A13: =Horaire!A13 -> PASSAMAINTY | B13: =Horaire!B13 -> 0.20833333 | C13: =Horaire!C13 -> C1 | D13: =VLOOKUP(C13,'Liste chauffeur'!$B$5:$L$20,2,TRUE)&" "&VLOOKUP(C13,'Liste chauffeur'!$B$5:$L$20,3,TRUE) -> EL ANZIZE SALIM Hamada | F13: =COUNTBLANK(E13) -> 1 | N13: =IF(F13=1,"",L13-E13) | O13: =H13+J13-I13 -> 0 | P13: =IF(F13=1,0,P$6) -> 0 | Q13: =IF(P13=0,0,O13/P13) -> 0
A14: =Horaire!A14 -> VAHIBE 2 | B14: =Horaire!B14 -> 0.20833333 | C14: =Horaire!C14 -> C11 | D14: =VLOOKUP(C14,'Liste chauffeur'!$B$5:$L$20,2,TRUE)&" "&VLOOKUP(C14,'Liste chauffeur'!$B$5:$L$20,3,TRUE) -> MADI BOINA Mkidachi | F14: =COUNTBLANK(E14) -> 1 | N14: =IF(F14=1,"",L14-E14) | O14: =H14+J14-I14 -> 0 | P14: =IF(F14=1,0,P$6) -> 0 | Q14: =IF(P14=0,0,O14/P14) -> 0
A15: =Horaire!A15 -> VAHIBE | B15: =Horaire!B15 -> 0.21527778 | C15: =Horaire!C15 -> C2 | D15: =VLOOKUP(C15,'Liste chauffeur'!$B$5:$L$20,2,TRUE)&" "&VLOOKUP(C15,'Liste chauffeur'!$B$5:$L$20,3,TRUE) -> BINA HALADI Bina | F15: =COUNTBLANK(E15) -> 1 | N15: =IF(F15=1,"",L15-E15) | O15: =H15+J15-I15 -> 0 | P15: =IF(F15=1,0,P$6) -> 0 | Q15: =IF(P15=0,0,O15/P15) -> 0
A16: =Horaire!A16 -> VAHIBE 2 | B16: =Horaire!B16 -> 0.21527778 | C16: =Horaire!C16 -> C8 | D16: =VLOOKUP(C16,'Liste chauffeur'!$B$5:$L$20,2,TRUE)&" "&VLOOKUP(C16,'Liste chauffeur'!$B$5:$L$20,3,TRUE) -> HADHURAMI Makinedine | F16: =COUNTBLANK(E16) -> 1 | N16: =IF(F16=1,"",L16-E16) | O16: =H16+J16-I16 -> 0 | P16: =IF(F16=1,0,P$6) -> 0 | Q16: =IF(P16=0,0,O16/P16) -> 0
A17: =Horaire!A17 -> PASSAMAINTY | B17: =Horaire!B17 -> 0.21527778 | C17: =Horaire!C17 -> C3 | D17: =VLOOKUP(C17,'Liste chauffeur'!$B$5:$L$20,2,TRUE)&" "&VLOOKUP(C17,'Liste chauffeur'!$B$5:$L$20,3,TRUE) -> ABDOU MINIHADJI Amada | F17: =COUNTBLANK(E17) -> 1 | N17: =IF(F17=1,"",L17-E17) | O17: =H17+J17-I17 -> 0 | P17: =IF(F17=1,0,P$6) -> 0 | Q17: =IF(P17=0,0,O17/P17) -> 0
A18: =Horaire!A18 -> VAHIBE | B18: =Horaire!B18 -> 0.22222222 | C18: =Horaire!C18 -> C1 | D18: =VLOOKUP(C18,'Liste chauffeur'!$B$5:$L$20,2,TRUE)&" "&VLOOKUP(C18,'Liste chauffeur'!$B$5:$L$20,3,TRUE) -> EL ANZIZE SALIM Hamada | F18: =COUNTBLANK(E18) -> 1 | O18: =H18+J18-I18 -> 0 | P18: =IF(F18=1,0,P$6) -> 0 | Q18: =IF(P18=0,0,O18/P18) -> 0
A19: =Horaire!A19 -> VAHIBE 2 | B19: =Horaire!B19 -> 0.22222222 | C19: =Horaire!C19 -> C9 | D19: =VLOOKUP(C19,'Liste chauffeur'!$B$5:$L$20,2,TRUE)&" "&VLOOKUP(C19,'Liste chauffeur'!$B$5:$L$20,3,TRUE) -> SANDI Maanrouf | F19: =COUNTBLANK(E19) -> 1 | N19: =IF(F19=1,"",L19-E19) | O19: =H19+J19-I19 -> 0 | P19: =IF(F19=1,0,P$6) -> 0 | Q19: =IF(P19=0,0,O19/P19) -> 0
A20: =Horaire!A20 -> PASSAMAINTY | B20: =Horaire!B20 -> 0.22222222 | C20: =Horaire!C20 -> C4 | D20: =VLOOKUP(C20,'Liste chauffeur'!$B$5:$L$20,2,TRUE)&" "&VLOOKUP(C20,'Liste chauffeur'!$B$5:$L$20,3,TRUE) -> TOUMBOU Toibourani | F20: =COUNTBLANK(E20) -> 1 | N20: =IF(F20=1,"",L20-E20) | O20: =H20+J20-I20 -> 0 | P20: =IF(F20=1,0,P$6) -> 0 | Q20: =IF(P20=0,0,O20/P20) -> 0
A21: =Horaire!A21 -> PASSAMAINTY | B21: =Horaire!B21 -> 0.22222222 | C21: =Horaire!C21 -> C11 | D21: =VLOOKUP(C21,'Liste chauffeur'!$B$5:$L$20,2,TRUE)&" "&VLOOKUP(C21,'Liste chauffeur'!$B$5:$L$20,3,TRUE) -> MADI BOINA Mkidachi | F21: =COUNTBLANK(E21) -> 1 | N21: =IF(F21=1,"",L21-E21) | O21: =H21+J21-I21 -> 0 | P21: =IF(F21=1,0,P$6) -> 0 | Q21: =IF(P21=0,0,O21/P21) -> 0
A22: =Horaire!A22 -> VAHIBE | B22: =Horaire!B22 -> 0.22916667 | C22: =Horaire!C22 -> C3 | D22: =VLOOKUP(C22,'Liste chauffeur'!$B$5:$L$20,2,TRUE)&" "&VLOOKUP(C22,'Liste chauffeur'!$B$5:$L$20,3,TRUE) -> ABDOU MINIHADJI Amada | F22: =COUNTBLANK(E22) -> 1 | N22: =IF(F22=1,"",L22-E22) | O22: =H22+J22-I22 -> 0 | P22: =IF(F22=1,0,P$6) -> 0 | Q22: =IF(P22=0,0,O22/P22) -> 0
A23: =Horaire!A23 -> VAHIBE 2 | B23: =Horaire!B23 -> 0.22916667 | C23: =Horaire!C23 -> C10 | D23: =VLOOKUP(C23,'Liste chauffeur'!$B$5:$L$20,2,TRUE)&" "&VLOOKUP(C23,'Liste chauffeur'!$B$5:$L$20,3,TRUE) -> ISSIHAKA M'Changama | F23: =COUNTBLANK(E23) -> 1 | N23: =IF(F23=1,"",L23-E23) | O23: =H23+J23-I23 -> 0 | P23: =IF(F23=1,0,P$6) -> 0 | Q23: =IF(P23=0,0,O23/P23) -> 0
A24: =Horaire!A24 -> PASSAMAINTY | B24: =Horaire!B24 -> 0.22916667 | C24: =Horaire!C24 -> C2 | D24: =VLOOKUP(C24,'Liste chauffeur'!$B$5:$L$20,2,TRUE)&" "&VLOOKUP(C24,'Liste chauffeur'!$B$5:$L$20,3,TRUE) -> BINA HALADI Bina | F24: =COUNTBLANK(E24) -> 1 | N24: =IF(F24=1,"",L24-E24) | O24: =H24+J24-I24 -> 0 | P24: =IF(F24=1,0,P$6) -> 0 | Q24: =IF(P24=0,0,O24/P24) -> 0
A25: =Horaire!A25 -> PASSAMAINTY | B25: =Horaire!B25 -> 0.22916667 | C25: =Horaire!C25 -> C8 | D25: =VLOOKUP(C25,'Liste chauffeur'!$B$5:$L$20,2,TRUE)&" "&VLOOKUP(C25,'Liste chauffeur'!$B$5:$L$20,3,TRUE) -> HADHURAMI Makinedine | F25: =COUNTBLANK(E25) -> 1 | O25: =H25+J25-I25 -> 0 | P25: =IF(F25=1,0,P$6) -> 0 | Q25: =IF(P25=0,0,O25/P25) -> 0
A26: =Horaire!A26 -> VAHIBE | B26: =Horaire!B26 -> 0.23611111 | C26: =Horaire!C26 -> C4 | D26: =VLOOKUP(C26,'Liste chauffeur'!$B$5:$L$20,2,TRUE)&" "&VLOOKUP(C26,'Liste chauffeur'!$B$5:$L$20,3,TRUE) -> TOUMBOU Toibourani | F26: =COUNTBLANK(E26) -> 1 | N26: =IF(F26=1,"",L26-E26) | O26: =H26+J26-I26 -> 0 | P26: =IF(F26=1,0,P$6) -> 0 | Q26: =IF(P26=0,0,O26/P26) -> 0
A27: =Horaire!A27 -> VAHIBE 2 | B27: =Horaire!B27 -> 0.23611111 | C27: =Horaire!C27 -> C11 | D27: =VLOOKUP(C27,'Liste chauffeur'!$B$5:$L$20,2,TRUE)&" "&VLOOKUP(C27,'Liste chauffeur'!$B$5:$L$20,3,TRUE) -> MADI BOINA Mkidachi | F27: =COUNTBLANK(E27) -> 1 | N27: =IF(F27=1,"",L27-E27) | O27: =H27+J27-I27 -> 0 | P27: =IF(F27=1,0,P$6) -> 0 | Q27: =IF(P27=0,0,O27/P27) -> 0
A28: =Horaire!A28 -> PASSAMAINTY | B28: =Horaire!B28 -> 0.23611111 | C28: =Horaire!C28 -> C1 | D28: =VLOOKUP(C28,'Liste chauffeur'!$B$5:$L$20,2,TRUE)&" "&VLOOKUP(C28,'Liste chauffeur'!$B$5:$L$20,3,TRUE) -> EL ANZIZE SALIM Hamada | F28: =COUNTBLANK(E28) -> 1 | N28: =IF(F28=1,"",L28-E28) | O28: =H28+J28-I28 -> 0 | P28: =IF(F28=1,0,P$6) -> 0 | Q28: =IF(P28=0,0,O28/P28) -> 0
A29: =Horaire!A29 -> PASSAMAINTY | B29: =Horaire!B29 -> 0.23611111 | C29: =Horaire!C29 -> C9 | D29: =VLOOKUP(C29,'Liste chauffeur'!$B$5:$L$20,2,TRUE)&" "&VLOOKUP(C29,'Liste chauffeur'!$B$5:$L$20,3,TRUE) -> SANDI Maanrouf | F29: =COUNTBLANK(E29) -> 1 | N29: =IF(F29=1,"",L29-E29) | O29: =H29+J29-I29 -> 0 | P29: =IF(F29=1,0,P$6) -> 0 | Q29: =IF(P29=0,0,O29/P29) -> 0
A30: =Horaire!A30 -> VAHIBE | B30: =Horaire!B30 -> 0.24305556 | C30: =Horaire!C30 -> C2 | D30: =VLOOKUP(C30,'Liste chauffeur'!$B$5:$L$20,2,TRUE)&" "&VLOOKUP(C30,'Liste chauffeur'!$B$5:$L$20,3,TRUE) -> BINA HALADI Bina | F30: =COUNTBLANK(E30) -> 1 | N30: =IF(F30=1,"",L30-E30) | O30: =H30+J30-I30 -> 0 | P30: =IF(F30=1,0,P$6) -> 0 | Q30: =IF(P30=0,0,O30/P30) -> 0
A31: =Horaire!A31 -> VAHIBE 2 | B31: =Horaire!B31 -> 0.24305556 | C31: =Horaire!C31 -> C8 | D31: =VLOOKUP(C31,'Liste chauffeur'!$B$5:$L$20,2,TRUE)&" "&VLOOKUP(C31,'Liste chauffeur'!$B$5:$L$20,3,TRUE) -> HADHURAMI Makinedine | F31: =COUNTBLANK(E31) -> 1 | N31: =IF(F31=1,"",L31-E31) | O31: =H31+J31-I31 -> 0 | P31: =IF(F31=1,0,P$6) -> 0 | Q31: =IF(P31=0,0,O31/P31) -> 0
A32: =Horaire!A32 -> PASSAMAINTY | B32: =Horaire!B32 -> 0.24305556 | C32: =Horaire!C32 -> C3 | D32: =VLOOKUP(C32,'Liste chauffeur'!$B$5:$L$20,2,TRUE)&" "&VLOOKUP(C32,'Liste chauffeur'!$B$5:$L$20,3,TRUE) -> ABDOU MINIHADJI Amada | F32: =COUNTBLANK(E32) -> 1 | O32: =H32+J32-I32 -> 0 | P32: =IF(F32=1,0,P$6) -> 0 | Q32: =IF(P32=0,0,O32/P32) -> 0
A33: =Horaire!A33 -> PASSAMAINTY | B33: =Horaire!B33 -> 0.24305556 | C33: =Horaire!C33 -> C10 | D33: =VLOOKUP(C33,'Liste chauffeur'!$B$5:$L$20,2,TRUE)&" "&VLOOKUP(C33,'Liste chauffeur'!$B$5:$L$20,3,TRUE) -> ISSIHAKA M'Changama | F33: =COUNTBLANK(E33) -> 1 | N33: =IF(F33=1,"",L33-E33) | O33: =H33+J33-I33 -> 0 | P33: =IF(F33=1,0,P$6) -> 0 | Q33: =IF(P33=0,0,O33/P33) -> 0
A34: =Horaire!A34 -> VAHIBE | B34: =Horaire!B34 -> 0.25 | C34: =Horaire!C34 -> C1 | D34: =VLOOKUP(C34,'Liste chauffeur'!$B$5:$L$20,2,TRUE)&" "&VLOOKUP(C34,'Liste chauffeur'!$B$5:$L$20,3,TRUE) -> EL ANZIZE SALIM Hamada | F34: =COUNTBLANK(E34) -> 1 | N34: =IF(F34=1,"",L34-E34) | O34: =H34+J34-I34 -> 0 | P34: =IF(F34=1,0,P$6) -> 0 | Q34: =IF(P34=0,0,O34/P34) -> 0
A35: =Horaire!A35 -> VAHIBE 2 | B35: =Horaire!B35 -> 0.25 | C35: =Horaire!C35 -> C9 | D35: =VLOOKUP(C35,'Liste chauffeur'!$B$5:$L$20,2,TRUE)&" "&VLOOKUP(C35,'Liste chauffeur'!$B$5:$L$20,3,TRUE) -> SANDI Maanrouf | F35: =COUNTBLANK(E35) -> 1 | N35: =IF(F35=1,"",L35-E35) | O35: =H35+J35-I35 -> 0 | P35: =IF(F35=1,0,P$6) -> 0 | Q35: =IF(P35=0,0,O35/P35) -> 0
A36: =Horaire!A36 -> PASSAMAINTY | B36: =Horaire!B36 -> 0.25 | C36: =Horaire!C36 -> C5 | D36: =VLOOKUP(C36,'Liste chauffeur'!$B$5:$L$20,2,TRUE)&" "&VLOOKUP(C36,'Liste chauffeur'!$B$5:$L$20,3,TRUE) -> AHAMADI Bacar Raenmouddine | F36: =COUNTBLANK(E36) -> 1 | N36: =IF(F36=1,"",L36-E36) | O36: =H36+J36-I36 -> 0 | P36: =IF(F36=1,0,P$6) -> 0 | Q36: =IF(P36=0,0,O36/P36) -> 0
A37: =Horaire!A37 -> PASSAMAINTY | B37: =Horaire!B37 -> 0.25 | C37: =Horaire!C37 -> C12 | D37: =VLOOKUP(C37,'Liste chauffeur'!$B$5:$L$20,2,TRUE)&" "&VLOOKUP(C37,'Liste chauffeur'!$B$5:$L$20,3,TRUE) -> ALILOIFFA Said Siradj | F37: =COUNTBLANK(E37) -> 1 | N37: =IF(F37=1,"",L37-E37) | O37: =H37+J37-I37 -> 0 | P37: =IF(F37=1,0,P$6) -> 0 | Q37: =IF(P37=0,0,O37/P37) -> 0
A38: =Horaire!A38 -> VAHIBE | B38: =Horaire!B38 -> 0.25694444 | C38: =Horaire!C38 -> C3 | D38: =VLOOKUP(C38,'Liste chauffeur'!$B$5:$L$20,2,TRUE)&" "&VLOOKUP(C38,'Liste chauffeur'!$B$5:$L$20,3,TRUE) -> ABDOU MINIHADJI Amada | F38: =COUNTBLANK(E38) -> 1 | N38: =IF(F38=1,"",L38-E38) | O38: =H38+J38-I38 -> 0 | P38: =IF(F38=1,0,P$6) -> 0 | Q38: =IF(P38=0,0,O38/P38) -> 0
A39: =Horaire!A39 -> VAHIBE 2 | B39: =Horaire!B39 -> 0.25694444 | C39: =Horaire!C39 -> C10 | D39: =VLOOKUP(C39,'Liste chauffeur'!$B$5:$L$20,2,TRUE)&" "&VLOOKUP(C39,'Liste chauffeur'!$B$5:$L$20,3,TRUE) -> ISSIHAKA M'Changama | F39: =COUNTBLANK(E39) -> 1 | N39: =IF(F39=1,"",L39-E39) | O39: =H39+J39-I39 -> 0 | P39: =IF(F39=1,0,P$6) -> 0 | Q39: =IF(P39=0,0,O39/P39) -> 0
A40: =Horaire!A40 -> PASSAMAINTY | B40: =Horaire!B40 -> 0.25694444 | C40: =Horaire!C40 -> C4 | D40: =VLOOKUP(C40,'Liste chauffeur'!$B$5:$L$20,2,TRUE)&" "&VLOOKUP(C40,'Liste chauffeur'!$B$5:$L$20,3,TRUE) -> TOUMBOU Toibourani | F40: =COUNTBLANK(E40) -> 1 | N40: =IF(F40=1,"",L40-E40) | O40: =H40+J40-I40 -> 0 | P40: =IF(F40=1,0,P$6) -> 0 | Q40: =IF(P40=0,0,O40/P40) -> 0
A41: =Horaire!A41 -> PASSAMAINTY | B41: =Horaire!B41 -> 0.25694444 | C41: =Horaire!C41 -> C11 | D41: =VLOOKUP(C41,'Liste chauffeur'!$B$5:$L$20,2,TRUE)&" "&VLOOKUP(C41,'Liste chauffeur'!$B$5:$L$20,3,TRUE) -> MADI BOINA Mkidachi | F41: =COUNTBLANK(E41) -> 1 | N41: =IF(F41=1,"",L41-E41) | O41: =H41+J41-I41 -> 0 | P41: =IF(F41=1,0,P$6) -> 0 | Q41: =IF(P41=0,0,O41/P41) -> 0
A42: =Horaire!A42 -> VAHIBE | B42: =Horaire!B42 -> 0.26388889 | C42: =Horaire!C42 -> C5 | D42: =VLOOKUP(C42,'Liste chauffeur'!$B$5:$L$20,2,TRUE)&" "&VLOOKUP(C42,'Liste chauffeur'!$B$5:$L$20,3,TRUE) -> AHAMADI Bacar Raenmouddine | F42: =COUNTBLANK(E42) -> 1 | N42: =IF(F42=1,"",L42-E42) | O42: =H42+J42-I42 -> 0 | P42: =IF(F42=1,0,P$6) -> 0 | Q42: =IF(P42=0,0,O42/P42) -> 0
A43: =Horaire!A43 -> VAHIBE 2 | B43: =Horaire!B43 -> 0.26388889 | C43: =Horaire!C43 -> C12 | D43: =VLOOKUP(C43,'Liste chauffeur'!$B$5:$L$20,2,TRUE)&" "&VLOOKUP(C43,'Liste chauffeur'!$B$5:$L$20,3,TRUE) -> ALILOIFFA Said Siradj | F43: =COUNTBLANK(E43) -> 1 | N43: =IF(F43=1,"",L43-E43) | O43: =H43+J43-I43 -> 0 | P43: =IF(F43=1,0,P$6) -> 0 | Q43: =IF(P43=0,0,O43/P43) -> 0
A44: =Horaire!A44 -> PASSAMAINTY | B44: =Horaire!B44 -> 0.26388889 | C44: =Horaire!C44 -> C2 | D44: =VLOOKUP(C44,'Liste chauffeur'!$B$5:$L$20,2,TRUE)&" "&VLOOKUP(C44,'Liste chauffeur'!$B$5:$L$20,3,TRUE) -> BINA HALADI Bina | F44: =COUNTBLANK(E44) -> 1 | N44: =IF(F44=1,"",L44-E44) | O44: =H44+J44-I44 -> 0 | P44: =IF(F44=1,0,P$6) -> 0 | Q44: =IF(P44=0,0,O44/P44) -> 0
... A56: =Horaire!A56 -> PASSAMAINTY | B56: =Horaire!B56 -> 0.28472222 | C56: =Horaire!C56 -> C10 | D56: =VLOOKUP(C56,'Liste chauffeur'!$B$5:$L$20,2,TRUE)&" "&VLOOKUP(C56,'Liste chauffeur'!$B$5:$L$20,3,TRUE) -> ISSIHAKA M'Changama | F56: =COUNTBLANK(E56) -> 1 | N56: =IF(F56=1,"",L56-E56) | O56: =H56+J56-I56 -> 0 | P56: =IF(F56=1,0,P$6) -> 0 | Q56: =IF(P56=0,0,O56/P56) -> 0
A57: =Horaire!A57 -> PASSAMAINTY | B57: =Horaire!B57 -> 0.28472222 | C57: =Horaire!C57 -> C5 | D57: =VLOOKUP(C57,'Liste chauffeur'!$B$5:$L$20,2,TRUE)&" "&VLOOKUP(C57,'Liste chauffeur'!$B$5:$L$20,3,TRUE) -> AHAMADI Bacar Raenmouddine | F57: =COUNTBLANK(E57) -> 1 | O57: =H57+J57-I57 -> 0 | P57: =IF(F57=1,0,P$6) -> 0 | Q57: =IF(P57=0,0,O57/P57) -> 0
A58: =Horaire!A58 -> VAHIBE | B58: =Horaire!B58 -> 0.29166667 | C58: =Horaire!C58 -> C1 | D58: =VLOOKUP(C58,'Liste chauffeur'!$B$5:$L$20,2,TRUE)&" "&VLOOKUP(C58,'Liste chauffeur'!$B$5:$L$20,3,TRUE) -> EL ANZIZE SALIM Hamada | F58: =COUNTBLANK(E58) -> 1 | O58: =H58+J58-I58 -> 0 | P58: =IF(F58=1,0,P$6) -> 0 | Q58: =IF(P58=0,0,O58/P58) -> 0
A59: =Horaire!A59 -> VAHIBE 2 | B59: =Horaire!B59 -> 0.29166667 | C59: =Horaire!C59 -> C3 | D59: =VLOOKUP(C59,'Liste chauffeur'!$B$5:$L$20,2,TRUE)&" "&VLOOKUP(C59,'Liste chauffeur'!$B$5:$L$20,3,TRUE) -> ABDOU MINIHADJI Amada | F59: =COUNTBLANK(E59) -> 1 | O59: =H59+J59-I59 -> 0 | P59: =IF(F59=1,0,P$6) -> 0 | Q59: =IF(P59=0,0,O59/P59) -> 0
A60: =Horaire!A60 -> PASSAMAINTY | B60: =Horaire!B60 -> 0.29166667 | C60: =Horaire!C60 -> C4 | D60: =VLOOKUP(C60,'Liste chauffeur'!$B$5:$L$20,2,TRUE)&" "&VLOOKUP(C60,'Liste chauffeur'!$B$5:$L$20,3,TRUE) -> TOUMBOU Toibourani | F60: =COUNTBLANK(E60) -> 1 | O60: =H60+J60-I60 -> 0 | P60: =IF(F60=1,0,P$6) -> 0 | Q60: =IF(P60=0,0,O60/P60) -> 0
A61: =Horaire!A61 -> PASSAMAINTY | B61: =Horaire!B61 -> 0.29166667 | C61: =Horaire!C61 -> C11 | D61: =VLOOKUP(C61,'Liste chauffeur'!$B$5:$L$20,2,TRUE)&" "&VLOOKUP(C61,'Liste chauffeur'!$B$5:$L$20,3,TRUE) -> MADI BOINA Mkidachi | F61: =COUNTBLANK(E61) -> 1 | O61: =H61+J61-I61 -> 0 | P61: =IF(F61=1,0,P$6) -> 0 | Q61: =IF(P61=0,0,O61/P61) -> 0
A62: =Horaire!A62 -> VAHIBE | B62: =Horaire!B62 -> 0.29861111 | C62: =Horaire!C62 -> C10 | D62: =VLOOKUP(C62,'Liste chauffeur'!$B$5:$L$20,2,TRUE)&" "&VLOOKUP(C62,'Liste chauffeur'!$B$5:$L$20,3,TRUE) -> ISSIHAKA M'Changama | F62: =COUNTBLANK(E62) -> 1 | O62: =H62+J62-I62 -> 0 | P62: =IF(F62=1,0,P$6) -> 0 | Q62: =IF(P62=0,0,O62/P62) -> 0
A63: =Horaire!A63 -> VAHIBE 2 | B63: =Horaire!B63 -> 0.29861111 | C63: =Horaire!C63 -> C5 | D63: =VLOOKUP(C63,'Liste chauffeur'!$B$5:$L$20,2,TRUE)&" "&VLOOKUP(C63,'Liste chauffeur'!$B$5:$L$20,3,TRUE) -> AHAMADI Bacar Raenmouddine | F63: =COUNTBLANK(E63) -> 1 | O63: =H63+J63-I63 -> 0 | P63: =IF(F63=1,0,P$6) -> 0 | Q63: =IF(P63=0,0,O63/P63) -> 0
A64: =Horaire!A64 -> PASSAMAINTY | B64: =Horaire!B64 -> 0.29861111 | C64: =Horaire!C64 -> C13 | D64: =VLOOKUP(C64,'Liste chauffeur'!$B$5:$L$20,2,TRUE)&" "&VLOOKUP(C64,'Liste chauffeur'!$B$5:$L$20,3,TRUE) -> ABDALLAH Ben (Taxi Vanille) | F64: =COUNTBLANK(E64) -> 1 | O64: =H64+J64-I64 -> 0 | P64: =IF(F64=1,0,P$6) -> 0 | Q64: =IF(P64=0,0,O64/P64) -> 0
A65: =Horaire!A65 -> PASSAMAINTY | B65: =Horaire!B65 -> 0.29861111 | C65: =Horaire!C65 -> C8 | D65: =VLOOKUP(C65,'Liste chauffeur'!$B$5:$L$20,2,TRUE)&" "&VLOOKUP(C65,'Liste chauffeur'!$B$5:$L$20,3,TRUE) -> HADHURAMI Makinedine | F65: =COUNTBLANK(E65) -> 1 | O65: =H65+J65-I65 -> 0 | P65: =IF(F65=1,0,P$6) -> 0 | Q65: =IF(P65=0,0,O65/P65) -> 0
A66: =Horaire!A66 -> VAHIBE | B66: =Horaire!B66 -> 0.30555556 | C66: =Horaire!C66 -> C4 | D66: =VLOOKUP(C66,'Liste chauffeur'!$B$5:$L$20,2,TRUE)&" "&VLOOKUP(C66,'Liste chauffeur'!$B$5:$L$20,3,TRUE) -> TOUMBOU Toibourani | F66: =COUNTBLANK(E66) -> 1 | O66: =H66+J66-I66 -> 0 | P66: =IF(F66=1,0,P$6) -> 0 | Q66: =IF(P66=0,0,O66/P66) -> 0
A67: =Horaire!A67 -> VAHIBE 2 | B67: =Horaire!B67 -> 0.30555556 | C67: =Horaire!C67 -> C11 | D67: =VLOOKUP(C67,'Liste chauffeur'!$B$5:$L$20,2,TRUE)&" "&VLOOKUP(C67,'Liste chauffeur'!$B$5:$L$20,3,TRUE) -> MADI BOINA Mkidachi | F67: =COUNTBLANK(E67) -> 1 | O67: =H67+J67-I67 -> 0 | P67: =IF(F67=1,0,P$6) -> 0 | Q67: =IF(P67=0,0,O67/P67) -> 0
A68: =Horaire!A68 -> PASSAMAINTY | B68: =Horaire!B68 -> 0.30555556 | C68: =Horaire!C68 -> C15 | D68: =VLOOKUP(C68,'Liste chauffeur'!$B$5:$L$20,2,TRUE)&" "&VLOOKUP(C68,'Liste chauffeur'!$B$5:$L$20,3,TRUE) -> HAMADA Babou | F68: =COUNTBLANK(E68) -> 1 | O68: =H68+J68-I68 -> 0 | P68: =IF(F68=1,0,P$6) -> 0 | Q68: =IF(P68=0,0,O68/P68) -> 0
... A101: =Horaire!A101 -> VAHIBE | B101: =Horaire!B101 -> 0.5 | C101: =Horaire!C101 -> C1 | D101: =VLOOKUP(C101,'Liste chauffeur'!$B$5:$L$20,2,TRUE)&" "&VLOOKUP(C101,'Liste chauffeur'!$B$5:$L$20,3,TRUE) -> EL ANZIZE SALIM Hamada | F101: =COUNTBLANK(E101) -> 1 | O101: =H101+J101-I101 -> 0 | P101: =IF(F101=1,0,P$6) -> 0 | Q101: =IF(P101=0,0,O101/P101) -> 0
B102: ST1 | F102: =SUM(F8:F101) -> 94 | N102: =AVERAGE(N8:N101) -> #DIV/0! | O102: =SUM(O8:O101) -> 0 | P102: =SUM(P8:P101) -> 0 | Q102: =IF(P102=0,0,O102/P102) -> 0
A103: =Horaire!A102 -> PASSAMAINTY | B103: =Horaire!B102 -> 0.5 | C103: =Horaire!C102 -> C14 | D103: =VLOOKUP(C103,'Liste chauffeur'!$B$5:$L$20,2,TRUE)&" "&VLOOKUP(C103,'Liste chauffeur'!$B$5:$L$20,3,TRUE) -> KAMARDINE Mansour | F103: =COUNTBLANK(E103) -> 1 | O103: =H103+J103-I103 -> 0 | P103: =IF(F103=1,0,P$6) -> 0 | Q103: =IF(P103=0,0,O103/P103) -> 0
A104: =Horaire!A103 -> VAHIBE | B104: =Horaire!B103 -> 0.52083333 | C104: =Horaire!C103 -> C14 | D104: =VLOOKUP(C104,'Liste chauffeur'!$B$5:$L$20,2,TRUE)&" "&VLOOKUP(C104,'Liste chauffeur'!$B$5:$L$20,3,TRUE) -> KAMARDINE Mansour | F104: =COUNTBLANK(E104) -> 1 | O104: =H104+J104-I104 -> 0 | P104: =IF(F104=1,0,P$6) -> 0 | Q104: =IF(P104=0,0,O104/P104) -> 0
A105: =Horaire!A104 -> PASSAMAINTY | B105: =Horaire!B104 -> 0.52083333 | C105: =Horaire!C104 -> C2 | D105: =VLOOKUP(C105,'Liste chauffeur'!$B$5:$L$20,2,TRUE)&" "&VLOOKUP(C105,'Liste chauffeur'!$B$5:$L$20,3,TRUE) -> BINA HALADI Bina | F105: =COUNTBLANK(E105) -> 1 | O105: =H105+J105-I105 -> 0 | P105: =IF(F105=1,0,P$6) -> 0 | Q105: =IF(P105=0,0,O105/P105) -> 0
A106: =Horaire!A105 -> VAHIBE | B106: =Horaire!B105 -> 0.54166667 | C106: =Horaire!C105 -> C2 | D106: =VLOOKUP(C106,'Liste chauffeur'!$B$5:$L$20,2,TRUE)&" "&VLOOKUP(C106,'Liste chauffeur'!$B$5:$L$20,3,TRUE) -> BINA HALADI Bina | F106: =COUNTBLANK(E106) -> 1 | O106: =H106+J106-I106 -> 0 | P106: =IF(F106=1,0,P$6) -> 0 | Q106: =IF(P106=0,0,O106/P106) -> 0
A107: =Horaire!A106 -> PASSAMAINTY | B107: =Horaire!B106 -> 0.54166667 | C107: =Horaire!C106 -> C14 | D107: =VLOOKUP(C107,'Liste chauffeur'!$B$5:$L$20,2,TRUE)&" "&VLOOKUP(C107,'Liste chauffeur'!$B$5:$L$20,3,TRUE) -> KAMARDINE Mansour | F107: =COUNTBLANK(E107) -> 1 | O107: =H107+J107-I107 -> 0 | P107: =IF(F107=1,0,P$6) -> 0 | Q107: =IF(P107=0,0,O107/P107) -> 0
A108: =Horaire!A107 -> VAHIBE | B108: =Horaire!B107 -> 0.5625 | C108: =Horaire!C107 -> C14 | D108: =VLOOKUP(C108,'Liste chauffeur'!$B$5:$L$20,2,TRUE)&" "&VLOOKUP(C108,'Liste chauffeur'!$B$5:$L$20,3,TRUE) -> KAMARDINE Mansour | F108: =COUNTBLANK(E108) -> 1 | O108: =H108+J108-I108 -> 0 | P108: =IF(F108=1,0,P$6) -> 0 | Q108: =IF(P108=0,0,O108/P108) -> 0
A109: =Horaire!A108 -> PASSAMAINTY | B109: =Horaire!B108 -> 0.5625 | C109: =Horaire!C108 -> C2 | D109: =VLOOKUP(C109,'Liste chauffeur'!$B$5:$L$20,2,TRUE)&" "&VLOOKUP(C109,'Liste chauffeur'!$B$5:$L$20,3,TRUE) -> BINA HALADI Bina | F109: =COUNTBLANK(E109) -> 1 | O109: =H109+J109-I109 -> 0 | P109: =IF(F109=1,0,P$6) -> 0 | Q109: =IF(P109=0,0,O109/P109) -> 0
A110: =Horaire!A109 -> VAHIBE | B110: =Horaire!B109 -> 0.58333333 | C110: =Horaire!C109 -> C2 | D110: =VLOOKUP(C110,'Liste chauffeur'!$B$5:$L$20,2,TRUE)&" "&VLOOKUP(C110,'Liste chauffeur'!$B$5:$L$20,3,TRUE) -> BINA HALADI Bina | F110: =COUNTBLANK(E110) -> 1 | O110: =H110+J110-I110 -> 0 | P110: =IF(F110=1,0,P$6) -> 0 | Q110: =IF(P110=0,0,O110/P110) -> 0
A111: =Horaire!A110 -> PASSAMAINTY | B111: =Horaire!B110 -> 0.58333333 | C111: =Horaire!C110 -> C14 | D111: =VLOOKUP(C111,'Liste chauffeur'!$B$5:$L$20,2,TRUE)&" "&VLOOKUP(C111,'Liste chauffeur'!$B$5:$L$20,3,TRUE) -> KAMARDINE Mansour | F111: =COUNTBLANK(E111) -> 1 | O111: =H111+J111-I111 -> 0 | P111: =IF(F111=1,0,P$6) -> 0 | Q111: =IF(P111=0,0,O111/P111) -> 0
A112: =Horaire!A111 -> VAHIBE | B112: =Horaire!B111 -> 0.60416667 | C112: =Horaire!C111 -> C3 | D112: =VLOOKUP(C112,'Liste chauffeur'!$B$5:$L$20,2,TRUE)&" "&VLOOKUP(C112,'Liste chauffeur'!$B$5:$L$20,3,TRUE) -> ABDOU MINIHADJI Amada | F112: =COUNTBLANK(E112) -> 1 | O112: =H112+J112-I112 -> 0 | P112: =IF(F112=1,0,P$6) -> 0 | Q112: =IF(P112=0,0,O112/P112) -> 0
A113: =Horaire!A112 -> PASSAMAINTY | B113: =Horaire!B112 -> 0.60416667 | C113: =Horaire!C112 -> C2 | D113: =VLOOKUP(C113,'Liste chauffeur'!$B$5:$L$20,2,TRUE)&" "&VLOOKUP(C113,'Liste chauffeur'!$B$5:$L$20,3,TRUE) -> BINA HALADI Bina | F113: =COUNTBLANK(E113) -> 1 | O113: =H113+J113-I113 -> 0 | P113: =IF(F113=1,0,P$6) -> 0 | Q113: =IF(P113=0,0,O113/P113) -> 0
A114: =Horaire!A113 -> VAHIBE | B114: =Horaire!B113 -> 0.625 | C114: =Horaire!C113 -> C2 | D114: =VLOOKUP(C114,'Liste chauffeur'!$B$5:$L$20,2,TRUE)&" "&VLOOKUP(C114,'Liste chauffeur'!$B$5:$L$20,3,TRUE) -> BINA HALADI Bina | F114: =COUNTBLANK(E114) -> 1 | O114: =H114+J114-I114 -> 0 | P114: =IF(F114=1,0,P$6) -> 0 | Q114: =IF(P114=0,0,O114/P114) -> 0
... A139: =Horaire!A138 -> PASSAMAINTY | B139: =Horaire!B138 -> 0.75 | C139: =Horaire!C138 -> C5 | D139: =VLOOKUP(C139,'Liste chauffeur'!$B$5:$L$20,2,TRUE)&" "&VLOOKUP(C139,'Liste chauffeur'!$B$5:$L$20,3,TRUE) -> AHAMADI Bacar Raenmouddine | F139: =COUNTBLANK(E139) -> 1 | O139: =H139+J139-I139 -> 0 | P139: =IF(F139=1,0,P$6) -> 0 | Q139: =IF(P139=0,0,O139/P139) -> 0
B140: ST2 | F140: =SUM(F103:F139) -> 37 | N140: =AVERAGE(N103:N139) -> #DIV/0! | O140: =SUM(O103:O139) -> 0 | P140: =SUM(P103:P139) -> 0 | Q140: =IF(P140=0,0,O140/P140) -> 0
A141: REMPLACEMENT | B141: ST3 | C141: C | F141: =F140+F102 -> 131 | N141: =AVERAGE(N1:N8,N103:N139) -> #DIV/0! | O141: =O102+O140 -> 0 | P141: =P102+P140 -> 0 | Q141: =IF(P141=0,0,O141/P141) -> 0
A142: REMPLACEMENT | C142: C
A143: REMPLACEMENT | C143: C
A144: REMPLACEMENT | C144: C
A145: REMPLACEMENT | C145: C
E147: Signature Chauffeur | J147: Signature Coordinateur
B150: Statistiques | C150: nbre de trajets planifiés | D150: Nbre trajets non effectués | E150: Nbre trajets effectués non planifiés | F150: Nbre trajets dont départ > 10 minutes en retard
B151: C1 | C151: =COUNTIF($B$8:$C$140,B151) -> 17 | D151: =C151-(COUNTIFS(C$8:C$140,B151,M$8:M$140,"")) -> 0 | E151: =COUNTIFS(M$8:M$140,$B151) -> 0 | F151: =COUNTIFS(G$8:G$140,$B151) -> 0
B152: C2 | C152: =COUNTIF($B$8:$C$140,B152) -> 16 | D152: =C152-(COUNTIFS(C$8:C$140,B152,M$8:M$140,"")) -> 0 | E152: =COUNTIFS(M$8:M$140,$B152) -> 0 | F152: =COUNTIFS(G$8:G$140,$B152) -> 0
B153: C3 | C153: =COUNTIF($B$8:$C$140,B153) -> 16 | D153: =C153-(COUNTIFS(C$8:C$140,B153,M$8:M$140,"")) -> 0 | E153: =COUNTIFS(M$8:M$140,$B153) -> 0 | F153: =COUNTIFS(G$8:G$140,$B153) -> 0
B154: C4 | C154: =COUNTIF($B$8:$C$140,B154) -> 9 | D154: =C154-(COUNTIFS(C$8:C$140,B154,M$8:M$140,"")) -> 0 | E154: =COUNTIFS(M$8:M$140,$B154) -> 0 | F154: =COUNTIFS(G$8:G$140,$B154) -> 0
B155: C5 | C155: =COUNTIF($B$8:$C$140,B155) -> 13 | D155: =C155-(COUNTIFS(C$8:C$140,B155,M$8:M$140,"")) -> 0 | E155: =COUNTIFS(M$8:M$140,$B155) -> 0 | F155: =COUNTIFS(G$8:G$140,$B155) -> 0
B156: C6 | C156: =COUNTIF($B$8:$C$140,B156) -> 0 | D156: =C156-(COUNTIFS(C$8:C$140,B156,M$8:M$140,"")) -> 0 | E156: =COUNTIFS(M$8:M$140,$B156) -> 0 | F156: =COUNTIFS(G$8:G$140,$B156) -> 0
B157: C7 | C157: =COUNTIF($B$8:$C$140,B157) -> 0 | D157: =C157-(COUNTIFS(C$8:C$140,B157,M$8:M$140,"")) -> 0 | E157: =COUNTIFS(M$8:M$140,$B157) -> 0 | F157: =COUNTIFS(G$8:G$140,$B157) -> 0
B158: C8 | C158: =COUNTIF($B$8:$C$140,B158) -> 7 | D158: =C158-(COUNTIFS(C$8:C$140,B158,M$8:M$140,"")) -> 0 | E158: =COUNTIFS(M$8:M$140,$B158) -> 0 | F158: =COUNTIFS(G$8:G$140,$B158) -> 0
B159: C9 | C159: =COUNTIF($B$8:$C$140,B159) -> 7 | D159: =C159-(COUNTIFS(C$8:C$140,B159,M$8:M$140,"")) -> 0 | E159: =COUNTIFS(M$8:M$140,$B159) -> 0 | F159: =COUNTIFS(G$8:G$140,$B159) -> 0
B160: C10 | C160: =COUNTIF($B$8:$C$140,B160) -> 7 | D160: =C160-(COUNTIFS(C$8:C$140,B160,M$8:M$140,"")) -> 0 | E160: =COUNTIFS(M$8:M$140,$B160) -> 0 | F160: =COUNTIFS(G$8:G$140,$B160) -> 0
B161: C11 | C161: =COUNTIF($B$8:$C$140,B161) -> 8 | D161: =C161-(COUNTIFS(C$8:C$140,B161,M$8:M$140,"")) -> 0 | E161: =COUNTIFS(M$8:M$140,$B161) -> 0 | F161: =COUNTIFS(G$8:G$140,$B161) -> 0
B162: C12 | C162: =COUNTIF($B$8:$C$140,B162) -> 11 | D162: =C162-(COUNTIFS(C$8:C$140,B162,M$8:M$140,"")) -> 0 | E162: =COUNTIFS(M$8:M$140,$B162) -> 0 | F162: =COUNTIFS(G$8:G$140,$B162) -> 0
... B177: C25 | C177: =COUNTIF($B$8:$C$140,B177) -> 0 | D177: =C177-(COUNTIFS(C$8:C$140,B177,M$8:M$140,"")) -> 0 | E177: =COUNTIFS(M$8:M$140,$B177) -> 0 | F177: =COUNTIFS(G$8:G$140,$B177) -> 0
C178: =SUM(C151:C177) -> 131 | D178: =SUM(D151:D177) -> 0 | E178: =SUM(E151:E177) -> 0 | F178: =SUM(F151:F177) -> 0
E179: =D178-E178 -> 0 | F179: =IF(E179=F178,"OK","ERREUR") -> OK

Sheet Feuille saisie samedi
A2: TYPE | B2: C11
A3: DATE | B3: 45627
A4: CHAUFFEUR | B4: =VLOOKUP(B2,'Liste chauffeur'!$B$5:$L$20,2,TRUE)&" "&VLOOKUP(B2,'Liste chauffeur'!$B$5:$L$20,3,TRUE) -> MADI BOINA Mkidachi
I6: Arrêt 1 | M6: Arrêt 2 | Q6: Arrêt 3 | W6: ARRIVEE | AA6: 8
B7: Heure théorique départ | C7: Horaire | D7: Chauffeur | E7: Heure réelle départ | F7: Trajet non effectué | G7: Départ avec plus de 10 mns retard | H7: Nbre personnes montée | I7: - | J7: + | K7: Heure arrivée arrêt 1 | L7: Délai | M7: - | N7: + | O7: Heure arrivée arrêt 2 | P7: Délai | Q7: - | R7: + | S7: Heure arrivée arrêt 3 | T7: Délai | U7: Nbre personnes descente | W7: Heure arrivée finale | X7: Commentaires | Y7: Temps Aller | Z7: Nbre personnes moyenne | AA7: Capacité max | AB7: Taux Fréquentation
A8: ='Horaire samedi'!A8 -> VAHIBE | B8: ='Horaire samedi'!B8 -> 0.25 | C8: ='Horaire samedi'!C8 -> C11 | D8: =VLOOKUP(C8,'Liste chauffeur'!$B$5:$L$20,2,TRUE)&" "&VLOOKUP(C8,'Liste chauffeur'!$B$5:$L$20,3,TRUE) -> MADI BOINA Mkidachi | F8: =COUNTBLANK(E8) -> 1 | Y8: =IF(F8=1,"",W8-E8) | Z8: =H8+J8-I8 -> 0 | AA8: =IF(F8=1,0,AA$6) -> 0 | AB8: =IF(AA8=0,0,Z8/AA8) -> 0
A9: ='Horaire samedi'!A9 -> VAHIBE | B9: ='Horaire samedi'!B9 -> 0.27083333 | C9: ='Horaire samedi'!C9 -> C9 | D9: =VLOOKUP(C9,'Liste chauffeur'!$B$5:$L$20,2,TRUE)&" "&VLOOKUP(C9,'Liste chauffeur'!$B$5:$L$20,3,TRUE) -> SANDI Maanrouf | F9: =COUNTBLANK(E9) -> 1 | Y9: =IF(F9=1,"",W9-E9) | Z9: =H9+J9-I9 -> 0 | AA9: =IF(F9=1,0,AA$6) -> 0 | AB9: =IF(AA9=0,0,Z9/AA9) -> 0
A10: ='Horaire samedi'!A10 -> PASSAMAINTY | B10: ='Horaire samedi'!B10 -> 0.27083333 | C10: ='Horaire samedi'!C10 -> C11 | D10: =VLOOKUP(C10,'Liste chauffeur'!$B$5:$L$20,2,TRUE)&" "&VLOOKUP(C10,'Liste chauffeur'!$B$5:$L$20,3,TRUE) -> MADI BOINA Mkidachi | F10: =COUNTBLANK(E10) -> 1 | Y10: =IF(F10=1,"",W10-E10) | Z10: =H10+J10-I10 -> 0 | AA10: =IF(F10=1,0,AA$6) -> 0 | AB10: =IF(AA10=0,0,Z10/AA10) -> 0
A11: ='Horaire samedi'!A11 -> VAHIBE | B11: ='Horaire samedi'!B11 -> 0.29166667 | C11: ='Horaire samedi'!C11 -> C11 | D11: =VLOOKUP(C11,'Liste chauffeur'!$B$5:$L$20,2,TRUE)&" "&VLOOKUP(C11,'Liste chauffeur'!$B$5:$L$20,3,TRUE) -> MADI BOINA Mkidachi | F11: =COUNTBLANK(E11) -> 1 | Y11: =IF(F11=1,"",W11-E11) | Z11: =H11+J11-I11 -> 0 | AA11: =IF(F11=1,0,AA$6) -> 0 | AB11: =IF(AA11=0,0,Z11/AA11) -> 0
A12: ='Horaire samedi'!A12 -> PASSAMAINTY | B12: ='Horaire samedi'!B12 -> 0.29166667 | C12: ='Horaire samedi'!C12 -> C9 | D12: =VLOOKUP(C12,'Liste chauffeur'!$B$5:$L$20,2,TRUE)&" "&VLOOKUP(C12,'Liste chauffeur'!$B$5:$L$20,3,TRUE) -> SANDI Maanrouf | F12: =COUNTBLANK(E12) -> 1 | L12: =K12-E12 -> 0 | P12: =O12-K12 -> 0 | T12: =S12-O12 -> 0 | V12: =IF(H12-I12+J12-M12+N12-Q12+R12=U12,"OK",H12-I12+J12-M12+N12-Q12+R12-U12) -> OK | Y12: =IF(F12=1,"",W12-E12) | Z12: =H12+J12-I12 -> 0 | AA12: =IF(F12=1,0,AA$6) -> 0 | AB12: =IF(AA12=0,0,Z12/AA12) -> 0
A13: ='Horaire samedi'!A13 -> VAHIBE | B13: ='Horaire samedi'!B13 -> 0.3125 | C13: ='Horaire samedi'!C13 -> C11 | D13: =VLOOKUP(C13,'Liste chauffeur'!$B$5:$L$20,2,TRUE)&" "&VLOOKUP(C13,'Liste chauffeur'!$B$5:$L$20,3,TRUE) -> MADI BOINA Mkidachi | F13: =COUNTBLANK(E13) -> 1 | L13: =K13-E13 -> 0 | P13: =O13-K13 -> 0 | T13: =S13-O13 -> 0 | Y13: =IF(F13=1,"",W13-E13) | Z13: =H13+J13-I13 -> 0 | AA13: =IF(F13=1,0,AA$6) -> 0 | AB13: =IF(AA13=0,0,Z13/AA13) -> 0
A14: ='Horaire samedi'!A14 -> PASSAMAINTY | B14: ='Horaire samedi'!B14 -> 0.3125 | C14: ='Horaire samedi'!C14 -> C9 | D14: =VLOOKUP(C14,'Liste chauffeur'!$B$5:$L$20,2,TRUE)&" "&VLOOKUP(C14,'Liste chauffeur'!$B$5:$L$20,3,TRUE) -> SANDI Maanrouf | F14: =COUNTBLANK(E14) -> 1 | L14: =K14-E14 -> 0 | P14: =O14-K14 -> 0 | T14: =S14-O14 -> 0 | Y14: =IF(F14=1,"",W14-E14) | Z14: =H14+J14-I14 -> 0 | AA14: =IF(F14=1,0,AA$6) -> 0 | AB14: =IF(AA14=0,0,Z14/AA14) -> 0
A15: ='Horaire samedi'!A15 -> VAHIBE | B15: ='Horaire samedi'!B15 -> 0.33333333 | C15: ='Horaire samedi'!C15 -> C9 | D15: =VLOOKUP(C15,'Liste chauffeur'!$B$5:$L$20,2,TRUE)&" "&VLOOKUP(C15,'Liste chauffeur'!$B$5:$L$20,3,TRUE) -> SANDI Maanrouf | F15: =COUNTBLANK(E15) -> 1 | L15: =K15-E15 -> 0 | P15: =O15-K15 -> 0 | T15: =S15-O15 -> 0 | Y15: =IF(F15=1,"",W15-E15) | Z15: =H15+J15-I15 -> 0 | AA15: =IF(F15=1,0,AA$6) -> 0 | AB15: =IF(AA15=0,0,Z15/AA15) -> 0
A16: ='Horaire samedi'!A16 -> PASSAMAINTY | B16: ='Horaire samedi'!B16 -> 0.33333333 | C16: ='Horaire samedi'!C16 -> C11 | D16: =VLOOKUP(C16,'Liste chauffeur'!$B$5:$L$20,2,TRUE)&" "&VLOOKUP(C16,'Liste chauffeur'!$B$5:$L$20,3,TRUE) -> MADI BOINA Mkidachi | F16: =COUNTBLANK(E16) -> 1 | L16: =K16-E16 -> 0 | P16: =O16-K16 -> 0 | T16: =S16-O16 -> 0 | V16: =IF(H16-I16+J16-M16+N16-Q16+R16=U16,"OK",H16-I16+J16-M16+N16-Q16+R16-U16) -> OK | Y16: =IF(F16=1,"",W16-E16) | Z16: =H16+J16-I16 -> 0 | AA16: =IF(F16=1,0,AA$6) -> 0 | AB16: =IF(AA16=0,0,Z16/AA16) -> 0
A17: ='Horaire samedi'!A17 -> VAHIBE | B17: ='Horaire samedi'!B17 -> 0.375 | C17: ='Horaire samedi'!C17 -> C11 | D17: =VLOOKUP(C17,'Liste chauffeur'!$B$5:$L$20,2,TRUE)&" "&VLOOKUP(C17,'Liste chauffeur'!$B$5:$L$20,3,TRUE) -> MADI BOINA Mkidachi | F17: =COUNTBLANK(E17) -> 1 | L17: =K17-E17 -> 0 | P17: =O17-K17 -> 0 | T17: =S17-O17 -> 0 | V17: =IF(H17-I17+J17-M17+N17-Q17+R17=U17,"OK",H17-I17+J17-M17+N17-Q17+R17-U17) -> OK | Y17: =IF(F17=1,"",W17-E17) | Z17: =H17+J17-I17 -> 0 | AA17: =IF(F17=1,0,AA$6) -> 0 | AB17: =IF(AA17=0,0,Z17/AA17) -> 0
A18: ='Horaire samedi'!A18 -> PASSAMAINTY | B18: ='Horaire samedi'!B18 -> 0.375 | C18: ='Horaire samedi'!C18 -> C9 | D18: =VLOOKUP(C18,'Liste chauffeur'!$B$5:$L$20,2,TRUE)&" "&VLOOKUP(C18,'Liste chauffeur'!$B$5:$L$20,3,TRUE) -> SANDI Maanrouf | F18: =COUNTBLANK(E18) -> 1 | Z18: =H18+J18-I18 -> 0 | AA18: =IF(F18=1,0,AA$6) -> 0 | AB18: =IF(AA18=0,0,Z18/AA18) -> 0
A19: ='Horaire samedi'!A19 -> VAHIBE | B19: ='Horaire samedi'!B19 -> 0.39583333 | C19: ='Horaire samedi'!C19 -> C9 | D19: =VLOOKUP(C19,'Liste chauffeur'!$B$5:$L$20,2,TRUE)&" "&VLOOKUP(C19,'Liste chauffeur'!$B$5:$L$20,3,TRUE) -> SANDI Maanrouf | F19: =COUNTBLANK(E19) -> 1 | L19: =K19-E19 -> 0 | P19: =O19-K19 -> 0 | T19: =S19-O19 -> 0 | V19: =IF(H19-I19+J19-M19+N19-Q19+R19=U19,"OK",H19-I19+J19-M19+N19-Q19+R19-U19) -> OK | Y19: =IF(F19=1,"",W19-E19) | Z19: =H19+J19-I19 -> 0 | AA19: =IF(F19=1,0,AA$6) -> 0 | AB19: =IF(AA19=0,0,Z19/AA19) -> 0
A20: ='Horaire samedi'!A20 -> PASSAMAINTY | B20: ='Horaire samedi'!B20 -> 0.39583333 | C20: ='Horaire samedi'!C20 -> C11 | D20: =VLOOKUP(C20,'Liste chauffeur'!$B$5:$L$20,2,TRUE)&" "&VLOOKUP(C20,'Liste chauffeur'!$B$5:$L$20,3,TRUE) -> MADI BOINA Mkidachi | F20: =COUNTBLANK(E20) -> 1 | L20: =K20-E20 -> 0 | P20: =O20-K20 -> 0 | T20: =S20-O20 -> 0 | V20: =IF(H20-I20+J20-M20+N20-Q20+R20=U20,"OK",H20-I20+J20-M20+N20-Q20+R20-U20) -> OK | Y20: =IF(F20=1,"",W20-E20) | Z20: =H20+J20-I20 -> 0 | AA20: =IF(F20=1,0,AA$6) -> 0 | AB20: =IF(AA20=0,0,Z20/AA20) -> 0
A21: ='Horaire samedi'!A21 -> VAHIBE | B21: ='Horaire samedi'!B21 -> 0.41666667 | C21: ='Horaire samedi'!C21 -> C11 | D21: =VLOOKUP(C21,'Liste chauffeur'!$B$5:$L$20,2,TRUE)&" "&VLOOKUP(C21,'Liste chauffeur'!$B$5:$L$20,3,TRUE) -> MADI BOINA Mkidachi | F21: =COUNTBLANK(E21) -> 1 | L21: =K21-E21 -> 0 | P21: =O21-K21 -> 0 | T21: =S21-O21 -> 0 | V21: =IF(H21-I21+J21-M21+N21-Q21+R21=U21,"OK",H21-I21+J21-M21+N21-Q21+R21-U21) -> OK | Y21: =IF(F21=1,"",W21-E21) | Z21: =H21+J21-I21 -> 0 | AA21: =IF(F21=1,0,AA$6) -> 0 | AB21: =IF(AA21=0,0,Z21/AA21) -> 0
A22: ='Horaire samedi'!A22 -> PASSAMAINTY | B22: ='Horaire samedi'!B22 -> 0.41666667 | C22: ='Horaire samedi'!C22 -> C9 | D22: =VLOOKUP(C22,'Liste chauffeur'!$B$5:$L$20,2,TRUE)&" "&VLOOKUP(C22,'Liste chauffeur'!$B$5:$L$20,3,TRUE) -> SANDI Maanrouf | F22: =COUNTBLANK(E22) -> 1 | L22: =K22-E22 -> 0 | P22: =O22-K22 -> 0 | T22: =S22-O22 -> 0 | V22: =IF(H22-I22+J22-M22+N22-Q22+R22=U22,"OK",H22-I22+J22-M22+N22-Q22+R22-U22) -> OK | Y22: =IF(F22=1,"",W22-E22) | Z22: =H22+J22-I22 -> 0 | AA22: =IF(F22=1,0,AA$6) -> 0 | AB22: =IF(AA22=0,0,Z22/AA22) -> 0
A23: ='Horaire samedi'!A23 -> VAHIBE | B23: ='Horaire samedi'!B23 -> 0.4375 | C23: ='Horaire samedi'!C23 -> C9 | D23: =VLOOKUP(C23,'Liste chauffeur'!$B$5:$L$20,2,TRUE)&" "&VLOOKUP(C23,'Liste chauffeur'!$B$5:$L$20,3,TRUE) -> SANDI Maanrouf | F23: =COUNTBLANK(E23) -> 1 | L23: =K23-E23 -> 0 | P23: =O23-K23 -> 0 | T23: =S23-O23 -> 0 | V23: =IF(H23-I23+J23-M23+N23-Q23+R23=U23,"OK",H23-I23+J23-M23+N23-Q23+R23-U23) -> OK | Y23: =IF(F23=1,"",W23-E23) | Z23: =H23+J23-I23 -> 0 | AA23: =IF(F23=1,0,AA$6) -> 0 | AB23: =IF(AA23=0,0,Z23/AA23) -> 0
A24: ='Horaire samedi'!A24 -> PASSAMAINTY | B24: ='Horaire samedi'!B24 -> 0.4375 | C24: ='Horaire samedi'!C24 -> C11 | D24: =VLOOKUP(C24,'Liste chauffeur'!$B$5:$L$20,2,TRUE)&" "&VLOOKUP(C24,'Liste chauffeur'!$B$5:$L$20,3,TRUE) -> MADI BOINA Mkidachi | F24: =COUNTBLANK(E24) -> 1 | L24: =K24-E24 -> 0 | P24: =O24-K24 -> 0 | T24: =S24-O24 -> 0 | V24: =IF(H24-I24+J24-M24+N24-Q24+R24=U24,"OK",H24-I24+J24-M24+N24-Q24+R24-U24) -> OK | Y24: =IF(F24=1,"",W24-E24) | Z24: =H24+J24-I24 -> 0 | AA24: =IF(F24=1,0,AA$6) -> 0 | AB24: =IF(AA24=0,0,Z24/AA24) -> 0
A25: ='Horaire samedi'!A25 -> VAHIBE | B25: ='Horaire samedi'!B25 -> 0.45833333 | C25: ='Horaire samedi'!C25 -> C11 | D25: =VLOOKUP(C25,'Liste chauffeur'!$B$5:$L$20,2,TRUE)&" "&VLOOKUP(C25,'Liste chauffeur'!$B$5:$L$20,3,TRUE) -> MADI BOINA Mkidachi | F25: =COUNTBLANK(E25) -> 1 | Z25: =H25+J25-I25 -> 0 | AA25: =IF(F25=1,0,AA$6) -> 0 | AB25: =IF(AA25=0,0,Z25/AA25) -> 0
A26: ='Horaire samedi'!A26 -> PASSAMAINTY | B26: ='Horaire samedi'!B26 -> 0.45833333 | C26: ='Horaire samedi'!C26 -> C9 | D26: =VLOOKUP(C26,'Liste chauffeur'!$B$5:$L$20,2,TRUE)&" "&VLOOKUP(C26,'Liste chauffeur'!$B$5:$L$20,3,TRUE) -> SANDI Maanrouf | F26: =COUNTBLANK(E26) -> 1 | L26: =K26-E26 -> 0 | P26: =O26-K26 -> 0 | T26: =S26-O26 -> 0 | V26: =IF(H26-I26+J26-M26+N26-Q26+R26=U26,"OK",H26-I26+J26-M26+N26-Q26+R26-U26) -> OK | Y26: =IF(F26=1,"",W26-E26) | Z26: =H26+J26-I26 -> 0 | AA26: =IF(F26=1,0,AA$6) -> 0 | AB26: =IF(AA26=0,0,Z26/AA26) -> 0
A27: ='Horaire samedi'!A27 -> VAHIBE | B27: ='Horaire samedi'!B27 -> 0.47916667 | C27: ='Horaire samedi'!C27 -> C9 | D27: =VLOOKUP(C27,'Liste chauffeur'!$B$5:$L$20,2,TRUE)&" "&VLOOKUP(C27,'Liste chauffeur'!$B$5:$L$20,3,TRUE) -> SANDI Maanrouf | F27: =COUNTBLANK(E27) -> 1 | L27: =K27-E27 -> 0 | P27: =O27-K27 -> 0 | T27: =S27-O27 -> 0 | V27: =IF(H27-I27+J27-M27+N27-Q27+R27=U27,"OK",H27-I27+J27-M27+N27-Q27+R27-U27) -> OK | Y27: =IF(F27=1,"",W27-E27) | Z27: =H27+J27-I27 -> 0 | AA27: =IF(F27=1,0,AA$6) -> 0 | AB27: =IF(AA27=0,0,Z27/AA27) -> 0
A28: ='Horaire samedi'!A28 -> PASSAMAINTY | B28: ='Horaire samedi'!B28 -> 0.47916667 | C28: ='Horaire samedi'!C28 -> C11 | D28: =VLOOKUP(C28,'Liste chauffeur'!$B$5:$L$20,2,TRUE)&" "&VLOOKUP(C28,'Liste chauffeur'!$B$5:$L$20,3,TRUE) -> MADI BOINA Mkidachi | F28: =COUNTBLANK(E28) -> 1 | L28: =K28-E28 -> 0 | P28: =O28-K28 -> 0 | T28: =S28-O28 -> 0 | V28: =IF(H28-I28+J28-M28+N28-Q28+R28=U28,"OK",H28-I28+J28-M28+N28-Q28+R28-U28) -> OK | Y28: =IF(F28=1,"",W28-E28) | Z28: =H28+J28-I28 -> 0 | AA28: =IF(F28=1,0,AA$6) -> 0 | AB28: =IF(AA28=0,0,Z28/AA28) -> 0
A29: ='Horaire samedi'!A29 -> VAHIBE | B29: ='Horaire samedi'!B29 -> 0.5 | C29: ='Horaire samedi'!C29 -> C11 | D29: =VLOOKUP(C29,'Liste chauffeur'!$B$5:$L$20,2,TRUE)&" "&VLOOKUP(C29,'Liste chauffeur'!$B$5:$L$20,3,TRUE) -> MADI BOINA Mkidachi | F29: =COUNTBLANK(E29) -> 1 | L29: =K29-E29 -> 0 | P29: =O29-K29 -> 0 | T29: =S29-O29 -> 0 | V29: =IF(H29-I29+J29-M29+N29-Q29+R29=U29,"OK",H29-I29+J29-M29+N29-Q29+R29-U29) -> OK | Y29: =IF(F29=1,"",W29-E29) | Z29: =H29+J29-I29 -> 0 | AA29: =IF(F29=1,0,AA$6) -> 0 | AB29: =IF(AA29=0,0,Z29/AA29) -> 0
A30: ='Horaire samedi'!A30 -> PASSAMAINTY | B30: ='Horaire samedi'!B30 -> 0.5 | C30: ='Horaire samedi'!C30 -> C9 | D30: =VLOOKUP(C30,'Liste chauffeur'!$B$5:$L$20,2,TRUE)&" "&VLOOKUP(C30,'Liste chauffeur'!$B$5:$L$20,3,TRUE) -> SANDI Maanrouf | F30: =COUNTBLANK(E30) -> 1 | L30: =K30-E30 -> 0 | P30: =O30-K30 -> 0 | T30: =S30-O30 -> 0 | V30: =IF(H30-I30+J30-M30+N30-Q30+R30=U30,"OK",H30-I30+J30-M30+N30-Q30+R30-U30) -> OK | Y30: =IF(F30=1,"",W30-E30) | Z30: =H30+J30-I30 -> 0 | AA30: =IF(F30=1,0,AA$6) -> 0 | AB30: =IF(AA30=0,0,Z30/AA30) -> 0
B31: ST1 | F31: =SUM(F8:F30) -> 23 | G31: =SUM(G8:G30) -> 0 | Y31: =AVERAGE(Y8:Y30) -> #DIV/0! | Z31: =SUM(Z8:Z30) -> 0 | AA31: =SUM(AA8:AA30) -> 0 | AB31: =IF(AA31=0,0,Z31/AA31) -> 0
A32: ='Horaire samedi'!A31 -> VAHIBE | B32: ='Horaire samedi'!B31 -> 0.52083333 | C32: ='Horaire samedi'!C31 -> C9 | D32: =VLOOKUP(C32,'Liste chauffeur'!$B$5:$L$20,2,TRUE)&" "&VLOOKUP(C32,'Liste chauffeur'!$B$5:$L$20,3,TRUE) -> SANDI Maanrouf | F32: =COUNTBLANK(E32) -> 1 | L32: =K32-E32 -> 0 | P32: =O32-K32 -> 0 | T32: =S32-O32 -> 0 | V32: =IF(H32-I32+J32-M32+N32-Q32+R32=U32,"OK",H32-I32+J32-M32+N32-Q32+R32-U32) -> OK | Y32: =IF(F32=1,"",W32-E32) | Z32: =H32+J32-I32 -> 0 | AA32: =IF(F32=1,0,AA$6) -> 0 | AB32: =IF(AA32=0,0,Z32/AA32) -> 0
A33: ='Horaire samedi'!A32 -> PASSAMAINTY | B33: ='Horaire samedi'!B32 -> 0.52083333 | C33: ='Horaire samedi'!C32 -> C11 | D33: =VLOOKUP(C33,'Liste chauffeur'!$B$5:$L$20,2,TRUE)&" "&VLOOKUP(C33,'Liste chauffeur'!$B$5:$L$20,3,TRUE) -> MADI BOINA Mkidachi | F33: =COUNTBLANK(E33) -> 1 | Z33: =H33+J33-I33 -> 0 | AA33: =IF(F33=1,0,AA$6) -> 0 | AB33: =IF(AA33=0,0,Z33/AA33) -> 0
A34: ='Horaire samedi'!A33 -> VAHIBE | B34: ='Horaire samedi'!B33 -> 0.54166667 | C34: ='Horaire samedi'!C33 -> C11 | D34: =VLOOKUP(C34,'Liste chauffeur'!$B$5:$L$20,2,TRUE)&" "&VLOOKUP(C34,'Liste chauffeur'!$B$5:$L$20,3,TRUE) -> MADI BOINA Mkidachi | F34: =COUNTBLANK(E34) -> 1 | L34: =K34-E34 -> 0 | P34: =O34-K34 -> 0 | T34: =S34-O34 -> 0 | V34: =IF(H34-I34+J34-M34+N34-Q34+R34=U34,"OK",H34-I34+J34-M34+N34-Q34+R34-U34) -> OK | Y34: =IF(F34=1,"",W34-E34) | Z34: =H34+J34-I34 -> 0 | AA34: =IF(F34=1,0,AA$6) -> 0 | AB34: =IF(AA34=0,0,Z34/AA34) -> 0
A35: ='Horaire samedi'!A34 -> PASSAMAINTY | B35: ='Horaire samedi'!B34 -> 0.54166667 | C35: ='Horaire samedi'!C34 -> C9 | D35: =VLOOKUP(C35,'Liste chauffeur'!$B$5:$L$20,2,TRUE)&" "&VLOOKUP(C35,'Liste chauffeur'!$B$5:$L$20,3,TRUE) -> SANDI Maanrouf | F35: =COUNTBLANK(E35) -> 1 | L35: =K35-E35 -> 0 | V35: =IF(H35-I35+J35-M35+N35-Q35+R35=U35,"OK",H35-I35+J35-M35+N35-Q35+R35-U35) -> OK | Y35: =IF(F35=1,"",W35-E35) | Z35: =H35+J35-I35 -> 0 | AA35: =IF(F35=1,0,AA$6) -> 0 | AB35: =IF(AA35=0,0,Z35/AA35) -> 0
A36: ='Horaire samedi'!A35 -> VAHIBE | B36: ='Horaire samedi'!B35 -> 0.5625 | C36: ='Horaire samedi'!C35 -> C9 | D36: =VLOOKUP(C36,'Liste chauffeur'!$B$5:$L$20,2,TRUE)&" "&VLOOKUP(C36,'Liste chauffeur'!$B$5:$L$20,3,TRUE) -> SANDI Maanrouf | F36: =COUNTBLANK(E36) -> 1 | L36: =K36-E36 -> 0 | V36: =IF(H36-I36+J36-M36+N36-Q36+R36=U36,"OK",H36-I36+J36-M36+N36-Q36+R36-U36) -> OK | Y36: =IF(F36=1,"",W36-E36) | Z36: =H36+J36-I36 -> 0 | AA36: =IF(F36=1,0,AA$6) -> 0 | AB36: =IF(AA36=0,0,Z36/AA36) -> 0
A37: ='Horaire samedi'!A36 -> PASSAMAINTY | B37: ='Horaire samedi'!B36 -> 0.5625 | C37: ='Horaire samedi'!C36 -> C10 | D37: =VLOOKUP(C37,'Liste chauffeur'!$B$5:$L$20,2,TRUE)&" "&VLOOKUP(C37,'Liste chauffeur'!$B$5:$L$20,3,TRUE) -> ISSIHAKA M'Changama | F37: =COUNTBLANK(E37) -> 1 | L37: =K37-E37 -> 0 | V37: =IF(H37-I37+J37-M37+N37-Q37+R37=U37,"OK",H37-I37+J37-M37+N37-Q37+R37-U37) -> OK | Y37: =IF(F37=1,"",W37-E37) | Z37: =H37+J37-I37 -> 0 | AA37: =IF(F37=1,0,AA$6) -> 0 | AB37: =IF(AA37=0,0,Z37/AA37) -> 0
A38: ='Horaire samedi'!A37 -> VAHIBE | B38: ='Horaire samedi'!B37 -> 0.58333333 | C38: ='Horaire samedi'!C37 -> C10 | D38: =VLOOKUP(C38,'Liste chauffeur'!$B$5:$L$20,2,TRUE)&" "&VLOOKUP(C38,'Liste chauffeur'!$B$5:$L$20,3,TRUE) -> ISSIHAKA M'Changama | F38: =COUNTBLANK(E38) -> 1 | L38: =K38-E38 -> 0 | V38: =IF(H38-I38+J38-M38+N38-Q38+R38=U38,"OK",H38-I38+J38-M38+N38-Q38+R38-U38) -> OK | Y38: =IF(F38=1,"",W38-E38) | Z38: =H38+J38-I38 -> 0 | AA38: =IF(F38=1,0,AA$6) -> 0 | AB38: =IF(AA38=0,0,Z38/AA38) -> 0
A39: ='Horaire samedi'!A38 -> PASSAMAINTY | B39: ='Horaire samedi'!B38 -> 0.58333333 | C39: ='Horaire samedi'!C38 -> C8 | D39: =VLOOKUP(C39,'Liste chauffeur'!$B$5:$L$20,2,TRUE)&" "&VLOOKUP(C39,'Liste chauffeur'!$B$5:$L$20,3,TRUE) -> HADHURAMI Makinedine | F39: =COUNTBLANK(E39) -> 1 | L39: =K39-E39 -> 0 | V39: =IF(H39-I39+J39-M39+N39-Q39+R39=U39,"OK",H39-I39+J39-M39+N39-Q39+R39-U39) -> OK | Y39: =IF(F39=1,"",W39-E39) | Z39: =H39+J39-I39 -> 0 | AA39: =IF(F39=1,0,AA$6) -> 0 | AB39: =IF(AA39=0,0,Z39/AA39) -> 0
A40: ='Horaire samedi'!A39 -> VAHIBE | B40: ='Horaire samedi'!B39 -> 0.60416667 | C40: ='Horaire samedi'!C39 -> C8 | D40: =VLOOKUP(C40,'Liste chauffeur'!$B$5:$L$20,2,TRUE)&" "&VLOOKUP(C40,'Liste chauffeur'!$B$5:$L$20,3,TRUE) -> HADHURAMI Makinedine | F40: =COUNTBLANK(E40) -> 1 | L40: =K40-E40 -> 0 | V40: =IF(H40-I40+J40-M40+N40-Q40+R40=U40,"OK",H40-I40+J40-M40+N40-Q40+R40-U40) -> OK | Y40: =IF(F40=1,"",W40-E40) | Z40: =H40+J40-I40 -> 0 | AA40: =IF(F40=1,0,AA$6) -> 0 | AB40: =IF(AA40=0,0,Z40/AA40) -> 0
A41: ='Horaire samedi'!A40 -> PASSAMAINTY | B41: ='Horaire samedi'!B40 -> 0.60416667 | C41: ='Horaire samedi'!C40 -> C10 | D41: =VLOOKUP(C41,'Liste chauffeur'!$B$5:$L$20,2,TRUE)&" "&VLOOKUP(C41,'Liste chauffeur'!$B$5:$L$20,3,TRUE) -> ISSIHAKA M'Changama | F41: =COUNTBLANK(E41) -> 1 | L41: =K41-E41 -> 0 | V41: =IF(H41-I41+J41-M41+N41-Q41+R41=U41,"OK",H41-I41+J41-M41+N41-Q41+R41-U41) -> OK | Y41: =IF(F41=1,"",W41-E41) | Z41: =H41+J41-I41 -> 0 | AA41: =IF(F41=1,0,AA$6) -> 0 | AB41: =IF(AA41=0,0,Z41/AA41) -> 0
A42: ='Horaire samedi'!A41 -> VAHIBE | B42: ='Horaire samedi'!B41 -> 0.625 | C42: ='Horaire samedi'!C41 -> C10 | D42: =VLOOKUP(C42,'Liste chauffeur'!$B$5:$L$20,2,TRUE)&" "&VLOOKUP(C42,'Liste chauffeur'!$B$5:$L$20,3,TRUE) -> ISSIHAKA M'Changama | F42: =COUNTBLANK(E42) -> 1 | L42: =K42-E42 -> 0 | V42: =IF(H42-I42+J42-M42+N42-Q42+R42=U42,"OK",H42-I42+J42-M42+N42-Q42+R42-U42) -> OK | Y42: =IF(F42=1,"",W42-E42) | Z42: =H42+J42-I42 -> 0 | AA42: =IF(F42=1,0,AA$6) -> 0 | AB42: =IF(AA42=0,0,Z42/AA42) -> 0
A43: ='Horaire samedi'!A42 -> PASSAMAINTY | B43: ='Horaire samedi'!B42 -> 0.625 | C43: ='Horaire samedi'!C42 -> C8 | D43: =VLOOKUP(C43,'Liste chauffeur'!$B$5:$L$20,2,TRUE)&" "&VLOOKUP(C43,'Liste chauffeur'!$B$5:$L$20,3,TRUE) -> HADHURAMI Makinedine | F43: =COUNTBLANK(E43) -> 1 | L43: =K43-E43 -> 0 | V43: =IF(H43-I43+J43-M43+N43-Q43+R43=U43,"OK",H43-I43+J43-M43+N43-Q43+R43-U43) -> OK | Y43: =IF(F43=1,"",W43-E43) | Z43: =H43+J43-I43 -> 0 | AA43: =IF(F43=1,0,AA$6) -> 0 | AB43: =IF(AA43=0,0,Z43/AA43) -> 0
A44: ='Horaire samedi'!A43 -> VAHIBE | B44: ='Horaire samedi'!B43 -> 0.64583333 | C44: ='Horaire samedi'!C43 -> C8 | D44: =VLOOKUP(C44,'Liste chauffeur'!$B$5:$L$20,2,TRUE)&" "&VLOOKUP(C44,'Liste chauffeur'!$B$5:$L$20,3,TRUE) -> HADHURAMI Makinedine | F44: =COUNTBLANK(E44) -> 1 | L44: =K44-E44 -> 0 | V44: =IF(H44-I44+J44-M44+N44-Q44+R44=U44,"OK",H44-I44+J44-M44+N44-Q44+R44-U44) -> OK | Y44: =IF(F44=1,"",W44-E44) | Z44: =H44+J44-I44 -> 0 | AA44: =IF(F44=1,0,AA$6) -> 0 | AB44: =IF(AA44=0,0,Z44/AA44) -> 0
A45: ='Horaire samedi'!A44 -> PASSAMAINTY | B45: ='Horaire samedi'!B44 -> 0.64583333 | C45: ='Horaire samedi'!C44 -> C10 | D45: =VLOOKUP(C45,'Liste chauffeur'!$B$5:$L$20,2,TRUE)&" "&VLOOKUP(C45,'Liste chauffeur'!$B$5:$L$20,3,TRUE) -> ISSIHAKA M'Changama | F45: =COUNTBLANK(E45) -> 1 | L45: =K45-E45 -> 0 | V45: =IF(H45-I45+J45-M45+N45-Q45+R45=U45,"OK",H45-I45+J45-M45+N45-Q45+R45-U45) -> OK | Y45: =IF(F45=1,"",W45-E45) | Z45: =H45+J45-I45 -> 0 | AA45: =IF(F45=1,0,AA$6) -> 0 | AB45: =IF(AA45=0,0,Z45/AA45) -> 0
A46: ='Horaire samedi'!A45 -> VAHIBE | B46: ='Horaire samedi'!B45 -> 0.66666667 | C46: ='Horaire samedi'!C45 -> C10 | D46: =VLOOKUP(C46,'Liste chauffeur'!$B$5:$L$20,2,TRUE)&" "&VLOOKUP(C46,'Liste chauffeur'!$B$5:$L$20,3,TRUE) -> ISSIHAKA M'Changama | F46: =COUNTBLANK(E46) -> 1 | L46: =K46-E46 -> 0 | V46: =IF(H46-I46+J46-M46+N46-Q46+R46=U46,"OK",H46-I46+J46-M46+N46-Q46+R46-U46) -> OK | Y46: =IF(F46=1,"",W46-E46) | Z46: =H46+J46-I46 -> 0 | AA46: =IF(F46=1,0,AA$6) -> 0 | AB46: =IF(AA46=0,0,Z46/AA46) -> 0
A47: ='Horaire samedi'!A46 -> PASSAMAINTY | B47: ='Horaire samedi'!B46 -> 0.66666667 | C47: ='Horaire samedi'!C46 -> C8 | D47: =VLOOKUP(C47,'Liste chauffeur'!$B$5:$L$20,2,TRUE)&" "&VLOOKUP(C47,'Liste chauffeur'!$B$5:$L$20,3,TRUE) -> HADHURAMI Makinedine | F47: =COUNTBLANK(E47) -> 1 | L47: =K47-E47 -> 0 | V47: =IF(H47-I47+J47-M47+N47-Q47+R47=U47,"OK",H47-I47+J47-M47+N47-Q47+R47-U47) -> OK | Y47: =IF(F47=1,"",W47-E47) | Z47: =H47+J47-I47 -> 0 | AA47: =IF(F47=1,0,AA$6) -> 0 | AB47: =IF(AA47=0,0,Z47/AA47) -> 0
A48: ='Horaire samedi'!A47 -> VAHIBE | B48: ='Horaire samedi'!B47 -> 0.6875 | C48: ='Horaire samedi'!C47 -> C8 | D48: =VLOOKUP(C48,'Liste chauffeur'!$B$5:$L$20,2,TRUE)&" "&VLOOKUP(C48,'Liste chauffeur'!$B$5:$L$20,3,TRUE) -> HADHURAMI Makinedine | F48: =COUNTBLANK(E48) -> 1 | L48: =K48-E48 -> 0 | Y48: =IF(F48=1,"",W48-E48) | Z48: =H48+J48-I48 -> 0 | AA48: =IF(F48=1,0,AA$6) -> 0 | AB48: =IF(AA48=0,0,Z48/AA48) -> 0
A49: ='Horaire samedi'!A48 -> PASSAMAINTY | B49: ='Horaire samedi'!B48 -> 0.6875 | C49: ='Horaire samedi'!C48 -> C10 | D49: =VLOOKUP(C49,'Liste chauffeur'!$B$5:$L$20,2,TRUE)&" "&VLOOKUP(C49,'Liste chauffeur'!$B$5:$L$20,3,TRUE) -> ISSIHAKA M'Changama | F49: =COUNTBLANK(E49) -> 1 | Y49: =IF(F49=1,"",W49-E49) | Z49: =H49+J49-I49 -> 0 | AA49: =IF(F49=1,0,AA$6) -> 0 | AB49: =IF(AA49=0,0,Z49/AA49) -> 0
A50: ='Horaire samedi'!A49 -> VAHIBE | B50: ='Horaire samedi'!B49 -> 0.70833333 | C50: ='Horaire samedi'!C49 -> C10 | D50: =VLOOKUP(C50,'Liste chauffeur'!$B$5:$L$20,2,TRUE)&" "&VLOOKUP(C50,'Liste chauffeur'!$B$5:$L$20,3,TRUE) -> ISSIHAKA M'Changama | F50: =COUNTBLANK(E50) -> 1 | Y50: =IF(F50=1,"",W50-E50) | Z50: =H50+J50-I50 -> 0 | AA50: =IF(F50=1,0,AA$6) -> 0 | AB50: =IF(AA50=0,0,Z50/AA50) -> 0
A51: ='Horaire samedi'!A50 -> PASSAMAINTY | B51: ='Horaire samedi'!B50 -> 0.70833333 | C51: ='Horaire samedi'!C50 -> C8 | D51: =VLOOKUP(C51,'Liste chauffeur'!$B$5:$L$20,2,TRUE)&" "&VLOOKUP(C51,'Liste chauffeur'!$B$5:$L$20,3,TRUE) -> HADHURAMI Makinedine | F51: =COUNTBLANK(E51) -> 1 | Y51: =IF(F51=1,"",W51-E51) | Z51: =H51+J51-I51 -> 0 | AA51: =IF(F51=1,0,AA$6) -> 0 | AB51: =IF(AA51=0,0,Z51/AA51) -> 0
A52: ='Horaire samedi'!A51 -> VAHIBE | B52: ='Horaire samedi'!B51 -> 0.72916667 | C52: ='Horaire samedi'!C51 -> C8 | D52: =VLOOKUP(C52,'Liste chauffeur'!$B$5:$L$20,2,TRUE)&" "&VLOOKUP(C52,'Liste chauffeur'!$B$5:$L$20,3,TRUE) -> HADHURAMI Makinedine | F52: =COUNTBLANK(E52) -> 1 | Y52: =IF(F52=1,"",W52-E52) | Z52: =H52+J52-I52 -> 0 | AA52: =IF(F52=1,0,AA$6) -> 0 | AB52: =IF(AA52=0,0,Z52/AA52) -> 0
A53: ='Horaire samedi'!A52 -> PASSAMAINTY | B53: ='Horaire samedi'!B52 -> 0.72916667 | C53: ='Horaire samedi'!C52 -> C10 | D53: =VLOOKUP(C53,'Liste chauffeur'!$B$5:$L$20,2,TRUE)&" "&VLOOKUP(C53,'Liste chauffeur'!$B$5:$L$20,3,TRUE) -> ISSIHAKA M'Changama | F53: =COUNTBLANK(E53) -> 1 | Y53: =IF(F53=1,"",W53-E53) | Z53: =H53+J53-I53 -> 0 | AA53: =IF(F53=1,0,AA$6) -> 0 | AB53: =IF(AA53=0,0,Z53/AA53) -> 0
A54: ='Horaire samedi'!A53 -> VAHIBE | B54: ='Horaire samedi'!B53 -> 0.75 | C54: ='Horaire samedi'!C53 -> C10 | D54: =VLOOKUP(C54,'Liste chauffeur'!$B$5:$L$20,2,TRUE)&" "&VLOOKUP(C54,'Liste chauffeur'!$B$5:$L$20,3,TRUE) -> ISSIHAKA M'Changama | F54: =COUNTBLANK(E54) -> 1 | Y54: =IF(F54=1,"",W54-E54) | Z54: =H54+J54-I54 -> 0 | AA54: =IF(F54=1,0,AA$6) -> 0 | AB54: =IF(AA54=0,0,Z54/AA54) -> 0
A55: ='Horaire samedi'!A54 -> PASSAMAINTY | B55: ='Horaire samedi'!B54 -> 0.75 | C55: ='Horaire samedi'!C54 -> C8 | D55: =VLOOKUP(C55,'Liste chauffeur'!$B$5:$L$20,2,TRUE)&" "&VLOOKUP(C55,'Liste chauffeur'!$B$5:$L$20,3,TRUE) -> HADHURAMI Makinedine | F55: =COUNTBLANK(E55) -> 1 | Y55: =IF(F55=1,"",W55-E55) | Z55: =H55+J55-I55 -> 0 | AA55: =IF(F55=1,0,AA$6) -> 0 | AB55: =IF(AA55=0,0,Z55/AA55) -> 0
B56: ST2 | F56: =SUM(F32:F55) -> 24 | Y56: =AVERAGE(Y$32:Y$55) -> #DIV/0! | Z56: =SUM(Z$32:Z$55) -> 0 | AA56: =SUM(AA$32:AA$55) -> 0 | AB56: =IF(AA56=0,0,Z56/AA56) -> 0
B57: ST3 | F57: =F56+F31 -> 47 | Y57: =AVERAGE(Y$8:Y$30,Y$32:Y$55) -> #DIV/0! | Z57: =Z56+Z31 -> 0 | AA57: =AA56+AA31 -> 0 | AB57: =IF(AA57=0,0,Z57/AA57) -> 0
A58: REMPLACEMENT | C58: C | O58: =M58-#REF! -> #REF! | P58: =#REF!+#REF!-#REF! -> #REF!
A59: REMPLACEMENT | C59: C
A60: REMPLACEMENT | C60: C
A61: REMPLACEMENT | C61: C
A62: REMPLACEMENT | C62: C | O62: =M62-#REF! -> #REF! | P62: =#REF!+#REF!-#REF! -> #REF!
E64: Signature Chauffeur | I64: Signature Coordinateur
B67: Statistiques | C67: nbre de trajets planifiés | D67: Nbre trajets non effectués | E67: Nbre trajets effectués non planifiés | F67: Nbre trajets dont départ > 10 minutes en retard
B68: C1 | C68: =COUNTIF($B$8:$C$55,B68) -> 0 | D68: =C68-(COUNTIFS(C$8:C$55,B68,X$8:X$55,"")) -> 0 | E68: =COUNTIFS(X$8:X$55,$B68) -> 0 | F68: =COUNTIFS(G$8:G$55,$B68) -> 0
B69: C2 | C69: =COUNTIF($B$8:$C$55,B69) -> 0 | D69: =C69-(COUNTIFS(C$8:C$55,B69,X$8:X$55,"")) -> 0 | E69: =COUNTIFS(X$8:X$55,$B69) -> 0 | F69: =COUNTIFS(G$8:G$55,$B69) -> 0
B70: C3 | C70: =COUNTIF($B$8:$C$55,B70) -> 0 | D70: =C70-(COUNTIFS(C$8:C$55,B70,X$8:X$55,"")) -> 0 | E70: =COUNTIFS(X$8:X$55,$B70) -> 0 | F70: =COUNTIFS(G$8:G$55,$B70) -> 0
B71: C4 | C71: =COUNTIF($B$8:$C$55,B71) -> 0 | D71: =C71-(COUNTIFS(C$8:C$55,B71,X$8:X$55,"")) -> 0 | E71: =COUNTIFS(X$8:X$55,$B71) -> 0 | F71: =COUNTIFS(G$8:G$55,$B71) -> 0
B72: C5 | C72: =COUNTIF($B$8:$C$55,B72) -> 0 | D72: =C72-(COUNTIFS(C$8:C$55,B72,X$8:X$55,"")) -> 0 | E72: =COUNTIFS(X$8:X$55,$B72) -> 0 | F72: =COUNTIFS(G$8:G$55,$B72) -> 0
B73: C6 | C73: =COUNTIF($B$8:$C$55,B73) -> 0 | D73: =C73-(COUNTIFS(C$8:C$55,B73,X$8:X$55,"")) -> 0 | E73: =COUNTIFS(X$8:X$55,$B73) -> 0 | F73: =COUNTIFS(G$8:G$55,$B73) -> 0
B74: C7 | C74: =COUNTIF($B$8:$C$55,B74) -> 0 | D74: =C74-(COUNTIFS(C$8:C$55,B74,X$8:X$55,"")) -> 0 | E74: =COUNTIFS(X$8:X$55,$B74) -> 0 | F74: =COUNTIFS(G$8:G$55,$B74) -> 0
B75: C8 | C75: =COUNTIF($B$8:$C$55,B75) -> 9 | D75: =C75-(COUNTIFS(C$8:C$55,B75,X$8:X$55,"")) -> 0 | E75: =COUNTIFS(X$8:X$55,$B75) -> 0 | F75: =COUNTIFS(G$8:G$55,$B75) -> 0
B76: C9 | C76: =COUNTIF($B$8:$C$55,B76) -> 14 | D76: =C76-(COUNTIFS(C$8:C$55,B76,X$8:X$55,"")) -> 0 | E76: =COUNTIFS(X$8:X$55,$B76) -> 0 | F76: =COUNTIFS(G$8:G$55,$B76) -> 0
B77: C10 | C77: =COUNTIF($B$8:$C$55,B77) -> 10 | D77: =C77-(COUNTIFS(C$8:C$55,B77,X$8:X$55,"")) -> 0 | E77: =COUNTIFS(X$8:X$55,$B77) -> 0 | F77: =COUNTIFS(G$8:G$55,$B77) -> 0
B78: C11 | C78: =COUNTIF($B$8:$C$55,B78) -> 14 | D78: =C78-(COUNTIFS(C$8:C$55,B78,X$8:X$55,"")) -> 0 | E78: =COUNTIFS(X$8:X$55,$B78) -> 0 | F78: =COUNTIFS(G$8:G$55,$B78) -> 0
B79: C12 | C79: =COUNTIF($B$8:$C$55,B79) -> 0 | D79: =C79-(COUNTIFS(C$8:C$55,B79,X$8:X$55,"")) -> 0 | E79: =COUNTIFS(X$8:X$55,$B79) -> 0 | F79: =COUNTIFS(G$8:G$55,$B79) -> 0
... B93: C24 | C93: =COUNTIF($B$8:$C$55,B93) -> 0 | D93: =C93-(COUNTIFS(C$8:C$55,B93,X$8:X$55,"")) -> 0 | E93: =COUNTIFS(X$8:X$55,$B93) -> 0 | F93: =COUNTIFS(G$8:G$55,$B93) -> 0
C94: =SUM(C68:C93) -> 47 | D94: =SUM(D68:D93) -> 0 | E94: =SUM(E68:E93) -> 0 | F94: =SUM(F68:F93) -> 0
E95: =D94-E94 -> 0 | F95: =IF(E95=F94,"OK","ERREUR") -> OK

Sheet Feuille saisie dimanche 1
A2: TYPE | B2: C8
A3: DATE | B3: 45627
A4: CHAUFFEUR | B4: =VLOOKUP(B2,'Liste chauffeur'!$B$5:$L$20,2,TRUE)&" "&VLOOKUP(B2,'Liste chauffeur'!$B$5:$L$20,3,TRUE) -> HADHURAMI Makinedine
I6: Arrêt 1 | M6: Arrêt 2 | Q6: Arrêt 3 | W6: ARRIVEE | AA6: 8
B7: Heure théorique départ | C7: Horaire | D7: Chauffeur | E7: Heure réelle départ | F7: Trajet non effectué | G7: Départ avec plus de 10 mns retard | H7: Nbre personnes montée | I7: - | J7: + | K7: Heure arrivée arrêt 1 | L7: Délai | M7: - | N7: + | O7: Heure arrivée arrêt 2 | P7: Délai | Q7: - | R7: + | S7: Heure arrivée arrêt 3 | T7: Délai | U7: Nbre personnes descente | W7: Heure arrivée finale | X7: Commentaires | Y7: Temps Aller | Z7: Nbre personnes moyenne | AA7: Capacité max | AB7: Taux Fréquentation
A8: ='Horaire dimanche1'!A8 -> VAHIBE | B8: ='Horaire dimanche1'!B8 -> 0.33333333 | C8: ='Horaire dimanche1'!C8 -> C5 | D8: =VLOOKUP(C8,'Liste chauffeur'!$B$5:$L$20,2,TRUE)&" "&VLOOKUP(C8,'Liste chauffeur'!$B$5:$L$20,3,TRUE) -> AHAMADI Bacar Raenmouddine | F8: =COUNTBLANK(E8) -> 1 | Y8: =IF(F8=1,"",W8-E8) | Z8: =H8+J8-I8 -> 0 | AA8: =IF(F8=1,0,AA$6) -> 0 | AB8: =IF(AA8=0,0,Z8/AA8) -> 0
A9: ='Horaire dimanche1'!A9 -> PASSAMAINTY | B9: ='Horaire dimanche1'!B9 -> 0.35416667 | C9: ='Horaire dimanche1'!C9 -> C5 | D9: =VLOOKUP(C9,'Liste chauffeur'!$B$5:$L$20,2,TRUE)&" "&VLOOKUP(C9,'Liste chauffeur'!$B$5:$L$20,3,TRUE) -> AHAMADI Bacar Raenmouddine | F9: =COUNTBLANK(E9) -> 1 | Y9: =IF(F9=1,"",W9-E9) | Z9: =H9+J9-I9 -> 0 | AA9: =IF(F9=1,0,AA$6) -> 0 | AB9: =IF(AA9=0,0,Z9/AA9) -> 0
A10: ='Horaire dimanche1'!A10 -> VAHIBE | B10: ='Horaire dimanche1'!B10 -> 0.375 | C10: ='Horaire dimanche1'!C10 -> C5 | D10: =VLOOKUP(C10,'Liste chauffeur'!$B$5:$L$20,2,TRUE)&" "&VLOOKUP(C10,'Liste chauffeur'!$B$5:$L$20,3,TRUE) -> AHAMADI Bacar Raenmouddine | F10: =COUNTBLANK(E10) -> 1 | Y10: =IF(F10=1,"",W10-E10) | Z10: =H10+J10-I10 -> 0 | AA10: =IF(F10=1,0,AA$6) -> 0 | AB10: =IF(AA10=0,0,Z10/AA10) -> 0
A11: ='Horaire dimanche1'!A11 -> PASSAMAINTY | B11: ='Horaire dimanche1'!B11 -> 0.39583333 | C11: ='Horaire dimanche1'!C11 -> C5 | D11: =VLOOKUP(C11,'Liste chauffeur'!$B$5:$L$20,2,TRUE)&" "&VLOOKUP(C11,'Liste chauffeur'!$B$5:$L$20,3,TRUE) -> AHAMADI Bacar Raenmouddine | F11: =COUNTBLANK(E11) -> 1 | Y11: =IF(F11=1,"",W11-E11) | Z11: =H11+J11-I11 -> 0 | AA11: =IF(F11=1,0,AA$6) -> 0 | AB11: =IF(AA11=0,0,Z11/AA11) -> 0
A12: ='Horaire dimanche1'!A12 -> VAHIBE | B12: ='Horaire dimanche1'!B12 -> 0.41666667 | C12: ='Horaire dimanche1'!C12 -> C5 | D12: =VLOOKUP(C12,'Liste chauffeur'!$B$5:$L$20,2,TRUE)&" "&VLOOKUP(C12,'Liste chauffeur'!$B$5:$L$20,3,TRUE) -> AHAMADI Bacar Raenmouddine | F12: =COUNTBLANK(E12) -> 1 | L12: =K12-E12 -> 0 | P12: =O12-K12 -> 0 | T12: =S12-O12 -> 0 | V12: =IF(H12-I12+J12-M12+N12-Q12+R12=U12,"OK",H12-I12+J12-M12+N12-Q12+R12-U12) -> OK | Y12: =IF(F12=1,"",W12-E12) | Z12: =H12+J12-I12 -> 0 | AA12: =IF(F12=1,0,AA$6) -> 0 | AB12: =IF(AA12=0,0,Z12/AA12) -> 0
A13: ='Horaire dimanche1'!A13 -> PASSAMAINTY | B13: ='Horaire dimanche1'!B13 -> 0.4375 | C13: ='Horaire dimanche1'!C13 -> C5 | D13: =VLOOKUP(C13,'Liste chauffeur'!$B$5:$L$20,2,TRUE)&" "&VLOOKUP(C13,'Liste chauffeur'!$B$5:$L$20,3,TRUE) -> AHAMADI Bacar Raenmouddine | F13: =COUNTBLANK(E13) -> 1 | L13: =K13-E13 -> 0 | P13: =O13-K13 -> 0 | T13: =S13-O13 -> 0 | Y13: =IF(F13=1,"",W13-E13) | Z13: =H13+J13-I13 -> 0 | AA13: =IF(F13=1,0,AA$6) -> 0 | AB13: =IF(AA13=0,0,Z13/AA13) -> 0
A14: ='Horaire dimanche1'!A14 -> VAHIBE | B14: ='Horaire dimanche1'!B14 -> 0.45833333 | C14: ='Horaire dimanche1'!C14 -> C5 | D14: =VLOOKUP(C14,'Liste chauffeur'!$B$5:$L$20,2,TRUE)&" "&VLOOKUP(C14,'Liste chauffeur'!$B$5:$L$20,3,TRUE) -> AHAMADI Bacar Raenmouddine | F14: =COUNTBLANK(E14) -> 1 | L14: =K14-E14 -> 0 | P14: =O14-K14 -> 0 | T14: =S14-O14 -> 0 | Y14: =IF(F14=1,"",W14-E14) | Z14: =H14+J14-I14 -> 0 | AA14: =IF(F14=1,0,AA$6) -> 0 | AB14: =IF(AA14=0,0,Z14/AA14) -> 0
A15: ='Horaire dimanche1'!A15 -> PASSAMAINTY | B15: ='Horaire dimanche1'!B15 -> 0.47916667 | C15: ='Horaire dimanche1'!C15 -> C5 | D15: =VLOOKUP(C15,'Liste chauffeur'!$B$5:$L$20,2,TRUE)&" "&VLOOKUP(C15,'Liste chauffeur'!$B$5:$L$20,3,TRUE) -> AHAMADI Bacar Raenmouddine | F15: =COUNTBLANK(E15) -> 1 | L15: =K15-E15 -> 0 | P15: =O15-K15 -> 0 | T15: =S15-O15 -> 0 | Y15: =IF(F15=1,"",W15-E15) | Z15: =H15+J15-I15 -> 0 | AA15: =IF(F15=1,0,AA$6) -> 0 | AB15: =IF(AA15=0,0,Z15/AA15) -> 0
A16: ='Horaire dimanche1'!A16 -> VAHIBE | B16: ='Horaire dimanche1'!B16 -> 0.5 | C16: ='Horaire dimanche1'!C16 -> C5 | D16: =VLOOKUP(C16,'Liste chauffeur'!$B$5:$L$20,2,TRUE)&" "&VLOOKUP(C16,'Liste chauffeur'!$B$5:$L$20,3,TRUE) -> AHAMADI Bacar Raenmouddine | F16: =COUNTBLANK(E16) -> 1 | L16: =K16-E16 -> 0 | P16: =O16-K16 -> 0 | T16: =S16-O16 -> 0 | V16: =IF(H16-I16+J16-M16+N16-Q16+R16=U16,"OK",H16-I16+J16-M16+N16-Q16+R16-U16) -> OK | Y16: =IF(F16=1,"",W16-E16) | Z16: =H16+J16-I16 -> 0 | AA16: =IF(F16=1,0,AA$6) -> 0 | AB16: =IF(AA16=0,0,Z16/AA16) -> 0
B17: ST1 | F17: =SUM(F8:F16) -> 9 | G17: =SUM(G8:G16) -> 0 | Y17: =AVERAGE(Y8:Y16) -> #DIV/0! | Z17: =SUM(Z8:Z16) -> 0 | AA17: =SUM(AA8:AA16) -> 0 | AB17: =IF(AA17=0,0,Z17/AA17) -> 0
A18: ='Horaire dimanche1'!A17 -> PASSAMAINTY | B18: ='Horaire dimanche1'!B17 -> 0.52083333 | C18: ='Horaire dimanche1'!C17 -> C5 | D18: =VLOOKUP(C18,'Liste chauffeur'!$B$5:$L$20,2,TRUE)&" "&VLOOKUP(C18,'Liste chauffeur'!$B$5:$L$20,3,TRUE) -> AHAMADI Bacar Raenmouddine | F18: =COUNTBLANK(E18) -> 1 | L18: =K18-E18 -> 0 | P18: =O18-K18 -> 0 | T18: =S18-O18 -> 0 | V18: =IF(H18-I18+J18-M18+N18-Q18+R18=U18,"OK",H18-I18+J18-M18+N18-Q18+R18-U18) -> OK | Y18: =IF(F18=1,"",W18-E18) | Z18: =H18+J18-I18 -> 0 | AA18: =IF(F18=1,0,AA$6) -> 0 | AB18: =IF(AA18=0,0,Z18/AA18) -> 0
A19: ='Horaire dimanche1'!A18 -> VAHIBE | B19: ='Horaire dimanche1'!B18 -> 0.54166667 | C19: ='Horaire dimanche1'!C18 -> C5 | D19: =VLOOKUP(C19,'Liste chauffeur'!$B$5:$L$20,2,TRUE)&" "&VLOOKUP(C19,'Liste chauffeur'!$B$5:$L$20,3,TRUE) -> AHAMADI Bacar Raenmouddine | F19: =COUNTBLANK(E19) -> 1 | Z19: =H19+J19-I19 -> 0 | AA19: =IF(F19=1,0,AA$6) -> 0 | AB19: =IF(AA19=0,0,Z19/AA19) -> 0
A20: ='Horaire dimanche1'!A19 -> PASSAMAINTY | B20: ='Horaire dimanche1'!B19 -> 0.5625 | C20: ='Horaire dimanche1'!C19 -> C5 | D20: =VLOOKUP(C20,'Liste chauffeur'!$B$5:$L$20,2,TRUE)&" "&VLOOKUP(C20,'Liste chauffeur'!$B$5:$L$20,3,TRUE) -> AHAMADI Bacar Raenmouddine | F20: =COUNTBLANK(E20) -> 1 | L20: =K20-E20 -> 0 | P20: =O20-K20 -> 0 | T20: =S20-O20 -> 0 | V20: =IF(H20-I20+J20-M20+N20-Q20+R20=U20,"OK",H20-I20+J20-M20+N20-Q20+R20-U20) -> OK | Y20: =IF(F20=1,"",W20-E20) | Z20: =H20+J20-I20 -> 0 | AA20: =IF(F20=1,0,AA$6) -> 0 | AB20: =IF(AA20=0,0,Z20/AA20) -> 0
A21: ='Horaire dimanche1'!A20 -> VAHIBE | B21: ='Horaire dimanche1'!B20 -> 0.58333333 | C21: ='Horaire dimanche1'!C20 -> C8 | D21: =VLOOKUP(C21,'Liste chauffeur'!$B$5:$L$20,2,TRUE)&" "&VLOOKUP(C21,'Liste chauffeur'!$B$5:$L$20,3,TRUE) -> HADHURAMI Makinedine | F21: =COUNTBLANK(E21) -> 1 | L21: =K21-E21 -> 0 | P21: =O21-K21 -> 0 | T21: =S21-O21 -> 0 | V21: =IF(H21-I21+J21-M21+N21-Q21+R21=U21,"OK",H21-I21+J21-M21+N21-Q21+R21-U21) -> OK | Y21: =IF(F21=1,"",W21-E21) | Z21: =H21+J21-I21 -> 0 | AA21: =IF(F21=1,0,AA$6) -> 0 | AB21: =IF(AA21=0,0,Z21/AA21) -> 0
A22: ='Horaire dimanche1'!A21 -> PASSAMAINTY | B22: ='Horaire dimanche1'!B21 -> 0.60416667 | C22: ='Horaire dimanche1'!C21 -> C8 | D22: =VLOOKUP(C22,'Liste chauffeur'!$B$5:$L$20,2,TRUE)&" "&VLOOKUP(C22,'Liste chauffeur'!$B$5:$L$20,3,TRUE) -> HADHURAMI Makinedine | F22: =COUNTBLANK(E22) -> 1 | L22: =K22-E22 -> 0 | P22: =O22-K22 -> 0 | T22: =S22-O22 -> 0 | V22: =IF(H22-I22+J22-M22+N22-Q22+R22=U22,"OK",H22-I22+J22-M22+N22-Q22+R22-U22) -> OK | Y22: =IF(F22=1,"",W22-E22) | Z22: =H22+J22-I22 -> 0 | AA22: =IF(F22=1,0,AA$6) -> 0 | AB22: =IF(AA22=0,0,Z22/AA22) -> 0
A23: ='Horaire dimanche1'!A22 -> VAHIBE | B23: ='Horaire dimanche1'!B22 -> 0.625 | C23: ='Horaire dimanche1'!C22 -> C8 | D23: =VLOOKUP(C23,'Liste chauffeur'!$B$5:$L$20,2,TRUE)&" "&VLOOKUP(C23,'Liste chauffeur'!$B$5:$L$20,3,TRUE) -> HADHURAMI Makinedine | F23: =COUNTBLANK(E23) -> 1 | L23: =K23-E23 -> 0 | P23: =O23-K23 -> 0 | T23: =S23-O23 -> 0 | V23: =IF(H23-I23+J23-M23+N23-Q23+R23=U23,"OK",H23-I23+J23-M23+N23-Q23+R23-U23) -> OK | Y23: =IF(F23=1,"",W23-E23) | Z23: =H23+J23-I23 -> 0 | AA23: =IF(F23=1,0,AA$6) -> 0 | AB23: =IF(AA23=0,0,Z23/AA23) -> 0
A24: ='Horaire dimanche1'!A23 -> PASSAMAINTY | B24: ='Horaire dimanche1'!B23 -> 0.64583333 | C24: ='Horaire dimanche1'!C23 -> C8 | D24: =VLOOKUP(C24,'Liste chauffeur'!$B$5:$L$20,2,TRUE)&" "&VLOOKUP(C24,'Liste chauffeur'!$B$5:$L$20,3,TRUE) -> HADHURAMI Makinedine | F24: =COUNTBLANK(E24) -> 1 | L24: =K24-E24 -> 0 | P24: =O24-K24 -> 0 | T24: =S24-O24 -> 0 | V24: =IF(H24-I24+J24-M24+N24-Q24+R24=U24,"OK",H24-I24+J24-M24+N24-Q24+R24-U24) -> OK | Y24: =IF(F24=1,"",W24-E24) | Z24: =H24+J24-I24 -> 0 | AA24: =IF(F24=1,0,AA$6) -> 0 | AB24: =IF(AA24=0,0,Z24/AA24) -> 0
A25: ='Horaire dimanche1'!A24 -> VAHIBE | B25: ='Horaire dimanche1'!B24 -> 0.66666667 | C25: ='Horaire dimanche1'!C24 -> C8 | D25: =VLOOKUP(C25,'Liste chauffeur'!$B$5:$L$20,2,TRUE)&" "&VLOOKUP(C25,'Liste chauffeur'!$B$5:$L$20,3,TRUE) -> HADHURAMI Makinedine | F25: =COUNTBLANK(E25) -> 1 | L25: =K25-E25 -> 0 | P25: =O25-K25 -> 0 | T25: =S25-O25 -> 0 | V25: =IF(H25-I25+J25-M25+N25-Q25+R25=U25,"OK",H25-I25+J25-M25+N25-Q25+R25-U25) -> OK | Y25: =IF(F25=1,"",W25-E25) | Z25: =H25+J25-I25 -> 0 | AA25: =IF(F25=1,0,AA$6) -> 0 | AB25: =IF(AA25=0,0,Z25/AA25) -> 0
A26: ='Horaire dimanche1'!A25 -> PASSAMAINTY | B26: ='Horaire dimanche1'!B25 -> 0.6875 | C26: ='Horaire dimanche1'!C25 -> C8 | D26: =VLOOKUP(C26,'Liste chauffeur'!$B$5:$L$20,2,TRUE)&" "&VLOOKUP(C26,'Liste chauffeur'!$B$5:$L$20,3,TRUE) -> HADHURAMI Makinedine | F26: =COUNTBLANK(E26) -> 1 | Z26: =H26+J26-I26 -> 0 | AA26: =IF(F26=1,0,AA$6) -> 0 | AB26: =IF(AA26=0,0,Z26/AA26) -> 0
A27: ='Horaire dimanche1'!A26 -> VAHIBE | B27: ='Horaire dimanche1'!B26 -> 0.70833333 | C27: ='Horaire dimanche1'!C26 -> C8 | D27: =VLOOKUP(C27,'Liste chauffeur'!$B$5:$L$20,2,TRUE)&" "&VLOOKUP(C27,'Liste chauffeur'!$B$5:$L$20,3,TRUE) -> HADHURAMI Makinedine | F27: =COUNTBLANK(E27) -> 1 | L27: =K27-E27 -> 0 | P27: =O27-K27 -> 0 | T27: =S27-O27 -> 0 | V27: =IF(H27-I27+J27-M27+N27-Q27+R27=U27,"OK",H27-I27+J27-M27+N27-Q27+R27-U27) -> OK | Y27: =IF(F27=1,"",W27-E27) | Z27: =H27+J27-I27 -> 0 | AA27: =IF(F27=1,0,AA$6) -> 0 | AB27: =IF(AA27=0,0,Z27/AA27) -> 0
A28: ='Horaire dimanche1'!A27 -> PASSAMAINTY | B28: ='Horaire dimanche1'!B27 -> 0.72222222 | C28: ='Horaire dimanche1'!C27 -> C8 | D28: =VLOOKUP(C28,'Liste chauffeur'!$B$5:$L$20,2,TRUE)&" "&VLOOKUP(C28,'Liste chauffeur'!$B$5:$L$20,3,TRUE) -> HADHURAMI Makinedine | F28: =COUNTBLANK(E28) -> 1 | L28: =K28-E28 -> 0 | P28: =O28-K28 -> 0 | T28: =S28-O28 -> 0 | V28: =IF(H28-I28+J28-M28+N28-Q28+R28=U28,"OK",H28-I28+J28-M28+N28-Q28+R28-U28) -> OK | Y28: =IF(F28=1,"",W28-E28) | Z28: =H28+J28-I28 -> 0 | AA28: =IF(F28=1,0,AA$6) -> 0 | AB28: =IF(AA28=0,0,Z28/AA28) -> 0
A29: ='Horaire dimanche1'!A28 -> VAHIBE | B29: ='Horaire dimanche1'!B28 -> 0.74305556 | C29: ='Horaire dimanche1'!C28 -> C8 | D29: =VLOOKUP(C29,'Liste chauffeur'!$B$5:$L$20,2,TRUE)&" "&VLOOKUP(C29,'Liste chauffeur'!$B$5:$L$20,3,TRUE) -> HADHURAMI Makinedine | F29: =COUNTBLANK(E29) -> 1 | L29: =K29-E29 -> 0 | P29: =O29-K29 -> 0 | T29: =S29-O29 -> 0 | V29: =IF(H29-I29+J29-M29+N29-Q29+R29=U29,"OK",H29-I29+J29-M29+N29-Q29+R29-U29) -> OK | Y29: =IF(F29=1,"",W29-E29) | Z29: =H29+J29-I29 -> 0 | AA29: =IF(F29=1,0,AA$6) -> 0 | AB29: =IF(AA29=0,0,Z29/AA29) -> 0
A30: ='Horaire dimanche1'!A29 -> PASSAMAINTY | B30: ='Horaire dimanche1'!B29 -> 0.75694444 | C30: ='Horaire dimanche1'!C29 -> C8 | D30: =VLOOKUP(C30,'Liste chauffeur'!$B$5:$L$20,2,TRUE)&" "&VLOOKUP(C30,'Liste chauffeur'!$B$5:$L$20,3,TRUE) -> HADHURAMI Makinedine | F30: =COUNTBLANK(E30) -> 1 | L30: =K30-E30 -> 0 | P30: =O30-K30 -> 0 | T30: =S30-O30 -> 0 | V30: =IF(H30-I30+J30-M30+N30-Q30+R30=U30,"OK",H30-I30+J30-M30+N30-Q30+R30-U30) -> OK | Y30: =IF(F30=1,"",W30-E30) | Z30: =H30+J30-I30 -> 0 | AA30: =IF(F30=1,0,AA$6) -> 0 | AB30: =IF(AA30=0,0,Z30/AA30) -> 0
B31: ST2 | F31: =SUM(F18:F30) -> 13 | G31: =SUM(G18:G30) -> 0 | Y31: =AVERAGE(Y18:Y30) -> #DIV/0! | Z31: =SUM(Z18:Z30) -> 0 | AA31: =SUM(AA18:AA30) -> 0 | AB31: =IF(AA31=0,0,Z31/AA31) -> 0
B32: ST3 | F32: =F17+F31 -> 22 | G32: =G17+G31 -> 0 | Y32: =AVERAGE(Y8:Y16,Y18:Y30) -> #DIV/0! | Z32: =Z17+Z31 -> 0 | AA32: =AA17+AA31 -> 0 | AB32: =IF(AA32=0,0,Z32/AA32) -> 0
A33: REMPLACEMENT | C33: C | O33: =M33-#REF! -> #REF! | P33: =#REF!+#REF!-#REF! -> #REF!
A34: REMPLACEMENT | C34: C
A35: REMPLACEMENT | C35: C
A36: REMPLACEMENT | C36: C
A37: REMPLACEMENT | C37: C
A38: REMPLACEMENT | C38: C | O38: =M38-#REF! -> #REF! | P38: =#REF!+#REF!-#REF! -> #REF!
E40: Signature Chauffeur | I40: Signature Coordinateur
B43: Statistiques | C43: nbre de trajets planifiés | D43: Nbre trajets non effectués | E43: Nbre trajets effectués non planifiés | F43: Nbre trajets dont départ > 10 minutes en retard
B44: C1 | C44: =COUNTIF($B$8:$C$30,B44) -> 0 | D44: =C44-(COUNTIFS(C$8:C$30,B44,M$8:M$30,"")) -> 0 | E44: =COUNTIFS(M$8:M$30,$B44) -> 0 | F44: =COUNTIFS(G$8:G$30,$B44) -> 0
B45: C2 | C45: =COUNTIF($B$8:$C$30,B45) -> 0 | D45: =C45-(COUNTIFS(C$8:C$30,B45,M$8:M$30,"")) -> 0 | E45: =COUNTIFS(M$8:M$30,$B45) -> 0 | F45: =COUNTIFS(G$8:G$30,$B45) -> 0
B46: C3 | C46: =COUNTIF($B$8:$C$30,B46) -> 0 | D46: =C46-(COUNTIFS(C$8:C$30,B46,M$8:M$30,"")) -> 0 | E46: =COUNTIFS(M$8:M$30,$B46) -> 0 | F46: =COUNTIFS(G$8:G$30,$B46) -> 0
B47: C4 | C47: =COUNTIF($B$8:$C$30,B47) -> 0 | D47: =C47-(COUNTIFS(C$8:C$30,B47,M$8:M$30,"")) -> 0 | E47: =COUNTIFS(M$8:M$30,$B47) -> 0 | F47: =COUNTIFS(G$8:G$30,$B47) -> 0
B48: C5 | C48: =COUNTIF($B$8:$C$30,B48) -> 12 | D48: =C48-(COUNTIFS(C$8:C$30,B48,M$8:M$30,"")) -> 0 | E48: =COUNTIFS(M$8:M$30,$B48) -> 0 | F48: =COUNTIFS(G$8:G$30,$B48) -> 0
B49: C6 | C49: =COUNTIF($B$8:$C$30,B49) -> 0 | D49: =C49-(COUNTIFS(C$8:C$30,B49,M$8:M$30,"")) -> 0 | E49: =COUNTIFS(M$8:M$30,$B49) -> 0 | F49: =COUNTIFS(G$8:G$30,$B49) -> 0
B50: C7 | C50: =COUNTIF($B$8:$C$30,B50) -> 0 | D50: =C50-(COUNTIFS(C$8:C$30,B50,M$8:M$30,"")) -> 0 | E50: =COUNTIFS(M$8:M$30,$B50) -> 0 | F50: =COUNTIFS(G$8:G$30,$B50) -> 0
B51: C8 | C51: =COUNTIF($B$8:$C$30,B51) -> 10 | D51: =C51-(COUNTIFS(C$8:C$30,B51,M$8:M$30,"")) -> 0 | E51: =COUNTIFS(M$8:M$30,$B51) -> 0 | F51: =COUNTIFS(G$8:G$30,$B51) -> 0
B52: C9 | C52: =COUNTIF($B$8:$C$30,B52) -> 0 | D52: =C52-(COUNTIFS(C$8:C$30,B52,M$8:M$30,"")) -> 0 | E52: =COUNTIFS(M$8:M$30,$B52) -> 0 | F52: =COUNTIFS(G$8:G$30,$B52) -> 0
B53: C10 | C53: =COUNTIF($B$8:$C$30,B53) -> 0 | D53: =C53-(COUNTIFS(C$8:C$30,B53,M$8:M$30,"")) -> 0 | E53: =COUNTIFS(M$8:M$30,$B53) -> 0 | F53: =COUNTIFS(G$8:G$30,$B53) -> 0
B54: C11 | C54: =COUNTIF($B$8:$C$30,B54) -> 0 | D54: =C54-(COUNTIFS(C$8:C$30,B54,M$8:M$30,"")) -> 0 | E54: =COUNTIFS(M$8:M$30,$B54) -> 0 | F54: =COUNTIFS(G$8:G$30,$B54) -> 0
B55: C12 | C55: =COUNTIF($B$8:$C$30,B55) -> 0 | D55: =C55-(COUNTIFS(C$8:C$30,B55,M$8:M$30,"")) -> 0 | E55: =COUNTIFS(M$8:M$30,$B55) -> 0 | F55: =COUNTIFS(G$8:G$30,$B55) -> 0
... B70: C25 | C70: =COUNTIF($B$8:$C$30,B70) -> 0 | D70: =C70-(COUNTIFS(C$8:C$30,B70,M$8:M$30,"")) -> 0 | E70: =COUNTIFS(M$8:M$30,$B70) -> 0 | F70: =COUNTIFS(G$8:G$30,$B70) -> 0
C71: =SUM(C44:C70) -> 22 | D71: =SUM(D44:D70) -> 0 | E71: =SUM(E44:E70) -> 0 | F71: =SUM(F44:F70) -> 0
E72: =D71-E71 -> 0 | F72: =IF(E72=F71,"OK","ERREUR") -> OK

Sheet Feuille saisie dimanche 2
A2: TYPE | B2: C14
A3: DATE | B3: 45627
A4: CHAUFFEUR | B4: =VLOOKUP(B2,'Liste chauffeur'!$B$5:$L$20,2,TRUE)&" "&VLOOKUP(B2,'Liste chauffeur'!$B$5:$L$20,3,TRUE) -> KAMARDINE Mansour
I6: Arrêt 1 | M6: Arrêt 2 | Q6: Arrêt 3 | W6: ARRIVEE | AA6: 8
B7: Heure théorique départ | C7: Horaire | D7: Chauffeur | E7: Heure réelle départ | F7: Trajet non effectué | G7: Départ avec plus de 10 mns retard | H7: Nbre personnes montée | I7: - | J7: + | K7: Heure arrivée arrêt 1 | L7: Délai | M7: - | N7: + | O7: Heure arrivée arrêt 2 | P7: Délai | Q7: - | R7: + | S7: Heure arrivée arrêt 3 | T7: Délai | U7: Nbre personnes descente | W7: Heure arrivée finale | X7: Commentaires | Y7: Temps Aller | Z7: Nbre personnes moyenne | AA7: Capacité max | AB7: Taux Fréquentation
A8: ='Horaire dimanche2'!A8 -> VAHIBE | B8: ='Horaire dimanche1'!B8 -> 0.33333333 | C8: ='Horaire dimanche2'!C8 -> C10 | D8: =VLOOKUP(C8,'Liste chauffeur'!$B$5:$L$20,2,TRUE)&" "&VLOOKUP(C8,'Liste chauffeur'!$B$5:$L$20,3,TRUE) -> ISSIHAKA M'Changama | F8: =COUNTBLANK(E8) -> 1 | Y8: =IF(F8=1,"",W8-E8) | Z8: =H8+J8-I8 -> 0 | AA8: =IF(F8=1,0,AA$6) -> 0 | AB8: =IF(AA8=0,0,Z8/AA8) -> 0
A9: ='Horaire dimanche2'!A9 -> PASSAMAINTY | B9: ='Horaire dimanche1'!B9 -> 0.35416667 | C9: ='Horaire dimanche2'!C9 -> C10 | D9: =VLOOKUP(C9,'Liste chauffeur'!$B$5:$L$20,2,TRUE)&" "&VLOOKUP(C9,'Liste chauffeur'!$B$5:$L$20,3,TRUE) -> ISSIHAKA M'Changama | F9: =COUNTBLANK(E9) -> 1 | Y9: =IF(F9=1,"",W9-E9) | Z9: =H9+J9-I9 -> 0 | AA9: =IF(F9=1,0,AA$6) -> 0 | AB9: =IF(AA9=0,0,Z9/AA9) -> 0
A10: ='Horaire dimanche2'!A10 -> VAHIBE | B10: ='Horaire dimanche1'!B10 -> 0.375 | C10: ='Horaire dimanche2'!C10 -> C10 | D10: =VLOOKUP(C10,'Liste chauffeur'!$B$5:$L$20,2,TRUE)&" "&VLOOKUP(C10,'Liste chauffeur'!$B$5:$L$20,3,TRUE) -> ISSIHAKA M'Changama | F10: =COUNTBLANK(E10) -> 1 | Y10: =IF(F10=1,"",W10-E10) | Z10: =H10+J10-I10 -> 0 | AA10: =IF(F10=1,0,AA$6) -> 0 | AB10: =IF(AA10=0,0,Z10/AA10) -> 0
A11: ='Horaire dimanche2'!A11 -> PASSAMAINTY | B11: ='Horaire dimanche1'!B11 -> 0.39583333 | C11: ='Horaire dimanche2'!C11 -> C10 | D11: =VLOOKUP(C11,'Liste chauffeur'!$B$5:$L$20,2,TRUE)&" "&VLOOKUP(C11,'Liste chauffeur'!$B$5:$L$20,3,TRUE) -> ISSIHAKA M'Changama | F11: =COUNTBLANK(E11) -> 1 | Y11: =IF(F11=1,"",W11-E11) | Z11: =H11+J11-I11 -> 0 | AA11: =IF(F11=1,0,AA$6) -> 0 | AB11: =IF(AA11=0,0,Z11/AA11) -> 0
A12: ='Horaire dimanche2'!A12 -> VAHIBE | B12: ='Horaire dimanche1'!B12 -> 0.41666667 | C12: ='Horaire dimanche2'!C12 -> C10 | D12: =VLOOKUP(C12,'Liste chauffeur'!$B$5:$L$20,2,TRUE)&" "&VLOOKUP(C12,'Liste chauffeur'!$B$5:$L$20,3,TRUE) -> ISSIHAKA M'Changama | F12: =COUNTBLANK(E12) -> 1 | L12: =K12-E12 -> 0 | P12: =O12-K12 -> 0 | T12: =S12-O12 -> 0 | V12: =IF(H12-I12+J12-M12+N12-Q12+R12=U12,"OK",H12-I12+J12-M12+N12-Q12+R12-U12) -> OK | Y12: =IF(F12=1,"",W12-E12) | Z12: =H12+J12-I12 -> 0 | AA12: =IF(F12=1,0,AA$6) -> 0 | AB12: =IF(AA12=0,0,Z12/AA12) -> 0
A13: ='Horaire dimanche2'!A13 -> PASSAMAINTY | B13: ='Horaire dimanche1'!B13 -> 0.4375 | C13: ='Horaire dimanche2'!C13 -> C10 | D13: =VLOOKUP(C13,'Liste chauffeur'!$B$5:$L$20,2,TRUE)&" "&VLOOKUP(C13,'Liste chauffeur'!$B$5:$L$20,3,TRUE) -> ISSIHAKA M'Changama | F13: =COUNTBLANK(E13) -> 1 | L13: =K13-E13 -> 0 | P13: =O13-K13 -> 0 | T13: =S13-O13 -> 0 | Y13: =IF(F13=1,"",W13-E13) | Z13: =H13+J13-I13 -> 0 | AA13: =IF(F13=1,0,AA$6) -> 0 | AB13: =IF(AA13=0,0,Z13/AA13) -> 0
A14: ='Horaire dimanche2'!A14 -> VAHIBE | B14: ='Horaire dimanche1'!B14 -> 0.45833333 | C14: ='Horaire dimanche2'!C14 -> C10 | D14: =VLOOKUP(C14,'Liste chauffeur'!$B$5:$L$20,2,TRUE)&" "&VLOOKUP(C14,'Liste chauffeur'!$B$5:$L$20,3,TRUE) -> ISSIHAKA M'Changama | F14: =COUNTBLANK(E14) -> 1 | L14: =K14-E14 -> 0 | P14: =O14-K14 -> 0 | T14: =S14-O14 -> 0 | Y14: =IF(F14=1,"",W14-E14) | Z14: =H14+J14-I14 -> 0 | AA14: =IF(F14=1,0,AA$6) -> 0 | AB14: =IF(AA14=0,0,Z14/AA14) -> 0
A15: ='Horaire dimanche2'!A15 -> PASSAMAINTY | B15: ='Horaire dimanche1'!B15 -> 0.47916667 | C15: ='Horaire dimanche2'!C15 -> C10 | D15: =VLOOKUP(C15,'Liste chauffeur'!$B$5:$L$20,2,TRUE)&" "&VLOOKUP(C15,'Liste chauffeur'!$B$5:$L$20,3,TRUE) -> ISSIHAKA M'Changama | F15: =COUNTBLANK(E15) -> 1 | L15: =K15-E15 -> 0 | P15: =O15-K15 -> 0 | T15: =S15-O15 -> 0 | Y15: =IF(F15=1,"",W15-E15) | Z15: =H15+J15-I15 -> 0 | AA15: =IF(F15=1,0,AA$6) -> 0 | AB15: =IF(AA15=0,0,Z15/AA15) -> 0
A16: ='Horaire dimanche2'!A16 -> VAHIBE | B16: ='Horaire dimanche1'!B16 -> 0.5 | C16: ='Horaire dimanche2'!C16 -> C10 | D16: =VLOOKUP(C16,'Liste chauffeur'!$B$5:$L$20,2,TRUE)&" "&VLOOKUP(C16,'Liste chauffeur'!$B$5:$L$20,3,TRUE) -> ISSIHAKA M'Changama | F16: =COUNTBLANK(E16) -> 1 | L16: =K16-E16 -> 0 | P16: =O16-K16 -> 0 | T16: =S16-O16 -> 0 | V16: =IF(H16-I16+J16-M16+N16-Q16+R16=U16,"OK",H16-I16+J16-M16+N16-Q16+R16-U16) -> OK | Y16: =IF(F16=1,"",W16-E16) | Z16: =H16+J16-I16 -> 0 | AA16: =IF(F16=1,0,AA$6) -> 0 | AB16: =IF(AA16=0,0,Z16/AA16) -> 0
B17: ST1 | F17: =SUM(F8:F16) -> 9 | G17: =SUM(G8:G16) -> 0 | Y17: =AVERAGE(Y8:Y16) -> #DIV/0! | Z17: =SUM(Z8:Z16) -> 0 | AA17: =SUM(AA8:AA16) -> 0 | AB17: =IF(AA17=0,0,Z17/AA17) -> 0
A18: ='Horaire dimanche2'!A17 -> PASSAMAINTY | B18: ='Horaire dimanche1'!B17 -> 0.52083333 | C18: ='Horaire dimanche2'!C17 -> C10 | D18: =VLOOKUP(C18,'Liste chauffeur'!$B$5:$L$20,2,TRUE)&" "&VLOOKUP(C18,'Liste chauffeur'!$B$5:$L$20,3,TRUE) -> ISSIHAKA M'Changama | F18: =COUNTBLANK(E18) -> 1 | L18: =K18-E18 -> 0 | P18: =O18-K18 -> 0 | T18: =S18-O18 -> 0 | V18: =IF(H18-I18+J18-M18+N18-Q18+R18=U18,"OK",H18-I18+J18-M18+N18-Q18+R18-U18) -> OK | Y18: =IF(F18=1,"",W18-E18) | Z18: =H18+J18-I18 -> 0 | AA18: =IF(F18=1,0,AA$6) -> 0 | AB18: =IF(AA18=0,0,Z18/AA18) -> 0
A19: ='Horaire dimanche2'!A18 -> VAHIBE | B19: ='Horaire dimanche1'!B18 -> 0.54166667 | C19: ='Horaire dimanche2'!C18 -> C10 | D19: =VLOOKUP(C19,'Liste chauffeur'!$B$5:$L$20,2,TRUE)&" "&VLOOKUP(C19,'Liste chauffeur'!$B$5:$L$20,3,TRUE) -> ISSIHAKA M'Changama | F19: =COUNTBLANK(E19) -> 1 | Y19: =IF(F19=1,"",W19-E19) | Z19: =H19+J19-I19 -> 0 | AA19: =IF(F19=1,0,AA$6) -> 0 | AB19: =IF(AA19=0,0,Z19/AA19) -> 0
A20: ='Horaire dimanche2'!A19 -> PASSAMAINTY | B20: ='Horaire dimanche1'!B19 -> 0.5625 | C20: ='Horaire dimanche2'!C19 -> C10 | D20: =VLOOKUP(C20,'Liste chauffeur'!$B$5:$L$20,2,TRUE)&" "&VLOOKUP(C20,'Liste chauffeur'!$B$5:$L$20,3,TRUE) -> ISSIHAKA M'Changama | F20: =COUNTBLANK(E20) -> 1 | L20: =K20-E20 -> 0 | P20: =O20-K20 -> 0 | T20: =S20-O20 -> 0 | V20: =IF(H20-I20+J20-M20+N20-Q20+R20=U20,"OK",H20-I20+J20-M20+N20-Q20+R20-U20) -> OK | Y20: =IF(F20=1,"",W20-E20) | Z20: =H20+J20-I20 -> 0 | AA20: =IF(F20=1,0,AA$6) -> 0 | AB20: =IF(AA20=0,0,Z20/AA20) -> 0
A21: ='Horaire dimanche2'!A20 -> VAHIBE | B21: ='Horaire dimanche1'!B20 -> 0.58333333 | C21: ='Horaire dimanche2'!C20 -> C15 | D21: =VLOOKUP(C21,'Liste chauffeur'!$B$5:$L$20,2,TRUE)&" "&VLOOKUP(C21,'Liste chauffeur'!$B$5:$L$20,3,TRUE) -> HAMADA Babou | F21: =COUNTBLANK(E21) -> 1 | L21: =K21-E21 -> 0 | P21: =O21-K21 -> 0 | T21: =S21-O21 -> 0 | V21: =IF(H21-I21+J21-M21+N21-Q21+R21=U21,"OK",H21-I21+J21-M21+N21-Q21+R21-U21) -> OK | Y21: =IF(F21=1,"",W21-E21) | Z21: =H21+J21-I21 -> 0 | AA21: =IF(F21=1,0,AA$6) -> 0 | AB21: =IF(AA21=0,0,Z21/AA21) -> 0
A22: ='Horaire dimanche2'!A21 -> PASSAMAINTY | B22: ='Horaire dimanche1'!B21 -> 0.60416667 | C22: ='Horaire dimanche2'!C21 -> C15 | D22: =VLOOKUP(C22,'Liste chauffeur'!$B$5:$L$20,2,TRUE)&" "&VLOOKUP(C22,'Liste chauffeur'!$B$5:$L$20,3,TRUE) -> HAMADA Babou | F22: =COUNTBLANK(E22) -> 1 | L22: =K22-E22 -> 0 | P22: =O22-K22 -> 0 | T22: =S22-O22 -> 0 | V22: =IF(H22-I22+J22-M22+N22-Q22+R22=U22,"OK",H22-I22+J22-M22+N22-Q22+R22-U22) -> OK | Y22: =IF(F22=1,"",W22-E22) | Z22: =H22+J22-I22 -> 0 | AA22: =IF(F22=1,0,AA$6) -> 0 | AB22: =IF(AA22=0,0,Z22/AA22) -> 0
A23: ='Horaire dimanche2'!A22 -> VAHIBE | B23: ='Horaire dimanche1'!B22 -> 0.625 | C23: ='Horaire dimanche2'!C22 -> C15 | D23: =VLOOKUP(C23,'Liste chauffeur'!$B$5:$L$20,2,TRUE)&" "&VLOOKUP(C23,'Liste chauffeur'!$B$5:$L$20,3,TRUE) -> HAMADA Babou | F23: =COUNTBLANK(E23) -> 1 | L23: =K23-E23 -> 0 | P23: =O23-K23 -> 0 | T23: =S23-O23 -> 0 | V23: =IF(H23-I23+J23-M23+N23-Q23+R23=U23,"OK",H23-I23+J23-M23+N23-Q23+R23-U23) -> OK | Y23: =IF(F23=1,"",W23-E23) | Z23: =H23+J23-I23 -> 0 | AA23: =IF(F23=1,0,AA$6) -> 0 | AB23: =IF(AA23=0,0,Z23/AA23) -> 0
A24: ='Horaire dimanche2'!A23 -> PASSAMAINTY | B24: ='Horaire dimanche1'!B23 -> 0.64583333 | C24: ='Horaire dimanche2'!C23 -> C15 | D24: =VLOOKUP(C24,'Liste chauffeur'!$B$5:$L$20,2,TRUE)&" "&VLOOKUP(C24,'Liste chauffeur'!$B$5:$L$20,3,TRUE) -> HAMADA Babou | F24: =COUNTBLANK(E24) -> 1 | L24: =K24-E24 -> 0 | P24: =O24-K24 -> 0 | T24: =S24-O24 -> 0 | V24: =IF(H24-I24+J24-M24+N24-Q24+R24=U24,"OK",H24-I24+J24-M24+N24-Q24+R24-U24) -> OK | Y24: =IF(F24=1,"",W24-E24) | Z24: =H24+J24-I24 -> 0 | AA24: =IF(F24=1,0,AA$6) -> 0 | AB24: =IF(AA24=0,0,Z24/AA24) -> 0
A25: ='Horaire dimanche2'!A24 -> VAHIBE | B25: ='Horaire dimanche1'!B24 -> 0.66666667 | C25: ='Horaire dimanche2'!C24 -> C15 | D25: =VLOOKUP(C25,'Liste chauffeur'!$B$5:$L$20,2,TRUE)&" "&VLOOKUP(C25,'Liste chauffeur'!$B$5:$L$20,3,TRUE) -> HAMADA Babou | F25: =COUNTBLANK(E25) -> 1 | L25: =K25-E25 -> 0 | P25: =O25-K25 -> 0 | T25: =S25-O25 -> 0 | V25: =IF(H25-I25+J25-M25+N25-Q25+R25=U25,"OK",H25-I25+J25-M25+N25-Q25+R25-U25) -> OK | Y25: =IF(F25=1,"",W25-E25) | Z25: =H25+J25-I25 -> 0 | AA25: =IF(F25=1,0,AA$6) -> 0 | AB25: =IF(AA25=0,0,Z25/AA25) -> 0
A26: ='Horaire dimanche2'!A25 -> PASSAMAINTY | B26: ='Horaire dimanche1'!B25 -> 0.6875 | C26: ='Horaire dimanche2'!C25 -> C15 | D26: =VLOOKUP(C26,'Liste chauffeur'!$B$5:$L$20,2,TRUE)&" "&VLOOKUP(C26,'Liste chauffeur'!$B$5:$L$20,3,TRUE) -> HAMADA Babou | F26: =COUNTBLANK(E26) -> 1 | Y26: =IF(F26=1,"",W26-E26) | Z26: =H26+J26-I26 -> 0 | AA26: =IF(F26=1,0,AA$6) -> 0 | AB26: =IF(AA26=0,0,Z26/AA26) -> 0
A27: ='Horaire dimanche2'!A26 -> VAHIBE | B27: ='Horaire dimanche1'!B26 -> 0.70833333 | C27: ='Horaire dimanche2'!C26 -> C15 | D27: =VLOOKUP(C27,'Liste chauffeur'!$B$5:$L$20,2,TRUE)&" "&VLOOKUP(C27,'Liste chauffeur'!$B$5:$L$20,3,TRUE) -> HAMADA Babou | F27: =COUNTBLANK(E27) -> 1 | L27: =K27-E27 -> 0 | P27: =O27-K27 -> 0 | T27: =S27-O27 -> 0 | V27: =IF(H27-I27+J27-M27+N27-Q27+R27=U27,"OK",H27-I27+J27-M27+N27-Q27+R27-U27) -> OK | Y27: =IF(F27=1,"",W27-E27) | Z27: =H27+J27-I27 -> 0 | AA27: =IF(F27=1,0,AA$6) -> 0 | AB27: =IF(AA27=0,0,Z27/AA27) -> 0
A28: ='Horaire dimanche2'!A27 -> PASSAMAINTY | B28: ='Horaire dimanche1'!B27 -> 0.72222222 | C28: ='Horaire dimanche2'!C27 -> C15 | D28: =VLOOKUP(C28,'Liste chauffeur'!$B$5:$L$20,2,TRUE)&" "&VLOOKUP(C28,'Liste chauffeur'!$B$5:$L$20,3,TRUE) -> HAMADA Babou | F28: =COUNTBLANK(E28) -> 1 | L28: =K28-E28 -> 0 | P28: =O28-K28 -> 0 | T28: =S28-O28 -> 0 | V28: =IF(H28-I28+J28-M28+N28-Q28+R28=U28,"OK",H28-I28+J28-M28+N28-Q28+R28-U28) -> OK | Y28: =IF(F28=1,"",W28-E28) | Z28: =H28+J28-I28 -> 0 | AA28: =IF(F28=1,0,AA$6) -> 0 | AB28: =IF(AA28=0,0,Z28/AA28) -> 0
A29: ='Horaire dimanche2'!A28 -> VAHIBE | B29: ='Horaire dimanche1'!B28 -> 0.74305556 | C29: ='Horaire dimanche2'!C28 -> C15 | D29: =VLOOKUP(C29,'Liste chauffeur'!$B$5:$L$20,2,TRUE)&" "&VLOOKUP(C29,'Liste chauffeur'!$B$5:$L$20,3,TRUE) -> HAMADA Babou | F29: =COUNTBLANK(E29) -> 1 | L29: =K29-E29 -> 0 | P29: =O29-K29 -> 0 | T29: =S29-O29 -> 0 | V29: =IF(H29-I29+J29-M29+N29-Q29+R29=U29,"OK",H29-I29+J29-M29+N29-Q29+R29-U29) -> OK | Y29: =IF(F29=1,"",W29-E29) | Z29: =H29+J29-I29 -> 0 | AA29: =IF(F29=1,0,AA$6) -> 0 | AB29: =IF(AA29=0,0,Z29/AA29) -> 0
A30: ='Horaire dimanche2'!A29 -> PASSAMAINTY | B30: ='Horaire dimanche1'!B29 -> 0.75694444 | C30: ='Horaire dimanche2'!C29 -> C15 | D30: =VLOOKUP(C30,'Liste chauffeur'!$B$5:$L$20,2,TRUE)&" "&VLOOKUP(C30,'Liste chauffeur'!$B$5:$L$20,3,TRUE) -> HAMADA Babou | F30: =COUNTBLANK(E30) -> 1 | L30: =K30-E30 -> 0 | P30: =O30-K30 -> 0 | T30: =S30-O30 -> 0 | V30: =IF(H30-I30+J30-M30+N30-Q30+R30=U30,"OK",H30-I30+J30-M30+N30-Q30+R30-U30) -> OK | Y30: =IF(F30=1,"",W30-E30) | Z30: =H30+J30-I30 -> 0 | AA30: =IF(F30=1,0,AA$6) -> 0 | AB30: =IF(AA30=0,0,Z30/AA30) -> 0
B31: ST2 | F31: =SUM(F18:F30) -> 13 | G31: =SUM(G18:G30) -> 0 | Y31: =AVERAGE(Y18:Y30) -> #DIV/0! | Z31: =SUM(Z18:Z30) -> 0 | AA31: =SUM(AA18:AA30) -> 0 | AB31: =IF(AA31=0,0,Z31/AA31) -> 0
B32: ST3 | F32: =F17+F31 -> 22 | G32: =G17+G31 -> 0 | Y32: =AVERAGE(Y8:Y16,Y18:Y30) -> #DIV/0! | Z32: =Z17+Z31 -> 0 | AA32: =AA17+AA31 -> 0 | AB32: =IF(AA32=0,0,Z32/AA32) -> 0
A33: REMPLACEMENT | C33: C | O33: =M33-#REF! -> #REF! | P33: =#REF!+#REF!-#REF! -> #REF!
A34: REMPLACEMENT | C34: C
A35: REMPLACEMENT | C35: C
A36: REMPLACEMENT | C36: C
A37: REMPLACEMENT | C37: C | O37: =M37-#REF! -> #REF! | P37: =#REF!+#REF!-#REF! -> #REF!
E39: Signature Chauffeur | I39: Signature Coordinateur
B42: Statistiques | C42: nbre de trajets planifiés | D42: Nbre trajets non effectués | E42: Nbre trajets effectués non planifiés | F42: Nbre trajets dont départ > 10 minutes en retard
B43: C1 | C43: =COUNTIF($B$8:$C$30,B43) -> 0 | D43: =C43-(COUNTIFS(C$8:C$30,B43,M$8:M$30,"")) -> 0 | E43: =COUNTIFS(M$8:M$30,$B43) -> 0 | F43: =COUNTIFS(G$8:G$30,$B43) -> 0
B44: C2 | C44: =COUNTIF($B$8:$C$30,B44) -> 0 | D44: =C44-(COUNTIFS(C$8:C$30,B44,M$8:M$30,"")) -> 0 | E44: =COUNTIFS(M$8:M$30,$B44) -> 0 | F44: =COUNTIFS(G$8:G$30,$B44) -> 0
B45: C3 | C45: =COUNTIF($B$8:$C$30,B45) -> 0 | D45: =C45-(COUNTIFS(C$8:C$30,B45,M$8:M$30,"")) -> 0 | E45: =COUNTIFS(M$8:M$30,$B45) -> 0 | F45: =COUNTIFS(G$8:G$30,$B45) -> 0
B46: C4 | C46: =COUNTIF($B$8:$C$30,B46) -> 0 | D46: =C46-(COUNTIFS(C$8:C$30,B46,M$8:M$30,"")) -> 0 | E46: =COUNTIFS(M$8:M$30,$B46) -> 0 | F46: =COUNTIFS(G$8:G$30,$B46) -> 0
B47: C5 | C47: =COUNTIF($B$8:$C$30,B47) -> 0 | D47: =C47-(COUNTIFS(C$8:C$30,B47,M$8:M$30,"")) -> 0 | E47: =COUNTIFS(M$8:M$30,$B47) -> 0 | F47: =COUNTIFS(G$8:G$30,$B47) -> 0
B48: C6 | C48: =COUNTIF($B$8:$C$30,B48) -> 0 | D48: =C48-(COUNTIFS(C$8:C$30,B48,M$8:M$30,"")) -> 0 | E48: =COUNTIFS(M$8:M$30,$B48) -> 0 | F48: =COUNTIFS(G$8:G$30,$B48) -> 0
B49: C7 | C49: =COUNTIF($B$8:$C$30,B49) -> 0 | D49: =C49-(COUNTIFS(C$8:C$30,B49,M$8:M$30,"")) -> 0 | E49: =COUNTIFS(M$8:M$30,$B49) -> 0 | F49: =COUNTIFS(G$8:G$30,$B49) -> 0
B50: C8 | C50: =COUNTIF($B$8:$C$30,B50) -> 0 | D50: =C50-(COUNTIFS(C$8:C$30,B50,M$8:M$30,"")) -> 0 | E50: =COUNTIFS(M$8:M$30,$B50) -> 0 | F50: =COUNTIFS(G$8:G$30,$B50) -> 0
B51: C9 | C51: =COUNTIF($B$8:$C$30,B51) -> 0 | D51: =C51-(COUNTIFS(C$8:C$30,B51,M$8:M$30,"")) -> 0 | E51: =COUNTIFS(M$8:M$30,$B51) -> 0 | F51: =COUNTIFS(G$8:G$30,$B51) -> 0
B52: C10 | C52: =COUNTIF($B$8:$C$30,B52) -> 12 | D52: =C52-(COUNTIFS(C$8:C$30,B52,M$8:M$30,"")) -> 0 | E52: =COUNTIFS(M$8:M$30,$B52) -> 0 | F52: =COUNTIFS(G$8:G$30,$B52) -> 0
B53: C11 | C53: =COUNTIF($B$8:$C$30,B53) -> 0 | D53: =C53-(COUNTIFS(C$8:C$30,B53,M$8:M$30,"")) -> 0 | E53: =COUNTIFS(M$8:M$30,$B53) -> 0 | F53: =COUNTIFS(G$8:G$30,$B53) -> 0
B54: C12 | C54: =COUNTIF($B$8:$C$30,B54) -> 0 | D54: =C54-(COUNTIFS(C$8:C$30,B54,M$8:M$30,"")) -> 0 | E54: =COUNTIFS(M$8:M$30,$B54) -> 0 | F54: =COUNTIFS(G$8:G$30,$B54) -> 0
... B69: C25 | C69: =COUNTIF($B$8:$C$30,B69) -> 0 | D69: =C69-(COUNTIFS(C$8:C$30,B69,M$8:M$30,"")) -> 0 | E69: =COUNTIFS(M$8:M$30,$B69) -> 0 | F69: =COUNTIFS(G$8:G$30,$B69) -> 0
C70: =SUM(C43:C69) -> 22 | D70: =SUM(D43:D69) -> 0 | E70: =SUM(E43:E69) -> 0 | F70: =SUM(F43:F69) -> 0
E71: =D70-E70 -> 0 | F71: =IF(E71=F70,"OK","ERREUR") -> OK

Sheet coordinateur matin
A1: COORDINATEUR LIGNE4 NAVETTES CARIBUS | F1: 46143 | I1: NOM COORDINATEUR
A2: * | B2: Heure théorique départ | C2: Type chauffeur prévu | D2: Nom chauffeur prévu | E2: Astreinte | F2: Nom Chauffeur réel ( si différent) | G2: Heure réelle départ | H2: Nbre personnes montantes
A3: =Horaire!A8 -> VAHIBE | B3: =Horaire!B8 -> 0.1875 | C3: =Horaire!C8 -> C2 | D3: =VLOOKUP(C3,'Liste chauffeur'!$B$5:$L$20,2,TRUE)&" "&VLOOKUP(C3,'Liste chauffeur'!$B$5:$L$20,3,TRUE) -> BINA HALADI Bina | E3: C7
A4: =Horaire!A9 -> VAHIBE | B4: =Horaire!B9 -> 0.19444444 | C4: =Horaire!C9 -> C1 | D4: =VLOOKUP(C4,'Liste chauffeur'!$B$5:$L$20,2,TRUE)&" "&VLOOKUP(C4,'Liste chauffeur'!$B$5:$L$20,3,TRUE) -> EL ANZIZE SALIM Hamada | E4: C7
A5: =Horaire!A10 -> VAHIBE | B5: =Horaire!B10 -> 0.20138889 | C5: =Horaire!C10 -> C3 | D5: =VLOOKUP(C5,'Liste chauffeur'!$B$5:$L$20,2,TRUE)&" "&VLOOKUP(C5,'Liste chauffeur'!$B$5:$L$20,3,TRUE) -> ABDOU MINIHADJI Amada | E5: C7
A6: =Horaire!A11 -> PASSAMAINTY | B6: =Horaire!B11 -> 0.20138889 | C6: =Horaire!C11 -> C2 | D6: =VLOOKUP(C6,'Liste chauffeur'!$B$5:$L$20,2,TRUE)&" "&VLOOKUP(C6,'Liste chauffeur'!$B$5:$L$20,3,TRUE) -> BINA HALADI Bina | E6: C7
A7: =Horaire!A12 -> VAHIBE | B7: =Horaire!B12 -> 0.20833333 | C7: =Horaire!C12 -> C4 | D7: =VLOOKUP(C7,'Liste chauffeur'!$B$5:$L$20,2,TRUE)&" "&VLOOKUP(C7,'Liste chauffeur'!$B$5:$L$20,3,TRUE) -> TOUMBOU Toibourani | E7: C7 | F7: =IF(ISBLANK('Feuille saisie'!M12)=TRUE,"",'Feuille saisie'!M12)
A8: =Horaire!A13 -> PASSAMAINTY | B8: =Horaire!B13 -> 0.20833333 | C8: =Horaire!C13 -> C1 | D8: =VLOOKUP(C8,'Liste chauffeur'!$B$5:$L$20,2,TRUE)&" "&VLOOKUP(C8,'Liste chauffeur'!$B$5:$L$20,3,TRUE) -> EL ANZIZE SALIM Hamada | E8: C7 | F8: =IF(ISBLANK('Feuille saisie'!M13)=TRUE,"",'Feuille saisie'!M13) | I8: Observations :
A9: =Horaire!A14 -> VAHIBE 2 | B9: =Horaire!B14 -> 0.20833333 | C9: =Horaire!C14 -> C11 | D9: =VLOOKUP(C9,'Liste chauffeur'!$B$5:$L$20,2,TRUE)&" "&VLOOKUP(C9,'Liste chauffeur'!$B$5:$L$20,3,TRUE) -> MADI BOINA Mkidachi | E9: C7 | F9: =IF(ISBLANK('Feuille saisie'!M14)=TRUE,"",'Feuille saisie'!M14)
A10: =Horaire!A15 -> VAHIBE | B10: =Horaire!B15 -> 0.21527778 | C10: =Horaire!C15 -> C2 | D10: =VLOOKUP(C10,'Liste chauffeur'!$B$5:$L$20,2,TRUE)&" "&VLOOKUP(C10,'Liste chauffeur'!$B$5:$L$20,3,TRUE) -> BINA HALADI Bina | E10: C7 | F10: =IF(ISBLANK('Feuille saisie'!M15)=TRUE,"",'Feuille saisie'!M15)
A11: =Horaire!A16 -> VAHIBE 2 | B11: =Horaire!B16 -> 0.21527778 | C11: =Horaire!C16 -> C8 | D11: =VLOOKUP(C11,'Liste chauffeur'!$B$5:$L$20,2,TRUE)&" "&VLOOKUP(C11,'Liste chauffeur'!$B$5:$L$20,3,TRUE) -> HADHURAMI Makinedine | E11: C7 | F11: =IF(ISBLANK('Feuille saisie'!M16)=TRUE,"",'Feuille saisie'!M16)
A12: =Horaire!A17 -> PASSAMAINTY | B12: =Horaire!B17 -> 0.21527778 | C12: =Horaire!C17 -> C3 | D12: =VLOOKUP(C12,'Liste chauffeur'!$B$5:$L$20,2,TRUE)&" "&VLOOKUP(C12,'Liste chauffeur'!$B$5:$L$20,3,TRUE) -> ABDOU MINIHADJI Amada | E12: C7 | F12: =IF(ISBLANK('Feuille saisie'!M17)=TRUE,"",'Feuille saisie'!M17)
A13: =Horaire!A18 -> VAHIBE | B13: =Horaire!B18 -> 0.22222222 | C13: =Horaire!C18 -> C1 | D13: =VLOOKUP(C13,'Liste chauffeur'!$B$5:$L$20,2,TRUE)&" "&VLOOKUP(C13,'Liste chauffeur'!$B$5:$L$20,3,TRUE) -> EL ANZIZE SALIM Hamada | E13: C7
A14: =Horaire!A19 -> VAHIBE 2 | B14: =Horaire!B19 -> 0.22222222 | C14: =Horaire!C19 -> C9 | D14: =VLOOKUP(C14,'Liste chauffeur'!$B$5:$L$20,2,TRUE)&" "&VLOOKUP(C14,'Liste chauffeur'!$B$5:$L$20,3,TRUE) -> SANDI Maanrouf | E14: C7 | F14: =IF(ISBLANK('Feuille saisie'!M19)=TRUE,"",'Feuille saisie'!M19)
A15: =Horaire!A20 -> PASSAMAINTY | B15: =Horaire!B20 -> 0.22222222 | C15: =Horaire!C20 -> C4 | D15: =VLOOKUP(C15,'Liste chauffeur'!$B$5:$L$20,2,TRUE)&" "&VLOOKUP(C15,'Liste chauffeur'!$B$5:$L$20,3,TRUE) -> TOUMBOU Toibourani | E15: C7 | F15: =IF(ISBLANK('Feuille saisie'!M20)=TRUE,"",'Feuille saisie'!M20)
A16: =Horaire!A21 -> PASSAMAINTY | B16: =Horaire!B21 -> 0.22222222 | C16: =Horaire!C21 -> C11 | D16: =VLOOKUP(C16,'Liste chauffeur'!$B$5:$L$20,2,TRUE)&" "&VLOOKUP(C16,'Liste chauffeur'!$B$5:$L$20,3,TRUE) -> MADI BOINA Mkidachi | E16: C7 | F16: =IF(ISBLANK('Feuille saisie'!M21)=TRUE,"",'Feuille saisie'!M21)
A17: =Horaire!A22 -> VAHIBE | B17: =Horaire!B22 -> 0.22916667 | C17: =Horaire!C22 -> C3 | D17: =VLOOKUP(C17,'Liste chauffeur'!$B$5:$L$20,2,TRUE)&" "&VLOOKUP(C17,'Liste chauffeur'!$B$5:$L$20,3,TRUE) -> ABDOU MINIHADJI Amada | E17: C7 | F17: =IF(ISBLANK('Feuille saisie'!M22)=TRUE,"",'Feuille saisie'!M22)
A18: =Horaire!A23 -> VAHIBE 2 | B18: =Horaire!B23 -> 0.22916667 | C18: =Horaire!C23 -> C10 | D18: =VLOOKUP(C18,'Liste chauffeur'!$B$5:$L$20,2,TRUE)&" "&VLOOKUP(C18,'Liste chauffeur'!$B$5:$L$20,3,TRUE) -> ISSIHAKA M'Changama | E18: C7 | F18: =IF(ISBLANK('Feuille saisie'!M23)=TRUE,"",'Feuille saisie'!M23)
A19: =Horaire!A24 -> PASSAMAINTY | B19: =Horaire!B24 -> 0.22916667 | C19: =Horaire!C24 -> C2 | D19: =VLOOKUP(C19,'Liste chauffeur'!$B$5:$L$20,2,TRUE)&" "&VLOOKUP(C19,'Liste chauffeur'!$B$5:$L$20,3,TRUE) -> BINA HALADI Bina | E19: C7 | F19: =IF(ISBLANK('Feuille saisie'!M24)=TRUE,"",'Feuille saisie'!M24)
A20: =Horaire!A25 -> PASSAMAINTY | B20: =Horaire!B25 -> 0.22916667 | C20: =Horaire!C25 -> C8 | D20: =VLOOKUP(C20,'Liste chauffeur'!$B$5:$L$20,2,TRUE)&" "&VLOOKUP(C20,'Liste chauffeur'!$B$5:$L$20,3,TRUE) -> HADHURAMI Makinedine | E20: C7
A21: =Horaire!A26 -> VAHIBE | B21: =Horaire!B26 -> 0.23611111 | C21: =Horaire!C26 -> C4 | D21: =VLOOKUP(C21,'Liste chauffeur'!$B$5:$L$20,2,TRUE)&" "&VLOOKUP(C21,'Liste chauffeur'!$B$5:$L$20,3,TRUE) -> TOUMBOU Toibourani | E21: C7 | F21: =IF(ISBLANK('Feuille saisie'!M26)=TRUE,"",'Feuille saisie'!M26)
A22: =Horaire!A27 -> VAHIBE 2 | B22: =Horaire!B27 -> 0.23611111 | C22: =Horaire!C27 -> C11 | D22: =VLOOKUP(C22,'Liste chauffeur'!$B$5:$L$20,2,TRUE)&" "&VLOOKUP(C22,'Liste chauffeur'!$B$5:$L$20,3,TRUE) -> MADI BOINA Mkidachi | E22: C7 | F22: =IF(ISBLANK('Feuille saisie'!M27)=TRUE,"",'Feuille saisie'!M27)
A23: =Horaire!A28 -> PASSAMAINTY | B23: =Horaire!B28 -> 0.23611111 | C23: =Horaire!C28 -> C1 | D23: =VLOOKUP(C23,'Liste chauffeur'!$B$5:$L$20,2,TRUE)&" "&VLOOKUP(C23,'Liste chauffeur'!$B$5:$L$20,3,TRUE) -> EL ANZIZE SALIM Hamada | E23: C7 | F23: =IF(ISBLANK('Feuille saisie'!M28)=TRUE,"",'Feuille saisie'!M28)
A24: =Horaire!A29 -> PASSAMAINTY | B24: =Horaire!B29 -> 0.23611111 | C24: =Horaire!C29 -> C9 | D24: =VLOOKUP(C24,'Liste chauffeur'!$B$5:$L$20,2,TRUE)&" "&VLOOKUP(C24,'Liste chauffeur'!$B$5:$L$20,3,TRUE) -> SANDI Maanrouf | E24: C7 | F24: =IF(ISBLANK('Feuille saisie'!M29)=TRUE,"",'Feuille saisie'!M29) | I24: Absences :
A25: =Horaire!A30 -> VAHIBE | B25: =Horaire!B30 -> 0.24305556 | C25: =Horaire!C30 -> C2 | D25: =VLOOKUP(C25,'Liste chauffeur'!$B$5:$L$20,2,TRUE)&" "&VLOOKUP(C25,'Liste chauffeur'!$B$5:$L$20,3,TRUE) -> BINA HALADI Bina | E25: C7 | F25: =IF(ISBLANK('Feuille saisie'!M30)=TRUE,"",'Feuille saisie'!M30)
A26: =Horaire!A31 -> VAHIBE 2 | B26: =Horaire!B31 -> 0.24305556 | C26: =Horaire!C31 -> C8 | D26: =VLOOKUP(C26,'Liste chauffeur'!$B$5:$L$20,2,TRUE)&" "&VLOOKUP(C26,'Liste chauffeur'!$B$5:$L$20,3,TRUE) -> HADHURAMI Makinedine | E26: C7 | F26: =IF(ISBLANK('Feuille saisie'!M31)=TRUE,"",'Feuille saisie'!M31)
A27: =Horaire!A32 -> PASSAMAINTY | B27: =Horaire!B32 -> 0.24305556 | C27: =Horaire!C32 -> C3 | D27: =VLOOKUP(C27,'Liste chauffeur'!$B$5:$L$20,2,TRUE)&" "&VLOOKUP(C27,'Liste chauffeur'!$B$5:$L$20,3,TRUE) -> ABDOU MINIHADJI Amada | E27: C7
A28: =Horaire!A33 -> PASSAMAINTY | B28: =Horaire!B33 -> 0.24305556 | C28: =Horaire!C33 -> C10 | D28: =VLOOKUP(C28,'Liste chauffeur'!$B$5:$L$20,2,TRUE)&" "&VLOOKUP(C28,'Liste chauffeur'!$B$5:$L$20,3,TRUE) -> ISSIHAKA M'Changama | E28: C7 | F28: =IF(ISBLANK('Feuille saisie'!M33)=TRUE,"",'Feuille saisie'!M33)
A29: =Horaire!A34 -> VAHIBE | B29: =Horaire!B34 -> 0.25 | C29: =Horaire!C34 -> C1 | D29: =VLOOKUP(C29,'Liste chauffeur'!$B$5:$L$20,2,TRUE)&" "&VLOOKUP(C29,'Liste chauffeur'!$B$5:$L$20,3,TRUE) -> EL ANZIZE SALIM Hamada | E29: C7 | F29: =IF(ISBLANK('Feuille saisie'!M34)=TRUE,"",'Feuille saisie'!M34)
A30: =Horaire!A35 -> VAHIBE 2 | B30: =Horaire!B35 -> 0.25 | C30: =Horaire!C35 -> C9 | D30: =VLOOKUP(C30,'Liste chauffeur'!$B$5:$L$20,2,TRUE)&" "&VLOOKUP(C30,'Liste chauffeur'!$B$5:$L$20,3,TRUE) -> SANDI Maanrouf | E30: C7 | F30: =IF(ISBLANK('Feuille saisie'!M35)=TRUE,"",'Feuille saisie'!M35)
A31: =Horaire!A36 -> PASSAMAINTY | B31: =Horaire!B36 -> 0.25 | C31: =Horaire!C36 -> C5 | D31: =VLOOKUP(C31,'Liste chauffeur'!$B$5:$L$20,2,TRUE)&" "&VLOOKUP(C31,'Liste chauffeur'!$B$5:$L$20,3,TRUE) -> AHAMADI Bacar Raenmouddine | E31: C7 | F31: =IF(ISBLANK('Feuille saisie'!M36)=TRUE,"",'Feuille saisie'!M36)
A32: =Horaire!A37 -> PASSAMAINTY | B32: =Horaire!B37 -> 0.25 | C32: =Horaire!C37 -> C12 | D32: =VLOOKUP(C32,'Liste chauffeur'!$B$5:$L$20,2,TRUE)&" "&VLOOKUP(C32,'Liste chauffeur'!$B$5:$L$20,3,TRUE) -> ALILOIFFA Said Siradj | E32: C7 | F32: =IF(ISBLANK('Feuille saisie'!M37)=TRUE,"",'Feuille saisie'!M37) | I32: Trajets non effectués :
A33: =Horaire!A38 -> VAHIBE | B33: =Horaire!B38 -> 0.25694444 | C33: =Horaire!C38 -> C3 | D33: =VLOOKUP(C33,'Liste chauffeur'!$B$5:$L$20,2,TRUE)&" "&VLOOKUP(C33,'Liste chauffeur'!$B$5:$L$20,3,TRUE) -> ABDOU MINIHADJI Amada | E33: C7 | F33: =IF(ISBLANK('Feuille saisie'!M38)=TRUE,"",'Feuille saisie'!M38)
A34: =Horaire!A39 -> VAHIBE 2 | B34: =Horaire!B39 -> 0.25694444 | C34: =Horaire!C39 -> C10 | D34: =VLOOKUP(C34,'Liste chauffeur'!$B$5:$L$20,2,TRUE)&" "&VLOOKUP(C34,'Liste chauffeur'!$B$5:$L$20,3,TRUE) -> ISSIHAKA M'Changama | E34: C7 | F34: =IF(ISBLANK('Feuille saisie'!M39)=TRUE,"",'Feuille saisie'!M39)
A35: =Horaire!A40 -> PASSAMAINTY | B35: =Horaire!B40 -> 0.25694444 | C35: =Horaire!C40 -> C4 | D35: =VLOOKUP(C35,'Liste chauffeur'!$B$5:$L$20,2,TRUE)&" "&VLOOKUP(C35,'Liste chauffeur'!$B$5:$L$20,3,TRUE) -> TOUMBOU Toibourani | E35: C7 | F35: =IF(ISBLANK('Feuille saisie'!M40)=TRUE,"",'Feuille saisie'!M40)
A36: =Horaire!A41 -> PASSAMAINTY | B36: =Horaire!B41 -> 0.25694444 | C36: =Horaire!C41 -> C11 | D36: =VLOOKUP(C36,'Liste chauffeur'!$B$5:$L$20,2,TRUE)&" "&VLOOKUP(C36,'Liste chauffeur'!$B$5:$L$20,3,TRUE) -> MADI BOINA Mkidachi | E36: C7 | F36: =IF(ISBLANK('Feuille saisie'!M41)=TRUE,"",'Feuille saisie'!M41)
A37: =Horaire!A42 -> VAHIBE | B37: =Horaire!B42 -> 0.26388889 | C37: =Horaire!C42 -> C5 | D37: =VLOOKUP(C37,'Liste chauffeur'!$B$5:$L$20,2,TRUE)&" "&VLOOKUP(C37,'Liste chauffeur'!$B$5:$L$20,3,TRUE) -> AHAMADI Bacar Raenmouddine | E37: C7 | F37: =IF(ISBLANK('Feuille saisie'!M42)=TRUE,"",'Feuille saisie'!M42)
A38: =Horaire!A43 -> VAHIBE 2 | B38: =Horaire!B43 -> 0.26388889 | C38: =Horaire!C43 -> C12 | D38: =VLOOKUP(C38,'Liste chauffeur'!$B$5:$L$20,2,TRUE)&" "&VLOOKUP(C38,'Liste chauffeur'!$B$5:$L$20,3,TRUE) -> ALILOIFFA Said Siradj | E38: C7 | F38: =IF(ISBLANK('Feuille saisie'!M43)=TRUE,"",'Feuille saisie'!M43)
A39: =Horaire!A44 -> PASSAMAINTY | B39: =Horaire!B44 -> 0.26388889 | C39: =Horaire!C44 -> C2 | D39: =VLOOKUP(C39,'Liste chauffeur'!$B$5:$L$20,2,TRUE)&" "&VLOOKUP(C39,'Liste chauffeur'!$B$5:$L$20,3,TRUE) -> BINA HALADI Bina | E39: C7 | F39: =IF(ISBLANK('Feuille saisie'!M44)=TRUE,"",'Feuille saisie'!M44)
A40: =Horaire!A45 -> PASSAMAINTY | B40: =Horaire!B45 -> 0.26388889 | C40: =Horaire!C45 -> C8 | D40: =VLOOKUP(C40,'Liste chauffeur'!$B$5:$L$20,2,TRUE)&" "&VLOOKUP(C40,'Liste chauffeur'!$B$5:$L$20,3,TRUE) -> HADHURAMI Makinedine | E40: C7 | F40: =IF(ISBLANK('Feuille saisie'!M45)=TRUE,"",'Feuille saisie'!M45)
A41: =Horaire!A46 -> VAHIBE | B41: =Horaire!B46 -> 0.27083333 | C41: =Horaire!C46 -> C4 | D41: =VLOOKUP(C41,'Liste chauffeur'!$B$5:$L$20,2,TRUE)&" "&VLOOKUP(C41,'Liste chauffeur'!$B$5:$L$20,3,TRUE) -> TOUMBOU Toibourani | E41: C7 | F41: =IF(ISBLANK('Feuille saisie'!M46)=TRUE,"",'Feuille saisie'!M46)
A42: =Horaire!A47 -> VAHIBE 2 | B42: =Horaire!B47 -> 0.27083333 | C42: =Horaire!C47 -> C11 | D42: =VLOOKUP(C42,'Liste chauffeur'!$B$5:$L$20,2,TRUE)&" "&VLOOKUP(C42,'Liste chauffeur'!$B$5:$L$20,3,TRUE) -> MADI BOINA Mkidachi | E42: C7 | F42: =IF(ISBLANK('Feuille saisie'!M47)=TRUE,"",'Feuille saisie'!M47)
A43: =Horaire!A48 -> PASSAMAINTY | B43: =Horaire!B48 -> 0.27083333 | C43: =Horaire!C48 -> C15 | D43: =VLOOKUP(C43,'Liste chauffeur'!$B$5:$L$20,2,TRUE)&" "&VLOOKUP(C43,'Liste chauffeur'!$B$5:$L$20,3,TRUE) -> HAMADA Babou | E43: C7 | F43: =IF(ISBLANK('Feuille saisie'!M48)=TRUE,"",'Feuille saisie'!M48) | I43: Signature Coordinateur 1 :
A44: =Horaire!A49 -> PASSAMAINTY | B44: =Horaire!B49 -> 0.27083333 | C44: =Horaire!C49 -> C9 | D44: =VLOOKUP(C44,'Liste chauffeur'!$B$5:$L$20,2,TRUE)&" "&VLOOKUP(C44,'Liste chauffeur'!$B$5:$L$20,3,TRUE) -> SANDI Maanrouf | E44: C7 | F44: =IF(ISBLANK('Feuille saisie'!M49)=TRUE,"",'Feuille saisie'!M49)
A45: =Horaire!A50 -> VAHIBE | B45: =Horaire!B50 -> 0.27777778 | C45: =Horaire!C50 -> C2 | D45: =VLOOKUP(C45,'Liste chauffeur'!$B$5:$L$20,2,TRUE)&" "&VLOOKUP(C45,'Liste chauffeur'!$B$5:$L$20,3,TRUE) -> BINA HALADI Bina | E45: C7 | F45: =IF(ISBLANK('Feuille saisie'!M50)=TRUE,"",'Feuille saisie'!M50)
A46: =Horaire!A51 -> VAHIBE 2 | B46: =Horaire!B51 -> 0.27777778 | C46: =Horaire!C51 -> C8 | D46: =VLOOKUP(C46,'Liste chauffeur'!$B$5:$L$20,2,TRUE)&" "&VLOOKUP(C46,'Liste chauffeur'!$B$5:$L$20,3,TRUE) -> HADHURAMI Makinedine | E46: C7 | F46: =IF(ISBLANK('Feuille saisie'!M51)=TRUE,"",'Feuille saisie'!M51)
A47: =Horaire!A52 -> PASSAMAINTY | B47: =Horaire!B52 -> 0.27777778 | C47: =Horaire!C52 -> C1 | D47: =VLOOKUP(C47,'Liste chauffeur'!$B$5:$L$20,2,TRUE)&" "&VLOOKUP(C47,'Liste chauffeur'!$B$5:$L$20,3,TRUE) -> EL ANZIZE SALIM Hamada | E47: C7 | F47: =IF(ISBLANK('Feuille saisie'!M52)=TRUE,"",'Feuille saisie'!M52)
A48: =Horaire!A53 -> PASSAMAINTY | B48: =Horaire!B53 -> 0.27777778 | C48: =Horaire!C53 -> C3 | D48: =VLOOKUP(C48,'Liste chauffeur'!$B$5:$L$20,2,TRUE)&" "&VLOOKUP(C48,'Liste chauffeur'!$B$5:$L$20,3,TRUE) -> ABDOU MINIHADJI Amada | E48: C7 | F48: =IF(ISBLANK('Feuille saisie'!M53)=TRUE,"",'Feuille saisie'!M53)
A49: =Horaire!A54 -> VAHIBE | B49: =Horaire!B54 -> 0.28472222 | C49: =Horaire!C54 -> C15 | D49: =VLOOKUP(C49,'Liste chauffeur'!$B$5:$L$20,2,TRUE)&" "&VLOOKUP(C49,'Liste chauffeur'!$B$5:$L$20,3,TRUE) -> HAMADA Babou | E49: C7 | F49: =IF(ISBLANK('Feuille saisie'!M54)=TRUE,"",'Feuille saisie'!M54)
A50: =Horaire!A55 -> VAHIBE 2 | B50: =Horaire!B55 -> 0.28472222 | C50: =Horaire!C55 -> C9 | D50: =VLOOKUP(C50,'Liste chauffeur'!$B$5:$L$20,2,TRUE)&" "&VLOOKUP(C50,'Liste chauffeur'!$B$5:$L$20,3,TRUE) -> SANDI Maanrouf | E50: C7 | F50: =IF(ISBLANK('Feuille saisie'!M55)=TRUE,"",'Feuille saisie'!M55) | I50: Observations :
A51: =Horaire!A56 -> PASSAMAINTY | B51: =Horaire!B56 -> 0.28472222 | C51: =Horaire!C56 -> C10 | D51: =VLOOKUP(C51,'Liste chauffeur'!$B$5:$L$20,2,TRUE)&" "&VLOOKUP(C51,'Liste chauffeur'!$B$5:$L$20,3,TRUE) -> ISSIHAKA M'Changama | E51: C7 | F51: =IF(ISBLANK('Feuille saisie'!M56)=TRUE,"",'Feuille saisie'!M56)
A52: =Horaire!A57 -> PASSAMAINTY | B52: =Horaire!B57 -> 0.28472222 | C52: =Horaire!C57 -> C5 | D52: =VLOOKUP(C52,'Liste chauffeur'!$B$5:$L$20,2,TRUE)&" "&VLOOKUP(C52,'Liste chauffeur'!$B$5:$L$20,3,TRUE) -> AHAMADI Bacar Raenmouddine | E52: C7
A53: =Horaire!A58 -> VAHIBE | B53: =Horaire!B58 -> 0.29166667 | C53: =Horaire!C58 -> C1 | D53: =VLOOKUP(C53,'Liste chauffeur'!$B$5:$L$20,2,TRUE)&" "&VLOOKUP(C53,'Liste chauffeur'!$B$5:$L$20,3,TRUE) -> EL ANZIZE SALIM Hamada | E53: C7
A54: =Horaire!A59 -> VAHIBE 2 | B54: =Horaire!B59 -> 0.29166667 | C54: =Horaire!C59 -> C3 | D54: =VLOOKUP(C54,'Liste chauffeur'!$B$5:$L$20,2,TRUE)&" "&VLOOKUP(C54,'Liste chauffeur'!$B$5:$L$20,3,TRUE) -> ABDOU MINIHADJI Amada | E54: C7
A55: =Horaire!A60 -> PASSAMAINTY | B55: =Horaire!B60 -> 0.29166667 | C55: =Horaire!C60 -> C4 | D55: =VLOOKUP(C55,'Liste chauffeur'!$B$5:$L$20,2,TRUE)&" "&VLOOKUP(C55,'Liste chauffeur'!$B$5:$L$20,3,TRUE) -> TOUMBOU Toibourani | E55: C7
A56: =Horaire!A61 -> PASSAMAINTY | B56: =Horaire!B61 -> 0.29166667 | C56: =Horaire!C61 -> C11 | D56: =VLOOKUP(C56,'Liste chauffeur'!$B$5:$L$20,2,TRUE)&" "&VLOOKUP(C56,'Liste chauffeur'!$B$5:$L$20,3,TRUE) -> MADI BOINA Mkidachi | E56: C7
A57: =Horaire!A62 -> VAHIBE | B57: =Horaire!B62 -> 0.29861111 | C57: =Horaire!C62 -> C10 | D57: =VLOOKUP(C57,'Liste chauffeur'!$B$5:$L$20,2,TRUE)&" "&VLOOKUP(C57,'Liste chauffeur'!$B$5:$L$20,3,TRUE) -> ISSIHAKA M'Changama | E57: C7
A58: =Horaire!A63 -> VAHIBE 2 | B58: =Horaire!B63 -> 0.29861111 | C58: =Horaire!C63 -> C5 | D58: =VLOOKUP(C58,'Liste chauffeur'!$B$5:$L$20,2,TRUE)&" "&VLOOKUP(C58,'Liste chauffeur'!$B$5:$L$20,3,TRUE) -> AHAMADI Bacar Raenmouddine | E58: C7
A59: =Horaire!A64 -> PASSAMAINTY | B59: =Horaire!B64 -> 0.29861111 | C59: =Horaire!C64 -> C13 | D59: =VLOOKUP(C59,'Liste chauffeur'!$B$5:$L$20,2,TRUE)&" "&VLOOKUP(C59,'Liste chauffeur'!$B$5:$L$20,3,TRUE) -> ABDALLAH Ben (Taxi Vanille) | E59: C7
A60: =Horaire!A65 -> PASSAMAINTY | B60: =Horaire!B65 -> 0.29861111 | C60: =Horaire!C65 -> C8 | D60: =VLOOKUP(C60,'Liste chauffeur'!$B$5:$L$20,2,TRUE)&" "&VLOOKUP(C60,'Liste chauffeur'!$B$5:$L$20,3,TRUE) -> HADHURAMI Makinedine | E60: C7
A61: =Horaire!A66 -> VAHIBE | B61: =Horaire!B66 -> 0.30555556 | C61: =Horaire!C66 -> C4 | D61: =VLOOKUP(C61,'Liste chauffeur'!$B$5:$L$20,2,TRUE)&" "&VLOOKUP(C61,'Liste chauffeur'!$B$5:$L$20,3,TRUE) -> TOUMBOU Toibourani | E61: C7
A62: =Horaire!A67 -> VAHIBE 2 | B62: =Horaire!B67 -> 0.30555556 | C62: =Horaire!C67 -> C11 | D62: =VLOOKUP(C62,'Liste chauffeur'!$B$5:$L$20,2,TRUE)&" "&VLOOKUP(C62,'Liste chauffeur'!$B$5:$L$20,3,TRUE) -> MADI BOINA Mkidachi | E62: C7
A63: =Horaire!A68 -> PASSAMAINTY | B63: =Horaire!B68 -> 0.30555556 | C63: =Horaire!C68 -> C15 | D63: =VLOOKUP(C63,'Liste chauffeur'!$B$5:$L$20,2,TRUE)&" "&VLOOKUP(C63,'Liste chauffeur'!$B$5:$L$20,3,TRUE) -> HAMADA Babou | E63: C7
... A65: =Horaire!A70 -> VAHIBE | B65: =Horaire!B70 -> 0.3125 | C65: =Horaire!C70 -> C13 | D65: =VLOOKUP(C65,'Liste chauffeur'!$B$5:$L$20,2,TRUE)&" "&VLOOKUP(C65,'Liste chauffeur'!$B$5:$L$20,3,TRUE) -> ABDALLAH Ben (Taxi Vanille) | E65: C7
A66: =Horaire!A71 -> VAHIBE 2 | B66: =Horaire!B71 -> 0.3125 | C66: =Horaire!C71 -> C8 | D66: =VLOOKUP(C66,'Liste chauffeur'!$B$5:$L$20,2,TRUE)&" "&VLOOKUP(C66,'Liste chauffeur'!$B$5:$L$20,3,TRUE) -> HADHURAMI Makinedine | E66: C7 | I66: Absences :
A67: =Horaire!A72 -> PASSAMAINTY | B67: =Horaire!B72 -> 0.3125 | C67: =Horaire!C72 -> C3 | D67: =VLOOKUP(C67,'Liste chauffeur'!$B$5:$L$20,2,TRUE)&" "&VLOOKUP(C67,'Liste chauffeur'!$B$5:$L$20,3,TRUE) -> ABDOU MINIHADJI Amada | E67: C7
A68: =Horaire!A73 -> PASSAMAINTY | B68: =Horaire!B73 -> 0.3125 | C68: =Horaire!C73 -> C1 | D68: =VLOOKUP(C68,'Liste chauffeur'!$B$5:$L$20,2,TRUE)&" "&VLOOKUP(C68,'Liste chauffeur'!$B$5:$L$20,3,TRUE) -> EL ANZIZE SALIM Hamada | E68: C7
A69: =Horaire!A74 -> VAHIBE | B69: =Horaire!B74 -> 0.31944444 | C69: =Horaire!C74 -> C15 | D69: =VLOOKUP(C69,'Liste chauffeur'!$B$5:$L$20,2,TRUE)&" "&VLOOKUP(C69,'Liste chauffeur'!$B$5:$L$20,3,TRUE) -> HAMADA Babou | E69: C7
A70: =Horaire!A75 -> VAHIBE 2 | B70: =Horaire!B75 -> 0.31944444 | C70: =Horaire!C75 -> C9 | D70: =VLOOKUP(C70,'Liste chauffeur'!$B$5:$L$20,2,TRUE)&" "&VLOOKUP(C70,'Liste chauffeur'!$B$5:$L$20,3,TRUE) -> SANDI Maanrouf | E70: C7
A71: =Horaire!A76 -> PASSAMAINTY | B71: =Horaire!B76 -> 0.31944444 | C71: =Horaire!C76 -> C10 | D71: =VLOOKUP(C71,'Liste chauffeur'!$B$5:$L$20,2,TRUE)&" "&VLOOKUP(C71,'Liste chauffeur'!$B$5:$L$20,3,TRUE) -> ISSIHAKA M'Changama | E71: C7
A72: =Horaire!A77 -> PASSAMAINTY | B72: =Horaire!B77 -> 0.31944444 | C72: =Horaire!C77 -> C5 | D72: =VLOOKUP(C72,'Liste chauffeur'!$B$5:$L$20,2,TRUE)&" "&VLOOKUP(C72,'Liste chauffeur'!$B$5:$L$20,3,TRUE) -> AHAMADI Bacar Raenmouddine | E72: C7
A73: =Horaire!A78 -> VAHIBE | B73: =Horaire!B78 -> 0.32638889 | C73: =Horaire!C78 -> C3 | D73: =VLOOKUP(C73,'Liste chauffeur'!$B$5:$L$20,2,TRUE)&" "&VLOOKUP(C73,'Liste chauffeur'!$B$5:$L$20,3,TRUE) -> ABDOU MINIHADJI Amada | E73: C7
A74: =Horaire!A79 -> VAHIBE 2 | B74: =Horaire!B79 -> 0.32638889 | C74: =Horaire!C79 -> C1 | D74: =VLOOKUP(C74,'Liste chauffeur'!$B$5:$L$20,2,TRUE)&" "&VLOOKUP(C74,'Liste chauffeur'!$B$5:$L$20,3,TRUE) -> EL ANZIZE SALIM Hamada | E74: C7 | I74: Trajets non effectués :
A75: =Horaire!A80 -> PASSAMAINTY | B75: =Horaire!B80 -> 0.32638889 | C75: =Horaire!C80 -> C4 | D75: =VLOOKUP(C75,'Liste chauffeur'!$B$5:$L$20,2,TRUE)&" "&VLOOKUP(C75,'Liste chauffeur'!$B$5:$L$20,3,TRUE) -> TOUMBOU Toibourani | E75: C7
A76: =Horaire!A81 -> PASSAMAINTY | B76: =Horaire!B81 -> 0.32638889 | C76: =Horaire!C81 -> C11 | D76: =VLOOKUP(C76,'Liste chauffeur'!$B$5:$L$20,2,TRUE)&" "&VLOOKUP(C76,'Liste chauffeur'!$B$5:$L$20,3,TRUE) -> MADI BOINA Mkidachi | E76: C7
A77: =Horaire!A82 -> VAHIBE | B77: =Horaire!B82 -> 0.33333333 | C77: =Horaire!C82 -> C5 | D77: =VLOOKUP(C77,'Liste chauffeur'!$B$5:$L$20,2,TRUE)&" "&VLOOKUP(C77,'Liste chauffeur'!$B$5:$L$20,3,TRUE) -> AHAMADI Bacar Raenmouddine | E77: C7
A78: =Horaire!A83 -> VAHIBE 2 | B78: =Horaire!B83 -> 0.33333333 | C78: =Horaire!C83 -> C10 | D78: =VLOOKUP(C78,'Liste chauffeur'!$B$5:$L$20,2,TRUE)&" "&VLOOKUP(C78,'Liste chauffeur'!$B$5:$L$20,3,TRUE) -> ISSIHAKA M'Changama | E78: C7
A79: =Horaire!A84 -> PASSAMAINTY | B79: =Horaire!B84 -> 0.33333333 | C79: =Horaire!C84 -> C13 | D79: =VLOOKUP(C79,'Liste chauffeur'!$B$5:$L$20,2,TRUE)&" "&VLOOKUP(C79,'Liste chauffeur'!$B$5:$L$20,3,TRUE) -> ABDALLAH Ben (Taxi Vanille) | E79: C7
A80: =Horaire!A85 -> VAHIBE | B80: =Horaire!B85 -> 0.34375 | C80: =Horaire!C85 -> C4 | D80: =VLOOKUP(C80,'Liste chauffeur'!$B$5:$L$20,2,TRUE)&" "&VLOOKUP(C80,'Liste chauffeur'!$B$5:$L$20,3,TRUE) -> TOUMBOU Toibourani | E80: C7
A81: =Horaire!A86 -> PASSAMAINTY | B81: =Horaire!B86 -> 0.34375 | C81: =Horaire!C86 -> C15 | D81: =VLOOKUP(C81,'Liste chauffeur'!$B$5:$L$20,2,TRUE)&" "&VLOOKUP(C81,'Liste chauffeur'!$B$5:$L$20,3,TRUE) -> HAMADA Babou | E81: C7
A82: =Horaire!A87 -> VAHIBE | B82: =Horaire!B87 -> 0.35416667 | C82: =Horaire!C87 -> C14 | D82: =VLOOKUP(C82,'Liste chauffeur'!$B$5:$L$20,2,TRUE)&" "&VLOOKUP(C82,'Liste chauffeur'!$B$5:$L$20,3,TRUE) -> KAMARDINE Mansour | E82: C7
A83: =Horaire!A88 -> PASSAMAINTY | B83: =Horaire!B88 -> 0.35416667 | C83: =Horaire!C88 -> C1 | D83: =VLOOKUP(C83,'Liste chauffeur'!$B$5:$L$20,2,TRUE)&" "&VLOOKUP(C83,'Liste chauffeur'!$B$5:$L$20,3,TRUE) -> EL ANZIZE SALIM Hamada | E83: C7
A84: =Horaire!A89 -> VAHIBE | B84: =Horaire!B89 -> 0.375 | C84: =Horaire!C89 -> C1 | D84: =VLOOKUP(C84,'Liste chauffeur'!$B$5:$L$20,2,TRUE)&" "&VLOOKUP(C84,'Liste chauffeur'!$B$5:$L$20,3,TRUE) -> EL ANZIZE SALIM Hamada | E84: C7
A85: =Horaire!A90 -> PASSAMAINTY | B85: =Horaire!B90 -> 0.375 | C85: =Horaire!C90 -> C14 | D85: =VLOOKUP(C85,'Liste chauffeur'!$B$5:$L$20,2,TRUE)&" "&VLOOKUP(C85,'Liste chauffeur'!$B$5:$L$20,3,TRUE) -> KAMARDINE Mansour | I85: Signature Coordinateur 1 :
A86: =Horaire!A91 -> VAHIBE | B86: =Horaire!B91 -> 0.39583333 | C86: =Horaire!C91 -> C14 | D86: =VLOOKUP(C86,'Liste chauffeur'!$B$5:$L$20,2,TRUE)&" "&VLOOKUP(C86,'Liste chauffeur'!$B$5:$L$20,3,TRUE) -> KAMARDINE Mansour
A87: =Horaire!A92 -> PASSAMAINTY | B87: =Horaire!B92 -> 0.39583333 | C87: =Horaire!C92 -> C1 | D87: =VLOOKUP(C87,'Liste chauffeur'!$B$5:$L$20,2,TRUE)&" "&VLOOKUP(C87,'Liste chauffeur'!$B$5:$L$20,3,TRUE) -> EL ANZIZE SALIM Hamada
A88: =Horaire!A93 -> VAHIBE | B88: =Horaire!B93 -> 0.41666667 | C88: =Horaire!C93 -> C1 | D88: =VLOOKUP(C88,'Liste chauffeur'!$B$5:$L$20,2,TRUE)&" "&VLOOKUP(C88,'Liste chauffeur'!$B$5:$L$20,3,TRUE) -> EL ANZIZE SALIM Hamada
A89: =Horaire!A94 -> PASSAMAINTY | B89: =Horaire!B94 -> 0.41666667 | C89: =Horaire!C94 -> C14 | D89: =VLOOKUP(C89,'Liste chauffeur'!$B$5:$L$20,2,TRUE)&" "&VLOOKUP(C89,'Liste chauffeur'!$B$5:$L$20,3,TRUE) -> KAMARDINE Mansour
A90: =Horaire!A95 -> VAHIBE | B90: =Horaire!B95 -> 0.4375 | C90: =Horaire!C95 -> C14 | D90: =VLOOKUP(C90,'Liste chauffeur'!$B$5:$L$20,2,TRUE)&" "&VLOOKUP(C90,'Liste chauffeur'!$B$5:$L$20,3,TRUE) -> KAMARDINE Mansour
A91: =Horaire!A96 -> PASSAMAINTY | B91: =Horaire!B96 -> 0.4375 | C91: =Horaire!C96 -> C1 | D91: =VLOOKUP(C91,'Liste chauffeur'!$B$5:$L$20,2,TRUE)&" "&VLOOKUP(C91,'Liste chauffeur'!$B$5:$L$20,3,TRUE) -> EL ANZIZE SALIM Hamada
A92: =Horaire!A97 -> VAHIBE | B92: =Horaire!B97 -> 0.45833333 | C92: =Horaire!C97 -> C1 | D92: =VLOOKUP(C92,'Liste chauffeur'!$B$5:$L$20,2,TRUE)&" "&VLOOKUP(C92,'Liste chauffeur'!$B$5:$L$20,3,TRUE) -> EL ANZIZE SALIM Hamada
A93: =Horaire!A98 -> PASSAMAINTY | B93: =Horaire!B98 -> 0.45833333 | C93: =Horaire!C98 -> C14 | D93: =VLOOKUP(C93,'Liste chauffeur'!$B$5:$L$20,2,TRUE)&" "&VLOOKUP(C93,'Liste chauffeur'!$B$5:$L$20,3,TRUE) -> KAMARDINE Mansour
A94: =Horaire!A99 -> VAHIBE | B94: =Horaire!B99 -> 0.47916667 | C94: =Horaire!C99 -> C14 | D94: =VLOOKUP(C94,'Liste chauffeur'!$B$5:$L$20,2,TRUE)&" "&VLOOKUP(C94,'Liste chauffeur'!$B$5:$L$20,3,TRUE) -> KAMARDINE Mansour
A95: =Horaire!A100 -> PASSAMAINTY | B95: =Horaire!B100 -> 0.47916667 | C95: =Horaire!C100 -> C1 | D95: =VLOOKUP(C95,'Liste chauffeur'!$B$5:$L$20,2,TRUE)&" "&VLOOKUP(C95,'Liste chauffeur'!$B$5:$L$20,3,TRUE) -> EL ANZIZE SALIM Hamada
A96: =Horaire!A101 -> VAHIBE | B96: =Horaire!B101 -> 0.5 | C96: =Horaire!C101 -> C1 | D96: =VLOOKUP(C96,'Liste chauffeur'!$B$5:$L$20,2,TRUE)&" "&VLOOKUP(C96,'Liste chauffeur'!$B$5:$L$20,3,TRUE) -> EL ANZIZE SALIM Hamada
A97: =Horaire!A102 -> PASSAMAINTY | B97: =Horaire!B102 -> 0.5 | C97: =Horaire!C102 -> C14 | D97: =VLOOKUP(C97,'Liste chauffeur'!$B$5:$L$20,2,TRUE)&" "&VLOOKUP(C97,'Liste chauffeur'!$B$5:$L$20,3,TRUE) -> KAMARDINE Mansour
... A99: =Horaire!A104 -> PASSAMAINTY | B99: =Horaire!B104 -> 0.52083333 | C99: =Horaire!C104 -> C2 | D99: =VLOOKUP(C99,'Liste chauffeur'!$B$5:$L$20,2,TRUE)&" "&VLOOKUP(C99,'Liste chauffeur'!$B$5:$L$20,3,TRUE) -> BINA HALADI Bina
A100: =Horaire!A105 -> VAHIBE | B100: =Horaire!B105 -> 0.54166667 | C100: =Horaire!C105 -> C2 | D100: =VLOOKUP(C100,'Liste chauffeur'!$B$5:$L$20,2,TRUE)&" "&VLOOKUP(C100,'Liste chauffeur'!$B$5:$L$20,3,TRUE) -> BINA HALADI Bina | I100: Observations :
A101: =Horaire!A106 -> PASSAMAINTY | B101: =Horaire!B106 -> 0.54166667 | C101: =Horaire!C106 -> C14 | D101: =VLOOKUP(C101,'Liste chauffeur'!$B$5:$L$20,2,TRUE)&" "&VLOOKUP(C101,'Liste chauffeur'!$B$5:$L$20,3,TRUE) -> KAMARDINE Mansour
A102: =Horaire!A107 -> VAHIBE | B102: =Horaire!B107 -> 0.5625 | C102: =Horaire!C107 -> C14 | D102: =VLOOKUP(C102,'Liste chauffeur'!$B$5:$L$20,2,TRUE)&" "&VLOOKUP(C102,'Liste chauffeur'!$B$5:$L$20,3,TRUE) -> KAMARDINE Mansour
...

Sheet coordinateur samedi
A1: COORDINATEUR LIGNE 4 NAVETTES CARIBUS (SAMEDI) | E1: ='coordinateur matin'!F1 -> 46143 | I1: NOM COORDINATEUR
A2: Depart | B2: Heure théorique départ | C2: Type chauffeur prévu | D2: Nom chauffeur prévu | E2: Astreinte | F2: Nom Chauffeur réel ( si différent) | G2: Heure réelle départ | H2: Nbre personnes montantes
A3: ='Horaire samedi'!A8 -> VAHIBE | B3: ='Horaire samedi'!B8 -> 0.25 | C3: ='Horaire samedi'!C8 -> C11 | D3: =VLOOKUP(C3,'Liste chauffeur'!$B$5:$L$20,2,TRUE)&" "&VLOOKUP(C3,'Liste chauffeur'!$B$5:$L$20,3,TRUE) -> MADI BOINA Mkidachi
A4: ='Horaire samedi'!A10 -> PASSAMAINTY | B4: ='Horaire samedi'!B10 -> 0.27083333 | C4: ='Horaire samedi'!C10 -> C11 | D4: =VLOOKUP(C4,'Liste chauffeur'!$B$5:$L$20,2,TRUE)&" "&VLOOKUP(C4,'Liste chauffeur'!$B$5:$L$20,3,TRUE) -> MADI BOINA Mkidachi | I4: Observations :
A5: ='Horaire samedi'!A9 -> VAHIBE | B5: ='Horaire samedi'!B9 -> 0.27083333 | C5: ='Horaire samedi'!C9 -> C9 | D5: =VLOOKUP(C5,'Liste chauffeur'!$B$5:$L$20,2,TRUE)&" "&VLOOKUP(C5,'Liste chauffeur'!$B$5:$L$20,3,TRUE) -> SANDI Maanrouf
A6: ='Horaire samedi'!A12 -> PASSAMAINTY | B6: ='Horaire samedi'!B12 -> 0.29166667 | C6: ='Horaire samedi'!C12 -> C9 | D6: =VLOOKUP(C6,'Liste chauffeur'!$B$5:$L$20,2,TRUE)&" "&VLOOKUP(C6,'Liste chauffeur'!$B$5:$L$20,3,TRUE) -> SANDI Maanrouf
A7: ='Horaire samedi'!A11 -> VAHIBE | B7: ='Horaire samedi'!B11 -> 0.29166667 | C7: ='Horaire samedi'!C11 -> C11 | D7: =VLOOKUP(C7,'Liste chauffeur'!$B$5:$L$20,2,TRUE)&" "&VLOOKUP(C7,'Liste chauffeur'!$B$5:$L$20,3,TRUE) -> MADI BOINA Mkidachi | F7: =IF(ISBLANK('Feuille saisie'!M12)=TRUE,"",'Feuille saisie'!M12)
A8: ='Horaire samedi'!A14 -> PASSAMAINTY | B8: ='Horaire samedi'!B14 -> 0.3125 | C8: ='Horaire samedi'!C14 -> C9 | D8: =VLOOKUP(C8,'Liste chauffeur'!$B$5:$L$20,2,TRUE)&" "&VLOOKUP(C8,'Liste chauffeur'!$B$5:$L$20,3,TRUE) -> SANDI Maanrouf | F8: =IF(ISBLANK('Feuille saisie'!M13)=TRUE,"",'Feuille saisie'!M13)
A9: ='Horaire samedi'!A13 -> VAHIBE | B9: ='Horaire samedi'!B13 -> 0.3125 | C9: ='Horaire samedi'!C13 -> C11 | D9: =VLOOKUP(C9,'Liste chauffeur'!$B$5:$L$20,2,TRUE)&" "&VLOOKUP(C9,'Liste chauffeur'!$B$5:$L$20,3,TRUE) -> MADI BOINA Mkidachi | F9: =IF(ISBLANK('Feuille saisie'!M14)=TRUE,"",'Feuille saisie'!M14)
A10: ='Horaire samedi'!A16 -> PASSAMAINTY | B10: ='Horaire samedi'!B16 -> 0.33333333 | C10: ='Horaire samedi'!C16 -> C11 | D10: =VLOOKUP(C10,'Liste chauffeur'!$B$5:$L$20,2,TRUE)&" "&VLOOKUP(C10,'Liste chauffeur'!$B$5:$L$20,3,TRUE) -> MADI BOINA Mkidachi | F10: =IF(ISBLANK('Feuille saisie'!M15)=TRUE,"",'Feuille saisie'!M15)
A11: ='Horaire samedi'!A15 -> VAHIBE | B11: ='Horaire samedi'!B15 -> 0.33333333 | C11: ='Horaire samedi'!C15 -> C9 | D11: =VLOOKUP(C11,'Liste chauffeur'!$B$5:$L$20,2,TRUE)&" "&VLOOKUP(C11,'Liste chauffeur'!$B$5:$L$20,3,TRUE) -> SANDI Maanrouf | F11: =IF(ISBLANK('Feuille saisie'!M16)=TRUE,"",'Feuille saisie'!M16)
A12: ='Horaire samedi'!A18 -> PASSAMAINTY | B12: ='Horaire samedi'!B18 -> 0.375 | C12: ='Horaire samedi'!C18 -> C9 | D12: =VLOOKUP(C12,'Liste chauffeur'!$B$5:$L$20,2,TRUE)&" "&VLOOKUP(C12,'Liste chauffeur'!$B$5:$L$20,3,TRUE) -> SANDI Maanrouf | F12: =IF(ISBLANK('Feuille saisie'!M17)=TRUE,"",'Feuille saisie'!M17)
A13: ='Horaire samedi'!A17 -> VAHIBE | B13: ='Horaire samedi'!B17 -> 0.375 | C13: ='Horaire samedi'!C17 -> C11 | D13: =VLOOKUP(C13,'Liste chauffeur'!$B$5:$L$20,2,TRUE)&" "&VLOOKUP(C13,'Liste chauffeur'!$B$5:$L$20,3,TRUE) -> MADI BOINA Mkidachi | I13: Absences :
A14: ='Horaire samedi'!A20 -> PASSAMAINTY | B14: ='Horaire samedi'!B20 -> 0.39583333 | C14: ='Horaire samedi'!C20 -> C11 | D14: =VLOOKUP(C14,'Liste chauffeur'!$B$5:$L$20,2,TRUE)&" "&VLOOKUP(C14,'Liste chauffeur'!$B$5:$L$20,3,TRUE) -> MADI BOINA Mkidachi | F14: =IF(ISBLANK('Feuille saisie'!M19)=TRUE,"",'Feuille saisie'!M19)
A15: ='Horaire samedi'!A19 -> VAHIBE | B15: ='Horaire samedi'!B19 -> 0.39583333 | C15: ='Horaire samedi'!C19 -> C9 | D15: =VLOOKUP(C15,'Liste chauffeur'!$B$5:$L$20,2,TRUE)&" "&VLOOKUP(C15,'Liste chauffeur'!$B$5:$L$20,3,TRUE) -> SANDI Maanrouf | F15: =IF(ISBLANK('Feuille saisie'!M20)=TRUE,"",'Feuille saisie'!M20)
A16: ='Horaire samedi'!A22 -> PASSAMAINTY | B16: ='Horaire samedi'!B22 -> 0.41666667 | C16: ='Horaire samedi'!C22 -> C9 | D16: =VLOOKUP(C16,'Liste chauffeur'!$B$5:$L$20,2,TRUE)&" "&VLOOKUP(C16,'Liste chauffeur'!$B$5:$L$20,3,TRUE) -> SANDI Maanrouf | F16: =IF(ISBLANK('Feuille saisie'!M21)=TRUE,"",'Feuille saisie'!M21)
A17: ='Horaire samedi'!A21 -> VAHIBE | B17: ='Horaire samedi'!B21 -> 0.41666667 | C17: ='Horaire samedi'!C21 -> C11 | D17: =VLOOKUP(C17,'Liste chauffeur'!$B$5:$L$20,2,TRUE)&" "&VLOOKUP(C17,'Liste chauffeur'!$B$5:$L$20,3,TRUE) -> MADI BOINA Mkidachi | F17: =IF(ISBLANK('Feuille saisie'!M22)=TRUE,"",'Feuille saisie'!M22) | I17: Trajets non effectués :
A18: ='Horaire samedi'!A24 -> PASSAMAINTY | B18: ='Horaire samedi'!B24 -> 0.4375 | C18: ='Horaire samedi'!C24 -> C11 | D18: =VLOOKUP(C18,'Liste chauffeur'!$B$5:$L$20,2,TRUE)&" "&VLOOKUP(C18,'Liste chauffeur'!$B$5:$L$20,3,TRUE) -> MADI BOINA Mkidachi | F18: =IF(ISBLANK('Feuille saisie'!M23)=TRUE,"",'Feuille saisie'!M23)
A19: ='Horaire samedi'!A23 -> VAHIBE | B19: ='Horaire samedi'!B23 -> 0.4375 | C19: ='Horaire samedi'!C23 -> C9 | D19: =VLOOKUP(C19,'Liste chauffeur'!$B$5:$L$20,2,TRUE)&" "&VLOOKUP(C19,'Liste chauffeur'!$B$5:$L$20,3,TRUE) -> SANDI Maanrouf | F19: =IF(ISBLANK('Feuille saisie'!M24)=TRUE,"",'Feuille saisie'!M24)
A20: ='Horaire samedi'!A26 -> PASSAMAINTY | B20: ='Horaire samedi'!B26 -> 0.45833333 | C20: ='Horaire samedi'!C26 -> C9 | D20: =VLOOKUP(C20,'Liste chauffeur'!$B$5:$L$20,2,TRUE)&" "&VLOOKUP(C20,'Liste chauffeur'!$B$5:$L$20,3,TRUE) -> SANDI Maanrouf
A21: ='Horaire samedi'!A25 -> VAHIBE | B21: ='Horaire samedi'!B25 -> 0.45833333 | C21: ='Horaire samedi'!C25 -> C11 | D21: =VLOOKUP(C21,'Liste chauffeur'!$B$5:$L$20,2,TRUE)&" "&VLOOKUP(C21,'Liste chauffeur'!$B$5:$L$20,3,TRUE) -> MADI BOINA Mkidachi | F21: =IF(ISBLANK('Feuille saisie'!M26)=TRUE,"",'Feuille saisie'!M26)
A22: ='Horaire samedi'!A28 -> PASSAMAINTY | B22: ='Horaire samedi'!B28 -> 0.47916667 | C22: ='Horaire samedi'!C28 -> C11 | D22: =VLOOKUP(C22,'Liste chauffeur'!$B$5:$L$20,2,TRUE)&" "&VLOOKUP(C22,'Liste chauffeur'!$B$5:$L$20,3,TRUE) -> MADI BOINA Mkidachi | F22: =IF(ISBLANK('Feuille saisie'!M27)=TRUE,"",'Feuille saisie'!M27)
A23: ='Horaire samedi'!A27 -> VAHIBE | B23: ='Horaire samedi'!B27 -> 0.47916667 | C23: ='Horaire samedi'!C27 -> C9 | D23: =VLOOKUP(C23,'Liste chauffeur'!$B$5:$L$20,2,TRUE)&" "&VLOOKUP(C23,'Liste chauffeur'!$B$5:$L$20,3,TRUE) -> SANDI Maanrouf | F23: =IF(ISBLANK('Feuille saisie'!M28)=TRUE,"",'Feuille saisie'!M28)
A24: ='Horaire samedi'!A30 -> PASSAMAINTY | B24: ='Horaire samedi'!B30 -> 0.5 | C24: ='Horaire samedi'!C30 -> C9 | D24: =VLOOKUP(C24,'Liste chauffeur'!$B$5:$L$20,2,TRUE)&" "&VLOOKUP(C24,'Liste chauffeur'!$B$5:$L$20,3,TRUE) -> SANDI Maanrouf | F24: =IF(ISBLANK('Feuille saisie'!M29)=TRUE,"",'Feuille saisie'!M29)
A25: ='Horaire samedi'!A29 -> VAHIBE | B25: ='Horaire samedi'!B29 -> 0.5 | C25: ='Horaire samedi'!C29 -> C11 | D25: =VLOOKUP(C25,'Liste chauffeur'!$B$5:$L$20,2,TRUE)&" "&VLOOKUP(C25,'Liste chauffeur'!$B$5:$L$20,3,TRUE) -> MADI BOINA Mkidachi | F25: =IF(ISBLANK('Feuille saisie'!M30)=TRUE,"",'Feuille saisie'!M30) | I25: Signature Coordinateur 1 :
A26: ='Horaire samedi'!A32 -> PASSAMAINTY | B26: ='Horaire samedi'!B32 -> 0.52083333 | C26: ='Horaire samedi'!C32 -> C11 | D26: =VLOOKUP(C26,'Liste chauffeur'!$B$5:$L$20,2,TRUE)&" "&VLOOKUP(C26,'Liste chauffeur'!$B$5:$L$20,3,TRUE) -> MADI BOINA Mkidachi | F26: =IF(ISBLANK('Feuille saisie'!M31)=TRUE,"",'Feuille saisie'!M31)
A27: ='Horaire samedi'!A31 -> VAHIBE | B27: ='Horaire samedi'!B31 -> 0.52083333 | C27: ='Horaire samedi'!C31 -> C9 | D27: =VLOOKUP(C27,'Liste chauffeur'!$B$5:$L$20,2,TRUE)&" "&VLOOKUP(C27,'Liste chauffeur'!$B$5:$L$20,3,TRUE) -> SANDI Maanrouf
A28: ='Horaire samedi'!A34 -> PASSAMAINTY | B28: ='Horaire samedi'!B34 -> 0.54166667 | C28: ='Horaire samedi'!C34 -> C9 | D28: =VLOOKUP(C28,'Liste chauffeur'!$B$5:$L$20,2,TRUE)&" "&VLOOKUP(C28,'Liste chauffeur'!$B$5:$L$20,3,TRUE) -> SANDI Maanrouf | F28: =IF(ISBLANK('Feuille saisie'!M33)=TRUE,"",'Feuille saisie'!M33)
A29: ='Horaire samedi'!A33 -> VAHIBE | B29: ='Horaire samedi'!B33 -> 0.54166667 | C29: ='Horaire samedi'!C33 -> C11 | D29: =VLOOKUP(C29,'Liste chauffeur'!$B$5:$L$20,2,TRUE)&" "&VLOOKUP(C29,'Liste chauffeur'!$B$5:$L$20,3,TRUE) -> MADI BOINA Mkidachi | F29: =IF(ISBLANK('Feuille saisie'!M34)=TRUE,"",'Feuille saisie'!M34)
A30: ='Horaire samedi'!A36 -> PASSAMAINTY | B30: ='Horaire samedi'!B36 -> 0.5625 | C30: ='Horaire samedi'!C36 -> C10 | D30: =VLOOKUP(C30,'Liste chauffeur'!$B$5:$L$20,2,TRUE)&" "&VLOOKUP(C30,'Liste chauffeur'!$B$5:$L$20,3,TRUE) -> ISSIHAKA M'Changama | F30: =IF(ISBLANK('Feuille saisie'!M35)=TRUE,"",'Feuille saisie'!M35) | I30: Observations :
A31: ='Horaire samedi'!A35 -> VAHIBE | B31: ='Horaire samedi'!B35 -> 0.5625 | C31: ='Horaire samedi'!C35 -> C9 | D31: =VLOOKUP(C31,'Liste chauffeur'!$B$5:$L$20,2,TRUE)&" "&VLOOKUP(C31,'Liste chauffeur'!$B$5:$L$20,3,TRUE) -> SANDI Maanrouf | F31: =IF(ISBLANK('Feuille saisie'!M36)=TRUE,"",'Feuille saisie'!M36)
A32: ='Horaire samedi'!A38 -> PASSAMAINTY | B32: ='Horaire samedi'!B38 -> 0.58333333 | C32: ='Horaire samedi'!C38 -> C8 | D32: =VLOOKUP(C32,'Liste chauffeur'!$B$5:$L$20,2,TRUE)&" "&VLOOKUP(C32,'Liste chauffeur'!$B$5:$L$20,3,TRUE) -> HADHURAMI Makinedine | F32: =IF(ISBLANK('Feuille saisie'!M37)=TRUE,"",'Feuille saisie'!M37)
A33: ='Horaire samedi'!A37 -> VAHIBE | B33: ='Horaire samedi'!B37 -> 0.58333333 | C33: ='Horaire samedi'!C37 -> C10 | D33: =VLOOKUP(C33,'Liste chauffeur'!$B$5:$L$20,2,TRUE)&" "&VLOOKUP(C33,'Liste chauffeur'!$B$5:$L$20,3,TRUE) -> ISSIHAKA M'Changama | F33: =IF(ISBLANK('Feuille saisie'!M38)=TRUE,"",'Feuille saisie'!M38)
A34: ='Horaire samedi'!A40 -> PASSAMAINTY | B34: ='Horaire samedi'!B40 -> 0.60416667 | C34: ='Horaire samedi'!C40 -> C10 | D34: =VLOOKUP(C34,'Liste chauffeur'!$B$5:$L$20,2,TRUE)&" "&VLOOKUP(C34,'Liste chauffeur'!$B$5:$L$20,3,TRUE) -> ISSIHAKA M'Changama | F34: =IF(ISBLANK('Feuille saisie'!M39)=TRUE,"",'Feuille saisie'!M39)
A35: ='Horaire samedi'!A39 -> VAHIBE | B35: ='Horaire samedi'!B39 -> 0.60416667 | C35: ='Horaire samedi'!C39 -> C8 | D35: =VLOOKUP(C35,'Liste chauffeur'!$B$5:$L$20,2,TRUE)&" "&VLOOKUP(C35,'Liste chauffeur'!$B$5:$L$20,3,TRUE) -> HADHURAMI Makinedine | F35: =IF(ISBLANK('Feuille saisie'!M40)=TRUE,"",'Feuille saisie'!M40)
A36: ='Horaire samedi'!A42 -> PASSAMAINTY | B36: ='Horaire samedi'!B42 -> 0.625 | C36: ='Horaire samedi'!C42 -> C8 | D36: =VLOOKUP(C36,'Liste chauffeur'!$B$5:$L$20,2,TRUE)&" "&VLOOKUP(C36,'Liste chauffeur'!$B$5:$L$20,3,TRUE) -> HADHURAMI Makinedine | F36: =IF(ISBLANK('Feuille saisie'!M41)=TRUE,"",'Feuille saisie'!M41)
A37: ='Horaire samedi'!A41 -> VAHIBE | B37: ='Horaire samedi'!B41 -> 0.625 | C37: ='Horaire samedi'!C41 -> C10 | D37: =VLOOKUP(C37,'Liste chauffeur'!$B$5:$L$20,2,TRUE)&" "&VLOOKUP(C37,'Liste chauffeur'!$B$5:$L$20,3,TRUE) -> ISSIHAKA M'Changama | F37: =IF(ISBLANK('Feuille saisie'!M42)=TRUE,"",'Feuille saisie'!M42)
A38: ='Horaire samedi'!A44 -> PASSAMAINTY | B38: ='Horaire samedi'!B44 -> 0.64583333 | C38: ='Horaire samedi'!C44 -> C10 | D38: =VLOOKUP(C38,'Liste chauffeur'!$B$5:$L$20,2,TRUE)&" "&VLOOKUP(C38,'Liste chauffeur'!$B$5:$L$20,3,TRUE) -> ISSIHAKA M'Changama | F38: =IF(ISBLANK('Feuille saisie'!M43)=TRUE,"",'Feuille saisie'!M43)
A39: ='Horaire samedi'!A43 -> VAHIBE | B39: ='Horaire samedi'!B43 -> 0.64583333 | C39: ='Horaire samedi'!C43 -> C8 | D39: =VLOOKUP(C39,'Liste chauffeur'!$B$5:$L$20,2,TRUE)&" "&VLOOKUP(C39,'Liste chauffeur'!$B$5:$L$20,3,TRUE) -> HADHURAMI Makinedine | F39: =IF(ISBLANK('Feuille saisie'!M44)=TRUE,"",'Feuille saisie'!M44) | I39: Absences :
A40: ='Horaire samedi'!A46 -> PASSAMAINTY | B40: ='Horaire samedi'!B46 -> 0.66666667 | C40: ='Horaire samedi'!C46 -> C8 | D40: =VLOOKUP(C40,'Liste chauffeur'!$B$5:$L$20,2,TRUE)&" "&VLOOKUP(C40,'Liste chauffeur'!$B$5:$L$20,3,TRUE) -> HADHURAMI Makinedine | F40: =IF(ISBLANK('Feuille saisie'!M45)=TRUE,"",'Feuille saisie'!M45)
A41: ='Horaire samedi'!A45 -> VAHIBE | B41: ='Horaire samedi'!B45 -> 0.66666667 | C41: ='Horaire samedi'!C45 -> C10 | D41: =VLOOKUP(C41,'Liste chauffeur'!$B$5:$L$20,2,TRUE)&" "&VLOOKUP(C41,'Liste chauffeur'!$B$5:$L$20,3,TRUE) -> ISSIHAKA M'Changama | F41: =IF(ISBLANK('Feuille saisie'!M46)=TRUE,"",'Feuille saisie'!M46)
A42: ='Horaire samedi'!A48 -> PASSAMAINTY | B42: ='Horaire samedi'!B48 -> 0.6875 | C42: ='Horaire samedi'!C48 -> C10 | D42: =VLOOKUP(C42,'Liste chauffeur'!$B$5:$L$20,2,TRUE)&" "&VLOOKUP(C42,'Liste chauffeur'!$B$5:$L$20,3,TRUE) -> ISSIHAKA M'Changama | F42: =IF(ISBLANK('Feuille saisie'!M47)=TRUE,"",'Feuille saisie'!M47)
A43: ='Horaire samedi'!A47 -> VAHIBE | B43: ='Horaire samedi'!B47 -> 0.6875 | C43: ='Horaire samedi'!C47 -> C8 | D43: =VLOOKUP(C43,'Liste chauffeur'!$B$5:$L$20,2,TRUE)&" "&VLOOKUP(C43,'Liste chauffeur'!$B$5:$L$20,3,TRUE) -> HADHURAMI Makinedine | F43: =IF(ISBLANK('Feuille saisie'!M48)=TRUE,"",'Feuille saisie'!M48) | I43: Trajets non effectués :
A44: ='Horaire samedi'!A50 -> PASSAMAINTY | B44: ='Horaire samedi'!B50 -> 0.70833333 | C44: ='Horaire samedi'!C50 -> C8 | D44: =VLOOKUP(C44,'Liste chauffeur'!$B$5:$L$20,2,TRUE)&" "&VLOOKUP(C44,'Liste chauffeur'!$B$5:$L$20,3,TRUE) -> HADHURAMI Makinedine | F44: =IF(ISBLANK('Feuille saisie'!M49)=TRUE,"",'Feuille saisie'!M49)
A45: ='Horaire samedi'!A49 -> VAHIBE | B45: ='Horaire samedi'!B49 -> 0.70833333 | C45: ='Horaire samedi'!C49 -> C10 | D45: =VLOOKUP(C45,'Liste chauffeur'!$B$5:$L$20,2,TRUE)&" "&VLOOKUP(C45,'Liste chauffeur'!$B$5:$L$20,3,TRUE) -> ISSIHAKA M'Changama | F45: =IF(ISBLANK('Feuille saisie'!M50)=TRUE,"",'Feuille saisie'!M50)
A46: ='Horaire samedi'!A52 -> PASSAMAINTY | B46: ='Horaire samedi'!B52 -> 0.72916667 | C46: ='Horaire samedi'!C52 -> C10 | D46: =VLOOKUP(C46,'Liste chauffeur'!$B$5:$L$20,2,TRUE)&" "&VLOOKUP(C46,'Liste chauffeur'!$B$5:$L$20,3,TRUE) -> ISSIHAKA M'Changama | F46: =IF(ISBLANK('Feuille saisie'!M51)=TRUE,"",'Feuille saisie'!M51)
A47: ='Horaire samedi'!A51 -> VAHIBE | B47: ='Horaire samedi'!B51 -> 0.72916667 | C47: ='Horaire samedi'!C51 -> C8 | D47: =VLOOKUP(C47,'Liste chauffeur'!$B$5:$L$20,2,TRUE)&" "&VLOOKUP(C47,'Liste chauffeur'!$B$5:$L$20,3,TRUE) -> HADHURAMI Makinedine | F47: =IF(ISBLANK('Feuille saisie'!M52)=TRUE,"",'Feuille saisie'!M52)
A48: ='Horaire samedi'!A54 -> PASSAMAINTY | B48: ='Horaire samedi'!B54 -> 0.75 | C48: ='Horaire samedi'!C54 -> C8 | D48: =VLOOKUP(C48,'Liste chauffeur'!$B$5:$L$20,2,TRUE)&" "&VLOOKUP(C48,'Liste chauffeur'!$B$5:$L$20,3,TRUE) -> HADHURAMI Makinedine | F48: =IF(ISBLANK('Feuille saisie'!M53)=TRUE,"",'Feuille saisie'!M53)
A49: ='Horaire samedi'!A53 -> VAHIBE | B49: ='Horaire samedi'!B53 -> 0.75 | C49: ='Horaire samedi'!C53 -> C10 | D49: =VLOOKUP(C49,'Liste chauffeur'!$B$5:$L$20,2,TRUE)&" "&VLOOKUP(C49,'Liste chauffeur'!$B$5:$L$20,3,TRUE) -> ISSIHAKA M'Changama | F49: =IF(ISBLANK('Feuille saisie'!M54)=TRUE,"",'Feuille saisie'!M54)

Sheet coordinateur dimanche1
A1: COORDINATEUR LIGNE 4 NAVETTES CARIBUS MARS 2026 (DIMANCHE 1) | F1: {='coordinateur matin'!F1:F1} -> 46143 | I1: NOM COORDINATEUR
A2: Depart | B2: Heure théorique départ | C2: Type chauffeur prévu | D2: Nom chauffeur prévu | E2: Astreinte | F2: Nom Chauffeur réel ( si différent) | G2: Heure réelle départ | H2: Nbre personnes montantes
A3: ='Horaire dimanche1'!A8 -> VAHIBE | B3: ='Horaire dimanche1'!B8 -> 0.33333333 | C3: ='Horaire dimanche1'!C8 -> C5 | D3: =VLOOKUP(C3,'Liste chauffeur'!$B$5:$L$20,2,TRUE)&" "&VLOOKUP(C3,'Liste chauffeur'!$B$5:$L$20,3,TRUE) -> AHAMADI Bacar Raenmouddine
A4: ='Horaire dimanche1'!A9 -> PASSAMAINTY | B4: ='Horaire dimanche1'!B9 -> 0.35416667 | C4: ='Horaire dimanche1'!C9 -> C5 | D4: =VLOOKUP(C4,'Liste chauffeur'!$B$5:$L$20,2,TRUE)&" "&VLOOKUP(C4,'Liste chauffeur'!$B$5:$L$20,3,TRUE) -> AHAMADI Bacar Raenmouddine | I4: Observations :
A5: ='Horaire dimanche1'!A10 -> VAHIBE | B5: ='Horaire dimanche1'!B10 -> 0.375 | C5: ='Horaire dimanche1'!C10 -> C5 | D5: =VLOOKUP(C5,'Liste chauffeur'!$B$5:$L$20,2,TRUE)&" "&VLOOKUP(C5,'Liste chauffeur'!$B$5:$L$20,3,TRUE) -> AHAMADI Bacar Raenmouddine
A6: ='Horaire dimanche1'!A11 -> PASSAMAINTY | B6: ='Horaire dimanche1'!B11 -> 0.39583333 | C6: ='Horaire dimanche1'!C11 -> C5 | D6: =VLOOKUP(C6,'Liste chauffeur'!$B$5:$L$20,2,TRUE)&" "&VLOOKUP(C6,'Liste chauffeur'!$B$5:$L$20,3,TRUE) -> AHAMADI Bacar Raenmouddine | I6: Absences :
A7: ='Horaire dimanche1'!A12 -> VAHIBE | B7: ='Horaire dimanche1'!B12 -> 0.41666667 | C7: ='Horaire dimanche1'!C12 -> C5 | D7: =VLOOKUP(C7,'Liste chauffeur'!$B$5:$L$20,2,TRUE)&" "&VLOOKUP(C7,'Liste chauffeur'!$B$5:$L$20,3,TRUE) -> AHAMADI Bacar Raenmouddine | F7: =IF(ISBLANK('Feuille saisie'!M12)=TRUE,"",'Feuille saisie'!M12)
A8: ='Horaire dimanche1'!A13 -> PASSAMAINTY | B8: ='Horaire dimanche1'!B13 -> 0.4375 | C8: ='Horaire dimanche1'!C13 -> C5 | D8: =VLOOKUP(C8,'Liste chauffeur'!$B$5:$L$20,2,TRUE)&" "&VLOOKUP(C8,'Liste chauffeur'!$B$5:$L$20,3,TRUE) -> AHAMADI Bacar Raenmouddine | F8: =IF(ISBLANK('Feuille saisie'!M13)=TRUE,"",'Feuille saisie'!M13)
A9: ='Horaire dimanche1'!A14 -> VAHIBE | B9: ='Horaire dimanche1'!B14 -> 0.45833333 | C9: ='Horaire dimanche1'!C14 -> C5 | D9: =VLOOKUP(C9,'Liste chauffeur'!$B$5:$L$20,2,TRUE)&" "&VLOOKUP(C9,'Liste chauffeur'!$B$5:$L$20,3,TRUE) -> AHAMADI Bacar Raenmouddine | F9: =IF(ISBLANK('Feuille saisie'!M14)=TRUE,"",'Feuille saisie'!M14) | I9: Trajets non effectués :
A10: ='Horaire dimanche1'!A15 -> PASSAMAINTY | B10: ='Horaire dimanche1'!B15 -> 0.47916667 | C10: ='Horaire dimanche1'!C15 -> C5 | D10: =VLOOKUP(C10,'Liste chauffeur'!$B$5:$L$20,2,TRUE)&" "&VLOOKUP(C10,'Liste chauffeur'!$B$5:$L$20,3,TRUE) -> AHAMADI Bacar Raenmouddine | F10: =IF(ISBLANK('Feuille saisie'!M15)=TRUE,"",'Feuille saisie'!M15)
A11: ='Horaire dimanche1'!A16 -> VAHIBE | B11: ='Horaire dimanche1'!B16 -> 0.5 | C11: ='Horaire dimanche1'!C16 -> C5 | D11: =VLOOKUP(C11,'Liste chauffeur'!$B$5:$L$20,2,TRUE)&" "&VLOOKUP(C11,'Liste chauffeur'!$B$5:$L$20,3,TRUE) -> AHAMADI Bacar Raenmouddine | F11: =IF(ISBLANK('Feuille saisie'!M16)=TRUE,"",'Feuille saisie'!M16) | I11: Signature Coordinateur 1 :
A12: ='Horaire dimanche1'!A17 -> PASSAMAINTY | B12: ='Horaire dimanche1'!B17 -> 0.52083333 | C12: ='Horaire dimanche1'!C17 -> C5 | D12: =VLOOKUP(C12,'Liste chauffeur'!$B$5:$L$20,2,TRUE)&" "&VLOOKUP(C12,'Liste chauffeur'!$B$5:$L$20,3,TRUE) -> AHAMADI Bacar Raenmouddine | F12: =IF(ISBLANK('Feuille saisie'!M17)=TRUE,"",'Feuille saisie'!M17)
A13: ='Horaire dimanche1'!A18 -> VAHIBE | B13: ='Horaire dimanche1'!B18 -> 0.54166667 | C13: ='Horaire dimanche1'!C18 -> C5 | D13: =VLOOKUP(C13,'Liste chauffeur'!$B$5:$L$20,2,TRUE)&" "&VLOOKUP(C13,'Liste chauffeur'!$B$5:$L$20,3,TRUE) -> AHAMADI Bacar Raenmouddine
A14: ='Horaire dimanche1'!A19 -> PASSAMAINTY | B14: ='Horaire dimanche1'!B19 -> 0.5625 | C14: ='Horaire dimanche1'!C19 -> C5 | D14: =VLOOKUP(C14,'Liste chauffeur'!$B$5:$L$20,2,TRUE)&" "&VLOOKUP(C14,'Liste chauffeur'!$B$5:$L$20,3,TRUE) -> AHAMADI Bacar Raenmouddine | F14: =IF(ISBLANK('Feuille saisie'!M19)=TRUE,"",'Feuille saisie'!M19) | I14: Observations :
A15: ='Horaire dimanche1'!A20 -> VAHIBE | B15: ='Horaire dimanche1'!B20 -> 0.58333333 | C15: ='Horaire dimanche1'!C20 -> C8 | D15: =VLOOKUP(C15,'Liste chauffeur'!$B$5:$L$20,2,TRUE)&" "&VLOOKUP(C15,'Liste chauffeur'!$B$5:$L$20,3,TRUE) -> HADHURAMI Makinedine | F15: =IF(ISBLANK('Feuille saisie'!M20)=TRUE,"",'Feuille saisie'!M20)
A16: ='Horaire dimanche1'!A21 -> PASSAMAINTY | B16: ='Horaire dimanche1'!B21 -> 0.60416667 | C16: ='Horaire dimanche1'!C21 -> C8 | D16: =VLOOKUP(C16,'Liste chauffeur'!$B$5:$L$20,2,TRUE)&" "&VLOOKUP(C16,'Liste chauffeur'!$B$5:$L$20,3,TRUE) -> HADHURAMI Makinedine | F16: =IF(ISBLANK('Feuille saisie'!M21)=TRUE,"",'Feuille saisie'!M21) | I16: Absences :
A17: ='Horaire dimanche1'!A22 -> VAHIBE | B17: ='Horaire dimanche1'!B22 -> 0.625 | C17: ='Horaire dimanche1'!C22 -> C8 | D17: =VLOOKUP(C17,'Liste chauffeur'!$B$5:$L$20,2,TRUE)&" "&VLOOKUP(C17,'Liste chauffeur'!$B$5:$L$20,3,TRUE) -> HADHURAMI Makinedine | F17: =IF(ISBLANK('Feuille saisie'!M22)=TRUE,"",'Feuille saisie'!M22)
A18: ='Horaire dimanche1'!A23 -> PASSAMAINTY | B18: ='Horaire dimanche1'!B23 -> 0.64583333 | C18: ='Horaire dimanche1'!C23 -> C8 | D18: =VLOOKUP(C18,'Liste chauffeur'!$B$5:$L$20,2,TRUE)&" "&VLOOKUP(C18,'Liste chauffeur'!$B$5:$L$20,3,TRUE) -> HADHURAMI Makinedine | F18: =IF(ISBLANK('Feuille saisie'!M23)=TRUE,"",'Feuille saisie'!M23)
A19: ='Horaire dimanche1'!A24 -> VAHIBE | B19: ='Horaire dimanche1'!B24 -> 0.66666667 | C19: ='Horaire dimanche1'!C24 -> C8 | D19: =VLOOKUP(C19,'Liste chauffeur'!$B$5:$L$20,2,TRUE)&" "&VLOOKUP(C19,'Liste chauffeur'!$B$5:$L$20,3,TRUE) -> HADHURAMI Makinedine | F19: =IF(ISBLANK('Feuille saisie'!M24)=TRUE,"",'Feuille saisie'!M24) | I19: Trajets non effectués :
A20: ='Horaire dimanche1'!A25 -> PASSAMAINTY | B20: ='Horaire dimanche1'!B25 -> 0.6875 | C20: ='Horaire dimanche1'!C25 -> C8 | D20: =VLOOKUP(C20,'Liste chauffeur'!$B$5:$L$20,2,TRUE)&" "&VLOOKUP(C20,'Liste chauffeur'!$B$5:$L$20,3,TRUE) -> HADHURAMI Makinedine
A21: ='Horaire dimanche1'!A26 -> VAHIBE | B21: ='Horaire dimanche1'!B26 -> 0.70833333 | C21: ='Horaire dimanche1'!C26 -> C8 | D21: =VLOOKUP(C21,'Liste chauffeur'!$B$5:$L$20,2,TRUE)&" "&VLOOKUP(C21,'Liste chauffeur'!$B$5:$L$20,3,TRUE) -> HADHURAMI Makinedine | F21: =IF(ISBLANK('Feuille saisie'!M26)=TRUE,"",'Feuille saisie'!M26) | I21: Signature Coordinateur 1 :
A22: ='Horaire dimanche1'!A27 -> PASSAMAINTY | B22: ='Horaire dimanche1'!B27 -> 0.72222222 | C22: ='Horaire dimanche1'!C27 -> C8 | D22: =VLOOKUP(C22,'Liste chauffeur'!$B$5:$L$20,2,TRUE)&" "&VLOOKUP(C22,'Liste chauffeur'!$B$5:$L$20,3,TRUE) -> HADHURAMI Makinedine | F22: =IF(ISBLANK('Feuille saisie'!M27)=TRUE,"",'Feuille saisie'!M27)
A23: ='Horaire dimanche1'!A28 -> VAHIBE | B23: ='Horaire dimanche1'!B28 -> 0.74305556 | C23: ='Horaire dimanche1'!C28 -> C8 | D23: =VLOOKUP(C23,'Liste chauffeur'!$B$5:$L$20,2,TRUE)&" "&VLOOKUP(C23,'Liste chauffeur'!$B$5:$L$20,3,TRUE) -> HADHURAMI Makinedine | F23: =IF(ISBLANK('Feuille saisie'!M28)=TRUE,"",'Feuille saisie'!M28)
A24: ='Horaire dimanche1'!A29 -> PASSAMAINTY | B24: ='Horaire dimanche1'!B29 -> 0.75694444 | C24: ='Horaire dimanche1'!C29 -> C8 | D24: =VLOOKUP(C24,'Liste chauffeur'!$B$5:$L$20,2,TRUE)&" "&VLOOKUP(C24,'Liste chauffeur'!$B$5:$L$20,3,TRUE) -> HADHURAMI Makinedine | F24: =IF(ISBLANK('Feuille saisie'!M29)=TRUE,"",'Feuille saisie'!M29)

Sheet coordinateur dimanche2
A1: COORDINATEUR MATIN LIGNE 4 NAVETTES CARIBUS MARS 2026 (DIMANCHE 2) | I1: NOM COORDINATEUR
A2: Depart | B2: Heure théorique départ | C2: Type chauffeur prévu | D2: Nom chauffeur prévu | E2: Astreinte | F2: Nom Chauffeur réel ( si différent) | G2: Heure réelle départ | H2: Nbre personnes montantes
A3: ='Horaire dimanche2'!A8 -> VAHIBE | B3: ='Horaire dimanche2'!B8 -> 0.33333333 | C3: ='Horaire dimanche2'!C8 -> C10 | D3: =VLOOKUP(C3,'Liste chauffeur'!$B$5:$L$20,2,TRUE)&" "&VLOOKUP(C3,'Liste chauffeur'!$B$5:$L$20,3,TRUE) -> ISSIHAKA M'Changama
A4: ='Horaire dimanche2'!A9 -> PASSAMAINTY | B4: ='Horaire dimanche2'!B9 -> 0.35416667 | C4: ='Horaire dimanche2'!C9 -> C10 | D4: =VLOOKUP(C4,'Liste chauffeur'!$B$5:$L$20,2,TRUE)&" "&VLOOKUP(C4,'Liste chauffeur'!$B$5:$L$20,3,TRUE) -> ISSIHAKA M'Changama | I4: Observations :
A5: ='Horaire dimanche2'!A10 -> VAHIBE | B5: ='Horaire dimanche2'!B10 -> 0.375 | C5: ='Horaire dimanche2'!C10 -> C10 | D5: =VLOOKUP(C5,'Liste chauffeur'!$B$5:$L$20,2,TRUE)&" "&VLOOKUP(C5,'Liste chauffeur'!$B$5:$L$20,3,TRUE) -> ISSIHAKA M'Changama
A6: ='Horaire dimanche2'!A11 -> PASSAMAINTY | B6: ='Horaire dimanche2'!B11 -> 0.39583333 | C6: ='Horaire dimanche2'!C11 -> C10 | D6: =VLOOKUP(C6,'Liste chauffeur'!$B$5:$L$20,2,TRUE)&" "&VLOOKUP(C6,'Liste chauffeur'!$B$5:$L$20,3,TRUE) -> ISSIHAKA M'Changama | I6: Absences :
A7: ='Horaire dimanche2'!A12 -> VAHIBE | B7: ='Horaire dimanche2'!B12 -> 0.41666667 | C7: ='Horaire dimanche2'!C12 -> C10 | D7: =VLOOKUP(C7,'Liste chauffeur'!$B$5:$L$20,2,TRUE)&" "&VLOOKUP(C7,'Liste chauffeur'!$B$5:$L$20,3,TRUE) -> ISSIHAKA M'Changama | F7: =IF(ISBLANK('Feuille saisie'!M12)=TRUE,"",'Feuille saisie'!M12)
A8: ='Horaire dimanche2'!A13 -> PASSAMAINTY | B8: ='Horaire dimanche2'!B13 -> 0.4375 | C8: ='Horaire dimanche2'!C13 -> C10 | D8: =VLOOKUP(C8,'Liste chauffeur'!$B$5:$L$20,2,TRUE)&" "&VLOOKUP(C8,'Liste chauffeur'!$B$5:$L$20,3,TRUE) -> ISSIHAKA M'Changama | F8: =IF(ISBLANK('Feuille saisie'!M13)=TRUE,"",'Feuille saisie'!M13)
A9: ='Horaire dimanche2'!A14 -> VAHIBE | B9: ='Horaire dimanche2'!B14 -> 0.45833333 | C9: ='Horaire dimanche2'!C14 -> C10 | D9: =VLOOKUP(C9,'Liste chauffeur'!$B$5:$L$20,2,TRUE)&" "&VLOOKUP(C9,'Liste chauffeur'!$B$5:$L$20,3,TRUE) -> ISSIHAKA M'Changama | F9: =IF(ISBLANK('Feuille saisie'!M14)=TRUE,"",'Feuille saisie'!M14) | I9: Trajets non effectués :
A10: ='Horaire dimanche2'!A15 -> PASSAMAINTY | B10: ='Horaire dimanche2'!B15 -> 0.47916667 | C10: ='Horaire dimanche2'!C15 -> C10 | D10: =VLOOKUP(C10,'Liste chauffeur'!$B$5:$L$20,2,TRUE)&" "&VLOOKUP(C10,'Liste chauffeur'!$B$5:$L$20,3,TRUE) -> ISSIHAKA M'Changama | F10: =IF(ISBLANK('Feuille saisie'!M15)=TRUE,"",'Feuille saisie'!M15)
A11: ='Horaire dimanche2'!A16 -> VAHIBE | B11: ='Horaire dimanche2'!B16 -> 0.5 | C11: ='Horaire dimanche2'!C16 -> C10 | D11: =VLOOKUP(C11,'Liste chauffeur'!$B$5:$L$20,2,TRUE)&" "&VLOOKUP(C11,'Liste chauffeur'!$B$5:$L$20,3,TRUE) -> ISSIHAKA M'Changama | F11: =IF(ISBLANK('Feuille saisie'!M16)=TRUE,"",'Feuille saisie'!M16) | I11: Signature Coordinateur 1 :
A12: ='Horaire dimanche2'!A17 -> PASSAMAINTY | B12: ='Horaire dimanche2'!B17 -> 0.52083333 | C12: ='Horaire dimanche2'!C17 -> C10 | D12: =VLOOKUP(C12,'Liste chauffeur'!$B$5:$L$20,2,TRUE)&" "&VLOOKUP(C12,'Liste chauffeur'!$B$5:$L$20,3,TRUE) -> ISSIHAKA M'Changama | F12: =IF(ISBLANK('Feuille saisie'!M17)=TRUE,"",'Feuille saisie'!M17)
A13: ='Horaire dimanche2'!A18 -> VAHIBE | B13: ='Horaire dimanche2'!B18 -> 0.54166667 | C13: ='Horaire dimanche2'!C18 -> C10 | D13: =VLOOKUP(C13,'Liste chauffeur'!$B$5:$L$20,2,TRUE)&" "&VLOOKUP(C13,'Liste chauffeur'!$B$5:$L$20,3,TRUE) -> ISSIHAKA M'Changama
A14: ='Horaire dimanche2'!A19 -> PASSAMAINTY | B14: ='Horaire dimanche2'!B19 -> 0.5625 | C14: ='Horaire dimanche2'!C19 -> C10 | D14: =VLOOKUP(C14,'Liste chauffeur'!$B$5:$L$20,2,TRUE)&" "&VLOOKUP(C14,'Liste chauffeur'!$B$5:$L$20,3,TRUE) -> ISSIHAKA M'Changama | F14: =IF(ISBLANK('Feuille saisie'!M19)=TRUE,"",'Feuille saisie'!M19) | I14: Observations :
A15: ='Horaire dimanche2'!A20 -> VAHIBE | B15: ='Horaire dimanche2'!B20 -> 0.58333333 | C15: ='Horaire dimanche2'!C20 -> C15 | D15: =VLOOKUP(C15,'Liste chauffeur'!$B$5:$L$20,2,TRUE)&" "&VLOOKUP(C15,'Liste chauffeur'!$B$5:$L$20,3,TRUE) -> HAMADA Babou | F15: =IF(ISBLANK('Feuille saisie'!M20)=TRUE,"",'Feuille saisie'!M20)
A16: ='Horaire dimanche2'!A21 -> PASSAMAINTY | B16: ='Horaire dimanche2'!B21 -> 0.60416667 | C16: ='Horaire dimanche2'!C21 -> C15 | D16: =VLOOKUP(C16,'Liste chauffeur'!$B$5:$L$20,2,TRUE)&" "&VLOOKUP(C16,'Liste chauffeur'!$B$5:$L$20,3,TRUE) -> HAMADA Babou | F16: =IF(ISBLANK('Feuille saisie'!M21)=TRUE,"",'Feuille saisie'!M21) | I16: Absences :
A17: ='Horaire dimanche2'!A22 -> VAHIBE | B17: ='Horaire dimanche2'!B22 -> 0.625 | C17: ='Horaire dimanche2'!C22 -> C15 | D17: =VLOOKUP(C17,'Liste chauffeur'!$B$5:$L$20,2,TRUE)&" "&VLOOKUP(C17,'Liste chauffeur'!$B$5:$L$20,3,TRUE) -> HAMADA Babou | F17: =IF(ISBLANK('Feuille saisie'!M22)=TRUE,"",'Feuille saisie'!M22)
A18: ='Horaire dimanche2'!A23 -> PASSAMAINTY | B18: ='Horaire dimanche2'!B23 -> 0.64583333 | C18: ='Horaire dimanche2'!C23 -> C15 | D18: =VLOOKUP(C18,'Liste chauffeur'!$B$5:$L$20,2,TRUE)&" "&VLOOKUP(C18,'Liste chauffeur'!$B$5:$L$20,3,TRUE) -> HAMADA Babou | F18: =IF(ISBLANK('Feuille saisie'!M23)=TRUE,"",'Feuille saisie'!M23)
A19: ='Horaire dimanche2'!A24 -> VAHIBE | B19: ='Horaire dimanche2'!B24 -> 0.66666667 | C19: ='Horaire dimanche2'!C24 -> C15 | D19: =VLOOKUP(C19,'Liste chauffeur'!$B$5:$L$20,2,TRUE)&" "&VLOOKUP(C19,'Liste chauffeur'!$B$5:$L$20,3,TRUE) -> HAMADA Babou | F19: =IF(ISBLANK('Feuille saisie'!M24)=TRUE,"",'Feuille saisie'!M24) | I19: Trajets non effectués :
A20: ='Horaire dimanche2'!A25 -> PASSAMAINTY | B20: ='Horaire dimanche2'!B25 -> 0.6875 | C20: ='Horaire dimanche2'!C25 -> C15 | D20: =VLOOKUP(C20,'Liste chauffeur'!$B$5:$L$20,2,TRUE)&" "&VLOOKUP(C20,'Liste chauffeur'!$B$5:$L$20,3,TRUE) -> HAMADA Babou
A21: ='Horaire dimanche2'!A26 -> VAHIBE | B21: ='Horaire dimanche2'!B26 -> 0.70833333 | C21: ='Horaire dimanche2'!C26 -> C15 | D21: =VLOOKUP(C21,'Liste chauffeur'!$B$5:$L$20,2,TRUE)&" "&VLOOKUP(C21,'Liste chauffeur'!$B$5:$L$20,3,TRUE) -> HAMADA Babou | F21: =IF(ISBLANK('Feuille saisie'!M26)=TRUE,"",'Feuille saisie'!M26) | I21: Signature Coordinateur 1 :
A22: ='Horaire dimanche2'!A27 -> PASSAMAINTY | B22: ='Horaire dimanche2'!B27 -> 0.72222222 | C22: ='Horaire dimanche2'!C27 -> C15 | D22: =VLOOKUP(C22,'Liste chauffeur'!$B$5:$L$20,2,TRUE)&" "&VLOOKUP(C22,'Liste chauffeur'!$B$5:$L$20,3,TRUE) -> HAMADA Babou | F22: =IF(ISBLANK('Feuille saisie'!M27)=TRUE,"",'Feuille saisie'!M27)
A23: ='Horaire dimanche2'!A28 -> VAHIBE | B23: ='Horaire dimanche2'!B28 -> 0.74305556 | C23: ='Horaire dimanche2'!C28 -> C15 | D23: =VLOOKUP(C23,'Liste chauffeur'!$B$5:$L$20,2,TRUE)&" "&VLOOKUP(C23,'Liste chauffeur'!$B$5:$L$20,3,TRUE) -> HAMADA Babou | F23: =IF(ISBLANK('Feuille saisie'!M28)=TRUE,"",'Feuille saisie'!M28)
A24: ='Horaire dimanche2'!A29 -> PASSAMAINTY | B24: ='Horaire dimanche2'!B29 -> 0.75694444 | C24: ='Horaire dimanche2'!C29 -> C15 | D24: =VLOOKUP(C24,'Liste chauffeur'!$B$5:$L$20,2,TRUE)&" "&VLOOKUP(C24,'Liste chauffeur'!$B$5:$L$20,3,TRUE) -> HAMADA Babou | F24: =IF(ISBLANK('Feuille saisie'!M29)=TRUE,"",'Feuille saisie'!M29)

Sheet Liste chauffeur
D2: LISTE DES INTERVENANTS SUR LA LIGNE 4
B4: Type chauffeur | C4: Nom chauffeur | D4: Prénom Chauffeur | E4: N° telephone | F4: Mail | G4: SIRET | H4: Secteur | I4: N° Licence | J4: N° Carte conducteur | K4: Validité carte conducteur | L4: N° immatriculation | M4: Date première immatriculation | N4: Capacité | O4: Modalité facturation
A5: n | B5: C1 | C5: EL ANZIZE SALIM | D5: Hamada | E5: 0639 22 81 28 | F5: elsalimhamada@hotmail.com | G5: 024 076 531 00011 | H5: Mamoudzou | I5: 976_M_209 | J5: 413 | K5: 46877 | L5: GM_515_YL | M5: 45012 | N5: 9 | O5: Journée
B6: C10 | C6: ISSIHAKA | D6: M'Changama | E6: 639277141 | G6: 750529018 | H6: Mamoudzou | I6: 976-M-247 | J6: 66 | K6: 46135 | L6: GM-253-PW | M6: 44994 | N6: 9 | O6: Journée
B7: C11 | C7: MADI BOINA | D7: Mkidachi | E7: 0639 22 08 67 | F7: madiboinamkidachi@hotmail.com | G7: 500 793 526 00012 | H7: NORD | I7: 976-N-63 | J7: 985 | K7: 44456 | L7: GS-501-ZK | M7: 45273 | N7: 9 | O7: Journée
B8: C12 | C8: ALILOIFFA | D8: Said Siradj | E8: 639391517 | F8: tpm.aliloiffa@gmail.com | G8: 024 084 527 00043 | H8: Mamoudzou Centre Sud | I8: 976-C-006 | J8: 525 | K8: 46731 | L8: GS-608-GG | M8: 45238 | N8: 9 | O8: Trajet
A9: n | B9: C13 | C9: ABDALLAH | D9: Ben (Taxi Vanille) | E9: 639634834 | L9: WW-661-KR | M9: 46082 | N9: 9 | O9: Trajet
B10: C14 | C10: KAMARDINE | D10: Mansour | E10: 639211543 | I10: 976-N-261 | J10: 585 | L10: WW-629-KR | M10: 46081 | O10: Trajet
B11: C15 | C11: KAMARDINE | D11: Mansour (Salarié)
B12: C15 | C12: HAMADA | D12: Babou | E12: 639217270
A13: n | B13: C2 | C13: BINA HALADI | D13: Bina | E13: 0639 06 05 82 | F13: wonamaore@gmail.com | G13: 853 690 428 000 18 | H13: Sud | I13: 976-S-045 | J13: 1414 | K13: 45181 | L13: WW-654-KR | M13: 44581 | N13: 9 | O13: Journée
B14: C3 | C14: ABDOU MINIHADJI | D14: Amada | E14: 0639 65 03 93 | F14: abdouminihadjiamada@hotmail.com | G14: 066 311 101 000 19 | H14: Centre Sud | I14: 976-CS-057 | J14: 505 | K14: 45305 | L14: FY-654-BF | M14: 44279 | N14: 9 | O14: Journée
A15: n | B15: C4 | C15: TOUMBOU | D15: Toibourani | E15: 0639 19 14 22 | F15: toumboutoibourani@outlook.fr / anlia.toumbou97620@gmail.com | G15: 024 054 710 000 25 | H15: Mamoudzou | I15: 976-M-177 | J15: 357 | K15: 45028 | L15: GF_215_AQ | M15: 44624 | N15: 9 | O15: Journée
B16: C5 | C16: AHAMADI Bacar | D16: Raenmouddine | E16: 0639024054 | F16: ahamadi.rahim@gmail.com | G16: 499 252 468 00032 | H16: Mamoudzou | I16: 976-MD-207 | J16: 49 | K16: 47657 | L16: HC-007-YA | M16: 45755 | N16: 9 | O16: Journée
B17: C6 | C17: OUSSENI | D17: Soula | E17: 0639 69 03 87 | F17: soulaousseni415@gmail.com | G17: 066 307 372 000 12 | H17: Centre NORD | I17: 976-CN-003 | J17: 249 | K17: 43132 | L17: GP_813_HX | M17: 45083 | N17: 9 | O17: Journée
A18: n | B18: C7 | C18: HAMIDOU | D18: Dahalani | E18: 0639978304 | F18: kaquicha.habiba.assia@gmail.com | G18: 89891536800010 | H18: Mamoudzou | I18: 976-MD-233 | J18: 1126 | K18: 45966 | L18: EB-387-HJ | M18: 42474 | O18: Journée
A19: n | B19: C8 | C19: HADHURAMI | D19: Makinedine | E19: 0639 94 46 40 | F19: Hadhuramimakinedine976@gmail.com | G19: 054 397 211 00019 | H19: SUD | I19: 976_S_069 | J19: 150 | K19: 45874 | L19: FZ-411-ZD | M19: 44362 | N19: 9 | O19: Journée
B20: C9 | C20: SANDI | D20: Maanrouf | E20: 0639 40 58 85 | F20: maanroufsandi@laposte.net | G20: 024 069 635 000 19 | H20: Sud | I20: 976-S-006 | J20: 1184 | K20: 45262 | L20: GW-255-NY | M20: 45406 | N20: 9 | O20: Journée
B21: D9 | C21: RENEE | D21: Assanati | E21: 0639 07 82 51 | G21: 024 065 633 000 18 | H21: NORD | I21: 976-N-032 | J21: 1337 | K21: 45235 | L21: GR-921-XZ
B22: D14 | C22: AHAMADI | D22: Laydine | E22: 639585187 | F22: ahamadilaydine@gmail.com | G22: 79468048800018 | H22: Mamoudzou Centre Nord | I22: 976-M-422 976-CN-030 | J22: 1119 | K22: 46735 | L22: WW-620-KR
B23: Coordinateur matin | C23: ALLAOUI | D23: Soibrane | E23: 639653182 | I23: 976-M-079 | J23: 806 | L23: FZ-148-HW | M23: 44336
B24: Coordinateur PM | C24: EL ANZIZE SALIM | D24: Hamada | E24: 0639 22 81 28 | F24: elsalimhamada@hotmail.com | G24: 024 076 531 00011 | H24: Mamoudzou | I24: 976_M_209 | J24: 413 | K24: 46877 | L24: GM_515_YL | M24: 45012
B25: Coordinateur Samedi et dimanche matin | C25: TOUMBOU | D25: Toibranne | E25: 0639 19 14 22 | F25: toumboutoibourani@outlook.fr / anlia.toumbou97620@gmail.com | G25: 024 054 710 000 25 | H25: Mamoudzou | I25: 976-M-177 | J25: 357 | K25: 45028 | L25: GF_215_AQ | M25: 44624
B26: Coordinateur Samedi PM | C26: EL ANZIZE SALIM | D26: Hamada | E26: 0639 22 81 28 | F26: elsalimhamada@hotmail.com | G26: 024 076 531 00011 | H26: Mamoudzou | I26: 976_M_209 | J26: 413 | K26: 46877 | L26: GM_515_YL | M26: 45012
B27: Coordinateur Dimanche PM | C27: ALLAOUI | D27: Soibrane | E27: 639653182 | I27: 976-M-079 | J27: 806 | L27: FZ-148-HW | M27: 44336
C28: EL ANZIZE SALIM | D28: Hamada | E28: 0639 22 81 28 | F28: elsalimhamada@hotmail.com | G28: 024 076 531 00011 | H28: Mamoudzou | I28: 976_M_209 | J28: 413 | K28: 46877 | L28: GM_515_YL | M28: 45012 | N28: 9 | O28: Journée
C29: ALLAOUI | D29: Soibrane | E29: 0639 65 31 82 | F29: stt653182@hotmail.com | G29: 024 043 30 000 11 | H29: Centre Sud Mamoudzou | I29: 976-CS-048 976_M_079 | J29: 806 | K29: 43222 | L29: FZ_148_HW GP_645_QW | M29: 20/05/2021 20/06/2023
C30: HADHURAMI | D30: Makinedine | E30: 0639 94 46 40 | F30: Hadhuramimakinedine976@gmail.com | G30: 054 397 211 00019 | H30: SUD | I30: 976_S_069 | J30: 150 | K30: 45874 | L30: FZ-411-ZD | M30: 44362
C31: BOURA MIRADJI | D31: Issoufe | E31: 0639 03 18 92 | F31: bmiradjy.issouf@gmail.com | G31: 508 780 632 000 32 | H31: Sud | I31: 976-S-050 | J31: 548 | K31: 45242 | L31: GC-763-ES | M31: 44474
C32: TOURNANT
C33: MOHAMED | D33: Ali (laglace) | E33: 0639 01 04 89 | F33: samirahanie1@gmail.com | G33: 499 987 972 000 19 | H33: Mamoudzou | I33: 976-M-322 | J33: 623 | K33: 46915 | L33: GR-558_LA | M33: 45196
C34: ABDOU MINIHADJI | D34: Amada | E34: 0639 65 03 93 | F34: abdouminihadjiamada@hotmail.com | G34: 066 311 101 000 19 | H34: Centre Sud | I34: 976-CS-057 | J34: 505 | K34: 45305 | L34: FY-654-BF | M34: 44279
C35: BARAKA | D35: Soumaila | E35: 0639 24 71 32 | F35: barakasoumaila6@gmail.com | G35: 801 318 460 000 12 | H35: Mamoudzou | I35: 976-M-382 | J35: 992 | K35: 44247 | L35: DA-546-VX | M35: 42579
C36: TOUMBOU | D36: Toibourani | E36: 0639 19 14 22 | F36: toumboutoibourani@outlook.fr / anlia.toumbou97620@gmail.com | G36: 024 054 710 000 25 | H36: Mamoudzou | I36: 976-M-177 | J36: 357 | K36: 45028 | L36: GF_215_AQ | M36: 44624
C38: ABDOU HAMIDOUNE | D38: Nassabia | E38: 0639 23 54 34 | F38: abdouhamidoune.nassabia@gmail.com | G38: 099 385 932 000 19 | H38: Mamoudzou | I38: 976-M-189 | J38: 504 | K38: 46657 | L38: GY-652-NV | M38: 45504
C39: ABDOURAHIM | D39: Mohamed
C40: ISSOUF | D40: Dailami
C41: VELOU M'COLO | D41: M'Berou
C42: AHAMADI | D42: Laydine
C43: AHAMADI Bacar | D43: Raenmouddine
C44: SOULAIMANA | D44: Ben
C45: ABDOU MINIHADJI | D45: Amada | E45: 0639 65 03 93 | F45: abdouminihadjiamada@hotmail.com | G45: 066 311 101 000 19 | H45: Centre Sud | I45: 976-CS-057 | J45: 505 | K45: 45305 | L45: FY-654-BF | M45: 44279
C46: OUSSENI | D46: Soula | E46: 0639 69 03 87 | F46: soulaousseni415@gmail.com | G46: 066 307 372 000 12 | H46: Centre NORD | I46: 976-CN-003 | J46: 249 | K46: 43132 | L46: GP_813_HX | M46: 45083
C47: ASSANATI | D47: Renée | E47: 0639 07 82 51 | G47: 024 065 633 000 18 | H47: NORD | I47: 976-N-032 | J47: 1337 | K47: 45235 | L47: GR-921-XZ | M47: 45219
C48: AMBDI | D48: Houmadi | E48: 0639 23 55 69 | F48: ambdihoumadi976@gmail.com | G48: 066 312 224 000 26 | H48: Sud | I48: 976-S-023 | J48: 759 | K48: 45639 | L48: GC-122-QA | M48: 44495
C49: BINA HALADI | D49: Bina | E49: 0639 06 05 82 | F49: wonamaore@gmail.com | G49: 853 690 428 000 18 | H49: Sud | I49: 976-S-045 | J49: 1414 | K49: 45181 | L49: GE-883-ES | M49: 44581
C50: COMBO | D50: Said | E50: 0639 68 37 93 | F50: combosaid5@gmail.cpm | G50: 054 394 853 00029 | H50: Mamoudzou | I50: 976-M-164 | J50: 920 | K50: 44871 | L50: GB-965-EQ | M50: 44419
C51: SANDI | D51: Maanrouf | E51: 0639 40 58 85 | F51: maanroufsandi@laposte.net | G51: 024 069 635 000 19 | H51: Sud | I51: 976-S-006 | J51: 1184 | K51: 45262 | L51: GW-255-NY | M51: 45406
C52: BARAKA | D52: Soumaila | E52: 0639 24 71 32 | F52: barakasoumaila6@gmail.com | G52: 801 318 460 000 12 | H52: Mamoudzou | I52: 976-M-382 | J52: 992 | K52: 44247 | L52: DA-546-VX | M52: 42579
C53: TOUMBOU | D53: Toibourani | E53: 0639 19 14 22 | F53: toumboutoibourani@outlook.fr / anlia.toumbou97620@gmail.com | G53: 024 054 710 000 25 | H53: Mamoudzou | I53: 976-M-177 | J53: 357 | K53: 45028 | L53: GF_215_AQ | M53: 44624
C54: ABDOU MINIHADJI | D54: Amada
C55: SANDI | D55: Maanrouf
C56: TOUMBOU | D56: Toibourani
C62: ADINANI | D62: Zoubert
C63: ALLAOUI | D63: Inzoudine
C64: ALLAOUI | D64: Soibrane
C65: BINA HALIDI | D65: Bina
C66: COMBO | D66: Said
C67: ELANZIZE SALIM | D67: Hamada
C68: OUSSENI | D68: Soula
C69: RENE | D69: Assanati

Sheet Horaire
A3: DATE | D3: NOVEMBRE
A4: CHAUFFEUR
A7: DEPART | B7: Heure théorique départ | C7: Type chauffeur prévu | D7: Nom chauffeur prévu | E7: Nbre trajets | F7: Delai entre 2 départs | G7: Délai avant | H7: Astreinte 1 | I7: Nom Chauffeur astreinte 1 | J7: Astreinte 2 | K7: Nom Chauffeur astreinte 2 | L7: Heure réelle départ | M7: Nbre personnes + | N7: Commentaires
A8: VAHIBE | B8: 0.1875 | C8: C2 | D8: =VLOOKUP(C8,'Liste chauffeur'!$B$5:$L$20,2,TRUE)&" "&VLOOKUP(C8,'Liste chauffeur'!$B$5:$L$20,3,TRUE) -> BINA HALADI Bina | E8: 1 | F8: =B11-B8 -> 0.013888889
A9: VAHIBE | B9: 0.19444444 | C9: C1 | D9: =VLOOKUP(C9,'Liste chauffeur'!$B$5:$L$20,2,TRUE)&" "&VLOOKUP(C9,'Liste chauffeur'!$B$5:$L$20,3,TRUE) -> EL ANZIZE SALIM Hamada | E9: 1 | F9: =B13-B9 -> 0.013888889
A10: VAHIBE | B10: 0.20138889 | C10: C3 | D10: =VLOOKUP(C10,'Liste chauffeur'!$B$5:$L$20,2,TRUE)&" "&VLOOKUP(C10,'Liste chauffeur'!$B$5:$L$20,3,TRUE) -> ABDOU MINIHADJI Amada | E10: 1 | F10: =B17-B10 -> 0.013888889
A11: PASSAMAINTY | B11: 0.20138889 | C11: C2 | D11: =VLOOKUP(C11,'Liste chauffeur'!$B$5:$L$20,2,TRUE)&" "&VLOOKUP(C11,'Liste chauffeur'!$B$5:$L$20,3,TRUE) -> BINA HALADI Bina | E11: 2 | F11: =B15-B11 -> 0.013888889
A12: VAHIBE | B12: 0.20833333 | C12: C4 | D12: =VLOOKUP(C12,'Liste chauffeur'!$B$5:$L$20,2,TRUE)&" "&VLOOKUP(C12,'Liste chauffeur'!$B$5:$L$20,3,TRUE) -> TOUMBOU Toibourani | E12: 1 | F12: =B20-B12 -> 0.013888889
A13: PASSAMAINTY | B13: 0.20833333 | C13: C1 | D13: =VLOOKUP(C13,'Liste chauffeur'!$B$5:$L$20,2,TRUE)&" "&VLOOKUP(C13,'Liste chauffeur'!$B$5:$L$20,3,TRUE) -> EL ANZIZE SALIM Hamada | E13: 2 | F13: =B18-B13 -> 0.013888889
A14: VAHIBE 2 | B14: 0.20833333 | C14: C11 | D14: =VLOOKUP(C14,'Liste chauffeur'!$B$5:$L$20,2,TRUE)&" "&VLOOKUP(C14,'Liste chauffeur'!$B$5:$L$20,3,TRUE) -> MADI BOINA Mkidachi | E14: 1 | F14: =B21-B14 -> 0.013888889
A15: VAHIBE | B15: 0.21527778 | C15: C2 | D15: =VLOOKUP(C15,'Liste chauffeur'!$B$5:$L$20,2,TRUE)&" "&VLOOKUP(C15,'Liste chauffeur'!$B$5:$L$20,3,TRUE) -> BINA HALADI Bina | E15: 3 | F15: =B24-B15 -> 0.013888889
A16: VAHIBE 2 | B16: 0.21527778 | C16: C8 | D16: =VLOOKUP(C16,'Liste chauffeur'!$B$5:$L$20,2,TRUE)&" "&VLOOKUP(C16,'Liste chauffeur'!$B$5:$L$20,3,TRUE) -> HADHURAMI Makinedine | E16: 1 | F16: =B25-B16 -> 0.013888889
A17: PASSAMAINTY | B17: 0.21527778 | C17: C3 | D17: =VLOOKUP(C17,'Liste chauffeur'!$B$5:$L$20,2,TRUE)&" "&VLOOKUP(C17,'Liste chauffeur'!$B$5:$L$20,3,TRUE) -> ABDOU MINIHADJI Amada | E17: 2 | F17: =B22-B17 -> 0.013888889
A18: VAHIBE | B18: 0.22222222 | C18: C1 | D18: =VLOOKUP(C18,'Liste chauffeur'!$B$5:$L$20,2,TRUE)&" "&VLOOKUP(C18,'Liste chauffeur'!$B$5:$L$20,3,TRUE) -> EL ANZIZE SALIM Hamada | E18: 3 | F18: =B28-B18 -> 0.013888889
A19: VAHIBE 2 | B19: 0.22222222 | C19: C9 | D19: =VLOOKUP(C19,'Liste chauffeur'!$B$5:$L$20,2,TRUE)&" "&VLOOKUP(C19,'Liste chauffeur'!$B$5:$L$20,3,TRUE) -> SANDI Maanrouf | E19: 1 | F19: =B29-B19 -> 0.013888889
A20: PASSAMAINTY | B20: 0.22222222 | C20: C4 | D20: =VLOOKUP(C20,'Liste chauffeur'!$B$5:$L$20,2,TRUE)&" "&VLOOKUP(C20,'Liste chauffeur'!$B$5:$L$20,3,TRUE) -> TOUMBOU Toibourani | E20: 2 | F20: =B26-B20 -> 0.013888889
A21: PASSAMAINTY | B21: 0.22222222 | C21: C11 | D21: =VLOOKUP(C21,'Liste chauffeur'!$B$5:$L$20,2,TRUE)&" "&VLOOKUP(C21,'Liste chauffeur'!$B$5:$L$20,3,TRUE) -> MADI BOINA Mkidachi | E21: 2 | F21: =B27-B21 -> 0.013888889
A22: VAHIBE | B22: 0.22916667 | C22: C3 | D22: =VLOOKUP(C22,'Liste chauffeur'!$B$5:$L$20,2,TRUE)&" "&VLOOKUP(C22,'Liste chauffeur'!$B$5:$L$20,3,TRUE) -> ABDOU MINIHADJI Amada | E22: 3 | F22: =B32-B22 -> 0.013888889
A23: VAHIBE 2 | B23: 0.22916667 | C23: C10 | D23: =VLOOKUP(C23,'Liste chauffeur'!$B$5:$L$20,2,TRUE)&" "&VLOOKUP(C23,'Liste chauffeur'!$B$5:$L$20,3,TRUE) -> ISSIHAKA M'Changama | E23: 1 | F23: =B33-B23 -> 0.013888889
A24: PASSAMAINTY | B24: 0.22916667 | C24: C2 | D24: =VLOOKUP(C24,'Liste chauffeur'!$B$5:$L$20,2,TRUE)&" "&VLOOKUP(C24,'Liste chauffeur'!$B$5:$L$20,3,TRUE) -> BINA HALADI Bina | E24: 4 | F24: =B30-B24 -> 0.013888889
A25: PASSAMAINTY | B25: 0.22916667 | C25: C8 | D25: =VLOOKUP(C25,'Liste chauffeur'!$B$5:$L$20,2,TRUE)&" "&VLOOKUP(C25,'Liste chauffeur'!$B$5:$L$20,3,TRUE) -> HADHURAMI Makinedine | E25: 2 | F25: =B31-B25 -> 0.013888889
A26: VAHIBE | B26: 0.23611111 | C26: C4 | D26: =VLOOKUP(C26,'Liste chauffeur'!$B$5:$L$20,2,TRUE)&" "&VLOOKUP(C26,'Liste chauffeur'!$B$5:$L$20,3,TRUE) -> TOUMBOU Toibourani | E26: 3 | F26: =B40-B26 -> 0.020833333
A27: VAHIBE 2 | B27: 0.23611111 | C27: C11 | D27: =VLOOKUP(C27,'Liste chauffeur'!$B$5:$L$20,2,TRUE)&" "&VLOOKUP(C27,'Liste chauffeur'!$B$5:$L$20,3,TRUE) -> MADI BOINA Mkidachi | E27: 3 | F27: =B41-B27 -> 0.020833333
A28: PASSAMAINTY | B28: 0.23611111 | C28: C1 | D28: =VLOOKUP(C28,'Liste chauffeur'!$B$5:$L$20,2,TRUE)&" "&VLOOKUP(C28,'Liste chauffeur'!$B$5:$L$20,3,TRUE) -> EL ANZIZE SALIM Hamada | E28: 4 | F28: =B34-B28 -> 0.013888889
A29: PASSAMAINTY | B29: 0.23611111 | C29: C9 | D29: =VLOOKUP(C29,'Liste chauffeur'!$B$5:$L$20,2,TRUE)&" "&VLOOKUP(C29,'Liste chauffeur'!$B$5:$L$20,3,TRUE) -> SANDI Maanrouf | E29: 2 | F29: =B35-B29 -> 0.013888889
A30: VAHIBE | B30: 0.24305556 | C30: C2 | D30: =VLOOKUP(C30,'Liste chauffeur'!$B$5:$L$20,2,TRUE)&" "&VLOOKUP(C30,'Liste chauffeur'!$B$5:$L$20,3,TRUE) -> BINA HALADI Bina | E30: 5 | F30: =B44-B30 -> 0.020833333
A31: VAHIBE 2 | B31: 0.24305556 | C31: C8 | D31: =VLOOKUP(C31,'Liste chauffeur'!$B$5:$L$20,2,TRUE)&" "&VLOOKUP(C31,'Liste chauffeur'!$B$5:$L$20,3,TRUE) -> HADHURAMI Makinedine | E31: 3 | F31: =B45-B31 -> 0.020833333
A32: PASSAMAINTY | B32: 0.24305556 | C32: C3 | D32: =VLOOKUP(C32,'Liste chauffeur'!$B$5:$L$20,2,TRUE)&" "&VLOOKUP(C32,'Liste chauffeur'!$B$5:$L$20,3,TRUE) -> ABDOU MINIHADJI Amada | E32: 4 | F32: =B38-B32 -> 0.013888889
A33: PASSAMAINTY | B33: 0.24305556 | C33: C10 | D33: =VLOOKUP(C33,'Liste chauffeur'!$B$5:$L$20,2,TRUE)&" "&VLOOKUP(C33,'Liste chauffeur'!$B$5:$L$20,3,TRUE) -> ISSIHAKA M'Changama | E33: 2 | F33: =B39-B33 -> 0.013888889
A34: VAHIBE | B34: 0.25 | C34: C1 | D34: =VLOOKUP(C34,'Liste chauffeur'!$B$5:$L$20,2,TRUE)&" "&VLOOKUP(C34,'Liste chauffeur'!$B$5:$L$20,3,TRUE) -> EL ANZIZE SALIM Hamada | E34: 5 | F34: =B52-B34 -> 0.027777778
A35: VAHIBE 2 | B35: 0.25 | C35: C9 | D35: =VLOOKUP(C35,'Liste chauffeur'!$B$5:$L$20,2,TRUE)&" "&VLOOKUP(C35,'Liste chauffeur'!$B$5:$L$20,3,TRUE) -> SANDI Maanrouf | E35: 3 | F35: =B49-B35 -> 0.020833333
A36: PASSAMAINTY | B36: 0.25 | C36: C5 | D36: =VLOOKUP(C36,'Liste chauffeur'!$B$5:$L$20,2,TRUE)&" "&VLOOKUP(C36,'Liste chauffeur'!$B$5:$L$20,3,TRUE) -> AHAMADI Bacar Raenmouddine | E36: 1 | F36: =B42-B36 -> 0.013888889
A37: PASSAMAINTY | B37: 0.25 | C37: C12 | D37: =VLOOKUP(C37,'Liste chauffeur'!$B$5:$L$20,2,TRUE)&" "&VLOOKUP(C37,'Liste chauffeur'!$B$5:$L$20,3,TRUE) -> ALILOIFFA Said Siradj | E37: 1 | F37: =B43-B37 -> 0.013888889
A38: VAHIBE | B38: 0.25694444 | C38: C3 | D38: =VLOOKUP(C38,'Liste chauffeur'!$B$5:$L$20,2,TRUE)&" "&VLOOKUP(C38,'Liste chauffeur'!$B$5:$L$20,3,TRUE) -> ABDOU MINIHADJI Amada | E38: 5 | F38: =B53-B38 -> 0.020833333
A39: VAHIBE 2 | B39: 0.25694444 | C39: C10 | D39: =VLOOKUP(C39,'Liste chauffeur'!$B$5:$L$20,2,TRUE)&" "&VLOOKUP(C39,'Liste chauffeur'!$B$5:$L$20,3,TRUE) -> ISSIHAKA M'Changama | E39: 3 | F39: =B56-B39 -> 0.027777778
A40: PASSAMAINTY | B40: 0.25694444 | C40: C4 | D40: =VLOOKUP(C40,'Liste chauffeur'!$B$5:$L$20,2,TRUE)&" "&VLOOKUP(C40,'Liste chauffeur'!$B$5:$L$20,3,TRUE) -> TOUMBOU Toibourani | E40: 4 | F40: =B46-B40 -> 0.013888889
A41: PASSAMAINTY | B41: 0.25694444 | C41: C11 | D41: =VLOOKUP(C41,'Liste chauffeur'!$B$5:$L$20,2,TRUE)&" "&VLOOKUP(C41,'Liste chauffeur'!$B$5:$L$20,3,TRUE) -> MADI BOINA Mkidachi | E41: 4 | F41: =B47-B41 -> 0.013888889
A42: VAHIBE | B42: 0.26388889 | C42: C5 | D42: =VLOOKUP(C42,'Liste chauffeur'!$B$5:$L$20,2,TRUE)&" "&VLOOKUP(C42,'Liste chauffeur'!$B$5:$L$20,3,TRUE) -> AHAMADI Bacar Raenmouddine | E42: 2 | F42: =B57-B42 -> 0.020833333
A43: VAHIBE 2 | B43: 0.26388889 | C43: C12 | D43: =VLOOKUP(C43,'Liste chauffeur'!$B$5:$L$20,2,TRUE)&" "&VLOOKUP(C43,'Liste chauffeur'!$B$5:$L$20,3,TRUE) -> ALILOIFFA Said Siradj | E43: 2
A44: PASSAMAINTY | B44: 0.26388889 | C44: C2 | D44: =VLOOKUP(C44,'Liste chauffeur'!$B$5:$L$20,2,TRUE)&" "&VLOOKUP(C44,'Liste chauffeur'!$B$5:$L$20,3,TRUE) -> BINA HALADI Bina | E44: 6 | F44: =B50-B44 -> 0.013888889
A45: PASSAMAINTY | B45: 0.26388889 | C45: C8 | D45: =VLOOKUP(C45,'Liste chauffeur'!$B$5:$L$20,2,TRUE)&" "&VLOOKUP(C45,'Liste chauffeur'!$B$5:$L$20,3,TRUE) -> HADHURAMI Makinedine | E45: 4 | F45: =B51-B45 -> 0.013888889
A46: VAHIBE | B46: 0.27083333 | C46: C4 | D46: =VLOOKUP(C46,'Liste chauffeur'!$B$5:$L$20,2,TRUE)&" "&VLOOKUP(C46,'Liste chauffeur'!$B$5:$L$20,3,TRUE) -> TOUMBOU Toibourani | E46: 5 | F46: =B60-B46 -> 0.020833333
A47: VAHIBE 2 | B47: 0.27083333 | C47: C11 | D47: =VLOOKUP(C47,'Liste chauffeur'!$B$5:$L$20,2,TRUE)&" "&VLOOKUP(C47,'Liste chauffeur'!$B$5:$L$20,3,TRUE) -> MADI BOINA Mkidachi | E47: 5 | F47: =B61-B47 -> 0.020833333
A48: PASSAMAINTY | B48: 0.27083333 | C48: C15 | D48: =VLOOKUP(C48,'Liste chauffeur'!$B$5:$L$20,2,TRUE)&" "&VLOOKUP(C48,'Liste chauffeur'!$B$5:$L$20,3,TRUE) -> HAMADA Babou | E48: 1 | F48: =B54-B48 -> 0.013888889
A49: PASSAMAINTY | B49: 0.27083333 | C49: C9 | D49: =VLOOKUP(C49,'Liste chauffeur'!$B$5:$L$20,2,TRUE)&" "&VLOOKUP(C49,'Liste chauffeur'!$B$5:$L$20,3,TRUE) -> SANDI Maanrouf | E49: 4 | F49: =B55-B49 -> 0.013888889
A50: VAHIBE | B50: 0.27777778 | C50: C2 | D50: =VLOOKUP(C50,'Liste chauffeur'!$B$5:$L$20,2,TRUE)&" "&VLOOKUP(C50,'Liste chauffeur'!$B$5:$L$20,3,TRUE) -> BINA HALADI Bina | E50: 7 | F50: =B64-B50 -> 0.020833333
A51: VAHIBE 2 | B51: 0.27777778 | C51: C8 | D51: =VLOOKUP(C51,'Liste chauffeur'!$B$5:$L$20,2,TRUE)&" "&VLOOKUP(C51,'Liste chauffeur'!$B$5:$L$20,3,TRUE) -> HADHURAMI Makinedine | E51: 5 | F51: =B65-B51 -> 0.020833333
A52: PASSAMAINTY | B52: 0.27777778 | C52: C1 | D52: =VLOOKUP(C52,'Liste chauffeur'!$B$5:$L$20,2,TRUE)&" "&VLOOKUP(C52,'Liste chauffeur'!$B$5:$L$20,3,TRUE) -> EL ANZIZE SALIM Hamada | E52: 6 | F52: =B58-B52 -> 0.013888889
A53: PASSAMAINTY | B53: 0.27777778 | C53: C3 | D53: =VLOOKUP(C53,'Liste chauffeur'!$B$5:$L$20,2,TRUE)&" "&VLOOKUP(C53,'Liste chauffeur'!$B$5:$L$20,3,TRUE) -> ABDOU MINIHADJI Amada | E53: 6 | F53: =B59-B53 -> 0.013888889
A54: VAHIBE | B54: 0.28472222 | C54: C15 | D54: =VLOOKUP(C54,'Liste chauffeur'!$B$5:$L$20,2,TRUE)&" "&VLOOKUP(C54,'Liste chauffeur'!$B$5:$L$20,3,TRUE) -> HAMADA Babou | E54: 2 | F54: =B68-B54 -> 0.020833333
A55: VAHIBE 2 | B55: 0.28472222 | C55: C9 | D55: =VLOOKUP(C55,'Liste chauffeur'!$B$5:$L$20,2,TRUE)&" "&VLOOKUP(C55,'Liste chauffeur'!$B$5:$L$20,3,TRUE) -> SANDI Maanrouf | E55: 5 | F55: =B69-B55 -> 0.020833333
A56: PASSAMAINTY | B56: 0.28472222 | C56: C10 | D56: =VLOOKUP(C56,'Liste chauffeur'!$B$5:$L$20,2,TRUE)&" "&VLOOKUP(C56,'Liste chauffeur'!$B$5:$L$20,3,TRUE) -> ISSIHAKA M'Changama | E56: 4 | F56: =B62-B56 -> 0.013888889
A57: PASSAMAINTY | B57: 0.28472222 | C57: C5 | D57: =VLOOKUP(C57,'Liste chauffeur'!$B$5:$L$20,2,TRUE)&" "&VLOOKUP(C57,'Liste chauffeur'!$B$5:$L$20,3,TRUE) -> AHAMADI Bacar Raenmouddine | E57: 3 | F57: =B63-B57 -> 0.013888889
A58: VAHIBE | B58: 0.29166667 | C58: C1 | D58: =VLOOKUP(C58,'Liste chauffeur'!$B$5:$L$20,2,TRUE)&" "&VLOOKUP(C58,'Liste chauffeur'!$B$5:$L$20,3,TRUE) -> EL ANZIZE SALIM Hamada | E58: 7 | F58: =B73-B58 -> 0.020833333
A59: VAHIBE 2 | B59: 0.29166667 | C59: C3 | D59: =VLOOKUP(C59,'Liste chauffeur'!$B$5:$L$20,2,TRUE)&" "&VLOOKUP(C59,'Liste chauffeur'!$B$5:$L$20,3,TRUE) -> ABDOU MINIHADJI Amada | E59: 7 | F59: =B72-B59 -> 0.020833333
A60: PASSAMAINTY | B60: 0.29166667 | C60: C4 | D60: =VLOOKUP(C60,'Liste chauffeur'!$B$5:$L$20,2,TRUE)&" "&VLOOKUP(C60,'Liste chauffeur'!$B$5:$L$20,3,TRUE) -> TOUMBOU Toibourani | E60: 6 | F60: =B66-B60 -> 0.013888889
A61: PASSAMAINTY | B61: 0.29166667 | C61: C11 | D61: =VLOOKUP(C61,'Liste chauffeur'!$B$5:$L$20,2,TRUE)&" "&VLOOKUP(C61,'Liste chauffeur'!$B$5:$L$20,3,TRUE) -> MADI BOINA Mkidachi | E61: 6 | F61: =B67-B61 -> 0.013888889
A62: VAHIBE | B62: 0.29861111 | C62: C10 | D62: =VLOOKUP(C62,'Liste chauffeur'!$B$5:$L$20,2,TRUE)&" "&VLOOKUP(C62,'Liste chauffeur'!$B$5:$L$20,3,TRUE) -> ISSIHAKA M'Changama | E62: 5 | F62: =B76-B62 -> 0.020833333
A63: VAHIBE 2 | B63: 0.29861111 | C63: C5 | D63: =VLOOKUP(C63,'Liste chauffeur'!$B$5:$L$20,2,TRUE)&" "&VLOOKUP(C63,'Liste chauffeur'!$B$5:$L$20,3,TRUE) -> AHAMADI Bacar Raenmouddine | E63: 4 | F63: =B77-B63 -> 0.020833333
A64: PASSAMAINTY | B64: 0.29861111 | C64: C13 | D64: =VLOOKUP(C64,'Liste chauffeur'!$B$5:$L$20,2,TRUE)&" "&VLOOKUP(C64,'Liste chauffeur'!$B$5:$L$20,3,TRUE) -> ABDALLAH Ben (Taxi Vanille) | E64: 1 | F64: =B70-B64 -> 0.013888889
A65: PASSAMAINTY | B65: 0.29861111 | C65: C8 | D65: =VLOOKUP(C65,'Liste chauffeur'!$B$5:$L$20,2,TRUE)&" "&VLOOKUP(C65,'Liste chauffeur'!$B$5:$L$20,3,TRUE) -> HADHURAMI Makinedine | E65: 6 | F65: =B71-B65 -> 0.013888889
A66: VAHIBE | B66: 0.30555556 | C66: C4 | D66: =VLOOKUP(C66,'Liste chauffeur'!$B$5:$L$20,2,TRUE)&" "&VLOOKUP(C66,'Liste chauffeur'!$B$5:$L$20,3,TRUE) -> TOUMBOU Toibourani | E66: 7 | F66: =B80-B66 -> 0.020833333
A67: VAHIBE 2 | B67: 0.30555556 | C67: C11 | D67: =VLOOKUP(C67,'Liste chauffeur'!$B$5:$L$20,2,TRUE)&" "&VLOOKUP(C67,'Liste chauffeur'!$B$5:$L$20,3,TRUE) -> MADI BOINA Mkidachi | E67: 7 | F67: =B81-B67 -> 0.020833333
A68: PASSAMAINTY | B68: 0.30555556 | C68: C15 | D68: =VLOOKUP(C68,'Liste chauffeur'!$B$5:$L$20,2,TRUE)&" "&VLOOKUP(C68,'Liste chauffeur'!$B$5:$L$20,3,TRUE) -> HAMADA Babou | E68: 3 | F68: =B74-B68 -> 0.013888889
A69: PASSAMAINTY | B69: 0.30555556 | C69: C9 | D69: =VLOOKUP(C69,'Liste chauffeur'!$B$5:$L$20,2,TRUE)&" "&VLOOKUP(C69,'Liste chauffeur'!$B$5:$L$20,3,TRUE) -> SANDI Maanrouf | E69: 6 | F69: =B75-B69 -> 0.013888889
A70: VAHIBE | B70: 0.3125 | C70: C13 | D70: =VLOOKUP(C70,'Liste chauffeur'!$B$5:$L$20,2,TRUE)&" "&VLOOKUP(C70,'Liste chauffeur'!$B$5:$L$20,3,TRUE) -> ABDALLAH Ben (Taxi Vanille) | E70: 2 | F70: =B84-B70 -> 0.020833333
A71: VAHIBE 2 | B71: 0.3125 | C71: C8 | D71: =VLOOKUP(C71,'Liste chauffeur'!$B$5:$L$20,2,TRUE)&" "&VLOOKUP(C71,'Liste chauffeur'!$B$5:$L$20,3,TRUE) -> HADHURAMI Makinedine | E71: 7
A72: PASSAMAINTY | B72: 0.3125 | C72: C3 | D72: =VLOOKUP(C72,'Liste chauffeur'!$B$5:$L$20,2,TRUE)&" "&VLOOKUP(C72,'Liste chauffeur'!$B$5:$L$20,3,TRUE) -> ABDOU MINIHADJI Amada | E72: 8 | F72: =B78-B72 -> 0.013888889
A73: PASSAMAINTY | B73: 0.3125 | C73: C1 | D73: =VLOOKUP(C73,'Liste chauffeur'!$B$5:$L$20,2,TRUE)&" "&VLOOKUP(C73,'Liste chauffeur'!$B$5:$L$20,3,TRUE) -> EL ANZIZE SALIM Hamada | E73: 8 | F73: =B79-B73 -> 0.013888889
A74: VAHIBE | B74: 0.31944444 | C74: C15 | D74: =VLOOKUP(C74,'Liste chauffeur'!$B$5:$L$20,2,TRUE)&" "&VLOOKUP(C74,'Liste chauffeur'!$B$5:$L$20,3,TRUE) -> HAMADA Babou | E74: 4 | F74: =B86-B74 -> 0.024305556
A75: VAHIBE 2 | B75: 0.31944444 | C75: C9 | D75: =VLOOKUP(C75,'Liste chauffeur'!$B$5:$L$20,2,TRUE)&" "&VLOOKUP(C75,'Liste chauffeur'!$B$5:$L$20,3,TRUE) -> SANDI Maanrouf | E75: 7
A76: PASSAMAINTY | B76: 0.31944444 | C76: C10 | D76: =VLOOKUP(C76,'Liste chauffeur'!$B$5:$L$20,2,TRUE)&" "&VLOOKUP(C76,'Liste chauffeur'!$B$5:$L$20,3,TRUE) -> ISSIHAKA M'Changama | E76: 6 | F76: =B83-B76 -> 0.013888889
A77: PASSAMAINTY | B77: 0.31944444 | C77: C5 | D77: =VLOOKUP(C77,'Liste chauffeur'!$B$5:$L$20,2,TRUE)&" "&VLOOKUP(C77,'Liste chauffeur'!$B$5:$L$20,3,TRUE) -> AHAMADI Bacar Raenmouddine | E77: 5 | F77: =B82-B77 -> 0.013888889
A78: VAHIBE | B78: 0.32638889 | C78: C3 | D78: =VLOOKUP(C78,'Liste chauffeur'!$B$5:$L$20,2,TRUE)&" "&VLOOKUP(C78,'Liste chauffeur'!$B$5:$L$20,3,TRUE) -> ABDOU MINIHADJI Amada | E78: 9
A79: VAHIBE 2 | B79: 0.32638889 | C79: C1 | D79: =VLOOKUP(C79,'Liste chauffeur'!$B$5:$L$20,2,TRUE)&" "&VLOOKUP(C79,'Liste chauffeur'!$B$5:$L$20,3,TRUE) -> EL ANZIZE SALIM Hamada | E79: 9 | F79: =B88-B79 -> 0.027777778
A80: PASSAMAINTY | B80: 0.32638889 | C80: C4 | D80: =VLOOKUP(C80,'Liste chauffeur'!$B$5:$L$20,2,TRUE)&" "&VLOOKUP(C80,'Liste chauffeur'!$B$5:$L$20,3,TRUE) -> TOUMBOU Toibourani | E80: 8 | F80: =B85-B80 -> 0.017361111
A81: PASSAMAINTY | B81: 0.32638889 | C81: C11 | D81: =VLOOKUP(C81,'Liste chauffeur'!$B$5:$L$20,2,TRUE)&" "&VLOOKUP(C81,'Liste chauffeur'!$B$5:$L$20,3,TRUE) -> MADI BOINA Mkidachi | E81: 8
A82: VAHIBE | B82: 0.33333333 | C82: C5 | D82: =VLOOKUP(C82,'Liste chauffeur'!$B$5:$L$20,2,TRUE)&" "&VLOOKUP(C82,'Liste chauffeur'!$B$5:$L$20,3,TRUE) -> AHAMADI Bacar Raenmouddine | E82: 6
A83: VAHIBE 2 | B83: 0.33333333 | C83: C10 | D83: =VLOOKUP(C83,'Liste chauffeur'!$B$5:$L$20,2,TRUE)&" "&VLOOKUP(C83,'Liste chauffeur'!$B$5:$L$20,3,TRUE) -> ISSIHAKA M'Changama | E83: 7
A84: PASSAMAINTY | B84: 0.33333333 | C84: C13 | D84: =VLOOKUP(C84,'Liste chauffeur'!$B$5:$L$20,2,TRUE)&" "&VLOOKUP(C84,'Liste chauffeur'!$B$5:$L$20,3,TRUE) -> ABDALLAH Ben (Taxi Vanille) | E84: 3
A85: VAHIBE | B85: 0.34375 | C85: C4 | D85: =VLOOKUP(C85,'Liste chauffeur'!$B$5:$L$20,2,TRUE)&" "&VLOOKUP(C85,'Liste chauffeur'!$B$5:$L$20,3,TRUE) -> TOUMBOU Toibourani | E85: 9
A86: PASSAMAINTY | B86: 0.34375 | C86: C15 | D86: =VLOOKUP(C86,'Liste chauffeur'!$B$5:$L$20,2,TRUE)&" "&VLOOKUP(C86,'Liste chauffeur'!$B$5:$L$20,3,TRUE) -> HAMADA Babou | E86: 5 | F86: =B87-B86 -> 0.010416667
A87: VAHIBE | B87: 0.35416667 | C87: C14 | D87: =VLOOKUP(C87,'Liste chauffeur'!$B$5:$L$20,2,TRUE)&" "&VLOOKUP(C87,'Liste chauffeur'!$B$5:$L$20,3,TRUE) -> KAMARDINE Mansour | E87: 1 | F87: =B90-B87 -> 0.020833333
A88: PASSAMAINTY | B88: 0.35416667 | C88: C1 | D88: =VLOOKUP(C88,'Liste chauffeur'!$B$5:$L$20,2,TRUE)&" "&VLOOKUP(C88,'Liste chauffeur'!$B$5:$L$20,3,TRUE) -> EL ANZIZE SALIM Hamada | E88: 10 | F88: =B89-B88 -> 0.020833333
A89: VAHIBE | B89: 0.375 | C89: C1 | D89: =VLOOKUP(C89,'Liste chauffeur'!$B$5:$L$20,2,TRUE)&" "&VLOOKUP(C89,'Liste chauffeur'!$B$5:$L$20,3,TRUE) -> EL ANZIZE SALIM Hamada | E89: 11 | F89: =B92-B89 -> 0.020833333
A90: PASSAMAINTY | B90: 0.375 | C90: C14 | D90: =VLOOKUP(C90,'Liste chauffeur'!$B$5:$L$20,2,TRUE)&" "&VLOOKUP(C90,'Liste chauffeur'!$B$5:$L$20,3,TRUE) -> KAMARDINE Mansour | E90: 2 | F90: =B91-B90 -> 0.020833333
A91: VAHIBE | B91: 0.39583333 | C91: C14 | D91: =VLOOKUP(C91,'Liste chauffeur'!$B$5:$L$20,2,TRUE)&" "&VLOOKUP(C91,'Liste chauffeur'!$B$5:$L$20,3,TRUE) -> KAMARDINE Mansour | E91: 3 | F91: =B94-B91 -> 0.020833333
A92: PASSAMAINTY | B92: 0.39583333 | C92: C1 | D92: =VLOOKUP(C92,'Liste chauffeur'!$B$5:$L$20,2,TRUE)&" "&VLOOKUP(C92,'Liste chauffeur'!$B$5:$L$20,3,TRUE) -> EL ANZIZE SALIM Hamada | E92: 12 | F92: =B93-B92 -> 0.020833333
A93: VAHIBE | B93: 0.41666667 | C93: C1 | D93: =VLOOKUP(C93,'Liste chauffeur'!$B$5:$L$20,2,TRUE)&" "&VLOOKUP(C93,'Liste chauffeur'!$B$5:$L$20,3,TRUE) -> EL ANZIZE SALIM Hamada | E93: 13 | F93: =B96-B93 -> 0.020833333
A94: PASSAMAINTY | B94: 0.41666667 | C94: C14 | D94: =VLOOKUP(C94,'Liste chauffeur'!$B$5:$L$20,2,TRUE)&" "&VLOOKUP(C94,'Liste chauffeur'!$B$5:$L$20,3,TRUE) -> KAMARDINE Mansour | E94: 4 | F94: =B95-B94 -> 0.020833333
A95: VAHIBE | B95: 0.4375 | C95: C14 | D95: =VLOOKUP(C95,'Liste chauffeur'!$B$5:$L$20,2,TRUE)&" "&VLOOKUP(C95,'Liste chauffeur'!$B$5:$L$20,3,TRUE) -> KAMARDINE Mansour | E95: 5 | F95: =B98-B95 -> 0.020833333
A96: PASSAMAINTY | B96: 0.4375 | C96: C1 | D96: =VLOOKUP(C96,'Liste chauffeur'!$B$5:$L$20,2,TRUE)&" "&VLOOKUP(C96,'Liste chauffeur'!$B$5:$L$20,3,TRUE) -> EL ANZIZE SALIM Hamada | E96: 14 | F96: =B97-B96 -> 0.020833333
A97: VAHIBE | B97: 0.45833333 | C97: C1 | D97: =VLOOKUP(C97,'Liste chauffeur'!$B$5:$L$20,2,TRUE)&" "&VLOOKUP(C97,'Liste chauffeur'!$B$5:$L$20,3,TRUE) -> EL ANZIZE SALIM Hamada | E97: 15 | F97: =B100-B97 -> 0.020833333
A98: PASSAMAINTY | B98: 0.45833333 | C98: C14 | D98: =VLOOKUP(C98,'Liste chauffeur'!$B$5:$L$20,2,TRUE)&" "&VLOOKUP(C98,'Liste chauffeur'!$B$5:$L$20,3,TRUE) -> KAMARDINE Mansour | E98: 6 | F98: =B99-B98 -> 0.020833333
A99: VAHIBE | B99: 0.47916667 | C99: C14 | D99: =VLOOKUP(C99,'Liste chauffeur'!$B$5:$L$20,2,TRUE)&" "&VLOOKUP(C99,'Liste chauffeur'!$B$5:$L$20,3,TRUE) -> KAMARDINE Mansour | E99: 7 | F99: =B102-B99 -> 0.020833333
A100: PASSAMAINTY | B100: 0.47916667 | C100: C1 | D100: =VLOOKUP(C100,'Liste chauffeur'!$B$5:$L$20,2,TRUE)&" "&VLOOKUP(C100,'Liste chauffeur'!$B$5:$L$20,3,TRUE) -> EL ANZIZE SALIM Hamada | E100: 16 | F100: =B101-B100 -> 0.020833333
A101: VAHIBE | B101: 0.5 | C101: C1 | D101: =VLOOKUP(C101,'Liste chauffeur'!$B$5:$L$20,2,TRUE)&" "&VLOOKUP(C101,'Liste chauffeur'!$B$5:$L$20,3,TRUE) -> EL ANZIZE SALIM Hamada | E101: 17 | F101: =B104-B101 -> 0.020833333
A102: PASSAMAINTY | B102: 0.5 | C102: C14 | D102: =VLOOKUP(C102,'Liste chauffeur'!$B$5:$L$20,2,TRUE)&" "&VLOOKUP(C102,'Liste chauffeur'!$B$5:$L$20,3,TRUE) -> KAMARDINE Mansour | E102: 8 | F102: =B103-B102 -> 0.020833333
A103: VAHIBE | B103: 0.52083333 | C103: C14 | D103: =VLOOKUP(C103,'Liste chauffeur'!$B$5:$L$20,2,TRUE)&" "&VLOOKUP(C103,'Liste chauffeur'!$B$5:$L$20,3,TRUE) -> KAMARDINE Mansour | E103: 9 | F103: =B106-B103 -> 0.020833333
A104: PASSAMAINTY | B104: 0.52083333 | C104: C2 | D104: =VLOOKUP(C104,'Liste chauffeur'!$B$5:$L$20,2,TRUE)&" "&VLOOKUP(C104,'Liste chauffeur'!$B$5:$L$20,3,TRUE) -> BINA HALADI Bina | E104: 8 | F104: =B105-B104 -> 0.020833333
...

Sheet Horaire samedi
A3: DATE | D3: NOVEMBRE
A4: CHAUFFEUR
A7: DEPART | B7: Heure théorique départ | C7: Type chauffeur prévu | D7: Nom chauffeur prévu | E7: Nbre trajets | F7: Delai entre 2 départs | G7: Délai avant | H7: Astreinte 1 | I7: Nom Chauffeur astreinte 1 | J7: Astreinte 2 | K7: Nom Chauffeur astreinte 2 | L7: Heure réelle départ | M7: Nbre personnes + | N7: Commentaires
A8: VAHIBE | B8: 0.25 | C8: C11 | D8: =VLOOKUP(C8,'Liste chauffeur'!$B$5:$L$20,2,TRUE)&" "&VLOOKUP(C8,'Liste chauffeur'!$B$5:$L$20,3,TRUE) -> MADI BOINA Mkidachi | E8: 1 | F8: =B10-B8 -> 0.020833333
A9: VAHIBE | B9: 0.27083333 | C9: C9 | D9: =VLOOKUP(C9,'Liste chauffeur'!$B$5:$L$20,2,TRUE)&" "&VLOOKUP(C9,'Liste chauffeur'!$B$5:$L$20,3,TRUE) -> SANDI Maanrouf | E9: 1 | F9: =B12-B9 -> 0.020833333
A10: PASSAMAINTY | B10: 0.27083333 | C10: C11 | D10: =VLOOKUP(C10,'Liste chauffeur'!$B$5:$L$20,2,TRUE)&" "&VLOOKUP(C10,'Liste chauffeur'!$B$5:$L$20,3,TRUE) -> MADI BOINA Mkidachi | E10: 2 | F10: =B11-B10 -> 0.020833333
A11: VAHIBE | B11: 0.29166667 | C11: C11 | D11: =VLOOKUP(C11,'Liste chauffeur'!$B$5:$L$20,2,TRUE)&" "&VLOOKUP(C11,'Liste chauffeur'!$B$5:$L$20,3,TRUE) -> MADI BOINA Mkidachi | E11: 3 | F11: =B13-B11 -> 0.020833333
A12: PASSAMAINTY | B12: 0.29166667 | C12: C9 | D12: =VLOOKUP(C12,'Liste chauffeur'!$B$5:$L$20,2,TRUE)&" "&VLOOKUP(C12,'Liste chauffeur'!$B$5:$L$20,3,TRUE) -> SANDI Maanrouf | E12: 2 | F12: =B14-B12 -> 0.020833333
A13: VAHIBE | B13: 0.3125 | C13: C11 | D13: =VLOOKUP(C13,'Liste chauffeur'!$B$5:$L$20,2,TRUE)&" "&VLOOKUP(C13,'Liste chauffeur'!$B$5:$L$20,3,TRUE) -> MADI BOINA Mkidachi | E13: 4 | F13: =B16-B13 -> 0.020833333
A14: PASSAMAINTY | B14: 0.3125 | C14: C9 | D14: =VLOOKUP(C14,'Liste chauffeur'!$B$5:$L$20,2,TRUE)&" "&VLOOKUP(C14,'Liste chauffeur'!$B$5:$L$20,3,TRUE) -> SANDI Maanrouf | E14: 3 | F14: =B15-B14 -> 0.020833333
A15: VAHIBE | B15: 0.33333333 | C15: C9 | D15: =VLOOKUP(C15,'Liste chauffeur'!$B$5:$L$20,2,TRUE)&" "&VLOOKUP(C15,'Liste chauffeur'!$B$5:$L$20,3,TRUE) -> SANDI Maanrouf | E15: 4 | F15: =B18-B15 -> 0.041666667
A16: PASSAMAINTY | B16: 0.33333333 | C16: C11 | D16: =VLOOKUP(C16,'Liste chauffeur'!$B$5:$L$20,2,TRUE)&" "&VLOOKUP(C16,'Liste chauffeur'!$B$5:$L$20,3,TRUE) -> MADI BOINA Mkidachi | E16: 5 | F16: =B17-B16 -> 0.041666667
A17: VAHIBE | B17: 0.375 | C17: C11 | D17: =VLOOKUP(C17,'Liste chauffeur'!$B$5:$L$20,2,TRUE)&" "&VLOOKUP(C17,'Liste chauffeur'!$B$5:$L$20,3,TRUE) -> MADI BOINA Mkidachi | E17: 6 | F17: =B20-B17 -> 0.020833333
A18: PASSAMAINTY | B18: 0.375 | C18: C9 | D18: =VLOOKUP(C18,'Liste chauffeur'!$B$5:$L$20,2,TRUE)&" "&VLOOKUP(C18,'Liste chauffeur'!$B$5:$L$20,3,TRUE) -> SANDI Maanrouf | E18: 5 | F18: =B19-B18 -> 0.020833333
A19: VAHIBE | B19: 0.39583333 | C19: C9 | D19: =VLOOKUP(C19,'Liste chauffeur'!$B$5:$L$20,2,TRUE)&" "&VLOOKUP(C19,'Liste chauffeur'!$B$5:$L$20,3,TRUE) -> SANDI Maanrouf | E19: 6 | F19: =B22-B19 -> 0.020833333
A20: PASSAMAINTY | B20: 0.39583333 | C20: C11 | D20: =VLOOKUP(C20,'Liste chauffeur'!$B$5:$L$20,2,TRUE)&" "&VLOOKUP(C20,'Liste chauffeur'!$B$5:$L$20,3,TRUE) -> MADI BOINA Mkidachi | E20: 7 | F20: =B21-B20 -> 0.020833333
A21: VAHIBE | B21: 0.41666667 | C21: C11 | D21: =VLOOKUP(C21,'Liste chauffeur'!$B$5:$L$20,2,TRUE)&" "&VLOOKUP(C21,'Liste chauffeur'!$B$5:$L$20,3,TRUE) -> MADI BOINA Mkidachi | E21: 8 | F21: =B24-B21 -> 0.020833333
A22: PASSAMAINTY | B22: 0.41666667 | C22: C9 | D22: =VLOOKUP(C22,'Liste chauffeur'!$B$5:$L$20,2,TRUE)&" "&VLOOKUP(C22,'Liste chauffeur'!$B$5:$L$20,3,TRUE) -> SANDI Maanrouf | E22: 7 | F22: =B23-B22 -> 0.020833333
A23: VAHIBE | B23: 0.4375 | C23: C9 | D23: =VLOOKUP(C23,'Liste chauffeur'!$B$5:$L$20,2,TRUE)&" "&VLOOKUP(C23,'Liste chauffeur'!$B$5:$L$20,3,TRUE) -> SANDI Maanrouf | E23: 8 | F23: =B26-B23 -> 0.020833333
A24: PASSAMAINTY | B24: 0.4375 | C24: C11 | D24: =VLOOKUP(C24,'Liste chauffeur'!$B$5:$L$20,2,TRUE)&" "&VLOOKUP(C24,'Liste chauffeur'!$B$5:$L$20,3,TRUE) -> MADI BOINA Mkidachi | E24: 9 | F24: =B25-B24 -> 0.020833333
A25: VAHIBE | B25: 0.45833333 | C25: C11 | D25: =VLOOKUP(C25,'Liste chauffeur'!$B$5:$L$20,2,TRUE)&" "&VLOOKUP(C25,'Liste chauffeur'!$B$5:$L$20,3,TRUE) -> MADI BOINA Mkidachi | E25: 10 | F25: =B28-B25 -> 0.020833333
A26: PASSAMAINTY | B26: 0.45833333 | C26: C9 | D26: =VLOOKUP(C26,'Liste chauffeur'!$B$5:$L$20,2,TRUE)&" "&VLOOKUP(C26,'Liste chauffeur'!$B$5:$L$20,3,TRUE) -> SANDI Maanrouf | E26: 9 | F26: =B27-B26 -> 0.020833333
A27: VAHIBE | B27: 0.47916667 | C27: C9 | D27: =VLOOKUP(C27,'Liste chauffeur'!$B$5:$L$20,2,TRUE)&" "&VLOOKUP(C27,'Liste chauffeur'!$B$5:$L$20,3,TRUE) -> SANDI Maanrouf | E27: 10 | F27: =B30-B27 -> 0.020833333
A28: PASSAMAINTY | B28: 0.47916667 | C28: C11 | D28: =VLOOKUP(C28,'Liste chauffeur'!$B$5:$L$20,2,TRUE)&" "&VLOOKUP(C28,'Liste chauffeur'!$B$5:$L$20,3,TRUE) -> MADI BOINA Mkidachi | E28: 11 | F28: =B29-B28 -> 0.020833333
A29: VAHIBE | B29: 0.5 | C29: C11 | D29: =VLOOKUP(C29,'Liste chauffeur'!$B$5:$L$20,2,TRUE)&" "&VLOOKUP(C29,'Liste chauffeur'!$B$5:$L$20,3,TRUE) -> MADI BOINA Mkidachi | E29: 12 | F29: =B32-B29 -> 0.020833333
A30: PASSAMAINTY | B30: 0.5 | C30: C9 | D30: =VLOOKUP(C30,'Liste chauffeur'!$B$5:$L$20,2,TRUE)&" "&VLOOKUP(C30,'Liste chauffeur'!$B$5:$L$20,3,TRUE) -> SANDI Maanrouf | E30: 11 | F30: =B31-B30 -> 0.020833333
A31: VAHIBE | B31: 0.52083333 | C31: C9 | D31: =VLOOKUP(C31,'Liste chauffeur'!$B$5:$L$20,2,TRUE)&" "&VLOOKUP(C31,'Liste chauffeur'!$B$5:$L$20,3,TRUE) -> SANDI Maanrouf | E31: 12 | F31: =B34-B31 -> 0.020833333
A32: PASSAMAINTY | B32: 0.52083333 | C32: C11 | D32: =VLOOKUP(C32,'Liste chauffeur'!$B$5:$L$20,2,TRUE)&" "&VLOOKUP(C32,'Liste chauffeur'!$B$5:$L$20,3,TRUE) -> MADI BOINA Mkidachi | E32: 13 | F32: =B33-B32 -> 0.020833333
A33: VAHIBE | B33: 0.54166667 | C33: C11 | D33: =VLOOKUP(C33,'Liste chauffeur'!$B$5:$L$20,2,TRUE)&" "&VLOOKUP(C33,'Liste chauffeur'!$B$5:$L$20,3,TRUE) -> MADI BOINA Mkidachi | E33: 14
A34: PASSAMAINTY | B34: 0.54166667 | C34: C9 | D34: =VLOOKUP(C34,'Liste chauffeur'!$B$5:$L$20,2,TRUE)&" "&VLOOKUP(C34,'Liste chauffeur'!$B$5:$L$20,3,TRUE) -> SANDI Maanrouf | E34: 13 | F34: =B35-B34 -> 0.020833333
A35: VAHIBE | B35: 0.5625 | C35: C9 | D35: =VLOOKUP(C35,'Liste chauffeur'!$B$5:$L$20,2,TRUE)&" "&VLOOKUP(C35,'Liste chauffeur'!$B$5:$L$20,3,TRUE) -> SANDI Maanrouf | E35: 14
A36: PASSAMAINTY | B36: 0.5625 | C36: C10 | D36: =VLOOKUP(C36,'Liste chauffeur'!$B$5:$L$20,2,TRUE)&" "&VLOOKUP(C36,'Liste chauffeur'!$B$5:$L$20,3,TRUE) -> ISSIHAKA M'Changama | E36: 1 | F36: =B37-B36 -> 0.020833333
A37: VAHIBE | B37: 0.58333333 | C37: C10 | D37: =VLOOKUP(C37,'Liste chauffeur'!$B$5:$L$20,2,TRUE)&" "&VLOOKUP(C37,'Liste chauffeur'!$B$5:$L$20,3,TRUE) -> ISSIHAKA M'Changama | E37: 2 | F37: =B40-B37 -> 0.020833333
A38: PASSAMAINTY | B38: 0.58333333 | C38: C8 | D38: =VLOOKUP(C38,'Liste chauffeur'!$B$5:$L$20,2,TRUE)&" "&VLOOKUP(C38,'Liste chauffeur'!$B$5:$L$20,3,TRUE) -> HADHURAMI Makinedine | E38: 1 | F38: =B39-B38 -> 0.020833333
A39: VAHIBE | B39: 0.60416667 | C39: C8 | D39: =VLOOKUP(C39,'Liste chauffeur'!$B$5:$L$20,2,TRUE)&" "&VLOOKUP(C39,'Liste chauffeur'!$B$5:$L$20,3,TRUE) -> HADHURAMI Makinedine | E39: 2 | F39: =B42-B39 -> 0.020833333
A40: PASSAMAINTY | B40: 0.60416667 | C40: C10 | D40: =VLOOKUP(C40,'Liste chauffeur'!$B$5:$L$20,2,TRUE)&" "&VLOOKUP(C40,'Liste chauffeur'!$B$5:$L$20,3,TRUE) -> ISSIHAKA M'Changama | E40: 3 | F40: =B41-B40 -> 0.020833333
A41: VAHIBE | B41: 0.625 | C41: C10 | D41: =VLOOKUP(C41,'Liste chauffeur'!$B$5:$L$20,2,TRUE)&" "&VLOOKUP(C41,'Liste chauffeur'!$B$5:$L$20,3,TRUE) -> ISSIHAKA M'Changama | E41: 4 | F41: =B44-B41 -> 0.020833333
A42: PASSAMAINTY | B42: 0.625 | C42: C8 | D42: =VLOOKUP(C42,'Liste chauffeur'!$B$5:$L$20,2,TRUE)&" "&VLOOKUP(C42,'Liste chauffeur'!$B$5:$L$20,3,TRUE) -> HADHURAMI Makinedine | E42: 3 | F42: =B43-B42 -> 0.020833333
A43: VAHIBE | B43: 0.64583333 | C43: C8 | D43: =VLOOKUP(C43,'Liste chauffeur'!$B$5:$L$20,2,TRUE)&" "&VLOOKUP(C43,'Liste chauffeur'!$B$5:$L$20,3,TRUE) -> HADHURAMI Makinedine | E43: 4 | F43: =B46-B43 -> 0.020833333
A44: PASSAMAINTY | B44: 0.64583333 | C44: C10 | D44: =VLOOKUP(C44,'Liste chauffeur'!$B$5:$L$20,2,TRUE)&" "&VLOOKUP(C44,'Liste chauffeur'!$B$5:$L$20,3,TRUE) -> ISSIHAKA M'Changama | E44: 5 | F44: =B45-B44 -> 0.020833333
A45: VAHIBE | B45: 0.66666667 | C45: C10 | D45: =VLOOKUP(C45,'Liste chauffeur'!$B$5:$L$20,2,TRUE)&" "&VLOOKUP(C45,'Liste chauffeur'!$B$5:$L$20,3,TRUE) -> ISSIHAKA M'Changama | E45: 6 | F45: =B48-B45 -> 0.020833333
A46: PASSAMAINTY | B46: 0.66666667 | C46: C8 | D46: =VLOOKUP(C46,'Liste chauffeur'!$B$5:$L$20,2,TRUE)&" "&VLOOKUP(C46,'Liste chauffeur'!$B$5:$L$20,3,TRUE) -> HADHURAMI Makinedine | E46: 5 | F46: =B47-B46 -> 0.020833333
A47: VAHIBE | B47: 0.6875 | C47: C8 | D47: =VLOOKUP(C47,'Liste chauffeur'!$B$5:$L$20,2,TRUE)&" "&VLOOKUP(C47,'Liste chauffeur'!$B$5:$L$20,3,TRUE) -> HADHURAMI Makinedine | E47: 6 | F47: =B50-B47 -> 0.020833333
A48: PASSAMAINTY | B48: 0.6875 | C48: C10 | D48: =VLOOKUP(C48,'Liste chauffeur'!$B$5:$L$20,2,TRUE)&" "&VLOOKUP(C48,'Liste chauffeur'!$B$5:$L$20,3,TRUE) -> ISSIHAKA M'Changama | E48: 7 | F48: =B49-B48 -> 0.020833333
A49: VAHIBE | B49: 0.70833333 | C49: C10 | D49: =VLOOKUP(C49,'Liste chauffeur'!$B$5:$L$20,2,TRUE)&" "&VLOOKUP(C49,'Liste chauffeur'!$B$5:$L$20,3,TRUE) -> ISSIHAKA M'Changama | E49: 8 | F49: =B52-B49 -> 0.020833333
A50: PASSAMAINTY | B50: 0.70833333 | C50: C8 | D50: =VLOOKUP(C50,'Liste chauffeur'!$B$5:$L$20,2,TRUE)&" "&VLOOKUP(C50,'Liste chauffeur'!$B$5:$L$20,3,TRUE) -> HADHURAMI Makinedine | E50: 7 | F50: =B51-B50 -> 0.020833333
A51: VAHIBE | B51: 0.72916667 | C51: C8 | D51: =VLOOKUP(C51,'Liste chauffeur'!$B$5:$L$20,2,TRUE)&" "&VLOOKUP(C51,'Liste chauffeur'!$B$5:$L$20,3,TRUE) -> HADHURAMI Makinedine | E51: 8 | F51: =B54-B51 -> 0.020833333
A52: PASSAMAINTY | B52: 0.72916667 | C52: C10 | D52: =VLOOKUP(C52,'Liste chauffeur'!$B$5:$L$20,2,TRUE)&" "&VLOOKUP(C52,'Liste chauffeur'!$B$5:$L$20,3,TRUE) -> ISSIHAKA M'Changama | E52: 9 | F52: =B53-B52 -> 0.020833333
A53: VAHIBE | B53: 0.75 | C53: C10 | D53: =VLOOKUP(C53,'Liste chauffeur'!$B$5:$L$20,2,TRUE)&" "&VLOOKUP(C53,'Liste chauffeur'!$B$5:$L$20,3,TRUE) -> ISSIHAKA M'Changama | E53: 10
A54: PASSAMAINTY | B54: 0.75 | C54: C8 | D54: =VLOOKUP(C54,'Liste chauffeur'!$B$5:$L$20,2,TRUE)&" "&VLOOKUP(C54,'Liste chauffeur'!$B$5:$L$20,3,TRUE) -> HADHURAMI Makinedine | E54: 9

Sheet Horaire dimanche1
A3: DATE | D3: NOVEMBRE
A4: CHAUFFEUR
A7: DEPART | B7: Heure théorique départ | C7: Type chauffeur prévu | D7: Nom chauffeur prévu | E7: Nbre trajets | F7: Delai entre 2 départs | G7: Délai avant | H7: Astreinte 1 | I7: Nom Chauffeur astreinte 1 | J7: Astreinte 2 | K7: Nom Chauffeur astreinte 2 | L7: Heure réelle départ | M7: Nbre personnes + | N7: Commentaires
A8: VAHIBE | B8: 0.33333333 | C8: C5 | D8: =VLOOKUP(C8,'Liste chauffeur'!$B$5:$L$20,2,TRUE)&" "&VLOOKUP(C8,'Liste chauffeur'!$B$5:$L$20,3,TRUE) -> AHAMADI Bacar Raenmouddine | E8: 1 | F8: =B9-B8 -> 0.020833333
A9: PASSAMAINTY | B9: 0.35416667 | C9: C5 | D9: =VLOOKUP(C9,'Liste chauffeur'!$B$5:$L$20,2,TRUE)&" "&VLOOKUP(C9,'Liste chauffeur'!$B$5:$L$20,3,TRUE) -> AHAMADI Bacar Raenmouddine | E9: 2 | F9: =B10-B9 -> 0.020833333
A10: VAHIBE | B10: 0.375 | C10: C5 | D10: =VLOOKUP(C10,'Liste chauffeur'!$B$5:$L$20,2,TRUE)&" "&VLOOKUP(C10,'Liste chauffeur'!$B$5:$L$20,3,TRUE) -> AHAMADI Bacar Raenmouddine | E10: 3 | F10: =B11-B10 -> 0.020833333
A11: PASSAMAINTY | B11: 0.39583333 | C11: C5 | D11: =VLOOKUP(C11,'Liste chauffeur'!$B$5:$L$20,2,TRUE)&" "&VLOOKUP(C11,'Liste chauffeur'!$B$5:$L$20,3,TRUE) -> AHAMADI Bacar Raenmouddine | E11: 4 | F11: =B12-B11 -> 0.020833333
A12: VAHIBE | B12: 0.41666667 | C12: C5 | D12: =VLOOKUP(C12,'Liste chauffeur'!$B$5:$L$20,2,TRUE)&" "&VLOOKUP(C12,'Liste chauffeur'!$B$5:$L$20,3,TRUE) -> AHAMADI Bacar Raenmouddine | E12: 5 | F12: =B13-B12 -> 0.020833333
A13: PASSAMAINTY | B13: 0.4375 | C13: C5 | D13: =VLOOKUP(C13,'Liste chauffeur'!$B$5:$L$20,2,TRUE)&" "&VLOOKUP(C13,'Liste chauffeur'!$B$5:$L$20,3,TRUE) -> AHAMADI Bacar Raenmouddine | E13: 6 | F13: =B14-B13 -> 0.020833333
A14: VAHIBE | B14: 0.45833333 | C14: C5 | D14: =VLOOKUP(C14,'Liste chauffeur'!$B$5:$L$20,2,TRUE)&" "&VLOOKUP(C14,'Liste chauffeur'!$B$5:$L$20,3,TRUE) -> AHAMADI Bacar Raenmouddine | E14: 7 | F14: =B15-B14 -> 0.020833333
A15: PASSAMAINTY | B15: 0.47916667 | C15: C5 | D15: =VLOOKUP(C15,'Liste chauffeur'!$B$5:$L$20,2,TRUE)&" "&VLOOKUP(C15,'Liste chauffeur'!$B$5:$L$20,3,TRUE) -> AHAMADI Bacar Raenmouddine | E15: 8 | F15: =B16-B15 -> 0.020833333
A16: VAHIBE | B16: 0.5 | C16: C5 | D16: =VLOOKUP(C16,'Liste chauffeur'!$B$5:$L$20,2,TRUE)&" "&VLOOKUP(C16,'Liste chauffeur'!$B$5:$L$20,3,TRUE) -> AHAMADI Bacar Raenmouddine | E16: 9 | F16: =B17-B16 -> 0.020833333
A17: PASSAMAINTY | B17: 0.52083333 | C17: C5 | D17: =VLOOKUP(C17,'Liste chauffeur'!$B$5:$L$20,2,TRUE)&" "&VLOOKUP(C17,'Liste chauffeur'!$B$5:$L$20,3,TRUE) -> AHAMADI Bacar Raenmouddine | E17: 10 | F17: =B18-B17 -> 0.020833333
A18: VAHIBE | B18: 0.54166667 | C18: C5 | D18: =VLOOKUP(C18,'Liste chauffeur'!$B$5:$L$20,2,TRUE)&" "&VLOOKUP(C18,'Liste chauffeur'!$B$5:$L$20,3,TRUE) -> AHAMADI Bacar Raenmouddine | E18: 11 | F18: =B19-B18 -> 0.020833333
